Workbook

Sheet About
A1: GaHEbIC Government and Household Expenditures by ISIC Code
A3: Source: | B3: 2020年全国投入产出表
B4: 国家统计局
B5: 2020
B6: https://data.stats.gov.cn/files/html/quickSearch/trcc/trcc01.html
A8: Notes
A9: “2020年全国投入产出表”是根据我国2020年全年投入产出表中竞争型和非竞争型两张表结合美国EPS模型总结出来42个部门的投入产出表。政府消费支出是根据“2020年全国投入产出表”中各行业政府消费支出数额乘以当年2020年人民币相对2012美元的汇率得出。
A21: We convert 2020 RMB to 2012 USD with the following conversion factor:
A22: 0.13765068 | B22: 2020年人民币相对2012美元

Sheet 2020年全国投入产出表
A1: 2020年全国投入产出表
A2: (按当年生产者价格计算） （Data are calculated at producers' prices in 2020)
A3: 单位：万元
A4: 投入 产出 | C4: 部门名称 | AU4: 最终使用 | BE4: 进口 | BF4: 总产出
D5: 农林牧渔产品和服务 | E5: 煤炭开采和洗选产品 | F5: 石油和天然气开采产品 | G5: 金属矿采选产品&非金属矿 | H5: 开采辅助活动和其他采矿产品 | I5: 食品和烟草 | J5: 纺织品、纺织服装鞋帽皮革羽绒及其制品 | K5: 木材加工品和家具 | L5: 造纸印刷和文教体育用品 | M5: 石油、炼焦产品和核燃料加工品 | N5: 化学原料和化学制品制造业&化学纤维制造业 | O5: 医药制造业 | P5: 橡胶和塑料制品业 | Q5: 非金属矿物制品 | R5: 黑色金属冶炼和压延加工品 | S5: 有色金属冶炼和压延加工品 | T5: 金属制品 | U5: 通用设备 | V5: 专用设备 | W5: 汽车制造业 | X5: 铁路、船舶、航空航天和其他运输设备 | Y5: 电气机械和器材 | Z5: 通信设备、计算机和其他电子设备&仪器仪表 | AA5: 其他制造产品和废品废料、金属制品、机械和设备修理服务 | AB5: 电力、热力生产和供应 | AC5: 燃气生产和供应 | AD5: 水的生产和供应 | AE5: 建筑 | AF5: 批发和零售 | AG5: 交通运输、仓储和邮政 | AH5: 住宿和餐饮 | AI5: 信息传输、软件和信息技术服务 | AJ5: 金融 | AK5: 房地产 | AL5: 租赁和商务服务 | AM5: 研究和试验发展 | AN5: 综合技术服务 | AO5: 居民服务、修理和其他服务 | AP5: 教育 | AQ5: 卫生和社会工作 | AR5: 文化、体育和娱乐 | AS5: 水利、环境和公共设施管理、公共管理、社会保障和社会组织 | AT5: 中间使用合计 | AU5: 农村居民消费支出 | AV5: 城镇居民消费支出 | AW5: 居民消费支出 | AX5: 政府消费支出 | AY5: 消费支出合计 | AZ5: 固定资本形成总额 | BA5: 存货变动 | BB5: 资本形成总额 | BC5: 出口 | BD5: 最终使用合计
B6: 部门名称 | C6: 代码 | D6: ISIC 01T03 | E6: ISIC 05 | F6: ISIC 06 | G6: ISIC 07T08 | H6: ISIC 09 | I6: ISIC 10T12 | J6: ISIC 13T15 | K6: ISIC 16 | L6: ISIC 17T18 | M6: ISIC 19 | N6: ISIC 20 | O6: ISIC 21 | P6: ISIC 22 | Q6: ISIC 231 | R6: ISIC 241 | S6: ISIC 242 | T6: ISIC 25 | U6: ISIC 28 | V6: ISIC 239 | W6: ISIC 29 | X6: ISIC 30 | Y6: ISIC 27 | Z6: ISIC 26 | AA6: ISIC 31T33 | AB6: ISIC 351 | AC6: ISIC 352T353 | AD6: ISIC 36T39 | AE6: ISIC 41T43 | AF6: ISIC 45T47 | AG6: ISIC 49T53 | AH6: ISIC 55T56 | AI6: ISIC 58T60 | AJ6: ISIC 64T66 | AK6: ISIC 68 | AL6: ISIC 61 | AM6: ISIC 64T66 | AN6: ISIC 69T82 | AO6: ISIC 97T98 | AP6: ISIC 85 | AQ6: ISIC 86T88 | AR6: ISIC 90T96 | AS6: ISIC 84 | AT6: TIU | AU6: FU101 | AV6: FU102 | AW6: THC | AX6: FU103 | AY6: TC | AZ6: FU201 | BA6: FU202 | BB6: GCF | BC6: EX | BD6: TFU | BE6: IM | BF6: GO
B7: 农林牧渔产品和服务 | C7: ISIC 01T03 | D7: 1.8313377e+08 | E7: 203490.68 | F7: 2231.1266 | G7: 30366.118 | H7: 118.5489 | I7: 4.6758672e+08 | J7: 82006169 | K7: 31973463 | L7: 53736067 | M7: 15804.36 | N7: 11513733 | O7: 44821825 | P7: 7680873.6 | Q7: 218881.19 | R7: 20627.162 | S7: 15998.126 | T7: 97311.762 | U7: 27411.881 | V7: 79539.685 | W7: 26629.608 | X7: 12565.824 | Y7: 68073.761 | Z7: 2175.5736 | AA7: 3451035.2 | AB7: 101721.23 | AC7: 1310.7869 | AD7: 0 | AE7: 18834172 | AF7: 13768.593 | AG7: 154389.97 | AH7: 53857079 | AI7: 509534.92 | AJ7: 67279.739 | AK7: 336941.13 | AL7: 7363183.4 | AM7: 4230391.8 | AN7: 1149759.6 | AO7: 2268491.1 | AP7: 612269.39 | AQ7: 605609.6 | AR7: 477755.87 | AS7: 9519615.7 | AT7: 9.5485469e+08 | AU7: 1.0974545e+08 | AV7: 2.21055e+08 | AW7: 3.3080046e+08 | AX7: 19639628 | AY7: 3.5044008e+08 | AZ7: 17577340 | BA7: 54901502 | BB7: 72478841 | BC7: 18171672 | BD7: 4.410906e+08 | BE7: 64262038 | BF7: 1.3316833e+09
B8: 煤炭开采和洗选产品 | C8: ISIC 05 | D8: 601665.54 | E8: 36204794 | F8: 63785.09 | G8: 1725453.9 | H8: 60512.779 | I8: 2167450.2 | J8: 1809485.7 | K8: 280086.13 | L8: 3698845.9 | M8: 22001120 | N8: 21794626 | O8: 436019.62 | P8: 562146.69 | Q8: 34167884 | R8: 21281683 | S8: 3302161.3 | T8: 494727.51 | U8: 360707.78 | V8: 252507.67 | W8: 48318.135 | X8: 49904.046 | Y8: 214230.21 | Z8: 20070.619 | AA8: 178085.14 | AB8: 93800322 | AC8: 2360515.5 | AD8: 0 | AE8: 843243.22 | AF8: 45563.861 | AG8: 128090.52 | AH8: 50429.81 | AI8: 0 | AJ8: 17218.23 | AK8: 63307.69 | AL8: 64.301927 | AM8: 234549.27 | AN8: 170081.94 | AO8: 326757.73 | AP8: 607785.82 | AQ8: 360760.39 | AR8: 41612.685 | AS8: 603682.15 | AT8: 2.5115017e+08 | AU8: 753293.48 | AV8: 468986.1 | AW8: 1222279.6 | AX8: 0 | AY8: 1222279.6 | AZ8: 0 | BA8: -2627614.6 | BB8: -2627614.6 | BC8: 260795.54 | BD8: -1144539.5 | BE8: 14933018 | BF8: 2.3507261e+08
B9: 石油和天然气开采产品 | C9: ISIC 06 | D9: 0 | E9: 44377.409 | F9: 535454.39 | G9: 31524.519 | H9: 15664.728 | I9: 0 | J9: 0 | K9: 0 | L9: 59261.943 | M9: 1.8788629e+08 | N9: 16889360 | O9: 26683.811 | P9: 822898.06 | Q9: 1363725.2 | R9: 372310.78 | S9: 752409.26 | T9: 586961.7 | U9: 564473.99 | V9: 372468.27 | W9: 425241.53 | X9: 143883.1 | Y9: 68067.405 | Z9: 0 | AA9: 0 | AB9: 6735286.1 | AC9: 33825564 | AD9: 0 | AE9: 0 | AF9: 0 | AG9: 487.91953 | AH9: 0 | AI9: 0 | AJ9: 0 | AK9: 0 | AL9: 0 | AM9: 2507.1572 | AN9: 0 | AO9: 0 | AP9: 0 | AQ9: 34579.89 | AR9: 1756.0257 | AS9: 48307.892 | AT9: 2.5160955e+08 | AU9: 0 | AV9: 0 | AW9: 0 | AX9: 0 | AY9: 0 | AZ9: 0 | BA9: 288640.91 | BB9: 288640.91 | BC9: 1085317.4 | BD9: 1373958.3 | BE9: 1.4529394e+08 | BF9: 1.0768957e+08
B10: 金属矿采选产品&非金属矿 | C10: ISIC 07T08 | D10: 2307.8115 | E10: 45270.046 | F10: 20550.068 | G10: 12059565 | H10: 74468.261 | I10: 62486.304 | J10: 20915.922 | K10: 14130.601 | L10: 917816.89 | M10: 351666.07 | N10: 13663939 | O10: 218560.81 | P10: 57763.344 | Q10: 51091549 | R10: 1.3243884e+08 | S10: 78502943 | T10: 6503772.5 | U10: 64839.412 | V10: 122513 | W10: 165447.68 | X10: 51425.009 | Y10: 614877.85 | Z10: 90520.249 | AA10: 56747.979 | AB10: 106588.82 | AC10: 0 | AD10: 0 | AE10: 24113819 | AF10: 60555.457 | AG10: 179268.15 | AH10: 4016.8528 | AI10: 87.113672 | AJ10: 747.23883 | AK10: 376.87524 | AL10: 1678.8514 | AM10: 333550.56 | AN10: 3880.5923 | AO10: 3727.6437 | AP10: 2965.1177 | AQ10: 1023.0554 | AR10: 5435.0281 | AS10: 31541.554 | AT10: 3.2204805e+08 | AU10: 0 | AV10: 0 | AW10: 0 | AX10: 0 | AY10: 0 | AZ10: 0 | BA10: 2801192.3 | BB10: 2801192.3 | BC10: 3333103.9 | BD10: 6134296.2 | BE10: 1.3464774e+08 | BF10: 1.935346e+08
B11: 开采辅助活动和其他采矿产品 | C11: ISIC 09 | D11: 0 | E11: 1372272.6 | F11: 16942467 | G11: 1047957.7 | H11: 177012.62 | I11: 466046.59 | J11: 0 | K11: 0 | L11: 0 | M11: 0 | N11: 0 | O11: 0 | P11: 0 | Q11: 0 | R11: 0 | S11: 0 | T11: 0 | U11: 0 | V11: 0 | W11: 0 | X11: 0 | Y11: 0 | Z11: 12.672237 | AA11: 0 | AB11: 231004.91 | AC11: 0 | AD11: 0 | AE11: 0 | AF11: 0 | AG11: 0 | AH11: 0 | AI11: 0 | AJ11: 0 | AK11: 0 | AL11: 0 | AM11: 0 | AN11: 0 | AO11: 0 | AP11: 0 | AQ11: 0 | AR11: 0 | AS11: 0 | AT11: 20236774 | AU11: 0 | AV11: 0 | AW11: 0 | AX11: 0 | AY11: 0 | AZ11: 0 | BA11: 0 | BB11: 0 | BC11: 0 | BD11: 0 | BE11: 0 | BF11: 20236774
B12: 食品和烟草 | C12: ISIC 10T12 | D12: 1.0818487e+08 | E12: 413271.66 | F12: 79328.127 | G12: 942010.65 | H12: 15471.043 | I12: 2.4937249e+08 | J12: 14128692 | K12: 1247437.6 | L12: 3016090.2 | M12: 3256002.6 | N12: 25114335 | O12: 7560676.1 | P12: 750764.12 | Q12: 1766033.1 | R12: 3822314.4 | S12: 4171930.4 | T12: 2846827.7 | U12: 4402856.9 | V12: 2451141.6 | W12: 2157646.4 | X12: 1244965.2 | Y12: 4524092.6 | Z12: 7303684.3 | AA12: 618269.9 | AB12: 5006459.1 | AC12: 538269.51 | AD12: 432454.55 | AE12: 5743107.4 | AF12: 2301664 | AG12: 7651112.8 | AH12: 1.2774375e+08 | AI12: 5595412.7 | AJ12: 2856239.9 | AK12: 4673588.7 | AL12: 16568941 | AM12: 4782871.6 | AN12: 3289851.4 | AO12: 7513197.7 | AP12: 12503171 | AQ12: 7006157.7 | AR12: 9671567.6 | AS12: 7647553.5 | AT12: 6.7966914e+08 | AU12: 1.5618843e+08 | AV12: 4.5232673e+08 | AW12: 6.0851517e+08 | AX12: 0 | AY12: 6.0851517e+08 | AZ12: 0 | BA12: 8525640.2 | BB12: 8525640.2 | BC12: 35833494 | BD12: 6.528743e+08 | BE12: 81180640 | BF12: 1.2513628e+09
B13: 纺织品、纺织服装鞋帽皮革羽绒及其制品 | C13: ISIC 13T15 | D13: 255022.54 | E13: 1536716.5 | F13: 172891.15 | G13: 431377.15 | H13: 299060.73 | I13: 3696564.2 | J13: 3.1484617e+08 | K13: 8109575.9 | L13: 21141410 | M13: 892568.3 | N13: 3692227 | O13: 4066224.9 | P13: 3366898.1 | Q13: 4050298.9 | R13: 649060.66 | S13: 445858.55 | T13: 2025532.9 | U13: 1951908.6 | V13: 1960493.2 | W13: 5639280.4 | X13: 1374959.5 | Y13: 3039653 | Z13: 3035965.5 | AA13: 4187381.8 | AB13: 864761.17 | AC13: 343622.09 | AD13: 391871.28 | AE13: 4541077.5 | AF13: 3219495.3 | AG13: 5114728.6 | AH13: 3509705.2 | AI13: 999494.99 | AJ13: 4708210.4 | AK13: 2106065.8 | AL13: 16680635 | AM13: 2606793.1 | AN13: 1524598.3 | AO13: 2503390.6 | AP13: 1549810.4 | AQ13: 9533818.8 | AR13: 4734179.3 | AS13: 25315084 | AT13: 4.7300487e+08 | AU13: 23013748 | AV13: 1.0819378e+08 | AW13: 1.3120753e+08 | AX13: 0 | AY13: 1.3120753e+08 | AZ13: 0 | BA13: -3571111.2 | BB13: -3571111.2 | BC13: 1.8680114e+08 | BD13: 3.1443756e+08 | BE13: 30055498 | BF13: 7.5738693e+08
B14: 木材加工品和家具 | C14: ISIC 16 | D14: 336188.95 | E14: 3559037.5 | F14: 156891.3 | G14: 254624.37 | H14: 6327.7151 | I14: 845240.04 | J14: 918481.02 | K14: 81780667 | L14: 90084970 | M14: 186690.2 | N14: 1302287.3 | O14: 114696.06 | P14: 708459.64 | Q14: 1957227.2 | R14: 49068.256 | S14: 185262.26 | T14: 4792477.8 | U14: 931517.23 | V14: 637156.81 | W14: 5926683.2 | X14: 652732.73 | Y14: 1177748.8 | Z14: 1019650 | AA14: 1295524.2 | AB14: 201717.8 | AC14: 4011.8598 | AD14: 3316.5085 | AE14: 57246609 | AF14: 423651.48 | AG14: 934919.87 | AH14: 196032.43 | AI14: 922455.74 | AJ14: 474744.04 | AK14: 546486.36 | AL14: 599781.95 | AM14: 50562.204 | AN14: 401102.15 | AO14: 635895.59 | AP14: 342879.72 | AQ14: 75136.026 | AR14: 319747.38 | AS14: 3983063.1 | AT14: 1.8446106e+08 | AU14: 5007508 | AV14: 17646337 | AW14: 22653845 | AX14: 0 | AY14: 22653845 | AZ14: 21595789 | BA14: 1674063.1 | BB14: 23269852 | BC14: 44765297 | BD14: 90688994 | BE14: 9736870.7 | BF14: 2.6541318e+08
B15: 造纸印刷和文教体育用品 | C15: ISIC 17T18 | D15: 1025682.3 | E15: 31068.882 | F15: 9688.6354 | G15: 315134.03 | H15: 18042.408 | I15: 13214440 | J15: 3599305.4 | K15: 2513515.7 | L15: 1.0517187e+08 | M15: 357515.63 | N15: 4061404.6 | O15: 4907967.4 | P15: 1782237.4 | Q15: 8915729.5 | R15: 89427.25 | S15: 336660.37 | T15: 1916810.8 | U15: 1926288.9 | V15: 1841924.1 | W15: 1597372.5 | X15: 344645.46 | Y15: 5512884.5 | Z15: 5349964.6 | AA15: 807927.26 | AB15: 458088.57 | AC15: 13078.613 | AD15: 21179.986 | AE15: 5313847 | AF15: 8789370.8 | AG15: 4327923.9 | AH15: 1732626.8 | AI15: 27520721 | AJ15: 20038604 | AK15: 5345538.8 | AL15: 69510376 | AM15: 2605460.1 | AN15: 5513422.2 | AO15: 1759661.7 | AP15: 12646201 | AQ15: 288424.63 | AR15: 7453946.6 | AS15: 20046565 | AT15: 3.5651903e+08 | AU15: 6120942 | AV15: 29346782 | AW15: 35467724 | AX15: 0 | AY15: 35467724 | AZ15: 4281134.6 | BA15: -8038986.6 | BB15: -3757852 | BC15: 66074535 | BD15: 97784407 | BE15: 25910671 | BF15: 4.2839277e+08
B16: 石油、炼焦产品和核燃料加工品 | C16: ISIC 19 | D16: 4991926.8 | E16: 700362.55 | F16: 395976.19 | G16: 7776692.3 | H16: 799185.8 | I16: 1015050.6 | J16: 1120310.3 | K16: 1004346.3 | L16: 1858172.8 | M16: 22688076 | N16: 63847205 | O16: 474305.06 | P16: 2190479.3 | Q16: 19987604 | R16: 42144147 | S16: 7221065.2 | T16: 3078282.8 | U16: 2035296.8 | V16: 1035075.2 | W16: 1106854 | X16: 444478.82 | Y16: 1121539.9 | Z16: 1058861.3 | AA16: 836932.65 | AB16: 10310485 | AC16: 1882494.5 | AD16: 38463.432 | AE16: 37120733 | AF16: 3295901.8 | AG16: 96331786 | AH16: 1029117.6 | AI16: 1116149.6 | AJ16: 3729490.6 | AK16: 1528256.1 | AL16: 19256951 | AM16: 1475382.6 | AN16: 12374899 | AO16: 1218116.8 | AP16: 2786127.9 | AQ16: 239725.61 | AR16: 469119.18 | AS16: 5767314 | AT16: 3.8789839e+08 | AU16: 5745628.2 | AV16: 28313585 | AW16: 34059213 | AX16: 0 | AY16: 34059213 | AZ16: 0 | BA16: -5955399.2 | BB16: -5955399.2 | BC16: 15981224 | BD16: 44085038 | BE16: 22650148 | BF16: 4.0933328e+08
B17: 化学原料和化学制品制造业&化学纤维制造业 | C17: ISIC 20 | D17: 75932742 | E17: 2724058.2 | F17: 3946860.5 | G17: 9732267.1 | H17: 1246400.1 | I17: 5072727.7 | J17: 54593583 | K17: 16223100 | L17: 51348513 | M17: 14670765 | N17: 2.9296505e+08 | O17: 11936419 | P17: 1.1027181e+08 | Q17: 31280002 | R17: 3761259 | S17: 9341339.8 | T17: 10641344 | U17: 4653059.2 | V17: 2243331.6 | W17: 6970340.2 | X17: 2118210.8 | Y17: 26478745 | Z17: 15451768 | AA17: 5086887.6 | AB17: 221438.67 | AC17: 31293.166 | AD17: 2463333.3 | AE17: 75178170 | AF17: 101065.7 | AG17: 988410.01 | AH17: 2502380.8 | AI17: 1218070.3 | AJ17: 301378.84 | AK17: 339047.64 | AL17: 4302489.1 | AM17: 14442889 | AN17: 20348720 | AO17: 13522936 | AP17: 7517280.1 | AQ17: 538883.13 | AR17: 1609725.6 | AS17: 8727065.8 | AT17: 9.0682206e+08 | AU17: 2773014.2 | AV17: 19771297 | AW17: 22544311 | AX17: 0 | AY17: 22544311 | AZ17: 0 | BA17: -17407692 | BB17: -17407692 | BC17: 66207878 | BD17: 71344496 | BE17: 1.2306996e+08 | BF17: 8.5509659e+08
B18: 医药制造业 | C18: ISIC 21 | D18: 6070961.4 | E18: 41905.124 | F18: 18810.369 | G18: 6112.285 | H18: 670.13328 | I18: 812022.34 | J18: 88147.315 | K18: 2763.5262 | L18: 656674.07 | M18: 14976.676 | N18: 1196871 | O18: 61912202 | P18: 81220.679 | Q18: 569294.79 | R18: 104789.23 | S18: 14108.632 | T18: 174018.27 | U18: 7811.941 | V18: 424487.47 | W18: 10204.664 | X18: 10869.323 | Y18: 124300.88 | Z18: 501241.91 | AA18: 124963.88 | AB18: 16580.568 | AC18: 375.41193 | AD18: 16573.363 | AE18: 2238386.7 | AF18: 10825.857 | AG18: 152802.04 | AH18: 814.26546 | AI18: 302859.27 | AJ18: 71563.525 | AK18: 15249.379 | AL18: 178518.28 | AM18: 1060731.9 | AN18: 2592341.8 | AO18: 184325.83 | AP18: 710406.22 | AQ18: 1.6382985e+08 | AR18: 24625.037 | AS18: 264315.07 | AT18: 2.4463781e+08 | AU18: 16266751 | AV18: 47595954 | AW18: 63862704 | AX18: 0 | AY18: 63862704 | AZ18: 0 | BA18: -336221.76 | BB18: -336221.76 | BC18: 22931108 | BD18: 86457591 | BE18: 31039262 | BF18: 3.0005614e+08
... B49: 中间投入合计 | C49: TII | D49: 5.0993601e+08 | E49: 1.1507411e+08 | F49: 39965777 | G49: 89225006 | H49: 11697851 | I49: 9.4434911e+08 | J49: 6.1291057e+08 | K49: 2.0981156e+08 | L49: 5.3265536e+08 | M49: 3.0874252e+08 | N49: 6.5708287e+08 | O49: 2.1422011e+08 | P49: 2.7175232e+08 | Q49: 5.0245189e+08 | R49: 5.2721563e+08 | S49: 4.0509258e+08 | T49: 3.9228391e+08 | U49: 4.0882303e+08 | V49: 2.8939979e+08 | W49: 5.6098102e+08 | X49: 1.2377234e+08 | Y49: 5.7633942e+08 | Z49: 9.9720917e+08 | AA49: 67374684 | AB49: 4.8115356e+08 | AC49: 61699159 | AD49: 20179486 | AE49: 2.140212e+09 | AF49: 5.4491128e+08 | AG49: 7.4239633e+08 | AH49: 2.8646918e+08 | AI49: 5.1722835e+08 | AJ49: 3.9319876e+08 | AK49: 2.9696594e+08 | AL49: 6.440355e+08 | AM49: 1.356294e+08 | AN49: 3.3464331e+08 | AO49: 1.4306091e+08 | AP49: 1.591954e+08 | AQ49: 2.9186652e+08 | AR49: 77833015 | AS49: 3.9682481e+08 | AT49: 1.6826058e+10 | AU49: 8.1664287e+08 | AV49: 3.0234403e+09 | AW49: 3.8400831e+09 | AX49: 1.7362538e+09 | AY49: 5.5763369e+09 | AZ49: 4.243704e+09 | BA49: 91509938 | BB49: 4.3352139e+09 | BC49: 1.8792607e+09 | BD49: 1.1790812e+10 | BE49: 1.6265915e+09 | BF49: 2.6990278e+10
A50: 增加值 | B50: 劳动者报酬 | C50: VA001 | D50: 8.2110938e+08 | E50: 49156976 | F50: 10684587 | G50: 34146732 | H50: 9070894.8 | I50: 92288060 | J50: 78070179 | K50: 25339701 | L50: 70607745 | M50: 12815275 | N50: 47509590 | O50: 30588661 | P50: 35944267 | Q50: 74959952 | R50: 39116759 | S50: 35418934 | T50: 57488356 | U50: 46988960 | V50: 51031136 | W50: 36758514 | X50: 17700419 | Y50: 47111754 | Z50: 1.0033013e+08 | AA50: 25541968 | AB50: 61395231 | AC50: 7256304.2 | AD50: 8632889.8 | AE50: 4.6964543e+08 | AF50: 5.197925e+08 | AG50: 2.3052393e+08 | AH50: 85067117 | AI50: 2.0697374e+08 | AJ50: 2.1528198e+08 | AK50: 1.9273312e+08 | AL50: 2.5275721e+08 | AM50: 65841577 | AN50: 1.1541846e+08 | AO50: 1.2768977e+08 | AP50: 2.8165049e+08 | AQ50: 1.7178319e+08 | AR50: 51172540 | AS50: 4.0760071e+08 | AT50: 5.2956554e+09
B51: 生产税净额 | C51: VA002 | D51: -45528241 | E51: 23728884 | F51: 26393586 | G51: 29203561 | H51: 1127941.3 | I51: 82927930 | J51: 1055456.5 | K51: 5439494.6 | L51: 11735860 | M51: 49155196 | N51: 37768625 | O51: 11543782 | P51: 9432919.7 | Q51: 23472867 | R51: 16809804 | S51: 20103753 | T51: 11219547 | U51: 16723538 | V51: 14548977 | W51: 41488606 | X51: 2028722 | Y51: 4541468.5 | Z51: -3678836.3 | AA51: 13432368 | AB51: 20698378 | AC51: 1010550.5 | AD51: 1860447.2 | AE51: 98116386 | AF51: 95383190 | AG51: 8513567.4 | AH51: 1360038.7 | AI51: 13092894 | AJ51: 82718116 | AK51: 1.2344272e+08 | AL51: 27690531 | AM51: 1588413.6 | AN51: 11715875 | AO51: 5023484.2 | AP51: 625840.59 | AQ51: 119102.01 | AR51: 1590021 | AS51: 2016363.5 | AT51: 8.9580223e+08
B52: 固定资产折旧 | C52: VA003 | D52: 23048580 | E52: 11857467 | F52: 23934532 | G52: 14045535 | H52: 881427.49 | I52: 30616039 | J52: 17159912 | K52: 7115541.2 | L52: 23476685 | M52: 11540323 | N52: 37261753 | O52: 7442373.5 | P52: 13681348 | Q52: 36252425 | R52: 31732256 | S52: 20256127 | T52: 17451920 | U52: 16689439 | V52: 12133973 | W52: 15404030 | X52: 3816835 | Y52: 15983410 | Z52: 35286960 | AA52: 6722131.4 | AB52: 97784316 | AC52: 5463404 | AD52: 6900167.1 | AE52: 27714364 | AF52: 1.1846713e+08 | AG52: 2.0022194e+08 | AH52: 46183808 | AI52: 1.2669418e+08 | AJ52: 36197644 | AK52: 70284261 | AL52: 35220354 | AM52: 20894697 | AN52: 47257246 | AO52: 18811001 | AP52: 77784703 | AQ52: 31476065 | AR52: 19443052 | AS52: 92345943 | AT52: 1.5058198e+09
B53: 营业盈余 | C53: VA004 | D53: 23117527 | E53: 35255171 | F53: 6711085 | G53: 26913765 | H53: -2541340.5 | I53: 1.0118166e+08 | J53: 48190809 | K53: 17706882 | L53: 55330297 | M53: 27079971 | N53: 75473751 | O53: 36261214 | P53: 27380722 | Q53: 95894758 | R53: 68635495 | S53: 43798631 | T53: 41037940 | U53: 43686016 | V53: 20237211 | W53: 51825291 | X53: 8695606.9 | Y53: 53690206 | Z53: 59374527 | AA53: 51110402 | AB53: 38471081 | AC53: 5841588 | AD53: 3105561.8 | AE53: 1.2461676e+08 | AF53: 2.1996059e+08 | AG53: 17515502 | AH53: 12909620 | AI53: 1.0125364e+08 | AJ53: 5.0197366e+08 | AK53: 3.8320744e+08 | AL53: 2859006.3 | AM53: 7602478.7 | AN53: 10750979 | AO53: 5752421.8 | AP53: 13231126 | AQ53: 4827324.6 | AR53: 5804782 | AS53: 8918362 | AT53: 2.4669426e+09
B54: 增加值合计 | C54: TVA | D54: 8.2174724e+08 | E54: 1.199985e+08 | F54: 67723790 | G54: 1.0430959e+08 | H54: 8538923.1 | I54: 3.0701369e+08 | J54: 1.4447636e+08 | K54: 55601618 | L54: 1.6115059e+08 | M54: 1.0059076e+08 | N54: 1.9801372e+08 | O54: 85836030 | P54: 86439257 | Q54: 2.3058e+08 | R54: 1.5629431e+08 | S54: 1.1957745e+08 | T54: 1.2719776e+08 | U54: 1.2408795e+08 | V54: 97951296 | W54: 1.4547644e+08 | X54: 32241583 | Y54: 1.2132684e+08 | Z54: 1.9131278e+08 | AA54: 96806870 | AB54: 2.1834901e+08 | AC54: 19571847 | AD54: 20499066 | AE54: 7.2009294e+08 | AF54: 9.5360341e+08 | AG54: 4.5677494e+08 | AH54: 1.4552058e+08 | AI54: 4.4801444e+08 | AJ54: 8.3617139e+08 | AK54: 7.6966754e+08 | AL54: 3.185271e+08 | AM54: 95927166 | AN54: 1.8514256e+08 | AO54: 1.5727667e+08 | AP54: 3.7329216e+08 | AQ54: 2.0820568e+08 | AR54: 78010395 | AS54: 5.1088137e+08 | AT54: 1.016422e+10
A55: 总投入 | C55: TI | D55: 1.3316833e+09 | E55: 2.3507261e+08 | F55: 1.0768957e+08 | G55: 1.935346e+08 | H55: 20236774 | I55: 1.2513628e+09 | J55: 7.5738693e+08 | K55: 2.6541318e+08 | L55: 6.9380595e+08 | M55: 4.0933328e+08 | N55: 8.5509659e+08 | O55: 3.0005614e+08 | P55: 3.5819158e+08 | Q55: 7.3303189e+08 | R55: 6.8350994e+08 | S55: 5.2467002e+08 | T55: 5.1948167e+08 | U55: 5.3291099e+08 | V55: 3.8735108e+08 | W55: 7.0645746e+08 | X55: 1.5601392e+08 | Y55: 6.9766625e+08 | Z55: 1.188522e+09 | AA55: 1.6418155e+08 | AB55: 6.9950257e+08 | AC55: 81271005 | AD55: 40678552 | AE55: 2.860305e+09 | AF55: 1.4985147e+09 | AG55: 1.1991713e+09 | AH55: 4.3198976e+08 | AI55: 9.6524279e+08 | AJ55: 1.2293702e+09 | AK55: 1.0666335e+09 | AL55: 9.625626e+08 | AM55: 2.3155657e+08 | AN55: 5.1978587e+08 | AO55: 3.0033759e+08 | AP55: 5.3248756e+08 | AQ55: 5.000722e+08 | AR55: 1.5584341e+08 | AS55: 9.0770619e+08 | AT55: 2.6990278e+10

Sheet GaHEbIC-government
A1: Unit: USD | B1: ISIC 01T03 | C1: ISIC 05 | D1: ISIC 06 | E1: ISIC 07T08 | F1: ISIC 09 | G1: ISIC 10T12 | H1: ISIC 13T15 | I1: ISIC 16 | J1: ISIC 17T18 | K1: ISIC 19 | L1: ISIC 20 | M1: ISIC 21 | N1: ISIC 22 | O1: ISIC 231 | P1: ISIC 239 | Q1: ISIC 241 | R1: ISIC 242 | S1: ISIC 25 | T1: ISIC 26 | U1: ISIC 27 | V1: ISIC 28 | W1: ISIC 29 | X1: ISIC 30 | Y1: ISIC 31T33 | Z1: ISIC 351 | AA1: ISIC 352T353 | AB1: ISIC 36T39 | AC1: ISIC 41T43 | AD1: ISIC 45T47 | AE1: ISIC 49T53 | AF1: ISIC 55T56 | AG1: ISIC 58T60 | AH1: ISIC 61 | AI1: ISIC 62T63 | AJ1: ISIC 64T66 | AK1: ISIC 68 | AL1: ISIC 69T82 | AM1: ISIC 84 | AN1: ISIC 85 | AO1: ISIC 86T88 | AP1: ISIC 90T96 | AQ1: ISIC 97T98
A2: Government Expenditures | B2: ='2020年全国投入产出表'!$AX$7*10000*About!$A$22 -> 2.7034081e+10 | C2: ='2020年全国投入产出表'!AX$8*10000*About!$A$22 -> 0 | D2: ='2020年全国投入产出表'!AX$9*10000*About!$A$22 -> 0 | E2: ='2020年全国投入产出表'!$AX$10*10000*About!$A$22 -> 0 | F2: ='2020年全国投入产出表'!$AX$11*10000*About!$A$22 -> 0 | G2: ='2020年全国投入产出表'!$AX$12*10000*About!$A$22 -> 0 | H2: ='2020年全国投入产出表'!$AX$13*10000*About!$A$22 -> 0 | I2: ='2020年全国投入产出表'!$AX$14*10000*About!$A$22 -> 0 | J2: ='2020年全国投入产出表'!$AX$15*10000*About!$A$22 -> 0 | K2: ='2020年全国投入产出表'!$AX$16*10000*About!$A$22 -> 0 | L2: ='2020年全国投入产出表'!$AX$17*10000*About!$A$22 -> 0 | M2: ='2020年全国投入产出表'!$AX$18*10000*About!$A$22 -> 0 | N2: ='2020年全国投入产出表'!$AX$19*10000*About!$A$22 -> 0 | O2: ='2020年全国投入产出表'!$AX$20*10000*About!$A$22 -> 0 | P2: ='2020年全国投入产出表'!$AX$25*10000*About!$A$22 -> 0 | Q2: ='2020年全国投入产出表'!$AX$21*10000*About!$A$22 -> 0 | R2: ='2020年全国投入产出表'!$AX$22*10000*About!$A$22 -> 0 | S2: ='2020年全国投入产出表'!$AX$23*10000*About!$A$22 -> 0 | T2: ='2020年全国投入产出表'!$AX$29*10000*About!$A$22 -> 0 | U2: ='2020年全国投入产出表'!$AX$28*10000*About!$A$22 -> 0 | V2: ='2020年全国投入产出表'!$AX$24*10000*About!$A$22 -> 0 | W2: ='2020年全国投入产出表'!$AX$26*10000*About!$A$22 -> 0 | X2: ='2020年全国投入产出表'!$AX$27*10000*About!$A$22 -> 0 | Y2: ='2020年全国投入产出表'!$AX$30*10000*About!$A$22 -> 0 | Z2: ='2020年全国投入产出表'!$AX$31*10000*About!$A$22 -> 0 | AA2: ='2020年全国投入产出表'!$AX$32*10000*About!$A$22 -> 0 | AB2: ='2020年全国投入产出表'!$AX$33*10000*About!$A$22 -> 0 | AC2: ='2020年全国投入产出表'!$AX$34*10000*About!$A$22 -> 0 | AD2: ='2020年全国投入产出表'!$AX$35*10000*About!$A$22 -> 0 | AE2: ='2020年全国投入产出表'!$AX$36*10000*About!$A$22 -> 5.8897574e+10 | AF2: ='2020年全国投入产出表'!$AX$37*10000*About!$A$22 -> 0 | AG2: ='2020年全国投入产出表'!$AX$38*10000*About!$A$22 -> 0 | AH2: ='2020年全国投入产出表'!$AX$41*10000*About!$A$22 -> 3.0497381e+10 | AI2: ='2020年全国投入产出表'!$AX$42*10000*About!$A$22 -> 8.3866125e+10 | AJ2: ='2020年全国投入产出表'!$AX$39*10000*About!$A$22 -> 6.2083832e+10 | AK2: ='2020年全国投入产出表'!$AX$40*10000*About!$A$22 -> 0 | AL2: ='2020年全国投入产出表'!$AX$43*10000*About!$A$22 -> 1.1754407e+11 | AM2: ='2020年全国投入产出表'!$AX$48*10000*About!$A$22 -> 1.1449633e+12 | AN2: ='2020年全国投入产出表'!$AX$45*10000*About!$A$22 -> 3.7126808e+11 | AO2: ='2020年全国投入产出表'!$AX$46*10000*About!$A$22 -> 4.3594423e+11 | AP2: ='2020年全国投入产出表'!$AX$47*10000*About!$A$22 -> 5.7866401e+10 | AQ2: ='2020年全国投入产出表'!$AX$44*10000*About!$A$22 -> 0
B3: 农林牧渔产品和服务 | C3: 煤炭开采和洗选产品 | D3: 石油和天然气开采产品 | E3: 金属矿采选产品&非金属矿 | F3: 开采辅助活动和其他采矿产品 | G3: 食品和烟草 | H3: 纺织品、纺织服装鞋帽皮革羽绒及其制品 | I3: 木材加工品和家具 | J3: 造纸印刷和文教体育用品 | K3: 石油、炼焦产品和核燃料加工品 | L3: 化学原料和化学制品制造业&化学纤维制造业 | M3: 医药制造业 | N3: 橡胶和塑料制品业 | O3: 非金属矿物制品 | P3: 专用设备 | Q3: 黑色金属冶炼和压延加工品 | R3: 有色金属冶炼和压延加工品 | S3: 金属制品 | T3: 通信设备、计算机和其他电子设备&仪器仪表 | U3: 电气机械和器材 | V3: 通用设备 | W3: 汽车制造业 | X3: 铁路、船舶、航空航天和其他运输设备 | Y3: 其他制造产品和废品废料、金属制品、机械和设备修理服务 | Z3: 电力、热力生产和供应 | AA3: 燃气生产和供应 | AB3: 水的生产和供应 | AC3: 建筑 | AD3: 批发和零售 | AE3: 交通运输、仓储和邮政 | AF3: 住宿和餐饮 | AG3: 信息传输、软件和信息技术服务 | AH3: 租赁和商务服务 | AI3: 研究和试验发展 | AJ3: 金融 | AK3: 房地产 | AL3: 综合技术服务 | AM3: 水利、环境和公共设施管理、公共管理、社会保障和社会组织 | AN3: 教育 | AO3: 卫生和社会工作 | AP3: 文化、体育和娱乐 | AQ3: 居民服务、修理和其他服务

Sheet GaHEbIC-household
A1: Unit: USD | B1: ISIC 01T03 | C1: ISIC 05 | D1: ISIC 06 | E1: ISIC 07T08 | F1: ISIC 09 | G1: ISIC 10T12 | H1: ISIC 13T15 | I1: ISIC 16 | J1: ISIC 17T18 | K1: ISIC 19 | L1: ISIC 20 | M1: ISIC 21 | N1: ISIC 22 | O1: ISIC 231 | P1: ISIC 239 | Q1: ISIC 241 | R1: ISIC 242 | S1: ISIC 25 | T1: ISIC 26 | U1: ISIC 27 | V1: ISIC 28 | W1: ISIC 29 | X1: ISIC 30 | Y1: ISIC 31T33 | Z1: ISIC 351 | AA1: ISIC 352T353 | AB1: ISIC 36T39 | AC1: ISIC 41T43 | AD1: ISIC 45T47 | AE1: ISIC 49T53 | AF1: ISIC 55T56 | AG1: ISIC 58T60 | AH1: ISIC 61 | AI1: ISIC 62T63 | AJ1: ISIC 64T66 | AK1: ISIC 68 | AL1: ISIC 69T82 | AM1: ISIC 84 | AN1: ISIC 85 | AO1: ISIC 86T88 | AP1: ISIC 90T96 | AQ1: ISIC 97T98
A2: Household Expenditures | B2: ='2020年全国投入产出表'!$AW$7*10000*About!$A$22 -> 4.5534907e+11 | C2: ='2020年全国投入产出表'!$AW$8*10000*About!$A$22 -> 1.6824761e+09 | D2: ='2020年全国投入产出表'!$AW$9*10000*About!$A$22 -> 0 | E2: ='2020年全国投入产出表'!$AW$10*10000*About!$A$22 -> 0 | F2: ='2020年全国投入产出表'!$AW$11*10000*About!$A$22 -> 0 | G2: ='2020年全国投入产出表'!$AW$12*10000*About!$A$22 -> 8.3762525e+11 | H2: ='2020年全国投入产出表'!$AW$13*10000*About!$A$22 -> 1.8060805e+11 | I2: ='2020年全国投入产出表'!$AW$14*10000*About!$A$22 -> 3.1183171e+10 | J2: ='2020年全国投入产出表'!$AW$15*10000*About!$A$22 -> 4.8821562e+10 | K2: ='2020年全国投入产出表'!$AW$16*10000*About!$A$22 -> 4.6882737e+10 | L2: ='2020年全国投入产出表'!$AW$17*10000*About!$A$22 -> 3.1032397e+10 | M2: ='2020年全国投入产出表'!$AX$18*10000*About!$A$22 -> 0 | N2: ='2020年全国投入产出表'!$AW$19*10000*About!$A$22 -> 8.8382266e+09 | O2: ='2020年全国投入产出表'!$AW$20*10000*About!$A$22 -> 7.552418e+09 | P2: ='2020年全国投入产出表'!$AW$25*10000*About!$A$22 -> 5.9414287e+09 | Q2: ='2020年全国投入产出表'!$AW$21*10000*About!$A$22 -> 0 | R2: ='2020年全国投入产出表'!$AW$22*10000*About!$A$22 -> 0 | S2: ='2020年全国投入产出表'!$AW$23*10000*About!$A$22 -> 6.7180235e+09 | T2: ='2020年全国投入产出表'!$AW$29*10000*About!$A$22 -> 9.2317551e+10 | U2: ='2020年全国投入产出表'!$AW$28*10000*About!$A$22 -> 5.5227614e+10 | V2: ='2020年全国投入产出表'!$AW$24*10000*About!$A$22 -> 2.2089726e+09 | W2: ='2020年全国投入产出表'!$AW$26*10000*About!$A$22 -> 2.0412444e+11 | X2: ='2020年全国投入产出表'!$AW$27*10000*About!$A$22 -> 2.0266324e+10 | Y2: ='2020年全国投入产出表'!$AW$30*10000*About!$A$22 -> 6.2694049e+09 | Z2: ='2020年全国投入产出表'!$AW$31*10000*About!$A$22 -> 8.4690148e+10 | AA2: ='2020年全国投入产出表'!$AW$32*10000*About!$A$22 -> 4.6488153e+10 | AB2: ='2020年全国投入产出表'!$AW$33*10000*About!$A$22 -> 2.8627618e+10 | AC2: ='2020年全国投入产出表'!$AW$34*10000*About!$A$22 -> 0 | AD2: ='2020年全国投入产出表'!$AW$35*10000*About!$A$22 -> 3.0005126e+11 | AE2: ='2020年全国投入产出表'!$AW$36*10000*About!$A$22 -> 1.8993861e+11 | AF2: ='2020年全国投入产出表'!$AW$37*10000*About!$A$22 -> 2.5147854e+11 | AG2: ='2020年全国投入产出表'!$AW$38*10000*About!$A$22 -> 1.7168059e+11 | AH2: ='2020年全国投入产出表'!$AW$41*10000*About!$A$22 -> 4.9307424e+10 | AI2: ='2020年全国投入产出表'!$AW$42*10000*About!$A$22 -> 0 | AJ2: ='2020年全国投入产出表'!$AW$39*10000*About!$A$22 -> 4.1293678e+11 | AK2: ='2020年全国投入产出表'!$AW$40*10000*About!$A$22 -> 7.563358e+11 | AL2: ='2020年全国投入产出表'!$AW$43*10000*About!$A$22 -> 6.0565444e+09 | AM2: ='2020年全国投入产出表'!$AW$48*10000*About!$A$22 -> 1.5967753e+10 | AN2: ='2020年全国投入产出表'!$AW$45*10000*About!$A$22 -> 3.2361434e+11 | AO2: ='2020年全国投入产出表'!$AW$46*10000*About!$A$22 -> 2.3628398e+11 | AP2: ='2020年全国投入产出表'!$AW$47*10000*About!$A$22 -> 7.2992572e+10 | AQ2: ='2020年全国投入产出表'!$AW$44*10000*About!$A$22 -> 2.0889382e+11
B3: 农林牧渔产品和服务 | C3: 煤炭开采和洗选产品 | D3: 石油和天然气开采产品 | E3: 金属矿采选产品&非金属矿 | F3: 开采辅助活动和其他采矿产品 | G3: 食品和烟草 | H3: 纺织品、纺织服装鞋帽皮革羽绒及其制品 | I3: 木材加工品和家具 | J3: 造纸印刷和文教体育用品 | K3: 石油、炼焦产品和核燃料加工品 | L3: 化学原料和化学制品制造业&化学纤维制造业 | M3: 医药制造业 | N3: 橡胶和塑料制品业 | O3: 非金属矿物制品 | P3: 专用设备 | Q3: 黑色金属冶炼和压延加工品 | R3: 有色金属冶炼和压延加工品 | S3: 金属制品 | T3: 通信设备、计算机和其他电子设备&仪器仪表 | U3: 电气机械和器材 | V3: 通用设备 | W3: 汽车制造业 | X3: 铁路、船舶、航空航天和其他运输设备 | Y3: 其他制造产品和废品废料、金属制品、机械和设备修理服务 | Z3: 电力、热力生产和供应 | AA3: 燃气生产和供应 | AB3: 水的生产和供应 | AC3: 建筑 | AD3: 批发和零售 | AE3: 交通运输、仓储和邮政 | AF3: 住宿和餐饮 | AG3: 信息传输、软件和信息技术服务 | AH3: 租赁和商务服务 | AI3: 研究和试验发展 | AJ3: 金融 | AK3: 房地产 | AL3: 综合技术服务 | AM3: 水利、环境和公共设施管理、公共管理、社会保障和社会组织 | AN3: 教育 | AO3: 卫生和社会工作 | AP3: 文化、体育和娱乐 | AQ3: 居民服务、修理和其他服务
