Workbook

Sheet About
A1: TTS Transportation Technology Shareweights
A3: Source: | B3: LDVs (except battery electric vehicles in the Last Year)
B4: EIA
B5: 2020
B6: Annual Energy Outlook 2020
B7: https://www.eia.gov/outlooks/aeo/supplement/excel/suptab_39.xlsx
B8: Table 39
B10: LDVs (battery electric vehicles in the Last Year)
B11: The Edison Foundation Institute for Electric Innovation
B12: 2018
B13: Electric Vehicle Sales Forecast and the Charging Infrastructure Required Through 2030
B14: http://www.ehcar.net/library/rapport/rapport233.pdf
B15: Figure 2
B17: Bloomberg New Energy Finance
B18: 2020
B19: Long-term passenger vehicle outlook
B20: https://bnef.turtl.co/story/evo-2020/page/3?teaser=yes
B21: Figure 2
B23: freight HDVs, Last Year passenger HDVs
B24: EIA
B25: 2020
B26: Annual Energy Outlook 2020
B27: https://www.eia.gov/outlooks/aeo/supplement/excel/suptab_49.xlsx
B28: Table 49
B30: First Year passenger HDVs, First Year passenger motorbikes
B31: See SYVbT variable.
B33: Last Year passenger motorbikes
B34: Clean Rider
B35: 2014
B36: The electric scooter market
B37: http://cleanrider.com/electric-scooter-market/
B39: RevZilla Motorsports
B40: 2015
B41: How Many Motorcycles wer Sold in the U.S. Last Year?
B42: https://www.revzilla.com/common-tread/us-motorcycle-sales
A44: Notes
A45: This variable provides the shareweights used in the modified logit equation for vehicle
A46: technology selection. We base them on estimated potential maximum sales shares in each year.
A47: For more on this, see the "Modified Logit" equation description at:
A48: https://jgcri.github.io/gcam-doc/choice.html
A50: When adapting the model to a new country or region, it may be helpful
A51: to calibrate this variable after replacing the input data for other variables.
A53: To make it easier to set the values for this variable, it is set up to interpolate
A54: between the current sales share and the potential 2050 sales share.
A55: The easiest way to calibrate this variable is to simply adjust these first and
A56: last year values (on the "Data" tab).
A58: Here are the assumptions we use for the U.S.:
B60: First and Last Simulated Year Values
B62: All nonroad modes have a 100% share of the "nonroad vehicle"
B63: technology type and a 0% share of the other technology types.
B64: Technology allocation is only used for on-road vehicles in the EPS.
B66: On-road modes all have a 0% share of the "nonroad vehicle"
B67: technology type.
B69: The technology that is the reference type for a given vehicle type is
B70: allowed a 100% share in all years. (This is "gasoline vehicle" for LDVs
B71: and motorbikes, "diesel vehicle" for HDVs.)
B73: First Simulated Year Values Only
B75: For passenger LDVs, we use the sales shares by technology from AEO 38
B76: in year 2030 as the maximum potential in the first simulated year.
... B127: as 100% of U.S. motorbike sales in 205.

Sheet Vehicle Sales Database
A1: Index | B1: Year | C1: FuelType | D1: Fuel Type Adjusted | E1: Class | F1: UseType | G1: Class2 | H1: Database Class | I1: EPS Class | J1: Sales | M1: Fuel Adjustment | P1: Class Adjustment
A2: 1 | B2: 2015 | C2: 插电式混合动力 | D2: =VLOOKUP(C2,M$3:N$16,2,FALSE) -> plugin hybrid vehicle | E2: 大型客车 | F2: 城市公交 | G2: 商用车 | H2: =VLOOKUP(E2&F2&G2,$S$3:$U$68,2,FALSE) -> 公交车 | I2: =VLOOKUP(E2&F2&G2,$S$3:$U$68,3,FALSE) -> Passenger HDV | J2: 16295 | M2: FuelType | N2: Fuel Type Adjusted | P2: Class | Q2: UseType | R2: Class2 | S2: Key | T2: Database | U2: EPS | V2: 数量
A3: 2 | B3: 2016 | C3: 插电式混合动力 | D3: =VLOOKUP(C3,M$3:N$16,2,FALSE) -> plugin hybrid vehicle | E3: 大型客车 | F3: 城市公交 | G3: 商用车 | H3: =VLOOKUP(E3&F3&G3,$S$3:$U$68,2,FALSE) -> 公交车 | I3: =VLOOKUP(E3&F3&G3,$S$3:$U$68,3,FALSE) -> Passenger HDV | J3: 4474 | M3: 插电式混合动力 | N3: plugin hybrid vehicle | P3: 小型客车 | Q3: 非营运 | R3: 乘用车 | S3: =P3&Q3&R3 -> 小型客车非营运乘用车 | T3: 乘用车 | U3: Passenger LDV | V3: =SUMIFS(J:J,E:E,P3,F:F,Q3,G:G,R3) -> 150944896
A4: 3 | B4: 2017 | C4: 插电式混合动力 | D4: =VLOOKUP(C4,M$3:N$16,2,FALSE) -> plugin hybrid vehicle | E4: 大型客车 | F4: 城市公交 | G4: 商用车 | H4: =VLOOKUP(E4&F4&G4,$S$3:$U$68,2,FALSE) -> 公交车 | I4: =VLOOKUP(E4&F4&G4,$S$3:$U$68,3,FALSE) -> Passenger HDV | J4: 12043 | M4: 柴油 | N4: diesel vehicle | P4: 轻型货车 | Q4: 非营运 | R4: 商用车 | S4: =P4&Q4&R4 -> 轻型货车非营运商用车 | T4: 轻型货车 | U4: Freight LDV | V4: =SUMIFS(J:J,E:E,P4,F:F,Q4,G:G,R4) -> 10907801
A5: 4 | B5: 2018 | C5: 插电式混合动力 | D5: =VLOOKUP(C5,M$3:N$16,2,FALSE) -> plugin hybrid vehicle | E5: 大型客车 | F5: 城市公交 | G5: 商用车 | H5: =VLOOKUP(E5&F5&G5,$S$3:$U$68,2,FALSE) -> 公交车 | I5: =VLOOKUP(E5&F5&G5,$S$3:$U$68,3,FALSE) -> Passenger HDV | J5: 5764 | M5: 纯电动 | N5: battery electric vehicle | P5: 重型货车 | Q5: 营运 | R5: 商用车 | S5: =P5&Q5&R5 -> 重型货车营运商用车 | T5: 中重型货车 | U5: Freight HDV | V5: =SUMIFS(J:J,E:E,P5,F:F,Q5,G:G,R5) -> 6273983
A6: 5 | B6: 2019 | C6: 插电式混合动力 | D6: =VLOOKUP(C6,M$3:N$16,2,FALSE) -> plugin hybrid vehicle | E6: 大型客车 | F6: 城市公交 | G6: 商用车 | H6: =VLOOKUP(E6&F6&G6,$S$3:$U$68,2,FALSE) -> 公交车 | I6: =VLOOKUP(E6&F6&G6,$S$3:$U$68,3,FALSE) -> Passenger HDV | J6: 4294 | M6: 混合动力 | N6: hybrid fuel vehicle | P6: 轻型货车 | Q6: 营运 | R6: 商用车 | S6: =P6&Q6&R6 -> 轻型货车营运商用车 | T6: 轻型货车 | U6: Freight LDV | V6: =SUMIFS(J:J,E:E,P6,F:F,Q6,G:G,R6) -> 3069497
A7: 6 | B7: 2020 | C7: 插电式混合动力 | D7: =VLOOKUP(C7,M$3:N$16,2,FALSE) -> plugin hybrid vehicle | E7: 大型客车 | F7: 城市公交 | G7: 商用车 | H7: =VLOOKUP(E7&F7&G7,$S$3:$U$68,2,FALSE) -> 公交车 | I7: =VLOOKUP(E7&F7&G7,$S$3:$U$68,3,FALSE) -> Passenger HDV | J7: 5040 | M7: 汽油 | N7: gasoline vehicle | P7: 小型客车 | Q7: 出租租赁 | R7: 乘用车 | S7: =P7&Q7&R7 -> 小型客车出租租赁乘用车 | T7: 出租车 | U7: Passenger LDV | V7: =SUMIFS(J:J,E:E,P7,F:F,Q7,G:G,R7) -> 2976234
A8: 7 | B8: 2021 | C8: 插电式混合动力 | D8: =VLOOKUP(C8,M$3:N$16,2,FALSE) -> plugin hybrid vehicle | E8: 大型客车 | F8: 城市公交 | G8: 商用车 | H8: =VLOOKUP(E8&F8&G8,$S$3:$U$68,2,FALSE) -> 公交车 | I8: =VLOOKUP(E8&F8&G8,$S$3:$U$68,3,FALSE) -> Passenger HDV | J8: 1224 | M8: 汽油-天然气 | N8: natural gas vehicle | P8: 未知 | Q8: 非营运 | R8: 商用车 | S8: =P8&Q8&R8 -> 未知非营运商用车 | T8: Unknown | U8: Unknown | V8: =SUMIFS(J:J,E:E,P8,F:F,Q8,G:G,R8) -> 2193211
A9: 8 | B9: 2015 | C9: 柴油 | D9: =VLOOKUP(C9,M$3:N$16,2,FALSE) -> diesel vehicle | E9: 大型客车 | F9: 城市公交 | G9: 商用车 | H9: =VLOOKUP(E9&F9&G9,$S$3:$U$68,2,FALSE) -> 公交车 | I9: =VLOOKUP(E9&F9&G9,$S$3:$U$68,3,FALSE) -> Passenger HDV | J9: 21733 | M9: 燃料电池 | N9: hydrogen vehicle | P9: 微型客车 | Q9: 非营运 | R9: 乘用车 | S9: =P9&Q9&R9 -> 微型客车非营运乘用车 | T9: 乘用车 | U9: Passenger LDV | V9: =SUMIFS(J:J,E:E,P9,F:F,Q9,G:G,R9) -> 1396360
A10: 9 | B10: 2016 | C10: 柴油 | D10: =VLOOKUP(C10,M$3:N$16,2,FALSE) -> diesel vehicle | E10: 大型客车 | F10: 城市公交 | G10: 商用车 | H10: =VLOOKUP(E10&F10&G10,$S$3:$U$68,2,FALSE) -> 公交车 | I10: =VLOOKUP(E10&F10&G10,$S$3:$U$68,3,FALSE) -> Passenger HDV | J10: 7308 | M10: 天然气 | N10: natural gas vehicle | P10: 小型客车 | Q10: 非营运 | R10: 商用车 | S10: =P10&Q10&R10 -> 小型客车非营运商用车 | T10: 乘用车 | U10: Passenger LDV | V10: =SUMIFS(J:J,E:E,P10,F:F,Q10,G:G,R10) -> 1152779
A11: 10 | B11: 2017 | C11: 柴油 | D11: =VLOOKUP(C11,M$3:N$16,2,FALSE) -> diesel vehicle | E11: 大型客车 | F11: 城市公交 | G11: 商用车 | H11: =VLOOKUP(E11&F11&G11,$S$3:$U$68,2,FALSE) -> 公交车 | I11: =VLOOKUP(E11&F11&G11,$S$3:$U$68,3,FALSE) -> Passenger HDV | J11: 4681 | M11: 无 | N11: unknown | P11: 重型货车 | Q11: 未知 | R11: 商用车 | S11: =P11&Q11&R11 -> 重型货车未知商用车 | T11: 中重型货车 | U11: Freight HDV | V11: =SUMIFS(J:J,E:E,P11,F:F,Q11,G:G,R11) -> 683717
A12: 11 | B12: 2018 | C12: 柴油 | D12: =VLOOKUP(C12,M$3:N$16,2,FALSE) -> diesel vehicle | E12: 大型客车 | F12: 城市公交 | G12: 商用车 | H12: =VLOOKUP(E12&F12&G12,$S$3:$U$68,2,FALSE) -> 公交车 | I12: =VLOOKUP(E12&F12&G12,$S$3:$U$68,3,FALSE) -> Passenger HDV | J12: 2329 | M12: 甲醇 | N12: other fuel vehicle | P12: 大型客车 | Q12: 城市公交 | R12: 商用车 | S12: =P12&Q12&R12 -> 大型客车城市公交商用车 | T12: 公交车 | U12: Passenger HDV | V12: =SUMIFS(J:J,E:E,P12,F:F,Q12,G:G,R12) -> 551293
A13: 12 | B13: 2019 | C13: 柴油 | D13: =VLOOKUP(C13,M$3:N$16,2,FALSE) -> diesel vehicle | E13: 大型客车 | F13: 城市公交 | G13: 商用车 | H13: =VLOOKUP(E13&F13&G13,$S$3:$U$68,2,FALSE) -> 公交车 | I13: =VLOOKUP(E13&F13&G13,$S$3:$U$68,3,FALSE) -> Passenger HDV | J13: 1012 | M13: 柴油-天然气 | N13: natural gas vehicle | P13: 重型货车 | Q13: 非营运 | R13: 商用车 | S13: =P13&Q13&R13 -> 重型货车非营运商用车 | T13: 中重型货车 | U13: Freight HDV | V13: =SUMIFS(J:J,E:E,P13,F:F,Q13,G:G,R13) -> 500202
A14: 13 | B14: 2020 | C14: 柴油 | D14: =VLOOKUP(C14,M$3:N$16,2,FALSE) -> diesel vehicle | E14: 大型客车 | F14: 城市公交 | G14: 商用车 | H14: =VLOOKUP(E14&F14&G14,$S$3:$U$68,2,FALSE) -> 公交车 | I14: =VLOOKUP(E14&F14&G14,$S$3:$U$68,3,FALSE) -> Passenger HDV | J14: 662 | M14: 柴油-甲醇 | N14: hybrid fuel vehicle | P14: 中型货车 | Q14: 营运 | R14: 商用车 | S14: =P14&Q14&R14 -> 中型货车营运商用车 | T14: 中重型货车 | U14: Freight HDV | V14: =SUMIFS(J:J,E:E,P14,F:F,Q14,G:G,R14) -> 285237
... A16: 15 | B16: 2015 | C16: 纯电动 | D16: =VLOOKUP(C16,M$3:N$16,2,FALSE) -> battery electric vehicle | E16: 大型客车 | F16: 城市公交 | G16: 商用车 | H16: =VLOOKUP(E16&F16&G16,$S$3:$U$68,2,FALSE) -> 公交车 | I16: =VLOOKUP(E16&F16&G16,$S$3:$U$68,3,FALSE) -> Passenger HDV | J16: 44539 | M16: 增程式混合动力 | N16: hybrid fuel vehicle | P16: 大型客车 | Q16: 非营运 | R16: 商用车 | S16: =P16&Q16&R16 -> 大型客车非营运商用车 | T16: 道路客车 | U16: Passenger HDV | V16: =SUMIFS(J:J,E:E,P16,F:F,Q16,G:G,R16) -> 232628
A17: 16 | B17: 2016 | C17: 纯电动 | D17: =VLOOKUP(C17,M$3:N$16,2,FALSE) -> battery electric vehicle | E17: 大型客车 | F17: 城市公交 | G17: 商用车 | H17: =VLOOKUP(E17&F17&G17,$S$3:$U$68,2,FALSE) -> 公交车 | I17: =VLOOKUP(E17&F17&G17,$S$3:$U$68,3,FALSE) -> Passenger HDV | J17: 60979 | P17: 大型客车 | Q17: 公路客运 | R17: 商用车 | S17: =P17&Q17&R17 -> 大型客车公路客运商用车 | T17: 道路客车 | U17: Passenger HDV | V17: =SUMIFS(J:J,E:E,P17,F:F,Q17,G:G,R17) -> 201564
A18: 17 | B18: 2017 | C18: 纯电动 | D18: =VLOOKUP(C18,M$3:N$16,2,FALSE) -> battery electric vehicle | E18: 大型客车 | F18: 城市公交 | G18: 商用车 | H18: =VLOOKUP(E18&F18&G18,$S$3:$U$68,2,FALSE) -> 公交车 | I18: =VLOOKUP(E18&F18&G18,$S$3:$U$68,3,FALSE) -> Passenger HDV | J18: 56938 | P18: NULL | Q18: 非营运 | R18: 乘用车 | S18: =P18&Q18&R18 -> NULL非营运乘用车 | T18: 乘用车 | U18: Unknown | V18: =SUMIFS(J:J,E:E,P18,F:F,Q18,G:G,R18) -> 198660
A19: 18 | B19: 2018 | C19: 纯电动 | D19: =VLOOKUP(C19,M$3:N$16,2,FALSE) -> battery electric vehicle | E19: 大型客车 | F19: 城市公交 | G19: 商用车 | H19: =VLOOKUP(E19&F19&G19,$S$3:$U$68,2,FALSE) -> 公交车 | I19: =VLOOKUP(E19&F19&G19,$S$3:$U$68,3,FALSE) -> Passenger HDV | J19: 79727 | P19: 中型货车 | Q19: 非营运 | R19: 商用车 | S19: =P19&Q19&R19 -> 中型货车非营运商用车 | T19: 中重型货车 | U19: Freight HDV | V19: =SUMIFS(J:J,E:E,P19,F:F,Q19,G:G,R19) -> 193197
A20: 19 | B20: 2019 | C20: 纯电动 | D20: =VLOOKUP(C20,M$3:N$16,2,FALSE) -> battery electric vehicle | E20: 大型客车 | F20: 城市公交 | G20: 商用车 | H20: =VLOOKUP(E20&F20&G20,$S$3:$U$68,2,FALSE) -> 公交车 | I20: =VLOOKUP(E20&F20&G20,$S$3:$U$68,3,FALSE) -> Passenger HDV | J20: 67030 | P20: 未知 | Q20: 营运 | R20: 商用车 | S20: =P20&Q20&R20 -> 未知营运商用车 | T20: Unknown | U20: Unknown | V20: =SUMIFS(J:J,E:E,P20,F:F,Q20,G:G,R20) -> 191372
A21: 20 | B21: 2020 | C21: 纯电动 | D21: =VLOOKUP(C21,M$3:N$16,2,FALSE) -> battery electric vehicle | E21: 大型客车 | F21: 城市公交 | G21: 商用车 | H21: =VLOOKUP(E21&F21&G21,$S$3:$U$68,2,FALSE) -> 公交车 | I21: =VLOOKUP(E21&F21&G21,$S$3:$U$68,3,FALSE) -> Passenger HDV | J21: 51600 | P21: 中型客车 | Q21: 非营运 | R21: 商用车 | S21: =P21&Q21&R21 -> 中型客车非营运商用车 | T21: 道路客车 | U21: Passenger HDV | V21: =SUMIFS(J:J,E:E,P21,F:F,Q21,G:G,R21) -> 161822
A22: 21 | B22: 2021 | C22: 纯电动 | D22: =VLOOKUP(C22,M$3:N$16,2,FALSE) -> battery electric vehicle | E22: 大型客车 | F22: 城市公交 | G22: 商用车 | H22: =VLOOKUP(E22&F22&G22,$S$3:$U$68,2,FALSE) -> 公交车 | I22: =VLOOKUP(E22&F22&G22,$S$3:$U$68,3,FALSE) -> Passenger HDV | J22: 39634 | P22: 中型货车 | Q22: 未知 | R22: 商用车 | S22: =P22&Q22&R22 -> 中型货车未知商用车 | T22: 中重型货车 | U22: Freight HDV | V22: =SUMIFS(J:J,E:E,P22,F:F,Q22,G:G,R22) -> 159848
A23: 22 | B23: 2015 | C23: 混合动力 | D23: =VLOOKUP(C23,M$3:N$16,2,FALSE) -> hybrid fuel vehicle | E23: 大型客车 | F23: 城市公交 | G23: 商用车 | H23: =VLOOKUP(E23&F23&G23,$S$3:$U$68,2,FALSE) -> 公交车 | I23: =VLOOKUP(E23&F23&G23,$S$3:$U$68,3,FALSE) -> Passenger HDV | J23: 7940 | P23: 小型客车 | Q23: 营运 | R23: 商用车 | S23: =P23&Q23&R23 -> 小型客车营运商用车 | T23: 出租车 | U23: Passenger LDV | V23: =SUMIFS(J:J,E:E,P23,F:F,Q23,G:G,R23) -> 144693
A24: 23 | B24: 2016 | C24: 混合动力 | D24: =VLOOKUP(C24,M$3:N$16,2,FALSE) -> hybrid fuel vehicle | E24: 大型客车 | F24: 城市公交 | G24: 商用车 | H24: =VLOOKUP(E24&F24&G24,$S$3:$U$68,2,FALSE) -> 公交车 | I24: =VLOOKUP(E24&F24&G24,$S$3:$U$68,3,FALSE) -> Passenger HDV | J24: 12742 | P24: 小型客车 | Q24: 营运 | R24: 乘用车 | S24: =P24&Q24&R24 -> 小型客车营运乘用车 | T24: 出租车 | U24: Passenger LDV | V24: =SUMIFS(J:J,E:E,P24,F:F,Q24,G:G,R24) -> 121818
A25: 24 | B25: 2017 | C25: 混合动力 | D25: =VLOOKUP(C25,M$3:N$16,2,FALSE) -> hybrid fuel vehicle | E25: 大型客车 | F25: 城市公交 | G25: 商用车 | H25: =VLOOKUP(E25&F25&G25,$S$3:$U$68,2,FALSE) -> 公交车 | I25: =VLOOKUP(E25&F25&G25,$S$3:$U$68,3,FALSE) -> Passenger HDV | J25: 2171 | P25: 小型客车 | Q25: 公路客运 | R25: 乘用车 | S25: =P25&Q25&R25 -> 小型客车公路客运乘用车 | T25: 道路客车 | U25: Passenger LDV | V25: =SUMIFS(J:J,E:E,P25,F:F,Q25,G:G,R25) -> 93633
A26: 25 | B26: 2018 | C26: 混合动力 | D26: =VLOOKUP(C26,M$3:N$16,2,FALSE) -> hybrid fuel vehicle | E26: 大型客车 | F26: 城市公交 | G26: 商用车 | H26: =VLOOKUP(E26&F26&G26,$S$3:$U$68,2,FALSE) -> 公交车 | I26: =VLOOKUP(E26&F26&G26,$S$3:$U$68,3,FALSE) -> Passenger HDV | J26: 228 | P26: 小型客车 | Q26: 未知 | R26: 商用车 | S26: =P26&Q26&R26 -> 小型客车未知商用车 | T26: 出租车 | U26: Passenger LDV | V26: =SUMIFS(J:J,E:E,P26,F:F,Q26,G:G,R26) -> 81321
A27: 26 | B27: 2019 | C27: 混合动力 | D27: =VLOOKUP(C27,M$3:N$16,2,FALSE) -> hybrid fuel vehicle | E27: 大型客车 | F27: 城市公交 | G27: 商用车 | H27: =VLOOKUP(E27&F27&G27,$S$3:$U$68,2,FALSE) -> 公交车 | I27: =VLOOKUP(E27&F27&G27,$S$3:$U$68,3,FALSE) -> Passenger HDV | J27: 3 | P27: 中型客车 | Q27: 公路客运 | R27: 商用车 | S27: =P27&Q27&R27 -> 中型客车公路客运商用车 | T27: 道路客车 | U27: Passenger HDV | V27: =SUMIFS(J:J,E:E,P27,F:F,Q27,G:G,R27) -> 69510
A28: 27 | B28: 2021 | C28: 混合动力 | D28: =VLOOKUP(C28,M$3:N$16,2,FALSE) -> hybrid fuel vehicle | E28: 大型客车 | F28: 城市公交 | G28: 商用车 | H28: =VLOOKUP(E28&F28&G28,$S$3:$U$68,2,FALSE) -> 公交车 | I28: =VLOOKUP(E28&F28&G28,$S$3:$U$68,3,FALSE) -> Passenger HDV | J28: 2 | P28: 中型客车 | Q28: 城市公交 | R28: 商用车 | S28: =P28&Q28&R28 -> 中型客车城市公交商用车 | T28: 公交车 | U28: Passenger HDV | V28: =SUMIFS(J:J,E:E,P28,F:F,Q28,G:G,R28) -> 30427
... A68: 67 | B68: 2020 | C68: 汽油 | D68: =VLOOKUP(C68,M$3:N$16,2,FALSE) -> gasoline vehicle | E68: 小型客车 | F68: 城市公交 | G68: 商用车 | H68: =VLOOKUP(E68&F68&G68,$S$3:$U$68,2,FALSE) -> 公交车 | I68: =VLOOKUP(E68&F68&G68,$S$3:$U$68,3,FALSE) -> Passenger LDV | J68: 106 | P68: NULL | Q68: 公路客运 | R68: 乘用车 | S68: =P68&Q68&R68 -> NULL公路客运乘用车 | T68: Unknown | U68: Unknown | V68: =SUMIFS(J:J,E:E,P68,F:F,Q68,G:G,R68) -> 1
A69: 68 | B69: 2021 | C69: 汽油 | D69: =VLOOKUP(C69,M$3:N$16,2,FALSE) -> gasoline vehicle | E69: 小型客车 | F69: 城市公交 | G69: 商用车 | H69: =VLOOKUP(E69&F69&G69,$S$3:$U$68,2,FALSE) -> 公交车 | I69: =VLOOKUP(E69&F69&G69,$S$3:$U$68,3,FALSE) -> Passenger LDV | J69: 34
A70: 69 | B70: 2016 | C70: 汽油-天然气 | D70: =VLOOKUP(C70,M$3:N$16,2,FALSE) -> natural gas vehicle | E70: 小型客车 | F70: 城市公交 | G70: 商用车 | H70: =VLOOKUP(E70&F70&G70,$S$3:$U$68,2,FALSE) -> 公交车 | I70: =VLOOKUP(E70&F70&G70,$S$3:$U$68,3,FALSE) -> Passenger LDV | J70: 88
A71: 70 | B71: 2017 | C71: 汽油-天然气 | D71: =VLOOKUP(C71,M$3:N$16,2,FALSE) -> natural gas vehicle | E71: 小型客车 | F71: 城市公交 | G71: 商用车 | H71: =VLOOKUP(E71&F71&G71,$S$3:$U$68,2,FALSE) -> 公交车 | I71: =VLOOKUP(E71&F71&G71,$S$3:$U$68,3,FALSE) -> Passenger LDV | J71: 11
A72: 71 | B72: 2018 | C72: 汽油-天然气 | D72: =VLOOKUP(C72,M$3:N$16,2,FALSE) -> natural gas vehicle | E72: 小型客车 | F72: 城市公交 | G72: 商用车 | H72: =VLOOKUP(E72&F72&G72,$S$3:$U$68,2,FALSE) -> 公交车 | I72: =VLOOKUP(E72&F72&G72,$S$3:$U$68,3,FALSE) -> Passenger LDV | J72: 60
A73: 72 | B73: 2019 | C73: 汽油-天然气 | D73: =VLOOKUP(C73,M$3:N$16,2,FALSE) -> natural gas vehicle | E73: 小型客车 | F73: 城市公交 | G73: 商用车 | H73: =VLOOKUP(E73&F73&G73,$S$3:$U$68,2,FALSE) -> 公交车 | I73: =VLOOKUP(E73&F73&G73,$S$3:$U$68,3,FALSE) -> Passenger LDV | J73: 129
A74: 73 | B74: 2020 | C74: 汽油-天然气 | D74: =VLOOKUP(C74,M$3:N$16,2,FALSE) -> natural gas vehicle | E74: 小型客车 | F74: 城市公交 | G74: 商用车 | H74: =VLOOKUP(E74&F74&G74,$S$3:$U$68,2,FALSE) -> 公交车 | I74: =VLOOKUP(E74&F74&G74,$S$3:$U$68,3,FALSE) -> Passenger LDV | J74: 82
A75: 74 | B75: 2016 | C75: 天然气 | D75: =VLOOKUP(C75,M$3:N$16,2,FALSE) -> natural gas vehicle | E75: 小型客车 | F75: 城市公交 | G75: 商用车 | H75: =VLOOKUP(E75&F75&G75,$S$3:$U$68,2,FALSE) -> 公交车 | I75: =VLOOKUP(E75&F75&G75,$S$3:$U$68,3,FALSE) -> Passenger LDV | J75: 5
A76: 75 | B76: 2017 | C76: 天然气 | D76: =VLOOKUP(C76,M$3:N$16,2,FALSE) -> natural gas vehicle | E76: 小型客车 | F76: 城市公交 | G76: 商用车 | H76: =VLOOKUP(E76&F76&G76,$S$3:$U$68,2,FALSE) -> 公交车 | I76: =VLOOKUP(E76&F76&G76,$S$3:$U$68,3,FALSE) -> Passenger LDV | J76: 256
A77: 76 | B77: 2018 | C77: 天然气 | D77: =VLOOKUP(C77,M$3:N$16,2,FALSE) -> natural gas vehicle | E77: 小型客车 | F77: 城市公交 | G77: 商用车 | H77: =VLOOKUP(E77&F77&G77,$S$3:$U$68,2,FALSE) -> 公交车 | I77: =VLOOKUP(E77&F77&G77,$S$3:$U$68,3,FALSE) -> Passenger LDV | J77: 115
A78: 77 | B78: 2019 | C78: 天然气 | D78: =VLOOKUP(C78,M$3:N$16,2,FALSE) -> natural gas vehicle | E78: 小型客车 | F78: 城市公交 | G78: 商用车 | H78: =VLOOKUP(E78&F78&G78,$S$3:$U$68,2,FALSE) -> 公交车 | I78: =VLOOKUP(E78&F78&G78,$S$3:$U$68,3,FALSE) -> Passenger LDV | J78: 40
A79: 78 | B79: 2020 | C79: 天然气 | D79: =VLOOKUP(C79,M$3:N$16,2,FALSE) -> natural gas vehicle | E79: 小型客车 | F79: 城市公交 | G79: 商用车 | H79: =VLOOKUP(E79&F79&G79,$S$3:$U$68,2,FALSE) -> 公交车 | I79: =VLOOKUP(E79&F79&G79,$S$3:$U$68,3,FALSE) -> Passenger LDV | J79: 1
A80: 79 | B80: 2017 | C80: 柴油 | D80: =VLOOKUP(C80,M$3:N$16,2,FALSE) -> diesel vehicle | E80: 中型货车 | F80: 城市公交 | G80: 商用车 | H80: =VLOOKUP(E80&F80&G80,$S$3:$U$68,2,FALSE) -> 公交车 | I80: =VLOOKUP(E80&F80&G80,$S$3:$U$68,3,FALSE) -> Passenger HDV | J80: 51
... A1161: 1160 | B1161: 2020 | C1161: 汽油 | D1161: =VLOOKUP(C1161,M$3:N$16,2,FALSE) -> gasoline vehicle | E1161: 中型客车 | F1161: 营运 | G1161: 乘用车 | H1161: =VLOOKUP(E1161&F1161&G1161,$S$3:$U$68,2,FALSE) -> 道路客车 | I1161: =VLOOKUP(E1161&F1161&G1161,$S$3:$U$68,3,FALSE) -> Passenger HDV | J1161: 1

Sheet Pivot Table
A1: 求和项:Sales | B1: 列标签
A2: 行标签 | B2: battery electric vehicle | C2: diesel vehicle | D2: gasoline vehicle | E2: hybrid fuel vehicle | F2: hydrogen vehicle | G2: LPG vehicle | H2: natural gas vehicle | I2: other fuel vehicle | J2: plugin hybrid vehicle | K2: unknown | L2: 总计 | N2: Fuel Type | O2: battery electric vehicle | P2: natural gas vehicle | Q2: gasoline vehicle | R2: diesel vehicle | S2: plugin hybrid vehicle | T2: LPG vehicle | U2: hydrogen vehicle | V2: hybrid fuel vehicle | W2: other fuel vehicle
A3: Freight HDV | B3: 49887 | C3: 7556854 | D3: 402 | E3: 106 | F3: 4322 | H3: 484270 | I3: 117 | J3: 1156 | K3: 4 | L3: 8097118 | N3: Freight HDV
A4: 2015 | B4: 5722 | C4: 543387 | D4: 213 | H4: 14079 | L4: 563401 | N4: 2015 | O4: =B4/($L4-$K4) -> 0.010156177 | P4: =H4/($L4-$K4) -> 0.024989306 | Q4: =D4/($L4-$K4) -> 0.0003780611 | R4: =C4/($L4-$K4) -> 0.96447646 | S4: =J4/($L4-$K4) -> 0 | T4: =G4/($L4-$K4) -> 0 | U4: =F4/($L4-$K4) -> 0 | V4: =E4/($L4-$K4) -> 0 | W4: =I4/($L4-$K4) -> 0
A5: 2016 | B5: 4529 | C5: 761880 | D5: 25 | E5: 6 | H5: 15344 | K5: 4 | L5: 781788 | N5: 2016 | O5: =B5/($L5-$K5) -> 0.0057931603 | P5: =H5/($L5-$K5) -> 0.019626905 | Q5: =D5/($L5-$K5) -> 3.1978142e-05 | R5: =C5/($L5-$K5) -> 0.97454028 | S5: =J5/($L5-$K5) -> 0 | T5: =G5/($L5-$K5) -> 0 | U5: =F5/($L5-$K5) -> 0 | V5: =E5/($L5-$K5) -> 7.6747542e-06 | W5: =I5/($L5-$K5) -> 0
A6: 2017 | B6: 16933 | C6: 1061952 | D6: 46 | E6: 56 | F6: 933 | H6: 70507 | J6: 1120 | L6: 1151547 | N6: 2017 | O6: =B6/($L6-$K6) -> 0.014704567 | P6: =H6/($L6-$K6) -> 0.06122807 | Q6: =D6/($L6-$K6) -> 3.9946264e-05 | R6: =C6/($L6-$K6) -> 0.92219597 | S6: =J6/($L6-$K6) -> 0.00097260468 | T6: =G6/($L6-$K6) -> 0 | U6: =F6/($L6-$K6) -> 0.00081021443 | V6: =E6/($L6-$K6) -> 4.8630234e-05 | W6: =I6/($L6-$K6) -> 0
A7: 2018 | B7: 1648 | C7: 1070295 | D7: 40 | E7: 2 | F7: 404 | H7: 65710 | L7: 1138099 | N7: 2018 | O7: =B7/($L7-$K7) -> 0.0014480287 | P7: =H7/($L7-$K7) -> 0.057736629 | Q7: =D7/($L7-$K7) -> 3.5146327e-05 | R7: =C7/($L7-$K7) -> 0.94042346 | S7: =J7/($L7-$K7) -> 0 | T7: =G7/($L7-$K7) -> 0 | U7: =F7/($L7-$K7) -> 0.00035497791 | V7: =E7/($L7-$K7) -> 1.7573164e-06 | W7: =I7/($L7-$K7) -> 0
A8: 2019 | B8: 5962 | C8: 1141356 | D8: 30 | F8: 2014 | H8: 116202 | I8: 13 | L8: 1265577 | N8: 2019 | O8: =B8/($L8-$K8) -> 0.0047108947 | P8: =H8/($L8-$K8) -> 0.091817408 | Q8: =D8/($L8-$K8) -> 2.3704603e-05 | R8: =C8/($L8-$K8) -> 0.90184635 | S8: =J8/($L8-$K8) -> 0 | T8: =G8/($L8-$K8) -> 0 | U8: =F8/($L8-$K8) -> 0.001591369 | V8: =E8/($L8-$K8) -> 0 | W8: =I8/($L8-$K8) -> 1.0271995e-05
A9: 2020 | B9: 4111 | C9: 1530088 | D9: 44 | E9: 24 | F9: 146 | H9: 142829 | I9: 14 | J9: 11 | L9: 1677267 | N9: 2020 | O9: =B9/($L9-$K9) -> 0.0024510111 | P9: =H9/($L9-$K9) -> 0.085155792 | Q9: =D9/($L9-$K9) -> 2.6233152e-05 | R9: =C9/($L9-$K9) -> 0.9122507 | S9: =J9/($L9-$K9) -> 6.558288e-06 | T9: =G9/($L9-$K9) -> 0 | U9: =F9/($L9-$K9) -> 8.7046368e-05 | V9: =E9/($L9-$K9) -> 1.4308992e-05 | W9: =I9/($L9-$K9) -> 8.346912e-06
A10: 2021 | B10: 10982 | C10: 1447896 | D10: 4 | E10: 18 | F10: 825 | H10: 59599 | I10: 90 | J10: 25 | L10: 1519439 | N10: 2021 | O10: =B10/($L10-$K10) -> 0.0072276676 | P10: =H10/($L10-$K10) -> 0.039224345 | Q10: =D10/($L10-$K10) -> 2.6325506e-06 | R10: =C10/($L10-$K10) -> 0.95291486 | S10: =J10/($L10-$K10) -> 1.6453441e-05 | T10: =G10/($L10-$K10) -> 0 | U10: =F10/($L10-$K10) -> 0.00054296355 | V10: =E10/($L10-$K10) -> 1.1846478e-05 | W10: =I10/($L10-$K10) -> 5.9232388e-05
A11: Freight LDV | B11: 217086 | C11: 7283616 | D11: 6562410 | E11: 12 | F11: 3 | H11: 176564 | J11: 1667 | L11: 14241358 | N11: Freight LDV
A12: 2015 | B12: 24785 | C12: 763006 | D12: 706406 | E12: 4 | H12: 36040 | L12: 1530241 | N12: 2015 | O12: =B12/($L12-$K12) -> 0.016196795 | P12: =H12/($L12-$K12) -> 0.023551846 | Q12: =D12/($L12-$K12) -> 0.46163055 | R12: =C12/($L12-$K12) -> 0.49861819 | S12: =J12/($L12-$K12) -> 0 | T12: =G12/($L12-$K12) -> 0 | U12: =F12/($L12-$K12) -> 0 | V12: =E12/($L12-$K12) -> 2.6139673e-06 | W12: =I12/($L12-$K12) -> 0
A13: 2016 | B13: 17755 | C13: 876597 | D13: 756679 | H13: 16696 | L13: 1667727 | N13: 2016 | O13: =B13/($L13-$K13) -> 0.010646227 | P13: =H13/($L13-$K13) -> 0.010011231 | Q13: =D13/($L13-$K13) -> 0.45371874 | R13: =C13/($L13-$K13) -> 0.5256238 | S13: =J13/($L13-$K13) -> 0 | T13: =G13/($L13-$K13) -> 0 | U13: =F13/($L13-$K13) -> 0 | V13: =E13/($L13-$K13) -> 0 | W13: =I13/($L13-$K13) -> 0
A14: 2017 | B14: 61786 | C14: 1024613 | D14: 838364 | H14: 20278 | L14: 1945041 | N14: 2017 | O14: =B14/($L14-$K14) -> 0.031765911 | P14: =H14/($L14-$K14) -> 0.010425487 | Q14: =D14/($L14-$K14) -> 0.43102639 | R14: =C14/($L14-$K14) -> 0.52678221 | S14: =J14/($L14-$K14) -> 0 | T14: =G14/($L14-$K14) -> 0 | U14: =F14/($L14-$K14) -> 0 | V14: =E14/($L14-$K14) -> 0 | W14: =I14/($L14-$K14) -> 0
A15: 2018 | B15: 40792 | C15: 1036146 | D15: 940137 | H15: 27190 | J15: 1 | L15: 2044266 | N15: 2018 | O15: =B15/($L15-$K15) -> 0.01995435 | P15: =H15/($L15-$K15) -> 0.013300617 | Q15: =D15/($L15-$K15) -> 0.45988976 | R15: =C15/($L15-$K15) -> 0.50685478 | S15: =J15/($L15-$K15) -> 4.8917313e-07 | T15: =G15/($L15-$K15) -> 0 | U15: =F15/($L15-$K15) -> 0 | V15: =E15/($L15-$K15) -> 0 | W15: =I15/($L15-$K15) -> 0
A16: 2019 | B16: 18134 | C16: 1052509 | D16: 1086406 | H16: 32818 | J16: 98 | L16: 2189965 | N16: 2019 | O16: =B16/($L16-$K16) -> 0.0082804976 | P16: =H16/($L16-$K16) -> 0.014985628 | Q16: =D16/($L16-$K16) -> 0.49608373 | R16: =C16/($L16-$K16) -> 0.4806054 | S16: =J16/($L16-$K16) -> 4.4749574e-05 | T16: =G16/($L16-$K16) -> 0 | U16: =F16/($L16-$K16) -> 0 | V16: =E16/($L16-$K16) -> 0 | W16: =I16/($L16-$K16) -> 0
A17: 2020 | B17: 15349 | C17: 1319180 | D17: 1157774 | H17: 21626 | J17: 318 | L17: 2514247 | N17: 2020 | O17: =B17/($L17-$K17) -> 0.0061048099 | P17: =H17/($L17-$K17) -> 0.0086013824 | Q17: =D17/($L17-$K17) -> 0.46048539 | R17: =C17/($L17-$K17) -> 0.52468194 | S17: =J17/($L17-$K17) -> 0.00012647922 | T17: =G17/($L17-$K17) -> 0 | U17: =F17/($L17-$K17) -> 0 | V17: =E17/($L17-$K17) -> 0 | W17: =I17/($L17-$K17) -> 0
A18: 2021 | B18: 38485 | C18: 1211565 | D18: 1076644 | E18: 8 | F18: 3 | H18: 21916 | J18: 1250 | L18: 2349871 | N18: 2021 | O18: =B18/($L18-$K18) -> 0.016377495 | P18: =H18/($L18-$K18) -> 0.0093264694 | Q18: =D18/($L18-$K18) -> 0.45817153 | R18: =C18/($L18-$K18) -> 0.51558788 | S18: =J18/($L18-$K18) -> 0.00053194409 | T18: =G18/($L18-$K18) -> 0 | U18: =F18/($L18-$K18) -> 1.2766658e-06 | V18: =E18/($L18-$K18) -> 3.4044422e-06 | W18: =I18/($L18-$K18) -> 0
A19: Passenger HDV | B19: 512915 | C19: 547268 | D19: 102586 | E19: 24163 | F19: 4155 | H19: 53334 | I19: 5 | J19: 51218 | K19: 38 | L19: 1295682 | N19: Passenger HDV
A20: 2015 | B20: 85938 | C20: 123176 | D20: 18249 | E20: 8354 | H20: 25597 | J20: 16901 | K20: 38 | L20: 278253 | N20: 2015 | O20: =B20/($L20-$K20) -> 0.30889061 | P20: =H20/($L20-$K20) -> 0.092004385 | Q20: =D20/($L20-$K20) -> 0.065593156 | R20: =C20/($L20-$K20) -> 0.44273673 | S20: =J20/($L20-$K20) -> 0.060747983 | T20: =G20/($L20-$K20) -> 0 | U20: =F20/($L20-$K20) -> 0 | V20: =E20/($L20-$K20) -> 0.030027137 | W20: =I20/($L20-$K20) -> 0
A21: 2016 | B21: 91058 | C21: 113793 | D21: 19181 | E21: 13270 | F21: 29 | H21: 11598 | J21: 5344 | L21: 254273 | N21: 2016 | O21: =B21/($L21-$K21) -> 0.35811116 | P21: =H21/($L21-$K21) -> 0.045612393 | Q21: =D21/($L21-$K21) -> 0.075434671 | R21: =C21/($L21-$K21) -> 0.44752294 | S21: =J21/($L21-$K21) -> 0.021016781 | T21: =G21/($L21-$K21) -> 0 | U21: =F21/($L21-$K21) -> 0.00011405065 | V21: =E21/($L21-$K21) -> 0.052188003 | W21: =I21/($L21-$K21) -> 0
A22: 2017 | B22: 76566 | C22: 85307 | D22: 16807 | E22: 2295 | F22: 115 | H22: 8781 | J22: 12561 | L22: 202432 | N22: 2017 | O22: =B22/($L22-$K22) -> 0.37823071 | P22: =H22/($L22-$K22) -> 0.043377529 | Q22: =D22/($L22-$K22) -> 0.083025411 | R22: =C22/($L22-$K22) -> 0.42141065 | S22: =J22/($L22-$K22) -> 0.062050466 | T22: =G22/($L22-$K22) -> 0 | U22: =F22/($L22-$K22) -> 0.000568092 | V22: =E22/($L22-$K22) -> 0.01133714 | W22: =I22/($L22-$K22) -> 0
A23: 2018 | B23: 85927 | C23: 72442 | D23: 12754 | E23: 239 | F23: 437 | H23: 3832 | I23: 5 | J23: 5839 | L23: 181475 | N23: 2018 | O23: =B23/($L23-$K23) -> 0.47349222 | P23: =H23/($L23-$K23) -> 0.021115856 | Q23: =D23/($L23-$K23) -> 0.070279653 | R23: =C23/($L23-$K23) -> 0.39918446 | S23: =J23/($L23-$K23) -> 0.032175231 | T23: =G23/($L23-$K23) -> 0 | U23: =F23/($L23-$K23) -> 0.0024080452 | V23: =E23/($L23-$K23) -> 0.0013169858 | W23: =I23/($L23-$K23) -> 2.7552004e-05
A24: 2019 | B24: 72243 | C24: 70020 | D24: 15305 | E24: 3 | F24: 1176 | H24: 2082 | J24: 4298 | L24: 165127 | N24: 2019 | O24: =B24/($L24-$K24) -> 0.43749962 | P24: =H24/($L24-$K24) -> 0.012608477 | Q24: =D24/($L24-$K24) -> 0.092686235 | R24: =C24/($L24-$K24) -> 0.42403726 | S24: =J24/($L24-$K24) -> 0.026028451 | T24: =G24/($L24-$K24) -> 0 | U24: =F24/($L24-$K24) -> 0.0071217911 | V24: =E24/($L24-$K24) -> 1.8167834e-05 | W24: =I24/($L24-$K24) -> 0
A25: 2020 | B25: 55145 | C25: 35741 | D25: 7949 | F25: 1351 | H25: 915 | J25: 5049 | L25: 106150 | N25: 2020 | O25: =B25/($L25-$K25) -> 0.51950071 | P25: =H25/($L25-$K25) -> 0.0086198775 | Q25: =D25/($L25-$K25) -> 0.074884597 | R25: =C25/($L25-$K25) -> 0.33670278 | S25: =J25/($L25-$K25) -> 0.047564767 | T25: =G25/($L25-$K25) -> 0 | U25: =F25/($L25-$K25) -> 0.012727273 | V25: =E25/($L25-$K25) -> 0 | W25: =I25/($L25-$K25) -> 0
A26: 2021 | B26: 46038 | C26: 46789 | D26: 12341 | E26: 2 | F26: 1047 | H26: 529 | J26: 1226 | L26: 107972 | N26: 2021 | O26: =B26/($L26-$K26) -> 0.42638832 | P26: =H26/($L26-$K26) -> 0.0048994184 | Q26: =D26/($L26-$K26) -> 0.11429815 | R26: =C26/($L26-$K26) -> 0.43334383 | S26: =J26/($L26-$K26) -> 0.011354796 | T26: =G26/($L26-$K26) -> 0 | U26: =F26/($L26-$K26) -> 0.0096969585 | V26: =E26/($L26-$K26) -> 1.8523321e-05 | W26: =I26/($L26-$K26) -> 0
A27: Passenger LDV | B27: 5711717 | C27: 1203924 | D27: 144403802 | E27: 2485070 | F27: 77 | G27: 10354 | H27: 2028005 | I27: 26020 | J27: 1106569 | L27: 156975538 | N27: Passenger LDV
A28: 2015 | B28: 135782 | C28: 163367 | D28: 19291074 | E28: 69444 | H28: 1495689 | I28: 578 | J28: 12662 | L28: 21168596 | N28: 2015 | O28: =B28/($L28-$K28) -> 0.006414313 | P28: =H28/($L28-$K28) -> 0.070656032 | Q28: =D28/($L28-$K28) -> 0.91130626 | R28: =C28/($L28-$K28) -> 0.0077174225 | S28: =J28/($L28-$K28) -> 0.0005981502 | T28: =G28/($L28-$K28) -> 0 | U28: =F28/($L28-$K28) -> 0 | V28: =E28/($L28-$K28) -> 0.0032805199 | W28: =I28/($L28-$K28) -> 2.7304598e-05
A29: 2016 | B29: 246143 | C29: 154701 | D29: 24058794 | E29: 157772 | F29: 8 | G29: 1722 | H29: 110827 | I29: 205 | J29: 24705 | L29: 24754877 | N29: 2016 | O29: =B29/($L29-$K29) -> 0.0099432124 | P29: =H29/($L29-$K29) -> 0.0044769764 | Q29: =D29/($L29-$K29) -> 0.97188098 | R29: =C29/($L29-$K29) -> 0.006249314 | S29: =J29/($L29-$K29) -> 0.00099798516 | T29: =G29/($L29-$K29) -> 6.956205e-05 | U29: =F29/($L29-$K29) -> 3.2316864e-07 | V29: =E29/($L29-$K29) -> 0.0063733704 | W29: =I29/($L29-$K29) -> 8.2811965e-06
A30: 2017 | B30: 508748 | C30: 160842 | D30: 23725630 | E30: 222304 | F30: 50 | G30: 5287 | H30: 99873 | I30: 2309 | J30: 58890 | L30: 24783933 | N30: 2017 | O30: =B30/($L30-$K30) -> 0.020527331 | P30: =H30/($L30-$K30) -> 0.0040297478 | Q30: =D30/($L30-$K30) -> 0.95729883 | R30: =C30/($L30-$K30) -> 0.006489769 | S30: =J30/($L30-$K30) -> 0.0023761362 | T30: =G30/($L30-$K30) -> 0.00021332369 | U30: =F30/($L30-$K30) -> 2.0174361e-06 | V30: =E30/($L30-$K30) -> 0.0089696821 | W30: =I30/($L30-$K30) -> 9.3165197e-05
A31: 2018 | B31: 744374 | C31: 188491 | D31: 21161732 | E31: 308721 | G31: 3142 | H31: 127403 | I31: 1842 | J31: 187801 | L31: 22723506 | N31: 2018 | O31: =B31/($L31-$K31) -> 0.032757885 | P31: =H31/($L31-$K31) -> 0.0056066612 | Q31: =D31/($L31-$K31) -> 0.93127055 | R31: =C31/($L31-$K31) -> 0.0082949788 | S31: =J31/($L31-$K31) -> 0.0082646137 | T31: =G31/($L31-$K31) -> 0.00013827092 | U31: =F31/($L31-$K31) -> 0 | V31: =E31/($L31-$K31) -> 0.013585976 | W31: =I31/($L31-$K31) -> 8.1061435e-05
A32: 2019 | B32: 724626 | C32: 157907 | D32: 20272632 | E32: 376905 | G32: 203 | H32: 107211 | I32: 14561 | J32: 200475 | L32: 21854520 | N32: 2019 | O32: =B32/($L32-$K32) -> 0.033156802 | P32: =H32/($L32-$K32) -> 0.0049056671 | Q32: =D32/($L32-$K32) -> 0.92761735 | R32: =C32/($L32-$K32) -> 0.0072253703 | S32: =J32/($L32-$K32) -> 0.0091731596 | T32: =G32/($L32-$K32) -> 9.2886963e-06 | U32: =F32/($L32-$K32) -> 0 | V32: =E32/($L32-$K32) -> 0.017246089 | W32: =I32/($L32-$K32) -> 0.00066626949
A33: 2020 | B33: 939086 | C33: 187404 | D33: 18373144 | E33: 552189 | H33: 41878 | I33: 5688 | J33: 207790 | L33: 20307179 | N33: 2020 | O33: =B33/($L33-$K33) -> 0.04624404 | P33: =H33/($L33-$K33) -> 0.0020622264 | Q33: =D33/($L33-$K33) -> 0.90476102 | R33: =C33/($L33-$K33) -> 0.0092284605 | S33: =J33/($L33-$K33) -> 0.010232342 | T33: =G33/($L33-$K33) -> 0 | U33: =F33/($L33-$K33) -> 0 | V33: =E33/($L33-$K33) -> 0.027191812 | W33: =I33/($L33-$K33) -> 0.00028009799
A34: 2021 | B34: 2412958 | C34: 191212 | D34: 17520796 | E34: 797735 | F34: 19 | H34: 45124 | I34: 837 | J34: 414246 | L34: 21382927 | N34: 2021 | O34: =B34/($L34-$K34) -> 0.11284507 | P34: =H34/($L34-$K34) -> 0.0021102817 | Q34: =D34/($L34-$K34) -> 0.81938249 | R34: =C34/($L34-$K34) -> 0.0089422744 | S34: =J34/($L34-$K34) -> 0.019372745 | T34: =G34/($L34-$K34) -> 0 | U34: =F34/($L34-$K34) -> 8.8855936e-07 | V34: =E34/($L34-$K34) -> 0.0373071 | W34: =I34/($L34-$K34) -> 3.9143378e-05
A35: Unknown | B35: 3058 | C35: 16503 | D35: 2339472 | E35: 22971 | H35: 10200 | J35: 6003 | K35: 192895 | L35: 2591102
A36: 2015 | B36: 261 | C36: 16431 | D36: 2172590 | H36: 10200 | K36: 192895 | L36: 2392377
A37: 2021 | B37: 2797 | C37: 72 | D37: 166882 | E37: 22971 | J37: 6003 | L37: 198725
A38: 总计 | B38: 6494663 | C38: 16608165 | D38: 153408672 | E38: 2532322 | F38: 8557 | G38: 10354 | H38: 2752373 | I38: 26142 | J38: 1166613 | K38: 192937 | L38: 183200798

Sheet Electric Ratio
A1: 求和项:Sales | B1: 列标签
A2: 行标签 | B2: battery electric vehicle | C2: diesel vehicle | D2: gasoline vehicle | E2: hybrid fuel vehicle | F2: hydrogen vehicle | G2: LPG vehicle | H2: natural gas vehicle | I2: other fuel vehicle | J2: plugin hybrid vehicle | K2: unknown | L2: 总计 | O2: 车型占比 | P2: 电动化率 | Q2: 混动占比 | R2: 纯电占比 | S2: 车型占比 | T2: 电动化率 | U2: 混动占比 | V2: 纯电占比 | W2: 车型占比 | X2: 电动化率 | Y2: 混动占比 | Z2: 纯电占比 | AA2: 车型占比 | AB2: 电动化率 | AC2: 混动占比 | AD2: 纯电占比 | AE2: 车型占比 | AF2: 电动化率 | AG2: 混动占比 | AH2: 纯电占比 | AI2: 车型占比 | AJ2: 电动化率 | AK2: 混动占比 | AL2: 纯电占比 | AM2: 车型占比 | AN2: 电动化率 | AO2: 混动占比 | AP2: 纯电占比 | AQ2: 车型占比 | AR2: 电动化率 | AS2: 混动占比 | AT2: 纯电占比 | AU2: 车型占比 | AV2: 电动化率 | AW2: 混动占比 | AX2: 纯电占比 | AY2: 车型占比 | AZ2: 电动化率 | BA2: 混动占比 | BB2: 纯电占比
A3: Freight HDV | B3: 49887 | C3: 7556854 | D3: 402 | E3: 106 | F3: 4322 | H3: 484270 | I3: 117 | J3: 1156 | K3: 4 | L3: 8097118 | N3: EPS Type | O3: Freight HDV | S3: Freight LDV | W3: Passenger HDV | AI3: Passenger LDV
A4: 中重型货车 | B4: 49887 | C4: 7556854 | D4: 402 | E4: 106 | F4: 4322 | H4: 484270 | I4: 117 | J4: 1156 | K4: 4 | L4: 8097118 | N4: Database Type | O4: 中重型货车 | S4: 轻型货车 | W4: 合并 | AA4: 道路客车 | AE4: 公交车 | AI4: 合并 | AM4: 乘用车 | AQ4: 出租车 | AU4: 道路客车 | AY4: 公交车
A5: 2015 | B5: 5722 | C5: 543387 | D5: 213 | H5: 14079 | L5: 563401 | N5: 2015-2021 | O5: =L4/L4 -> 1 | P5: =(J4+B4)/L4 -> 0.0063038479 | Q5: =J4/(J4+B4) -> 0.022647572 | R5: =B4/(B4+J4) -> 0.97735243 | S5: =L13/L13 -> 1 | T5: =(J13+B13)/L13 -> 0.015360403 | U5: =J13/(J13+B13) -> 0.0076204669 | V5: =B13/(B13+J13) -> 0.99237953 | W5: =AA5+AE5 -> 1 | X5: =AB5*AA5+AF5*AE5 -> 0.43539464 | Y5: =(AA5*AB5*AC5+AE5*AF5*AG5)/(AA5*AB5+AE5*AF5) -> 0.01205722 | Z5: =(AA5*AB5*AD5+AE5*AF5*AH5)/(AA5*AB5+AE5*AF5) -> 0.90920935 | AA5: =L22/(L22+L30) -> 0.54903055 | AB5: =(J22+B22)/L22 -> 0.15372753 | AC5: =J22/(J22+B22) -> 0.018581344 | AD5: =B22/(B22+J22) -> 0.98141866 | AE5: =L30/(L22+L30) -> 0.45096945 | AF5: =(B30+J30)/L30 -> 0.77830889 | AG5: =J30/(J30+B39) -> 0.010488406 | AH5: =B30/(B30+J30) -> 0.89184566 | AI5: =AM5+AQ5+AU5+AY5 -> 1 | AJ5: =(AM5*AN5+AQ5*AR5+AU5*AV5+AY5*AZ5) -> 0.043435341 | AK5: =(AM5*AN5*AO5+AQ5*AR5*AS5+AU5*AV5*AW5+AY5*AZ5*BA5)/(AM5*AN5+AQ5*AR5+AU5*AV5+AY5*AZ5) -> 0.16229431 | AL5: =(AM5*AN5*AP5+AQ5*AR5*AT5+AU5*AV5*AX5+AY5*AZ5*BB5)/(AM5*AN5+AQ5*AR5+AU5*AV5+AY5*AZ5) -> 0.83770569 | AM5: =L39/(L39+L47+L55+L63) -> 0.97785901 | AN5: =(J39+B39)/L39 -> 0.037040691 | AO5: =J39/(J39+B39) -> 0.18385826 | AP5: =B39/(B39+J39) -> 0.81614174 | AQ5: =L47/(L39+L47+L55+L63) -> 0.021366482 | AR5: =(B47+J47)/L47 -> 0.33657423 | AS5: =J47/(J47+B47) -> 0.054196435 | AT5: =B47/(B47+J47) -> 0.94580357 | AU5: =L55/(L39+L47+L55+L63) -> 0.00073858005 | AV5: =(B55+J55)/L55 -> 0.023374361 | AW5: =J55/(J55+B55) -> 0.0062730627 | AX5: =B55/(B55+J55) -> 0.99372694 | AY5: =L63/(L39+L47+L55+L63) -> 3.5929165e-05 | AZ5: =(B63+J63)/L63 -> 0.16968085 | BA5: =J63/(J63+B63) -> 0 | BB5: =B63/(B63+J63) -> 1
A6: 2016 | B6: 4529 | C6: 761880 | D6: 25 | E6: 6 | H6: 15344 | K6: 4 | L6: 781788 | N6: 2015 | O6: =L5/L5 -> 1 | P6: =(J5+B5)/L5 -> 0.010156177 | Q6: =J5/(J5+B5) -> 0 | R6: =B5/(B5+J5) -> 1 | S6: =L14/L14 -> 1 | T6: =(J14+B14)/L14 -> 0.016196795 | U6: =J14/(J14+B14) -> 0 | V6: =B14/(B14+J14) -> 1 | W6: =AA6+AE6 -> 1 | X6: =AB6*AA6+AF6*AE6 -> 0.36958811 | Y6: =(AA6*AB6*AC6+AE6*AF6*AG6)/(AA6*AB6+AE6*AF6) -> 0.078797614 | Z6: =(AA6*AB6*AD6+AE6*AF6*AH6)/(AA6*AB6+AE6*AF6) -> 0.83565573 | AA6: =L23/(L23+L31) -> 0.53563484 | AB6: =(J23+B23)/L23 -> 0.28081346 | AC6: =J23/(J23+B23) -> 0.014479249 | AD6: =B23/(B23+J23) -> 0.98552075 | AE6: =L31/(L23+L31) -> 0.46436516 | AF6: =(B31+J31)/L31 -> 0.47198768 | AG6: =J31/(J31+B40) -> 0.12293752 | AH6: =B31/(B31+J31) -> 0.73280753 | AI6: =AM6+AQ6+AU6+AY6 -> 1 | AJ6: =(AM6*AN6+AQ6*AR6+AU6*AV6+AY6*AZ6) -> 0.0070124632 | AK6: =(AM6*AN6*AO6+AQ6*AR6*AS6+AU6*AV6*AW6+AY6*AZ6*BA6)/(AM6*AN6+AQ6*AR6+AU6*AV6+AY6*AZ6) -> 0.08529816 | AL6: =(AM6*AN6*AP6+AQ6*AR6*AT6+AU6*AV6*AX6+AY6*AZ6*BB6)/(AM6*AN6+AQ6*AR6+AU6*AV6+AY6*AZ6) -> 0.91470184 | AM6: =L40/(L40+L48+L56+L64) -> 0.98191226 | AN6: =(J40+B40)/L40 -> 0.00607557 | AO6: =J40/(J40+B40) -> 0.079447282 | AP6: =B40/(B40+J40) -> 0.92055272 | AQ6: =L48/(L40+L48+L56+L64) -> 0.017548731 | AR6: =(B48+J48)/L48 -> 0.059238402 | AS6: =J48/(J48+B48) -> 0.11946742 | AT6: =B48/(B48+J48) -> 0.88053258 | AU6: =L56/(L40+L48+L56+L64) -> 0.00050683569 | AV6: =(B56+J56)/L56 -> 0.00027961599 | AW6: =J56/(J56+B56) -> 0 | AX6: =B56/(B56+J56) -> 1 | AY6: =L64/(L40+L48+L56+L64) -> 3.2170296e-05 | AZ6: =(B64+J64)/L64 -> 0.22026432 | BA6: =J64/(J64+B64) -> 0 | BB6: =B64/(B64+J64) -> 1
A7: 2017 | B7: 16933 | C7: 1061952 | D7: 46 | E7: 56 | F7: 933 | H7: 70507 | J7: 1120 | L7: 1151547 | N7: 2016 | O7: =L5/L5 -> 1 | P7: =(J6+B6)/L6 -> 0.0057931306 | Q7: =J6/(J6+B6) -> 0 | R7: =B6/(B6+J6) -> 1 | S7: =L14/L14 -> 1 | T7: =(J15+B15)/L15 -> 0.010646227 | U7: =J15/(J15+B15) -> 0 | V7: =B15/(B15+J15) -> 1 | W7: =AA7+AE7 -> 1 | X7: =AB7*AA7+AF7*AE7 -> 0.37912795 | Y7: =(AA7*AB7*AC7+AE7*AF7*AG7)/(AA7*AB7+AE7*AF7) -> 0.022941066 | Z7: =(AA7*AB7*AD7+AE7*AF7*AH7)/(AA7*AB7+AE7*AF7) -> 0.94456547 | AA7: =L24/(L24+L32) -> 0.62035293 | AB7: =(J24+B24)/L24 -> 0.19620386 | AC7: =J24/(J24+B24) -> 0.028110763 | AD7: =B24/(B24+J24) -> 0.97188924 | AE7: =L32/(L24+L32) -> 0.37964707 | AF7: =(B32+J32)/L32 -> 0.67803054 | AG7: =J32/(J32+B41) -> 0.02049661 | AH7: =B32/(B32+J32) -> 0.93164561 | AI7: =AM7+AQ7+AU7+AY7 -> 1 | AJ7: =(AM7*AN7+AQ7*AR7+AU7*AV7+AY7*AZ7) -> 0.010941198 | AK7: =(AM7*AN7*AO7+AQ7*AR7*AS7+AU7*AV7*AW7+AY7*AZ7*BA7)/(AM7*AN7+AQ7*AR7+AU7*AV7+AY7*AZ7) -> 0.091213522 | AL7: =(AM7*AN7*AP7+AQ7*AR7*AT7+AU7*AV7*AX7+AY7*AZ7*BB7)/(AM7*AN7+AQ7*AR7+AU7*AV7+AY7*AZ7) -> 0.90878648 | AM7: =L41/(L41+L49+L57+L65) -> 0.9861319 | AN7: =(J41+B41)/L41 -> 0.0096563212 | AO7: =J41/(J41+B41) -> 0.092989318 | AP7: =B41/(B41+J41) -> 0.90701068 | AQ7: =L49/(L41+L49+L57+L65) -> 0.013550219 | AR7: =(B49+J49)/L49 -> 0.1046644 | AS7: =J49/(J49+B49) -> 0.079326649 | AT7: =B49/(B49+J49) -> 0.92067335 | AU7: =L57/(L41+L49+L57+L65) -> 0.00030272823 | AV7: =(B57+J57)/L57 -> 0.0018681612 | AW7: =J57/(J57+B57) -> 0 | AX7: =B57/(B57+J57) -> 1 | AY7: =L65/(L41+L49+L57+L65) -> 1.514853e-05 | AZ7: =(B65+J65)/L65 -> 0 | BA7: =IFERROR(J65/(J65+B65),BA5) -> 0 | BB7: =IFERROR(B65/(B65+J65),BB5) -> 1
A8: 2018 | B8: 1648 | C8: 1070295 | D8: 40 | E8: 2 | F8: 404 | H8: 65710 | L8: 1138099 | N8: 2017 | O8: =L6/L6 -> 1 | P8: =(J7+B7)/L7 -> 0.015677172 | Q8: =J7/(J7+B7) -> 0.06203955 | R8: =B7/(B7+J7) -> 0.93796045 | S8: =L15/L15 -> 1 | T8: =(J16+B16)/L16 -> 0.031765911 | U8: =J16/(J16+B16) -> 0 | V8: =B16/(B16+J16) -> 1 | W8: =AA8+AE8 -> 1 | X8: =AB8*AA8+AF8*AE8 -> 0.44028118 | Y8: =(AA8*AB8*AC8+AE8*AF8*AG8)/(AA8*AB8+AE8*AF8) -> 0.02675972 | Z8: =(AA8*AB8*AD8+AE8*AF8*AH8)/(AA8*AB8+AE8*AF8) -> 0.85906628 | AA8: =L25/(L25+L33) -> 0.57428173 | AB8: =(J25+B25)/L25 -> 0.16203453 | AC8: =J25/(J25+B25) -> 0.024738546 | AD8: =B25/(B25+J25) -> 0.97526145 | AE8: =L33/(L25+L33) -> 0.42571827 | AF8: =(B33+J33)/L33 -> 0.81562794 | AG8: =J33/(J33+B42) -> 0.027301374 | AH8: =B33/(B33+J33) -> 0.82792716 | AI8: =AM8+AQ8+AU8+AY8 -> 1 | AJ8: =(AM8*AN8+AQ8*AR8+AU8*AV8+AY8*AZ8) -> 0.022903467 | AK8: =(AM8*AN8*AO8+AQ8*AR8*AS8+AU8*AV8*AW8+AY8*AZ8*BA8)/(AM8*AN8+AQ8*AR8+AU8*AV8+AY8*AZ8) -> 0.1037457 | AL8: =(AM8*AN8*AP8+AQ8*AR8*AT8+AU8*AV8*AX8+AY8*AZ8*BB8)/(AM8*AN8+AQ8*AR8+AU8*AV8+AY8*AZ8) -> 0.8962543 | AM8: =L42/(L42+L50+L58+L66) -> 0.97716545 | AN8: =(J42+B42)/L42 -> 0.020046409 | AO8: =J42/(J42+B42) -> 0.11238475 | AP8: =B42/(B42+J42) -> 0.88761525 | AQ8: =L50/(L42+L50+L58+L66) -> 0.021733193 | AR8: =(B50+J50)/L50 -> 0.15131611 | AS8: =J50/(J50+B50) -> 0.053113958 | AT8: =B50/(B50+J50) -> 0.94688604 | AU8: =L58/(L42+L50+L58+L66) -> 0.0010505597 | AV8: =(B58+J58)/L58 -> 0.023812267 | AW8: =J58/(J58+B58) -> 0 | AX8: =B58/(B58+J58) -> 1 | AY8: =L66/(L42+L50+L58+L66) -> 5.079904e-05 | AZ8: =(B66+J66)/L66 -> 0.023828435 | BA8: =J66/(J66+B66) -> 0 | BB8: =B66/(B66+J66) -> 1
A9: 2019 | B9: 5962 | C9: 1141356 | D9: 30 | F9: 2014 | H9: 116202 | I9: 13 | L9: 1265577 | N9: 2018 | O9: =L7/L7 -> 1 | P9: =(J8+B8)/L8 -> 0.0014480287 | Q9: =J8/(J8+B8) -> 0 | R9: =B8/(B8+J8) -> 1 | S9: =L16/L16 -> 1 | T9: =(J17+B17)/L17 -> 0.01995484 | U9: =J17/(J17+B17) -> 2.451401e-05 | V9: =B17/(B17+J17) -> 0.99997549 | W9: =AA9+AE9 -> 1 | X9: =AB9*AA9+AF9*AE9 -> 0.50566745 | Y9: =(AA9*AB9*AC9+AE9*AF9*AG9)/(AA9*AB9+AE9*AF9) -> 0.010064986 | Z9: =(AA9*AB9*AD9+AE9*AF9*AH9)/(AA9*AB9+AE9*AF9) -> 0.93637077 | AA9: =L26/(L26+L34) -> 0.49390274 | AB9: =(J26+B26)/L26 -> 0.069317535 | AC9: =J26/(J26+B26) -> 0.012071463 | AD9: =B26/(B26+J26) -> 0.98792854 | AE9: =L34/(L26+L34) -> 0.50609726 | AF9: =(B34+J34)/L34 -> 0.93150342 | AG9: =J34/(J34+B43) -> 0.0099192725 | AH9: =B34/(B34+J34) -> 0.93262656 | AI9: =AM9+AQ9+AU9+AY9 -> 1 | AJ9: =(AM9*AN9+AQ9*AR9+AU9*AV9+AY9*AZ9) -> 0.041022499 | AK9: =(AM9*AN9*AO9+AQ9*AR9*AS9+AU9*AV9*AW9+AY9*AZ9*BA9)/(AM9*AN9+AQ9*AR9+AU9*AV9+AY9*AZ9) -> 0.20146539 | AL9: =(AM9*AN9*AP9+AQ9*AR9*AT9+AU9*AV9*AX9+AY9*AZ9*BB9)/(AM9*AN9+AQ9*AR9+AU9*AV9+AY9*AZ9) -> 0.79853461 | AM9: =L43/(L43+L51+L59+L67) -> 0.97463142 | AN9: =(J43+B43)/L43 -> 0.033992077 | AO9: =J43/(J43+B43) -> 0.2357749 | AP9: =B43/(B43+J43) -> 0.7642251 | AQ9: =L51/(L43+L51+L59+L67) -> 0.024276227 | AR9: =(B51+J51)/L51 -> 0.32499035 | AS9: =J51/(J51+B51) -> 0.057474983 | AT9: =B51/(B51+J51) -> 0.94252502 | AU9: =L59/(L43+L51+L59+L67) -> 0.0010431929 | AV9: =(B59+J59)/L59 -> 0.0025311116 | AW9: =J59/(J59+B59) -> 0 | AX9: =B59/(B59+J59) -> 1 | AY9: =L67/(L43+L51+L59+L67) -> 4.9156147e-05 | AZ9: =(B67+J67)/L67 -> 0.011638317 | BA9: =J67/(J67+B67) -> 0 | BB9: =B67/(B67+J67) -> 1
A10: 2020 | B10: 4111 | C10: 1530088 | D10: 44 | E10: 24 | F10: 146 | H10: 142829 | I10: 14 | J10: 11 | L10: 1677267 | N10: 2019 | O10: =L8/L8 -> 1 | P10: =(J9+B9)/L9 -> 0.0047108947 | Q10: =J9/(J9+B9) -> 0 | R10: =B9/(B9+J9) -> 1 | S10: =L17/L17 -> 1 | T10: =(J18+B18)/L18 -> 0.0083252472 | U10: =J18/(J18+B18) -> 0.0053751645 | V10: =B18/(B18+J18) -> 0.99462484 | W10: =AA10+AE10 -> 1 | X10: =AB10*AA10+AF10*AE10 -> 0.46352807 | Y10: =(AA10*AB10*AC10+AE10*AF10*AG10)/(AA10*AB10+AE10*AF10) -> 0.008355345 | Z10: =(AA10*AB10*AD10+AE10*AF10*AH10)/(AA10*AB10+AE10*AF10) -> 0.94384709 | AA10: =L27/(L27+L35) -> 0.53768312 | AB10: =(J27+B27)/L27 -> 0.046313608 | AC10: =J27/(J27+B27) -> 0.00097276265 | AD10: =B27/(B27+J27) -> 0.99902724 | AE10: =L35/(L27+L35) -> 0.46231688 | AF10: =(B35+J35)/L35 -> 0.94875624 | AG10: =J35/(J35+B44) -> 0.0087744751 | AH10: =B35/(B35+J35) -> 0.94071435 | AI10: =AM10+AQ10+AU10+AY10 -> 1 | AJ10: =(AM10*AN10+AQ10*AR10+AU10*AV10+AY10*AZ10) -> 0.042329962 | AK10: =(AM10*AN10*AO10+AQ10*AR10*AS10+AU10*AV10*AW10+AY10*AZ10*BA10)/(AM10*AN10+AQ10*AR10+AU10*AV10+AY10*AZ10) -> 0.21670607 | AL10: =(AM10*AN10*AP10+AQ10*AR10*AT10+AU10*AV10*AX10+AY10*AZ10*BB10)/(AM10*AN10+AQ10*AR10+AU10*AV10+AY10*AZ10) -> 0.78329393 | AM10: =L44/(L44+L52+L60+L68) -> 0.97004954 | AN10: =(J44+B44)/L44 -> 0.031539625 | AO10: =J44/(J44+B44) -> 0.27452631 | AP10: =B44/(B44+J44) -> 0.72547369 | AQ10: =L52/(L44+L52+L60+L68) -> 0.029315995 | AR10: =(B52+J52)/L52 -> 0.40004245 | AS10: =J52/(J52+B52) -> 0.065953446 | AT10: =B52/(B52+J52) -> 0.93404655 | AU10: =L60/(L44+L52+L60+L68) -> 0.00061090337 | AV10: =(B60+J60)/L60 -> 0.0086884878 | AW10: =J60/(J60+B60) -> 0.10344828 | AX10: =B60/(B60+J60) -> 0.89655172 | AY10: =L68/(L44+L52+L60+L68) -> 2.3564919e-05 | AZ10: =(B68+J68)/L68 -> 0.085436893 | BA10: =J68/(J68+B68) -> 0 | BB10: =B68/(B68+J68) -> 1
A11: 2021 | B11: 10982 | C11: 1447896 | D11: 4 | E11: 18 | F11: 825 | H11: 59599 | I11: 90 | J11: 25 | L11: 1519439 | N11: 2020 | O11: =L9/L9 -> 1 | P11: =(J10+B10)/L10 -> 0.0024575694 | Q11: =J10/(J10+B10) -> 0.0026686075 | R11: =B10/(B10+J10) -> 0.99733139 | S11: =L18/L18 -> 1 | T11: =(J19+B19)/L19 -> 0.0062312891 | U11: =J19/(J19+B19) -> 0.02029744 | V11: =B19/(B19+J19) -> 0.97970256 | W11: =AA11+AE11 -> 1 | X11: =AB11*AA11+AF11*AE11 -> 0.56706547 | Y11: =(AA11*AB11*AC11+AE11*AF11*AG11)/(AA11*AB11+AE11*AF11) -> 0.0064132174 | Z11: =(AA11*AB11*AD11+AE11*AF11*AH11)/(AA11*AB11+AE11*AF11) -> 0.91612121 | AA11: =L28/(L28+L36) -> 0.43130476 | AB11: =(J28+B28)/L28 -> 0.053753577 | AC11: =J28/(J28+B28) -> 0.00365705 | AD11: =B28/(B28+J28) -> 0.99634295 | AE11: =L36/(L28+L36) -> 0.56869524 | AF11: =(B36+J36)/L36 -> 0.95636689 | AG11: =J36/(J36+B45) -> 0.0065307053 | AH11: =B36/(B36+J36) -> 0.91270157 | AI11: =AM11+AQ11+AU11+AY11 -> 1 | AJ11: =(AM11*AN11+AQ11*AR11+AU11*AV11+AY11*AZ11) -> 0.056476382 | AK11: =(AM11*AN11*AO11+AQ11*AR11*AS11+AU11*AV11*AW11+AY11*AZ11*BA11)/(AM11*AN11+AQ11*AR11+AU11*AV11+AY11*AZ11) -> 0.18117913 | AL11: =(AM11*AN11*AP11+AQ11*AR11*AT11+AU11*AV11*AX11+AY11*AZ11*BB11)/(AM11*AN11+AQ11*AR11+AU11*AV11+AY11*AZ11) -> 0.81882087 | AM11: =L45/(L45+L53+L61+L69) -> 0.98018573 | AN11: =(J45+B45)/L45 -> 0.048318529 | AO11: =J45/(J45+B45) -> 0.20282583 | AP11: =B45/(B45+J45) -> 0.79717417 | AQ11: =L53/(L45+L53+L61+L69) -> 0.018810441 | AR11: =(B53+J53)/L53 -> 0.48163419 | AS11: =J53/(J53+B53) -> 0.069127831 | AT11: =B53/(B53+J53) -> 0.93087217 | AU11: =L61/(L45+L53+L61+L69) -> 0.00093114854 | AV11: =(B61+J61)/L61 -> 0.025331853 | AW11: =J61/(J61+B61) -> 0 | AX11: =B61/(B61+J61) -> 1 | AY11: =L69/(L45+L53+L61+L69) -> 7.2683655e-05 | AZ11: =(B69+J69)/L69 -> 0.43902439 | BA11: =J69/(J69+B69) -> 0 | BB11: =B69/(B69+J69) -> 1
A12: Freight LDV | B12: 217086 | C12: 7283616 | D12: 6562410 | E12: 12 | F12: 3 | H12: 176564 | J12: 1667 | L12: 14241358 | N12: 2021 | O12: =L10/L10 -> 1 | P12: =(J11+B11)/L11 -> 0.007244121 | Q12: =J11/(J11+B11) -> 0.0022712819 | R12: =B11/(B11+J11) -> 0.99772872 | S12: =L19/L19 -> 1 | T12: =(J20+B20)/L20 -> 0.016909439 | U12: =J20/(J20+B20) -> 0.031458412 | V12: =B20/(B20+J20) -> 0.96854159 | W12: =AA12+AE12 -> 1 | X12: =AB12*AA12+AF12*AE12 -> 0.43774312 | Y12: =(AA12*AB12*AC12+AE12*AF12*AG12)/(AA12*AB12+AE12*AF12) -> 0.00057617001 | Z12: =(AA12*AB12*AD12+AE12*AF12*AH12)/(AA12*AB12+AE12*AF12) -> 0.9740606 | AA12: =L29/(L29+L37) -> 0.59399659 | AB12: =(J29+B29)/L29 -> 0.076900288 | AC12: =J29/(J29+B29) -> 0.000405515 | AD12: =B29/(B29+J29) -> 0.99959448 | AE12: =L37/(L29+L37) -> 0.40600341 | AF12: =(B37+J37)/L37 -> 0.96566827 | AG12: =J37/(J37+B46) -> 0.00059605261 | AH12: =B37/(B37+J37) -> 0.9710857 | AI12: =AM12+AQ12+AU12+AY12 -> 1 | AJ12: =(AM12*AN12+AQ12*AR12+AU12*AV12+AY12*AZ12) -> 0.13221782 | AK12: =(AM12*AN12*AO12+AQ12*AR12*AS12+AU12*AV12*AW12+AY12*AZ12*BA12)/(AM12*AN12+AQ12*AR12+AU12*AV12+AY12*AZ12) -> 0.14652144 | AL12: =(AM12*AN12*AP12+AQ12*AR12*AT12+AU12*AV12*AX12+AY12*AZ12*BB12)/(AM12*AN12+AQ12*AR12+AU12*AV12+AY12*AZ12) -> 0.85347856 | AM12: =L46/(L46+L54+L62+L70) -> 0.97427476 | AN12: =(J46+B46)/L46 -> 0.11784348 | AO12: =J46/(J46+B46) -> 0.1640434 | AP12: =B46/(B46+J46) -> 0.8359566 | AQ12: =L54/(L46+L54+L62+L70) -> 0.02498021 | AR12: =(B54+J54)/L54 -> 0.69399794 | AS12: =J54/(J54+B54) -> 0.031054845 | AT12: =B54/(B54+J54) -> 0.96894515 | AU12: =L62/(L46+L54+L62+L70) -> 0.00073488536 | AV12: =(B62+J62)/L62 -> 0.090238004 | AW12: =J62/(J62+B62) -> 0.0035260931 | AX12: =B62/(B62+J62) -> 0.99647391 | AY12: =L70/(L46+L54+L62+L70) -> 1.0148283e-05 | AZ12: =(B70+J70)/L70 -> 0.33179724 | BA12: =J70/(J70+B70) -> 0 | BB12: =B70/(B70+J70) -> 1
A13: 轻型货车 | B13: 217086 | C13: 7283616 | D13: 6562410 | E13: 12 | F13: 3 | H13: 176564 | J13: 1667 | L13: 14241358 | N13: 2025 | O13: 1 | P13: =HLOOKUP(O$4,$O$24:$U$33,ROW(P13)-10,FALSE) -> 0.026420039 | Q13: =Q5 -> 0.022647572 | R13: =R5 -> 0.97735243 | S13: =100% -> 1 | T13: =HLOOKUP(S$4,$O$24:$U$33,ROW(T13)-10,FALSE) -> 0.089203147 | U13: =U5 -> 0.0076204669 | V13: =V5 -> 0.99237953 | W13: =AA13+AE13 -> 1 | X13: =AB13*AA13+AF13*AE13 -> 0.34046608 | Y13: =(AA13*AB13*AC13+AE13*AF13*AG13)/(AA13*AB13+AE13*AF13) -> 0.013194562 | Z13: =(AA13*AB13*AD13+AE13*AF13*AH13)/(AA13*AB13+AE13*AF13) -> 0.92179751 | AA13: =S36/(R36+S36) -> 0.75096772 | AB13: =HLOOKUP(AA$4,$O$24:$U$33,ROW(AB13)-10,FALSE) -> 0.1516 | AC13: =AC5 -> 0.018581344 | AD13: =AD5 -> 0.98141866 | AE13: =R36/(R36+S36) -> 0.24903228 | AF13: =HLOOKUP(AE$4,$O$24:$U$33,ROW(AF13)-10,FALSE) -> 0.91 | AG13: =AG5 -> 0.010488406 | AH13: =AH5 -> 0.89184566 | AI13: =AM13+AQ13+AU13+AY13 -> 1 | AJ13: =(AM13*AN13+AQ13*AR13+AU13*AV13+AY13*AZ13) -> 0.10622057 | AK13: =(AM13*AN13*AO13+AQ13*AR13*AS13+AU13*AV13*AW13+AY13*AZ13*BA13)/(AM13*AN13+AQ13*AR13+AU13*AV13+AY13*AZ13) -> 0.17368893 | AL13: =(AM13*AN13*AP13+AQ13*AR13*AT13+AU13*AV13*AX13+AY13*AZ13*BB13)/(AM13*AN13+AQ13*AR13+AU13*AV13+AY13*AZ13) -> 0.82631107 | AM13: =O36/(O36+P36+R36+S36) -> 0.98776333 | AN13: =HLOOKUP(AM$4,$O$24:$U$33,ROW(AN13)-10,FALSE) -> 0.1 | AO13: =AO5 -> 0.18385826 | AP13: =AP5 -> 0.81614174 | AQ13: =P36/(O36+P36+R36+S36) -> 0.0057557062 | AR13: =HLOOKUP(AQ$4,$O$24:$U$33,ROW(AR13)-10,FALSE) -> 0.91 | AS13: =AS5 -> 0.054196435 | AT13: =AT5 -> 0.94580357 | AU13: =S36/(O36+P36+R36+S36) -> 0.0048669938 | AV13: =HLOOKUP(AU$4,$O$24:$U$33,ROW(AV13)-10,FALSE) -> 0.1516 | AW13: =AW5 -> 0.0062730627 | AX13: =AX5 -> 0.99372694 | AY13: =R36/(O36+P36+R36+S36) -> 0.0016139689 | AZ13: =HLOOKUP(AY$4,$O$24:$U$33,ROW(AZ13)-10,FALSE) -> 0.91 | BA13: =BA5 -> 0 | BB13: =BB5 -> 1
A14: 2015 | B14: 24785 | C14: 763006 | D14: 706406 | E14: 4 | H14: 36040 | L14: 1530241 | N14: 2030 | O14: 1 | P14: =HLOOKUP(O$4,$O$24:$U$33,ROW(P14)-10,FALSE) -> 0.059427603 | Q14: =Q13 -> 0.022647572 | R14: =R13 -> 0.97735243 | S14: =100% -> 1 | T14: =HLOOKUP(S$4,$O$24:$U$33,ROW(T14)-10,FALSE) -> 0.18086855 | U14: =U13 -> 0.0076204669 | V14: =V13 -> 0.99237953 | W14: =AA14+AE14 -> 1 | X14: =AB14*AA14+AF14*AE14 -> 0.52305415 | Y14: =(AA14*AB14*AC14+AE14*AF14*AG14)/(AA14*AB14+AE14*AF14) -> 0.013646501 | Z14: =(AA14*AB14*AD14+AE14*AF14*AH14)/(AA14*AB14+AE14*AF14) -> 0.9267996 | AA14: =S37/(R37+S37) -> 0.67119227 | AB14: =HLOOKUP(AA$4,$O$24:$U$33,ROW(AB14)-10,FALSE) -> 0.30410161 | AC14: =AC13 -> 0.018581344 | AD14: =AD13 -> 0.98141866 | AE14: =R37/(R37+S37) -> 0.32880773 | AF14: =HLOOKUP(AE$4,$O$24:$U$33,ROW(AF14)-10,FALSE) -> 0.97 | AG14: =AG13 -> 0.010488406 | AH14: =AH13 -> 0.89184566 | AI14: =AM14+AQ14+AU14+AY14 -> 1 | AJ14: =(AM14*AN14+AQ14*AR14+AU14*AV14+AY14*AZ14) -> 0.15655173 | AK14: =(AM14*AN14*AO14+AQ14*AR14*AS14+AU14*AV14*AW14+AY14*AZ14*BA14)/(AM14*AN14+AQ14*AR14+AU14*AV14+AY14*AZ14) -> 0.17581857 | AL14: =(AM14*AN14*AP14+AQ14*AR14*AT14+AU14*AV14*AX14+AY14*AZ14*BB14)/(AM14*AN14+AQ14*AR14+AU14*AV14+AY14*AZ14) -> 0.82418143 | AM14: =O37/(O37+P37+R37+S37) -> 0.98833879 | AN14: =HLOOKUP(AM$4,$O$24:$U$33,ROW(AN14)-10,FALSE) -> 0.15 | AO14: =AO13 -> 0.18385826 | AP14: =AP13 -> 0.81614174 | AQ14: =P37/(O37+P37+R37+S37) -> 0.0049255857 | AR14: =HLOOKUP(AQ$4,$O$24:$U$33,ROW(AR14)-10,FALSE) -> 0.97 | AS14: =AS13 -> 0.054196435 | AT14: =AT13 -> 0.94580357 | AU14: =S37/(O37+P37+R37+S37) -> 0.0045208998 | AV14: =HLOOKUP(AU$4,$O$24:$U$33,ROW(AV14)-10,FALSE) -> 0.30410161 | AW14: =AW13 -> 0.0062730627 | AX14: =AX13 -> 0.99372694 | AY14: =R37/(O37+P37+R37+S37) -> 0.0022147258 | AZ14: =HLOOKUP(AY$4,$O$24:$U$33,ROW(AZ14)-10,FALSE) -> 0.97 | BA14: =BA13 -> 0 | BB14: =BB13 -> 1
A15: 2016 | B15: 17755 | C15: 876597 | D15: 756679 | H15: 16696 | L15: 1667727 | N15: 2035 | O15: 1 | P15: =HLOOKUP(O$4,$O$24:$U$33,ROW(P15)-10,FALSE) -> 0.10442111 | Q15: =Q14 -> 0.022647572 | R15: =R14 -> 0.97735243 | S15: =100% -> 1 | T15: =HLOOKUP(S$4,$O$24:$U$33,ROW(T15)-10,FALSE) -> 0.29922705 | U15: =U14 -> 0.0076204669 | V15: =V14 -> 0.99237953 | W15: =AA15+AE15 -> 1 | X15: =AB15*AA15+AF15*AE15 -> 0.60054664 | Y15: =(AA15*AB15*AC15+AE15*AF15*AG15)/(AA15*AB15+AE15*AF15) -> 0.015441441 | Z15: =(AA15*AB15*AD15+AE15*AF15*AH15)/(AA15*AB15+AE15*AF15) -> 0.94666607 | AA15: =S38/(R38+S38) -> 0.76699955 | AB15: =HLOOKUP(AA$4,$O$24:$U$33,ROW(AB15)-10,FALSE) -> 0.4792 | AC15: =AC14 -> 0.018581344 | AD15: =AD14 -> 0.98141866 | AE15: =R38/(R38+S38) -> 0.23300045 | AF15: =HLOOKUP(AE$4,$O$24:$U$33,ROW(AF15)-10,FALSE) -> 1 | AG15: =AG14 -> 0.010488406 | AH15: =AH14 -> 0.89184566 | AI15: =AM15+AQ15+AU15+AY15 -> 1 | AJ15: =(AM15*AN15+AQ15*AR15+AU15*AV15+AY15*AZ15) -> 0.20655035 | AK15: =(AM15*AN15*AO15+AQ15*AR15*AS15+AU15*AV15*AW15+AY15*AZ15*BA15)/(AM15*AN15+AQ15*AR15+AU15*AV15+AY15*AZ15) -> 0.17727154 | AL15: =(AM15*AN15*AP15+AQ15*AR15*AT15+AU15*AV15*AX15+AY15*AZ15*BB15)/(AM15*AN15+AQ15*AR15+AU15*AV15+AY15*AZ15) -> 0.82272846 | AM15: =O38/(O38+P38+R38+S38) -> 0.98835738 | AN15: =HLOOKUP(AM$4,$O$24:$U$33,ROW(AN15)-10,FALSE) -> 0.2 | AO15: =AO14 -> 0.18385826 | AP15: =AP14 -> 0.81614174 | AQ15: =P38/(O38+P38+R38+S38) -> 0.0047238013 | AR15: =HLOOKUP(AQ$4,$O$24:$U$33,ROW(AR15)-10,FALSE) -> 1 | AS15: =AS14 -> 0.054196435 | AT15: =AT14 -> 0.94580357 | AU15: =S38/(O38+P38+R38+S38) -> 0.0053067339 | AV15: =HLOOKUP(AU$4,$O$24:$U$33,ROW(AV15)-10,FALSE) -> 0.4792 | AW15: =AW14 -> 0.0062730627 | AX15: =AX14 -> 0.99372694 | AY15: =R38/(O38+P38+R38+S38) -> 0.0016120889 | AZ15: =HLOOKUP(AY$4,$O$24:$U$33,ROW(AZ15)-10,FALSE) -> 1 | BA15: =BA14 -> 0 | BB15: =BB14 -> 1
A16: 2017 | B16: 61786 | C16: 1024613 | D16: 838364 | H16: 20278 | L16: 1945041 | N16: 2040 | O16: 1 | P16: =HLOOKUP(O$4,$O$24:$U$33,ROW(P16)-10,FALSE) -> 0.17782076 | Q16: =Q15 -> 0.022647572 | R16: =R15 -> 0.97735243 | S16: =100% -> 1 | T16: =HLOOKUP(S$4,$O$24:$U$33,ROW(T16)-10,FALSE) -> 0.45018795 | U16: =U15 -> 0.0076204669 | V16: =V15 -> 0.99237953 | W16: =AA16+AE16 -> 1 | X16: =AB16*AA16+AF16*AE16 -> 0.75772861 | Y16: =(AA16*AB16*AC16+AE16*AF16*AG16)/(AA16*AB16+AE16*AF16) -> 0.015066662 | Z16: =(AA16*AB16*AD16+AE16*AF16*AH16)/(AA16*AB16+AE16*AF16) -> 0.942518 | AA16: =S39/(R39+S39) -> 0.67092604 | AB16: =HLOOKUP(AA$4,$O$24:$U$33,ROW(AB16)-10,FALSE) -> 0.6389 | AC16: =AC15 -> 0.018581344 | AD16: =AD15 -> 0.98141866 | AE16: =R39/(R39+S39) -> 0.32907396 | AF16: =HLOOKUP(AE$4,$O$24:$U$33,ROW(AF16)-10,FALSE) -> 1 | AG16: =AG15 -> 0.010488406 | AH16: =AH15 -> 0.89184566 | AI16: =AM16+AQ16+AU16+AY16 -> 1 | AJ16: =(AM16*AN16+AQ16*AR16+AU16*AV16+AY16*AZ16) -> 0.28653448 | AK16: =(AM16*AN16*AO16+AQ16*AR16*AS16+AU16*AV16*AW16+AY16*AZ16*BA16)/(AM16*AN16+AQ16*AR16+AU16*AV16+AY16*AZ16) -> 0.17855992 | AL16: =(AM16*AN16*AP16+AQ16*AR16*AT16+AU16*AV16*AX16+AY16*AZ16*BB16)/(AM16*AN16+AQ16*AR16+AU16*AV16+AY16*AZ16) -> 0.82144008 | AM16: =O39/(O39+P39+R39+S39) -> 0.98865382 | AN16: =HLOOKUP(AM$4,$O$24:$U$33,ROW(AN16)-10,FALSE) -> 0.28 | AO16: =AO15 -> 0.18385826 | AP16: =AP15 -> 0.81614174 | AQ16: =P39/(O39+P39+R39+S39) -> 0.0045984979 | AR16: =HLOOKUP(AQ$4,$O$24:$U$33,ROW(AR16)-10,FALSE) -> 1 | AS16: =AS15 -> 0.054196435 | AT16: =AT15 -> 0.94580357 | AU16: =S39/(O39+P39+R39+S39) -> 0.0045271937 | AV16: =HLOOKUP(AU$4,$O$24:$U$33,ROW(AV16)-10,FALSE) -> 0.6389 | AW16: =AW15 -> 0.0062730627 | AX16: =AX15 -> 0.99372694 | AY16: =R39/(O39+P39+R39+S39) -> 0.0022204856 | AZ16: =HLOOKUP(AY$4,$O$24:$U$33,ROW(AZ16)-10,FALSE) -> 1 | BA16: =BA15 -> 0 | BB16: =BB15 -> 1
A17: 2018 | B17: 40792 | C17: 1036146 | D17: 940137 | H17: 27190 | J17: 1 | L17: 2044266 | N17: 2045 | O17: 1 | P17: =HLOOKUP(O$4,$O$24:$U$33,ROW(P17)-10,FALSE) -> 0.27339725 | Q17: =Q16 -> 0.022647572 | R17: =R16 -> 0.97735243 | S17: =100% -> 1 | T17: =HLOOKUP(S$4,$O$24:$U$33,ROW(T17)-10,FALSE) -> 0.61094922 | U17: =U16 -> 0.0076204669 | V17: =V16 -> 0.99237953 | W17: =AA17+AE17 -> 1 | X17: =AB17*AA17+AF17*AE17 -> 0.85030307 | Y17: =(AA17*AB17*AC17+AE17*AF17*AG17)/(AA17*AB17+AE17*AF17) -> 0.016248565 | Z17: =(AA17*AB17*AD17+AE17*AF17*AH17)/(AA17*AB17+AE17*AF17) -> 0.95559936 | AA17: =S40/(R40+S40) -> 0.75490129 | AB17: =HLOOKUP(AA$4,$O$24:$U$33,ROW(AB17)-10,FALSE) -> 0.8017 | AC17: =AC16 -> 0.018581344 | AD17: =AD16 -> 0.98141866 | AE17: =R40/(R40+S40) -> 0.24509871 | AF17: =HLOOKUP(AE$4,$O$24:$U$33,ROW(AF17)-10,FALSE) -> 1 | AG17: =AG16 -> 0.010488406 | AH17: =AH16 -> 0.89184566 | AI17: =AM17+AQ17+AU17+AY17 -> 1 | AJ17: =(AM17*AN17+AQ17*AR17+AU17*AV17+AY17*AZ17) -> 0.40680742 | AK17: =(AM17*AN17*AO17+AQ17*AR17*AS17+AU17*AV17*AW17+AY17*AZ17*BA17)/(AM17*AN17+AQ17*AR17+AU17*AV17+AY17*AZ17) -> 0.17928344 | AL17: =(AM17*AN17*AP17+AQ17*AR17*AT17+AU17*AV17*AX17+AY17*AZ17*BB17)/(AM17*AN17+AQ17*AR17+AU17*AV17+AY17*AZ17) -> 0.82071656 | AM17: =O40/(O40+P40+R40+S40) -> 0.98689258 | AN17: =HLOOKUP(AM$4,$O$24:$U$33,ROW(AN17)-10,FALSE) -> 0.4 | AO17: =AO16 -> 0.18385826 | AP17: =AP16 -> 0.81614174 | AQ17: =P40/(O40+P40+R40+S40) -> 0.0060462861 | AR17: =HLOOKUP(AQ$4,$O$24:$U$33,ROW(AR17)-10,FALSE) -> 1 | AS17: =AS16 -> 0.054196435 | AT17: =AT16 -> 0.94580357 | AU17: =S40/(O40+P40+R40+S40) -> 0.0053304578 | AV17: =HLOOKUP(AU$4,$O$24:$U$33,ROW(AV17)-10,FALSE) -> 0.8017 | AW17: =AW16 -> 0.0062730627 | AX17: =AX16 -> 0.99372694 | AY17: =R40/(O40+P40+R40+S40) -> 0.0017306743 | AZ17: =HLOOKUP(AY$4,$O$24:$U$33,ROW(AZ17)-10,FALSE) -> 1 | BA17: =BA16 -> 0 | BB17: =BB16 -> 1
A18: 2019 | B18: 18134 | C18: 1052509 | D18: 1086406 | H18: 32818 | J18: 98 | L18: 2189965 | N18: 2050 | O18: 1 | P18: =HLOOKUP(O$4,$O$24:$U$33,ROW(P18)-10,FALSE) -> 0.38 | Q18: =Q17 -> 0.022647572 | R18: =R17 -> 0.97735243 | S18: =100% -> 1 | T18: =HLOOKUP(S$4,$O$24:$U$33,ROW(T18)-10,FALSE) -> 0.79601574 | U18: =U17 -> 0.0076204669 | V18: =V17 -> 0.99237953 | W18: =AA18+AE18 -> 1 | X18: =AB18*AA18+AF18*AE18 -> 1 | Y18: =(AA18*AB18*AC18+AE18*AF18*AG18)/(AA18*AB18+AE18*AF18) -> 0.016021876 | Z18: =(AA18*AB18*AD18+AE18*AF18*AH18)/(AA18*AB18+AE18*AF18) -> 0.95309035 | AA18: =S41/(R41+S41) -> 0.68374053 | AB18: =HLOOKUP(AA$4,$O$24:$U$33,ROW(AB18)-10,FALSE) -> 1 | AC18: =AC17 -> 0.018581344 | AD18: =AD17 -> 0.98141866 | AE18: =R41/(R41+S41) -> 0.31625947 | AF18: =HLOOKUP(AE$4,$O$24:$U$33,ROW(AF18)-10,FALSE) -> 1 | AG18: =AG17 -> 0.010488406 | AH18: =AH17 -> 0.89184566 | AI18: =AM18+AQ18+AU18+AY18 -> 1 | AJ18: =(AM18*AN18+AQ18*AR18+AU18*AV18+AY18*AZ18) -> 0.50634653 | AK18: =(AM18*AN18*AO18+AQ18*AR18*AS18+AU18*AV18*AW18+AY18*AZ18*BA18)/(AM18*AN18+AQ18*AR18+AU18*AV18+AY18*AZ18) -> 0.17986652 | AL18: =(AM18*AN18*AP18+AQ18*AR18*AT18+AU18*AV18*AX18+AY18*AZ18*BB18)/(AM18*AN18+AQ18*AR18+AU18*AV18+AY18*AZ18) -> 0.82013348 | AM18: =O41/(O41+P41+R41+S41) -> 0.98730694 | AN18: =HLOOKUP(AM$4,$O$24:$U$33,ROW(AN18)-10,FALSE) -> 0.5 | AO18: =AO17 -> 0.18385826 | AP18: =AP17 -> 0.81614174 | AQ18: =P41/(O41+P41+R41+S41) -> 0.0051710904 | AR18: =HLOOKUP(AQ$4,$O$24:$U$33,ROW(AR18)-10,FALSE) -> 1 | AS18: =AS17 -> 0.054196435 | AT18: =AT17 -> 0.94580357 | AU18: =S41/(O41+P41+R41+S41) -> 0.0051430736 | AV18: =HLOOKUP(AU$4,$O$24:$U$33,ROW(AV18)-10,FALSE) -> 1 | AW18: =AW17 -> 0.0062730627 | AX18: =AX17 -> 0.99372694 | AY18: =R41/(O41+P41+R41+S41) -> 0.0023788933 | AZ18: =HLOOKUP(AY$4,$O$24:$U$33,ROW(AZ18)-10,FALSE) -> 1 | BA18: =BA17 -> 0 | BB18: =BB17 -> 1
A19: 2020 | B19: 15349 | C19: 1319180 | D19: 1157774 | H19: 21626 | J19: 318 | L19: 2514247 | N19: 2055 | O19: 1 | P19: =HLOOKUP(O$4,$O$24:$U$33,ROW(P19)-10,FALSE) -> 0.48312408 | Q19: =Q18 -> 0.022647572 | R19: =R18 -> 0.97735243 | S19: =100% -> 1 | T19: =HLOOKUP(S$4,$O$24:$U$33,ROW(T19)-10,FALSE) -> 0.9 | U19: =U18 -> 0.0076204669 | V19: =V18 -> 0.99237953 | W19: =AA19+AE19 -> 1 | X19: =AB19*AA19+AF19*AE19 -> 1 | Y19: =(AA19*AB19*AC19+AE19*AF19*AG19)/(AA19*AB19+AE19*AF19) -> 0.016507815 | Z19: =(AA19*AB19*AD19+AE19*AF19*AH19)/(AA19*AB19+AE19*AF19) -> 0.95846874 | AA19: =S42/(R42+S42) -> 0.74378536 | AB19: =HLOOKUP(AA$4,$O$24:$U$33,ROW(AB19)-10,FALSE) -> 1 | AC19: =AC18 -> 0.018581344 | AD19: =AD18 -> 0.98141866 | AE19: =R42/(R42+S42) -> 0.25621464 | AF19: =HLOOKUP(AE$4,$O$24:$U$33,ROW(AF19)-10,FALSE) -> 1 | AG19: =AG18 -> 0.010488406 | AH19: =AH18 -> 0.89184566 | AI19: =AM19+AQ19+AU19+AY19 -> 1 | AJ19: =(AM19*AN19+AQ19*AR19+AU19*AV19+AY19*AZ19) -> 0.65423161 | AK19: =(AM19*AN19*AO19+AQ19*AR19*AS19+AU19*AV19*AW19+AY19*AZ19*BA19)/(AM19*AN19+AQ19*AR19+AU19*AV19+AY19*AZ19) -> 0.18092211 | AL19: =(AM19*AN19*AP19+AQ19*AR19*AT19+AU19*AV19*AX19+AY19*AZ19*BB19)/(AM19*AN19+AQ19*AR19+AU19*AV19+AY19*AZ19) -> 0.81907789 | AM19: =O42/(O42+P42+R42+S42) -> 0.98790968 | AN19: =HLOOKUP(AM$4,$O$24:$U$33,ROW(AN19)-10,FALSE) -> 0.65 | AO19: =AO18 -> 0.18385826 | AP19: =AP18 -> 0.81614174 | AQ19: =P42/(O42+P42+R42+S42) -> 0.0049579078 | AR19: =HLOOKUP(AQ$4,$O$24:$U$33,ROW(AR19)-10,FALSE) -> 1 | AS19: =AS18 -> 0.054196435 | AT19: =AT18 -> 0.94580357 | AU19: =S42/(O42+P42+R42+S42) -> 0.0053049805 | AV19: =HLOOKUP(AU$4,$O$24:$U$33,ROW(AV19)-10,FALSE) -> 1 | AW19: =AW18 -> 0.0062730627 | AX19: =AX18 -> 0.99372694 | AY19: =R42/(O42+P42+R42+S42) -> 0.0018274273 | AZ19: =HLOOKUP(AY$4,$O$24:$U$33,ROW(AZ19)-10,FALSE) -> 1 | BA19: =BA18 -> 0 | BB19: =BB18 -> 1
A20: 2021 | B20: 38485 | C20: 1211565 | D20: 1076644 | E20: 8 | F20: 3 | H20: 21916 | J20: 1250 | L20: 2349871 | N20: 2060 | O20: 1 | P20: =HLOOKUP(O$4,$O$24:$U$33,ROW(P20)-10,FALSE) -> 0.58094619 | Q20: =Q19 -> 0.022647572 | R20: =R19 -> 0.97735243 | S20: =100% -> 1 | T20: =HLOOKUP(S$4,$O$24:$U$33,ROW(T20)-10,FALSE) -> 1 | U20: =U19 -> 0.0076204669 | V20: =V19 -> 0.99237953 | W20: =AA20+AE20 -> 1 | X20: =AB20*AA20+AF20*AE20 -> 1 | Y20: =(AA20*AB20*AC20+AE20*AF20*AG20)/(AA20*AB20+AE20*AF20) -> 0.016051969 | Z20: =(AA20*AB20*AD20+AE20*AF20*AH20)/(AA20*AB20+AE20*AF20) -> 0.95342343 | AA20: =S43/(R43+S43) -> 0.68745907 | AB20: =HLOOKUP(AA$4,$O$24:$U$33,ROW(AB20)-10,FALSE) -> 1 | AC20: =AC19 -> 0.018581344 | AD20: =AD19 -> 0.98141866 | AE20: =R43/(R43+S43) -> 0.31254093 | AF20: =HLOOKUP(AE$4,$O$24:$U$33,ROW(AF20)-10,FALSE) -> 1 | AG20: =AG19 -> 0.010488406 | AH20: =AH19 -> 0.89184566 | AI20: =AM20+AQ20+AU20+AY20 -> 1 | AJ20: =(AM20*AN20+AQ20*AR20+AU20*AV20+AY20*AZ20) -> 0.80289881 | AK20: =(AM20*AN20*AO20+AQ20*AR20*AS20+AU20*AV20*AW20+AY20*AZ20*BA20)/(AM20*AN20+AQ20*AR20+AU20*AV20+AY20*AZ20) -> 0.18101569 | AL20: =(AM20*AN20*AP20+AQ20*AR20*AT20+AU20*AV20*AX20+AY20*AZ20*BB20)/(AM20*AN20+AQ20*AR20+AU20*AV20+AY20*AZ20) -> 0.81898431 | AM20: =O43/(O43+P43+R43+S43) -> 0.98550596 | AN20: =HLOOKUP(AM$4,$O$24:$U$33,ROW(AN20)-10,FALSE) -> 0.8 | AO20: =AO19 -> 0.18385826 | AP20: =AP19 -> 0.81614174 | AQ20: =P43/(O43+P43+R43+S43) -> 0.0064158482 | AR20: =HLOOKUP(AQ$4,$O$24:$U$33,ROW(AR20)-10,FALSE) -> 1 | AS20: =AS19 -> 0.054196435 | AT20: =AT19 -> 0.94580357 | AU20: =S43/(O43+P43+R43+S43) -> 0.0055534245 | AV20: =HLOOKUP(AU$4,$O$24:$U$33,ROW(AV20)-10,FALSE) -> 1 | AW20: =AW19 -> 0.0062730627 | AX20: =AX19 -> 0.99372694 | AY20: =R43/(O43+P43+R43+S43) -> 0.0025247648 | AZ20: =HLOOKUP(AY$4,$O$24:$U$33,ROW(AZ20)-10,FALSE) -> 1 | BA20: =BA19 -> 0 | BB20: =BB19 -> 1
A21: Passenger HDV | B21: 512915 | C21: 547268 | D21: 102586 | E21: 24163 | F21: 4155 | H21: 53334 | I21: 5 | J21: 51218 | K21: 38 | L21: 1295682
A22: 道路客车 | B22: 107325 | C22: 488708 | D22: 98628 | E22: 957 | F22: 936 | H22: 12740 | I22: 5 | J22: 2032 | K22: 38 | L22: 711369
A23: 2015 | B23: 41247 | C23: 87105 | D23: 14744 | E23: 414 | H23: 4888 | J23: 606 | K23: 38 | L23: 149042
A24: 2016 | B24: 30079 | C24: 104312 | D24: 19137 | E24: 528 | F24: 5 | H24: 2808 | J24: 870 | L24: 157739 | N24: Electric Ratio | O24: 乘用车 | P24: 出租车 | Q24: 轻型货车 | R24: 公交车 | S24: 道路客车 | T24: 专用重型货车 | U24: 中重型货车
A25: 2017 | B25: 18371 | C25: 78701 | D25: 16714 | E25: 4 | F25: 112 | H25: 1885 | J25: 466 | L25: 116253 | N25: 2020 | O25: 0.075 | P25: 0.8 | Q25: 0.0088393183 | R25: 0.8 | S25: 0.06 | T25: 0.026466098 | U25: 0.0013456519
A26: 2018 | B26: 6138 | C26: 69234 | D26: 12719 | E26: 11 | F26: 132 | H26: 1317 | I26: 5 | J26: 75 | L26: 89631 | N26: 2025 | O26: 0.1 | P26: 0.91 | Q26: 0.089203147 | R26: 0.91 | S26: 0.1516 | T26: 0.050728989 | U26: 0.026420039
A27: 2019 | B27: 4108 | C27: 68141 | D27: 15158 | F27: 436 | H27: 939 | J27: 4 | L27: 88786 | N27: 2030 | O27: 0.15 | P27: 0.97 | Q27: 0.18086855 | R27: 0.97 | S27: 0.30410161 | T27: 0.086030248 | U27: 0.059427603
A28: 2020 | B28: 2452 | C28: 34949 | D28: 7877 | F28: 12 | H28: 484 | J28: 9 | L28: 45783 | N28: 2035 | O28: 0.2 | P28: 1 | Q28: 0.29922705 | R28: 1 | S28: 0.4792 | T28: 0.13804053 | U28: 0.10442111
A29: 2021 | B29: 4930 | C29: 46266 | D29: 12279 | F29: 239 | H29: 419 | J29: 2 | L29: 64135 | N29: 2040 | O29: 0.28 | P29: 1 | Q29: 0.45018795 | R29: 1 | S29: 0.6389 | T29: 0.20773315 | U29: 0.17782076
A30: 公交车 | B30: 405590 | C30: 58560 | D30: 3958 | E30: 23206 | F30: 3219 | H30: 40594 | J30: 49186 | L30: 584313 | N30: 2045 | O30: 0.4 | P30: 1 | Q30: 0.61094922 | R30: 1 | S30: 0.8017 | T30: 0.30051292 | U30: 0.27339725
A31: 2015 | B31: 44691 | C31: 36071 | D31: 3505 | E31: 7940 | H31: 20709 | J31: 16295 | L31: 129211 | N31: 2050 | O31: 0.5 | P31: 1 | Q31: 0.79601574 | R31: 1 | S31: 1 | T31: 0.55 | U31: 0.38
A32: 2016 | B32: 60979 | C32: 9481 | D32: 44 | E32: 12742 | F32: 24 | H32: 8790 | J32: 4474 | L32: 96534 | N32: 2055 | O32: 0.65 | P32: 1 | Q32: 0.9 | R32: 1 | S32: 1 | T32: 0.65 | U32: 0.48312408
A33: 2017 | B33: 58195 | C33: 6606 | D33: 93 | E33: 2291 | F33: 3 | H33: 6896 | J33: 12095 | L33: 86179 | N33: 2060 | O33: 0.8 | P33: 1 | Q33: 1 | R33: 1 | S33: 1 | T33: 0.8 | U33: 0.58094619
A34: 2018 | B34: 79789 | C34: 3208 | D34: 35 | E34: 228 | F34: 305 | H34: 2515 | J34: 5764 | L34: 91844
A35: 2019 | B35: 68135 | C35: 1879 | D35: 147 | E35: 3 | F35: 740 | H35: 1143 | J35: 4294 | L35: 76341 | N35: Vehicle Sales (10^4 units) | O35: 乘用车 | P35: 出租车 | Q35: 轻型货车 | R35: 公交车 | S35: 道路客车 | T35: 专用重型货车 | U35: 中重型货车
A36: 2020 | B36: 52693 | C36: 792 | D36: 72 | F36: 1339 | H36: 431 | J36: 5040 | L36: 60367 | N36: 2025 | O36: 3082.6339 | P36: 17.962537 | Q36: 335.59623 | R36: 5.0369104 | S36: 15.189023 | T36: 8.7615081 | U36: 71.220316
A37: 2021 | B37: 41108 | C37: 523 | D37: 62 | E37: 2 | F37: 808 | H37: 110 | J37: 1224 | L37: 43837 | N37: 2030 | O37: 3068.9825 | P37: 15.294893 | Q37: 453.21817 | R37: 6.8771505 | S37: 14.038266 | T37: 12.515839 | U37: 103.8069
A38: Passenger LDV | B38: 5711717 | C38: 1203924 | D38: 144403802 | E38: 2485070 | F38: 77 | G38: 10354 | H38: 2028005 | I38: 26020 | J38: 1106569 | L38: 156975538 | N38: 2035 | O38: 3138.68 | P38: 15.001153 | Q38: 525.29932 | R38: 5.1194346 | S38: 16.852345 | T38: 13.781221 | U38: 85.065555
A39: 乘用车 | B39: 4640373 | C39: 1082981 | D39: 142926417 | E39: 2386515 | F39: 9 | G39: 705 | H39: 1416706 | I39: 867 | J39: 1045371 | L39: 153499944 | N39: 2040 | O39: 3094.8208 | P39: 14.394853 | Q39: 620.49784 | R39: 6.9508708 | S39: 14.171647 | T39: 16.929402 | U39: 101.63246
A40: 2015 | B40: 116252 | C40: 162140 | D40: 19122611 | E40: 64210 | H40: 1310439 | I40: 19 | J40: 10033 | L40: 20785704 | N40: 2045 | O40: 2957.5436 | P40: 18.119657 | Q40: 725.55273 | R40: 5.1865268 | S40: 15.974445 | T40: 19.117453 | U40: 94.067238
A41: 2016 | B41: 213806 | C41: 135244 | D41: 23861857 | E41: 154515 | G41: 27 | H41: 24197 | I41: 8 | J41: 21920 | L41: 24411574 | N41: 2050 | O41: 2910.573 | P41: 15.244333 | Q41: 826.10225 | R41: 7.0129584 | S41: 15.16174 | T41: 22.199015 | U41: 102.45345
A42: 2017 | B42: 430923 | C42: 140143 | D42: 23360361 | E42: 207862 | G42: 165 | H42: 23568 | I42: 420 | J42: 54561 | L42: 24218003 | N42: 2055 | O42: 2835.3761 | P42: 14.229573 | Q42: 944.58374 | R42: 5.2448557 | S42: 15.225698 | T42: 25.048221 | U42: 100.05856
A43: 2018 | B43: 575327 | C43: 164883 | D43: 20902419 | E43: 285928 | G43: 512 | H43: 40262 | I43: 215 | J43: 177497 | L43: 22147043 | N43: 2060 | O43: 2759.1343 | P43: 17.962537 | Q43: 1067.2723 | R43: 7.0686179 | S43: 15.547997 | T43: 28.425986 | U43: 104.6604
A44: 2019 | B44: 485080 | C44: 138471 | D44: 20030934 | E44: 350626 | G44: 1 | H44: 11264 | I44: 32 | J44: 183559 | L44: 21199967
A45: 2020 | B45: 766699 | C45: 166742 | D45: 18234329 | E45: 539014 | H45: 2806 | I45: 145 | J45: 195072 | L45: 19904807
A46: 2021 | B46: 2052286 | C46: 175358 | D46: 17413906 | E46: 784360 | F46: 9 | H46: 4170 | I46: 28 | J46: 402729 | L46: 20832846
A47: 出租车 | B47: 1067694 | C47: 95487 | D47: 1387504 | E47: 98553 | F47: 68 | G47: 9649 | H47: 608726 | I47: 25153 | J47: 61181 | L47: 3354015
A48: 2015 | B48: 19377 | C48: 811 | D48: 158637 | E48: 5234 | H48: 184235 | I48: 559 | J48: 2629 | L48: 371482
A49: 2016 | B49: 32323 | C49: 18655 | D49: 190027 | E49: 3257 | F49: 8 | G49: 1695 | H49: 86487 | I49: 197 | J49: 2785 | L49: 335434
A50: 2017 | B50: 77175 | C50: 18448 | D50: 341239 | E50: 14442 | F50: 50 | G50: 5122 | H50: 75940 | I50: 1889 | J50: 4329 | L50: 538634
A51: 2018 | B51: 168974 | C51: 18771 | D51: 239703 | E51: 22793 | G51: 2630 | H51: 86839 | I51: 1627 | J51: 10304 | L51: 551641
A52: 2019 | B52: 239398 | C52: 16407 | D52: 231239 | E52: 26279 | G52: 202 | H52: 95729 | I52: 14529 | J52: 16904 | L52: 640687
A53: 2020 | B53: 171260 | C53: 13305 | D53: 127036 | E53: 13174 | H53: 38951 | I53: 5543 | J53: 12718 | L53: 381987
A54: 2021 | B54: 359187 | C54: 9090 | D54: 99623 | E54: 13374 | F54: 10 | H54: 40545 | I54: 809 | J54: 11512 | L54: 534150
A55: 道路客车 | B55: 2693 | C55: 24423 | D55: 87105 | E55: 2 | H55: 1699 | J55: 17 | L55: 115939
A56: 2015 | B56: 3 | C56: 405 | D56: 9392 | H56: 929 | L56: 10729
A57: 2016 | B57: 14 | C57: 785 | D57: 6645 | H57: 50 | L57: 7494
A58: 2017 | B58: 620 | C58: 2172 | D58: 23147 | H58: 98 | L58: 26037
A59: 2018 | B59: 60 | C59: 4246 | D59: 19272 | H59: 127 | L59: 23705
A60: 2019 | B60: 104 | C60: 3024 | D60: 10162 | H60: 49 | J60: 12 | L60: 13351
A61: 2020 | B61: 479 | C61: 7043 | D61: 11349 | E61: 1 | H61: 37 | L61: 18909
A62: 2021 | B62: 1413 | C62: 6748 | D62: 7138 | E62: 1 | H62: 409 | J62: 5 | L62: 15714
A63: 公交车 | B63: 957 | C63: 1033 | D63: 2776 | H63: 874 | L63: 5640
A64: 2015 | B64: 150 | C64: 11 | D64: 434 | H64: 86 | L64: 681
A65: 2016 | C65: 17 | D65: 265 | H65: 93 | L65: 375
A66: 2017 | B66: 30 | C66: 79 | D66: 883 | H66: 267 | L66: 1259
A67: 2018 | B67: 13 | C67: 591 | D67: 338 | H67: 175 | L67: 1117
A68: 2019 | B68: 44 | C68: 5 | D68: 297 | H68: 169 | L68: 515
A69: 2020 | B69: 648 | C69: 314 | D69: 430 | H69: 84 | L69: 1476
A70: 2021 | B70: 72 | C70: 16 | D70: 129 | L70: 217
A71: Unknown | B71: 2797 | C71: 304 | D71: 174306 | E71: 22970 | H71: 138 | J71: 6003 | L71: 206518
A72: 乘用车 | B72: 2796 | C72: 71 | D72: 166821 | E72: 22970 | J72: 6002 | L72: 198660
A73: 2021 | B73: 2796 | C73: 71 | D73: 166821 | E73: 22970 | J73: 6002 | L73: 198660
A74: 出租车 | B74: 1 | C74: 1 | D74: 61 | J74: 1 | L74: 64
A75: 2021 | B75: 1 | C75: 1 | D75: 61 | J75: 1 | L75: 64
A76: 道路客车 | C76: 232 | D76: 7424 | H76: 138 | L76: 7794
A77: 2015 | C77: 232 | D77: 7424 | H77: 138 | L77: 7794
A78: 总计 | B78: 6494402 | C78: 16591966 | D78: 151243506 | E78: 2532321 | F78: 8557 | G78: 10354 | H78: 2742311 | I78: 26142 | J78: 1166613 | K78: 42 | L78: 180816214

Sheet Hydrogen
B1: 《节能与新能源汽车技术路线图2.0》
B2: 2020 | C2: 燃料电池混合动力技术成熟，商用车市场启动，保有量达到1万辆规模 | K2: Average Vehicle Lifetime | O2: Average Vehicle Lifetime
B3: 2025 | C3: 将基于现有储运加注技术，各城市因地制宜，经济辐射半径150KM，运行车辆5万~10万辆 | K3: Passenger | L3: Freight | O3: Passenger | P3: Freight
C4: 以城市物流用车，公共服务用车的批量应用为主+大型SUV应用 | J4: LDV | K4: 9 | L4: 15 | N4: LDV | O4: 9 | P4: 15
B5: 2035 | C5: 突破新一代储运技术，突破加氢站数量瓶颈，城市间联网跨域运行，保有量100万辆左右 | J5: HDV | K5: 15 | L5: 15 | N5: HDV | O5: 15 | P5: 15
C6: 以燃料电池商用车为主体
C8: 公交车 | E8: 道路客车 | G8: Passenger HDV | O8: 乘用车 | Q8: 出租车 | S8: Passenger LDV | AA8: 专用重货 | AC8: 普通重货 | AE8: Freight HDV
C9: 保有量 | D9: 销量 | E9: 保有量 | F9: 销量 | G9: Ownership | H9: Sales | I9: Target | J9: Proposed Sale | K9: Ownership | L9: Sales % | M9: Smoothed Sale % | O9: 保有量 | P9: 销量 | Q9: 保有量 | R9: 销量 | S9: Ownership | T9: Sales | U9: Target | V9: Proposed Sale | W9: Ownership | X9: Sales % | Y9: Smoothed Sale % | AA9: 保有量 | AB9: 销量 | AC9: 保有量 | AD9: 销量 | AE9: Ownership | AF9: Sales | AG9: Target | AH9: Proposed Sale | AI9: Ownership | AJ9: Sales % | AK9: Smoothed Sale %
B10: 2015 | C10: 482975 | D10: ='Electric Ratio'!L64+'Electric Ratio'!L31 -> 129892 | E10: 1814325 | F10: ='Electric Ratio'!L23+'Electric Ratio'!L56 -> 159771 | G10: =C10+E10 -> 2297300 | H10: =D10+F10 -> 289663 | I10: 0 | J10: ='Pivot Table'!F20 -> 0 | K10: =I10 -> 0 | L10: =J10/H10 -> 0 | M10: =MAX(L$10:L$16) -> 0.0065700893 | O10: 13323.621 | P10: 1547.1217 | Q10: 109.2083 | R10: 18.300217 | S10: =(O10+Q10)*10000 -> 1.343283e+08 | T10: =(P10+R10)*10000 -> 15654220 | U10: 0 | V10: ='Pivot Table'!F28 -> 0 | W10: =U10 -> 0 | X10: =V10/T10 -> 0 | Y10: =MAX(X$10:X$16) -> 1.6989392e-06 | AA10: 475244 | AB10: 9344.1371 | AC10: 6313956 | AD10: 124143.54 | AE10: =(AA10+AC10) -> 6789200 | AF10: =(AB10+AD10) -> 133487.67 | AG10: 0 | AH10: ='Pivot Table'!F4 -> 0 | AI10: =AG10 -> 0 | AJ10: =AH10/AF10 -> 0 | AK10: =MAX(AJ$10:AJ$16) -> 0.0014854603
B11: 2016 | C11: 515051 | D11: ='Electric Ratio'!L65+'Electric Ratio'!L32 -> 96909 | E11: 1783449 | F11: ='Electric Ratio'!L24+'Electric Ratio'!L57 -> 165233 | G11: =C11+E11 -> 2298500 | H11: =D11+F11 -> 262142 | I11: =I10+J11 -> 29 | J11: ='Pivot Table'!F21 -> 29 | K11: =I11 -> 29 | L11: =J11/H11 -> 0.00011062706 | M11: =MAX(L$10:L$16) -> 0.0065700893 | O11: 15064.57 | P11: 1978.1601 | Q11: 110.2563 | R11: 16.941017 | S11: =(O11+Q11)*10000 -> 1.5174826e+08 | T11: =(P11+R11)*10000 -> 19951011 | U11: =U10+V11 -> 8 | V11: ='Pivot Table'!F29 -> 8 | W11: =U11 -> 8 | X11: =V11/T11 -> 4.0098218e-07 | Y11: =MAX(X$10:X$16) -> 1.6989392e-06 | AA11: 495719 | AB11: 65487.762 | AC11: 6585981 | AD11: 870051.7 | AE11: =(AA11+AC11) -> 7081700 | AF11: =(AB11+AD11) -> 935539.46 | AG11: =AG10+AH11 -> 0 | AH11: ='Pivot Table'!F5 -> 0 | AI11: =AG11 -> 0 | AJ11: =AH11/AF11 -> 0 | AK11: =MAX(AJ$10:AJ$16) -> 0.0014854603
B12: 2017 | C12: 554820 | D12: ='Electric Ratio'!L66+'Electric Ratio'!L33 -> 87438 | E12: 1764080 | F12: ='Electric Ratio'!L25+'Electric Ratio'!L58 -> 142290 | G12: =C12+E12 -> 2318900 | H12: =D12+F12 -> 229728 | I12: =I11+J12 -> 144 | J12: ='Pivot Table'!F22 -> 115 | K12: =I12 -> 144 | L12: =J12/H12 -> 0.000500592 | M12: =MAX(L$10:L$16) -> 0.0065700893 | O12: 17685.569 | P12: 2925.9286 | Q12: 110.2823 | R12: 17.084317 | S12: =(O12+Q12)*10000 -> 1.7795851e+08 | T12: =(P12+R12)*10000 -> 29430129 | U12: =U11+V12 -> 58 | V12: ='Pivot Table'!F30 -> 50 | W12: =U12 -> 58 | X12: =V12/T12 -> 1.6989392e-06 | Y12: =MAX(X$10:X$16) -> 1.6989392e-06 | AA12: 536263 | AB12: 92020.411 | AC12: 7124637 | AD12: 1222556.9 | AE12: =(AA12+AC12) -> 7660900 | AF12: =(AB12+AD12) -> 1314577.3 | AG12: =AG11+AH12 -> 933 | AH12: ='Pivot Table'!F6 -> 933 | AI12: =AG12 -> 933 | AJ12: =AH12/AF12 -> 0.00070973384 | AK12: =MAX(AJ$10:AJ$16) -> 0.0014854603
B13: 2018 | C13: 565933 | D13: ='Electric Ratio'!L67+'Electric Ratio'!L34 -> 92961 | E13: 1771367 | F13: ='Electric Ratio'!L26+'Electric Ratio'!L59 -> 113336 | G13: =C13+E13 -> 2337300 | H13: =D13+F13 -> 206297 | I13: =I12+J13 -> 581 | J13: ='Pivot Table'!F23 -> 437 | K13: =I13 -> 581 | L13: =J13/H13 -> 0.0021183052 | M13: =MAX(L$10:L$16) -> 0.0065700893 | O13: 20306.556 | P13: 3016.2556 | Q13: 109.7237 | R13: 16.688217 | S13: =(O13+Q13)*10000 -> 2.0416279e+08 | T13: =(P13+R13)*10000 -> 30329438 | U13: =U12+V13 -> 58 | V13: ='Pivot Table'!F31 -> 0 | W13: =U13 -> 58 | X13: =V13/T13 -> 0 | Y13: =MAX(X$10:X$16) -> 1.6989392e-06 | AA13: 583744 | AB13: 105952.53 | AC13: 7755456 | AD13: 1407655.1 | AE13: =(AA13+AC13) -> 8339200 | AF13: =(AB13+AD13) -> 1513607.6 | AG13: =AG12+AH13 -> 1337 | AH13: ='Pivot Table'!F7 -> 404 | AI13: =AG13 -> 1337 | AJ13: =AH13/AF13 -> 0.00026691198 | AK13: =MAX(AJ$10:AJ$16) -> 0.0014854603
B14: 2019 | C14: 584026 | D14: ='Electric Ratio'!L68+'Electric Ratio'!L35 -> 76856 | E14: 1742574 | F14: ='Electric Ratio'!L27+'Electric Ratio'!L60 -> 102137 | G14: =C14+E14 -> 2326600 | H14: =D14+F14 -> 178993 | I14: =I13+J14 -> 1757 | J14: ='Pivot Table'!F24 -> 1176 | K14: =I14 -> 1757 | L14: =J14/H14 -> 0.0065700893 | M14: =MAX(L$10:L$16) -> 0.0065700893 | O14: 22244.815 | P14: 2447.2817 | Q14: 110.247 | R14: 2.9605 | S14: =(O14+Q14)*10000 -> 2.2355062e+08 | T14: =(P14+R14)*10000 -> 24502422 | U14: =U13+V14 -> 58 | V14: ='Pivot Table'!F32 -> 0 | W14: =U14 -> 58 | X14: =V14/T14 -> 0 | Y14: =MAX(X$10:X$16) -> 1.6989392e-06 | AA14: 614579 | AB14: 94906.606 | AC14: 8165121 | AD14: 1260902.1 | AE14: =(AA14+AC14) -> 8779700 | AF14: =(AB14+AD14) -> 1355808.7 | AG14: =AG13+AH14 -> 3351 | AH14: ='Pivot Table'!F8 -> 2014 | AI14: =AG14 -> 3351 | AJ14: =AH14/AF14 -> 0.0014854603 | AK14: =MAX(AJ$10:AJ$16) -> 0.0014854603
B15: 2020 | C15: 585426.39 | D15: ='Electric Ratio'!L69+'Electric Ratio'!L36 -> 61843 | E15: 1742574 | F15: 205319.57 | G15: =C15+E15 -> 2328000.4 | H15: =D15+F15 -> 267162.57 | I15: =I14+J15 -> 3108 | J15: ='Pivot Table'!F25 -> 1351 | K15: =I15 -> 3108 | L15: =J15/H15 -> 0.0050568461 | M15: =MAX(L$10:L$16) -> 0.0065700893 | O15: 24835.923 | P15: 3235.5851 | Q15: 110.247 | R15: 17.473817 | S15: =(O15+Q15)*10000 -> 2.494617e+08 | T15: =(P15+R15)*10000 -> 32530589 | U15: =U14+V15 -> 58 | V15: ='Pivot Table'!F33 -> 0 | W15: =U15 -> 58 | X15: =V15/T15 -> 0 | Y15: =MAX(X$10:X$16) -> 1.6989392e-06 | AA15: 655841.19 | AB15: 105941.47 | AC15: 8243435 | AD15: 937624.34 | AE15: =(AA15+AC15) -> 8899276.1 | AF15: =(AB15+AD15) -> 1043565.8 | AG15: =AG14+AH15 -> 3497 | AH15: ='Pivot Table'!F9 -> 146 | AI15: =AG15 -> 3497 | AJ15: =AH15/AF15 -> 0.00013990493 | AK15: =MAX(AJ$10:AJ$16) -> 0.0014854603
B16: 2021 | C16: 586619.74 | D16: ='Electric Ratio'!L70+'Electric Ratio'!L37 -> 44054 | E16: 1742574 | F16: 188975.78 | G16: =C16+E16 -> 2329193.7 | H16: =D16+F16 -> 233029.78 | I16: =I15+J16 -> 4155 | J16: ='Pivot Table'!F26 -> 1047 | K16: =I16 -> 4155 | L16: =J16/H16 -> 0.004492988 | M16: =MAX(L$10:L$16) -> 0.0065700893 | O16: 27041.873 | P16: 3003.3143 | Q16: 110.247 | R16: 20.798917 | S16: =(O16+Q16)*10000 -> 2.715212e+08 | T16: =(P16+R16)*10000 -> 30241132 | U16: =U15+V16 -> 77 | V16: ='Pivot Table'!F34 -> 19 | W16: =U16 -> 77 | X16: =V16/T16 -> 6.2828336e-07 | Y16: =MAX(X$10:X$16) -> 1.6989392e-06 | AA16: 693274.02 | AB16: 96003.921 | AC16: 8310649.6 | AD16: 845372.22 | AE16: =(AA16+AC16) -> 9003923.7 | AF16: =(AB16+AD16) -> 941376.15 | AG16: =AG15+AH16 -> 4322 | AH16: ='Pivot Table'!F10 -> 825 | AI16: =AG16 -> 4322 | AJ16: =AH16/AF16 -> 0.00087637657 | AK16: =MAX(AJ$10:AJ$16) -> 0.0014854603
B17: 2022 | C17: 587768.76 | D17: 52462.015 | E17: 1742574 | F17: 169965.17 | G17: =C17+E17 -> 2330342.8 | H17: =D17+F17 -> 222427.18 | J17: =2*2429.785*B17-9812843 -> 13207.54 | K17: =SUM(J3:J17) -> 17362.54 | L17: =J17/H17 -> 0.059379164 | M17: =B17*0.02244905-45.32156 -> 0.0704191 | O17: 29146.604 | P17: 3066.266 | Q17: 110.247 | R17: 18.300217 | S17: =(O17+Q17)*10000 -> 2.9256851e+08 | T17: =(P17+R17)*10000 -> 30845662 | V17: =2*1741.681*B17-7041279 -> 2078.964 | W17: =SUM(V9:V17) -> 2155.964 | X17: =V17/T17 -> 6.7398911e-05 | Y17: =B17*0.0001262923-0.2554258 -> -6.27694e-05 | AA17: 731295.76 | AB17: 87114.677 | AC17: 8375762.1 | AD17: 717291.05 | AE17: =(AA17+AC17) -> 9107057.8 | AF17: =(AB17+AD17) -> 804405.73 | AH17: =2*310.1729*B17-1251279 -> 3060.2076 | AI17: =SUM(AH3:AH17) -> 7382.2076 | AJ17: =AH17/AF17 -> 0.0038043086 | AK17: =B17*0.000423519-0.851899 -> 0.004456418
B18: 2023 | C18: 588877.95 | D18: 62851.198 | E18: 1742574 | F18: 150118.52 | G18: =C18+E18 -> 2331452 | H18: =D18+F18 -> 212969.72 | J18: =2*2429.785*B18-9812843 -> 18067.11 | K18: =SUM(J4:J18) -> 35429.65 | L18: =J18/H18 -> 0.084834173 | M18: =B18*0.02244905-45.32156 -> 0.09286815 | O18: 31123.529 | P18: 3107.2305 | Q18: 110.247 | R18: 16.941017 | S18: =(O18+Q18)*10000 -> 3.1233776e+08 | T18: =(P18+R18)*10000 -> 31241715 | V18: =2*1741.681*B18-7041279 -> 5562.326 | W18: =SUM(V10:V18) -> 7718.29 | X18: =V18/T18 -> 0.00017804163 | Y18: =B18*0.0001262923-0.2554258 -> 6.35229e-05 | AA18: 769937.24 | AB18: 81308.73 | AC18: 8438986.8 | AD18: 629554.46 | AE18: =(AA18+AC18) -> 9208924 | AF18: =(AB18+AD18) -> 710863.19 | AH18: =2*310.1729*B18-1251279 -> 3680.5534 | AI18: =SUM(AH4:AH18) -> 11062.761 | AJ18: =AH18/AF18 -> 0.0051775833 | AK18: =B18*0.000423519-0.851899 -> 0.004879937
B19: 2024 | C19: 589943.94 | D19: 47964.982 | E19: 1742574 | F19: 131676.95 | G19: =C19+E19 -> 2332517.9 | H19: =D19+F19 -> 179641.93 | J19: =2*2429.785*B19-9812843 -> 22926.68 | K19: =SUM(J5:J19) -> 58356.33 | L19: =J19/H19 -> 0.12762433 | M19: =B19*0.02244905-45.32156 -> 0.1153172 | O19: 32940.487 | P19: 3114.8997 | Q19: 110.247 | R19: 17.084317 | S19: =(O19+Q19)*10000 -> 3.3050734e+08 | T19: =(P19+R19)*10000 -> 31319840 | V19: =2*1741.681*B19-7041279 -> 9045.688 | W19: =SUM(V11:V19) -> 16763.978 | X19: =V19/T19 -> 0.00028881654 | Y19: =B19*0.0001262923-0.2554258 -> 0.0001898152 | AA19: 808961.79 | AB19: 82521.908 | AC19: 8500091.5 | AD19: 636360.19 | AE19: =(AA19+AC19) -> 9309053.3 | AF19: =(AB19+AD19) -> 718882.1 | AH19: =2*310.1729*B19-1251279 -> 4300.8992 | AI19: =SUM(AH5:AH19) -> 15363.66 | AJ19: =AH19/AF19 -> 0.0059827602 | AK19: =B19*0.000423519-0.851899 -> 0.005303456
B20: 2025 | C20: 590980.91 | D20: 25056.971 | E20: 1742574 | F20: 118714.73 | G20: =C20+E20 -> 2333554.9 | H20: =D20+F20 -> 143771.71 | I20: 80000 | J20: =2*2429.785*B20-9812843 -> 27786.25 | K20: =SUM(J6:J20) -> 86142.58 | L20: =J20/H20 -> 0.19326647 | M20: =B20*0.02244905-45.32156 -> 0.13776625 | O20: 34601.131 | P20: 3121.459 | Q20: 110.247 | R20: 16.688217 | S20: =(O20+Q20)*10000 -> 3.4711378e+08 | T20: =(P20+R20)*10000 -> 31381472 | U20: 20000 | V20: =2*1741.681*B20-7041279 -> 12529.05 | W20: =SUM(V12:V20) -> 29285.028 | X20: =V20/T20 -> 0.00039924991 | Y20: =B20*0.0001262923-0.2554258 -> 0.0003161075 | AA20: 848776.36 | AB20: 91126.169 | AC20: 8559855.5 | AD20: 732437.87 | AE20: =(AA20+AC20) -> 9408631.9 | AF20: =(AB20+AD20) -> 823564.04 | AG20: 20000 | AH20: =2*310.1729*B20-1251279 -> 4921.245 | AI20: =SUM(AH6:AH20) -> 20284.905 | AJ20: =AH20/AF20 -> 0.0059755462 | AK20: =B20*0.000423519-0.851899 -> 0.005726975
B21: 2026 | C21: 591982.52 | D21: 69505.613 | E21: 1742574 | F21: 115428.99 | G21: =C21+E21 -> 2334556.5 | H21: =D21+F21 -> 184934.6 | J21: =2*2429.785*B21-9812843 -> 32645.82 | K21: =SUM(J7:J21) -> 118788.4 | L21: =J21/H21 -> 0.17652629 | M21: =B21*0.02244905-45.32156 -> 0.1602153 | O21: 36083.427 | P21: 3100.2857 | Q21: 110.247 | R21: 2.9605 | S21: =(O21+Q21)*10000 -> 3.6193674e+08 | T21: =(P21+R21)*10000 -> 31032462 | V21: =2*1741.681*B21-7041279 -> 16012.412 | W21: =SUM(V13:V21) -> 45247.44 | X21: =V21/T21 -> 0.0005159891 | Y21: =B21*0.0001262923-0.2554258 -> 0.0004423998 | AA21: 889055.27 | AB21: 103735.74 | AC21: 8617885.6 | AD21: 876665.9 | AE21: =(AA21+AC21) -> 9506940.8 | AF21: =(AB21+AD21) -> 980401.63 | AH21: =2*310.1729*B21-1251279 -> 5541.5908 | AI21: =SUM(AH7:AH21) -> 25826.496 | AJ21: =AH21/AF21 -> 0.005652368 | AK21: =B21*0.000423519-0.851899 -> 0.006150494
B22: 2027 | C22: 592952.37 | D22: 106963.85 | E22: 1742574 | F22: 122950.84 | G22: =C22+E22 -> 2335526.4 | H22: =D22+F22 -> 229914.7 | J22: =2*2429.785*B22-9812843 -> 37505.39 | K22: =SUM(J8:J22) -> 156293.79 | L22: =J22/H22 -> 0.16312741 | M22: =B22*0.02244905-45.32156 -> 0.18266435 | O22: 37387.914 | P22: 3075.8228 | Q22: 110.247 | R22: 17.473817 | S22: =(O22+Q22)*10000 -> 3.7498161e+08 | T22: =(P22+R22)*10000 -> 30932966 | V22: =2*1741.681*B22-7041279 -> 19495.774 | W22: =SUM(V14:V22) -> 64743.214 | X22: =V22/T22 -> 0.0006302588 | Y22: =B22*0.0001262923-0.2554258 -> 0.0005686921 | AA22: 929838.78 | AB22: 117708.52 | AC22: 8674360.9 | AD22: 1023057.9 | AE22: =(AA22+AC22) -> 9604199.6 | AF22: =(AB22+AD22) -> 1140766.4 | AH22: =2*310.1729*B22-1251279 -> 6161.9366 | AI22: =SUM(AH8:AH22) -> 31988.433 | AJ22: =AH22/AF22 -> 0.005401576 | AK22: =B22*0.000423519-0.851899 -> 0.006574013
B23: 2028 | C23: 593897.08 | D23: 69408.703 | E23: 1742574 | F23: 138142.31 | G23: =C23+E23 -> 2336471.1 | H23: =D23+F23 -> 207551.01 | J23: =2*2429.785*B23-9812843 -> 42364.96 | K23: =SUM(J9:J23) -> 198658.75 | L23: =J23/H23 -> 0.20411831 | M23: =B23*0.02244905-45.32156 -> 0.2051134 | O23: 38522.942 | P23: 3060.006 | Q23: 110.247 | R23: 20.798917 | S23: =(O23+Q23)*10000 -> 3.8633189e+08 | T23: =(P23+R23)*10000 -> 30808050 | V23: =2*1741.681*B23-7041279 -> 22979.136 | W23: =SUM(V15:V23) -> 87722.35 | X23: =V23/T23 -> 0.00074588091 | Y23: =B23*0.0001262923-0.2554258 -> 0.0006949844 | AA23: 971318.99 | AB23: 129712.97 | AC23: 8729641.5 | AD23: 1118978.4 | AE23: =(AA23+AC23) -> 9700960.5 | AF23: =(AB23+AD23) -> 1248691.4 | AH23: =2*310.1729*B23-1251279 -> 6782.2824 | AI23: =SUM(AH9:AH23) -> 38770.715 | AJ23: =AH23/AF23 -> 0.005431512 | AK23: =B23*0.000423519-0.851899 -> 0.006997532
B24: 2029 | C24: 594811.92 | D24: 51424.848 | E24: 1742574 | F24: 155503.92 | G24: =C24+E24 -> 2337385.9 | H24: =D24+F24 -> 206928.77 | J24: =2*2429.785*B24-9812843 -> 47224.53 | K24: =SUM(J10:J24) -> 245883.28 | L24: =J24/H24 -> 0.22821635 | M24: =B24*0.02244905-45.32156 -> 0.22756245 | O24: 39488.316 | P24: 3048.9214 | Q24: 110.247 | R24: 18.300217 | S24: =(O24+Q24)*10000 -> 3.9598563e+08 | T24: =(P24+R24)*10000 -> 30672216 | V24: =2*1741.681*B24-7041279 -> 26462.498 | W24: =SUM(V16:V24) -> 114184.85 | X24: =V24/T24 -> 0.00086275143 | Y24: =B24*0.0001262923-0.2554258 -> 0.0008212767 | AA24: 1013213.5 | AB24: 136402.27 | AC24: 8783430.5 | AD24: 1123952.9 | AE24: =(AA24+AC24) -> 9796644.1 | AF24: =(AB24+AD24) -> 1260355.2 | AH24: =2*310.1729*B24-1251279 -> 7402.6282 | AI24: =SUM(AH10:AH24) -> 46173.343 | AJ24: =AH24/AF24 -> 0.0058734461 | AK24: =B24*0.000423519-0.851899 -> 0.007421051
B25: 2030 | C25: 595703.04 | D25: 46554.508 | E25: 1742574 | F25: 169887.22 | G25: =C25+E25 -> 2338277 | H25: =D25+F25 -> 216441.73 | J25: =2*2429.785*B25-9812843 -> 52084.1 | K25: =SUM(J11:J25) -> 297967.38 | L25: =J25/H25 -> 0.24063798 | M25: =B25*0.02244905-45.32156 -> 0.2500115 | O25: 40299.012 | P25: 3059.8766 | Q25: 110.247 | R25: 16.941017 | S25: =(O25+Q25)*10000 -> 4.0409259e+08 | T25: =(P25+R25)*10000 -> 30768176 | V25: =2*1741.681*B25-7041279 -> 29945.86 | W25: =SUM(V17:V25) -> 144111.71 | X25: =V25/T25 -> 0.0009732738 | Y25: =B25*0.0001262923-0.2554258 -> 0.000947569 | AA25: 1055716.1 | AB25: 138232.43 | AC25: 8836066.2 | AD25: 1047690 | AE25: =(AA25+AC25) -> 9891782.3 | AF25: =(AB25+AD25) -> 1185922.4 | AH25: =2*310.1729*B25-1251279 -> 8022.974 | AI25: =SUM(AH11:AH25) -> 54196.317 | AJ25: =AH25/AF25 -> 0.0067651761 | AK25: =B25*0.000423519-0.851899 -> 0.00784457
B26: 2031 | C26: 596571.34 | D26: 64378.651 | E26: 1742574 | F26: 177754.65 | G26: =C26+E26 -> 2339145.3 | H26: =D26+F26 -> 242133.3 | J26: =2*2429.785*B26-9812843 -> 56943.67 | K26: =SUM(J12:J26) -> 354882.05 | L26: =J26/H26 -> 0.23517488 | M26: =B26*0.02244905-45.32156 -> 0.27246055 | O26: 40966.431 | P26: 3086.0505 | Q26: 110.247 | R26: 17.084317 | S26: =(O26+Q26)*10000 -> 4.1076678e+08 | T26: =(P26+R26)*10000 -> 31031348 | V26: =2*1741.681*B26-7041279 -> 33429.222 | W26: =SUM(V18:V26) -> 175461.97 | X26: =V26/T26 -> 0.0010772726 | Y26: =B26*0.0001262923-0.2554258 -> 0.0010738613 | AA26: 1098803 | AB26: 137163.46 | AC26: 8887584.2 | AD26: 939485.45 | AE26: =(AA26+AC26) -> 9986387.1 | AF26: =(AB26+AD26) -> 1076648.9 | AH26: =2*310.1729*B26-1251279 -> 8643.3198 | AI26: =SUM(AH12:AH26) -> 62839.637 | AJ26: =AH26/AF26 -> 0.0080279837 | AK26: =B26*0.000423519-0.851899 -> 0.008268089
B27: 2032 | C27: 597415.17 | D27: 53305.84 | E27: 1742574 | F27: 177865.09 | G27: =C27+E27 -> 2339989.2 | H27: =D27+F27 -> 231170.93 | J27: =2*2429.785*B27-9812843 -> 61803.24 | K27: =SUM(J13:J27) -> 416570.29 | L27: =J27/H27 -> 0.26734867 | M27: =B27*0.02244905-45.32156 -> 0.2949096 | O27: 41502.161 | P27: 3118.5915 | Q27: 110.247 | R27: 16.688217 | S27: =(O27+Q27)*10000 -> 4.1612408e+08 | T27: =(P27+R27)*10000 -> 31352797 | V27: =2*1741.681*B27-7041279 -> 36912.584 | W27: =SUM(V19:V27) -> 206812.22 | X27: =V27/T27 -> 0.0011773298 | Y27: =B27*0.0001262923-0.2554258 -> 0.0012001536 | AA27: 1142320.9 | AB27: 135372.99 | AC27: 8937868.6 | AD27: 849070.8 | AE27: =(AA27+AC27) -> 10080189 | AF27: =(AB27+AD27) -> 984443.79 | AH27: =2*310.1729*B27-1251279 -> 9263.6656 | AI27: =SUM(AH13:AH27) -> 71170.303 | AJ27: =AH27/AF27 -> 0.0094100503 | AK27: =B27*0.000423519-0.851899 -> 0.008691608
B28: 2033 | C28: 598240.27 | D28: 63676.301 | E28: 1742574 | F28: 171749.67 | G28: =C28+E28 -> 2340814.3 | H28: =D28+F28 -> 235425.98 | J28: =2*2429.785*B28-9812843 -> 66662.81 | K28: =SUM(J14:J28) -> 482796.1 | L28: =J28/H28 -> 0.28315826 | M28: =B28*0.02244905-45.32156 -> 0.31735865 | O28: 41922.915 | P28: 3150.8534 | Q28: 110.247 | R28: 2.9605 | S28: =(O28+Q28)*10000 -> 4.2033162e+08 | T28: =(P28+R28)*10000 -> 31538139 | V28: =2*1741.681*B28-7041279 -> 40395.946 | W28: =SUM(V20:V28) -> 238162.48 | X28: =V28/T28 -> 0.0012808602 | Y28: =B28*0.0001262923-0.2554258 -> 0.0013264459 | AA28: 1186496 | AB28: 135163.39 | AC28: 8987245.8 | AD28: 803440.98 | AE28: =(AA28+AC28) -> 10173742 | AF28: =(AB28+AD28) -> 938604.37 | AH28: =2*310.1729*B28-1251279 -> 9884.0114 | AI28: =SUM(AH14:AH28) -> 80650.314 | AJ28: =AH28/AF28 -> 0.010530541 | AK28: =B28*0.000423519-0.851899 -> 0.009115127
B29: 2034 | C29: 599045 | D29: 48769.71 | E29: 1742574 | F29: 162472.83 | G29: =C29+E29 -> 2341619 | H29: =D29+F29 -> 211242.54 | J29: =2*2429.785*B29-9812843 -> 71522.38 | K29: =SUM(J15:J29) -> 553142.48 | L29: =J29/H29 -> 0.33857943 | M29: =B29*0.02244905-45.32156 -> 0.3398077 | O29: 42240.835 | P29: 3168.6944 | Q29: 110.247 | R29: 17.473817 | S29: =(O29+Q29)*10000 -> 4.2351082e+08 | T29: =(P29+R29)*10000 -> 31861682 | V29: =2*1741.681*B29-7041279 -> 43879.308 | W29: =SUM(V21:V29) -> 269512.74 | X29: =V29/T29 -> 0.0013771812 | Y29: =B29*0.0001262923-0.2554258 -> 0.0014527382 | AA29: 1231184.7 | AB29: 137712.88 | AC29: 9035602.9 | AD29: 807353.16 | AE29: =(AA29+AC29) -> 10266788 | AF29: =(AB29+AD29) -> 945066.04 | AH29: =2*310.1729*B29-1251279 -> 10504.357 | AI29: =SUM(AH15:AH29) -> 89140.671 | AJ29: =AH29/AF29 -> 0.011114945 | AK29: =B29*0.000423519-0.851899 -> 0.009538646
B30: 2035 | C30: 599829.26 | D30: 25841.23 | E30: 1742574 | F30: 152775.01 | G30: =C30+E30 -> 2342403.3 | H30: =D30+F30 -> 178616.24 | I30: 600000 | J30: =2*2429.785*B30-9812843 -> 76381.95 | K30: =SUM(J16:J30) -> 628173.43 | L30: =J30/H30 -> 0.42763162 | M30: =B30*0.02244905-45.32156 -> 0.36225675 | O30: 42468.937 | P30: 3169.21 | Q30: 110.247 | R30: 20.798917 | S30: =(O30+Q30)*10000 -> 4.2579184e+08 | T30: =(P30+R30)*10000 -> 31900089 | U30: 320000 | V30: =2*1741.681*B30-7041279 -> 47362.67 | W30: =SUM(V22:V30) -> 300863 | X30: =V30/T30 -> 0.001484719 | Y30: =B30*0.0001262923-0.2554258 -> 0.0015790305 | AA30: 1276316.3 | AB30: 143648.33 | AC30: 9082919.8 | AD30: 853927.39 | AE30: =(AA30+AC30) -> 10359236 | AF30: =(AB30+AD30) -> 997575.72 | AG30: 100000 | AH30: =2*310.1729*B30-1251279 -> 11124.703 | AI30: =SUM(AH16:AH30) -> 100119.37 | AJ30: =AH30/AF30 -> 0.011151738 | AK30: =B30*0.000423519-0.851899 -> 0.009962165
B31: 2036 | C31: 600598.37 | D31: 70274.727 | E31: 1742574 | F31: 144613.74 | G31: =C31+E31 -> 2343172.4 | H31: =D31+F31 -> 214888.47 | J31: =2*2429.785*B31-9812843 -> 81241.52 | K31: =SUM(J17:J31) -> 708367.95 | L31: =J31/H31 -> 0.37806365 | M31: =B31*0.02244905-45.32156 -> 0.3847058 | O31: 42620.866 | P31: 3155.3009 | Q31: 110.247 | R31: 18.300217 | S31: =(O31+Q31)*10000 -> 4.2731113e+08 | T31: =(P31+R31)*10000 -> 31736011 | V31: =2*1741.681*B31-7041279 -> 50846.032 | W31: =SUM(V23:V31) -> 332213.26 | X31: =V31/T31 -> 0.0016021557 | Y31: =B31*0.0001262923-0.2554258 -> 0.0017053228 | AA31: 1322138.9 | AB31: 152502.87 | AC31: 9129505.1 | AD31: 926613.35 | AE31: =(AA31+AC31) -> 10451644 | AF31: =(AB31+AD31) -> 1079116.2 | AH31: =2*310.1729*B31-1251279 -> 11745.049 | AI31: =SUM(AH17:AH31) -> 111039.42 | AJ31: =AH31/AF31 -> 0.010883952 | AK31: =B31*0.000423519-0.851899 -> 0.010385684
B32: 2037 | C32: 601349.34 | D32: 107714.82 | E32: 1742574 | F32: 139439.83 | G32: =C32+E32 -> 2343923.3 | H32: =D32+F32 -> 247154.65 | J32: =2*2429.785*B32-9812843 -> 86101.09 | K32: =SUM(J18:J32) -> 781261.5 | L32: =J32/H32 -> 0.34836929 | M32: =B32*0.02244905-45.32156 -> 0.40715485 | O32: 42706.618 | P32: 3129.0747 | Q32: 110.247 | R32: 16.941017 | S32: =(O32+Q32)*10000 -> 4.2816865e+08 | T32: =(P32+R32)*10000 -> 31460158 | V32: =2*1741.681*B32-7041279 -> 54329.394 | W32: =SUM(V24:V32) -> 363563.51 | X32: =V32/T32 -> 0.001726927 | Y32: =B32*0.0001262923-0.2554258 -> 0.0018316151 | AA32: 1368427.2 | AB32: 162137.77 | AC32: 9175165.8 | AD32: 1000206.5 | AE32: =(AA32+AC32) -> 10543593 | AF32: =(AB32+AD32) -> 1162344.3 | AH32: =2*310.1729*B32-1251279 -> 12365.395 | AI32: =SUM(AH18:AH32) -> 120344.61 | AJ32: =AH32/AF32 -> 0.010638323 | AK32: =B32*0.000423519-0.851899 -> 0.010809203
B33: 2038 | C33: 602086.57 | D33: 70145.934 | E33: 1742574 | F33: 138102.04 | G33: =C33+E33 -> 2344660.6 | H33: =D33+F33 -> 208247.97 | J33: =2*2429.785*B33-9812843 -> 90960.66 | K33: =SUM(J19:J33) -> 854155.05 | L33: =J33/H33 -> 0.43679013 | M33: =B33*0.02244905-45.32156 -> 0.4296039 | O33: 42736.87 | P33: 3097.4219 | Q33: 110.247 | R33: 17.084317 | S33: =(O33+Q33)*10000 -> 4.2847117e+08 | T33: =(P33+R33)*10000 -> 31145062 | V33: =2*1741.681*B33-7041279 -> 57812.756 | W33: =SUM(V25:V33) -> 394913.77 | X33: =V33/T33 -> 0.0018562415 | Y33: =B33*0.0001262923-0.2554258 -> 0.0019579074 | AA33: 1415401.1 | AB33: 171207.79 | AC33: 9220159.4 | AD33: 1050890.2 | AE33: =(AA33+AC33) -> 10635561 | AF33: =(AB33+AD33) -> 1222098 | AH33: =2*310.1729*B33-1251279 -> 12985.74 | AI33: =SUM(AH19:AH33) -> 129649.8 | AJ33: =AH33/AF33 -> 0.010625777 | AK33: =B33*0.000423519-0.851899 -> 0.011232722
B34: 2039 | C34: 602808.64 | D34: 52146.915 | E34: 1742574 | F34: 140561.7 | G34: =C34+E34 -> 2345382.6 | H34: =D34+F34 -> 192708.62 | J34: =2*2429.785*B34-9812843 -> 95820.23 | K34: =SUM(J20:J34) -> 927048.6 | L34: =J34/H34 -> 0.49722857 | M34: =B34*0.02244905-45.32156 -> 0.45205295 | O34: 42719.893 | P34: 3063.0554 | Q34: 110.247 | R34: 16.688217 | S34: =(O34+Q34)*10000 -> 4.283014e+08 | T34: =(P34+R34)*10000 -> 30797436 | V34: =2*1741.681*B34-7041279 -> 61296.118 | W34: =SUM(V26:V34) -> 426264.03 | X34: =V34/T34 -> 0.0019902994 | Y34: =B34*0.0001262923-0.2554258 -> 0.0020841997 | AA34: 1462929.8 | AB34: 178100.5 | AC34: 9264389.5 | AD34: 1063914.5 | AE34: =(AA34+AC34) -> 10727319 | AF34: =(AB34+AD34) -> 1242015 | AH34: =2*310.1729*B34-1251279 -> 13606.086 | AI34: =SUM(AH20:AH34) -> 138954.98 | AJ34: =AH34/AF34 -> 0.010954849 | AK34: =B34*0.000423519-0.851899 -> 0.011656241
B35: 2040 | C35: 603515.27 | D35: 47261.142 | E35: 1742574 | F35: 145865.05 | G35: =C35+E35 -> 2346089.3 | H35: =D35+F35 -> 193126.19 | J35: =2*2429.785*B35-9812843 -> 100679.8 | K35: =SUM(J21:J35) -> 999942.15 | L35: =J35/H35 -> 0.52131613 | M35: =B35*0.02244905-45.32156 -> 0.474502 | O35: 42663.221 | P35: 3029.251 | Q35: 110.247 | R35: 2.9605 | S35: =(O35+Q35)*10000 -> 4.2773468e+08 | T35: =(P35+R35)*10000 -> 30322115 | V35: =2*1741.681*B35-7041279 -> 64779.48 | W35: =SUM(V27:V35) -> 457614.29 | X35: =V35/T35 -> 0.0021363774 | Y35: =B35*0.0001262923-0.2554258 -> 0.002210492 | AA35: 1510947 | AB35: 182521.19 | AC35: 9307829.6 | AD35: 1039998.5 | AE35: =(AA35+AC35) -> 10818777 | AF35: =(AB35+AD35) -> 1222519.7 | AH35: =2*310.1729*B35-1251279 -> 14226.432 | AI35: =SUM(AH21:AH35) -> 148260.17 | AJ35: =AH35/AF35 -> 0.011636976 | AK35: =B35*0.000423519-0.851899 -> 0.01207976
B36: 2041 | C36: 604210.08 | D36: 65073.466 | E36: 1742574 | F36: 152409.96 | G36: =C36+E36 -> 2346784.1 | H36: =D36+F36 -> 217483.43 | J36: =2*2429.785*B36-9812843 -> 105539.37 | K36: =SUM(J22:J36) -> 1072835.7 | L36: =J36/H36 -> 0.48527546 | M36: =B36*0.02244905-45.32156 -> 0.49695105 | O36: 42573.613 | P36: 2998.5554 | Q36: 110.247 | R36: 17.473817 | S36: =(O36+Q36)*10000 -> 4.268386e+08 | T36: =(P36+R36)*10000 -> 30160292 | V36: =2*1741.681*B36-7041279 -> 68262.842 | W36: =SUM(V28:V36) -> 488964.55 | X36: =V36/T36 -> 0.0022633349 | Y36: =B36*0.0001262923-0.2554258 -> 0.0023367843 | AA36: 1559653.7 | AB36: 185297.03 | AC36: 9350693.3 | AD36: 993854.2 | AE36: =(AA36+AC36) -> 10910347 | AF36: =(AB36+AD36) -> 1179151.2 | AH36: =2*310.1729*B36-1251279 -> 14846.778 | AI36: =SUM(AH22:AH36) -> 157565.36 | AJ36: =AH36/AF36 -> 0.012591072 | AK36: =B36*0.000423519-0.851899 -> 0.012503279
B37: 2042 | C37: 604892.45 | D37: 53988.202 | E37: 1742574 | F37: 158400.99 | G37: =C37+E37 -> 2347466.4 | H37: =D37+F37 -> 212389.19 | J37: =2*2429.785*B37-9812843 -> 110398.94 | K37: =SUM(J23:J37) -> 1145729.2 | L37: =J37/H37 -> 0.51979548 | M37: =B37*0.02244905-45.32156 -> 0.5194001 | O37: 42456.437 | P37: 2972.2991 | Q37: 110.247 | R37: 20.798917 | S37: =(O37+Q37)*10000 -> 4.2566684e+08 | T37: =(P37+R37)*10000 -> 29930981 | V37: =2*1741.681*B37-7041279 -> 71746.204 | W37: =SUM(V29:V37) -> 520314.8 | X37: =V37/T37 -> 0.0023970549 | Y37: =B37*0.0001262923-0.2554258 -> 0.0024630766 | AA37: 1608972.5 | AB37: 187300.5 | AC37: 9392934 | AD37: 946398.41 | AE37: =(AA37+AC37) -> 11001906 | AF37: =(AB37+AD37) -> 1133698.9 | AH37: =2*310.1729*B37-1251279 -> 15467.124 | AI37: =SUM(AH23:AH37) -> 166870.55 | AJ37: =AH37/AF37 -> 0.013643061 | AK37: =B37*0.000423519-0.851899 -> 0.012926798
B38: 2043 | C38: 605562.54 | D38: 64346.398 | E38: 1742574 | F38: 162364.29 | G38: =C38+E38 -> 2348136.5 | H38: =D38+F38 -> 226710.69 | J38: =2*2429.785*B38-9812843 -> 115258.51 | K38: =SUM(J24:J38) -> 1218622.8 | L38: =J38/H38 -> 0.50839469 | M38: =B38*0.02244905-45.32156 -> 0.54184915 | O38: 42316.341 | P38: 2951.729 | Q38: 110.247 | R38: 18.300217 | S38: =(O38+Q38)*10000 -> 4.2426588e+08 | T38: =(P38+R38)*10000 -> 29700292 | V38: =2*1741.681*B38-7041279 -> 75229.566 | W38: =SUM(V30:V38) -> 551665.06 | X38: =V38/T38 -> 0.0025329571 | Y38: =B38*0.0001262923-0.2554258 -> 0.0025893689 | AA38: 1658880 | AB38: 189825.61 | AC38: 9434555.7 | AD38: 916218.64 | AE38: =(AA38+AC38) -> 11093436 | AF38: =(AB38+AD38) -> 1106044.3 | AH38: =2*310.1729*B38-1251279 -> 16087.469 | AI38: =SUM(AH24:AH38) -> 176175.73 | AJ38: =AH38/AF38 -> 0.01454505 | AK38: =B38*0.000423519-0.851899 -> 0.013350317
B39: 2044 | C39: 606221.41 | D39: 49428.575 | E39: 1742574 | F39: 163539.26 | G39: =C39+E39 -> 2348795.4 | H39: =D39+F39 -> 212967.83 | J39: =2*2429.785*B39-9812843 -> 120118.08 | K39: =SUM(J25:J39) -> 1291516.3 | L39: =J39/H39 -> 0.56401983 | M39: =B39*0.02244905-45.32156 -> 0.5642982 | O39: 42157.284 | P39: 2937.1769 | Q39: 110.247 | R39: 16.941017 | S39: =(O39+Q39)*10000 -> 4.2267531e+08 | T39: =(P39+R39)*10000 -> 29541179 | V39: =2*1741.681*B39-7041279 -> 78712.928 | W39: =SUM(V31:V39) -> 583015.32 | X39: =V39/T39 -> 0.0026645155 | Y39: =B39*0.0001262923-0.2554258 -> 0.0027156612 | AA39: 1709417.1 | AB39: 193830.46 | AC39: 9475615.7 | AD39: 912647.56 | AE39: =(AA39+AC39) -> 11185033 | AF39: =(AB39+AD39) -> 1106478 | AH39: =2*310.1729*B39-1251279 -> 16707.815 | AI39: =SUM(AH25:AH39) -> 185480.92 | AJ39: =AH39/AF39 -> 0.015099997 | AK39: =B39*0.000423519-0.851899 -> 0.013773836
B40: 2045 | C40: 606869.88 | D40: 26489.701 | E40: 1742574 | F40: 162007.76 | G40: =C40+E40 -> 2349443.9 | H40: =D40+F40 -> 188497.46 | J40: =2*2429.785*B40-9812843 -> 124977.65 | K40: =SUM(J26:J40) -> 1364409.9 | L40: =J40/H40 -> 0.66302034 | M40: =B40*0.02244905-45.32156 -> 0.58674725 | O40: 41982.602 | P40: 2927.9577 | Q40: 110.247 | R40: 17.084317 | S40: =(O40+Q40)*10000 -> 4.2092849e+08 | T40: =(P40+R40)*10000 -> 29450420 | V40: =2*1741.681*B40-7041279 -> 82196.29 | W40: =SUM(V32:V40) -> 614365.58 | X40: =V40/T40 -> 0.0027910057 | Y40: =B40*0.0001262923-0.2554258 -> 0.0028419535 | AA40: 1760616.6 | AB40: 199619.01 | AC40: 9516159.8 | AD40: 934243.1 | AE40: =(AA40+AC40) -> 11276776 | AF40: =(AB40+AD40) -> 1133862.1 | AH40: =2*310.1729*B40-1251279 -> 17328.161 | AI40: =SUM(AH26:AH40) -> 194786.11 | AJ40: =AH40/AF40 -> 0.015282423 | AK40: =B40*0.000423519-0.851899 -> 0.014197355
B41: 2046 | C41: 607509.16 | D41: 70914.01 | E41: 1742574 | F41: 158548.33 | G41: =C41+E41 -> 2350083.2 | H41: =D41+F41 -> 229462.34 | J41: =2*2429.785*B41-9812843 -> 129837.22 | K41: =SUM(J27:J41) -> 1437303.4 | L41: =J41/H41 -> 0.56583238 | M41: =B41*0.02244905-45.32156 -> 0.6091963 | O41: 41795.139 | P41: 2922.4662 | Q41: 110.247 | R41: 16.688217 | S41: =(O41+Q41)*10000 -> 4.1905386e+08 | T41: =(P41+R41)*10000 -> 29391544 | V41: =2*1741.681*B41-7041279 -> 85679.652 | W41: =SUM(V33:V41) -> 645715.84 | X41: =V41/T41 -> 0.0029151123 | Y41: =B41*0.0001262923-0.2554258 -> 0.0029682458 | AA41: 1812546.9 | AB41: 206934.51 | AC41: 9556257.5 | AD41: 971507.94 | AE41: =(AA41+AC41) -> 11368804 | AF41: =(AB41+AD41) -> 1178442.4 | AH41: =2*310.1729*B41-1251279 -> 17948.507 | AI41: =SUM(AH27:AH41) -> 204091.29 | AJ41: =AH41/AF41 -> 0.015230703 | AK41: =B41*0.000423519-0.851899 -> 0.014620874
B42: 2047 | C42: 608138.2 | D42: 108343.86 | E42: 1742574 | F42: 154311.26 | G42: =C42+E42 -> 2350712.2 | H42: =D42+F42 -> 262655.12 | J42: =2*2429.785*B42-9812843 -> 134696.79 | K42: =SUM(J28:J42) -> 1510197 | L42: =J42/H42 -> 0.51282758 | M42: =B42*0.02244905-45.32156 -> 0.63164535 | O42: 41597.328 | P42: 2918.41 | Q42: 110.247 | R42: 2.9605 | S42: =(O42+Q42)*10000 -> 4.1707575e+08 | T42: =(P42+R42)*10000 -> 29213705 | V42: =2*1741.681*B42-7041279 -> 89163.014 | W42: =SUM(V34:V42) -> 677066.09 | X42: =V42/T42 -> 0.0030520954 | Y42: =B42*0.0001262923-0.2554258 -> 0.0030945381 | AA42: 1865096.6 | AB42: 214864.03 | AC42: 9595837 | AD42: 1011074.9 | AE42: =(AA42+AC42) -> 11460934 | AF42: =(AB42+AD42) -> 1225938.9 | AH42: =2*310.1729*B42-1251279 -> 18568.853 | AI42: =SUM(AH28:AH42) -> 213396.48 | AJ42: =AH42/AF42 -> 0.015146637 | AK42: =B42*0.000423519-0.851899 -> 0.015044393
... B55: 2060 | C55: 615673.68 | D55: 48413.043 | E55: 1742574 | F55: 152563.31 | G55: =C55+E55 -> 2358247.7 | H55: =D55+F55 -> 200976.36 | J55: =2*2429.785*B55-9812843 -> 197871.2 | K55: =SUM(J41:J55) -> 2457813.1 | L55: =J55/H55 -> 0.98454965 | M55: =B55*0.02244905-45.32156 -> 0.923483 | O55: 38895.347 | P55: 2749.1054 | Q55: 110.247 | R55: 16.688217 | S55: =(O55+Q55)*10000 -> 3.9005594e+08 | T55: =(P55+R55)*10000 -> 27657936 | V55: =2*1741.681*B55-7041279 -> 134446.72 | W55: =SUM(V47:V55) -> 1084619.4 | X55: =V55/T55 -> 0.004861054 | Y55: =B55*0.0001262923-0.2554258 -> 0.004736338 | AA55: 2621609.9 | AB55: 299252.05 | AC55: 10079656 | AD55: 1064551.7 | AE55: =(AA55+AC55) -> 12701265 | AF55: =(AB55+AD55) -> 1363803.8 | AH55: =2*310.1729*B55-1251279 -> 26633.348 | AI55: =SUM(AH41:AH55) -> 334363.91 | AJ55: =AH55/AF55 -> 0.019528725 | AK55: =B55*0.000423519-0.851899 -> 0.02055014

Sheet AEO 38
E1: 2020 | F1: 2021 | G1: 2022 | H1: 2023 | I1: 2024 | J1: 2025 | K1: 2026 | L1: 2027 | M1: 2028 | N1: 2029 | O1: 2030 | P1: 2031 | Q1: 2032 | R1: 2033 | S1: 2034 | T1: 2035 | U1: 2036 | V1: 2037 | W1: 2038 | X1: 2039 | Y1: 2040 | Z1: 2041 | AA1: 2042 | AB1: 2043 | AC1: 2044 | AD1: 2045 | AE1: 2046 | AF1: 2047 | AG1: 2048 | AH1: 2049 | AI1: 2050 | AJ1: Growth (2020-2050)
A10: Table 38. Light-Duty Vehicle Sales by Technology Type
A11: https://www.eia.gov/outlooks/aeo/data/browser/#/?id=48-AEO2021&cases=highogs&sourcekey=0
A12: Mon Mar 08 2021 16:20:29 GMT-0800 (Pacific Standard Time)
A13: Source: U.S. Energy Information Administration
B14: full name | C14: api key | D14: units | E14: 2020 | F14: 2021 | G14: 2022 | H14: 2023 | I14: 2024 | J14: 2025 | K14: 2026 | L14: 2027 | M14: 2028 | N14: 2029 | O14: 2030 | P14: 2031 | Q14: 2032 | R14: 2033 | S14: 2034 | T14: 2035 | U14: 2036 | V14: 2037 | W14: 2038 | X14: 2039 | Y14: 2040 | Z14: 2041 | AA14: 2042 | AB14: 2043 | AC14: 2044 | AD14: 2045 | AE14: 2046 | AF14: 2047 | AG14: 2048 | AH14: 2049 | AI14: 2050 | AJ14: Growth (2020-2050)
A15: New Car Sales | C15: 48-AEO2021.2.
A16: Conventional Cars | C16: 48-AEO2021.3.
A17: Gasoline ICE Vehicles | B17: Light-Duty Vehicle Sales: Conventional Cars: Gasoline: High oil and gas supply | C17: 48-AEO2021.4.highogs-d120120a | D17: thousands | E17: 4430.54 | F17: 4768.9263 | G17: 5242.686 | H17: 5277.4258 | I17: 5332.4824 | J17: 5366.3647 | K17: 5276.0283 | L17: 5157.7227 | M17: 5160.4292 | N17: 5150.4785 | O17: 5149.1211 | P17: 5129.0278 | Q17: 5123.6499 | R17: 5107.165 | S17: 5106.6157 | T17: 5067.0293 | U17: 4988.6606 | V17: 4915.4424 | W17: 4879.7422 | X17: 4824.8184 | Y17: 4767.0156 | Z17: 4718.7866 | AA17: 4672.1494 | AB17: 4616.104 | AC17: 4570.187 | AD17: 4571.7012 | AE17: 4505.4287 | AF17: 4434.6743 | AG17: 4405.3608 | AH17: 4332.688 | AI17: 4252.9243 | AJ17: -0.001
A18: TDI Diesel ICE | B18: Light-Duty Vehicle Sales: Conventional Cars: TDI Diesel: High oil and gas supply | C18: 48-AEO2021.5.highogs-d120120a | D18: thousands | E18: 0.091703 | F18: 0.090031 | G18: 0.094424 | H18: 0.089815 | I18: 0.08771 | J18: 0.08925 | K18: 0.086431 | L18: 0.083304 | M18: 0.08455 | N18: 0.084075 | O18: 0.083118 | P18: 0.084137 | Q18: 0.083978 | R18: 0.083596 | S18: 0.084752 | T18: 0.084326 | U18: 0.083612 | V18: 0.081953 | W18: 0.081093 | X18: 0.081319 | Y18: 0.078959 | Z18: 0.078244 | AA18: 0.077311 | AB18: 0.076276 | AC18: 0.075326 | AD18: 0.075413 | AE18: 0.074002 | AF18: 0.072725 | AG18: 0.071912 | AH18: 0.070517 | AI18: 0.069125 | AJ18: -0.009
A19: Total Conventional Cars | B19: Light-Duty Vehicle Sales: Conventional Cars: Total: High oil and gas supply | C19: 48-AEO2021.6.highogs-d120120a | D19: thousands | E19: 4430.6318 | F19: 4769.0161 | G19: 5242.7803 | H19: 5277.5156 | I19: 5332.5703 | J19: 5366.4541 | K19: 5276.1147 | L19: 5157.8062 | M19: 5160.5137 | N19: 5150.5625 | O19: 5149.2041 | P19: 5129.1118 | Q19: 5123.7339 | R19: 5107.2485 | S19: 5106.7007 | T19: 5067.1138 | U19: 4988.7441 | V19: 4915.5244 | W19: 4879.8232 | X19: 4824.8999 | Y19: 4767.0947 | Z19: 4718.8647 | AA19: 4672.2266 | AB19: 4616.1802 | AC19: 4570.2622 | AD19: 4571.7764 | AE19: 4505.5029 | AF19: 4434.7471 | AG19: 4405.4326 | AH19: 4332.7583 | AI19: 4252.9937 | AJ19: -0.001
A20: Alternative-Fuel Cars | C20: 48-AEO2021.8.
A21: Ethanol-Flex Fuel ICE | B21: Light-Duty Vehicle Sales: Alternative-Fuel Cars: Ethanol-Flex Fuel ICE: High oil and gas supply | C21: 48-AEO2021.9.highogs-d120120a | D21: thousands | E21: 82.86573 | F21: 88.778244 | G21: 97.887756 | H21: 98.749519 | I21: 99.876137 | J21: 100.60027 | K21: 99.069313 | L21: 97.080338 | M21: 97.452324 | N21: 97.519157 | O21: 97.80072 | P21: 97.808365 | Q21: 98.015251 | R21: 98.066704 | S21: 98.425705 | T21: 98.079758 | U21: 96.899742 | V21: 95.840691 | W21: 95.533234 | X21: 94.846573 | Y21: 94.080093 | Z21: 93.468681 | AA21: 92.857796 | AB21: 92.05088 | AC21: 91.469421 | AD21: 91.848557 | AE21: 90.8843 | AF21: 89.801239 | AG21: 89.570892 | AH21: 88.466881 | AI21: 87.250069 | AJ21: 0.002
A22: 100 Mile Electric Vehicle | B22: Light-Duty Vehicle Sales: Alternative-Fuel Cars: 100 Mile Electric Vehicle: High oil and gas supply | C22: 48-AEO2021.10.highogs-d120120a | D22: thousands | E22: 2.014161 | F22: 2.116755 | G22: 2.187926 | H22: 2.115665 | I22: 2.1331 | J22: 2.187847 | K22: 2.250745 | L22: 2.319192 | M22: 2.463099 | N22: 2.616289 | O22: 2.802221 | P22: 2.953589 | Q22: 3.120451 | R22: 3.262651 | S22: 3.40547 | T22: 3.49672 | U22: 3.548795 | V22: 3.589806 | W22: 3.646011 | X22: 3.673913 | Y22: 3.693691 | Z22: 3.701219 | AA22: 3.707546 | AB22: 3.704162 | AC22: 3.70677 | AD22: 3.748243 | AE22: 3.730523 | AF22: 3.707829 | AG22: 3.718948 | AH22: 3.697174 | AI22: 3.669234 | AJ22: 0.02
A23: 200 Mile Electric Vehicle | B23: Light-Duty Vehicle Sales: Alternative-Fuel Cars: 200 Mile Electric Vehicle: High oil and gas supply | C23: 48-AEO2021.11.highogs-d120120a | D23: thousands | E23: 45.0984 | F23: 43.183132 | G23: 44.87886 | H23: 42.311188 | I23: 41.21912 | J23: 41.567673 | K23: 41.456791 | L23: 43.14045 | M23: 46.895927 | N23: 51.488796 | O23: 58.315022 | P23: 64.530876 | Q23: 72.045967 | R23: 79.581985 | S23: 87.853249 | T23: 94.674225 | U23: 100.86777 | V23: 107.29221 | W23: 114.55816 | X23: 120.88749 | Y23: 127.42668 | Z23: 133.08254 | AA23: 138.54511 | AB23: 144.04106 | AC23: 150.03532 | AD23: 158.08809 | AE23: 163.42651 | AF23: 168.74788 | AG23: 175.61302 | AH23: 181.70338 | AI23: 187.48808 | AJ23: 0.049
A24: 300 Mile Electric Vehicle | B24: Light-Duty Vehicle Sales: Alternative-Fuel Cars: 300 Mile Electric Vehicle: High oil and gas supply | C24: 48-AEO2021.12.highogs-d120120a | D24: thousands | E24: 65.759254 | F24: 57.491383 | G24: 66.992439 | H24: 73.780128 | I24: 80.019737 | J24: 83.488007 | K24: 88.954521 | L24: 94.401581 | M24: 105.24663 | N24: 117.28207 | O24: 132.60144 | P24: 153.49263 | Q24: 173.61665 | R24: 198.33243 | S24: 225.30927 | T24: 254.45285 | U24: 278.03854 | V24: 303.48288 | W24: 332.54962 | X24: 360.70767 | Y24: 386.63501 | Z24: 406.61685 | AA24: 425.57904 | AB24: 443.11395 | AC24: 462.9602 | AD24: 488.96314 | AE24: 510.02222 | AF24: 528.28735 | AG24: 553.2616 | AH24: 572.91254 | AI24: 594.61017 | AJ24: 0.076
A25: Plug-in 10 Gasoline Hybrid | B25: Light-Duty Vehicle Sales: Alternative-Fuel Cars: Plug-in 10 Gasoline Hybrid: High oil and gas supply | C25: 48-AEO2021.13.highogs-d120120a | D25: thousands | E25: 20.674416 | F25: 28.176989 | G25: 33.950932 | H25: 36.931286 | I25: 41.969532 | J25: 48.640995 | K25: 55.013874 | L25: 62.905365 | M25: 73.882957 | N25: 77.068756 | O25: 80.696732 | P25: 81.135765 | Q25: 83.302795 | R25: 84.292328 | S25: 85.728806 | T25: 84.681641 | U25: 83.560677 | V25: 82.382141 | W25: 81.626305 | X25: 79.956459 | Y25: 78.624977 | Z25: 76.511696 | AA25: 74.205223 | AB25: 72.000122 | AC25: 69.958206 | AD25: 68.774048 | AE25: 66.15274 | AF25: 63.704296 | AG25: 61.705101 | AH25: 59.545723 | AI25: 57.139908 | AJ25: 0.034
A26: Plug-in 40 Gasoline Hybrid | B26: Light-Duty Vehicle Sales: Alternative-Fuel Cars: Plug-in 40 Gasoline Hybrid: High oil and gas supply | C26: 48-AEO2021.14.highogs-d120120a | D26: thousands | E26: 5.310642 | F26: 5.630332 | G26: 5.241416 | H26: 4.634056 | I26: 4.410059 | J26: 4.339242 | K26: 4.392287 | L26: 4.544848 | M26: 4.886629 | N26: 5.32712 | O26: 5.979389 | P26: 6.411442 | Q26: 6.825327 | R26: 7.164952 | S26: 7.520013 | T26: 7.705092 | U26: 7.815033 | V26: 7.905196 | W26: 8.024158 | X26: 8.055717 | Y26: 8.079099 | Z26: 8.036082 | AA26: 7.969784 | AB26: 7.89343 | AC26: 7.831873 | AD26: 7.857708 | AE26: 7.742971 | AF26: 7.623875 | AG26: 7.568454 | AH26: 7.464639 | AI26: 7.343002 | AJ26: 0.011
A27: Electric-Diesel Hybrid | B27: Light-Duty Vehicle Sales: Alternative-Fuel Cars: Electric-Diesel Hybrid: High oil and gas supply | C27: 48-AEO2021.15.highogs-d120120a | D27: thousands | E27: 0 | F27: 0 | G27: 0 | H27: 0 | I27: 0 | J27: 0 | K27: 0 | L27: 0 | M27: 0 | N27: 0 | O27: 0 | P27: 0 | Q27: 0 | R27: 0 | S27: 0 | T27: 0 | U27: 0 | V27: 0 | W27: 0 | X27: 0 | Y27: 0 | Z27: 0 | AA27: 0 | AB27: 0 | AC27: 0 | AD27: 0 | AE27: 0 | AF27: 0 | AG27: 0 | AH27: 0 | AI27: 0 | AJ27: - -
A28: Electric-Gasoline Hybrid | B28: Light-Duty Vehicle Sales: Alternative-Fuel Cars: Electric-Gasoline Hybrid: High oil and gas supply | C28: 48-AEO2021.16.highogs-d120120a | D28: thousands | E28: 121.39723 | F28: 136.90977 | G28: 161.62053 | H28: 172.90016 | I28: 185.48763 | J28: 197.37852 | K28: 206.53253 | L28: 216.44562 | M28: 232.97336 | N28: 246.07936 | O28: 261.67313 | P28: 274.52325 | Q28: 287.88394 | R28: 300.89297 | S28: 315.42978 | T28: 326.46143 | U28: 334.92172 | V28: 344.05875 | W28: 356.15479 | X28: 366.53769 | Y28: 377.08914 | Z28: 390.3526 | AA28: 401.86212 | AB28: 413.0246 | AC28: 425.68555 | AD28: 443.7468 | AE28: 455.27057 | AF28: 466.522 | AG28: 482.34302 | AH28: 494.32117 | AI28: 505.77969 | AJ28: 0.049
A29: Natural Gas ICE | B29: Light-Duty Vehicle Sales: Alternative-Fuel Cars: Natural Gas ICE: High oil and gas supply | C29: 48-AEO2021.17.highogs-d120120a | D29: thousands | E29: 0.436299 | F29: 0.446886 | G29: 0.548589 | H29: 0.607807 | I29: 0.654286 | J29: 0.681397 | K29: 0.675533 | L29: 0.660688 | M29: 0.663885 | N29: 0.659324 | O29: 0.654316 | P29: 0.660209 | Q29: 0.659287 | R29: 0.660811 | S29: 0.664577 | T29: 0.666657 | U29: 0.656994 | V29: 0.650827 | W29: 0.651406 | X29: 0.649305 | Y29: 0.644867 | Z29: 0.642947 | AA29: 0.64116 | AB29: 0.637366 | AC29: 0.635911 | AD29: 0.641543 | AE29: 0.638431 | AF29: 0.633144 | AG29: 0.634526 | AH29: 0.629213 | AI29: 0.624813 | AJ29: 0.012
A30: Natural Gas Bi-fuel | B30: Light-Duty Vehicle Sales: Alternative-Fuel Cars: Natural Gas Bi-fuel: High oil and gas supply | C30: 48-AEO2021.18.highogs-d120120a | D30: thousands | E30: 2.233771 | F30: 2.354919 | G30: 2.610208 | H30: 2.642015 | I30: 2.677342 | J30: 2.702859 | K30: 2.668197 | L30: 2.623082 | M30: 2.645067 | N30: 2.65579 | O30: 2.670106 | P30: 2.683413 | Q30: 2.699393 | R30: 2.713665 | S30: 2.737803 | T30: 2.741847 | U30: 2.720474 | V30: 2.704052 | W30: 2.709671 | X30: 2.704082 | Y30: 2.695708 | Z30: 2.690396 | AA30: 2.684189 | AB30: 2.672501 | AC30: 2.66801 | AD30: 2.692924 | AE30: 2.678834 | AF30: 2.660519 | AG30: 2.668229 | AH30: 2.650469 | AI30: 2.630525 | AJ30: 0.005
A31: Propane ICE | B31: Light-Duty Vehicle Sales: Alternative-Fuel Cars: Propane: High oil and gas supply | C31: 48-AEO2021.19.highogs-d120120a | D31: thousands | E31: 0.413892 | F31: 0.373083 | G31: 0.432242 | H31: 0.450286 | I31: 0.454892 | J31: 0.459537 | K31: 0.453937 | L31: 0.44736 | M31: 0.455217 | N31: 0.459614 | O31: 0.460688 | P31: 0.475505 | Q31: 0.478446 | R31: 0.485149 | S31: 0.491327 | T31: 0.499504 | U31: 0.495486 | V31: 0.49308 | W31: 0.496612 | X31: 0.499809 | Y31: 0.499778 | Z31: 0.502526 | AA31: 0.505401 | AB31: 0.506785 | AC31: 0.509286 | AD31: 0.517814 | AE31: 0.520073 | AF31: 0.519068 | AG31: 0.524132 | AH31: 0.521896 | AI31: 0.521648 | AJ31: 0.008
A32: Propane Bi-fuel | B32: Light-Duty Vehicle Sales: Alternative-Fuel Cars: Propane: High oil and gas supply | C32: 48-AEO2021.20.highogs-d120120a | D32: thousands | E32: 0.553153 | F32: 0.584848 | G32: 0.647259 | H32: 0.655402 | I32: 0.663684 | J32: 0.669541 | K32: 0.661359 | L32: 0.650377 | M32: 0.655528 | N32: 0.658057 | O32: 0.661973 | P32: 0.665104 | Q32: 0.668828 | R32: 0.672042 | S32: 0.677631 | T32: 0.678035 | U32: 0.672155 | V32: 0.667307 | W32: 0.668127 | X32: 0.666227 | Y32: 0.663661 | Z32: 0.661948 | AA32: 0.660016 | AB32: 0.656961 | AC32: 0.655442 | AD32: 0.661266 | AE32: 0.65729 | AF32: 0.652311 | AG32: 0.653646 | AH32: 0.648766 | AI32: 0.643394 | AJ32: 0.005
A33: Fuel Cell Methanol | B33: Light-Duty Vehicle Sales: Alternative-Fuel Cars: Fuel Cell Methanol: High oil and gas supply | C33: 48-AEO2021.21.highogs-d120120a | D33: thousands | E33: 0 | F33: 0 | G33: 0 | H33: 0 | I33: 0 | J33: 0 | K33: 0 | L33: 0 | M33: 0 | N33: 0 | O33: 0 | P33: 0 | Q33: 0 | R33: 0 | S33: 0 | T33: 0 | U33: 0 | V33: 0 | W33: 0 | X33: 0 | Y33: 0 | Z33: 0 | AA33: 0 | AB33: 0 | AC33: 0 | AD33: 0 | AE33: 0 | AF33: 0 | AG33: 0 | AH33: 0 | AI33: 0 | AJ33: - -
A34: Fuel Cell Hydrogen | B34: Light-Duty Vehicle Sales: Alternative-Fuel cars: Fuel Cell Hydrogen: High oil and gas supply | C34: 48-AEO2021.22.highogs-d120120a | D34: thousands | E34: 0.178328 | F34: 0.184374 | G34: 0.21913 | H34: 0.247297 | I34: 0.283277 | J34: 0.331866 | K34: 0.375719 | L34: 0.421967 | M34: 0.482801 | N34: 0.545208 | O34: 0.610859 | P34: 0.674256 | Q34: 0.736383 | R34: 0.794171 | S34: 0.850429 | T34: 0.896305 | U34: 0.928802 | V34: 0.958282 | W34: 0.992079 | X34: 1.019459 | Y34: 1.043306 | Z34: 1.067578 | AA34: 1.090818 | AB34: 1.110843 | AC34: 1.133713 | AD34: 1.169284 | AE34: 1.188951 | AF34: 1.205626 | AG34: 1.234655 | AH34: 1.250848 | AI34: 1.266985 | AJ34: 0.068
A35: Total Alternative Cars | B35: Light-Duty Vehicle Sales: Alternative-Fuel Cars: Total: High oil and gas supply | C35: 48-AEO2021.23.highogs-d120120a | D35: thousands | E35: 346.93527 | F35: 366.23074 | G35: 417.21722 | H35: 436.02481 | I35: 459.84882 | J35: 483.04776 | K35: 502.50482 | L35: 525.64087 | M35: 568.70343 | N35: 602.35956 | O35: 644.92664 | P35: 686.0144 | Q35: 730.05273 | R35: 776.91992 | S35: 829.09399 | T35: 875.03412 | U35: 911.12616 | V35: 950.02515 | W35: 997.61017 | X35: 1040.2043 | Y35: 1081.1759 | Z35: 1117.3351 | AA35: 1150.3082 | AB35: 1181.4126 | AC35: 1217.2496 | AD35: 1268.7095 | AE35: 1302.9135 | AF35: 1334.0649 | AG35: 1379.4961 | AH35: 1413.8126 | AI35: 1448.9677 | AJ35: 0.049
A36: Percent Alternative Car Sales | B36: Light-Duty Vehicle Sales: Percent Alternative Car: High oil and gas supply | C36: 48-AEO2021.25.highogs-d120120a | D36: percent | E36: 7.261757 | F36: 7.131706 | G36: 7.371333 | H36: 7.631429 | I36: 7.938805 | J36: 8.25793 | K36: 8.695931 | L36: 9.248628 | M36: 9.926372 | N36: 10.470497 | O36: 11.130689 | P36: 11.797069 | Q36: 12.471461 | R36: 13.203565 | S36: 13.967699 | T36: 14.725889 | U36: 15.443156 | V36: 16.196693 | W36: 16.973568 | X36: 17.735477 | Y36: 18.487104 | Z36: 19.144907 | AA36: 19.756144 | AB36: 20.37764 | AC36: 21.032349 | AD36: 21.72267 | AE36: 22.431475 | AF36: 23.125471 | AG36: 23.84638 | AH36: 24.602718 | AI36: 25.411739 | AJ36: 0.043
A37: Total New Car Sales | B37: Light-Duty Vehicle Sales: Total New Car: High oil and gas supply | C37: 48-AEO2021.26.highogs-d120120a | D37: thousands | E37: 4777.5669 | F37: 5135.2471 | G37: 5659.9976 | H37: 5713.5405 | I37: 5792.4189 | J37: 5849.502 | K37: 5778.6196 | L37: 5683.4473 | M37: 5729.2173 | N37: 5752.9219 | O37: 5794.1309 | P37: 5815.126 | Q37: 5853.7866 | R37: 5884.1685 | S37: 5935.7949 | T37: 5942.1479 | U37: 5899.8701 | V37: 5865.5498 | W37: 5877.4336 | X37: 5865.1045 | Y37: 5848.2705 | Z37: 5836.1997 | AA37: 5822.5347 | AB37: 5797.5928 | AC37: 5787.5117 | AD37: 5840.4858 | AE37: 5808.4165 | AF37: 5768.812 | AG37: 5784.9287 | AH37: 5746.5708 | AI37: 5701.9614 | AJ37: 0.006
A38: New Light Truck Sales | C38: 48-AEO2021.28.
A39: Conventional Light Trucks | C39: 48-AEO2021.29.
A40: Gasoline ICE Vehicles | B40: Light-Duty Vehicle Sales: Conventional Light Trucks: Gasoline: High oil and gas supply | C40: 48-AEO2021.30.highogs-d120120a | D40: thousands | E40: 6511.5112 | F40: 7292.9346 | G40: 7525.9263 | H40: 7716.5991 | I40: 8010.6343 | J40: 8217.6807 | K40: 8112.4087 | L40: 7927.6226 | M40: 7939.8613 | N40: 7908.9395 | O40: 7718.6572 | P40: 7683.6753 | Q40: 7655.0903 | R40: 7618.3013 | S40: 7564.605 | T40: 7588.0215 | U40: 7548.6802 | V40: 7479.4258 | W40: 7456.207 | X40: 7444.9131 | Y40: 7408.1597 | Z40: 7379.0337 | AA40: 7367.5815 | AB40: 7330.853 | AC40: 7297.3506 | AD40: 7318.8364 | AE40: 7272.2656 | AF40: 7213.9648 | AG40: 7236.2163 | AH40: 7160.7158 | AI40: 7073.6338 | AJ40: 0.003
A41: TDI Diesel ICE | B41: Light-Duty Vehicle Sales: Conventional Light Trucks: TDI Diesel: High oil and gas supply | C41: 48-AEO2021.31.highogs-d120120a | D41: thousands | E41: 46.653286 | F41: 86.627808 | G41: 118.90294 | H41: 111.87041 | I41: 112.74366 | J41: 118.86602 | K41: 113.95782 | L41: 110.3395 | M41: 114.4775 | N41: 115.45842 | O41: 113.54399 | P41: 113.89195 | Q41: 115.92995 | R41: 115.80641 | S41: 118.98551 | T41: 119.19649 | U41: 121.28391 | V41: 120.20547 | W41: 120.30798 | X41: 122.68635 | Y41: 120.37798 | Z41: 120.40474 | AA41: 120.17378 | AB41: 119.90891 | AC41: 119.43106 | AD41: 120.89611 | AE41: 119.21642 | AF41: 118.31202 | AG41: 118.43898 | AH41: 117.40183 | AI41: 115.73097 | AJ41: 0.031
A42: Total Conventional Light Trucks | B42: Light-Duty Vehicle Sales: Conventional Light Trucks: Total: High oil and gas supply | C42: 48-AEO2021.32.highogs-d120120a | D42: thousands | E42: 6558.1646 | F42: 7379.5625 | G42: 7644.8291 | H42: 7828.4697 | I42: 8123.3779 | J42: 8336.5469 | K42: 8226.3662 | L42: 8037.9619 | M42: 8054.3389 | N42: 8024.3979 | O42: 7832.2012 | P42: 7797.5674 | Q42: 7771.0205 | R42: 7734.1079 | S42: 7683.5903 | T42: 7707.2178 | U42: 7669.9639 | V42: 7599.6313 | W42: 7576.5151 | X42: 7567.5996 | Y42: 7528.5376 | Z42: 7499.4385 | AA42: 7487.7554 | AB42: 7450.7617 | AC42: 7416.7817 | AD42: 7439.7324 | AE42: 7391.4819 | AF42: 7332.2769 | AG42: 7354.6553 | AH42: 7278.1177 | AI42: 7189.3647 | AJ42: 0.003
A43: Alternative-Fuel Light Trucks | C43: 48-AEO2021.34.
A44: Ethanol-Flex Fuel ICE | B44: Light-Duty Vehicle Sales: Alternative-Fuel Light Trucks: Ethanol-Flex Fuel ICE: High oil and gas supply | C44: 48-AEO2021.35.highogs-d120120a | D44: thousands | E44: 658.6604 | F44: 672.66931 | G44: 696.22937 | H44: 714.13098 | I44: 741.75299 | J44: 761.37091 | K44: 754.85303 | L44: 739.60461 | M44: 742.00177 | N44: 740.44989 | O44: 724.60852 | P44: 722.61212 | Q44: 721.50848 | R44: 719.58472 | S44: 716.46832 | T44: 719.96906 | U44: 717.42847 | V44: 712.79492 | W44: 712.05939 | X44: 712.29938 | Y44: 710.03509 | Z44: 708.38904 | AA44: 708.26019 | AB44: 705.70605 | AC44: 703.53607 | AD44: 706.8219 | AE44: 703.31671 | AF44: 698.72473 | AG44: 701.90131 | AH44: 695.80841 | AI44: 688.55414 | AJ44: 0.001
A45: 100 Mile Electric Vehicle | B45: Light-Duty Vehicle Sales: Alternative-Fuel Light Trucks: 100 Mile Electric Vehicle: High oil and gas supply | C45: 48-AEO2021.36.highogs-d120120a | D45: thousands | E45: 0 | F45: 0 | G45: 0 | H45: 0 | I45: 0 | J45: 0 | K45: 0 | L45: 0 | M45: 0 | N45: 0 | O45: 0 | P45: 0 | Q45: 0 | R45: 0 | S45: 0 | T45: 0 | U45: 0 | V45: 0 | W45: 0 | X45: 0 | Y45: 0 | Z45: 0 | AA45: 0 | AB45: 0 | AC45: 0 | AD45: 0 | AE45: 0 | AF45: 0 | AG45: 0 | AH45: 0 | AI45: 0 | AJ45: - -
A46: 200 Mile Electric Vehicle | B46: Light-Duty Vehicle Sales: Alternative-Fuel Light Trucks: 200 Mile Electric Vehicle: High oil and gas supply | C46: 48-AEO2021.37.highogs-d120120a | D46: thousands | E46: 11.011377 | F46: 12.580558 | G46: 13.856382 | H46: 14.729568 | I46: 17.766371 | J46: 20.60214 | K46: 23.901951 | L46: 26.800146 | M46: 30.963303 | N46: 35.67075 | O46: 39.973484 | P46: 45.244709 | Q46: 51.161358 | R46: 57.174721 | S46: 63.200184 | T46: 69.40493 | U46: 75.094666 | V46: 80.330345 | W46: 85.896759 | X46: 91.319008 | Y46: 96.360229 | Z46: 101.13458 | AA46: 106.0079 | AB46: 110.53382 | AC46: 115.07858 | AD46: 120.59669 | AE46: 124.79433 | AF46: 128.80905 | AG46: 134.22469 | AH46: 138.1029 | AI46: 141.6815 | AJ46: 0.089
A47: 300 Mile Electric Vehicle | B47: Light-Duty Vehicle Sales: Alternative-Fuel Light Trucks: 300 Mile Electric Vehicle: High oil and gas supply | C47: 48-AEO2021.38.highogs-d120120a | D47: thousands | E47: 25.837799 | F47: 31.257812 | G47: 36.313629 | H47: 41.621761 | I47: 48.076756 | J47: 52.63586 | K47: 55.501873 | L47: 60.360519 | M47: 68.817986 | N47: 78.638527 | O47: 91.469398 | P47: 104.87369 | Q47: 121.0077 | R47: 137.83313 | S47: 156.39168 | T47: 175.18623 | U47: 193.61909 | V47: 212.34343 | W47: 232.89964 | X47: 252.66898 | Y47: 272.35217 | Z47: 286.00415 | AA47: 298.94357 | AB47: 311.78906 | AC47: 325.64084 | AD47: 343.58066 | AE47: 357.28461 | AF47: 370.97598 | AG47: 388.95462 | AH47: 404.65668 | AI47: 419.97311 | AJ47: 0.097
A48: Plug-in 10 Gasoline Hybrid | B48: Light-Duty Vehicle Sales: Alternative-Fuel Light Trucks: Plug-in 10 Gasoline Hybrid: High oil and gas supply | C48: 48-AEO2021.39.highogs-d120120a | D48: thousands | E48: 3.735878 | F48: 4.15414 | G48: 4.319993 | H48: 4.489612 | I48: 4.84607 | J48: 5.018435 | K48: 5.088077 | L48: 5.61109 | M48: 6.357627 | N48: 7.138061 | O48: 7.837564 | P48: 8.649984 | Q48: 9.527521 | R48: 10.36993 | S48: 11.207824 | T48: 12.104683 | U48: 12.992331 | V48: 13.974369 | W48: 15.18399 | X48: 16.544401 | Y48: 18.060143 | Z48: 19.723482 | AA48: 21.642765 | AB48: 23.778744 | AC48: 26.269089 | AD48: 29.479753 | AE48: 32.905865 | AF48: 36.874756 | AG48: 41.898773 | AH48: 47.256931 | AI48: 53.308647 | AJ48: 0.093
A49: Plug-in 40 Gasoline Hybrid | B49: Light-Duty Vehicle Sales: Alternative-Fuel Light Trucks: Plug-in 40 Gasoline Hybrid: High oil and gas supply | C49: 48-AEO2021.40.highogs-d120120a | D49: thousands | E49: 20.528244 | F49: 24.63999 | G49: 24.848988 | H49: 23.036037 | I49: 21.596161 | J49: 39.537579 | K49: 117.66729 | L49: 136.5762 | M49: 138.54099 | N49: 138.30026 | O49: 138.9269 | P49: 141.40266 | Q49: 145.65279 | R49: 149.34206 | S49: 152.88683 | T49: 156.19411 | U49: 157.88142 | V49: 159.08707 | W49: 161.10991 | X49: 162.46274 | Y49: 163.21619 | Z49: 162.86559 | AA49: 162.49562 | AB49: 161.73109 | AC49: 161.12625 | AD49: 161.92609 | AE49: 160.60345 | AF49: 158.96166 | AG49: 158.86812 | AH49: 157.11867 | AI49: 154.92442 | AJ49: 0.07
A50: Electric-Diesel Hybrid | B50: Light-Duty Vehicle Sales: Alternative-Fuel Light Trucks: Electric-Diesel Hybrid: High oil and gas supply | C50: 48-AEO2021.41.highogs-d120120a | D50: thousands | E50: 0 | F50: 0 | G50: 0 | H50: 0 | I50: 0 | J50: 0 | K50: 0 | L50: 0 | M50: 0 | N50: 0 | O50: 0 | P50: 0 | Q50: 0 | R50: 0 | S50: 0 | T50: 0 | U50: 0 | V50: 0 | W50: 0 | X50: 0 | Y50: 0 | Z50: 0 | AA50: 0 | AB50: 0 | AC50: 0 | AD50: 0 | AE50: 0 | AF50: 0 | AG50: 0 | AH50: 0 | AI50: 0 | AJ50: - -
A51: Electric-Gasoline Hybrid | B51: Light-Duty Vehicle Sales: Alternative-Fuel Light Trucks: Electric-Gasoline Hybrid: High oil and gas supply | C51: 48-AEO2021.42.highogs-d120120a | D51: thousands | E51: 216.35252 | F51: 258.38602 | G51: 276.32822 | H51: 286.79895 | I51: 303.40158 | J51: 318.14313 | K51: 371.40854 | L51: 393.50906 | M51: 407.98377 | N51: 419.66553 | O51: 430.00949 | P51: 443.32437 | Q51: 459.16483 | R51: 473.46197 | S51: 488.19302 | T51: 503.16168 | U51: 514.92602 | V51: 525.28986 | W51: 539.41119 | X51: 552.56995 | Y51: 564.76416 | Z51: 576.14087 | AA51: 588.35791 | AB51: 599.37817 | AC51: 611.1803 | AD51: 628.86725 | AE51: 639.23828 | AF51: 649.35614 | AG51: 666.44373 | AH51: 676.7312 | AI51: 685.68152 | AJ51: 0.039
A52: Natural Gas ICE | B52: Light-Duty Vehicle Sales: Alternative-Fuel Light Trucks: Natural Gas ICE: High oil and gas supply | C52: 48-AEO2021.43.highogs-d120120a | D52: thousands | E52: 0.87621 | F52: 0.99396 | G52: 1.051358 | H52: 1.104043 | I52: 1.17157 | J52: 1.219613 | K52: 1.229416 | L52: 1.212275 | M52: 1.219368 | N52: 1.217389 | O52: 1.198273 | P52: 1.197488 | Q52: 1.201549 | R52: 1.203048 | S52: 1.20606 | T52: 1.214379 | U52: 1.215034 | V52: 1.212165 | W52: 1.217994 | X52: 1.223647 | Y52: 1.226083 | Z52: 1.228431 | AA52: 1.232571 | AB52: 1.233757 | AC52: 1.236186 | AD52: 1.249331 | AE52: 1.248434 | AF52: 1.247343 | AG52: 1.25969 | AH52: 1.257967 | AI52: 1.254231 | AJ52: 0.012
A53: Natural Gas Bi-fuel | B53: Light-Duty Vehicle Sales: Alternative-Fuel Light Trucks: Natural Gas Bi-fuel: High oil and gas supply | C53: 48-AEO2021.44.highogs-d120120a | D53: thousands | E53: 4.78173 | F53: 5.351117 | G53: 5.552428 | H53: 5.691225 | I53: 5.91367 | J53: 6.088209 | K53: 6.102009 | L53: 6.004095 | M53: 6.035657 | N53: 6.033197 | O53: 5.919284 | P53: 5.918518 | Q53: 5.928925 | R53: 5.931232 | S53: 5.925938 | T53: 5.971416 | U53: 5.971017 | V53: 5.947062 | W53: 5.960375 | X53: 5.981478 | Y53: 5.980885 | Z53: 5.981805 | AA53: 5.99493 | AB53: 5.989414 | AC53: 5.98766 | AD53: 6.03448 | AE53: 6.021496 | AF53: 6.00085 | AG53: 6.047012 | AH53: 6.016849 | AI53: 5.976843 | AJ53: 0.007
A54: Propane ICE | B54: Light-Duty Vehicle Sales: Alternative-Fuel Light Trucks: Propane ICE: High oil and gas supply | C54: 48-AEO2021.45.highogs-d120120a | D54: thousands | E54: 0.896776 | F54: 1.05261 | G54: 1.111326 | H54: 1.151744 | I54: 1.203437 | J54: 1.242741 | K54: 1.266402 | L54: 1.268268 | M54: 1.290204 | N54: 1.307028 | O54: 1.301395 | P54: 1.309787 | Q54: 1.32857 | R54: 1.345282 | S54: 1.369719 | T54: 1.390582 | U54: 1.403345 | V54: 1.413517 | W54: 1.437301 | X54: 1.460814 | Y54: 1.48447 | Z54: 1.50961 | AA54: 1.535431 | AB54: 1.565146 | AC54: 1.59473 | AD54: 1.645246 | AE54: 1.670202 | AF54: 1.696109 | AG54: 1.738963 | AH54: 1.768739 | AI54: 1.797183 | AJ54: 0.023
A55: Propane Bi-fuel | B55: Light-Duty Vehicle Sales: Alternative-Fuel Light Trucks: Propane Bi-fuel: High oil and gas supply | C55: 48-AEO2021.46.highogs-d120120a | D55: thousands | E55: 3.090303 | F55: 3.458326 | G55: 3.588009 | H55: 3.677521 | I55: 3.820937 | J55: 3.933555 | K55: 3.942421 | L55: 3.87901 | M55: 3.899145 | N55: 3.897336 | O55: 3.82362 | P55: 3.822982 | Q55: 3.829474 | R55: 3.830739 | S55: 3.82691 | T55: 3.85623 | U55: 3.855715 | V55: 3.839862 | W55: 3.848069 | X55: 3.861467 | Y55: 3.860712 | Z55: 3.860967 | AA55: 3.869175 | AB55: 3.865335 | AC55: 3.863787 | AD55: 3.893517 | AE55: 3.884741 | AF55: 3.870961 | AG55: 3.900309 | AH55: 3.880196 | AI55: 3.853823 | AJ55: 0.007
A56: Fuel Cell Methanol | B56: Light-Duty Vehicle Sales: Alternative-Fuel Light Trucks: Fuel Cell Methanol: High oil and gas supply | C56: 48-AEO2021.47.highogs-d120120a | D56: thousands | E56: 0 | F56: 0 | G56: 0 | H56: 0 | I56: 0 | J56: 0 | K56: 0 | L56: 0 | M56: 0 | N56: 0 | O56: 0 | P56: 0 | Q56: 0 | R56: 0 | S56: 0 | T56: 0 | U56: 0 | V56: 0 | W56: 0 | X56: 0 | Y56: 0 | Z56: 0 | AA56: 0 | AB56: 0 | AC56: 0 | AD56: 0 | AE56: 0 | AF56: 0 | AG56: 0 | AH56: 0 | AI56: 0 | AJ56: - -
A57: Fuel Cell Hydrogen | B57: Light-Duty Vehicle Sales: Alternative-Fuel Light Trucks: Fuel Cell Hydrogen: High oil and gas supply | C57: 48-AEO2021.48.highogs-d120120a | D57: thousands | E57: 0.005264 | F57: 0.007763 | G57: 0.010618 | H57: 0.014217 | I57: 0.01919 | J57: 0.02647 | K57: 0.033589 | L57: 0.04159 | M57: 0.05206 | N57: 0.063929 | O57: 0.076158 | P57: 0.090309 | Q57: 0.105613 | R57: 0.121169 | S57: 0.13674 | T57: 0.152821 | U57: 0.167339 | V57: 0.180473 | W57: 0.193919 | X57: 0.20664 | Y57: 0.218224 | Z57: 0.229347 | AA57: 0.24035 | AB57: 0.250425 | AC57: 0.260603 | AD57: 0.273087 | AE57: 0.28232 | AF57: 0.291079 | AG57: 0.302643 | AH57: 0.310832 | AI57: 0.31805 | AJ57: 0.146
A58: Total Alternative Light Trucks | B58: Light-Duty Vehicle Sales: Alternative-Fuel Light Trucks: Total: High oil and gas supply | C58: 48-AEO2021.49.highogs-d120120a | D58: thousands | E58: 945.77661 | F58: 1014.5516 | G58: 1063.2103 | H58: 1096.4454 | I58: 1149.5688 | J58: 1209.8187 | K58: 1340.9945 | L58: 1374.8669 | M58: 1407.1617 | N58: 1432.382 | O58: 1445.144 | P58: 1478.4467 | Q58: 1520.4169 | R58: 1560.198 | S58: 1600.8132 | T58: 1648.6062 | U58: 1684.5546 | V58: 1716.413 | W58: 1759.2184 | X58: 1800.5984 | Y58: 1837.5584 | Z58: 1867.068 | AA58: 1898.5803 | AB58: 1925.821 | AC58: 1955.7743 | AD58: 2004.368 | AE58: 2031.2504 | AF58: 2056.8086 | AG58: 2105.5398 | AH58: 2132.9094 | AI58: 2157.3237 | AJ58: 0.028
A59: Percent Alternative Light Truck Sales | B59: Light-Duty Vehicle Sales: Percent Alternative Light Truck Sales: High oil and gas supply | C59: 48-AEO2021.51.highogs-d120120a | D59: percent | E59: 12.603731 | F59: 12.086465 | G59: 12.209526 | H59: 12.28522 | I59: 12.397017 | J59: 12.673083 | K59: 14.016348 | L59: 14.606309 | M59: 14.8725 | N59: 15.146613 | O59: 15.577128 | P59: 15.938383 | Q59: 16.363634 | R59: 16.7866 | S59: 17.241961 | T59: 17.621176 | U59: 18.007923 | V59: 18.424269 | W59: 18.843922 | X59: 19.220327 | Y59: 19.619257 | Z59: 19.933451 | AA59: 20.227066 | AB59: 20.538624 | AC59: 20.867033 | AD59: 21.223494 | AE59: 21.556913 | AF59: 21.906378 | AG59: 22.256832 | AH59: 22.663937 | AI59: 23.081156 | AJ59: 0.02
A60: Total New Light Truck Sales | B60: Light-Duty Vehicle Sales: Total New Truck: High oil and gas supply | C60: 48-AEO2021.52.highogs-d120120a | D60: thousands | E60: 7503.9414 | F60: 8394.1143 | G60: 8708.0391 | H60: 8924.915 | I60: 9272.9473 | J60: 9546.3652 | K60: 9567.3604 | L60: 9412.8291 | M60: 9461.501 | N60: 9456.7803 | O60: 9277.3457 | P60: 9276.0137 | Q60: 9291.4375 | R60: 9294.3057 | S60: 9284.4033 | T60: 9355.8242 | U60: 9354.5186 | V60: 9316.0439 | W60: 9335.7334 | X60: 9368.1982 | Y60: 9366.0957 | Z60: 9366.5068 | AA60: 9386.3359 | AB60: 9376.583 | AC60: 9372.5557 | AD60: 9444.1006 | AE60: 9422.7324 | AF60: 9389.0859 | AG60: 9460.1953 | AH60: 9411.0273 | AI60: 9346.6885 | AJ60: 0.007
A61: Percent Total Alternative Sales | B61: Light-Duty Vehicle Sales: Percent Total Alternative Sales: High oil and gas supply | C61: 48-AEO2021.54.highogs-d120120a | D61: percent | E61: 10.525676 | F61: 10.205821 | G61: 10.303618 | H61: 10.468798 | I61: 10.682898 | J61: 10.995588 | K61: 12.012916 | L61: 12.589248 | M61: 13.007057 | N61: 13.377918 | O61: 13.867725 | P61: 14.342594 | Q61: 14.859269 | R61: 15.397581 | S61: 15.965017 | T61: 16.496569 | U61: 17.015959 | V61: 17.563627 | W61: 18.121334 | X61: 18.648632 | Y61: 19.184069 | Z61: 19.630735 | AA61: 20.046778 | AB61: 20.477114 | AC61: 20.930143 | AD61: 21.414234 | AE61: 21.890434 | AF61: 22.370344 | AG61: 22.860004 | AH61: 23.398972 | AI61: 23.964218 | AJ61: 0.028
A62: EPACT Legislative Alternative Sales | B62: Light-Duty Vehicle Sales: EPACT Legislative Alternative Sales: High oil and gas supply | C62: 48-AEO2021.55.highogs-d120120a | D62: thousands | E62: 80.883011 | F62: 90.649094 | G62: 97.449028 | H62: 101.7138 | I62: 108.75757 | J62: 115.22839 | K62: 119.69295 | L62: 122.76823 | M62: 129.10582 | N62: 135.23233 | O62: 139.99101 | P62: 146.33977 | Q62: 152.87483 | R62: 158.91075 | S62: 164.60355 | T62: 170.33884 | U62: 174.24127 | V62: 177.27837 | W62: 181.0916 | X62: 184.44444 | Y62: 186.99703 | Z62: 189.37363 | AA62: 191.77718 | AB62: 193.48735 | AC62: 195.30904 | AD62: 198.80876 | AE62: 199.94949 | AF62: 200.75169 | AG62: 203.64053 | AH62: 204.13632 | AI62: 204.28915 | AJ62: 0.031
A63: ZEVP Legislative Alternative Sales | B63: Light-Duty Vehicle Sales: ZEVP Legislative Alternative Sales: High oil and gas supply | C63: 48-AEO2021.56.highogs-d120120a | D63: thousands | E63: 0 | F63: 0 | G63: 0 | H63: 0 | I63: 0 | J63: 0 | K63: 0 | L63: 0 | M63: 0 | N63: 0 | O63: 0 | P63: 0 | Q63: 0 | R63: 0 | S63: 0 | T63: 0 | U63: 0 | V63: 0 | W63: 0 | X63: 0 | Y63: 0 | Z63: 0 | AA63: 0 | AB63: 0 | AC63: 0 | AD63: 0 | AE63: 0 | AF63: 0 | AG63: 0 | AH63: 0 | AI63: 0 | AJ63: - -
A64: Total Sales | B64: Cars and Light Trucks | D64: 48-AEO2021.58.
A65: Conventional Gasoline | B65: Light-Duty Vehicle Sales: Total Sales, Cars and Light Trucks: Conventional Gasoline: High oil and gas supply | C65: 48-AEO2021.59.highogs-d120120a | D65: thousands | E65: 10942.051 | F65: 12061.861 | G65: 12768.612 | H65: 12994.024 | I65: 13343.117 | J65: 13584.045 | K65: 13388.438 | L65: 13085.346 | M65: 13100.29 | N65: 13059.418 | O65: 12867.778 | P65: 12812.703 | Q65: 12778.74 | R65: 12725.466 | S65: 12671.221 | T65: 12655.05 | U65: 12537.341 | V65: 12394.869 | W65: 12335.949 | X65: 12269.731 | Y65: 12175.175 | Z65: 12097.82 | AA65: 12039.73 | AB65: 11946.957 | AC65: 11867.537 | AD65: 11890.537 | AE65: 11777.694 | AF65: 11648.64 | AG65: 11641.577 | AH65: 11493.403 | AI65: 11326.559 | AJ65: 0.001
A66: TDI Diesel | B66: Light-Duty Vehicle Sales: Total Sales, Cars and Light Trucks: TDI Diesel: High oil and gas supply | C66: 48-AEO2021.60.highogs-d120120a | D66: thousands | E66: 46.744987 | F66: 86.717842 | G66: 118.99736 | H66: 111.96023 | I66: 112.83137 | J66: 118.95527 | K66: 114.04425 | L66: 110.42281 | M66: 114.56205 | N66: 115.5425 | O66: 113.62711 | P66: 113.97608 | Q66: 116.01392 | R66: 115.89001 | S66: 119.07026 | T66: 119.28082 | U66: 121.36752 | V66: 120.28741 | W66: 120.38907 | X66: 122.76766 | Y66: 120.45693 | Z66: 120.48299 | AA66: 120.25109 | AB66: 119.98519 | AC66: 119.50639 | AD66: 120.97152 | AE66: 119.29042 | AF66: 118.38474 | AG66: 118.5109 | AH66: 117.47234 | AI66: 115.80009 | AJ66: 0.031
A67: Flex-Fuel | B67: Light-Duty Vehicle Sales: Total Sales, Cars and Light Trucks: Flex-Fuel: High oil and gas supply | C67: 48-AEO2021.61.highogs-d120120a | D67: thousands | E67: 741.52612 | F67: 761.44757 | G67: 794.11713 | H67: 812.88049 | I67: 841.62915 | J67: 861.97113 | K67: 853.9223 | L67: 836.68494 | M67: 839.4541 | N67: 837.96906 | O67: 822.4093 | P67: 820.42053 | Q67: 819.52374 | R67: 817.65137 | S67: 814.89404 | T67: 818.04877 | U67: 814.32819 | V67: 808.63562 | W67: 807.59265 | X67: 807.14594 | Y67: 804.11517 | Z67: 801.85773 | AA67: 801.11798 | AB67: 797.7569 | AC67: 795.00549 | AD67: 798.67047 | AE67: 794.20099 | AF67: 788.526 | AG67: 791.47217 | AH67: 784.27527 | AI67: 775.80414 | AJ67: 0.002
A68: Electric | B68: Light-Duty Vehicle Sales: Total Sales, Cars and Light Trucks: Electric: High oil and gas supply | C68: 48-AEO2021.62.highogs-d120120a | D68: thousands | E68: 149.72099 | F68: 146.62964 | G68: 164.22925 | H68: 174.55832 | I68: 189.21509 | J68: 200.48154 | K68: 212.06589 | L68: 227.0219 | M68: 254.38696 | N68: 285.69641 | O68: 325.16159 | P68: 371.09552 | Q68: 420.95209 | R68: 476.18491 | S68: 536.15985 | T68: 597.21497 | U68: 651.16888 | V68: 707.03863 | W68: 769.55023 | X68: 829.25708 | Y68: 886.46777 | Z68: 930.53937 | AA68: 972.78314 | AB68: 1013.1821 | AC68: 1057.4216 | AD68: 1114.9769 | AE68: 1159.2582 | AF68: 1200.5282 | AG68: 1255.7728 | AH68: 1301.0726 | AI68: 1347.4221 | AJ68: 0.076
A69: Plug-in Electric Hybrid | B69: Light-Duty Vehicle Sales: Total Sales, Cars and Light Trucks: Plug-in Electric Hybrid: High oil and gas supply | C69: 48-AEO2021.63.highogs-d120120a | D69: thousands | E69: 50.24918 | F69: 62.601456 | G69: 68.361328 | H69: 69.090996 | I69: 72.821815 | J69: 97.536247 | K69: 182.16153 | L69: 209.63751 | M69: 223.66818 | N69: 227.8342 | O69: 233.44058 | P69: 237.59985 | Q69: 245.30843 | R69: 251.16927 | S69: 257.34348 | T69: 260.68552 | U69: 262.24948 | V69: 263.34875 | W69: 265.94437 | X69: 267.01932 | Y69: 267.98041 | Z69: 267.13684 | AA69: 266.31342 | AB69: 265.40338 | AC69: 265.18543 | AD69: 268.03763 | AE69: 267.40503 | AF69: 267.16458 | AG69: 270.04047 | AH69: 271.38596 | AI69: 272.71597 | AJ69: 0.058
A70: Electric Hybrid | B70: Light-Duty Vehicle Sales: Total Sales, Cars and Light Trucks: Electric Hybrid: High oil and gas supply | C70: 48-AEO2021.64.highogs-d120120a | D70: thousands | E70: 337.74976 | F70: 395.29581 | G70: 437.94873 | H70: 459.6991 | I70: 488.88922 | J70: 515.52167 | K70: 577.94104 | L70: 609.95471 | M70: 640.95709 | N70: 665.74487 | O70: 691.68256 | P70: 717.84759 | Q70: 747.04871 | R70: 774.35492 | S70: 803.62286 | T70: 829.62311 | U70: 849.84772 | V70: 869.34857 | W70: 895.56598 | X70: 919.10761 | Y70: 941.85327 | Z70: 966.49347 | AA70: 990.22009 | AB70: 1012.4028 | AC70: 1036.8658 | AD70: 1072.614 | AE70: 1094.5089 | AF70: 1115.8781 | AG70: 1148.7867 | AH70: 1171.0525 | AI70: 1191.4612 | AJ70: 0.043
A71: Gaseous (Propane and Natural Gas) | B71: Light-Duty Vehicle Sales: Total Sales, Cars and Light Trucks: Gaseous: High oil and gas supply | C71: 48-AEO2021.65.highogs-d120120a | D71: thousands | E71: 13.282132 | F71: 14.615747 | G71: 15.541418 | H71: 15.980041 | I71: 16.559818 | J71: 16.997454 | K71: 16.999275 | L71: 16.745153 | M71: 16.864073 | N71: 16.887737 | O71: 16.689655 | P71: 16.733006 | Q71: 16.794474 | R71: 16.841969 | S71: 16.899963 | T71: 17.01865 | U71: 16.990221 | V71: 16.927872 | W71: 16.989555 | X71: 17.046829 | Y71: 17.056164 | Z71: 17.07863 | AA71: 17.122871 | AB71: 17.127266 | AC71: 17.151009 | AD71: 17.336123 | AE71: 17.319502 | AF71: 17.280302 | AG71: 17.426506 | AH71: 17.374092 | AI71: 17.30246 | AJ71: 0.009
A72: Fuel Cell | B72: Light-Duty Vehicle Sales: Total Sales, Cars and Light Trucks: Fuel Cell: High oil and gas supply | C72: 48-AEO2021.66.highogs-d120120a | D72: thousands | E72: 0.183592 | F72: 0.192137 | G72: 0.229748 | H72: 0.261514 | I72: 0.302468 | J72: 0.358335 | K72: 0.409308 | L72: 0.463558 | M72: 0.534861 | N72: 0.609137 | O72: 0.687017 | P72: 0.764566 | Q72: 0.841996 | R72: 0.91534 | S72: 0.987169 | T72: 1.049125 | U72: 1.096141 | V72: 1.138755 | W72: 1.185998 | X72: 1.226098 | Y72: 1.26153 | Z72: 1.296925 | AA72: 1.331168 | AB72: 1.361268 | AC72: 1.394316 | AD72: 1.442371 | AE72: 1.471271 | AF72: 1.496705 | AG72: 1.537298 | AH72: 1.56168 | AI72: 1.585036 | AJ72: 0.074
A73: Total Vehicles Sales | B73: Light-Duty Vehicle Sales: Total Vehicles Sales: High oil and gas supply | C73: 48-AEO2021.67.highogs-d120120a | D73: thousands | E73: 12281.508 | F73: 13529.361 | G73: 14368.037 | H73: 14638.455 | I73: 15065.366 | J73: 15395.867 | K73: 15345.98 | L73: 15096.276 | M73: 15190.719 | N73: 15209.702 | O73: 15071.477 | P73: 15091.14 | Q73: 15145.225 | R73: 15178.475 | S73: 15220.198 | T73: 15297.973 | U73: 15254.389 | V73: 15181.594 | W73: 15213.167 | X73: 15233.303 | Y73: 15214.366 | Z73: 15202.707 | AA73: 15208.871 | AB73: 15174.176 | AC73: 15160.067 | AD73: 15284.586 | AE73: 15231.148 | AF73: 15157.898 | AG73: 15245.124 | AH73: 15157.598 | AI73: 15048.65 | AJ73: 0.007
A74: Conventional Gasoline Microhybrids | B74: Light-Duty Vehicle Sales: Microhybrids: Conventional Gasoline: High oil and gas supply | C74: 48-AEO2021.70.highogs-d120120a | D74: thousands | E74: 4206.5107 | F74: 5090.7202 | G74: 5831.457 | H74: 6484.8428 | I74: 7171.3462 | J74: 7545.5952 | K74: 7690.3438 | L74: 7513.686 | M74: 7519.2173 | N74: 7493.8716 | O74: 7390.2344 | P74: 7354.2939 | Q74: 7334.5723 | R74: 7308.4927 | S74: 7301.7461 | T74: 7328.3877 | U74: 7319.8413 | V74: 7302.4863 | W74: 7266.2422 | X74: 7249.9067 | Y74: 7218.2168 | Z74: 7191.5996 | AA74: 7154.7363 | AB74: 7123.269 | AC74: 7097.7935 | AD74: 7115.3486 | AE74: 7052.8403 | AF74: 7000.5347 | AG74: 7014.5352 | AH74: 6932.793 | AI74: 6848.6294 | AJ74: 0.016
A75: TDI Diesel Microhybrids | B75: Light-Duty Vehicle Sales: Microhybrids: TDI Diesel: High oil and gas supply | C75: 48-AEO2021.71.highogs-d120120a | D75: thousands | E75: 0 | F75: 0 | G75: 0 | H75: 0 | I75: 0 | J75: 0 | K75: 0 | L75: 0 | M75: 0 | N75: 0 | O75: 0 | P75: 0 | Q75: 0 | R75: 0 | S75: 0 | T75: 0 | U75: 0 | V75: 0 | W75: 0 | X75: 0 | Y75: 0 | Z75: 0 | AA75: 0 | AB75: 0 | AC75: 0 | AD75: 0 | AE75: 0 | AF75: 0 | AG75: 0 | AH75: 0 | AI75: 0 | AJ75: - -
A76: Total Alternative-Fueled Vehicle Sales | B76: Light-Duty Vehicle Sales: Alternative-Fueled Vehicles: High oil and gas supply | C76: 48-AEO2021.80.highogs-d120120a | D76: thousands | E76: 5545.9668 | F76: 6558.2207 | G76: 7430.8818 | H76: 8129.2725 | I76: 8893.5957 | J76: 9357.416 | K76: 9647.8867 | L76: 9524.6172 | M76: 9609.6436 | N76: 9644.1543 | O76: 9593.9326 | P76: 9632.7305 | Q76: 9701.0566 | R76: 9761.501 | S76: 9850.7246 | T76: 9971.3096 | U76: 10036.89 | V76: 10089.213 | W76: 10143.461 | X76: 10213.478 | Y76: 10257.407 | Z76: 10296.484 | AA76: 10323.875 | AB76: 10350.488 | AC76: 10390.324 | AD76: 10509.398 | AE76: 10506.294 | AF76: 10509.794 | AG76: 10618.083 | AH76: 10596.987 | AI76: 10570.721 | AJ76: 0.022

Sheet AEO 39
E1: 2020 | F1: 2021 | G1: 2022 | H1: 2023 | I1: 2024 | J1: 2025 | K1: 2026 | L1: 2027 | M1: 2028 | N1: 2029 | O1: 2030 | P1: 2031 | Q1: 2032 | R1: 2033 | S1: 2034 | T1: 2035 | U1: 2036 | V1: 2037 | W1: 2038 | X1: 2039 | Y1: 2040 | Z1: 2041 | AA1: 2042 | AB1: 2043 | AC1: 2044 | AD1: 2045 | AE1: 2046 | AF1: 2047 | AG1: 2048 | AH1: 2049 | AI1: 2050 | AJ1: Growth (2020-2050)
A10: Table 39. Light-Duty Vehicle Stock by Technology Type
A11: https://www.eia.gov/outlooks/aeo/data/browser/#/?id=49-AEO2021&cases=highogs&sourcekey=0
A12: Mon Mar 08 2021 16:27:05 GMT-0800 (Pacific Standard Time)
A13: Source: U.S. Energy Information Administration
B14: full name | C14: api key | D14: units | E14: 2020 | F14: 2021 | G14: 2022 | H14: 2023 | I14: 2024 | J14: 2025 | K14: 2026 | L14: 2027 | M14: 2028 | N14: 2029 | O14: 2030 | P14: 2031 | Q14: 2032 | R14: 2033 | S14: 2034 | T14: 2035 | U14: 2036 | V14: 2037 | W14: 2038 | X14: 2039 | Y14: 2040 | Z14: 2041 | AA14: 2042 | AB14: 2043 | AC14: 2044 | AD14: 2045 | AE14: 2046 | AF14: 2047 | AG14: 2048 | AH14: 2049 | AI14: 2050 | AJ14: Growth (2020-2050)
A15: Car Stock | C15: 49-AEO2021.2.
A16: Conventional Cars | C16: 49-AEO2021.3.
A17: Gasoline ICE Vehicles | B17: Light-Duty Vehicle Stock: Conventional Cars: Gasoline: High oil and gas supply | C17: 49-AEO2021.4.highogs-d120120a | D17: millions | E17: 119.49128 | F17: 117.53005 | G17: 116.09448 | H17: 114.76393 | I17: 113.57511 | J17: 112.50355 | K17: 111.36626 | L17: 110.06714 | M17: 108.6679 | N17: 107.17072 | O17: 105.61605 | P17: 104.0375 | Q17: 102.47129 | R17: 100.95171 | S17: 99.520668 | T17: 98.219856 | U17: 97.014999 | V17: 95.912788 | W17: 94.916138 | X17: 93.977226 | Y17: 93.080299 | Z17: 92.244904 | AA17: 91.455658 | AB17: 90.671829 | AC17: 89.905533 | AD17: 89.167786 | AE17: 88.391335 | AF17: 87.578125 | AG17: 86.772827 | AH17: 85.931778 | AI17: 85.049469 | AJ17: -0.011
A18: TDI Diesel ICE | B18: Light-Duty Vehicle Stock: Conventional Cars: TDI Diesel: High oil and gas supply | C18: 49-AEO2021.5.highogs-d120120a | D18: millions | E18: 0.551319 | F18: 0.515414 | G18: 0.480832 | H18: 0.44735 | I18: 0.415208 | J18: 0.383916 | K18: 0.352652 | L18: 0.320655 | M18: 0.288553 | N18: 0.256094 | O18: 0.223867 | P18: 0.193736 | Q18: 0.166132 | R18: 0.141886 | S18: 0.120139 | T18: 0.100964 | U18: 0.083839 | V18: 0.069611 | W18: 0.057764 | X18: 0.04892 | Y18: 0.042733 | Z18: 0.037966 | AA18: 0.033834 | AB18: 0.030226 | AC18: 0.027049 | AD18: 0.024248 | AE18: 0.02175 | AF18: 0.019524 | AG18: 0.017538 | AH18: 0.015767 | AI18: 0.014186 | AJ18: -0.115
A19: Total Conventional Cars | B19: Light-Duty Vehicle Stock: Conventional Cars: Total: High oil and gas supply | C19: 49-AEO2021.6.highogs-d120120a | D19: millions | E19: 120.0426 | F19: 118.04546 | G19: 116.57531 | H19: 115.21128 | I19: 113.99032 | J19: 112.88747 | K19: 111.71891 | L19: 110.38779 | M19: 108.95645 | N19: 107.42681 | O19: 105.83992 | P19: 104.23123 | Q19: 102.63742 | R19: 101.0936 | S19: 99.640808 | T19: 98.320824 | U19: 97.098839 | V19: 95.982399 | W19: 94.9739 | X19: 94.026146 | Y19: 93.123032 | Z19: 92.282867 | AA19: 91.489494 | AB19: 90.702057 | AC19: 89.932579 | AD19: 89.192032 | AE19: 88.413086 | AF19: 87.597649 | AG19: 86.790367 | AH19: 85.947548 | AI19: 85.063652 | AJ19: -0.011
A20: Alternative-Fuel Cars | C20: 49-AEO2021.8.
A21: Ethanol-Flex Fuel ICE | B21: Light-Duty Vehicle Stock: Alternative-Fuel Cars: Ethanol-Flex Fuel ICE: High oil and gas supply | C21: 49-AEO2021.9.highogs-d120120a | D21: millions | E21: 4.81977 | F21: 4.75031 | G21: 4.667916 | H21: 4.561073 | I21: 4.432448 | J21: 4.280411 | K21: 4.102745 | L21: 3.896137 | M21: 3.672335 | N21: 3.436058 | O21: 3.202705 | P21: 2.983507 | Q21: 2.783921 | R21: 2.603633 | S21: 2.451389 | T21: 2.322662 | U21: 2.21371 | V21: 2.129753 | W21: 2.064152 | X21: 2.012091 | Y21: 1.970178 | Z21: 1.935312 | AA21: 1.904843 | AB21: 1.877278 | AC21: 1.852057 | AD21: 1.829285 | AE21: 1.807348 | AF21: 1.786069 | AG21: 1.766213 | AH21: 1.746753 | AI21: 1.72748 | AJ21: -0.034
A22: 100 Mile Electric Vehicle | B22: Light-Duty Vehicle Stock: Alternative-Fuel Cars: 100 Mile Electric Vehicle: High oil and gas supply | C22: 49-AEO2021.10.highogs-d120120a | D22: millions | E22: 0.2087 | F22: 0.207682 | G22: 0.20613 | H22: 0.203787 | I22: 0.200711 | J22: 0.196726 | K22: 0.191489 | L22: 0.184551 | M22: 0.175948 | N22: 0.165944 | O22: 0.154299 | P22: 0.142059 | Q22: 0.129521 | R22: 0.117654 | S22: 0.106675 | T22: 0.097341 | U22: 0.089383 | V22: 0.082894 | W22: 0.077835 | X22: 0.074072 | Y22: 0.071455 | Z22: 0.069826 | AA22: 0.068859 | AB22: 0.068306 | AC22: 0.067978 | AD22: 0.067785 | AE22: 0.067623 | AF22: 0.067468 | AG22: 0.067344 | AH22: 0.067206 | AI22: 0.06704 | AJ22: -0.037
A23: 200 Mile Electric Vehicle | B23: Light-Duty Vehicle Stock: Alternative-Fuel Cars: 200 Mile Electric Vehicle: High oil and gas supply | C23: 49-AEO2021.11.highogs-d120120a | D23: millions | E23: 0.179655 | F23: 0.222129 | G23: 0.265959 | H23: 0.306464 | I23: 0.345079 | J23: 0.383168 | K23: 0.420106 | L23: 0.457544 | M23: 0.497239 | N23: 0.539716 | O23: 0.586851 | P23: 0.637604 | Q23: 0.692626 | R23: 0.752084 | S23: 0.815655 | T23: 0.882624 | U23: 0.952152 | V23: 1.025126 | W23: 1.102357 | X23: 1.183562 | Y23: 1.268491 | Z23: 1.356409 | AA23: 1.447242 | AB23: 1.540664 | AC23: 1.637078 | AD23: 1.737926 | AE23: 1.839939 | AF23: 1.942668 | AG23: 2.047268 | AH23: 2.152572 | AI23: 2.258034 | AJ23: 0.088
A24: 300 Mile Electric Vehicle | B24: Light-Duty Vehicle Stock: Alternative-Fuel Cars: 300 Mile Electric Vehicle: High oil and gas supply | C24: 49-AEO2021.12.highogs-d120120a | D24: millions | E24: 0.393782 | F24: 0.450104 | G24: 0.514506 | H24: 0.583989 | I24: 0.658225 | J24: 0.734493 | K24: 0.814564 | L24: 0.897842 | M24: 0.98908 | N24: 1.088617 | O24: 1.199078 | P24: 1.325061 | Q24: 1.465496 | R24: 1.622568 | S24: 1.799316 | T24: 1.998155 | U24: 2.21509 | V24: 2.452539 | W24: 2.714334 | X24: 2.997294 | Y24: 3.298755 | Z24: 3.613152 | AA24: 3.938946 | AB24: 4.273924 | AC24: 4.618994 | AD24: 4.977958 | AE24: 5.34427 | AF24: 5.713794 | AG24: 6.091805 | AH24: 6.47155 | AI24: 6.853736 | AJ24: 0.1
A25: Plug-in 10 Gasoline Hybrid | B25: Light-Duty Vehicle Stock: Alternative-Fuel Cars: Plug-in 10 Gasoline Hybrid: High oil and gas supply | C25: 49-AEO2021.13.highogs-d120120a | D25: millions | E25: 0.330181 | F25: 0.355496 | G25: 0.385448 | H25: 0.417252 | I25: 0.452909 | J25: 0.493805 | K25: 0.539306 | L25: 0.590244 | M25: 0.64921 | N25: 0.707933 | O25: 0.766922 | P25: 0.823085 | Q25: 0.87772 | R25: 0.93003 | S25: 0.981125 | T25: 1.029431 | U25: 1.075437 | V25: 1.119067 | W25: 1.15967 | X25: 1.19589 | Y25: 1.228204 | Z25: 1.255648 | AA25: 1.277728 | AB25: 1.294246 | AC25: 1.305044 | AD25: 1.311235 | AE25: 1.311623 | AF25: 1.306822 | AG25: 1.29775 | AH25: 1.28458 | AI25: 1.267598 | AJ25: 0.046
A26: Plug-in 40 Gasoline Hybrid | B26: Light-Duty Vehicle Stock: Alternative-Fuel Cars: Plug-in 40 Gasoline Hybrid: High oil and gas supply | C26: 49-AEO2021.14.highogs-d120120a | D26: millions | E26: 0.176629 | F26: 0.180273 | G26: 0.183 | H26: 0.184397 | I26: 0.184856 | J26: 0.184411 | K26: 0.182986 | L26: 0.180337 | M26: 0.176455 | N26: 0.171531 | O26: 0.166233 | P26: 0.160729 | Q26: 0.154849 | R26: 0.149003 | S26: 0.143009 | T26: 0.137811 | U26: 0.133569 | V26: 0.130784 | W26: 0.12888 | X26: 0.12791 | Y26: 0.127519 | Z26: 0.127738 | AA26: 0.128545 | AB26: 0.129651 | AC26: 0.130829 | AD26: 0.132134 | AE26: 0.133228 | AF26: 0.134071 | AG26: 0.134714 | AH26: 0.1351 | AI26: 0.135216 | AJ26: -0.009
A27: Electric-Diesel Hybrid | B27: Light-Duty Vehicle Stock: Alternative-Fuel Cars: Electric-Diesel Hybrid: High oil and gas supply | C27: 49-AEO2021.15.highogs-d120120a | D27: millions | E27: 0 | F27: 0 | G27: 0 | H27: 0 | I27: 0 | J27: 0 | K27: 0 | L27: 0 | M27: 0 | N27: 0 | O27: 0 | P27: 0 | Q27: 0 | R27: 0 | S27: 0 | T27: 0 | U27: 0 | V27: 0 | W27: 0 | X27: 0 | Y27: 0 | Z27: 0 | AA27: 0 | AB27: 0 | AC27: 0 | AD27: 0 | AE27: 0 | AF27: 0 | AG27: 0 | AH27: 0 | AI27: 0 | AJ27: - -
A28: Electric-Gasoline Hybrid | B28: Light-Duty Vehicle Stock: Alternative-Fuel Cars: Electric-Gasoline Hybrid: High oil and gas supply | C28: 49-AEO2021.16.highogs-d120120a | D28: millions | E28: 3.824201 | F28: 3.84422 | G28: 3.867943 | H28: 3.884074 | I28: 3.895516 | J28: 3.900524 | K28: 3.899959 | L28: 3.892796 | M28: 3.887737 | N28: 3.885102 | O28: 3.894004 | P28: 3.916075 | Q28: 3.955119 | R28: 4.013962 | S28: 4.090826 | T28: 4.188008 | U28: 4.300179 | V28: 4.429059 | W28: 4.573664 | X28: 4.729132 | Y28: 4.892908 | Z28: 5.06664 | AA28: 5.247162 | AB28: 5.431897 | AC28: 5.62186 | AD28: 5.819934 | AE28: 6.019128 | AF28: 6.219126 | AG28: 6.424462 | AH28: 6.631048 | AI28: 6.83834 | AJ28: 0.02
A29: Natural Gas ICE | B29: Light-Duty Vehicle Stock: Alternative-Fuel Cars: Natural Gas ICE: High oil and gas supply | C29: 49-AEO2021.17.highogs-d120120a | D29: millions | E29: 0.015593 | F29: 0.014617 | G29: 0.013816 | H29: 0.013116 | I29: 0.012489 | J29: 0.011909 | K29: 0.011371 | L29: 0.010848 | M29: 0.010378 | N29: 0.009943 | O29: 0.009573 | P29: 0.009277 | Q29: 0.009031 | R29: 0.008845 | S29: 0.008714 | T29: 0.008628 | U29: 0.008555 | V29: 0.00848 | W29: 0.008442 | X29: 0.00839 | Y29: 0.008345 | Z29: 0.008304 | AA29: 0.008261 | AB29: 0.00825 | AC29: 0.008246 | AD29: 0.008248 | AE29: 0.008241 | AF29: 0.008226 | AG29: 0.008212 | AH29: 0.008192 | AI29: 0.008169 | AJ29: -0.021
A30: Natural Gas Bi-fuel | B30: Light-Duty Vehicle Stock: Alternative-Fuel Cars: Natural Gas Bi-fuel: High oil and gas supply | C30: 49-AEO2021.18.highogs-d120120a | D30: millions | E30: 0.03605 | F30: 0.034826 | G30: 0.033961 | H30: 0.033183 | I30: 0.032493 | J30: 0.031749 | K30: 0.030946 | L30: 0.030037 | M30: 0.029102 | N30: 0.028146 | O30: 0.027256 | P30: 0.026449 | Q30: 0.025729 | R30: 0.025128 | S30: 0.024669 | T30: 0.024299 | U30: 0.023954 | V30: 0.023628 | W30: 0.023384 | X30: 0.023156 | Y30: 0.022946 | Z30: 0.022763 | AA30: 0.022592 | AB30: 0.022515 | AC30: 0.02246 | AD30: 0.022462 | AE30: 0.022443 | AF30: 0.022402 | AG30: 0.022373 | AH30: 0.02233 | AI30: 0.022273 | AJ30: -0.016
A31: Propane ICE | B31: Light-Duty Vehicle Stock: Alternative-Fuel Cars: Propane ICE: High oil and gas supply | C31: 49-AEO2021.19.highogs-d120120a | D31: millions | E31: 0.003385 | F31: 0.003453 | G31: 0.003601 | H31: 0.003778 | I31: 0.003951 | J31: 0.004123 | K31: 0.004289 | L31: 0.004447 | M31: 0.004609 | N31: 0.004771 | O31: 0.004924 | P31: 0.005083 | Q31: 0.005235 | R31: 0.005383 | S31: 0.005524 | T31: 0.005659 | U31: 0.005772 | V31: 0.005869 | W31: 0.00596 | X31: 0.006046 | Y31: 0.006119 | Z31: 0.006186 | AA31: 0.006252 | AB31: 0.006286 | AC31: 0.006348 | AD31: 0.00642 | AE31: 0.006488 | AF31: 0.006549 | AG31: 0.00661 | AH31: 0.006666 | AI31: 0.006717 | AJ31: 0.023
A32: Propane Bi-fuel | B32: Light-Duty Vehicle Stock: Alternative-Fuel Cars: Propane Bi-fuel: High oil and gas supply | C32: 49-AEO2021.20.highogs-d120120a | D32: millions | E32: 0.006075 | F32: 0.006042 | G32: 0.006111 | H32: 0.006208 | I32: 0.006301 | J32: 0.006386 | K32: 0.00646 | L32: 0.006519 | M32: 0.006577 | N32: 0.006629 | O32: 0.006673 | P32: 0.006712 | Q32: 0.006745 | R32: 0.00678 | S32: 0.00682 | T32: 0.006855 | U32: 0.006875 | V32: 0.006886 | W32: 0.006894 | X32: 0.0069 | Y32: 0.006896 | Z32: 0.006889 | AA32: 0.006882 | AB32: 0.00682 | AC32: 0.006809 | AD32: 0.006816 | AE32: 0.006816 | AF32: 0.006806 | AG32: 0.006798 | AH32: 0.006785 | AI32: 0.006767 | AJ32: 0.004
A33: Fuel Cell Methanol | B33: Light-Duty Vehicle Stock: Alternative-Fuel Cars: Fuel Cell Methanol: High oil and gas supply | C33: 49-AEO2021.21.highogs-d120120a | D33: millions | E33: 0 | F33: 0 | G33: 0 | H33: 0 | I33: 0 | J33: 0 | K33: 0 | L33: 0 | M33: 0 | N33: 0 | O33: 0 | P33: 0 | Q33: 0 | R33: 0 | S33: 0 | T33: 0 | U33: 0 | V33: 0 | W33: 0 | X33: 0 | Y33: 0 | Z33: 0 | AA33: 0 | AB33: 0 | AC33: 0 | AD33: 0 | AE33: 0 | AF33: 0 | AG33: 0 | AH33: 0 | AI33: 0 | AJ33: - -
A34: Fuel Cell Hydrogen | B34: Light-Duty Vehicle Stock: Alternative-Fuel Cars: Fuel Cell Hydrogen: High oil and gas supply | C34: 49-AEO2021.22.highogs-d120120a | D34: millions | E34: 0.007633 | F34: 0.007773 | G34: 0.00792 | H34: 0.008064 | I34: 0.008227 | J34: 0.008422 | K34: 0.008636 | L34: 0.008862 | M34: 0.009106 | N34: 0.009356 | O34: 0.009607 | P34: 0.00984 | Q34: 0.010005 | R34: 0.010155 | S34: 0.010284 | T34: 0.010482 | U34: 0.010742 | V34: 0.011088 | W34: 0.011463 | X34: 0.01189 | Y34: 0.012348 | Z34: 0.012841 | AA34: 0.013393 | AB34: 0.013969 | AC34: 0.014555 | AD34: 0.015143 | AE34: 0.015714 | AF34: 0.016263 | AG34: 0.016802 | AH34: 0.017319 | AI34: 0.017813 | AJ34: 0.029
A35: Total Alternative Cars | B35: Light-Duty Vehicle Stock: Alternative-Fuel Cars: Total: High oil and gas supply | C35: 49-AEO2021.23.highogs-d120120a | D35: millions | E35: 10.001653 | F35: 10.076924 | G35: 10.15631 | H35: 10.205386 | I35: 10.233208 | J35: 10.236128 | K35: 10.212856 | L35: 10.160166 | M35: 10.107775 | N35: 10.053744 | O35: 10.028126 | P35: 10.045481 | Q35: 10.115997 | R35: 10.245226 | S35: 10.444005 | T35: 10.711954 | U35: 11.035419 | V35: 11.425174 | W35: 11.877036 | X35: 12.376334 | Y35: 12.914163 | Z35: 13.481709 | AA35: 14.070706 | AB35: 14.673805 | AC35: 15.292259 | AD35: 15.935349 | AE35: 16.582863 | AF35: 17.230263 | AG35: 17.890352 | AH35: 18.5501 | AI35: 19.209183 | AJ35: 0.022
A36: Total Car Stock | B36: Light-Duty Vehicle Stock: Car Stock: Total: High oil and gas supply | C36: 49-AEO2021.25.highogs-d120120a | D36: millions | E36: 130.04425 | F36: 128.12239 | G36: 126.73162 | H36: 125.41666 | I36: 124.22353 | J36: 123.1236 | K36: 121.93176 | L36: 120.54796 | M36: 119.06422 | N36: 117.48055 | O36: 115.86804 | P36: 114.27671 | Q36: 112.75342 | R36: 111.33882 | S36: 110.08482 | T36: 109.03278 | U36: 108.13426 | V36: 107.40757 | W36: 106.85094 | X36: 106.40248 | Y36: 106.03719 | Z36: 105.76458 | AA36: 105.5602 | AB36: 105.37586 | AC36: 105.22484 | AD36: 105.12738 | AE36: 104.99595 | AF36: 104.82791 | AG36: 104.68072 | AH36: 104.49765 | AI36: 104.27284 | AJ36: -0.007
A37: Light Truck Stock | C37: 49-AEO2021.27.
A38: Conventional Light Trucks | C38: 49-AEO2021.28.
A39: Gasoline ICE Vehicles | B39: Light-Duty Vehicle Stock: Conventional Light Trucks: Gasoline: High oil and gas supply | C39: 49-AEO2021.29.highogs-d120120a | D39: millions | E39: 109.77512 | F39: 110.74385 | G39: 112.11185 | H39: 113.83586 | I39: 115.97203 | J39: 118.35767 | K39: 120.65992 | L39: 122.77535 | M39: 124.84524 | N39: 126.78989 | O39: 128.46132 | P39: 130.01047 | Q39: 131.39667 | R39: 132.62656 | S39: 133.67859 | T39: 134.59552 | U39: 135.30641 | V39: 135.80034 | W39: 136.15254 | X39: 136.38947 | Y39: 136.51288 | Z39: 136.56616 | AA39: 136.56909 | AB39: 136.49606 | AC39: 136.38095 | AD39: 136.2654 | AE39: 136.08591 | AF39: 135.8416 | AG39: 135.621 | AH39: 135.3295 | AI39: 134.95865 | AJ39: 0.007
A40: TDI Diesel ICE | B40: Light-Duty Vehicle Stock: Conventional Light Trucks: TDI Diesel: High oil and gas supply | C40: 49-AEO2021.30.highogs-d120120a | D40: millions | E40: 0.533402 | F40: 0.605817 | G40: 0.709082 | H40: 0.803499 | I40: 0.896429 | J40: 0.992479 | K40: 1.080195 | L40: 1.161038 | M40: 1.242479 | N40: 1.321012 | O40: 1.394312 | P40: 1.464582 | Q40: 1.532173 | R40: 1.593881 | S40: 1.652943 | T40: 1.706123 | U40: 1.755468 | V40: 1.799486 | W40: 1.840537 | X40: 1.880415 | Y40: 1.9144 | Z40: 1.945285 | AA40: 1.972792 | AB40: 1.996624 | AC40: 2.017366 | AD40: 2.037347 | AE40: 2.053565 | AF40: 2.067241 | AG40: 2.079544 | AH40: 2.089335 | AI40: 2.09616 | AJ40: 0.047
A41: Total Conventional Light Trucks | B41: Light-Duty Vehicle Stock: Conventional Light Trucks: Total: High oil and gas supply | C41: 49-AEO2021.31.highogs-d120120a | D41: millions | E41: 110.30852 | F41: 111.34967 | G41: 112.82093 | H41: 114.63936 | I41: 116.86846 | J41: 119.35015 | K41: 121.74011 | L41: 123.93639 | M41: 126.08772 | N41: 128.1109 | O41: 129.85564 | P41: 131.47505 | Q41: 132.92885 | R41: 134.22044 | S41: 135.33153 | T41: 136.30164 | U41: 137.06187 | V41: 137.59982 | W41: 137.99307 | X41: 138.26988 | Y41: 138.42728 | Z41: 138.51144 | AA41: 138.54189 | AB41: 138.49269 | AC41: 138.39831 | AD41: 138.30275 | AE41: 138.13947 | AF41: 137.90884 | AG41: 137.70055 | AH41: 137.41884 | AI41: 137.05481 | AJ41: 0.007
A42: Alternative-Fuel Light Trucks | C42: 49-AEO2021.33.
A43: Ethanol-Flex Fuel ICE | B43: Light-Duty Vehicle Stock: Alternative-Fuel Light Trucks: Ethanol-Flex Fuel ICE: High oil and gas supply | C43: 49-AEO2021.34.highogs-d120120a | D43: millions | E43: 15.7886 | F43: 15.792562 | G43: 15.765272 | H43: 15.707791 | I43: 15.623258 | J43: 15.520708 | K43: 15.389112 | L43: 15.228992 | M43: 15.067304 | N43: 14.911758 | O43: 14.753513 | P43: 14.592062 | Q43: 14.430001 | R43: 14.277225 | S43: 14.135702 | T43: 14.00994 | U43: 13.895649 | V43: 13.791718 | W43: 13.695763 | X43: 13.614037 | Y43: 13.549743 | Z43: 13.490777 | AA43: 13.439021 | AB43: 13.389459 | AC43: 13.341989 | AD43: 13.300771 | AE43: 13.258034 | AF43: 13.213305 | AG43: 13.174664 | AH43: 13.132721 | AI43: 13.08629 | AJ43: -0.006
A44: 100 Mile Electric Vehicle | B44: Light-Duty Vehicle Stock: Alternative-Fuel Light Trucks: 100 Mile Electric Vehicle: High oil and gas supply | C44: 49-AEO2021.35.highogs-d120120a | D44: millions | E44: 0.000668 | F44: 0.000601 | G44: 0.000533 | H44: 0.000432 | I44: 0.000354 | J44: 0.000299 | K44: 0.000254 | L44: 0.000221 | M44: 0.0002 | N44: 0.00018 | O44: 0.000162 | P44: 0.000144 | Q44: 0.000129 | R44: 0.000114 | S44: 0.000101 | T44: 9e-05 | U44: 7.4e-05 | V44: 6.1e-05 | W44: 5.5e-05 | X44: 4.9e-05 | Y44: 4.5e-05 | Z44: 4e-05 | AA44: 3.6e-05 | AB44: 3.3e-05 | AC44: 3e-05 | AD44: 2.7e-05 | AE44: 2.4e-05 | AF44: 2.2e-05 | AG44: 2e-05 | AH44: 1.8e-05 | AI44: 1.6e-05 | AJ44: -0.116
A45: 200 Mile Electric Vehicle | B45: Light-Duty Vehicle Stock: Alternative-Fuel Light Trucks: 200 Mile Electric Vehicle: High oil and gas supply | C45: 49-AEO2021.36.highogs-d120120a | D45: millions | E45: 0.035414 | F45: 0.047958 | G45: 0.061721 | H45: 0.076243 | I45: 0.093642 | J45: 0.113646 | K45: 0.136621 | L45: 0.162034 | M45: 0.191001 | N45: 0.223877 | O45: 0.260069 | P45: 0.300362 | Q45: 0.345288 | R45: 0.394836 | S45: 0.448917 | T45: 0.507624 | U45: 0.570221 | V45: 0.63605 | W45: 0.705188 | X45: 0.777257 | Y45: 0.851672 | Z45: 0.927907 | AA45: 1.005885 | AB45: 1.085015 | AC45: 1.165164 | AD45: 1.247044 | AE45: 1.329116 | AF45: 1.411047 | AG45: 1.494082 | AH45: 1.576498 | AI45: 1.657945 | AJ45: 0.137
A46: 300 Mile Electric Vehicle | B46: Light-Duty Vehicle Stock: Alternative-Fuel Light Trucks: 300 Mile Electric Vehicle: High oil and gas supply | C46: 49-AEO2021.37.highogs-d120120a | D46: millions | E46: 0.06068 | F46: 0.091848 | G46: 0.128022 | H46: 0.169351 | I46: 0.216854 | J46: 0.268508 | K46: 0.322425 | L46: 0.380315 | M46: 0.445483 | N46: 0.518951 | O46: 0.60329 | P46: 0.698625 | Q46: 0.807387 | R46: 0.929933 | S46: 1.067575 | T46: 1.220337 | U46: 1.387586 | V46: 1.569236 | W46: 1.766562 | X46: 1.97822 | Y46: 2.203554 | Z46: 2.435668 | AA46: 2.673063 | AB46: 2.914818 | AC46: 3.161079 | AD46: 3.415155 | AE46: 3.672006 | AF46: 3.930903 | AG46: 4.195453 | AH46: 4.462746 | AI46: 4.731887 | AJ46: 0.156
A47: Plug-in 10 Gasoline Hybrid | B47: Light-Duty Vehicle Stock: Alternative-Fuel Light Trucks: Plug-in 10 Gasoline Hybrid: High oil and gas supply | C47: 49-AEO2021.38.highogs-d120120a | D47: millions | E47: 0.056167 | F47: 0.060159 | G47: 0.064102 | H47: 0.067984 | I47: 0.071941 | J47: 0.075711 | K47: 0.07911 | L47: 0.082495 | M47: 0.085986 | N47: 0.089661 | O47: 0.093538 | P47: 0.097793 | Q47: 0.102625 | R47: 0.108345 | S47: 0.115073 | T47: 0.122521 | U47: 0.130545 | V47: 0.139217 | W47: 0.148826 | X47: 0.159552 | Y47: 0.171571 | Z47: 0.185105 | AA47: 0.200141 | AB47: 0.217075 | AC47: 0.236077 | AD47: 0.257751 | AE47: 0.282256 | AF47: 0.31008 | AG47: 0.342211 | AH47: 0.378898 | AI47: 0.420748 | AJ47: 0.069
A48: Plug-in 40 Gasoline Hybrid | B48: Light-Duty Vehicle Stock: Alternative-Fuel Light Trucks: Plug-in 40 Gasoline Hybrid: High oil and gas supply | C48: 49-AEO2021.39.highogs-d120120a | D48: millions | E48: 0.045998 | F48: 0.070582 | G48: 0.095418 | H48: 0.118328 | I48: 0.139605 | J48: 0.178533 | K48: 0.29515 | L48: 0.430112 | M48: 0.566321 | N48: 0.701171 | O48: 0.834845 | P48: 0.968715 | Q48: 1.103917 | R48: 1.239001 | S48: 1.373339 | T48: 1.506232 | U48: 1.634726 | V48: 1.757091 | W48: 1.873427 | X48: 1.982344 | Y48: 2.082342 | Z48: 2.172954 | AA48: 2.256005 | AB48: 2.331604 | AC48: 2.400024 | AD48: 2.462572 | AE48: 2.517167 | AF48: 2.563599 | AG48: 2.603974 | AH48: 2.637731 | AI48: 2.664862 | AJ48: 0.145
A49: Electric-Diesel Hybrid | B49: Light-Duty Vehicle Stock: Alternative-Fuel Light Trucks: Electric-Diesel Hybrid: High oil and gas supply | C49: 49-AEO2021.40.highogs-d120120a | D49: millions | E49: 0 | F49: 0 | G49: 0 | H49: 0 | I49: 0 | J49: 0 | K49: 0 | L49: 0 | M49: 0 | N49: 0 | O49: 0 | P49: 0 | Q49: 0 | R49: 0 | S49: 0 | T49: 0 | U49: 0 | V49: 0 | W49: 0 | X49: 0 | Y49: 0 | Z49: 0 | AA49: 0 | AB49: 0 | AC49: 0 | AD49: 0 | AE49: 0 | AF49: 0 | AG49: 0 | AH49: 0 | AI49: 0 | AJ49: - -
A50: Electric-Gasoline Hybrid | B50: Light-Duty Vehicle Stock: Alternative-Fuel Light Trucks: Electric-Gasoline Hybrid: High oil and gas supply | C50: 49-AEO2021.41.highogs-d120120a | D50: millions | E50: 0.958452 | F50: 1.190484 | G50: 1.439907 | H50: 1.698766 | I50: 1.972269 | J50: 2.256892 | K50: 2.589511 | L50: 2.936554 | M50: 3.289029 | N50: 3.642879 | O50: 3.993388 | P50: 4.342149 | Q50: 4.690197 | R50: 5.034131 | S50: 5.37346 | T50: 5.708565 | U50: 6.036191 | V50: 6.354293 | W50: 6.666058 | X50: 6.970408 | Y50: 7.265858 | Z50: 7.552022 | AA50: 7.83159 | AB50: 8.104107 | AC50: 8.371502 | AD50: 8.63977 | AE50: 8.901898 | AF50: 9.157935 | AG50: 9.415176 | AH50: 9.667517 | AI50: 9.91389 | AJ50: 0.081
A51: Natural Gas ICE | B51: Light-Duty Vehicle Stock: Alternative-Fuel Light Trucks: Natural Gas ICE: High oil and gas supply | C51: 49-AEO2021.42.highogs-d120120a | D51: millions | E51: 0.012927 | F51: 0.012425 | G51: 0.011995 | H51: 0.011642 | I51: 0.011374 | J51: 0.011137 | K51: 0.010949 | L51: 0.010763 | M51: 0.010627 | N51: 0.010483 | O51: 0.010403 | P51: 0.010339 | Q51: 0.010307 | R51: 0.010286 | S51: 0.010311 | T51: 0.010336 | U51: 0.010372 | V51: 0.010409 | W51: 0.010458 | X51: 0.010508 | Y51: 0.010563 | Z51: 0.010613 | AA51: 0.010648 | AB51: 0.010715 | AC51: 0.010779 | AD51: 0.010853 | AE51: 0.010917 | AF51: 0.010973 | AG51: 0.011037 | AH51: 0.011093 | AI51: 0.011143 | AJ51: -0.005
A52: Natural Gas Bi-fuel | B52: Light-Duty Vehicle Stock: Alternative-Fuel Light Trucks: Natural Gas Bi-fuel: High oil and gas supply | C52: 49-AEO2021.43.highogs-d120120a | D52: millions | E52: 0.033397 | F52: 0.034571 | G52: 0.035624 | H52: 0.03654 | I52: 0.037403 | J52: 0.038196 | K52: 0.038857 | L52: 0.039291 | M52: 0.039698 | N52: 0.040033 | O52: 0.040253 | P52: 0.040459 | Q52: 0.040672 | R52: 0.04087 | S52: 0.041126 | T52: 0.041374 | U52: 0.04161 | V52: 0.041803 | W52: 0.041997 | X52: 0.042182 | Y52: 0.042352 | Z52: 0.042487 | AA52: 0.042583 | AB52: 0.042702 | AC52: 0.042749 | AD52: 0.042856 | AE52: 0.042917 | AF52: 0.042944 | AG52: 0.043011 | AH52: 0.043033 | AI52: 0.043009 | AJ52: 0.008
A53: Propane ICE | B53: Light-Duty Vehicle Stock: Alternative-Fuel Light Trucks: Propane ICE: High oil and gas supply | C53: 49-AEO2021.44.highogs-d120120a | D53: millions | E53: 0.012971 | F53: 0.012653 | G53: 0.012443 | H53: 0.012311 | I53: 0.012257 | J53: 0.012265 | K53: 0.012331 | L53: 0.012419 | M53: 0.01255 | N53: 0.012714 | O53: 0.012881 | P53: 0.013065 | Q53: 0.01327 | R53: 0.013484 | S53: 0.013755 | T53: 0.014025 | U53: 0.014305 | V53: 0.01459 | W53: 0.01489 | X53: 0.015196 | Y53: 0.015514 | Z53: 0.015833 | AA53: 0.016146 | AB53: 0.016508 | AC53: 0.016891 | AD53: 0.017308 | AE53: 0.017727 | AF53: 0.018151 | AG53: 0.018599 | AH53: 0.019056 | AI53: 0.019522 | AJ53: 0.014
A54: Propane Bi-fuel | B54: Light-Duty Vehicle Stock: Alternative-Fuel Light Trucks: Propane Bi-fuel: High oil and gas supply | C54: 49-AEO2021.45.highogs-d120120a | D54: millions | E54: 0.059584 | F54: 0.05641 | G54: 0.053414 | H54: 0.050554 | I54: 0.04786 | J54: 0.045331 | K54: 0.042976 | L54: 0.040675 | M54: 0.038547 | N54: 0.036594 | O54: 0.034738 | P54: 0.03307 | Q54: 0.031593 | R54: 0.030281 | S54: 0.029326 | T54: 0.02847 | U54: 0.02779 | V54: 0.027237 | W54: 0.026826 | X54: 0.026491 | Y54: 0.026248 | Z54: 0.026024 | AA54: 0.025747 | AB54: 0.025836 | AC54: 0.025861 | AD54: 0.025925 | AE54: 0.02596 | AF54: 0.025972 | AG54: 0.02601 | AH54: 0.026019 | AI54: 0.025997 | AJ54: -0.027
A55: Fuel Cell Methanol | B55: Light-Duty Vehicle Stock: Alternative-Fuel Light Trucks: Fuel Cell Methanol: High oil and gas supply | C55: 49-AEO2021.46.highogs-d120120a | D55: millions | E55: 0 | F55: 0 | G55: 0 | H55: 0 | I55: 0 | J55: 0 | K55: 0 | L55: 0 | M55: 0 | N55: 0 | O55: 0 | P55: 0 | Q55: 0 | R55: 0 | S55: 0 | T55: 0 | U55: 0 | V55: 0 | W55: 0 | X55: 0 | Y55: 0 | Z55: 0 | AA55: 0 | AB55: 0 | AC55: 0 | AD55: 0 | AE55: 0 | AF55: 0 | AG55: 0 | AH55: 0 | AI55: 0 | AJ55: - -
A56: Fuel Cell Hydrogen | B56: Light-Duty Vehicle Stock: Alternative-Fuel Light Trucks: Fuel Cell Hydrogen: High oil and gas supply | C56: 49-AEO2021.47.highogs-d120120a | D56: millions | E56: 5e-06 | F56: 1.3e-05 | G56: 2.4e-05 | H56: 3.8e-05 | I56: 5.7e-05 | J56: 8.3e-05 | K56: 0.000117 | L56: 0.000158 | M56: 0.000209 | N56: 0.000272 | O56: 0.000346 | P56: 0.000434 | Q56: 0.000535 | R56: 0.000651 | S56: 0.00078 | T56: 0.000922 | U56: 0.001076 | V56: 0.001239 | W56: 0.001412 | X56: 0.001592 | Y56: 0.001778 | Z56: 0.001968 | AA56: 0.002162 | AB56: 0.002358 | AC56: 0.002556 | AD56: 0.002756 | AE56: 0.002957 | AF56: 0.003155 | AG56: 0.003355 | AH56: 0.003552 | AI56: 0.003745 | AJ56: 0.245
A57: Total Alternative Light Trucks | B57: Light-Duty Vehicle Stock: Alternative-Fuel Light Trucks: Total: High oil and gas supply | C57: 49-AEO2021.48.highogs-d120120a | D57: millions | E57: 17.064865 | F57: 17.370266 | G57: 17.668472 | H57: 17.949978 | I57: 18.226875 | J57: 18.521311 | K57: 18.917408 | L57: 19.324028 | M57: 19.746956 | N57: 20.188576 | O57: 20.637424 | P57: 21.097216 | Q57: 21.575924 | R57: 22.079157 | S57: 22.609467 | T57: 23.170435 | U57: 23.750145 | V57: 24.342945 | W57: 24.951464 | X57: 25.577835 | Y57: 26.221239 | Z57: 26.861395 | AA57: 27.503029 | AB57: 28.14023 | AC57: 28.7747 | AD57: 29.422791 | AE57: 30.060976 | AF57: 30.688084 | AG57: 31.327591 | AH57: 31.958881 | AI57: 32.579056 | AJ57: 0.022
A58: Total Light Truck Stock | B58: Light-Duty Vehicle Stock: Light Truck Stock: Total: High oil and gas supply | C58: 49-AEO2021.50.highogs-d120120a | D58: millions | E58: 127.37338 | F58: 128.71994 | G58: 130.48941 | H58: 132.58934 | I58: 135.09534 | J58: 137.87146 | K58: 140.65752 | L58: 143.26042 | M58: 145.83467 | N58: 148.29947 | O58: 150.49306 | P58: 152.57227 | Q58: 154.50478 | R58: 156.29961 | S58: 157.94099 | T58: 159.47208 | U58: 160.81201 | V58: 161.94276 | W58: 162.94453 | X58: 163.84772 | Y58: 164.64851 | Z58: 165.37283 | AA58: 166.04492 | AB58: 166.63292 | AC58: 167.17302 | AD58: 167.72554 | AE58: 168.20044 | AF58: 168.59692 | AG58: 169.02814 | AH58: 169.37772 | AI58: 169.63386 | AJ58: 0.01
A59: Total Stock | B59: Light-Duty Vehicle Stock: Total Vehicle Stock: High oil and gas supply | C59: 49-AEO2021.52.highogs-d120120a | D59: millions | E59: 257.41763 | F59: 256.84235 | G59: 257.22104 | H59: 258.00601 | I59: 259.31885 | J59: 260.99506 | K59: 262.58929 | L59: 263.80838 | M59: 264.89889 | N59: 265.78003 | O59: 266.36108 | P59: 266.84897 | Q59: 267.25818 | R59: 267.63843 | S59: 268.02582 | T59: 268.50485 | U59: 268.94629 | V59: 269.35034 | W59: 269.79547 | X59: 270.25018 | Y59: 270.6857 | Z59: 271.13742 | AA59: 271.60513 | AB59: 272.00879 | AC59: 272.39786 | AD59: 272.85291 | AE59: 273.19638 | AF59: 273.42483 | AG59: 273.70886 | AH59: 273.87537 | AI59: 273.90671 | AJ59: 0.002

Sheet AEO 44
A1: Fleet Vehicle Sales Commercial Light Trucks (Case High oil and gas supply)
A2: https://www.eia.gov/outlooks/aeo/data/browser/#/?id=54-AEO2021&region=0-0&cases=highogs&start=2019&end=2050&f=A&linechart=highogs-d120120a.57-54-AEO2021~highogs-d120120a.58-54-AEO2021~highogs-d120120a.59-54-AEO2021~highogs-d120120a.60-54-AEO2021~highogs-d120120a.61-54-AEO2021~highogs-d120120a.62-54-AEO2021~highogs-d120120a.63-54-AEO2021~highogs-d120120a.64-54-AEO2021~highogs-d120120a.65-54-AEO2021~highogs-d120120a.66-54-AEO2021&ctype=linechart&sourcekey=0
A3: 13:37:48 GMT-0700 (Pacific Daylight Time)
A4: Source: U.S. Energy Information Administration
A5: Year | B5: Gasoline thousands | C5: TDI Diesel thousands | D5: Propane thousands | E5: CNG/LNG thousands | F5: Ethanol Flex thousands | G5: Electric thousands | H5: Plug-in Gas thousands | I5: Plug-in Diesel thousands | J5: Fuel Cell thousands | K5: Total thousands
A6: 2050 | B6: 41.234306 | C6: 303.52524 | D6: 2.627345 | E6: 0.502718 | F6: 611.6178 | G6: 2.829432 | H6: 3.039656 | I6: 3.238246 | J6: 0 | K6: 968.61481
A7: 2049 | B7: 52.488136 | C7: 312.71551 | D7: 2.569427 | E7: 0.500157 | F7: 598.50061 | G7: 2.76706 | H7: 2.972651 | I7: 3.166863 | J7: 0 | K7: 975.68036
A8: 2048 | B8: 65.500671 | C8: 319.40762 | D8: 2.509144 | E8: 0.497451 | F8: 584.76025 | G8: 2.702139 | H8: 2.902907 | I8: 3.092562 | J8: 0 | K8: 981.3728
A9: 2047 | B9: 78.435829 | C9: 321.22879 | D9: 2.422277 | E9: 0.492299 | F9: 564.84399 | G9: 2.608591 | H9: 2.802408 | I9: 2.985498 | J9: 0 | K9: 975.81964
A10: 2046 | B10: 91.947372 | C10: 326.2695 | D10: 2.363222 | E10: 0.492833 | F10: 551.32526 | G10: 2.544994 | H10: 2.734086 | I10: 2.912712 | J10: 0 | K10: 980.58997
A11: 2045 | B11: 105.51059 | C11: 330.60977 | D11: 2.302584 | E11: 0.492989 | F11: 537.19427 | G11: 2.479692 | H11: 2.663932 | I11: 2.837975 | J11: 0 | K11: 984.09186
A12: 2044 | B12: 117.8755 | C12: 330.53674 | D12: 2.217451 | E12: 0.489471 | F12: 517.33258 | G12: 2.38801 | H12: 2.565438 | I12: 2.733046 | J12: 0 | K12: 976.13824
A13: 2043 | B13: 131.30927 | C13: 332.91736 | D13: 2.154994 | E13: 0.490473 | F13: 502.76123 | G13: 2.320749 | H13: 2.493179 | I13: 2.656066 | J13: 0 | K13: 977.10333
A14: 2042 | B14: 144.83325 | C14: 335.44135 | D14: 2.097138 | E14: 0.492202 | F14: 489.26349 | G14: 2.258443 | H14: 2.426244 | I14: 2.584758 | J14: 0 | K14: 979.39685
A15: 2041 | B15: 158.02544 | C15: 336.60053 | D15: 2.035352 | E15: 0.492843 | F15: 474.84888 | G15: 2.191905 | H15: 2.354763 | I15: 2.508606 | J15: 0 | K15: 979.05829
A16: 2040 | B16: 171.80562 | C16: 337.33624 | D16: 1.977708 | E16: 0.494308 | F16: 461.40045 | G16: 2.129827 | H16: 2.288072 | I16: 2.437559 | J16: 0 | K16: 979.86975
A17: 2039 | B17: 186.04433 | C17: 337.47348 | D17: 1.922608 | E17: 0.496506 | F17: 448.5455 | G17: 2.070488 | H17: 2.224324 | I17: 2.369647 | J17: 0 | K17: 981.14685
... A36: 2020 | B36: 180.74901 | C36: 276.82663 | D36: 0.814372 | E36: 0.604106 | F36: 266.90482 | G36: 0.895795 | H36: 0.942172 | I36: 1.003727 | J36: 0 | K36: 728.74066
A37: 2019

Sheet AEO 49
E1: 2020 | F1: 2021 | G1: 2022 | H1: 2023 | I1: 2024 | J1: 2025 | K1: 2026 | L1: 2027 | M1: 2028 | N1: 2029 | O1: 2030 | P1: 2031 | Q1: 2032 | R1: 2033 | S1: 2034 | T1: 2035 | U1: 2036 | V1: 2037 | W1: 2038 | X1: 2039 | Y1: 2040 | Z1: 2041 | AA1: 2042 | AB1: 2043 | AC1: 2044 | AD1: 2045 | AE1: 2046 | AF1: 2047 | AG1: 2048 | AH1: 2049 | AI1: 2050 | AJ1: Growth (2020-2050)
A11: Table 49. Freight Transportation Energy Use
A12: https://www.eia.gov/outlooks/aeo/data/browser/#/?id=58-AEO2021&cases=highogs&sourcekey=0
A13: Mon Mar 08 2021 16:29:49 GMT-0800 (Pacific Standard Time)
A14: Source: U.S. Energy Information Administration
B15: full name | C15: api key | D15: units | E15: 2020 | F15: 2021 | G15: 2022 | H15: 2023 | I15: 2024 | J15: 2025 | K15: 2026 | L15: 2027 | M15: 2028 | N15: 2029 | O15: 2030 | P15: 2031 | Q15: 2032 | R15: 2033 | S15: 2034 | T15: 2035 | U15: 2036 | V15: 2037 | W15: 2038 | X15: 2039 | Y15: 2040 | Z15: 2041 | AA15: 2042 | AB15: 2043 | AC15: 2044 | AD15: 2045 | AE15: 2046 | AF15: 2047 | AG15: 2048 | AH15: 2049 | AI15: 2050 | AJ15: Growth (2020-2050)
A16: Freight Truck Stock by Size Class | C16: 58-AEO2021.2.
A17: Vehicle Miles Traveled (billion miles) | C17: 58-AEO2021.4.
A18: Light Medium | C18: 58-AEO2021.5.
A19: Diesel | B19: Freight: Truck Stock: Vehicle Miles Traveled: Light Medium: Diesel: High oil and gas supply | C19: 58-AEO2021.6.highogs-d120120a | D19: billion miles | E19: 44.303616 | F19: 46.46851 | G19: 48.64381 | H19: 49.78685 | I19: 50.975182 | J19: 52.169327 | K19: 53.003296 | L19: 53.847748 | M19: 54.92065 | N19: 56.083549 | O19: 57.405666 | P19: 58.769749 | Q19: 60.050926 | R19: 61.100975 | S19: 62.185032 | T19: 63.344463 | U19: 64.250336 | V19: 64.989426 | W19: 65.736893 | X19: 66.457367 | Y19: 66.942749 | Z19: 67.447044 | AA19: 67.93074 | AB19: 68.498482 | AC19: 68.873764 | AD19: 69.274086 | AE19: 69.495872 | AF19: 69.753059 | AG19: 70.15863 | AH19: 70.541718 | AI19: 70.972908 | AJ19: 0.016
A20: Motor Gasoline | B20: Freight: Truck Stock: Vehicle Miles Traveled: Light Medium: Motor Gasoline: High oil and gas supply | C20: 58-AEO2021.7.highogs-d120120a | D20: billion miles | E20: 11.670487 | F20: 12.01163 | G20: 12.329393 | H20: 12.398815 | I20: 12.497584 | J20: 12.633912 | K20: 12.742443 | L20: 12.904199 | M20: 13.156378 | N20: 13.47327 | O20: 13.869823 | P20: 14.298347 | Q20: 14.758368 | R20: 15.217308 | S20: 15.705617 | T20: 16.229515 | U20: 16.727058 | V20: 17.217386 | W20: 17.729656 | X20: 18.240948 | Y20: 18.703653 | Z20: 19.203287 | AA20: 19.709454 | AB20: 20.256687 | AC20: 20.762129 | AD20: 21.284573 | AE20: 21.763906 | AF20: 22.258034 | AG20: 22.800196 | AH20: 23.335905 | AI20: 23.896128 | AJ20: 0.024
A21: Propane | B21: Freight: Truck Stock: Vehicle Miles Traveled: Light Medium: Propane: High oil and gas supply | C21: 58-AEO2021.8.highogs-d120120a | D21: billion miles | E21: 0.012334 | F21: 0.018281 | G21: 0.024646 | H21: 0.030636 | I21: 0.03672 | J21: 0.042852 | K21: 0.048635 | L21: 0.054351 | M21: 0.060354 | N21: 0.06658 | O21: 0.073035 | P21: 0.079679 | Q21: 0.086453 | R21: 0.093168 | S21: 0.10013 | T21: 0.107483 | U21: 0.114736 | V21: 0.122013 | W21: 0.129664 | X21: 0.137584 | Y21: 0.145181 | Z21: 0.153057 | AA21: 0.161202 | AB21: 0.16979 | AC21: 0.178193 | AD21: 0.187076 | AE21: 0.195868 | AF21: 0.205157 | AG21: 0.215387 | AH21: 0.226093 | AI21: 0.237484 | AJ21: 0.104
A22: Compressed/Liquefied Natural Gas | B22: Freight: Truck Stock: Vehicle Miles Traveled: Light Medium: Natural Gas: High oil and gas supply | C22: 58-AEO2021.9.highogs-d120120a | D22: billion miles | E22: 0.00651 | F22: 0.009375 | G22: 0.012327 | H22: 0.014945 | I22: 0.017472 | J22: 0.019891 | K22: 0.022038 | L22: 0.024058 | M22: 0.0261 | N22: 0.028134 | O22: 0.03017 | P22: 0.032181 | Q22: 0.034136 | R22: 0.035962 | S22: 0.037783 | T22: 0.039642 | U22: 0.041355 | V22: 0.042967 | W22: 0.044604 | X22: 0.046205 | Y22: 0.047577 | Z22: 0.048953 | AA22: 0.05033 | AB22: 0.051773 | AC22: 0.053101 | AD22: 0.054511 | AE22: 0.05586 | AF22: 0.057357 | AG22: 0.059118 | AH22: 0.061027 | AI22: 0.063147 | AJ22: 0.079
A23: Ethanol-Flex Fuel | B23: Freight: Truck Stock: Vehicle Miles Traveled: Light Medium: Ethanol-Flex Fuel: High oil and gas supply | C23: 58-AEO2021.10.highogs-d120120a | D23: billion miles | E23: 4.117043 | F23: 4.540388 | G23: 4.963326 | H23: 5.281196 | I23: 5.608263 | J23: 5.943142 | K23: 6.262032 | L23: 6.612732 | M23: 7.010355 | N23: 7.451281 | O23: 7.9248 | P23: 8.423628 | Q23: 8.942436 | R23: 9.462119 | S23: 10.000749 | T23: 10.569487 | U23: 11.123409 | V23: 11.685357 | W23: 12.272737 | X23: 12.885431 | Y23: 13.488983 | Z23: 14.153807 | AA23: 14.881503 | AB23: 15.670287 | AC23: 16.454727 | AD23: 17.294907 | AE23: 18.134251 | AF23: 19.022991 | AG23: 19.985868 | AH23: 20.989632 | AI23: 22.046141 | AJ23: 0.058
A24: Electric | B24: Freight: Truck Stock: Vehicle Miles Traveled: Light Medium: Electric: High oil and gas supply | C24: 58-AEO2021.11.highogs-d120120a | D24: billion miles | E24: 0.00537 | F24: 0.010535 | G24: 0.01645 | H24: 0.022448 | I24: 0.02875 | J24: 0.035238 | K24: 0.041526 | L24: 0.047812 | M24: 0.054347 | N24: 0.061033 | O24: 0.067904 | P24: 0.074933 | Q24: 0.082057 | R24: 0.089079 | S24: 0.096355 | T24: 0.104059 | U24: 0.111743 | V24: 0.119563 | W24: 0.127863 | X24: 0.136441 | Y24: 0.144896 | Z24: 0.153739 | AA24: 0.162937 | AB24: 0.172473 | AC24: 0.181706 | AD24: 0.191288 | AE24: 0.200721 | AF24: 0.210581 | AG24: 0.221283 | AH24: 0.232416 | AI24: 0.2443 | AJ24: 0.136
A25: Plug-in Diesel Hybrid | B25: Freight: Truck Stock: Vehicle Miles Traveled: Light Medium: Plug-in Diesel Hybrid: High oil and gas supply | C25: 58-AEO2021.12.highogs-d120120a | D25: billion miles | E25: 0.004667 | F25: 0.01022 | G25: 0.016645 | H25: 0.023188 | I25: 0.030054 | J25: 0.037112 | K25: 0.043949 | L25: 0.050772 | M25: 0.057853 | N25: 0.065108 | O25: 0.072574 | P25: 0.080206 | Q25: 0.087937 | R25: 0.095593 | S25: 0.103528 | T25: 0.111907 | U25: 0.12025 | V25: 0.128729 | W25: 0.137715 | X25: 0.146996 | Y25: 0.156132 | Z25: 0.165678 | AA25: 0.175606 | AB25: 0.185904 | AC25: 0.195889 | AD25: 0.206252 | AE25: 0.216448 | AF25: 0.227098 | AG25: 0.238653 | AH25: 0.250669 | AI25: 0.263491 | AJ25: 0.144
A26: Plug-in Gasoline Hybrid | B26: Freight: Truck Stock: Vehicle Miles Traveled: Light Medium: Plug-in Gasoline Hybrid: High oil and gas supply | C26: 58-AEO2021.13.highogs-d120120a | D26: billion miles | E26: 0.004737 | F26: 0.010373 | G26: 0.016895 | H26: 0.023536 | I26: 0.030505 | J26: 0.037669 | K26: 0.044608 | L26: 0.051534 | M26: 0.058721 | N26: 0.066085 | O26: 0.073662 | P26: 0.081409 | Q26: 0.089257 | R26: 0.097027 | S26: 0.105081 | T26: 0.113586 | U26: 0.122054 | V26: 0.13066 | W26: 0.139781 | X26: 0.149201 | Y26: 0.158475 | Z26: 0.168163 | AA26: 0.178241 | AB26: 0.188694 | AC26: 0.198828 | AD26: 0.209347 | AE26: 0.219695 | AF26: 0.230505 | AG26: 0.242233 | AH26: 0.25443 | AI26: 0.267445 | AJ26: 0.144
A27: Fuel Cell | B27: Freight: Truck Stock: Vehicle Miles Traveled: Light Medium: Fuel Cell: High oil and gas supply | C27: 58-AEO2021.14.highogs-d120120a | D27: billion miles | E27: 2e-06 | F27: 5e-06 | G27: 8e-06 | H27: 1.1e-05 | I27: 1.4e-05 | J27: 1.7e-05 | K27: 1.9e-05 | L27: 2.2e-05 | M27: 2.4e-05 | N27: 2.7e-05 | O27: 2.9e-05 | P27: 3.1e-05 | Q27: 3.4e-05 | R27: 3.5e-05 | S27: 3.7e-05 | T27: 3.9e-05 | U27: 4e-05 | V27: 4.2e-05 | W27: 4.3e-05 | X27: 4.4e-05 | Y27: 4.5e-05 | Z27: 4.6e-05 | AA27: 4.7e-05 | AB27: 4.7e-05 | AC27: 4.8e-05 | AD27: 4.8e-05 | AE27: 4.8e-05 | AF27: 4.8e-05 | AG27: 4.7e-05 | AH27: 4.7e-05 | AI27: 4.7e-05 | AJ27: 0.106
A28: Light Medium Subtotal | B28: Freight: Truck Stock: Vehicle Miles Traveled: Light Medium: High oil and gas supply | C28: 58-AEO2021.15.highogs-d120120a | D28: billion miles | E28: 60.124729 | F28: 63.079327 | G28: 66.02356 | H28: 67.581619 | I28: 69.224518 | J28: 70.919121 | K28: 72.208496 | L28: 73.593201 | M28: 75.344856 | N28: 77.295067 | O28: 79.51767 | P28: 81.840126 | Q28: 84.131516 | R28: 86.19136 | S28: 88.334435 | T28: 90.620224 | U28: 92.610786 | V28: 94.436134 | W28: 96.318832 | X28: 98.200081 | Y28: 99.787697 | Z28: 101.49389 | AA28: 103.25004 | AB28: 105.19402 | AC28: 106.89825 | AD28: 108.70194 | AE28: 110.28247 | AF28: 111.96469 | AG28: 113.92124 | AH28: 115.89179 | AI28: 117.99106 | AJ28: 0.023
A29: Medium | C29: 58-AEO2021.16.
A30: Diesel | B30: Freight: Truck Stock: Vehicle Miles Traveled: Medium: Diesel: High oil and gas supply | C30: 58-AEO2021.17.highogs-d120120a | D30: billion miles | E30: 34.473965 | F30: 35.473495 | G30: 36.95755 | H30: 37.959641 | I30: 39.124969 | J30: 40.335888 | K30: 41.264 | L30: 42.068516 | M30: 42.910355 | N30: 43.759945 | O30: 44.713017 | P30: 45.715141 | Q30: 46.789398 | R30: 47.786671 | S30: 48.873032 | T30: 50.144363 | U30: 51.413059 | V30: 52.670658 | W30: 54.011185 | X30: 55.482285 | Y30: 56.955433 | Z30: 58.566902 | AA30: 60.255966 | AB30: 62.128014 | AC30: 63.896786 | AD30: 65.736038 | AE30: 67.480141 | AF30: 69.220253 | AG30: 71.089844 | AH30: 73.088112 | AI30: 75.230225 | AJ30: 0.026
A31: Motor Gasoline | B31: Freight: Truck Stock: Vehicle Miles Traveled: Medium: Motor Gasoline: High oil and gas supply | C31: 58-AEO2021.18.highogs-d120120a | D31: billion miles | E31: 16.394169 | F31: 16.582535 | G31: 16.901983 | H31: 16.961668 | I31: 17.099653 | J31: 17.240475 | K31: 17.329367 | L31: 17.432796 | M31: 17.610531 | N31: 17.829197 | O31: 18.10059 | P31: 18.393978 | Q31: 18.731878 | R31: 19.043507 | S31: 19.403744 | T31: 19.829401 | U31: 20.229515 | V31: 20.658173 | W31: 21.11458 | X31: 21.643822 | Y31: 22.157524 | Z31: 22.724649 | AA31: 23.321432 | AB31: 23.983839 | AC31: 24.599024 | AD31: 25.222775 | AE31: 25.802208 | AF31: 26.379553 | AG31: 26.998093 | AH31: 27.652967 | AI31: 28.34454 | AJ31: 0.018
A32: Propane | B32: Freight: Truck Stock: Vehicle Miles Traveled: Medium: Propane: High oil and gas supply | C32: 58-AEO2021.19.highogs-d120120a | D32: billion miles | E32: 0.042377 | F32: 0.043695 | G32: 0.045804 | H32: 0.047491 | I32: 0.049514 | J32: 0.051738 | K32: 0.053756 | L32: 0.055728 | M32: 0.057872 | N32: 0.060161 | O32: 0.062822 | P32: 0.065789 | Q32: 0.069166 | R32: 0.072886 | S32: 0.077104 | T32: 0.081527 | U32: 0.086134 | V32: 0.09097 | W32: 0.096263 | X32: 0.102084 | Y32: 0.108285 | Z32: 0.115128 | AA32: 0.122455 | AB32: 0.130414 | AC32: 0.138415 | AD32: 0.146872 | AE32: 0.155459 | AF32: 0.16434 | AG32: 0.173872 | AH32: 0.183736 | AI32: 0.19453 | AJ32: 0.052
A33: Compressed/Liquefied Natural Gas | B33: Freight: Truck Stock: Vehicle Miles Traveled: Medium: Natural Gas: High oil and gas supply | C33: 58-AEO2021.20.highogs-d120120a | D33: billion miles | E33: 0.051877 | F33: 0.060931 | G33: 0.071687 | H33: 0.081669 | I33: 0.091757 | J33: 0.101626 | K33: 0.110331 | L33: 0.118092 | M33: 0.125515 | N33: 0.132515 | O33: 0.139316 | P33: 0.145888 | Q33: 0.152289 | R33: 0.15817 | S33: 0.164055 | T33: 0.170251 | U33: 0.176231 | V33: 0.182184 | W33: 0.188564 | X33: 0.19545 | Y33: 0.202531 | Z33: 0.210244 | AA33: 0.218386 | AB33: 0.227067 | AC33: 0.235354 | AD33: 0.24406 | AE33: 0.252594 | AF33: 0.261276 | AG33: 0.270614 | AH33: 0.280722 | AI33: 0.29179 | AJ33: 0.059
A34: Ethanol-Flex Fuel | B34: Freight: Truck Stock: Vehicle Miles Traveled: Medium: Ethanol-Flex Fuel: High oil and gas supply | C34: 58-AEO2021.21.highogs-d120120a | D34: billion miles | E34: 0.559701 | F34: 0.633097 | G34: 0.71984 | H34: 0.797148 | I34: 0.875121 | J34: 0.951475 | K34: 1.019397 | L34: 1.082565 | M34: 1.146466 | N34: 1.211985 | O34: 1.283031 | P34: 1.358459 | Q34: 1.439514 | R34: 1.521416 | S34: 1.612492 | T34: 1.713944 | U34: 1.817046 | V34: 1.927241 | W34: 2.042423 | X34: 2.17048 | Y34: 2.305455 | Z34: 2.452369 | AA34: 2.608402 | AB34: 2.777057 | AC34: 2.945768 | AD34: 3.123902 | AE34: 3.304722 | AF34: 3.492079 | AG34: 3.692852 | AH34: 3.91002 | AI34: 4.145447 | AJ34: 0.069
A35: Electric | B35: Freight: Truck Stock: Vehicle Miles Traveled: Medium: Electric: High oil and gas supply | C35: 58-AEO2021.22.highogs-d120120a | D35: billion miles | E35: 0.00542 | F35: 0.009429 | G35: 0.014236 | H35: 0.019151 | I35: 0.024204 | J35: 0.029276 | K35: 0.034014 | L35: 0.03843 | M35: 0.042785 | N35: 0.047171 | O35: 0.051713 | P35: 0.056411 | Q35: 0.061313 | R35: 0.066289 | S35: 0.071549 | T35: 0.077277 | U35: 0.083154 | V35: 0.089199 | W35: 0.095703 | X35: 0.10258 | Y35: 0.109815 | Z35: 0.117638 | AA35: 0.125907 | AB35: 0.134794 | AC35: 0.143706 | AD35: 0.153095 | AE35: 0.162652 | AF35: 0.17255 | AG35: 0.183171 | AH35: 0.194604 | AI35: 0.20696 | AJ35: 0.129
A36: Plug-in Diesel Hybrid | B36: Freight: Truck Stock: Vehicle Miles Traveled: Medium: Plug-in Diesel Hybrid: High oil and gas supply | C36: 58-AEO2021.23.highogs-d120120a | D36: billion miles | E36: 0.00386 | F36: 0.008219 | G36: 0.013495 | H36: 0.01894 | I36: 0.024531 | J36: 0.030138 | K36: 0.035384 | L36: 0.04027 | M36: 0.045077 | N36: 0.049907 | O36: 0.054896 | P36: 0.060042 | Q36: 0.0654 | R36: 0.070827 | S36: 0.076568 | T36: 0.082785 | U36: 0.089195 | V36: 0.095803 | W36: 0.102856 | X36: 0.110317 | Y36: 0.118164 | Z36: 0.126644 | AA36: 0.135607 | AB36: 0.145236 | AC36: 0.154893 | AD36: 0.165066 | AE36: 0.175419 | AF36: 0.18614 | AG36: 0.197642 | AH36: 0.21003 | AI36: 0.223412 | AJ36: 0.145
A37: Plug-in Gasoline Hybrid | B37: Freight: Truck Stock: Vehicle Miles Traveled: Medium: Plug-in Gasoline Hybrid: High oil and gas supply | C37: 58-AEO2021.24.highogs-d120120a | D37: billion miles | E37: 0.003625 | F37: 0.007719 | G37: 0.012674 | H37: 0.017787 | I37: 0.023038 | J37: 0.028304 | K37: 0.03323 | L37: 0.037818 | M37: 0.042333 | N37: 0.046869 | O37: 0.051554 | P37: 0.056387 | Q37: 0.061419 | R37: 0.066516 | S37: 0.071907 | T37: 0.077746 | U37: 0.083766 | V37: 0.089971 | W37: 0.096595 | X37: 0.103602 | Y37: 0.110972 | Z37: 0.118936 | AA37: 0.127353 | AB37: 0.136396 | AC37: 0.145465 | AD37: 0.155018 | AE37: 0.164742 | AF37: 0.17481 | AG37: 0.185612 | AH37: 0.197246 | AI37: 0.209813 | AJ37: 0.145
A38: Fuel Cell | B38: Freight: Truck Stock: Vehicle Miles Traveled: Medium: Fuel Cell: High oil and gas supply | C38: 58-AEO2021.25.highogs-d120120a | D38: billion miles | E38: 0.005931 | F38: 0.012627 | G38: 0.020733 | H38: 0.029097 | I38: 0.037687 | J38: 0.0463 | K38: 0.054359 | L38: 0.061865 | M38: 0.06925 | N38: 0.076671 | O38: 0.084335 | P38: 0.092241 | Q38: 0.100472 | R38: 0.10881 | S38: 0.117629 | T38: 0.12718 | U38: 0.137029 | V38: 0.147179 | W38: 0.158015 | X38: 0.169477 | Y38: 0.181532 | Z38: 0.194561 | AA38: 0.20833 | AB38: 0.223123 | AC38: 0.237958 | AD38: 0.253586 | AE38: 0.269492 | AF38: 0.285962 | AG38: 0.303633 | AH38: 0.322664 | AI38: 0.343222 | AJ38: 0.145
A39: Medium Subtotal | B39: Freight: Truck Stock: Vehicle Miles Traveled: Medium: High oil and gas supply | C39: 58-AEO2021.26.highogs-d120120a | D39: billion miles | E39: 51.540878 | F39: 52.831715 | G39: 54.758041 | H39: 55.932629 | I39: 57.35043 | J39: 58.815109 | K39: 59.933838 | L39: 60.935947 | M39: 62.05006 | N39: 63.214333 | O39: 64.541161 | P39: 65.944244 | Q39: 67.47068 | R39: 68.894958 | S39: 70.46814 | T39: 72.304413 | U39: 74.11515 | V39: 75.951416 | W39: 77.906181 | X39: 80.080231 | Y39: 82.249786 | Z39: 84.627113 | AA39: 87.123672 | AB39: 89.885834 | AC39: 92.497276 | AD39: 95.200439 | AE39: 97.767456 | AF39: 100.337 | AG39: 103.0956 | AH39: 106.03969 | AI39: 109.19002 | AJ39: 0.025
A40: Heavy | C40: 58-AEO2021.27.
A41: Diesel | B41: Freight: Truck Stock: Vehicle Miles Traveled: Heavy: Diesel: High oil and gas supply | C41: 58-AEO2021.28.highogs-d120120a | D41: billion miles | E41: 160.74234 | F41: 164.69356 | G41: 170.25006 | H41: 173.45579 | I41: 177.35992 | J41: 181.35458 | K41: 183.78087 | L41: 185.08688 | M41: 185.88377 | N41: 186.21794 | O41: 186.64908 | P41: 187.10757 | Q41: 187.66242 | R41: 187.99203 | S41: 188.75501 | T41: 190.17984 | U41: 191.44443 | V41: 192.5453 | W41: 193.78574 | X41: 195.14409 | Y41: 196.30774 | Z41: 197.77811 | AA41: 199.45316 | AB41: 201.4702 | AC41: 202.90762 | AD41: 204.33075 | AE41: 205.2179 | AF41: 205.8651 | AG41: 206.63888 | AH41: 207.51411 | AI41: 208.57773 | AJ41: 0.009
A42: Motor Gasoline | B42: Freight: Truck Stock: Vehicle Miles Traveled: Heavy: Motor Gasoline: High oil and gas supply | C42: 58-AEO2021.29.highogs-d120120a | D42: billion miles | E42: 0.163674 | F42: 0.149414 | G42: 0.137481 | H42: 0.125597 | I42: 0.116181 | J42: 0.108125 | K42: 0.101701 | L42: 0.097096 | M42: 0.093618 | N42: 0.090825 | O42: 0.089444 | P42: 0.088322 | Q42: 0.087162 | R42: 0.086113 | S42: 0.085427 | T42: 0.085232 | U42: 0.084828 | V42: 0.084627 | W42: 0.084642 | X42: 0.084828 | Y42: 0.084857 | Z42: 0.085285 | AA42: 0.085617 | AB42: 0.086119 | AC42: 0.086636 | AD42: 0.087336 | AE42: 0.087976 | AF42: 0.088679 | AG42: 0.089557 | AH42: 0.090485 | AI42: 0.091513 | AJ42: -0.019
A43: Propane | B43: Freight: Truck Stock: Vehicle Miles Traveled: Heavy: Propane: High oil and gas supply | C43: 58-AEO2021.30.highogs-d120120a | D43: billion miles | E43: 0.03345 | F43: 0.037316 | G43: 0.041475 | H43: 0.044704 | I43: 0.047663 | J43: 0.050243 | K43: 0.052097 | L43: 0.053384 | M43: 0.054333 | N43: 0.054956 | O43: 0.055498 | P43: 0.055923 | Q43: 0.056269 | R43: 0.056579 | S43: 0.057103 | T43: 0.057867 | U43: 0.058554 | V43: 0.059261 | W43: 0.06012 | X43: 0.061076 | Y43: 0.062069 | Z43: 0.063271 | AA43: 0.064589 | AB43: 0.066087 | AC43: 0.067456 | AD43: 0.068887 | AE43: 0.07024 | AF43: 0.071602 | AG43: 0.073094 | AH43: 0.074689 | AI43: 0.07642 | AJ43: 0.028
A44: Compressed/Liquefied Natural Gas | B44: Freight: Truck Stock: Vehicle Miles Traveled: Heavy: Natural Gas: High oil and gas supply | C44: 58-AEO2021.31.highogs-d120120a | D44: billion miles | E44: 1.935392 | F44: 2.008093 | G44: 2.077585 | H44: 2.094799 | I44: 2.09942 | J44: 2.093325 | K44: 2.066476 | L44: 2.03076 | M44: 1.99479 | N44: 1.959137 | O44: 1.930417 | P44: 1.909236 | Q44: 1.900709 | R44: 1.904166 | S44: 1.926255 | T44: 1.96884 | U44: 2.021522 | V44: 2.085245 | W44: 2.161508 | X44: 2.252393 | Y44: 2.358559 | Z44: 2.486901 | AA44: 2.63559 | AB44: 2.808012 | AC44: 2.992544 | AD44: 3.20176 | AE44: 3.42943 | AF44: 3.678354 | AG44: 3.954189 | AH44: 4.264853 | AI44: 4.613276 | AJ44: 0.029
A45: Ethanol-Flex Fuel | B45: Freight: Truck Stock: Vehicle Miles Traveled: Heavy: Ethanol-Flex Fuel: High oil and gas supply | C45: 58-AEO2021.32.highogs-d120120a | D45: billion miles | E45: 0 | F45: 0 | G45: 0 | H45: 0 | I45: 0 | J45: 0 | K45: 0 | L45: 0 | M45: 0 | N45: 0 | O45: 0 | P45: 0 | Q45: 0 | R45: 0 | S45: 0 | T45: 0 | U45: 0 | V45: 0 | W45: 0 | X45: 0 | Y45: 0 | Z45: 0 | AA45: 0 | AB45: 0 | AC45: 0 | AD45: 0 | AE45: 0 | AF45: 0 | AG45: 0 | AH45: 0 | AI45: 0 | AJ45: - -
A46: Electric | B46: Freight: Truck Stock: Vehicle Miles Traveled: Heavy: Electric: High oil and gas supply | C46: 58-AEO2021.33.highogs-d120120a | D46: billion miles | E46: 0.00115 | F46: 0.002301 | G46: 0.003689 | H46: 0.005134 | I46: 0.006642 | J46: 0.008178 | K46: 0.009642 | L46: 0.011039 | M46: 0.012421 | N46: 0.01379 | O46: 0.015163 | P46: 0.016513 | Q46: 0.017829 | R46: 0.019058 | S46: 0.020262 | T46: 0.021472 | U46: 0.022612 | V46: 0.023708 | W46: 0.024841 | X46: 0.02601 | Y46: 0.02715 | Z46: 0.028354 | AA46: 0.029631 | AB46: 0.030996 | AC46: 0.032318 | AD46: 0.033686 | AE46: 0.035029 | AF46: 0.036401 | AG46: 0.037859 | AH46: 0.039392 | AI46: 0.041021 | AJ46: 0.127
A47: Plug-in Diesel Hybrid | B47: Freight: Truck Stock: Vehicle Miles Traveled: Heavy: Plug-in Diesel Hybrid: High oil and gas supply | C47: 58-AEO2021.34.highogs-d120120a | D47: billion miles | E47: 0.002284 | F47: 0.003977 | G47: 0.006042 | H47: 0.008184 | I47: 0.010418 | J47: 0.012688 | K47: 0.014844 | L47: 0.016897 | M47: 0.018922 | N47: 0.020923 | O47: 0.022925 | P47: 0.024889 | Q47: 0.026797 | R47: 0.028576 | S47: 0.030318 | T47: 0.032076 | U47: 0.033747 | V47: 0.035371 | W47: 0.037024 | X47: 0.038717 | Y47: 0.040389 | Z47: 0.042192 | AA47: 0.044082 | AB47: 0.046104 | AC47: 0.04806 | AD47: 0.050086 | AE47: 0.052075 | AF47: 0.054107 | AG47: 0.056266 | AH47: 0.058538 | AI47: 0.060952 | AJ47: 0.116
A48: Plug-in Gasoline Hybrid | B48: Freight: Truck Stock: Vehicle Miles Traveled: Heavy: Plug-in Gasoline Hybrid: High oil and gas supply | C48: 58-AEO2021.35.highogs-d120120a | D48: billion miles | E48: 0.00253 | F48: 0.004396 | G48: 0.006672 | H48: 0.009034 | I48: 0.011496 | J48: 0.013998 | K48: 0.016375 | L48: 0.018637 | M48: 0.020869 | N48: 0.023074 | O48: 0.02528 | P48: 0.027443 | Q48: 0.029546 | R48: 0.031506 | S48: 0.033426 | T48: 0.035363 | U48: 0.037204 | V48: 0.038995 | W48: 0.040816 | X48: 0.042681 | Y48: 0.044525 | Z48: 0.046512 | AA48: 0.048595 | AB48: 0.050824 | AC48: 0.05298 | AD48: 0.055214 | AE48: 0.057406 | AF48: 0.059646 | AG48: 0.062026 | AH48: 0.06453 | AI48: 0.067191 | AJ48: 0.116
A49: Fuel Cell | B49: Freight: Truck Stock: Vehicle Miles Traveled: Heavy: Fuel Cell: High oil and gas supply | C49: 58-AEO2021.36.highogs-d120120a | D49: billion miles | E49: 0.002863 | F49: 0.005151 | G49: 0.007942 | H49: 0.010843 | I49: 0.013869 | J49: 0.016946 | K49: 0.019873 | L49: 0.02266 | M49: 0.025413 | N49: 0.028134 | O49: 0.030857 | P49: 0.033531 | Q49: 0.036129 | R49: 0.038555 | S49: 0.040928 | T49: 0.043319 | U49: 0.045589 | V49: 0.047791 | W49: 0.050038 | X49: 0.05234 | Y49: 0.05461 | Z49: 0.057046 | AA49: 0.059605 | AB49: 0.062343 | AC49: 0.064992 | AD49: 0.067735 | AE49: 0.070427 | AF49: 0.073179 | AG49: 0.076103 | AH49: 0.079178 | AI49: 0.082445 | AJ49: 0.119
A50: Heavy Subtotal | B50: Freight: Truck Stock: Vehicle Miles Traveled: Heavy: High oil and gas supply | C50: 58-AEO2021.37.highogs-d120120a | D50: billion miles | E50: 162.88361 | F50: 166.90398 | G50: 172.53108 | H50: 175.75407 | I50: 179.66538 | J50: 183.65779 | K50: 186.0614 | L50: 187.33722 | M50: 188.10358 | N50: 188.40834 | O50: 188.81807 | P50: 189.26286 | Q50: 189.81662 | R50: 190.1557 | S50: 190.94826 | T50: 192.42334 | U50: 193.74783 | V50: 194.91963 | W50: 196.24423 | X50: 197.70218 | Y50: 198.97949 | Z50: 200.58725 | AA50: 202.42015 | AB50: 204.62032 | AC50: 206.2525 | AD50: 207.89481 | AE50: 209.0195 | AF50: 209.9261 | AG50: 210.98755 | AH50: 212.18532 | AI50: 213.61003 | AJ50: 0.009
A51: Total Vehicle Miles Traveled | B51: Freight: Truck Stock: Vehicle Miles Traveled: High oil and gas supply | C51: 58-AEO2021.38.highogs-d120120a | D51: billion miles | E51: 274.54852 | F51: 282.8143 | G51: 293.31207 | H51: 299.26715 | I51: 306.24048 | J51: 313.39069 | K51: 318.20322 | L51: 321.86624 | M51: 325.49927 | N51: 328.91821 | O51: 332.87741 | P51: 337.0481 | Q51: 341.41858 | R51: 345.242 | S51: 349.75079 | T51: 355.34708 | U51: 360.47275 | V51: 365.30658 | W51: 370.46896 | X51: 375.98138 | Y51: 381.01614 | Z51: 386.70743 | AA51: 392.79382 | AB51: 399.70004 | AC51: 405.64749 | AD51: 411.79633 | AE51: 417.06876 | AF51: 422.22742 | AG51: 428.0033 | AH51: 434.11624 | AI51: 440.78909 | AJ51: 0.016
A52: Consumption (trillion Btu) | C52: 58-AEO2021.40.
A53: Light Medium | C53: 58-AEO2021.41.
A54: Diesel | B54: Freight: Truck Stock: Use: Light Medium: Diesel: High oil and gas supply | C54: 58-AEO2021.42.highogs-d120120a | D54: trillion Btu | E54: 425.51425 | F54: 440.58371 | G54: 455.0455 | H54: 459.3652 | I54: 463.56277 | J54: 467.237 | K54: 467.3674 | L54: 467.62799 | M54: 470.19318 | N54: 473.72711 | O54: 479.00006 | P54: 485.02005 | Q54: 490.67685 | R54: 494.77631 | S54: 499.55972 | T54: 505.27167 | U54: 509.2244 | V54: 512.11676 | W54: 515.32159 | X54: 518.63336 | Y54: 520.38464 | Z54: 522.54199 | AA54: 524.75317 | AB54: 527.86456 | AC54: 529.69794 | AD54: 531.86786 | AE54: 532.77289 | AF54: 534.08972 | AG54: 536.65717 | AH54: 539.1189 | AI54: 542.01917 | AJ54: 0.008
A55: Motor Gasoline | B55: Freight: Truck Stock: Use: Light Medium: Motor Gasoline: High oil and gas supply | C55: 58-AEO2021.43.highogs-d120120a | D55: trillion Btu | E55: 147.04254 | F55: 149.52405 | G55: 151.48608 | H55: 150.22948 | I55: 149.1449 | J55: 148.34405 | K55: 147.12764 | L55: 146.45103 | M55: 146.82654 | N55: 147.87546 | O55: 149.81079 | P55: 152.03992 | Q55: 154.64557 | R55: 157.308 | S55: 160.32317 | T55: 163.71887 | U55: 166.90434 | V55: 170.06863 | W55: 173.46829 | X55: 176.86972 | Y55: 179.83353 | Z55: 183.25606 | AA55: 186.80432 | AB55: 190.81557 | AC55: 194.50809 | AD55: 198.41193 | AE55: 201.97336 | AF55: 205.70529 | AG55: 209.87543 | AH55: 213.98112 | AI55: 218.27652 | AJ55: 0.013
A56: Propane | B56: Freight: Truck Stock: Use: Light Medium: Propane: High oil and gas supply | C56: 58-AEO2021.44.highogs-d120120a | D56: trillion Btu | E56: 0.13057 | F56: 0.189971 | G56: 0.253036 | H56: 0.311774 | I56: 0.370733 | J56: 0.429141 | K56: 0.482836 | L56: 0.534549 | M56: 0.588987 | N56: 0.645241 | O56: 0.70329 | P56: 0.763442 | Q56: 0.824494 | R56: 0.884703 | S56: 0.947274 | T56: 1.013298 | U56: 1.078138 | V56: 1.142968 | W56: 1.211041 | X56: 1.281403 | Y56: 1.348374 | Z56: 1.417784 | AA56: 1.489516 | AB56: 1.565205 | AC56: 1.639096 | AD56: 1.717343 | AE56: 1.794788 | AF56: 1.876933 | AG56: 1.967901 | AH56: 2.063403 | AI56: 2.16533 | AJ56: 0.098
A57: Compressed/Liquefied Natural Gas | B57: Freight: Truck Stock: Use: Light Medium: Natural Gas: High oil and gas supply | C57: 58-AEO2021.45.highogs-d120120a | D57: trillion Btu | E57: 0.072439 | F57: 0.101301 | G57: 0.130628 | H57: 0.155982 | I57: 0.179827 | J57: 0.2019 | K57: 0.22056 | L57: 0.237331 | M57: 0.254414 | N57: 0.271349 | O57: 0.288241 | P57: 0.304859 | Q57: 0.321 | R57: 0.336027 | S57: 0.351141 | T57: 0.366743 | U57: 0.381118 | V57: 0.394683 | W57: 0.408573 | X57: 0.422204 | Y57: 0.433602 | Z57: 0.44512 | AA57: 0.456742 | AB57: 0.469056 | AC57: 0.480455 | AD57: 0.492746 | AE57: 0.504659 | AF57: 0.518163 | AG57: 0.534254 | AH57: 0.551869 | AI57: 0.571567 | AJ57: 0.071
A58: Ethanol-Flex Fuel | B58: Freight: Truck Stock: Use: Light Medium: Ethanol-Flex Fuel: High oil and gas supply | C58: 58-AEO2021.46.highogs-d120120a | D58: trillion Btu | E58: 50.220936 | F58: 54.809902 | G58: 59.246746 | H58: 62.290188 | I58: 65.293396 | J58: 68.233864 | K58: 70.857208 | L58: 73.711029 | M58: 77.058762 | N58: 80.782852 | O58: 84.774193 | P58: 88.953712 | Q58: 93.29158 | R58: 97.603996 | S58: 102.05886 | T58: 106.79108 | U58: 111.35634 | V58: 116.0141 | W58: 120.90815 | X58: 126.06145 | Y58: 131.14949 | Z58: 136.87817 | AA58: 143.2412 | AB58: 150.21918 | AC58: 157.1794 | AD58: 164.68933 | AE58: 172.22414 | AF58: 180.23807 | AG58: 188.95334 | AH58: 198.01341 | AI58: 207.53979 | AJ58: 0.048
A59: Electric | B59: Freight: Truck Stock: Use: Light Medium: Electric: High oil and gas supply | C59: 58-AEO2021.47.highogs-d120120a | D59: trillion Btu | E59: 0.028212 | F59: 0.054613 | G59: 0.08473 | H59: 0.11513 | I59: 0.1469 | J59: 0.179347 | K59: 0.210444 | L59: 0.24114 | M59: 0.272809 | N59: 0.304808 | O59: 0.337367 | P59: 0.370432 | Q59: 0.403818 | R59: 0.436606 | S59: 0.470582 | T59: 0.506651 | U59: 0.542647 | V59: 0.579359 | W59: 0.61845 | X59: 0.658911 | Y59: 0.698811 | Z59: 0.740594 | AA59: 0.784091 | AB59: 0.829372 | AC59: 0.873107 | AD59: 0.91846 | AE59: 0.96304 | AF59: 1.009612 | AG59: 1.060153 | AH59: 1.1127 | AI59: 1.168803 | AJ59: 0.132
