Workbook
Name billion: [1]About!$A$93
Name billion: [2]About!$A$109
Name Eno_TM: '[3]1997 Table 1a Modified'!#REF!
Name Eno_TM: '[3]1997 Table 1a Modified'!#REF!
Name Eno_TM: '[3]1997 Table 1a Modified'!#REF!
Name Eno_TM: '[3]1997 Table 1a Modified'!#REF!
Name Eno_TM: '[3]1997 Table 1a Modified'!#REF!
Name Eno_Tons: '[3]1997 Table 1a Modified'!#REF!
Name Eno_Tons: '[3]1997 Table 1a Modified'!#REF!
Name Eno_Tons: '[3]1997 Table 1a Modified'!#REF!
Name Eno_Tons: '[3]1997 Table 1a Modified'!#REF!
Name Eno_Tons: '[3]1997 Table 1a Modified'!#REF!
Name NTS_YR: [4]About!$B$136
Name NTS_YR: About!$B$99
Name Sum_T2: '[3]1997 Table 1a Modified'!#REF!
Name Sum_T2: '[3]1997 Table 1a Modified'!#REF!
Name Sum_T2: '[3]1997 Table 1a Modified'!#REF!
Name Sum_T2: '[3]1997 Table 1a Modified'!#REF!
Name Sum_T2: '[3]1997 Table 1a Modified'!#REF!
Name Sum_TTM: '[3]1997 Table 1a Modified'!#REF!
Name Sum_TTM: '[3]1997 Table 1a Modified'!#REF!
Name Sum_TTM: '[3]1997 Table 1a Modified'!#REF!
Name Sum_TTM: '[3]1997 Table 1a Modified'!#REF!
Name Sum_TTM: '[3]1997 Table 1a Modified'!#REF!
Name ti_tbl_50: #REF!
Name ti_tbl_50: #REF!
Name ti_tbl_50: #REF!
Name ti_tbl_50: #REF!
Name ti_tbl_50: #REF!
Name ti_tbl_69: #REF!
Name ti_tbl_69: #REF!
Name ti_tbl_69: #REF!
Name ti_tbl_69: #REF!
Name ti_tbl_69: #REF!
Name trillion: [1]About!$A$94
Name trillion: [2]About!$A$110

Sheet About
A1: BNVFE BAU New Vehicle Fuel Economy
A3: Sources: | B3: See Notes section for which vehicle types use which sources
B4: EIA
B5: 2021, 2020
B6: Annual Energy Outlook 2021, 2020
B7: https://www.eia.gov/outlooks/aeo/tables_ref.cfm
B8: Tables 7, 35, 36, 38, 40, 47, 48, 49
B10: Bureau of Transportation Statistics
B11: 2017
B12: National Transportation Statistics
B13: https://www.rita.dot.gov/bts/sites/rita.dot.gov.bts/files/publications/national_transportation_statistics/index.html
B14: Table 1-40
B16: U.S. Coast Guard
B17: 2013
B18: National Recreational Boating Survey 2012
B19: http://www.uscgboating.org/library/recreational-boating-servey/2012survey%20report.pdf
B20: Page 63, Table 40
B22: U.S. Department of Energy
B23: 2015
B24: Fuel Cells Fact Sheet
B25: https://www.energy.gov/sites/prod/files/2015/11/f27/fcto_fuel_cells_fact_sheet.pdf
B27: Others as noted on "Calculations Etc" tab
B29: Passenger rail diesel vs. electric efficiency
B30: Environmental and Energy Study Institute
B31: 2018
B32: Electrification of U.S. Railways: Pie in the Sky, or Realistic Goal?
B33: https://www.eesi.org/articles/view/electrification-of-u.s.-railways-pie-in-the-sky-or-realistic-goal
B34: Third paragraph
A36: Notes
A37: This variable gives fuel economy for new vehicles in units of cargo distance per BTU.
A39: passenger LDVs
A40: Sources: AEO 7, AEO 40, others as noted on "Calculations Etc" tab
A41: The AEO provides new vehicle fuel economy in mpge terms. For each of the 7 EPS technologies, we take a weighted average of EIA's listed new vehicle
A42: fuel economy for all vehicles that would fall under the given technology. We then adjust by EIA's ratio of onroad:tested fuel economy from Table 7 and
A43: convert to thing-miles/BTU by multiplying by the passenger loading used in the file trans/AVLo and the BTU content of a gallon of gasoline.
A45: freight LDVs and HDVs
A46: Sources: see file trans/SYFAFE, AEO 7, AEO 49
A47: We classify AEO's light commercial trucks category as well as light-medium and medium duty vehicles
A48: in "freight LDVs" and heavy duty vehicles in "freight HDVs."
A50: The AEO does not contain information on the efficiency of new commercial light trucks broken out by vehicle technology. Therefore, we start with the
... A97: This vehicle type is not used in the U.S. model.
A99: NTS_YR | B99: 2019

Sheet AEO 7
B1: highogs.d120120a | C1: 2020 | D1: 2021 | E1: 2022 | F1: 2023 | G1: 2024 | H1: 2025 | I1: 2026 | J1: 2027 | K1: 2028 | L1: 2029 | M1: 2030 | N1: 2031 | O1: 2032 | P1: 2033 | Q1: 2034 | R1: 2035 | S1: 2036 | T1: 2037 | U1: 2038 | V1: 2039 | W1: 2040 | X1: 2041 | Y1: 2042 | Z1: 2043 | AA1: 2044 | AB1: 2045 | AC1: 2046 | AD1: 2047 | AE1: 2048 | AF1: 2049 | AG1: 2050
C3: Report | D3: Annual Energy Outlook 2021
C4: Scenario | D4: ref2021 | G4: Reference case
C5: Datekey | D5: d113020a
C6: Release Date | E6: January 2021
A10: TKI000 | B10: 7. Transportation Sector Key Indicators and Delivered Energy Consumption | AH10: Compound
AH11: Growth
AH12: 2020-2050
B13: Key Indicators and Consumption | C13: 2020 | D13: 2021 | E13: 2022 | F13: 2023 | G13: 2024 | H13: 2025 | I13: 2026 | J13: 2027 | K13: 2028 | L13: 2029 | M13: 2030 | N13: 2031 | O13: 2032 | P13: 2033 | Q13: 2034 | R13: 2035 | S13: 2036 | T13: 2037 | U13: 2038 | V13: 2039 | W13: 2040 | X13: 2041 | Y13: 2042 | Z13: 2043 | AA13: 2044 | AB13: 2045 | AC13: 2046 | AD13: 2047 | AE13: 2048 | AF13: 2049 | AG13: 2050 | AH13: (percent)
B15: Key Indicators
B16: Travel Indicators
B17: (billion vehicle miles traveled)
A18: TKI000:ba_Light-DutyVeh | B18: Light-Duty Vehicles less than 8,501 pounds | C18: 2628.8213 | D18: 2807.2766 | E18: 2862.5334 | F18: 2927.623 | G18: 2985.1787 | H18: 3035.5583 | I18: 3076.646 | J18: 3107.3425 | K18: 3133.9348 | L18: 3153.6963 | M18: 3170.1406 | N18: 3182.3604 | O18: 3194.3308 | P18: 3208.3691 | Q18: 3223.0125 | R18: 3240.585 | S18: 3258.4961 | T18: 3274.8767 | U18: 3290.0166 | V18: 3306.9768 | W18: 3326.3066 | X18: 3344.3862 | Y18: 3362.8257 | Z18: 3380.6958 | AA18: 3396.752 | AB18: 3412.0305 | AC18: 3428.1084 | AD18: 3442.5149 | AE18: 3458.3401 | AF18: 3474.7087 | AG18: 3490.9399 | AH18: 0.009499
A19: TKI000:ba_CommercialLig | B19: Commercial Light Trucks 1/ | C19: 89.884674 | D19: 93.705605 | E19: 96.386086 | F19: 98.338295 | G19: 100.59341 | H19: 102.85941 | I19: 104.50481 | J19: 105.69051 | K19: 106.73648 | L19: 107.65262 | M19: 108.58299 | N19: 109.54169 | O19: 110.61884 | P19: 111.70705 | Q19: 112.95861 | R19: 114.4644 | S19: 115.90713 | T19: 117.2149 | U19: 118.58162 | V19: 120.04366 | W19: 121.52813 | X19: 123.15266 | Y19: 124.79562 | Z19: 126.54729 | AA19: 128.13809 | AB19: 129.78653 | AC19: 131.39938 | AD19: 132.81888 | AE19: 134.41592 | AF19: 136.18376 | AG19: 138.01 | AH19: 0.014396
A20: TKI000:ba_FreightTrucks | B20: Freight Trucks greater than 10,000 pounds | C20: 274.54938 | D20: 282.81525 | E20: 293.31253 | F20: 299.26825 | G20: 306.24057 | H20: 313.39252 | I20: 318.20425 | J20: 321.86676 | K20: 325.49912 | L20: 328.91818 | M20: 332.87759 | N20: 337.04804 | O20: 341.41943 | P20: 345.24298 | Q20: 349.75104 | R20: 355.3486 | S20: 360.47449 | T20: 365.30786 | U20: 370.46982 | V20: 375.98251 | W20: 381.01727 | X20: 386.70856 | Y20: 392.7948 | Z20: 399.70087 | AA20: 405.64847 | AB20: 411.79804 | AC20: 417.07053 | AD20: 422.22894 | AE20: 428.00507 | AF20: 434.11798 | AG20: 440.79153 | AH20: 0.015907
B21: (billion passenger miles traveled)
A22: TKI000:buspassmiles | B22: Bus Transportation | C22: 108.32251 | D22: 134.82925 | E22: 154.71742 | F22: 169.65283 | G22: 180.92081 | H22: 189.4493 | I22: 195.91775 | J22: 200.87158 | K22: 204.4294 | L22: 207.17819 | M22: 209.42627 | N22: 211.01544 | O22: 212.35484 | P22: 213.3685 | Q22: 214.16457 | R22: 214.70816 | S22: 215.16942 | T22: 215.53513 | U22: 215.80548 | V22: 215.98587 | W22: 216.16197 | X22: 216.26544 | Y22: 216.33122 | Z22: 216.37845 | AA22: 216.40999 | AB22: 216.44157 | AC22: 216.45151 | AD22: 216.46837 | AE22: 216.483 | AF22: 216.55254 | AG22: 216.64348 | AH22: 0.023374
A23: TKI000:railpassmiles | B23: Passenger Rail | C23: 24.970692 | D23: 29.653244 | E23: 33.486446 | F23: 36.386101 | G23: 38.577961 | H23: 40.222988 | I23: 41.396164 | J23: 42.264778 | K23: 42.515728 | L23: 42.713291 | M23: 43.137005 | N23: 43.343742 | O23: 43.818241 | P23: 44.274139 | Q23: 44.835865 | R23: 45.310886 | S23: 45.831734 | T23: 46.32793 | U23: 46.816154 | V23: 47.317448 | W23: 47.980492 | X23: 48.58215 | Y23: 49.164021 | Z23: 49.763081 | AA23: 50.334721 | AB23: 50.97802 | AC23: 51.558666 | AD23: 52.079247 | AE23: 52.647175 | AF23: 53.282265 | AG23: 53.912506 | AH23: 0.025987
B24: (billion seat miles available)
A25: TKI000:ba_Air | B25: Air | C25: 738.85895 | D25: 1081.6603 | E25: 1215.7373 | F25: 1284.3009 | G25: 1340.2419 | H25: 1397.254 | I25: 1430.9814 | J25: 1455.4497 | K25: 1476.5328 | L25: 1495.9988 | M25: 1516.3666 | N25: 1539.9563 | O25: 1569.8956 | P25: 1600.4498 | Q25: 1634.8596 | R25: 1672.6685 | S25: 1707.1351 | T25: 1738.4458 | U25: 1770.8867 | V25: 1807.5973 | W25: 1848.892 | X25: 1889.7706 | Y25: 1930.5969 | Z25: 1971.072 | AA25: 2010.4889 | AB25: 2052.9485 | AC25: 2092.6599 | AD25: 2129.1379 | AE25: 2171.0725 | AF25: 2213.2192 | AG25: 2256.3169 | AH25: 0.037914
B26: (billion ton miles traveled)
A27: TKI000:ba_Rail | B27: Rail | C27: 1508.557 | D27: 1600.7733 | E27: 1616.5277 | F27: 1618.1086 | G27: 1617.9658 | H27: 1567.8839 | I27: 1587.1537 | J27: 1586.3214 | K27: 1606.0509 | L27: 1623.5897 | M27: 1641.5112 | N27: 1654.2195 | O27: 1664.4609 | P27: 1678.1671 | Q27: 1686.5093 | R27: 1700.8228 | S27: 1714.3484 | T27: 1725.9465 | U27: 1730.047 | V27: 1747.595 | W27: 1753.4669 | X27: 1765.8125 | Y27: 1783.1677 | Z27: 1804.6465 | AA27: 1808.4172 | AB27: 1822.5868 | AC27: 1832.4125 | AD27: 1846.7275 | AE27: 1860.8992 | AF27: 1876.0131 | AG27: 1898.7479 | AH27: 0.007697
A28: TKI000:ba_DomesticShipp | B28: Domestic Shipping | C28: 347.68133 | D28: 359.32346 | E28: 357.10059 | F28: 354.90668 | G28: 352.6954 | H28: 348.07819 | I28: 341.28058 | J28: 333.10046 | K28: 325.25259 | L28: 316.86505 | M28: 308.73145 | N28: 305.11627 | O28: 301.85187 | P28: 298.30835 | Q28: 295.38019 | R28: 292.62634 | S28: 289.63 | T28: 286.27258 | U28: 282.6651 | V28: 279.71716 | W28: 276.01688 | X28: 275.42545 | Y28: 275.00784 | Z28: 275.36859 | AA28: 274.91849 | AB28: 274.56326 | AC28: 273.54471 | AD28: 272.61859 | AE28: 271.43494 | AF28: 270.55728 | AG28: 270.13117 | AH28: -0.008377
B30: Energy Efficiency Indicators
B31: (miles per gallon)
A32: TKI000:ca_AvgCAFEStand | B32: New Light-Duty Vehicle CAFE Standard 2/ | C32: 34.471165 | D32: 35.386478 | E32: 36.015511 | F32: 36.532135 | G32: 36.999756 | H32: 37.485561 | I32: 38.067947 | J32: 38.072563 | K32: 38.080814 | L32: 38.095245 | M32: 38.18074 | N32: 38.191765 | O32: 38.206318 | P32: 38.220623 | Q32: 38.249493 | R32: 38.23008 | S32: 38.209507 | T32: 38.204479 | U32: 38.204224 | V32: 38.187893 | W32: 38.180141 | X32: 38.173969 | Y32: 38.160957 | Z32: 38.151768 | AA32: 38.148342 | AB32: 38.153297 | AC32: 38.143864 | AD32: 38.134365 | AE32: 38.120548 | AF32: 38.116928 | AG32: 38.114223 | AH32: 0.003354
A33: TKI000:ca_CarCAFEStand | B33: New Car 2/ | C33: 42.096588 | D33: 44.275085 | E33: 44.804096 | F33: 45.431927 | G33: 46.163593 | H33: 46.83271 | I33: 47.617275 | J33: 47.640335 | K33: 47.640335 | L33: 47.644814 | M33: 47.681995 | N33: 47.681995 | O33: 47.681995 | P33: 47.681995 | Q33: 47.681995 | R33: 47.681995 | S33: 47.681995 | T33: 47.681995 | U33: 47.681995 | V33: 47.681995 | W33: 47.681995 | X33: 47.681995 | Y33: 47.681995 | Z33: 47.683205 | AA33: 47.684814 | AB33: 47.687138 | AC33: 47.687138 | AD33: 47.687138 | AE33: 47.687138 | AF33: 47.689449 | AG33: 47.689449 | AH33: 0.004167
A34: TKI000:ca_TwukCAFEStand | B34: New Light Truck 2/ | C34: 30.906752 | D34: 31.515783 | E34: 31.942911 | F34: 32.461285 | G34: 32.91795 | H34: 33.400791 | I34: 33.955074 | J34: 33.955074 | K34: 33.955074 | L34: 33.955074 | M34: 33.955074 | N34: 33.955093 | O34: 33.955093 | P34: 33.955093 | Q34: 33.955093 | R34: 33.955128 | S34: 33.955128 | T34: 33.955128 | U34: 33.955128 | V34: 33.955128 | W34: 33.955128 | X34: 33.955128 | Y34: 33.955128 | Z34: 33.955128 | AA34: 33.955128 | AB34: 33.955128 | AC34: 33.955128 | AD34: 33.955128 | AE34: 33.955128 | AF34: 33.955128 | AG34: 33.955128 | AH34: 0.00314
A35: TKI000:ca_NewVehCred | B35: Compliance New Light-Duty Vehicle 3/ | C35: 35.428043 | D35: 36.588161 | E35: 37.27243 | F35: 37.693687 | G35: 38.000156 | H35: 38.414772 | I35: 38.930225 | J35: 39.067493 | K35: 39.131561 | L35: 39.187084 | M35: 39.367001 | N35: 39.458767 | O35: 39.570412 | P35: 39.688381 | Q35: 39.842903 | R35: 39.925739 | S35: 40.007633 | T35: 40.122059 | U35: 40.263226 | V35: 40.363659 | W35: 40.483315 | X35: 40.567554 | Y35: 40.636898 | Z35: 40.715225 | AA35: 40.813824 | AB35: 40.933929 | AC35: 41.032745 | AD35: 41.136253 | AE35: 41.233734 | AF35: 41.366283 | AG35: 41.510693 | AH35: 0.005296
A36: TKI000:ca_NewCarCred | B36: New Car 3/ | C36: 43.264011 | D36: 45.133469 | E36: 45.638382 | F36: 46.329559 | G36: 46.974045 | H36: 47.544498 | I36: 48.288284 | J36: 48.41925 | K36: 48.519196 | L36: 48.602192 | M36: 48.75803 | N36: 48.944359 | O36: 49.116051 | P36: 49.343533 | Q36: 49.588879 | R36: 49.838387 | S36: 50.062164 | T36: 50.324268 | U36: 50.609341 | V36: 50.887779 | W36: 51.161552 | X36: 51.375084 | Y36: 51.577618 | Z36: 51.784939 | AA36: 52.021469 | AB36: 52.278286 | AC36: 52.554256 | AD36: 52.823685 | AE36: 53.105881 | AF36: 53.415283 | AG36: 53.766708 | AH36: 0.007271
A37: TKI000:ca_NewTwukCred | B37: New Light Truck 3/ | C37: 31.76507 | D37: 32.790131 | E37: 33.304337 | F37: 33.675228 | G37: 33.948895 | H37: 34.370636 | I37: 34.850887 | J37: 34.987331 | K37: 35.027725 | L37: 35.055889 | M37: 35.139996 | N37: 35.184067 | O37: 35.253815 | P37: 35.313755 | Q37: 35.395432 | R37: 35.447819 | S37: 35.509632 | T37: 35.58049 | U37: 35.672146 | V37: 35.736599 | W37: 35.81567 | X37: 35.86631 | Y37: 35.911537 | Z37: 35.962078 | AA37: 36.021683 | AB37: 36.09063 | AC37: 36.147751 | AD37: 36.213341 | AE37: 36.274784 | AF37: 36.358318 | AG37: 36.442936 | AH37: 0.00459
A38: TKI000:ca_TestedNewVeh | B38: Tested New Light-Duty Vehicle 4/ | C38: 35.306622 | D38: 36.467899 | E38: 37.145805 | F38: 37.564754 | G38: 37.869587 | H38: 38.261166 | I38: 38.678329 | J38: 38.78212 | K38: 38.833714 | L38: 38.876083 | M38: 39.031017 | N38: 39.097122 | O38: 39.178814 | P38: 39.263397 | Q38: 39.380604 | R38: 39.428646 | S38: 39.476784 | T38: 39.553841 | U38: 39.655148 | V38: 39.718605 | W38: 39.800255 | X38: 39.857685 | Y38: 39.902508 | Z38: 39.954895 | AA38: 40.024872 | AB38: 40.112934 | AC38: 40.181061 | AD38: 40.254047 | AE38: 40.320404 | AF38: 40.416508 | AG38: 40.5215 | AH38: 0.004603
A39: TKI000:ca_TestedNewCar | B39: New Car 4/ | C39: 42.996372 | D39: 44.88583 | E39: 45.388092 | F39: 46.068283 | G39: 46.702301 | H39: 47.265957 | I39: 47.99147 | J39: 48.105293 | K39: 48.179577 | L39: 48.231701 | M39: 48.343479 | N39: 48.473526 | O39: 48.589264 | P39: 48.747791 | Q39: 48.918312 | R39: 49.08532 | S39: 49.232788 | T39: 49.410698 | U39: 49.605431 | V39: 49.791992 | W39: 49.975594 | X39: 50.118858 | Y39: 50.253036 | Z39: 50.390747 | AA39: 50.551331 | AB39: 50.726044 | AC39: 50.913406 | AD39: 51.097149 | AE39: 51.287189 | AF39: 51.498287 | AG39: 51.738174 | AH39: 0.006188
A40: TKI000:ca_TestedNewTwuk | B40: New Light Truck 4/ | C40: 31.69734 | D40: 32.714512 | E40: 33.224262 | F40: 33.594929 | G40: 33.868374 | H40: 34.261593 | I40: 34.620468 | J40: 34.71925 | K40: 34.751755 | L40: 34.772854 | M40: 34.839573 | N40: 34.86882 | O40: 34.918171 | P40: 34.957504 | Q40: 35.015827 | R40: 35.049236 | S40: 35.091114 | T40: 35.140182 | U40: 35.208858 | V40: 35.253445 | W40: 35.311043 | X40: 35.348305 | Y40: 35.381889 | Z40: 35.41943 | AA40: 35.464706 | AB40: 35.517353 | AC40: 35.560341 | AD40: 35.610996 | AE40: 35.657856 | AF40: 35.722626 | AG40: 35.788242 | AH40: 0.004054
A41: TKI000:ca_OnRoadNewVeh | B41: On-Road New Light-Duty Vehicle 5/ | C41: 28.801699 | D41: 29.748508 | E41: 30.302168 | F41: 30.643736 | G41: 30.892097 | H41: 31.211321 | I41: 31.551422 | J41: 31.636091 | K41: 31.678196 | L41: 31.712803 | M41: 31.839462 | N41: 31.893412 | O41: 31.960094 | P41: 32.029114 | Q41: 32.124813 | R41: 32.16391 | S41: 32.203083 | T41: 32.2659 | U41: 32.348515 | V41: 32.400196 | W41: 32.466755 | X41: 32.513561 | Y41: 32.550056 | Z41: 32.592743 | AA41: 32.649788 | AB41: 32.721619 | AC41: 32.77713 | AD41: 32.836617 | AE41: 32.890667 | AF41: 32.969021 | AG41: 33.054626 | AH41: 0.004601
A42: TKI000:ca_OnRoadNewCar | B42: New Car 5/ | C42: 35.111473 | D42: 36.65443 | E42: 37.064587 | F42: 37.620041 | G42: 38.137787 | H42: 38.598076 | I42: 39.190544 | J42: 39.283493 | K42: 39.344154 | L42: 39.386719 | M42: 39.477997 | N42: 39.584198 | O42: 39.678711 | P42: 39.808167 | Q42: 39.947414 | R42: 40.083797 | S42: 40.20422 | T42: 40.349506 | U42: 40.508526 | V42: 40.660873 | W42: 40.810806 | X42: 40.927799 | Y42: 41.037373 | Z42: 41.149826 | AA42: 41.280964 | AB42: 41.423634 | AC42: 41.576637 | AD42: 41.726685 | AE42: 41.881874 | AF42: 42.05426 | AG42: 42.250156 | AH42: 0.006188
A43: TKI000:ca_OnRoadNewTwuk | B43: New Light Truck 5/ | C43: 25.844681 | D43: 26.67404 | E43: 27.08967 | F43: 27.391895 | G43: 27.614851 | H43: 27.935465 | I43: 28.228077 | J43: 28.30862 | K43: 28.335123 | L43: 28.352325 | M43: 28.406727 | N43: 28.430573 | O43: 28.470812 | P43: 28.502882 | Q43: 28.550436 | R43: 28.577677 | S43: 28.611822 | T43: 28.651831 | U43: 28.707827 | V43: 28.744179 | W43: 28.791143 | X43: 28.821524 | Y43: 28.848907 | Z43: 28.879517 | AA43: 28.916433 | AB43: 28.95936 | AC43: 28.99441 | AD43: 29.035711 | AE43: 29.073919 | AF43: 29.12673 | AG43: 29.180231 | AH43: 0.004054
... A47: TKI000:ca_FreightTruck | B47: Freight Truck | C47: 7.238182 | D47: 7.310616 | E47: 7.389947 | F47: 7.476684 | G47: 7.574702 | H47: 7.686319 | I47: 7.80973 | J47: 7.944551 | K47: 8.083447 | L47: 8.230841 | M47: 8.382581 | N47: 8.536425 | O47: 8.686997 | P47: 8.827357 | Q47: 8.956337 | R47: 9.073474 | S47: 9.178899 | T47: 9.273054 | U47: 9.358724 | V47: 9.437573 | W47: 9.508476 | X47: 9.572987 | Y47: 9.62975 | Z47: 9.67997 | AA47: 9.724974 | AB47: 9.767028 | AC47: 9.806892 | AD47: 9.846315 | AE47: 9.885777 | AF47: 9.92395 | AG47: 9.961658 | AH47: 0.010703
B48: (seat miles per gallon)
A49: TKI000:ca_Aircraft | B49: Aircraft | C49: 71.028343 | D49: 72.22039 | E49: 72.564766 | F49: 73.078918 | G49: 73.855469 | H49: 74.440651 | I49: 74.946922 | J49: 75.432518 | K49: 75.920792 | L49: 76.399239 | M49: 76.903839 | N49: 77.42765 | O49: 77.983635 | P49: 78.569893 | Q49: 79.171509 | R49: 79.79718 | S49: 80.421959 | T49: 81.046387 | U49: 81.662766 | V49: 82.260727 | W49: 82.849083 | X49: 83.43293 | Y49: 84.016846 | Z49: 84.607124 | AA49: 85.178467 | AB49: 85.733246 | AC49: 86.278442 | AD49: 86.813042 | AE49: 87.369904 | AF49: 87.921379 | AG49: 88.469986 | AH49: 0.007346
B50: (ton miles/thousand Btu)
A51: TKI000:ca_Rail | B51: Rail | C51: 3.489371 | D51: 3.512003 | E51: 3.534782 | F51: 3.55771 | G51: 3.580785 | H51: 3.60401 | I51: 3.627386 | J51: 3.650914 | K51: 3.674594 | L51: 3.698428 | M51: 3.722416 | N51: 3.74656 | O51: 3.77086 | P51: 3.795318 | Q51: 3.819935 | R51: 3.844712 | S51: 3.869649 | T51: 3.894748 | U51: 3.920009 | V51: 3.945435 | W51: 3.971025 | X51: 3.996782 | Y51: 4.022705 | Z51: 4.048797 | AA51: 4.075058 | AB51: 4.101489 | AC51: 4.128091 | AD51: 4.154866 | AE51: 4.181815 | AF51: 4.208939 | AG51: 4.236238 | AH51: 0.006486
A52: TKI000:ca_DomesticShipp | B52: Domestic Shipping | C52: 4.84196 | D52: 4.870726 | E52: 4.899663 | F52: 4.928772 | G52: 4.958054 | H52: 4.987509 | I52: 5.01714 | J52: 5.046947 | K52: 5.076931 | L52: 5.107092 | M52: 5.137434 | N52: 5.167955 | O52: 5.198658 | P52: 5.229543 | Q52: 5.260611 | R52: 5.291864 | S52: 5.323303 | T52: 5.354929 | U52: 5.386742 | V52: 5.418745 | W52: 5.450938 | X52: 5.483322 | Y52: 5.515898 | Z52: 5.548667 | AA52: 5.581632 | AB52: 5.614792 | AC52: 5.64815 | AD52: 5.681705 | AE52: 5.71546 | AF52: 5.749416 | AG52: 5.783573 | AH52: 0.005941
B54: Energy Use by Mode
B55: (quadrillion Btu)
A56: TKI000:da_Light-DutyVeh | B56: Light-Duty Vehicles | C56: 13.684958 | D56: 14.333231 | E56: 14.327022 | F56: 14.365352 | G56: 14.366455 | H56: 14.341867 | I56: 14.287132 | J56: 14.207239 | K56: 14.125376 | L56: 14.028779 | M56: 13.931946 | N56: 13.831038 | O56: 13.740598 | P56: 13.671222 | Q56: 13.614177 | R56: 13.578903 | S56: 13.555063 | T56: 13.533011 | U56: 13.512934 | V56: 13.507698 | W56: 13.519425 | X56: 13.531686 | Y56: 13.55102 | Z56: 13.573046 | AA56: 13.591692 | AB56: 13.608699 | AC56: 13.631719 | AD56: 13.65046 | AE56: 13.676695 | AF56: 13.70651 | AG56: 13.736445 | AH56: 0.000125
A57: TKI000:da_CommercialLig | B57: Commercial Light Trucks 1/ | C57: 0.800598 | D57: 0.824583 | E57: 0.83718 | F57: 0.842737 | G57: 0.851008 | H57: 0.861964 | I57: 0.867177 | J57: 0.868256 | K57: 0.868721 | L57: 0.868144 | M57: 0.86827 | N57: 0.869091 | O57: 0.871659 | P57: 0.875056 | Q57: 0.880524 | R57: 0.888546 | S57: 0.896605 | T57: 0.904579 | U57: 0.913077 | V57: 0.922396 | W57: 0.932011 | X57: 0.942835 | Y57: 0.95338 | Z57: 0.965235 | AA57: 0.976007 | AB57: 0.987214 | AC57: 0.999347 | AD57: 1.008795 | AE57: 1.01946 | AF57: 1.031487 | AG57: 1.044088 | AH57: 0.008891
A58: TKI000:da_BusTransporta | B58: Bus Transportation | C58: 0.123601 | D58: 0.155229 | E58: 0.178087 | F58: 0.194794 | G58: 0.207087 | H58: 0.215933 | I58: 0.222447 | J58: 0.227387 | K58: 0.229827 | L58: 0.231575 | M58: 0.233385 | N58: 0.233909 | O58: 0.234577 | P58: 0.234898 | Q58: 0.235117 | R58: 0.234732 | S58: 0.234535 | T58: 0.234329 | U58: 0.233979 | V58: 0.23339 | W58: 0.232922 | X58: 0.232252 | Y58: 0.231514 | Z58: 0.230767 | AA58: 0.230025 | AB58: 0.229276 | AC58: 0.228442 | AD58: 0.227697 | AE58: 0.226858 | AF58: 0.226287 | AG58: 0.225795 | AH58: 0.020289
A59: TKI000:da_FreightTrucks | B59: Freight Trucks | C59: 5.215993 | D59: 5.320461 | E59: 5.459595 | F59: 5.506526 | G59: 5.562604 | H59: 5.610408 | I59: 5.606836 | J59: 5.575173 | K59: 5.54105 | L59: 5.498658 | M59: 5.463652 | N59: 5.431874 | O59: 5.406318 | P59: 5.379243 | Q59: 5.370211 | R59: 5.384785 | S59: 5.398619 | T59: 5.414024 | U59: 5.438496 | V59: 5.471154 | W59: 5.50076 | X59: 5.54297 | Y59: 5.59491 | Z59: 5.661906 | AA59: 5.718006 | AB59: 5.778462 | AC59: 5.827639 | AD59: 5.875145 | AE59: 5.930928 | AF59: 5.991611 | AG59: 6.059749 | AH59: 0.00501
A60: TKI000:da_Rail,Passenge | B60: Rail, Passenger | C60: 0.029437 | D60: 0.035251 | E60: 0.039934 | F60: 0.043478 | G60: 0.046156 | H60: 0.048166 | I60: 0.049615 | J60: 0.050695 | K60: 0.051001 | L60: 0.05125 | M60: 0.051752 | N60: 0.052019 | O60: 0.052574 | P60: 0.053111 | Q60: 0.053765 | R60: 0.05433 | S60: 0.054952 | T60: 0.05555 | U60: 0.056141 | V60: 0.056752 | W60: 0.057542 | X60: 0.058268 | Y60: 0.058979 | Z60: 0.059712 | AA60: 0.060418 | AB60: 0.061203 | AC60: 0.061918 | AD60: 0.062563 | AE60: 0.063254 | AF60: 0.064012 | AG60: 0.064756 | AH60: 0.026627
A61: TKI000:da_Rail,Freight | B61: Rail, Freight | C61: 0.432329 | D61: 0.455801 | E61: 0.45732 | F61: 0.454818 | G61: 0.451847 | H61: 0.435039 | I61: 0.437548 | J61: 0.4345 | K61: 0.437069 | L61: 0.438995 | M61: 0.44098 | N61: 0.44153 | O61: 0.441401 | P61: 0.442168 | Q61: 0.441502 | R61: 0.44238 | S61: 0.443024 | T61: 0.443147 | U61: 0.441338 | V61: 0.442941 | W61: 0.441565 | X61: 0.441809 | Y61: 0.443276 | Z61: 0.445724 | AA61: 0.443777 | AB61: 0.444372 | AC61: 0.443889 | AD61: 0.444473 | AE61: 0.444998 | AF61: 0.445721 | AG61: 0.448216 | AH61: 0.001204
A62: TKI000:da_Shipping,Dome | B62: Shipping, Domestic | C62: 0.077343 | D62: 0.079141 | E62: 0.078228 | F62: 0.07735 | G62: 0.076447 | H62: 0.075056 | I62: 0.073205 | J62: 0.071058 | K62: 0.068995 | L62: 0.066834 | M62: 0.064753 | N62: 0.063638 | O62: 0.062605 | P62: 0.061511 | Q62: 0.060562 | R62: 0.059665 | S62: 0.058721 | T62: 0.057711 | U62: 0.056659 | V62: 0.055745 | W62: 0.054692 | X62: 0.054265 | Y62: 0.053874 | Z62: 0.053634 | AA62: 0.05324 | AB62: 0.052873 | AC62: 0.052373 | AD62: 0.051891 | AE62: 0.05137 | AF62: 0.05091 | AG62: 0.050533 | AH62: -0.014087
A63: TKI000:da_Shipping,Inte | B63: Shipping, International | C63: 0.855887 | D63: 0.881465 | E63: 0.973998 | F63: 0.992193 | G63: 0.941402 | H63: 0.944552 | I63: 0.956481 | J63: 0.933812 | K63: 0.934805 | L63: 0.926796 | M63: 0.92926 | N63: 0.946328 | O63: 0.931566 | P63: 0.932016 | Q63: 0.929677 | R63: 0.944409 | S63: 0.930073 | T63: 0.929561 | U63: 0.939661 | V63: 0.926163 | W63: 0.924429 | X63: 0.937035 | Y63: 0.921133 | Z63: 0.92034 | AA63: 0.913829 | AB63: 0.914233 | AC63: 0.910465 | AD63: 0.908206 | AE63: 0.908689 | AF63: 0.907332 | AG63: 0.904865 | AH63: 0.001857
A64: TKI000:da_RecreationalB | B64: Recreational Boats | C64: 0.195878 | D64: 0.196657 | E64: 0.199716 | F64: 0.201514 | G64: 0.202257 | H64: 0.202574 | I64: 0.201854 | J64: 0.200378 | K64: 0.198674 | L64: 0.19683 | M64: 0.195069 | N64: 0.193556 | O64: 0.192489 | P64: 0.191383 | Q64: 0.190484 | R64: 0.189818 | S64: 0.18891 | T64: 0.187759 | U64: 0.186658 | V64: 0.185802 | W64: 0.185223 | X64: 0.184588 | Y64: 0.183882 | Z64: 0.183175 | AA64: 0.182329 | AB64: 0.18168 | AC64: 0.180906 | AD64: 0.17988 | AE64: 0.17914 | AF64: 0.178366 | AG64: 0.177572 | AH64: -0.003265
A65: TKI000:da_Air | B65: Air | C65: 1.860485 | D65: 2.530984 | E65: 2.826346 | F65: 2.963305 | G65: 3.051768 | H65: 3.120219 | I65: 3.144242 | J65: 3.161629 | K65: 3.182792 | L65: 3.201851 | M65: 3.222472 | N65: 3.248707 | O65: 3.287299 | P65: 3.325297 | Q65: 3.36779 | R65: 3.416815 | S65: 3.457473 | T65: 3.492202 | U65: 3.528905 | V65: 3.570296 | W65: 3.622022 | X65: 3.669847 | Y65: 3.719 | Z65: 3.765759 | AA65: 3.814193 | AB65: 3.866814 | AC65: 3.914752 | AD65: 3.951365 | AE65: 3.990626 | AF65: 4.026413 | AG65: 4.062809 | AH65: 0.026376
A66: TKI000:da_MilitaryUse | B66: Military Use | C66: 0.535966 | D66: 0.545011 | E66: 0.545749 | F66: 0.53257 | G66: 0.52388 | H66: 0.523357 | I66: 0.5221 | J66: 0.52193 | K66: 0.524808 | L66: 0.52365 | M66: 0.521666 | N66: 0.521585 | O66: 0.52242 | P66: 0.523287 | Q66: 0.524164 | R66: 0.525042 | S66: 0.525958 | T66: 0.526906 | U66: 0.527867 | V66: 0.528832 | W66: 0.529807 | X66: 0.530791 | Y66: 0.531775 | Z66: 0.532766 | AA66: 0.533758 | AB66: 0.534753 | AC66: 0.535749 | AD66: 0.536745 | AE66: 0.53774 | AF66: 0.538735 | AG66: 0.539727 | AH66: 0.000233
A67: TKI000:da_Lubricants | B67: Lubricants | C67: 0.121224 | D67: 0.1234 | E67: 0.124821 | F67: 0.125915 | G67: 0.126656 | H67: 0.127041 | I67: 0.127207 | J67: 0.126854 | K67: 0.126597 | L67: 0.126378 | M67: 0.126074 | N67: 0.125802 | O67: 0.125585 | P67: 0.125401 | Q67: 0.125289 | R67: 0.125205 | S67: 0.125084 | T67: 0.124934 | U67: 0.12483 | V67: 0.124758 | W67: 0.124673 | X67: 0.124589 | Y67: 0.124522 | Z67: 0.12444 | AA67: 0.124423 | AB67: 0.124498 | AC67: 0.124516 | AD67: 0.124474 | AE67: 0.124496 | AF67: 0.12447 | AG67: 0.124386 | AH67: 0.000858
... A69: TKI000:da_Total | B69: Total | C69: 24.63995 | D69: 26.246357 | E69: 26.803347 | F69: 27.032192 | G69: 27.130775 | H69: 27.230783 | I69: 27.186893 | J69: 27.080057 | K69: 26.990782 | L69: 26.860777 | M69: 26.742741 | N69: 26.653553 | O69: 26.566212 | P69: 26.51256 | Q69: 26.490156 | R69: 26.545183 | S69: 26.577869 | T69: 26.62192 | U69: 26.686522 | V69: 26.75659 | W69: 26.859634 | X69: 26.988043 | Y69: 27.108532 | Z69: 27.264854 | AA69: 27.401077 | AB69: 27.549936 | AC69: 27.685604 | AD69: 27.804758 | AE69: 27.932571 | AF69: 28.069273 | AG69: 28.223778 | AH69: 0.004537
B71: (million barrels per day oil equivalent)
A72: TKI000:ea_Light-DutyVeh | B72: Light-Duty Vehicles | C72: 7.422104 | D72: 7.773714 | E72: 7.769763 | F72: 7.790549 | G72: 7.790876 | H72: 7.778635 | I72: 7.749986 | J72: 7.707629 | K72: 7.66415 | L72: 7.612647 | M72: 7.560986 | N72: 7.507026 | O72: 7.458717 | P72: 7.421792 | Q72: 7.391498 | R72: 7.373047 | S72: 7.360369 | T72: 7.34863 | U72: 7.337916 | V72: 7.33523 | W72: 7.341699 | X72: 7.348314 | Y72: 7.358773 | Z72: 7.37068 | AA72: 7.380744 | AB72: 7.389912 | AC72: 7.40236 | AD72: 7.412508 | AE72: 7.426698 | AF72: 7.442851 | AG72: 7.459049 | AH72: 0.000166
A73: TKI000:ea_CommercialLig | B73: Commercial Light Trucks 1/ | C73: 0.417402 | D73: 0.429752 | E73: 0.4361 | F73: 0.438805 | G73: 0.442896 | H73: 0.448514 | I73: 0.451192 | J73: 0.451773 | K73: 0.452056 | L73: 0.451855 | M73: 0.452067 | N73: 0.452658 | O73: 0.454179 | P73: 0.456158 | Q73: 0.459232 | R73: 0.463664 | S73: 0.46811 | T73: 0.472552 | U73: 0.477285 | V73: 0.48244 | W73: 0.487753 | X73: 0.493671 | Y73: 0.499459 | Z73: 0.505901 | AA73: 0.511755 | AB73: 0.517801 | AC73: 0.524376 | AD73: 0.529585 | AE73: 0.535473 | AF73: 0.542111 | AG73: 0.549078 | AH73: 0.009181
A74: TKI000:ea_BusTransporta | B74: Bus Transportation | C74: 0.059765 | D74: 0.07508 | E74: 0.08616 | F74: 0.094233 | G74: 0.100171 | H74: 0.104438 | I74: 0.107584 | J74: 0.109979 | K74: 0.111142 | L74: 0.111985 | M74: 0.112868 | N74: 0.113118 | O74: 0.113448 | P74: 0.113605 | Q74: 0.113716 | R74: 0.11353 | S74: 0.113436 | T74: 0.113336 | U74: 0.113171 | V74: 0.112886 | W74: 0.112663 | X74: 0.112337 | Y74: 0.11198 | Z74: 0.11162 | AA74: 0.111264 | AB74: 0.110882 | AC74: 0.110487 | AD74: 0.110127 | AE74: 0.109734 | AF74: 0.109462 | AG74: 0.109221 | AH74: 0.020302
A75: TKI000:ea_FreightTrucks | B75: Freight Trucks | C75: 2.511301 | D75: 2.562341 | E75: 2.62972 | F75: 2.651934 | G75: 2.678503 | H75: 2.701084 | I75: 2.699315 | J75: 2.684517 | K75: 2.668267 | L75: 2.648567 | M75: 2.632661 | N75: 2.618124 | O75: 2.60683 | P75: 2.594657 | Q75: 2.591201 | R75: 2.599064 | S75: 2.606463 | T75: 2.614655 | U75: 2.627334 | V75: 2.643946 | W75: 2.65917 | X75: 2.680398 | Y75: 2.706399 | Z75: 2.73978 | AA75: 2.767942 | AB75: 2.797641 | AC75: 2.822753 | AD75: 2.846913 | AE75: 2.875512 | AF75: 2.906283 | AG75: 2.940435 | AH75: 0.005272
A76: TKI000:ea_Rail,Passenge | B76: Rail, Passenger | C76: 0.013936 | D76: 0.016692 | E76: 0.018912 | F76: 0.02059 | G76: 0.021857 | H76: 0.022807 | I76: 0.023493 | J76: 0.024005 | K76: 0.024148 | L76: 0.024265 | M76: 0.024503 | N76: 0.02463 | O76: 0.024893 | P76: 0.025147 | Q76: 0.025457 | R76: 0.025725 | S76: 0.026019 | T76: 0.026302 | U76: 0.026582 | V76: 0.026871 | W76: 0.027246 | X76: 0.027589 | Y76: 0.027926 | Z76: 0.028273 | AA76: 0.028608 | AB76: 0.028976 | AC76: 0.029316 | AD76: 0.029622 | AE76: 0.029951 | AF76: 0.030311 | AG76: 0.030663 | AH76: 0.026634
A77: TKI000:ea_Rail,Freight | B77: Rail, Freight | C77: 0.2052 | D77: 0.216413 | E77: 0.217179 | F77: 0.215971 | G77: 0.214533 | H77: 0.206519 | I77: 0.207688 | J77: 0.206239 | K77: 0.20741 | L77: 0.208304 | M77: 0.209237 | N77: 0.209471 | O77: 0.2094 | P77: 0.209744 | Q77: 0.209412 | R77: 0.20981 | S77: 0.210093 | T77: 0.210129 | U77: 0.209256 | V77: 0.209996 | W77: 0.209331 | X77: 0.209426 | Y77: 0.210104 | Z77: 0.211251 | AA77: 0.210315 | AB77: 0.210549 | AC77: 0.210321 | AD77: 0.210586 | AE77: 0.210842 | AF77: 0.21118 | AG77: 0.212342 | AH77: 0.001141
A78: TKI000:ea_Shipping,Dome | B78: Shipping, Domestic | C78: 0.036641 | D78: 0.037508 | E78: 0.037086 | F78: 0.03667 | G78: 0.03624 | H78: 0.035579 | I78: 0.034701 | J78: 0.033688 | K78: 0.032706 | L78: 0.031683 | M78: 0.030701 | N78: 0.030174 | O78: 0.029688 | P78: 0.029171 | Q78: 0.028723 | R78: 0.0283 | S78: 0.027854 | T78: 0.027376 | U78: 0.026879 | V78: 0.026447 | W78: 0.02595 | X78: 0.025747 | Y78: 0.025561 | Z78: 0.025448 | AA78: 0.025261 | AB78: 0.025081 | AC78: 0.024846 | AD78: 0.024618 | AE78: 0.024375 | AF78: 0.024158 | AG78: 0.023978 | AH78: -0.014035
A79: TKI000:ea_Shipping,Inte | B79: Shipping, International | C79: 0.390127 | D79: 0.399914 | E79: 0.434956 | F79: 0.441884 | G79: 0.422805 | H79: 0.424046 | I79: 0.428597 | J79: 0.420109 | K79: 0.420515 | L79: 0.417549 | M79: 0.418554 | N79: 0.425043 | O79: 0.419537 | P79: 0.41976 | Q79: 0.418936 | R79: 0.424556 | S79: 0.419202 | T79: 0.419055 | U79: 0.422916 | V79: 0.417875 | W79: 0.417271 | X79: 0.422074 | Y79: 0.416121 | Z79: 0.415873 | AA79: 0.413463 | AB79: 0.413624 | AC79: 0.412266 | AD79: 0.41146 | AE79: 0.411718 | AF79: 0.411262 | AG79: 0.410365 | AH79: 0.001687
A80: TKI000:ea_RecreationalB | B80: Recreational Boats | C80: 0.106203 | D80: 0.106628 | E80: 0.108291 | F80: 0.10927 | G80: 0.109676 | H80: 0.109872 | I80: 0.109505 | J80: 0.108728 | K80: 0.107827 | L80: 0.10685 | M80: 0.105917 | N80: 0.105118 | O80: 0.104561 | P80: 0.103983 | Q80: 0.103517 | R80: 0.103178 | S80: 0.102702 | T80: 0.102093 | U80: 0.101512 | V80: 0.101063 | W80: 0.100765 | X80: 0.100435 | Y80: 0.100065 | Z80: 0.099694 | AA80: 0.099248 | AB80: 0.098909 | AC80: 0.098502 | AD80: 0.097958 | AE80: 0.097569 | AF80: 0.097161 | AG80: 0.096743 | AH80: -0.003105
A81: TKI000:ea_Air | B81: Air | C81: 0.900305 | D81: 1.224288 | E81: 1.367005 | F81: 1.433183 | G81: 1.475928 | H81: 1.509005 | I81: 1.520615 | J81: 1.529019 | K81: 1.539247 | L81: 1.548459 | M81: 1.558426 | N81: 1.571105 | O81: 1.589755 | P81: 1.608117 | Q81: 1.628653 | R81: 1.652344 | S81: 1.671992 | T81: 1.688775 | U81: 1.706511 | V81: 1.726514 | W81: 1.75151 | X81: 1.77462 | Y81: 1.798373 | Z81: 1.820968 | AA81: 1.844373 | AB81: 1.869801 | AC81: 1.892966 | AD81: 1.910659 | AE81: 1.929632 | AF81: 1.946926 | AG81: 1.964514 | AH81: 0.02635
A82: TKI000:ea_MilitaryUse | B82: Military Use | C82: 0.257081 | D82: 0.261438 | E82: 0.261803 | F82: 0.255477 | G82: 0.251303 | H82: 0.251044 | I82: 0.250438 | J82: 0.25036 | K82: 0.251731 | L82: 0.251176 | M82: 0.250227 | N82: 0.250187 | O82: 0.250591 | P82: 0.251006 | Q82: 0.251428 | R82: 0.25185 | S82: 0.252288 | T82: 0.252742 | U82: 0.253204 | V82: 0.253666 | W82: 0.254136 | X82: 0.254607 | Y82: 0.255078 | Z82: 0.255554 | AA82: 0.256032 | AB82: 0.256496 | AC82: 0.25698 | AD82: 0.257459 | AE82: 0.257947 | AF82: 0.258428 | AG82: 0.258902 | AH82: 0.000235
A83: TKI000:ea_Lubricants | B83: Lubricants | C83: 0.057262 | D83: 0.05829 | E83: 0.058961 | F83: 0.059478 | G83: 0.059828 | H83: 0.06001 | I83: 0.060088 | J83: 0.059921 | K83: 0.0598 | L83: 0.059697 | M83: 0.059553 | N83: 0.059424 | O83: 0.059322 | P83: 0.059235 | Q83: 0.059183 | R83: 0.059143 | S83: 0.059086 | T83: 0.059015 | U83: 0.058966 | V83: 0.058931 | W83: 0.058892 | X83: 0.058852 | Y83: 0.05882 | Z83: 0.058781 | AA83: 0.058773 | AB83: 0.058809 | AC83: 0.058817 | AD83: 0.058797 | AE83: 0.058808 | AF83: 0.058795 | AG83: 0.058756 | AH83: 0.000858
... A85: TKI000:ea_Total | B85: Total | C85: 12.710937 | D85: 13.523485 | E85: 13.782738 | F85: 13.893643 | G85: 13.946235 | H85: 13.993832 | I85: 13.969633 | J85: 13.917164 | K85: 13.870161 | L85: 13.804184 | M85: 13.743266 | N85: 13.694123 | O85: 13.650218 | P85: 13.62207 | Q85: 13.610144 | R85: 13.63513 | S85: 13.652452 | T85: 13.673915 | U85: 13.704461 | V85: 13.741007 | W85: 13.793367 | X85: 13.856253 | Y85: 13.918808 | Z85: 13.997322 | AA85: 14.066484 | AB85: 14.140247 | AC85: 14.209555 | AD85: 14.270186 | AE85: 14.335911 | AF85: 14.406158 | AG85: 14.484777 | AH85: 0.004364
B87: 1/ Commercial trucks 8,501 to 10,000 pounds gross vehicle weight rating.
B88: 2/ CAFE standard based on projected new vehicle sales.
B89: 3/ Includes CAFE credits for alternative fueled vehicle sales and credit banking.
B90: 4/ Environmental Protection Agency rated miles per gallon.
B91: 5/ Tested new vehicle efficiency revised for on-road performance.
B92: 6/ Combined "on-the-road" estimate for all cars and light trucks.
B93: CAFE = Corporate average fuel economy.
B94: Btu = British thermal unit.
B95: Note: Totals may not equal sum of components due to independent rounding.
B96: Sources: 2020: U.S. Energy Information Administration (EIA), Short-Term Energy Outlook, October 2020 and EIA,
B97: AEO2021 National Energy Modeling System run highogs.d120120a. Projections: EIA, AEO2021 National Energy Modeling System run highogs.d120120a.

Sheet AEO 7 (2020)
B1: highogs.d112619a | C1: 2019 | D1: 2020 | E1: 2021 | F1: 2022 | G1: 2023 | H1: 2024 | I1: 2025 | J1: 2026 | K1: 2027 | L1: 2028 | M1: 2029 | N1: 2030 | O1: 2031 | P1: 2032 | Q1: 2033 | R1: 2034 | S1: 2035 | T1: 2036 | U1: 2037 | V1: 2038 | W1: 2039 | X1: 2040 | Y1: 2041 | Z1: 2042 | AA1: 2043 | AB1: 2044 | AC1: 2045 | AD1: 2046 | AE1: 2047 | AF1: 2048 | AG1: 2049 | AH1: 2050
C3: Report | D3: Annual Energy Outlook 2020
C4: Scenario | D4: highogs | G4: High oil and gas supply
C5: Datekey | D5: d112619a
C6: Release Date | E6: January 2020
A10: TKI000 | B10: 7. Transportation Sector Key Indicators and Delivered Energy Consumption
AI12: 2019-
B13: Key Indicators and Consumption | C13: 2019 | D13: 2020 | E13: 2021 | F13: 2022 | G13: 2023 | H13: 2024 | I13: 2025 | J13: 2026 | K13: 2027 | L13: 2028 | M13: 2029 | N13: 2030 | O13: 2031 | P13: 2032 | Q13: 2033 | R13: 2034 | S13: 2035 | T13: 2036 | U13: 2037 | V13: 2038 | W13: 2039 | X13: 2040 | Y13: 2041 | Z13: 2042 | AA13: 2043 | AB13: 2044 | AC13: 2045 | AD13: 2046 | AE13: 2047 | AF13: 2048 | AG13: 2049 | AH13: 2050 | AI13: 2050
B15: Key Indicators
B16: Travel Indicators
B17: (billion vehicle miles traveled)
A18: TKI000:ba_Light-DutyVeh | B18: Light-Duty Vehicles less than 8,501 pounds | C18: 2917.2534 | D18: 2975.1255 | E18: 3025.3584 | F18: 3062.7468 | G18: 3083.9775 | H18: 3096.5911 | I18: 3105.9812 | J18: 3125.592 | K18: 3146.8806 | L18: 3167.6331 | M18: 3188.2371 | N18: 3209.8457 | O18: 3233.3459 | P18: 3252.6282 | Q18: 3271.1394 | R18: 3285.1404 | S18: 3295.6909 | T18: 3311.9399 | U18: 3327.9958 | V18: 3344.2627 | W18: 3361.5449 | X18: 3379.7544 | Y18: 3396.2571 | Z18: 3413.8406 | AA18: 3432.0298 | AB18: 3451.1577 | AC18: 3472.0923 | AD18: 3496.9058 | AE18: 3524.3184 | AF18: 3555.4368 | AG18: 3588.8325 | AH18: 3624.4036 | AI18: 0.007026
A19: TKI000:ba_CommercialLig | B19: Commercial Light Trucks 1/ | C19: 99.321114 | D19: 100.61537 | E19: 102.27555 | F19: 103.79449 | G19: 104.99791 | H19: 105.84502 | I19: 106.78965 | J19: 107.83586 | K19: 109.08619 | L19: 110.31479 | M19: 111.61692 | N19: 112.77087 | O19: 114.26243 | P19: 115.52301 | Q19: 116.87927 | R19: 118.14617 | S19: 119.40303 | T19: 120.80527 | U19: 122.15245 | V19: 123.49687 | W19: 124.85643 | X19: 126.2754 | Y19: 127.71654 | Z19: 129.18462 | AA19: 130.707 | AB19: 132.37408 | AC19: 134.19019 | AD19: 136.27534 | AE19: 138.1423 | AF19: 140.20346 | AG19: 142.3405 | AH19: 144.47952 | AI19: 0.012163
A20: TKI000:ba_FreightTrucks | B20: Freight Trucks greater than 10,000 pounds | C20: 299.98956 | D20: 302.9967 | E20: 307.86118 | F20: 312.26749 | G20: 316.85519 | H20: 319.63693 | I20: 322.73798 | J20: 325.80005 | K20: 329.40594 | L20: 332.56686 | M20: 335.87531 | N20: 338.36066 | O20: 342.56183 | P20: 345.99631 | Q20: 349.88959 | R20: 353.1503 | S20: 356.89838 | T20: 360.95453 | U20: 364.40631 | V20: 367.98541 | W20: 371.4613 | X20: 375.17526 | Y20: 378.96576 | Z20: 382.97611 | AA20: 386.86951 | AB20: 391.47946 | AC20: 396.5683 | AD20: 402.70737 | AE20: 407.39862 | AF20: 413.09305 | AG20: 419.04983 | AH20: 425.07648 | AI20: 0.011306
B21: (billion passenger miles traveled)
A22: TKI000:buspassmiles | B22: Bus Transportation | C22: 210.1385 | D22: 211.1262 | E22: 212.11616 | F22: 213.08595 | G22: 214.01353 | H22: 214.96095 | I22: 215.98413 | J22: 216.98978 | K22: 217.98006 | L22: 218.98109 | M22: 219.96805 | N22: 220.90674 | O22: 221.80705 | P22: 222.67883 | Q22: 223.45596 | R22: 224.19052 | S22: 224.88495 | T22: 225.5426 | U22: 226.16771 | V22: 226.76289 | W22: 227.33022 | X22: 227.87238 | Y22: 228.39172 | Z22: 228.89146 | AA22: 229.37672 | AB22: 229.85208 | AC22: 230.32323 | AD22: 230.79691 | AE22: 231.28061 | AF22: 231.78067 | AG22: 232.30583 | AH22: 232.85057 | AI22: 0.003316
A23: TKI000:railpassmiles | B23: Passenger Rail | C23: 41.270718 | D23: 41.874931 | E23: 42.455513 | F23: 42.941441 | G23: 43.403492 | H23: 43.866783 | I23: 44.310471 | J23: 44.75193 | K23: 45.177658 | L23: 45.617382 | M23: 46.05724 | N23: 46.402245 | O23: 46.841446 | P23: 47.267838 | Q23: 47.680485 | R23: 48.055225 | S23: 48.435219 | T23: 48.803921 | U23: 49.166313 | V23: 49.530781 | W23: 49.890511 | X23: 50.244217 | Y23: 50.573273 | Z23: 50.897018 | AA23: 51.222713 | AB23: 51.549355 | AC23: 51.873222 | AD23: 52.227497 | AE23: 52.585468 | AF23: 52.972961 | AG23: 53.355492 | AH23: 53.757782 | AI23: 0.008563
B24: (billion seat miles available)
A25: TKI000:ba_Air | B25: Air | C25: 1222.9934 | D25: 1245.385 | E25: 1270.2579 | F25: 1290.4578 | G25: 1307.1332 | H25: 1325.8835 | I25: 1346.3998 | J25: 1366.3947 | K25: 1386.9773 | L25: 1409.3759 | M25: 1434.0159 | N25: 1459.4762 | O25: 1485.5172 | P25: 1512.3081 | Q25: 1538.871 | R25: 1563.6233 | S25: 1587.829 | T25: 1613.7333 | U25: 1640.1089 | V25: 1667.4398 | W25: 1695.8134 | X25: 1724.8636 | Y25: 1752.9756 | Z25: 1781.3413 | AA25: 1810.3131 | AB25: 1840.631 | AC25: 1874.0067 | AD25: 1909.9596 | AE25: 1947.4512 | AF25: 1987.4026 | AG25: 2028.574 | AH25: 2071.0894 | AI25: 0.017138
B26: (billion ton miles traveled)
A27: TKI000:ba_Rail | B27: Rail | C27: 1807.9623 | D27: 1730.8405 | E27: 1660.0334 | F27: 1651.2594 | G27: 1652.7242 | H27: 1638.4692 | I27: 1604.7769 | J27: 1643.9995 | K27: 1652.7871 | L27: 1662.7437 | M27: 1655.604 | N27: 1648.3021 | O27: 1654.8008 | P27: 1663.8508 | Q27: 1673.921 | R27: 1684.4979 | S27: 1686.808 | T27: 1698.2738 | U27: 1704.6904 | V27: 1701.2555 | W27: 1711.9681 | X27: 1715.1283 | Y27: 1722.2583 | Z27: 1735.2404 | AA27: 1747.2886 | AB27: 1760.9611 | AC27: 1777.2797 | AD27: 1802.0692 | AE27: 1818.0815 | AF27: 1839.249 | AG27: 1861.9969 | AH27: 1888.5421 | AI27: 0.001408
A28: TKI000:ba_DomesticShipp | B28: Domestic Shipping | C28: 416.68076 | D28: 409.15491 | E28: 404.52988 | F28: 396.47797 | G28: 388.98981 | H28: 379.45697 | I28: 370.07324 | J28: 361.44611 | K28: 352.76407 | L28: 343.56067 | M28: 333.81879 | N28: 323.79498 | O28: 320.25205 | P28: 316.14533 | Q28: 312.6521 | R28: 308.38547 | S28: 304.23715 | T28: 300.63773 | U28: 296.55325 | V28: 292.41882 | W28: 288.76395 | X28: 284.95685 | Y28: 283.66168 | Z28: 282.64859 | AA28: 281.33289 | AB28: 280.51184 | AC28: 279.8728 | AD28: 280.18787 | AE28: 279.40164 | AF28: 279.35028 | AG28: 279.69217 | AH28: 280.25092 | AI28: -0.012713
B30: Energy Efficiency Indicators
B31: (miles per gallon)
A32: TKI000:ca_AvgCAFEStand | B32: New Light-Duty Vehicle CAFE Standard 2/ | C32: 34.359936 | D32: 35.284824 | E32: 36.831001 | F32: 38.399506 | G32: 40.110416 | H32: 41.695168 | I32: 43.801582 | J32: 43.785816 | K32: 43.851311 | L32: 43.92421 | M32: 44.014652 | N32: 44.196796 | O32: 44.303349 | P32: 44.390171 | Q32: 44.493732 | R32: 44.60854 | S32: 44.698715 | T32: 44.789574 | U32: 44.882374 | V32: 44.963428 | W32: 45.039089 | X32: 45.11404 | Y32: 45.19231 | Z32: 45.25729 | AA32: 45.303879 | AB32: 45.340485 | AC32: 45.390274 | AD32: 45.422104 | AE32: 45.456978 | AF32: 45.47982 | AG32: 45.506924 | AH32: 45.514236 | AI32: 0.00911
A33: TKI000:ca_CarCAFEStand | B33: New Car 2/ | C33: 40.551155 | D33: 42.338371 | E33: 44.294533 | F33: 46.414017 | G33: 48.711933 | H33: 50.082985 | I33: 52.773457 | J33: 52.773731 | K33: 52.786339 | L33: 52.786339 | M33: 52.798622 | N33: 52.841564 | O33: 52.841564 | P33: 52.841564 | Q33: 52.841564 | R33: 52.841564 | S33: 52.841564 | T33: 52.841564 | U33: 52.841564 | V33: 52.841564 | W33: 52.841564 | X33: 52.842728 | Y33: 52.844788 | Z33: 52.844788 | AA33: 52.844788 | AB33: 52.844788 | AC33: 52.84753 | AD33: 52.84753 | AE33: 52.848724 | AF33: 52.848724 | AG33: 52.84988 | AH33: 52.84988 | AI33: 0.008582
A34: TKI000:ca_TwukCAFEStand | B34: New Light Truck 2/ | C34: 30.2997 | D34: 30.889185 | E34: 32.380001 | F34: 33.7799 | G34: 35.309071 | H34: 36.976479 | I34: 38.765255 | J34: 38.772991 | K34: 38.772991 | L34: 38.772991 | M34: 38.772991 | N34: 38.772991 | O34: 38.772991 | P34: 38.772991 | Q34: 38.772991 | R34: 38.772991 | S34: 38.772991 | T34: 38.772991 | U34: 38.772991 | V34: 38.772991 | W34: 38.772991 | X34: 38.772991 | Y34: 38.772991 | Z34: 38.772991 | AA34: 38.772991 | AB34: 38.772991 | AC34: 38.772991 | AD34: 38.772991 | AE34: 38.772991 | AF34: 38.772991 | AG34: 38.772991 | AH34: 38.773014 | AI34: 0.007986
A35: TKI000:ca_NewVehCred | B35: Compliance New Light-Duty Vehicle 3/ | C35: 35.348213 | D35: 36.238525 | E35: 37.596539 | F35: 39.37933 | G35: 40.901978 | H35: 42.360344 | I35: 44.567291 | J35: 44.831284 | K35: 44.934002 | L35: 45.040806 | M35: 45.183762 | N35: 45.495754 | O35: 45.787571 | P35: 46.034676 | Q35: 46.317448 | R35: 46.60257 | S35: 46.849384 | T35: 47.060444 | U35: 47.280041 | V35: 47.481697 | W35: 47.659729 | X35: 47.83065 | Y35: 47.980515 | Z35: 48.108444 | AA35: 48.197189 | AB35: 48.262737 | AC35: 48.3549 | AD35: 48.425739 | AE35: 48.504185 | AF35: 48.562855 | AG35: 48.634819 | AH35: 48.674248 | AI35: 0.010373
A36: TKI000:ca_NewCarCred | B36: New Car 3/ | C36: 42.356316 | D36: 43.482601 | E36: 45.545635 | F36: 47.835651 | G36: 49.962463 | H36: 51.477432 | I36: 54.131187 | J36: 54.288181 | K36: 54.274036 | L36: 54.345482 | M36: 54.476521 | N36: 54.755726 | O36: 55.19865 | P36: 55.546597 | Q36: 55.91061 | R36: 56.268238 | S36: 56.616009 | T36: 56.875309 | U36: 57.153564 | V36: 57.42186 | W36: 57.643833 | X36: 57.841148 | Y36: 57.984364 | Z36: 58.118862 | AA36: 58.223202 | AB36: 58.303883 | AC36: 58.397022 | AD36: 58.51268 | AE36: 58.621887 | AF36: 58.738182 | AG36: 58.859608 | AH36: 58.987617 | AI36: 0.010741
A37: TKI000:ca_NewTwukCred | B37: New Light Truck 3/ | C37: 30.865908 | D37: 31.724129 | E37: 32.910633 | F37: 34.543072 | G37: 35.889904 | H37: 37.32349 | I37: 39.26572 | J37: 39.595291 | K37: 39.653728 | L37: 39.666462 | M37: 39.683132 | N37: 39.748066 | O37: 39.797894 | P37: 39.852974 | Q37: 39.920296 | R37: 39.970135 | S37: 40.005047 | T37: 40.02647 | U37: 40.043442 | V37: 40.056137 | W37: 40.064693 | X37: 40.075218 | Y37: 40.075615 | Z37: 40.069695 | AA37: 40.055481 | AB37: 40.038029 | AC37: 40.029408 | AD37: 40.008018 | AE37: 39.996075 | AF37: 39.972542 | AG37: 39.958122 | AH37: 39.929474 | AI37: 0.00834
A38: TKI000:ca_TestedNewVeh | B38: Tested New Light-Duty Vehicle 4/ | C38: 34.962322 | D38: 35.991081 | E38: 37.288235 | F38: 39.051094 | G38: 40.553646 | H38: 41.976017 | I38: 44.120575 | J38: 44.336227 | K38: 44.414066 | L38: 44.500385 | M38: 44.615799 | N38: 44.876507 | O38: 45.111603 | P38: 45.306648 | Q38: 45.531082 | R38: 45.75457 | S38: 45.942371 | T38: 46.09964 | U38: 46.263412 | V38: 46.41185 | W38: 46.541386 | X38: 46.666012 | Y38: 46.777721 | Z38: 46.871037 | AA38: 46.931049 | AB38: 46.971848 | AC38: 47.034363 | AD38: 47.077263 | AE38: 47.126358 | AF38: 47.158012 | AG38: 47.200371 | AH38: 47.214767 | AI38: 0.009739
A39: TKI000:ca_TestedNewCar | B39: New Car 4/ | C39: 41.715885 | D39: 42.872379 | E39: 44.733494 | F39: 46.957069 | G39: 49.003487 | H39: 50.41568 | I39: 52.908669 | J39: 53.035347 | K39: 53.002815 | L39: 53.031281 | M39: 53.101597 | N39: 53.283951 | O39: 53.59354 | P39: 53.82737 | Q39: 54.068119 | R39: 54.300163 | S39: 54.521736 | T39: 54.675041 | U39: 54.843937 | V39: 55.006741 | W39: 55.136219 | X39: 55.248566 | Y39: 55.326115 | Z39: 55.397579 | AA39: 55.445976 | AB39: 55.477283 | AC39: 55.516716 | AD39: 55.571735 | AE39: 55.621513 | AF39: 55.67548 | AG39: 55.732971 | AH39: 55.794552 | AI39: 0.009425
A40: TKI000:ca_TestedNewTwuk | B40: New Light Truck 4/ | C40: 30.612513 | D40: 31.651661 | E40: 32.830524 | F40: 34.456524 | G40: 35.799854 | H40: 37.22747 | I40: 39.151051 | J40: 39.426971 | K40: 39.465645 | L40: 39.475208 | M40: 39.488102 | N40: 39.541683 | O40: 39.581787 | P40: 39.624954 | Q40: 39.679688 | R40: 39.716709 | S40: 39.740402 | T40: 39.750675 | U40: 39.756599 | V40: 39.759041 | W40: 39.758137 | X40: 39.759655 | Y40: 39.75499 | Z40: 39.745636 | AA40: 39.729229 | AB40: 39.710049 | AC40: 39.698334 | AD40: 39.675388 | AE40: 39.66048 | AF40: 39.635681 | AG40: 39.61845 | AH40: 39.589142 | AI40: 0.00833
A41: TKI000:ca_OnRoadNewVeh | B41: On-Road New Light-Duty Vehicle 5/ | C41: 28.524006 | D41: 29.363092 | E41: 30.420794 | F41: 31.858644 | G41: 33.084072 | H41: 34.244457 | I41: 35.994076 | J41: 36.169979 | K41: 36.233746 | L41: 36.304462 | M41: 36.398952 | N41: 36.612297 | O41: 36.804462 | P41: 36.963898 | Q41: 37.147385 | R41: 37.330143 | S41: 37.483685 | T41: 37.612339 | U41: 37.7463 | V41: 37.867699 | W41: 37.973671 | X41: 38.075638 | Y41: 38.16708 | Z41: 38.243473 | AA41: 38.292618 | AB41: 38.326035 | AC41: 38.377235 | AD41: 38.412346 | AE41: 38.45253 | AF41: 38.478436 | AG41: 38.513092 | AH41: 38.524834 | AI41: 0.009742
A42: TKI000:ca_OnRoadNewCar | B42: New Car 5/ | C42: 34.065807 | D42: 35.010216 | E42: 36.530029 | F42: 38.345837 | G42: 40.016972 | H42: 41.170189 | I42: 43.205997 | J42: 43.309448 | K42: 43.282879 | L42: 43.306126 | M42: 43.363548 | N42: 43.512459 | O42: 43.765274 | P42: 43.956223 | Q42: 44.152824 | R42: 44.342316 | S42: 44.523254 | T42: 44.648445 | U42: 44.786369 | V42: 44.919315 | W42: 45.025051 | X42: 45.116795 | Y42: 45.180122 | Z42: 45.23848 | AA42: 45.278004 | AB42: 45.303566 | AC42: 45.33577 | AD42: 45.380699 | AE42: 45.421349 | AF42: 45.46542 | AG42: 45.512367 | AH42: 45.562653 | AI42: 0.009425
A43: TKI000:ca_OnRoadNewTwuk | B43: New Light Truck 5/ | C43: 24.960157 | D43: 25.807436 | E43: 26.768633 | F43: 28.094404 | G43: 29.189699 | H43: 30.353718 | I43: 31.922125 | J43: 32.147099 | K43: 32.178631 | L43: 32.186428 | M43: 32.196941 | N43: 32.240631 | O43: 32.273327 | P43: 32.308525 | Q43: 32.353153 | R43: 32.383339 | S43: 32.402657 | T43: 32.411034 | U43: 32.415863 | V43: 32.417854 | W43: 32.417118 | X43: 32.418354 | Y43: 32.414551 | Z43: 32.406925 | AA43: 32.393547 | AB43: 32.377907 | AC43: 32.368355 | AD43: 32.349648 | AE43: 32.33749 | AF43: 32.317272 | AG43: 32.303223 | AH43: 32.279324 | AI43: 0.00833
... A47: TKI000:ca_FreightTruck | B47: Freight Truck | C47: 7.119165 | D47: 7.17094 | E47: 7.235986 | F47: 7.3073 | G47: 7.388516 | H47: 7.48128 | I47: 7.586367 | J47: 7.703835 | K47: 7.834221 | L47: 7.967885 | M47: 8.108215 | N47: 8.251791 | O47: 8.396469 | P47: 8.537745 | Q47: 8.669586 | R47: 8.791187 | S47: 8.902438 | T47: 9.004374 | U47: 9.096915 | V47: 9.181 | W47: 9.258368 | X47: 9.327685 | Y47: 9.391495 | Z47: 9.448672 | AA47: 9.500283 | AB47: 9.547491 | AC47: 9.591628 | AD47: 9.634123 | AE47: 9.675597 | AF47: 9.716289 | AG47: 9.756433 | AH47: 9.797481 | AI47: 0.010354
B48: (seat miles per gallon)
A49: TKI000:ca_Aircraft | B49: Aircraft | C49: 69.061409 | D49: 69.384445 | E49: 69.706734 | F49: 70.035477 | G49: 70.376755 | H49: 70.734436 | I49: 71.082642 | J49: 71.464615 | K49: 71.895363 | L49: 72.350365 | M49: 72.824806 | N49: 73.293343 | O49: 73.757736 | P49: 74.234024 | Q49: 74.700493 | R49: 75.177055 | S49: 75.653641 | T49: 76.137352 | U49: 76.621902 | V49: 77.107964 | W49: 77.601532 | X49: 78.09996 | Y49: 78.56591 | Z49: 79.031158 | AA49: 79.489037 | AB49: 79.918777 | AC49: 80.345123 | AD49: 80.761703 | AE49: 81.17762 | AF49: 81.591446 | AG49: 81.990547 | AH49: 82.372414 | AI49: 0.005702
B50: (ton miles/thousand Btu)
A51: TKI000:ca_Rail | B51: Rail | C51: 3.466884 | D51: 3.489371 | E51: 3.512003 | F51: 3.534782 | G51: 3.55771 | H51: 3.580785 | I51: 3.60401 | J51: 3.627386 | K51: 3.650914 | L51: 3.674594 | M51: 3.698428 | N51: 3.722416 | O51: 3.74656 | P51: 3.77086 | Q51: 3.795318 | R51: 3.819935 | S51: 3.844712 | T51: 3.869649 | U51: 3.894748 | V51: 3.920009 | W51: 3.945435 | X51: 3.971025 | Y51: 3.996782 | Z51: 4.022705 | AA51: 4.048797 | AB51: 4.075058 | AC51: 4.101489 | AD51: 4.128091 | AE51: 4.154866 | AF51: 4.181815 | AG51: 4.208939 | AH51: 4.236238 | AI51: 0.006486
A52: TKI000:ca_DomesticShipp | B52: Domestic Shipping | C52: 4.813365 | D52: 4.84196 | E52: 4.870726 | F52: 4.899663 | G52: 4.928772 | H52: 4.958054 | I52: 4.987509 | J52: 5.01714 | K52: 5.046947 | L52: 5.076931 | M52: 5.107092 | N52: 5.137434 | O52: 5.167955 | P52: 5.198658 | Q52: 5.229543 | R52: 5.260611 | S52: 5.291864 | T52: 5.323303 | U52: 5.354929 | V52: 5.386742 | W52: 5.418745 | X52: 5.450938 | Y52: 5.483322 | Z52: 5.515898 | AA52: 5.548667 | AB52: 5.581632 | AC52: 5.614792 | AD52: 5.64815 | AE52: 5.681705 | AF52: 5.71546 | AG52: 5.749416 | AH52: 5.783573 | AI52: 0.005941
B54: Energy Use by Mode
B55: (quadrillion Btu)
A56: TKI000:da_Light-DutyVeh | B56: Light-Duty Vehicles | C56: 15.312445 | D56: 15.30714 | E56: 15.236718 | F56: 15.068806 | G56: 14.804813 | H56: 14.499307 | I56: 14.167157 | J56: 13.909196 | K56: 13.685458 | L56: 13.482776 | M56: 13.299863 | N56: 13.139069 | O56: 13.002687 | P56: 12.863337 | Q56: 12.735183 | R56: 12.602709 | S56: 12.470579 | T56: 12.372916 | U56: 12.287333 | V56: 12.215109 | W56: 12.15875 | X56: 12.118073 | Y56: 12.081137 | Z56: 12.057517 | AA56: 12.045367 | AB56: 12.044356 | AC56: 12.055041 | AD56: 12.085419 | AE56: 12.129275 | AF56: 12.190246 | AG56: 12.262823 | AH56: 12.346762 | AI56: -0.00692
A57: TKI000:da_CommercialLig | B57: Commercial Light Trucks 1/ | C57: 0.891028 | D57: 0.891903 | E57: 0.895889 | F57: 0.89787 | G57: 0.89709 | H57: 0.89318 | I57: 0.892636 | J57: 0.892015 | K57: 0.892606 | L57: 0.893648 | M57: 0.895486 | N57: 0.896713 | O57: 0.901317 | P57: 0.904846 | Q57: 0.909857 | R57: 0.914968 | S57: 0.920246 | T57: 0.927079 | U57: 0.934283 | V57: 0.94158 | W57: 0.949261 | X57: 0.957789 | Y57: 0.966845 | Z57: 0.975906 | AA57: 0.98611 | AB57: 0.997791 | AC57: 1.010687 | AD57: 1.027074 | AE57: 1.040264 | AF57: 1.054572 | AG57: 1.069246 | AH57: 1.083799 | AI57: 0.006338
A58: TKI000:da_BusTransporta | B58: Bus Transportation | C58: 0.238531 | D58: 0.23989 | E58: 0.241259 | F58: 0.242609 | G58: 0.243913 | H58: 0.245252 | I58: 0.246684 | J58: 0.248104 | K58: 0.249516 | L58: 0.250953 | M58: 0.252383 | N58: 0.253717 | O58: 0.25501 | P58: 0.256269 | Q58: 0.257406 | R58: 0.258486 | S58: 0.259508 | T58: 0.26047 | U58: 0.261377 | V58: 0.262223 | W58: 0.263003 | X58: 0.263714 | Y58: 0.264353 | Z58: 0.264925 | AA58: 0.265439 | AB58: 0.265904 | AC58: 0.266333 | AD58: 0.266748 | AE58: 0.267177 | AF58: 0.267648 | AG58: 0.268208 | AH58: 0.268877 | AI58: 0.00387
A59: TKI000:da_FreightTrucks | B59: Freight Trucks | C59: 5.880958 | D59: 5.904005 | E59: 5.951757 | F59: 5.983958 | G59: 6.010647 | H59: 5.993482 | I59: 5.972905 | J59: 5.942755 | K59: 5.913831 | L59: 5.875737 | M59: 5.836956 | N59: 5.783237 | O59: 5.760028 | P59: 5.727354 | Q59: 5.709549 | R59: 5.688765 | S59: 5.682989 | T59: 5.688041 | U59: 5.689445 | V59: 5.697817 | W59: 5.709255 | X59: 5.729411 | Y59: 5.754163 | Z59: 5.786846 | AA59: 5.821076 | AB59: 5.869198 | AC59: 5.927293 | AD59: 6.001935 | AE59: 6.05612 | AF59: 6.125846 | AG59: 6.200032 | AH59: 6.275017 | AI59: 0.002094
A60: TKI000:da_Rail,Passenge | B60: Rail, Passenger | C60: 0.049125 | D60: 0.050002 | E60: 0.050829 | F60: 0.051513 | G60: 0.052173 | H60: 0.05283 | I60: 0.053461 | J60: 0.054088 | K60: 0.054688 | L60: 0.055315 | M60: 0.05594 | N60: 0.056411 | O60: 0.057057 | P60: 0.057683 | Q60: 0.058288 | R60: 0.058841 | S60: 0.059417 | T60: 0.059977 | U60: 0.060532 | V60: 0.061099 | W60: 0.061667 | X60: 0.062234 | Y60: 0.062772 | Z60: 0.063311 | AA60: 0.063864 | AB60: 0.064422 | AC60: 0.064971 | AD60: 0.065568 | AE60: 0.066151 | AF60: 0.066765 | AG60: 0.067348 | AH60: 0.067945 | AI60: 0.010517
A61: TKI000:da_Rail,Freight | B61: Rail, Freight | C61: 0.521495 | D61: 0.496032 | E61: 0.472674 | F61: 0.467146 | G61: 0.464547 | H61: 0.457573 | I61: 0.445275 | J61: 0.453219 | K61: 0.452705 | L61: 0.452497 | M61: 0.447651 | N61: 0.442804 | O61: 0.441685 | P61: 0.441239 | Q61: 0.441049 | R61: 0.440976 | S61: 0.438735 | T61: 0.43887 | U61: 0.43769 | V61: 0.433993 | W61: 0.433911 | X61: 0.431911 | Y61: 0.430911 | Z61: 0.431362 | AA61: 0.431558 | AB61: 0.432132 | AC61: 0.433326 | AD61: 0.436538 | AE61: 0.437579 | AF61: 0.439821 | AG61: 0.442391 | AH61: 0.445806 | AI61: -0.005046
A62: TKI000:da_Shipping,Dome | B62: Shipping, Domestic | C62: 0.089409 | D62: 0.087947 | E62: 0.085825 | F62: 0.083144 | G62: 0.081043 | H62: 0.07854 | I62: 0.076103 | J62: 0.073851 | K62: 0.071606 | L62: 0.069278 | M62: 0.066865 | N62: 0.064421 | O62: 0.063281 | P62: 0.062044 | Q62: 0.060933 | R62: 0.059681 | S62: 0.058471 | T62: 0.057385 | U62: 0.056209 | V62: 0.055025 | W62: 0.053933 | X62: 0.052831 | Y62: 0.052283 | Z62: 0.051792 | AA62: 0.051248 | AB62: 0.050799 | AC62: 0.050387 | AD62: 0.050149 | AE62: 0.049715 | AF62: 0.049415 | AG62: 0.049187 | AH62: 0.048997 | AI62: -0.019215
A63: TKI000:da_Shipping,Inte | B63: Shipping, International | C63: 0.927327 | D63: 1.008838 | E63: 0.971116 | F63: 0.886972 | G63: 0.891949 | H63: 0.875923 | I63: 0.889297 | J63: 0.864365 | K63: 0.875667 | L63: 0.876735 | M63: 0.862752 | N63: 0.876611 | O63: 0.877461 | P63: 0.865944 | Q63: 0.876064 | R63: 0.876109 | S63: 0.872912 | T63: 0.862727 | U63: 0.869371 | V63: 0.858956 | W63: 0.858436 | X63: 0.864699 | Y63: 0.853751 | Z63: 0.852309 | AA63: 0.849807 | AB63: 0.846604 | AC63: 0.844515 | AD63: 0.843746 | AE63: 0.841557 | AF63: 0.840549 | AG63: 0.839989 | AH63: 0.840091 | AI63: -0.003182
A64: TKI000:da_RecreationalB | B64: Recreational Boats | C64: 0.245487 | D64: 0.246247 | E64: 0.246891 | F64: 0.247228 | G64: 0.247401 | H64: 0.247561 | I64: 0.247747 | J64: 0.247872 | K64: 0.247948 | L64: 0.248034 | M64: 0.248119 | N64: 0.248128 | O64: 0.248119 | P64: 0.248079 | Q64: 0.247943 | R64: 0.247704 | S64: 0.247382 | T64: 0.247051 | U64: 0.246672 | V64: 0.246271 | W64: 0.245845 | X64: 0.245364 | Y64: 0.244837 | Z64: 0.244243 | AA64: 0.243636 | AB64: 0.243037 | AC64: 0.242467 | AD64: 0.241926 | AE64: 0.241387 | AF64: 0.240858 | AG64: 0.240316 | AH64: 0.23976 | AI64: -0.000761
A65: TKI000:da_Air | B65: Air | C65: 2.640944 | D65: 2.673067 | E65: 2.70635 | F65: 2.732191 | G65: 2.752433 | H65: 2.776094 | I65: 2.803131 | J65: 2.82868 | K65: 2.853517 | L65: 2.879811 | M65: 2.908522 | N65: 2.937199 | O65: 2.967398 | P65: 2.997719 | Q65: 3.0276 | R65: 3.053208 | S65: 3.077652 | T65: 3.104426 | U65: 3.132126 | V65: 3.160325 | W65: 3.189834 | X65: 3.220148 | Y65: 3.250173 | Z65: 3.279953 | AA65: 3.310731 | AB65: 3.34457 | AC65: 3.383125 | AD65: 3.426044 | AE65: 3.471181 | AF65: 3.520372 | AG65: 3.571743 | AH65: 3.624813 | AI65: 0.010267
A66: TKI000:da_MilitaryUse | B66: Military Use | C66: 0.512501 | D66: 0.526369 | E66: 0.515977 | F66: 0.504054 | G66: 0.488973 | H66: 0.47893 | I66: 0.47706 | J66: 0.475186 | K66: 0.474613 | L66: 0.477166 | M66: 0.476099 | N66: 0.47539 | O66: 0.475478 | P66: 0.475588 | Q66: 0.475726 | R66: 0.475885 | S66: 0.476065 | T66: 0.476268 | U66: 0.476499 | V66: 0.476747 | W66: 0.477015 | X66: 0.477302 | Y66: 0.4776 | Z66: 0.477913 | AA66: 0.478237 | AB66: 0.478571 | AC66: 0.478915 | AD66: 0.479268 | AE66: 0.479627 | AF66: 0.479993 | AG66: 0.480364 | AH66: 0.480741 | AI66: -0.002062
A67: TKI000:da_Lubricants | B67: Lubricants | C67: 0.131469 | D67: 0.130998 | E67: 0.130617 | F67: 0.130166 | G67: 0.129716 | H67: 0.129236 | I67: 0.128717 | J67: 0.12821 | K67: 0.127738 | L67: 0.127329 | M67: 0.126997 | N67: 0.126676 | O67: 0.126395 | P67: 0.126142 | Q67: 0.125896 | R67: 0.125704 | S67: 0.12555 | T67: 0.12549 | U67: 0.125464 | V67: 0.125469 | W67: 0.125512 | X67: 0.125529 | Y67: 0.125533 | Z67: 0.125612 | AA67: 0.125667 | AB67: 0.125765 | AC67: 0.12594 | AD67: 0.126144 | AE67: 0.126361 | AF67: 0.126627 | AG67: 0.126863 | AH67: 0.127078 | AI67: -0.001095
... A69: TKI000:da_Total | B69: Total | C69: 28.112638 | D69: 28.229656 | E69: 28.207281 | F69: 28.00946 | G69: 27.785589 | H69: 27.463036 | I69: 27.152018 | J69: 26.878296 | K69: 26.655809 | L69: 26.445753 | M69: 26.240934 | N69: 26.065762 | O69: 25.948496 | P69: 25.80217 | Q69: 25.701551 | R69: 25.580608 | S69: 25.470058 | T69: 25.412188 | U69: 25.37376 | V69: 25.339329 | W69: 25.342278 | X69: 25.372105 | Y69: 25.393759 | Z69: 25.455908 | AA69: 25.525803 | AB69: 25.624594 | AC69: 25.752531 | AD69: 25.930012 | AE69: 26.094328 | AF69: 26.300638 | AG69: 26.523647 | AH69: 26.762129 | AI69: -0.001587
B71: (million barrels per day oil equivalent)
A72: TKI000:ea_Light-DutyVeh | B72: Light-Duty Vehicles | C72: 8.299458 | D72: 8.297431 | E72: 8.258867 | F72: 8.167576 | G72: 8.024354 | H72: 7.858614 | I72: 7.680162 | J72: 7.54128 | K72: 7.420378 | L72: 7.311098 | M72: 7.21259 | N72: 7.126847 | O72: 7.05311 | P72: 6.977902 | Q72: 6.908753 | R72: 6.837132 | S72: 6.765776 | T72: 6.712733 | U72: 6.666179 | V72: 6.626825 | W72: 6.595639 | X72: 6.572973 | Y72: 6.552473 | Z72: 6.538953 | AA72: 6.532093 | AB72: 6.531311 | AC72: 6.536314 | AD72: 6.552357 | AE72: 6.575637 | AF72: 6.60852 | AG72: 6.647728 | AH72: 6.693235 | AI72: -0.006914
A73: TKI000:ea_CommercialLig | B73: Commercial Light Trucks 1/ | C73: 0.463645 | D73: 0.463938 | E73: 0.465786 | F73: 0.466659 | G73: 0.466108 | H73: 0.464014 | I73: 0.463842 | J73: 0.463561 | K73: 0.463877 | L73: 0.46449 | M73: 0.465553 | N73: 0.466452 | O73: 0.468995 | P73: 0.470979 | Q73: 0.473754 | R73: 0.476574 | S73: 0.479564 | T73: 0.483356 | U73: 0.487438 | V73: 0.491518 | W73: 0.495649 | X73: 0.500162 | Y73: 0.505092 | Z73: 0.509883 | AA73: 0.515413 | AB73: 0.521692 | AC73: 0.528346 | AD73: 0.53696 | AE73: 0.543866 | AF73: 0.551526 | AG73: 0.559404 | AH73: 0.567315 | AI73: 0.006531
A74: TKI000:ea_BusTransporta | B74: Bus Transportation | C74: 0.115227 | D74: 0.115901 | E74: 0.116581 | F74: 0.117251 | G74: 0.117882 | H74: 0.118551 | I74: 0.11926 | J74: 0.11995 | K74: 0.120641 | L74: 0.12134 | M74: 0.122028 | N74: 0.122645 | O74: 0.12329 | P74: 0.123892 | Q74: 0.124421 | R74: 0.124924 | S74: 0.125429 | T74: 0.125889 | U74: 0.126375 | V74: 0.126791 | W74: 0.127173 | X74: 0.127473 | Y74: 0.127798 | Z74: 0.128063 | AA74: 0.128311 | AB74: 0.128539 | AC74: 0.128753 | AD74: 0.128956 | AE74: 0.12916 | AF74: 0.129386 | AG74: 0.129657 | AH74: 0.129983 | AI74: 0.003895
A75: TKI000:ea_FreightTrucks | B75: Freight Trucks | C75: 2.827296 | D75: 2.838177 | E75: 2.861533 | F75: 2.877479 | G75: 2.89041 | H75: 2.883003 | I75: 2.873901 | J75: 2.859937 | K75: 2.846777 | L75: 2.829164 | M75: 2.811116 | N75: 2.785219 | O75: 2.775341 | P75: 2.760258 | Q75: 2.752032 | R75: 2.742399 | S75: 2.740685 | T75: 2.743816 | U75: 2.746544 | V75: 2.751515 | W75: 2.757982 | X75: 2.767448 | Y75: 2.780638 | Z75: 2.797015 | AA75: 2.814377 | AB75: 2.838605 | AC75: 2.867797 | AD75: 2.904866 | AE75: 2.931931 | AF75: 2.966593 | AG75: 3.003496 | AH75: 3.040895 | AI75: 0.002352
A76: TKI000:ea_Rail,Passenge | B76: Rail, Passenger | C76: 0.023255 | D76: 0.023671 | E76: 0.024065 | F76: 0.02439 | G76: 0.024703 | H76: 0.025016 | I76: 0.025317 | J76: 0.025614 | K76: 0.025899 | L76: 0.026196 | M76: 0.026491 | N76: 0.026709 | O76: 0.027018 | P76: 0.027313 | Q76: 0.027597 | R76: 0.027856 | S76: 0.02813 | T76: 0.028393 | U76: 0.028663 | V76: 0.028932 | W76: 0.029202 | X76: 0.029463 | Y76: 0.02972 | Z76: 0.029973 | AA76: 0.030235 | AB76: 0.030499 | AC76: 0.030761 | AD76: 0.031043 | AE76: 0.031319 | AF76: 0.031609 | AG76: 0.031885 | AH76: 0.032168 | AI76: 0.010521
A77: TKI000:ea_Rail,Freight | B77: Rail, Freight | C77: 0.247425 | D77: 0.235349 | E77: 0.224294 | F77: 0.221703 | G77: 0.220458 | H77: 0.217186 | I77: 0.211368 | J77: 0.215123 | K77: 0.214871 | L77: 0.214751 | M77: 0.212415 | N77: 0.21003 | O77: 0.209515 | P77: 0.209267 | Q77: 0.209119 | R77: 0.209029 | S77: 0.207961 | T77: 0.207993 | U77: 0.207494 | V77: 0.205728 | W77: 0.205676 | X77: 0.20464 | Y77: 0.204172 | Z77: 0.204352 | AA77: 0.204426 | AB77: 0.204688 | AC77: 0.205248 | AD77: 0.206758 | AE77: 0.207232 | AF77: 0.208277 | AG77: 0.209481 | AH77: 0.211086 | AI77: -0.005111
A78: TKI000:ea_Shipping,Dome | B78: Shipping, Domestic | C78: 0.042333 | D78: 0.041603 | E78: 0.040635 | F78: 0.0394 | G78: 0.038405 | H78: 0.037229 | I78: 0.03608 | J78: 0.035014 | K78: 0.033953 | L78: 0.032851 | M78: 0.031707 | N78: 0.030539 | O78: 0.030006 | P78: 0.029419 | Q78: 0.028888 | R78: 0.02829 | S78: 0.02772 | T78: 0.027204 | U78: 0.02666 | V78: 0.026101 | W78: 0.025585 | X78: 0.025052 | Y78: 0.024795 | Z78: 0.024559 | AA78: 0.0243 | AB78: 0.024088 | AC78: 0.023893 | AD78: 0.023781 | AE78: 0.023574 | AF78: 0.02343 | AG78: 0.023322 | AH78: 0.023231 | AI78: -0.019171
A79: TKI000:ea_Shipping,Inte | B79: Shipping, International | C79: 0.419044 | D79: 0.459324 | E79: 0.440255 | F79: 0.398147 | G79: 0.4 | H79: 0.394394 | I79: 0.399222 | J79: 0.390425 | K79: 0.394511 | L79: 0.39495 | M79: 0.390033 | N79: 0.394978 | O79: 0.395364 | P79: 0.391307 | Q79: 0.394931 | R79: 0.394969 | S79: 0.393888 | T79: 0.390292 | U79: 0.392778 | V79: 0.389117 | W79: 0.38898 | X79: 0.391189 | Y79: 0.387353 | Z79: 0.386861 | AA79: 0.386008 | AB79: 0.384915 | AC79: 0.384226 | AD79: 0.384005 | AE79: 0.383269 | AF79: 0.382965 | AG79: 0.382823 | AH79: 0.382909 | AI79: -0.002905
A80: TKI000:ea_RecreationalB | B80: Recreational Boats | C80: 0.13308 | D80: 0.1335 | E80: 0.133858 | F80: 0.134049 | G80: 0.134152 | H80: 0.134247 | I80: 0.134378 | J80: 0.134477 | K80: 0.134548 | L80: 0.134625 | M80: 0.134701 | N80: 0.134737 | O80: 0.134762 | P80: 0.134771 | Q80: 0.134727 | R80: 0.134629 | S80: 0.134484 | T80: 0.134326 | U80: 0.134143 | V80: 0.133947 | W80: 0.133738 | X80: 0.133498 | Y80: 0.13323 | Z80: 0.132925 | AA80: 0.132613 | AB80: 0.132305 | AC80: 0.132013 | AD80: 0.131737 | AE80: 0.131461 | AF80: 0.131191 | AG80: 0.130914 | AH80: 0.130629 | AI80: -0.0006
A81: TKI000:ea_Air | B81: Air | C81: 1.277419 | D81: 1.292941 | E81: 1.309023 | F81: 1.321509 | G81: 1.33129 | H81: 1.342723 | I81: 1.35579 | J81: 1.368137 | K81: 1.380141 | L81: 1.392848 | M81: 1.406724 | N81: 1.420583 | O81: 1.435178 | P81: 1.449832 | Q81: 1.464272 | R81: 1.476649 | S81: 1.488463 | T81: 1.501402 | U81: 1.514789 | V81: 1.528416 | W81: 1.542677 | X81: 1.557327 | Y81: 1.571836 | Z81: 1.586228 | AA81: 1.601101 | AB81: 1.617454 | AC81: 1.636085 | AD81: 1.656825 | AE81: 1.678637 | AF81: 1.702407 | AG81: 1.727231 | AH81: 1.752876 | AI81: 0.010259
A82: TKI000:ea_MilitaryUse | B82: Military Use | C82: 0.245757 | D82: 0.251956 | E82: 0.247274 | F82: 0.241855 | G82: 0.234618 | H82: 0.229808 | I82: 0.228918 | J82: 0.228018 | K82: 0.227745 | L82: 0.22897 | M82: 0.228454 | N82: 0.228098 | O82: 0.228149 | P82: 0.228197 | Q82: 0.228253 | R82: 0.228318 | S82: 0.228408 | T82: 0.228501 | U82: 0.228635 | V82: 0.228755 | W82: 0.228885 | X82: 0.228999 | Y82: 0.229148 | Z82: 0.229291 | AA82: 0.229445 | AB82: 0.229607 | AC82: 0.229775 | AD82: 0.229945 | AE82: 0.230114 | AF82: 0.230288 | AG82: 0.230466 | AH82: 0.230647 | AI82: -0.002045
A83: TKI000:ea_Lubricants | B83: Lubricants | C83: 0.062101 | D83: 0.061879 | E83: 0.061699 | F83: 0.061486 | G83: 0.061273 | H83: 0.061047 | I83: 0.060801 | J83: 0.060562 | K83: 0.060339 | L83: 0.060146 | M83: 0.059989 | N83: 0.059838 | O83: 0.059705 | P83: 0.059585 | Q83: 0.059469 | R83: 0.059378 | S83: 0.059306 | T83: 0.059277 | U83: 0.059265 | V83: 0.059268 | W83: 0.059288 | X83: 0.059296 | Y83: 0.059298 | Z83: 0.059335 | AA83: 0.059361 | AB83: 0.059407 | AC83: 0.05949 | AD83: 0.059586 | AE83: 0.059688 | AF83: 0.059814 | AG83: 0.059926 | AH83: 0.060027 | AI83: -0.001095
... A85: TKI000:ea_Total | B85: Total | C85: 14.473433 | D85: 14.53084 | E85: 14.515177 | F85: 14.408682 | G85: 14.284176 | H85: 14.113085 | I85: 13.944188 | J85: 13.801455 | K85: 13.680749 | L85: 13.568763 | M85: 13.462358 | N85: 13.368217 | O85: 13.305375 | P85: 13.229243 | Q85: 13.172801 | R85: 13.107446 | S85: 13.048519 | T85: 13.017055 | U85: 12.995325 | V85: 12.977034 | W85: 12.975856 | X85: 12.986323 | Y85: 12.997333 | Z85: 13.026218 | AA85: 13.060641 | AB85: 13.110025 | AC85: 13.173438 | AD85: 13.26224 | AE85: 13.34532 | AF85: 13.450161 | AG85: 13.563889 | AH85: 13.686009 | AI85: -0.001803
B87: 1/ Commercial trucks 8,501 to 10,000 pounds gross vehicle weight rating.
B88: 2/ CAFE standard based on projected new vehicle sales.
B89: 3/ Includes CAFE credits for alternative fueled vehicle sales and credit banking.
B90: 4/ Environmental Protection Agency rated miles per gallon.
B91: 5/ Tested new vehicle efficiency revised for on-road performance.
B92: 6/ Combined "on-the-road" estimate for all cars and light trucks.
B93: CAFE = Corporate average fuel economy.
B94: Btu = British thermal unit.
B95: Note: Totals may not equal sum of components due to independent rounding.
B96: Sources: 2019: U.S. Energy Information Administration (EIA), Short-Term Energy Outlook, October 2019 and EIA, AEO2020 National
B97: Energy Modeling System run highogs.d112619a. Projections: EIA, AEO2020 National Energy Modeling System run highogs.d112619a.

Sheet AEO 35
A1: ORIGINAL EIA CODE | F1: 2020 | G1: 2021 | H1: 2022 | I1: 2023 | J1: 2024 | K1: 2025 | L1: 2026 | M1: 2027 | N1: 2028 | O1: 2029 | P1: 2030 | Q1: 2031 | R1: 2032 | S1: 2033 | T1: 2034 | U1: 2035 | V1: 2036 | W1: 2037 | X1: 2038 | Y1: 2039 | Z1: 2040 | AA1: 2041 | AB1: 2042 | AC1: 2043 | AD1: 2044 | AE1: 2045 | AF1: 2046 | AG1: 2047 | AH1: 2048 | AI1: 2049 | AJ1: 2050 | AK1: Growth (2020-2050)
A10: TEU000 | B10: Table 35. Transportation Sector Energy Use by Mode and Type
B11: https://www.eia.gov/outlooks/aeo/data/browser/#/?id=45-AEO2021&region=0-0&cases=highogs&start=2019&end=2050&f=A&sourcekey=0
B12: Tue Mar 09 2021 10:51:32 GMT-0800 (Pacific Standard Time)
B13: Source: U.S. Energy Information Administration
C14: full name | D14: api key | E14: units | F14: 2020 | G14: 2021 | H14: 2022 | I14: 2023 | J14: 2024 | K14: 2025 | L14: 2026 | M14: 2027 | N14: 2028 | O14: 2029 | P14: 2030 | Q14: 2031 | R14: 2032 | S14: 2033 | T14: 2034 | U14: 2035 | V14: 2036 | W14: 2037 | X14: 2038 | Y14: 2039 | Z14: 2040 | AA14: 2041 | AB14: 2042 | AC14: 2043 | AD14: 2044 | AE14: 2045 | AF14: 2046 | AG14: 2047 | AH14: 2048 | AI14: 2049 | AJ14: 2050 | AK14: Growth (2020-2050)
B15: Energy Use by Mode | D15: 45-AEO2021.2.
B16: Highway | D16: 45-AEO2021.3.
A17: TEU000:ba_Light-DutyVeh | B17: Light-Duty Vehicles | C17: Transportation Energy Use: Highway: Light-Duty Vehicles: High oil and gas supply | D17: 45-AEO2021.4.highogs-d120120a | E17: trillion Btu | F17: 13684.959 | G17: 14333.232 | H17: 14327.021 | I17: 14365.353 | J17: 14366.454 | K17: 14341.867 | L17: 14287.134 | M17: 14207.24 | N17: 14125.377 | O17: 14028.782 | P17: 13931.946 | Q17: 13831.038 | R17: 13740.6 | S17: 13671.223 | T17: 13614.178 | U17: 13578.905 | V17: 13555.065 | W17: 13533.014 | X17: 13512.937 | Y17: 13507.699 | Z17: 13519.428 | AA17: 13531.689 | AB17: 13551.022 | AC17: 13573.049 | AD17: 13591.697 | AE17: 13608.703 | AF17: 13631.723 | AG17: 13650.464 | AH17: 13676.699 | AI17: 13706.515 | AJ17: 13736.45 | AK17: 0
A18: TEU000:ba_Automobiles | B18: Automobiles | C18: Transportation Energy Use: Highway: Light-Duty Vehicles: Automobiles: High oil and gas supply | D18: 45-AEO2021.5.highogs-d120120a | E18: trillion Btu | F18: 5675.0977 | G18: 5849.8979 | H18: 5755.2529 | I18: 5674.1973 | J18: 5571.2588 | K18: 5452.5518 | L18: 5322.6035 | M18: 5185.96 | N18: 5050.46 | O18: 4913.0923 | P18: 4785.4287 | Q18: 4662.6523 | R18: 4550.6763 | S18: 4453.6479 | T18: 4370.249 | U18: 4301.7231 | V18: 4245.416 | W18: 4198.5293 | X18: 4159.6685 | Y18: 4129.9312 | Z18: 4109.8428 | AA18: 4093.1614 | AB18: 4081.1697 | AC18: 4071.9587 | AD18: 4063.4624 | AE18: 4055.2773 | AF18: 4048.9263 | AG18: 4041.3586 | AH18: 4035.5654 | AI18: 4031.2227 | AJ18: 4027.0671 | AK18: -0.011
A19: TEU000:ba_LightTrucks | B19: Light Trucks | C19: Transportation Energy Use: Highway: Light-Duty Vehicles: Light Trucks: High oil and gas supply | D19: 45-AEO2021.6.highogs-d120120a | E19: trillion Btu | F19: 7993.563 | G19: 8466.5332 | H19: 8555.2402 | I19: 8674.8594 | J19: 8779.1953 | K19: 8873.6572 | L19: 8949.2451 | M19: 9006.3877 | N19: 9060.4141 | O19: 9101.5811 | P19: 9132.7764 | Q19: 9154.9971 | R19: 9176.8564 | S19: 9204.7871 | T19: 9231.3809 | U19: 9264.832 | V19: 9297.46 | W19: 9322.4297 | X19: 9341.3252 | Y19: 9365.9111 | Z19: 9397.7852 | AA19: 9426.7773 | AB19: 9458.1357 | AC19: 9489.3994 | AD19: 9516.5684 | AE19: 9541.7832 | AF19: 9571.1719 | AG19: 9597.5029 | AH19: 9629.5479 | AI19: 9663.7188 | AJ19: 9697.8213 | AK19: 0.006
A20: TEU000:ba_Motorcycles | B20: Motorcycles | C20: Transportation Energy Use: Highway: Light-Duty Vehicles: Motorcycles: High oil and gas supply | D20: 45-AEO2021.7.highogs-d120120a | E20: trillion Btu | F20: 16.299149 | G20: 16.800869 | H20: 16.528765 | I20: 16.295639 | J20: 15.999691 | K20: 15.658419 | L20: 15.284882 | M20: 14.89215 | N20: 14.502714 | O20: 14.107929 | P20: 13.741054 | Q20: 13.388216 | R20: 13.066401 | S20: 12.787572 | T20: 12.547906 | U20: 12.350933 | V20: 12.189022 | W20: 12.054244 | X20: 11.942542 | Y20: 11.85706 | Z20: 11.799364 | AA20: 11.751442 | AB20: 11.71702 | AC20: 11.690611 | AD20: 11.666224 | AE20: 11.642757 | AF20: 11.624537 | AG20: 11.602818 | AH20: 11.586204 | AI20: 11.573715 | AJ20: 11.561806 | AK20: -0.011
A21: TEU000:ba_CommercialLig | B21: Commercial Light Trucks | C21: Transportation Energy Use: Highway: Commercial Light Trucks: High oil and gas supply | D21: 45-AEO2021.8.highogs-d120120a | E21: trillion Btu | F21: 800.59766 | G21: 824.58264 | H21: 837.18012 | I21: 842.73663 | J21: 851.00818 | K21: 861.96362 | L21: 867.17664 | M21: 868.25635 | N21: 868.72144 | O21: 868.14349 | P21: 868.26971 | Q21: 869.091 | R21: 871.65924 | S21: 875.05597 | T21: 880.52374 | U21: 888.54584 | V21: 896.60486 | W21: 904.57898 | X21: 913.07678 | Y21: 922.39557 | Z21: 932.01129 | AA21: 942.83514 | AB21: 953.38037 | AC21: 965.23499 | AD21: 976.00677 | AE21: 987.21423 | AF21: 999.34717 | AG21: 1008.7945 | AH21: 1019.4604 | AI21: 1031.4871 | AJ21: 1044.0883 | AK21: 0.009
A22: TEU000:ba_Buses | B22: Buses | C22: Transportation Energy Use: Highway: Buses: High oil and gas supply | D22: 45-AEO2021.9.highogs-d120120a | E22: trillion Btu | F22: 123.60058 | G22: 155.22908 | H22: 178.08673 | I22: 194.79402 | J22: 207.08707 | K22: 215.93285 | L22: 222.4467 | M22: 227.38673 | N22: 229.82677 | O22: 231.57542 | P22: 233.38449 | Q22: 233.90918 | R22: 234.57722 | S22: 234.89816 | T22: 235.11737 | U22: 234.73181 | V22: 234.535 | W22: 234.32896 | X22: 233.97902 | Y22: 233.39026 | Z22: 232.92192 | AA22: 232.25186 | AB22: 231.51384 | AC22: 230.76698 | AD22: 230.02493 | AE22: 229.27586 | AF22: 228.442 | AG22: 227.6967 | AH22: 226.85817 | AI22: 226.28667 | AJ22: 225.79506 | AK22: 0.02
A23: TEU000:ba_Transit | B23: Transit | C23: Transportation Energy Use: Highway: Buses: Transit: High oil and gas supply | D23: 45-AEO2021.10.highogs-d120120a | E23: trillion Btu | F23: 65.868385 | G23: 77.343925 | H23: 85.037193 | I23: 90.397377 | J23: 94.148392 | K23: 96.454201 | L23: 98.028534 | M23: 99.228485 | N23: 98.787506 | O23: 98.326218 | P23: 98.456612 | Q23: 97.730179 | R23: 97.429573 | S23: 97.078491 | T23: 96.865768 | U23: 96.19072 | V23: 95.827606 | W23: 95.546768 | X23: 95.188217 | Y23: 94.635986 | Z23: 94.23497 | AA23: 93.65612 | AB23: 93.025208 | AC23: 92.393784 | AD23: 91.770996 | AE23: 91.134651 | AF23: 90.408363 | AG23: 89.765427 | AH23: 89.013596 | AI23: 88.517876 | AJ23: 88.092033 | AK23: 0.01
A24: TEU000:ba_Intercity | B24: Intercity | C24: Transportation Energy Use: Highway: Buses: Intercity: High oil and gas supply | D24: 45-AEO2021.11.highogs-d120120a | E24: trillion Btu | F24: 21.389296 | G24: 24.819853 | H24: 27.510082 | I24: 29.622658 | J24: 31.287823 | K24: 32.605827 | L24: 33.663296 | M24: 34.520813 | N24: 35.224197 | O24: 35.81303 | P24: 36.317593 | Q24: 36.759636 | R24: 37.152344 | S24: 37.510296 | T24: 37.844872 | U24: 38.157986 | V24: 38.449917 | W24: 38.72361 | X24: 38.985104 | Y24: 39.238808 | Z24: 39.486942 | AA24: 39.72662 | AB24: 39.958668 | AC24: 40.184944 | AD24: 40.404293 | AE24: 40.622166 | AF24: 40.834713 | AG24: 41.040451 | AH24: 41.248081 | AI24: 41.453495 | AJ24: 41.657665 | AK24: 0.022
A25: TEU000:ba_School | B25: School | C25: Transportation Energy Use: Highway: Buses: School: High oil and gas supply | D25: 45-AEO2021.12.highogs-d120120a | E25: trillion Btu | F25: 36.342903 | G25: 53.065319 | H25: 65.539474 | I25: 74.77401 | J25: 81.650841 | K25: 86.872803 | L25: 90.754913 | M25: 93.637444 | N25: 95.815033 | O25: 97.436134 | P25: 98.610291 | Q25: 99.419357 | R25: 99.995285 | S25: 100.30936 | T25: 100.40678 | U25: 100.38309 | V25: 100.25748 | W25: 100.05856 | X25: 99.805702 | Y25: 99.51545 | Z25: 99.200005 | AA25: 98.869118 | AB25: 98.529976 | AC25: 98.188255 | AD25: 97.849648 | AE25: 97.519051 | AF25: 97.198906 | AG25: 96.890816 | AH25: 96.596497 | AI25: 96.315292 | AJ25: 96.04538 | AK25: 0.033
A26: TEU000:ba_FreightTrucks | B26: Freight Trucks | C26: Transportation Energy Use: Highway: Freight Trucks: High oil and gas supply | D26: 45-AEO2021.13.highogs-d120120a | E26: trillion Btu | F26: 5217.8584 | G26: 5322.7695 | H26: 5462.249 | I26: 5509.6768 | J26: 5566.189 | K26: 5614.4268 | L26: 5611.2627 | M26: 5579.9849 | N26: 5546.2661 | O26: 5504.2886 | P26: 5469.7124 | Q26: 5438.3926 | R26: 5413.3032 | S26: 5386.6934 | T26: 5378.145 | U26: 5393.2607 | V26: 5407.6289 | W26: 5423.5879 | X26: 5448.6401 | Y26: 5481.9277 | Z26: 5512.1758 | AA26: 5555.085 | AB26: 5607.7852 | AC26: 5675.5957 | AD26: 5732.5215 | AE26: 5793.834 | AF26: 5843.8721 | AG26: 5892.3438 | AH26: 5949.0996 | AI26: 6010.8965 | AJ26: 6080.1992 | AK26: 0.005
A27: TEU000:ba_LightMedium | B27: Light Medium | C27: Transportation Energy Use: Highway: Freight Trucks: Light Medium: High oil and gas supply | D27: 45-AEO2021.14.highogs-d120120a | E27: trillion Btu | F27: 623.06995 | G27: 645.39587 | H27: 666.46094 | I27: 672.76428 | J27: 679.08014 | K27: 685.09302 | L27: 686.81488 | M27: 689.4306 | N27: 695.90314 | O27: 704.39606 | P27: 715.78516 | Q27: 728.40607 | R27: 741.20001 | S27: 752.46381 | T27: 764.91388 | U27: 778.96106 | V27: 790.86975 | W27: 801.79034 | X27: 813.50751 | Y27: 825.59967 | Z27: 835.62042 | AA27: 847.15546 | AB27: 859.51312 | AC27: 873.85864 | AD27: 886.58179 | AE27: 900.4129 | AF27: 912.65735 | AG27: 925.97638 | AH27: 941.71063 | AI27: 957.63281 | AJ27: 974.67029 | AK27: 0.015
A28: TEU000:ba_Medium | B28: Medium | C28: Transportation Energy Use: Highway: Freight Trucks: Medium: High oil and gas supply | D28: 45-AEO2021.15.highogs-d120120a | E28: trillion Btu | F28: 857.06537 | G28: 869.86615 | H28: 890.51807 | I28: 896.80109 | J28: 905.21356 | K28: 912.46588 | L28: 913.59228 | M28: 912.76141 | N28: 914.32025 | O28: 915.86731 | P28: 919.06012 | Q28: 922.55646 | R28: 927.62286 | S28: 931.74396 | T28: 938.57819 | U28: 949.5282 | V28: 960.74689 | W28: 973.51715 | X28: 988.40875 | Y28: 1006.5817 | Z28: 1024.9167 | AA28: 1046.2407 | AB28: 1069.5592 | AC28: 1096.8451 | AD28: 1122.9235 | AE28: 1150.4531 | AF28: 1176.5758 | AG28: 1203.0889 | AH28: 1232.1707 | AI28: 1263.6315 | AJ28: 1297.5896 | AK28: 0.014
A29: TEU000:ba_Large(>26000p | B29: Large (> 26000 pounds) | C29: Transportation Energy Use: Highway: Freight Trucks: Large: High oil and gas supply | D29: 45-AEO2021.16.highogs-d120120a | E29: trillion Btu | F29: 3737.7229 | G29: 3807.5073 | H29: 3905.2695 | I29: 3940.1116 | J29: 3981.8948 | K29: 4016.8679 | L29: 4010.8555 | M29: 3977.7935 | N29: 3936.0427 | O29: 3884.0256 | P29: 3834.8677 | Q29: 3787.4297 | R29: 3744.4802 | S29: 3702.4858 | T29: 3674.6531 | U29: 3664.7715 | V29: 3656.0122 | W29: 3648.28 | X29: 3646.7239 | Y29: 3649.7461 | Z29: 3651.6387 | AA29: 3661.6887 | AB29: 3678.7134 | AC29: 3704.8914 | AD29: 3723.0164 | AE29: 3742.968 | AF29: 3754.6394 | AG29: 3763.2793 | AH29: 3775.218 | AI29: 3789.6326 | AJ29: 3807.9399 | AK29: 0.001
B30: Non-Highway | D30: 45-AEO2021.18.
A31: TEU000:ca_Air | B31: Air | C31: Transportation Energy Use: Non-Highway: Air: High oil and gas supply | D31: 45-AEO2021.19.highogs-d120120a | E31: trillion Btu | F31: 1860.4854 | G31: 2530.9844 | H31: 2826.3455 | I31: 2963.3054 | J31: 3051.7676 | K31: 3120.2192 | L31: 3144.2419 | M31: 3161.6294 | N31: 3182.7922 | O31: 3201.8508 | P31: 3222.4722 | Q31: 3248.7065 | R31: 3287.2988 | S31: 3325.2964 | T31: 3367.7896 | U31: 3416.8149 | V31: 3457.4727 | W31: 3492.2017 | X31: 3528.9043 | Y31: 3570.2961 | Z31: 3622.0222 | AA31: 3669.8469 | AB31: 3718.9998 | AC31: 3765.7593 | AD31: 3814.1929 | AE31: 3866.814 | AF31: 3914.7515 | AG31: 3951.364 | AH31: 3990.6257 | AI31: 4026.4133 | AJ31: 4062.8081 | AK31: 0.026
A32: TEU000:ca_GeneralAviati | B32: General Aviation | C32: Transportation Energy Use: Non-Highway: Air: General Aviation: High oil and gas supply | D32: 45-AEO2021.20.highogs-d120120a | E32: trillion Btu | F32: 109.97633 | G32: 141.88948 | H32: 155.94163 | I32: 162.45311 | J32: 166.65692 | K32: 169.90941 | L32: 171.04748 | M32: 171.87045 | N32: 172.87425 | O32: 173.77844 | P32: 174.75746 | Q32: 176.00456 | R32: 177.84047 | S32: 179.64813 | T32: 181.67046 | U32: 184.0038 | V32: 185.9389 | W32: 187.59193 | X32: 189.3391 | Y32: 191.30975 | Z32: 193.77246 | AA32: 196.04944 | AB32: 198.38971 | AC32: 200.61627 | AD32: 202.92221 | AE32: 205.4279 | AF32: 207.71048 | AG32: 209.45377 | AH32: 211.3233 | AI32: 213.02757 | AJ32: 214.76041 | AK32: 0.023
A33: TEU000:ca_DomesticAirCa | B33: Domestic Passenger | C33: Transportation Energy Use: Non-Highway: Air: Domestic Passenger: High oil and gas supply | D33: 45-AEO2021.21.highogs-d120120a | E33: trillion Btu | F33: 1029.3035 | G33: 1377.4302 | H33: 1491.1099 | I33: 1527.3287 | J33: 1540.603 | K33: 1575.2826 | L33: 1594.6243 | M33: 1603.1229 | N33: 1606.5917 | O33: 1607.7135 | P33: 1610.0349 | Q33: 1616.2908 | R33: 1629.0068 | S33: 1642.5435 | T33: 1659.3156 | U33: 1678.5675 | V33: 1694.2118 | W33: 1706.4603 | X33: 1719.7704 | Y33: 1737.08 | Z33: 1758.8617 | AA33: 1779.666 | AB33: 1799.6539 | AC33: 1818.678 | AD33: 1836.4475 | AE33: 1856.6439 | AF33: 1873.9916 | AG33: 1887.5896 | AH33: 1904.7295 | AI33: 1921.5889 | AJ33: 1938.8723 | AK33: 0.021
A34: TEU000:ca_International | B34: International Passenger | C34: Transportation Energy Use: Non-Highway: Air: International Passenger: High oil and gas supply | D34: 45-AEO2021.22.highogs-d120120a | E34: trillion Btu | F34: 162.01057 | G34: 492.52274 | H34: 669.41522 | I34: 750.97778 | J34: 811.16065 | K34: 837.4071 | L34: 840.55621 | M34: 845.41003 | N34: 854.7381 | O34: 864.04321 | P34: 873.57477 | Q34: 884.18176 | R34: 898.26648 | S34: 911.64954 | T34: 925.93701 | U34: 942.49945 | V34: 956.36585 | W34: 968.7132 | X34: 981.62439 | Y34: 995.19794 | Z34: 1012.1129 | AA34: 1027.5292 | AB34: 1044.0427 | AC34: 1059.8073 | AD34: 1076.9177 | AE34: 1095.1249 | AF34: 1112.1973 | AG34: 1125.2657 | AH34: 1138.3204 | AI34: 1149.8088 | AJ34: 1161.4449 | AK34: 0.068
A35: TEU000:ca_FreightCarrie | B35: Dedicated Freight | C35: Transportation Energy Use: Non-Highway: Air: Dedicated Freight: High oil and gas supply | D35: 45-AEO2021.23.highogs-d120120a | E35: trillion Btu | F35: 559.19495 | G35: 519.14203 | H35: 509.87872 | I35: 522.54559 | J35: 533.34705 | K35: 537.62024 | L35: 538.01386 | M35: 541.22595 | N35: 548.58813 | O35: 556.31574 | P35: 564.1051 | Q35: 572.22961 | R35: 582.18518 | S35: 591.45514 | T35: 600.86682 | U35: 611.74402 | V35: 620.95605 | W35: 629.43628 | X35: 638.17041 | Y35: 646.7085 | Z35: 657.27508 | AA35: 666.6023 | AB35: 676.91339 | AC35: 686.65765 | AD35: 697.90521 | AE35: 709.61707 | AF35: 720.85217 | AG35: 729.05499 | AH35: 736.25275 | AI35: 741.98798 | AJ35: 747.73035 | AK35: 0.01
A36: TEU000:ca_Water | B36: Water | C36: Transportation Energy Use: Non-Highway: Water: High oil and gas supply | D36: 45-AEO2021.24.highogs-d120120a | E36: trillion Btu | F36: 1129.1088 | G36: 1157.2632 | H36: 1251.9425 | I36: 1271.0579 | J36: 1220.1064 | K36: 1222.1813 | L36: 1231.5403 | M36: 1205.2488 | N36: 1202.4742 | O36: 1190.4596 | P36: 1189.082 | Q36: 1203.5217 | R36: 1186.6602 | S36: 1184.9104 | T36: 1180.7228 | U36: 1193.8921 | V36: 1177.7051 | W36: 1175.0314 | X36: 1182.9781 | Y36: 1167.7097 | Z36: 1164.3445 | AA36: 1175.8888 | AB36: 1158.8889 | AC36: 1157.1489 | AD36: 1149.3973 | AE36: 1148.7852 | AF36: 1143.7438 | AG36: 1139.9766 | AH36: 1139.2001 | AI36: 1136.608 | AJ36: 1132.9697 | AK36: 0
A37: TEU000:ca_Freight | B37: Freight | C37: Transportation Energy Use: Non-Highway: Water: Freight: High oil and gas supply | D37: 45-AEO2021.25.highogs-d120120a | E37: trillion Btu | F37: 933.23035 | G37: 960.6062 | H37: 1052.2262 | I37: 1069.5435 | J37: 1017.8489 | K37: 1019.6077 | L37: 1029.6858 | M37: 1004.8707 | N37: 1003.7998 | O37: 993.62921 | P37: 994.01324 | Q37: 1009.9661 | R37: 994.1709 | S37: 993.52716 | T37: 990.23901 | U37: 1004.0739 | V37: 988.7948 | W37: 987.27228 | X37: 996.31964 | Y37: 981.9082 | Z37: 979.12146 | AA37: 991.30054 | AB37: 975.00702 | AC37: 973.97424 | AD37: 967.06848 | AE37: 967.10553 | AF37: 962.83832 | AG37: 960.09705 | AH37: 960.05969 | AI37: 958.24249 | AJ37: 955.39801 | AK37: 0.001
A38: TEU000:ca_DomesticShipp | B38: Domestic Shipping | C38: Transportation Energy Use: Non-Highway: Water: Freight: Domestic Shipping: High oil and gas supply | D38: 45-AEO2021.26.highogs-d120120a | E38: trillion Btu | F38: 77.343407 | G38: 79.141403 | H38: 78.228264 | I38: 77.350044 | J38: 76.446533 | K38: 75.055573 | L38: 73.204681 | M38: 71.058418 | N38: 68.994972 | O38: 66.833633 | P38: 64.753128 | Q38: 63.638058 | R38: 62.605038 | S38: 61.510983 | T38: 60.561947 | U38: 59.665359 | V38: 58.721436 | W38: 57.711258 | X38: 56.658974 | Y38: 55.745102 | Z38: 54.692238 | AA38: 54.265388 | AB38: 53.873783 | AC38: 53.634262 | AD38: 53.239914 | AE38: 52.87286 | AF38: 52.373196 | AG38: 51.890907 | AH38: 51.370388 | AI38: 50.910122 | AJ38: 50.533489 | AK38: -0.014
A39: TEU000:da_International | B39: International Shipping | C39: Transportation Energy Use: Non-Highway: Water: Freight: International Shipping: High oil and gas supply | D39: 45-AEO2021.27.highogs-d120120a | E39: trillion Btu | F39: 855.88696 | G39: 881.46478 | H39: 973.99793 | I39: 992.19336 | J39: 941.40234 | K39: 944.55212 | L39: 956.48108 | M39: 933.81226 | N39: 934.80481 | O39: 926.79559 | P39: 929.26013 | Q39: 946.32806 | R39: 931.56586 | S39: 932.01617 | T39: 929.67706 | U39: 944.40857 | V39: 930.07336 | W39: 929.56103 | X39: 939.66065 | Y39: 926.16309 | Z39: 924.4292 | AA39: 937.03516 | AB39: 921.13324 | AC39: 920.33997 | AD39: 913.82855 | AE39: 914.23267 | AF39: 910.46515 | AG39: 908.20612 | AH39: 908.68933 | AI39: 907.3324 | AJ39: 904.8645 | AK39: 0.002
A40: TEU000:da_RecreationalB | B40: Recreational Boats | C40: Transportation Energy Use: Non-Highway: Water: Recreational Boats: High oil and gas supply | D40: 45-AEO2021.28.highogs-d120120a | E40: trillion Btu | F40: 195.87843 | G40: 196.65694 | H40: 199.71631 | I40: 201.51434 | J40: 202.25748 | K40: 202.57369 | L40: 201.85445 | M40: 200.37804 | N40: 198.67445 | O40: 196.83032 | P40: 195.06877 | Q40: 193.55562 | R40: 192.48926 | S40: 191.38321 | T40: 190.48383 | U40: 189.81821 | V40: 188.91023 | W40: 187.75908 | X40: 186.65848 | Y40: 185.8015 | Z40: 185.22307 | AA40: 184.58832 | AB40: 183.88181 | AC40: 183.17465 | AD40: 182.32883 | AE40: 181.67963 | AF40: 180.9055 | AG40: 179.87953 | AH40: 179.14038 | AI40: 178.36557 | AJ40: 177.57169 | AK40: -0.003
A41: TEU000:da_Rail | B41: Rail | C41: Transportation Energy Use: Non-Highway: Rail: High oil and gas supply | D41: 45-AEO2021.29.highogs-d120120a | E41: trillion Btu | F41: 461.76639 | G41: 491.05136 | H41: 497.25409 | I41: 498.29584 | J41: 498.00287 | K41: 483.20465 | L41: 487.16257 | M41: 485.19531 | N41: 488.07013 | O41: 490.24463 | P41: 492.73157 | Q41: 493.54889 | R41: 493.9744 | S41: 495.27838 | T41: 495.26675 | U41: 496.70953 | V41: 497.9765 | W41: 498.69684 | X41: 497.479 | Y41: 499.69305 | Z41: 499.10703 | AA41: 500.07611 | AB41: 502.25479 | AC41: 505.43637 | AD41: 504.1955 | AE41: 505.57495 | AF41: 505.80637 | AG41: 507.0365 | AH41: 508.25165 | AI41: 509.73273 | AJ41: 512.97174 | AK41: 0.004
A42: TEU000:da_Freight | B42: Freight | C42: Transportation Energy Use: Non-Highway: Rail: Freight: High oil and gas supply | D42: 45-AEO2021.30.highogs-d120120a | E42: trillion Btu | F42: 432.32916 | G42: 455.80057 | H42: 457.32019 | I42: 454.81757 | J42: 451.84665 | K42: 435.03867 | L42: 437.54752 | M42: 434.49982 | N42: 437.06894 | O42: 438.99457 | P42: 440.98004 | Q42: 441.53027 | R42: 441.40082 | S42: 442.16769 | T42: 441.50205 | U42: 442.37979 | V42: 443.02426 | W42: 443.14713 | X42: 441.33752 | Y42: 442.94101 | Z42: 441.56534 | AA42: 441.80859 | AB42: 443.27573 | AC42: 445.72418 | AD42: 443.77713 | AE42: 444.37201 | AF42: 443.88855 | AG42: 444.47339 | AH42: 444.99793 | AI42: 445.72116 | AJ42: 448.21558 | AK42: 0.001
... A53: TEU000:fa_Total | B53: Total | C53: Transportation Energy Use: Total: High oil and gas supply | D53: 45-AEO2021.43.highogs-d120120a | E53: trillion Btu | F53: 24641.816 | G53: 26248.666 | H53: 26805.998 | I53: 27035.342 | J53: 27134.359 | K53: 27234.799 | L53: 27191.32 | M53: 27084.865 | N53: 26996.002 | O53: 26866.41 | P53: 26748.799 | Q53: 26660.07 | R53: 26573.197 | S53: 26520.012 | T53: 26498.09 | U53: 26553.664 | V53: 26586.883 | W53: 26631.479 | X53: 26696.67 | Y53: 26767.367 | Z53: 26871.051 | AA53: 27000.164 | AB53: 27121.412 | AC53: 27278.543 | AD53: 27415.6 | AE53: 27565.312 | AF53: 27701.846 | AG53: 27821.959 | AH53: 27950.746 | AI53: 28088.564 | AJ53: 28244.232 | AK53: 0.005
B54: Energy Use by Type | D54: 45-AEO2021.45.
A55: TEU000:ga_MotorGasoline | B55: Motor Gasoline excluding E85 | C55: Transportation Energy Use: Petroleum: Motor Gasoline: High oil and gas supply | D55: 45-AEO2021.46.highogs-d120120a | E55: trillion Btu | F55: 14809.331 | G55: 15470.562 | H55: 15477.318 | I55: 15509.706 | J55: 15508.433 | K55: 15483.517 | L55: 15421.747 | M55: 15333.079 | N55: 15245.05 | O55: 15143.332 | P55: 15043.969 | Q55: 14940.797 | R55: 14850.533 | S55: 14780.868 | T55: 14725.552 | U55: 14695.301 | V55: 14674.445 | W55: 14655.884 | X55: 14640.091 | Y55: 14640.239 | Z55: 14655.854 | AA55: 14675.101 | AB55: 14702.387 | AC55: 14734.696 | AD55: 14761.429 | AE55: 14788.444 | AF55: 14820.81 | AG55: 14848.021 | AH55: 14885.904 | AI55: 14929.089 | AJ55: 14974.693 | AK55: 0
A56: TEU000:ga_Ethanol | B56: E85 | C56: Transportation Energy Use: E85: High oil and gas supply | D56: 45-AEO2021.47.highogs-d120120a | E56: trillion Btu | F56: 33.666061 | G56: 36.292164 | H56: 35.002701 | I56: 36.768921 | J56: 37.090172 | K56: 37.279301 | L56: 37.273434 | M56: 36.962608 | N56: 36.692116 | O56: 36.407269 | P56: 36.183594 | Q56: 36.116623 | R56: 36.088921 | S56: 36.198486 | T56: 36.388977 | U56: 36.925545 | V56: 37.477287 | W56: 38.130039 | X56: 38.828465 | Y56: 39.735065 | Z56: 40.706123 | AA56: 41.727245 | AB56: 42.842529 | AC56: 43.978745 | AD56: 45.153854 | AE56: 46.265217 | AF56: 47.409328 | AG56: 48.760159 | AH56: 49.995644 | AI56: 51.544422 | AJ56: 53.091187 | AK56: 0.015
A57: TEU000:ga_Distillate(di | B57: Diesel | C57: Transportation Energy Use: Petroleum: Diesel: High oil and gas supply | D57: 45-AEO2021.48.highogs-d120120a | E57: trillion Btu | F57: 6144.374 | G57: 6254.561 | H57: 6296.688 | I57: 6333.9224 | J57: 6469.3887 | K57: 6508.3208 | L57: 6497.1807 | M57: 6493.1206 | N57: 6455.3403 | O57: 6414.4653 | P57: 6368.2964 | Q57: 6301.3911 | R57: 6279.1006 | S57: 6236.5176 | T57: 6213.1655 | U57: 6192.251 | V57: 6207.4717 | W57: 6203.5488 | X57: 6192.0122 | Y57: 6220.2158 | Z57: 6226.5527 | AA57: 6228.9126 | AB57: 6273.5908 | AC57: 6314.6074 | AD57: 6347.5444 | AE57: 6376.3735 | AF57: 6399.9995 | AG57: 6418.7915 | AH57: 6440.9194 | AI57: 6466.8232 | AJ57: 6500.1226 | AK57: 0.002
A58: TEU000:ga_JetFuel(keros | B58: Jet Fuel (kerosene & naphtha) | C58: Transportation Energy Use: Petroleum: Jet Fuel: High oil and gas supply | D58: 45-AEO2021.49.highogs-d120120a | E58: trillion Btu | F58: 2239.7639 | G58: 2917.0544 | H58: 3212.9678 | I58: 3340.0581 | J58: 3422.0215 | K58: 3490.0879 | L58: 3513.1729 | M58: 3530.4417 | N58: 3553.7649 | O58: 3571.9607 | P58: 3591.0972 | Q58: 3617.2712 | R58: 3656.4937 | S58: 3695.1418 | T58: 3738.2942 | U58: 3787.9761 | V58: 3829.3232 | W58: 3864.7639 | X58: 3902.1855 | Y58: 3944.3027 | Z58: 3996.7605 | AA58: 4045.3213 | AB58: 4095.2144 | AC58: 4142.7163 | AD58: 4191.8945 | AE58: 4245.2622 | AF58: 4293.9473 | AG58: 4331.3066 | AH58: 4371.3149 | AI58: 4407.8477 | AJ58: 4444.9878 | AK58: 0.023
A59: TEU000:ga_ResidualOil | B59: Residual Fuel Oil | C59: Transportation Energy Use: Petroleum: Residual Fuel Oil: High oil and gas supply | D59: 45-AEO2021.50.highogs-d120120a | E59: trillion Btu | F59: 434.51096 | G59: 495.77799 | H59: 725.47064 | I59: 768.43817 | J59: 637.95599 | K59: 643.69513 | L59: 671.79657 | M59: 613.03705 | N59: 614.04077 | O59: 592.20502 | P59: 596.73608 | Q59: 638.2135 | R59: 599.47522 | S59: 599.14294 | T59: 591.7016 | U59: 627.17792 | V59: 589.56049 | W59: 586.8938 | X59: 610.94092 | Y59: 575.47443 | Z59: 569.64368 | AA59: 599.98962 | AB59: 558.53235 | AC59: 555.12524 | AD59: 537.4079 | AE59: 537.04724 | AF59: 526.17023 | AG59: 519.23303 | AH59: 519.10999 | AI59: 514.34662 | AJ59: 506.8952 | AK59: 0.005
A60: TEU000:ga_AviationGasol | B60: Aviation Gasoline | C60: Transportation Energy Use: Petroleum: Aviation Gasoline: High oil and gas supply | D60: 45-AEO2021.51.highogs-d120120a | E60: trillion Btu | F60: 22.450933 | G60: 22.434891 | H60: 22.421618 | I60: 22.410635 | J60: 22.401548 | K60: 22.394032 | L60: 22.387812 | M60: 22.382666 | N60: 22.378407 | O60: 22.374884 | P60: 22.371969 | Q60: 22.369558 | R60: 22.367563 | S60: 22.365911 | T60: 22.364546 | U60: 22.363417 | V60: 22.36248 | W60: 22.361708 | X60: 22.361067 | Y60: 22.360538 | Z60: 22.3601 | AA60: 22.359737 | AB60: 22.359438 | AC60: 22.35919 | AD60: 22.358984 | AE60: 22.358814 | AF60: 22.358673 | AG60: 22.358557 | AH60: 22.358461 | AI60: 22.358381 | AJ60: 22.358315 | AK60: 0
A61: TEU000:ga_LiquefiedPetr | B61: Propane | C61: Transportation Energy Use: Petroleum: Propane: High oil and gas supply | D61: 45-AEO2021.52.highogs-d120120a | E61: trillion Btu | F61: 5.55008 | G61: 6.081212 | H61: 6.44719 | I61: 6.641568 | J61: 6.762898 | K61: 6.878024 | L61: 6.961869 | M61: 7.054108 | N61: 7.103945 | O61: 7.166772 | P61: 7.258247 | Q61: 7.319052 | R61: 7.419724 | S61: 7.521624 | T61: 7.697729 | U61: 7.864295 | V61: 8.053552 | W61: 8.252381 | X61: 8.475512 | Y61: 8.70771 | Z61: 8.956078 | AA61: 9.219524 | AB61: 9.490154 | AC61: 9.800427 | AD61: 10.104954 | AE61: 10.434702 | AF61: 10.753673 | AG61: 11.084869 | AH61: 11.440404 | AI61: 11.822479 | AJ61: 12.232215 | AK61: 0.027
A62: TEU000:ga_Lubricants | B62: Lubricants | C62: Transportation Energy Use: Petroleum: Lubricants: High oil and gas supply | D62: 45-AEO2021.53.highogs-d120120a | E62: trillion Btu | F62: 121.22439 | G62: 123.40012 | H62: 124.82059 | I62: 125.91473 | J62: 126.65642 | K62: 127.04057 | L62: 127.20718 | M62: 126.85352 | N62: 126.59703 | O62: 126.37843 | P62: 126.07404 | Q62: 125.8016 | R62: 125.58483 | S62: 125.40055 | T62: 125.28949 | U62: 125.20488 | V62: 125.08443 | W62: 124.93435 | X62: 124.83044 | Y62: 124.75782 | Z62: 124.67342 | AA62: 124.58897 | AB62: 124.5218 | AC62: 124.43999 | AD62: 124.42282 | AE62: 124.4984 | AF62: 124.51592 | AG62: 124.47363 | AH62: 124.49622 | AI62: 124.46999 | AJ62: 124.38553 | AK62: 0.001
A63: TEU000:ga_PetroleumSubt | B63: Petroleum and Other Liquids Subtotal | C63: Transportation Energy Use: Petroleum Subtotal: High oil and gas supply | D63: 45-AEO2021.54.highogs-d120120a | E63: trillion Btu | F63: 23810.873 | G63: 25326.166 | H63: 25901.135 | I63: 26143.859 | J63: 26230.709 | K63: 26319.215 | L63: 26297.729 | M63: 26162.932 | N63: 26060.969 | O63: 25914.291 | P63: 25791.986 | Q63: 25689.277 | R63: 25577.062 | S63: 25503.158 | T63: 25460.453 | U63: 25495.064 | V63: 25493.779 | W63: 25504.77 | X63: 25539.725 | Y63: 25575.793 | Z63: 25645.508 | AA63: 25747.221 | AB63: 25828.938 | AC63: 25947.725 | AD63: 26040.316 | AE63: 26150.686 | AF63: 26245.965 | AG63: 26324.029 | AH63: 26425.539 | AI63: 26528.301 | AJ63: 26638.766 | AK63: 0.004
A64: TEU000:ga_Methanol | B64: M85 | C64: Transportation Energy Use: M85: High oil and gas supply | D64: 45-AEO2021.55.highogs-d120120a | E64: trillion Btu | F64: 0 | G64: 0 | H64: 0 | I64: 0 | J64: 0 | K64: 0 | L64: 0 | M64: 0 | N64: 0 | O64: 0 | P64: 0 | Q64: 0 | R64: 0 | S64: 0 | T64: 0 | U64: 0 | V64: 0 | W64: 0 | X64: 0 | Y64: 0 | Z64: 0 | AA64: 0 | AB64: 0 | AC64: 0 | AD64: 0 | AE64: 0 | AF64: 0 | AG64: 0 | AH64: 0 | AI64: 0 | AJ64: 0 | AK64: - -
A65: TEU000:ga_Electricity | B65: Electricity | C65: Transportation Energy Use: Electricity: High oil and gas supply | D65: 45-AEO2021.56.highogs-d120120a | E65: trillion Btu | F65: 35.168571 | G65: 42.269836 | H65: 48.229595 | I65: 53.729454 | J65: 58.952888 | K65: 64.151711 | L65: 70.346672 | M65: 76.722725 | N65: 83.064751 | O65: 89.701584 | P65: 97.082611 | Q65: 104.90831 | R65: 113.70185 | S65: 123.35428 | T65: 133.98796 | U65: 145.52536 | V65: 157.87439 | W65: 170.92923 | X65: 184.78879 | Y65: 199.451 | Z65: 215.07665 | AA65: 230.8228 | AB65: 246.89191 | AC65: 263.1506 | AD65: 280.03836 | AE65: 296.74304 | AF65: 313.74149 | AG65: 330.81247 | AH65: 348.42777 | AI65: 366.78662 | AJ65: 385.29108 | AK65: 0.083
A66: TEU000:ga_CompressedNat | B66: Compressed/Liquefied Natural Gas | C66: Transportation Energy Use: Natural Gas: High oil and gas supply | D66: 45-AEO2021.57.highogs-d120120a | E66: trillion Btu | F66: 87.254913 | G66: 112.34695 | H66: 98.182472 | I66: 102.5098 | J66: 117.44493 | K66: 122.34285 | L66: 127.29278 | M66: 138.77521 | N66: 145.19153 | O66: 155.24695 | P66: 159.69446 | Q66: 164.35971 | R66: 177.78354 | S66: 187.52266 | T66: 198.24445 | U66: 203.44011 | V66: 216.74155 | W66: 227.36365 | X66: 235.34441 | Y66: 249.95869 | Z66: 263.73206 | AA66: 272.09653 | AB66: 290.60043 | AC66: 304.73328 | AD66: 320.40601 | AE66: 335.67789 | AF66: 350.99786 | AG66: 365.8024 | AH66: 379.2001 | AI66: 395.63809 | AJ66: 413.71472 | AK66: 0.053
A67: TEU000:ga_LiquidHydroge | B67: Hydrogen | C67: Transportation Energy Use: Hydrogen: High oil and gas supply | D67: 45-AEO2021.58.highogs-d120120a | E67: trillion Btu | F67: 0.277361 | G67: 0.294108 | H67: 0.298122 | I67: 0.302102 | J67: 0.305806 | K67: 0.310281 | L67: 0.315117 | M67: 0.321134 | N67: 0.32824 | O67: 0.336525 | P67: 0.346451 | Q67: 0.357042 | R67: 0.367403 | S67: 0.379223 | T67: 0.392209 | U67: 0.408699 | V67: 0.428046 | W67: 0.450503 | X67: 0.474421 | Y67: 0.500565 | Z67: 0.530612 | AA67: 0.558742 | AB67: 0.588498 | AC67: 0.640967 | AD67: 0.669637 | AE67: 0.698541 | AF67: 0.727324 | AG67: 0.755534 | AH67: 0.783753 | AI67: 0.811744 | AJ67: 0.839392 | AK67: 0.038
A68: TEU000:ga_PipelineFuelN | B68: Pipeline Fuel Natural Gas | C68: Transportation Energy Use: Pipeline Fuel Natural Gas: High oil and gas supply | D68: 45-AEO2021.59.highogs-d120120a | E68: trillion Btu | F68: 706.25012 | G68: 765.14197 | H68: 755.34998 | I68: 731.63831 | J68: 723.20685 | K68: 724.60596 | L68: 691.04956 | M68: 701.14313 | N68: 701.06634 | O68: 701.03687 | P68: 693.45966 | Q68: 694.47479 | R68: 697.11835 | S68: 697.96668 | T68: 696.89435 | U68: 700.55658 | V68: 708.85254 | W68: 718.20209 | X68: 725.97797 | Y68: 730.66339 | Z68: 734.56103 | AA68: 737.10724 | AB68: 741.27094 | AC68: 748.35034 | AD68: 759.38428 | AE68: 765.85901 | AF68: 773.89398 | AG68: 783.06421 | AH68: 778.31659 | AI68: 777.42078 | AJ68: 784.83752 | AK68: 0.004
A69: TEU000:ha_TotalConsumpt | B69: Total Consumption | C69: Transportation: Total Energy Use: High oil and gas supply | D69: 45-AEO2021.61.highogs-d120120a | E69: trillion Btu | F69: 24639.824 | G69: 26246.221 | H69: 26803.195 | I69: 27032.039 | J69: 27130.621 | K69: 27230.627 | L69: 27186.73 | M69: 27079.893 | N69: 26990.619 | O69: 26860.611 | P69: 26742.568 | Q69: 26653.377 | R69: 26566.033 | S69: 26512.381 | T69: 26489.973 | U69: 26544.994 | V69: 26577.676 | W69: 26621.715 | X69: 26686.311 | Y69: 26756.367 | Z69: 26859.408 | AA69: 26987.805 | AB69: 27108.289 | AC69: 27264.598 | AD69: 27400.816 | AE69: 27549.664 | AF69: 27685.326 | AG69: 27804.465 | AH69: 27932.266 | AI69: 28068.959 | AJ69: 28223.449 | AK69: 0.005

Sheet AEO 36
B1: ORIGINAL EIA CODE | G1: 2020 | H1: 2021 | I1: 2022 | J1: 2023 | K1: 2024 | L1: 2025 | M1: 2026 | N1: 2027 | O1: 2028 | P1: 2029 | Q1: 2030 | R1: 2031 | S1: 2032 | T1: 2033 | U1: 2034 | V1: 2035 | W1: 2036 | X1: 2037 | Y1: 2038 | Z1: 2039 | AA1: 2040 | AB1: 2041 | AC1: 2042 | AD1: 2043 | AE1: 2044 | AF1: 2045 | AG1: 2046 | AH1: 2047 | AI1: 2048 | AJ1: 2049 | AK1: 2050 | AL1: Growth (2020-2050)
B10: TEF000 | C10: Table 36. Transportation Sector Energy Use by Fuel Type Within a Mode
C11: https://www.eia.gov/outlooks/aeo/data/browser/#/?id=46-AEO2021&region=0-0&cases=highogs&start=2020&end=2050&f=A&linechart=highogs-d120120a.2-46-AEO2021&sourcekey=0
C12: Tue Mar 09 2021 10:55:36 GMT-0800 (Pacific Standard Time)
C13: Source: U.S. Energy Information Administration
D14: full name | E14: api key | F14: units | G14: 2020 | H14: 2021 | I14: 2022 | J14: 2023 | K14: 2024 | L14: 2025 | M14: 2026 | N14: 2027 | O14: 2028 | P14: 2029 | Q14: 2030 | R14: 2031 | S14: 2032 | T14: 2033 | U14: 2034 | V14: 2035 | W14: 2036 | X14: 2037 | Y14: 2038 | Z14: 2039 | AA14: 2040 | AB14: 2041 | AC14: 2042 | AD14: 2043 | AE14: 2044 | AF14: 2045 | AG14: 2046 | AH14: 2047 | AI14: 2048 | AJ14: 2049 | AK14: 2050 | AL14: Growth (2020-2050)
B15: TEF000:ba_Total | C15: Light-Duty Vehicle | D15: Transportation Energy Use: Light-Duty Vehicle: Total: High oil and gas supply | E15: 46-AEO2021.2.highogs-d120120a | F15: trillion Btu | G15: 13684.958 | H15: 14333.23 | I15: 14327.021 | J15: 14365.351 | K15: 14366.454 | L15: 14341.867 | M15: 14287.132 | N15: 14207.238 | O15: 14125.375 | P15: 14028.778 | Q15: 13931.945 | R15: 13831.037 | S15: 13740.597 | T15: 13671.221 | U15: 13614.176 | V15: 13578.902 | W15: 13555.062 | X15: 13533.011 | Y15: 13512.933 | Z15: 13507.697 | AA15: 13519.425 | AB15: 13531.686 | AC15: 13551.019 | AD15: 13573.045 | AE15: 13591.691 | AF15: 13608.698 | AG15: 13631.718 | AH15: 13650.46 | AI15: 13676.694 | AJ15: 13706.509 | AK15: 13736.444 | AL15: 0
B16: TEF000:ba_MotorGasoline | C16: Motor Gasoline excluding E85 | D16: Transportation Energy Use: Light-Duty Vehicle: Motor Gasoline: High oil and gas supply | E16: 46-AEO2021.3.highogs-d120120a | F16: trillion Btu | G16: 13581.067 | H16: 14217.864 | I16: 14204.684 | J16: 14234.458 | K16: 14228.428 | L16: 14196.801 | M16: 14134.474 | N16: 14047.195 | O16: 13957.598 | P16: 13853.153 | Q16: 13748.133 | R16: 13637.929 | S16: 13537.845 | T16: 13457.947 | U16: 13389.198 | V16: 13341.722 | W16: 13304.275 | X16: 13267.979 | Y16: 13232.908 | Z16: 13211.613 | AA16: 13206.084 | AB16: 13201.54 | AC16: 13203.803 | AD16: 13208.375 | AE16: 13209.466 | AF16: 13209.275 | AG16: 13214.956 | AH16: 13216.332 | AI16: 13224.988 | AJ16: 13236.756 | AK16: 13248.583 | AL16: -0.001
B17: TEF000:ba_Ethanol | C17: E85 | D17: Transportation Energy Use: Light-Duty Vehicle: Ethanol: High oil and gas supply | E17: 46-AEO2021.4.highogs-d120120a | F17: trillion Btu | G17: 28.416105 | H17: 30.452488 | I17: 29.12302 | J17: 30.393192 | K17: 30.446802 | L17: 30.334116 | M17: 30.097528 | N17: 29.617033 | O17: 29.162001 | P17: 28.684046 | Q17: 28.238894 | R17: 27.89463 | S17: 27.565693 | T17: 27.333168 | U17: 27.146755 | V17: 27.196278 | W17: 27.253397 | X17: 27.378733 | Y17: 27.519627 | Z17: 27.799347 | AA17: 28.120176 | AB17: 28.451086 | AC17: 28.833448 | AD17: 29.209904 | AE17: 29.608629 | AF17: 29.940838 | AG17: 30.281662 | AH17: 30.746485 | AI17: 31.104912 | AJ17: 31.619726 | AK17: 32.097847 | AL17: 0.004
B18: TEF000:ba_Distillate(di | C18: Distillate Fuel Oil (diesel) | D18: Transportation Energy Use: Light-Duty Vehicle: Distillate Fuel Oil: High oil and gas supply | E18: 46-AEO2021.5.highogs-d120120a | F18: trillion Btu | G18: 50.426529 | H18: 55.278618 | I18: 59.648018 | J18: 63.577545 | K18: 67.135139 | L18: 70.539833 | M18: 73.25473 | N18: 75.499329 | O18: 77.760559 | P18: 79.802612 | Q18: 81.587555 | R18: 83.76342 | S18: 85.430611 | T18: 87.035492 | U18: 88.688347 | V18: 89.765259 | W18: 91.44902 | X18: 92.978592 | Y18: 94.431015 | Z18: 96.027359 | AA18: 97.937485 | AB18: 99.244156 | AC18: 100.45963 | AD18: 101.86963 | AE18: 102.77992 | AF18: 103.6593 | AG18: 104.4415 | AH18: 105.12977 | AI18: 105.79958 | AJ18: 106.43681 | AK18: 106.99431 | AL18: 0.025
B19: TEF000:ba_CompressedNat | C19: Compressed/Liquefied Natural Gas | D19: Transportation Energy Use: Light-Duty Vehicle: Natural Gas: High oil and gas supply | E19: 46-AEO2021.6.highogs-d120120a | F19: trillion Btu | G19: 2.887658 | H19: 3.249438 | I19: 3.751801 | J19: 3.649184 | K19: 3.598443 | L19: 3.420532 | M19: 3.278207 | N19: 3.224597 | O19: 3.128891 | P19: 3.043377 | Q19: 2.930189 | R19: 2.84538 | S19: 2.807565 | T19: 2.752936 | U19: 2.8405 | V19: 2.815436 | W19: 2.799244 | X19: 2.788666 | Y19: 2.781472 | Z19: 2.774188 | AA19: 2.77026 | AB19: 2.767027 | AC19: 2.762215 | AD19: 2.766583 | AE19: 2.770975 | AF19: 2.797037 | AG19: 2.802228 | AH19: 2.805547 | AI19: 2.811294 | AJ19: 2.815169 | AK19: 2.817088 | AL19: -0.001
B20: TEF000:ba_LiquefiedPetr | C20: Propane | D20: Transportation Energy Use: Light-Duty Vehicle: Propane: High oil and gas supply | E20: 46-AEO2021.7.highogs-d120120a | F20: trillion Btu | G20: 2.846024 | H20: 2.942285 | I20: 2.906129 | J20: 2.776296 | K20: 2.601913 | L20: 2.458434 | M20: 2.350368 | N20: 2.277949 | O20: 2.191133 | P20: 2.122816 | Q20: 2.068783 | R20: 1.995096 | S20: 1.946926 | T20: 1.892876 | U20: 1.888577 | V20: 1.868202 | W20: 1.864922 | X20: 1.866992 | Y20: 1.880039 | Z20: 1.892009 | AA20: 1.913627 | AB20: 1.935318 | AC20: 1.952873 | AD20: 1.992234 | AE20: 2.030545 | AF20: 2.07902 | AG20: 2.117385 | AH20: 2.158455 | AI20: 2.199376 | AJ20: 2.247232 | AK20: 2.295216 | AL20: -0.007
B21: TEF000:ba_Electricity | C21: Electricity | D21: Transportation Energy Use: Light-Duty Vehicle: Electricity: High oil and gas supply | E21: 46-AEO2021.8.highogs-d120120a | F21: trillion Btu | G21: 19.048065 | H21: 23.163214 | I21: 26.624208 | J21: 30.209984 | K21: 33.955193 | L21: 38.020607 | M21: 43.378609 | N21: 49.120522 | O21: 55.223839 | P21: 61.65353 | Q21: 68.657272 | R21: 76.269974 | S21: 84.650574 | T21: 93.897057 | U21: 104.03822 | V21: 115.14317 | W21: 127.0094 | X21: 139.5842 | Y21: 152.9547 | Z21: 167.10631 | AA21: 182.0842 | AB21: 197.20474 | AC21: 212.63492 | AD21: 228.20642 | AE21: 244.3815 | AF21: 260.26431 | AG21: 276.40811 | AH21: 292.54785 | AI21: 309.022 | AJ21: 325.83713 | AK21: 342.83295 | AL21: 0.101
B22: TEF000:ba_LiquidHydroge | C22: Hydrogen | D22: Transportation Energy Use: Light-Duty Vehicle: Hydrogen: High oil and gas supply | E22: 46-AEO2021.9.highogs-d120120a | F22: trillion Btu | G22: 0.266917 | H22: 0.281279 | I22: 0.283635 | J22: 0.28641 | K22: 0.28925 | L22: 0.293185 | M22: 0.297653 | N22: 0.303392 | O22: 0.310604 | P22: 0.318999 | Q22: 0.328932 | R22: 0.33968 | S22: 0.350136 | T22: 0.362056 | U22: 0.375122 | V22: 0.391768 | W22: 0.411215 | X22: 0.433755 | Y22: 0.457773 | Z22: 0.484052 | AA22: 0.514214 | AB22: 0.542492 | AC22: 0.572403 | AD22: 0.625029 | AE22: 0.653853 | AF22: 0.68292 | AG22: 0.711874 | AH22: 0.740239 | AI22: 0.768635 | AJ22: 0.796764 | AK22: 0.824538 | AL22: 0.038
B23: TEF000:ca_CommercialLig | C23: Commercial Light Trucks | D23: Transportation Energy Use: Commercial Light Trucks: Total: High oil and gas supply | E23: 46-AEO2021.29.highogs-d120120a | F23: trillion Btu | G23: 800.46844 | H23: 824.44287 | I23: 837.03449 | J23: 842.58716 | K23: 850.85541 | L23: 861.80676 | M23: 867.01758 | N23: 868.0957 | O23: 868.55914 | P23: 867.97937 | Q23: 868.1029 | R23: 868.92139 | S23: 871.48572 | T23: 874.87817 | U23: 880.34076 | V23: 888.35675 | W23: 896.40918 | X23: 904.37647 | Y23: 912.86682 | Z23: 922.17767 | AA23: 931.78534 | AB23: 942.59998 | AC23: 953.13623 | AD23: 964.98138 | AE23: 975.74396 | AF23: 986.94171 | AG23: 999.06482 | AH23: 1008.5022 | AI23: 1019.1573 | AJ23: 1031.1726 | AK23: 1043.7616 | AL23: 0.009
B24: TEF000:clt_MotorGas | C24: Motor Gasoline excluding E85 | D24: Transportation Energy Use: Commercial Light Trucks: Motor Gasoline: High oil and gas supply | E24: 46-AEO2021.30.highogs-d120120a | F24: trillion Btu | G24: 537.63922 | H24: 549.02124 | I24: 553.43701 | J24: 552.53918 | K24: 553.84985 | L24: 558.0979 | M24: 559.31757 | N24: 558.51752 | O24: 558.05005 | P24: 557.38471 | Q24: 557.6698 | R24: 558.68781 | S24: 560.91553 | T24: 564.06213 | U24: 568.70306 | V24: 575.10583 | W24: 581.67926 | X24: 588.6919 | Y24: 596.10602 | Z24: 603.82745 | AA24: 611.60071 | AB24: 619.91455 | AC24: 628.06671 | AD24: 636.52405 | AE24: 643.84399 | AF24: 651.47339 | AG24: 659.53595 | AH24: 666.22131 | AI24: 674.02704 | AJ24: 683.00885 | AK24: 692.90338 | AL24: 0.008
B25: TEF000:clt_e85 | C25: E85 | D25: Transportation Energy Use: Commercial Light Trucks: E85: High oil and gas supply | E25: 46-AEO2021.31.highogs-d120120a | F25: trillion Btu | G25: 5.245657 | H25: 5.834772 | I25: 5.874416 | J25: 6.370223 | K25: 6.637703 | L25: 6.939426 | M25: 7.170085 | N25: 7.339712 | O25: 7.524295 | P25: 7.717445 | Q25: 7.938935 | R25: 8.216286 | S25: 8.517563 | T25: 8.859697 | U25: 9.236635 | V25: 9.723745 | W25: 10.218409 | X25: 10.745862 | Y25: 11.303436 | Z25: 11.93037 | AA25: 12.580648 | AB25: 13.270923 | AC25: 14.003905 | AD25: 14.763724 | AE25: 15.540169 | AF25: 16.319386 | AG25: 17.122738 | AH25: 18.008802 | AI25: 18.885925 | AJ25: 19.919947 | AK25: 20.988636 | AL25: 0.047
B26: TEF000:clt_Diesel | C26: Distillate Fuel Oil (diesel) | D26: Transportation Energy Use: Commercial Light Trucks: Distillate Fuel Oil: High oil and gas supply | E26: 46-AEO2021.32.highogs-d120120a | F26: trillion Btu | G26: 256.508 | H26: 268.36325 | I26: 276.36746 | J26: 282.16263 | K26: 288.6904 | L26: 294.96228 | M26: 298.63312 | N26: 300.27829 | O26: 300.96469 | P26: 300.7984 | Q26: 300.35568 | R26: 299.81741 | S26: 299.78546 | T26: 299.61514 | U26: 299.97806 | V26: 301.01364 | W26: 301.90744 | X26: 302.245 | Y26: 302.66998 | Z26: 303.53326 | AA26: 304.6131 | AB26: 306.31281 | AC26: 307.84912 | AD26: 310.35733 | AE26: 312.905 | AF26: 315.56928 | AG26: 318.69904 | AH26: 320.44229 | AI26: 322.28067 | AJ26: 324.13403 | AK26: 325.60376 | AL26: 0.008
... B29: TEF000:clt_electricity | C29: Electricity | D29: Transportation Energy Use: Commercial Light Trucks: Electricity: High oil and gas supply | E29: 46-AEO2021.35.highogs-d120120a | F29: trillion Btu | G29: 0.050417 | H29: 0.107022 | I29: 0.16552 | J29: 0.222413 | K29: 0.279699 | L29: 0.334366 | M29: 0.386959 | N29: 0.421211 | O29: 0.453864 | P29: 0.485523 | Q29: 0.516272 | R29: 0.546678 | S29: 0.57735 | T29: 0.608567 | U29: 0.641293 | V29: 0.676043 | W29: 0.710871 | X29: 0.745437 | Y29: 0.781257 | Z29: 0.818186 | AA29: 0.85662 | AB29: 0.897022 | AC29: 0.938748 | AD29: 0.982039 | AE29: 1.025013 | AF29: 1.070122 | AG29: 1.116352 | AH29: 1.162229 | AI29: 1.211357 | AJ29: 1.264043 | AK29: 1.319274 | AL29: 0.115
B30: TEF000:clt_hydrogen | C30: Hydrogen | D30: Transportation Energy Use: Commercial Light Trucks: Hydrogen: High oil and gas supply | E30: 46-AEO2021.36.highogs-d120120a | F30: trillion Btu | G30: 0 | H30: 0 | I30: 0 | J30: 0 | K30: 0 | L30: 0 | M30: 0 | N30: 0 | O30: 0 | P30: 0 | Q30: 0 | R30: 0 | S30: 0 | T30: 0 | U30: 0 | V30: 0 | W30: 0 | X30: 0 | Y30: 0 | Z30: 0 | AA30: 0 | AB30: 0 | AC30: 0 | AD30: 0 | AE30: 0 | AF30: 0 | AG30: 0 | AH30: 0 | AI30: 0 | AJ30: 0 | AK30: 0 | AL30: - -
B31: TEF000:da_Total | C31: Freight Trucks | D31: Transportation Energy Use: Freight Trucks: Total: High oil and gas supply | E31: 46-AEO2021.38.highogs-d120120a | F31: trillion Btu | G31: 5217.8579 | H31: 5322.7705 | I31: 5462.2485 | J31: 5509.6768 | K31: 5566.189 | L31: 5614.4272 | M31: 5611.2627 | N31: 5579.9858 | O31: 5546.2661 | P31: 5504.2886 | Q31: 5469.7139 | R31: 5438.3931 | S31: 5413.3027 | T31: 5386.6938 | U31: 5378.1445 | V31: 5393.2598 | W31: 5407.6289 | X31: 5423.5874 | Y31: 5448.6406 | Z31: 5481.9282 | AA31: 5512.1763 | AB31: 5555.0854 | AC31: 5607.7852 | AD31: 5675.5952 | AE31: 5732.5225 | AF31: 5793.8345 | AG31: 5843.8735 | AH31: 5892.3433 | AI31: 5949.0991 | AJ31: 6010.8965 | AK31: 6080.2002 | AL31: 0.005
B32: TEF000:da_MotorGasoline | C32: Motor Gasoline | D32: Transportation Energy Use: Freight Trucks: Motor Gasoline: High oil and gas supply | E32: 46-AEO2021.39.highogs-d120120a | F32: trillion Btu | G32: 519.87561 | H32: 529.23261 | I32: 540.16534 | J32: 540.77051 | K32: 542.62872 | L32: 544.2157 | M32: 543.74902 | N32: 544.12012 | O32: 547.58234 | P32: 552.57281 | Q32: 559.44678 | R32: 566.91583 | S32: 575.5744 | T32: 583.79224 | U32: 593.55695 | V32: 605.24219 | W32: 616.28076 | X32: 628.21258 | Y32: 641.26288 | Z32: 656.0072 | AA32: 670.15985 | AB32: 686.49145 | AC32: 704.27887 | AD32: 724.47455 | AE32: 743.81958 | AF32: 764.26392 | AG32: 783.86206 | AH32: 804.17108 | AI32: 826.5404 | AJ32: 849.91363 | AK32: 874.74042 | AL32: 0.017
B33: TEF000:da_Distillate(di | C33: Distillate Fuel Oil (diesel) | D33: Transportation Energy Use: Freight Trucks: Distillate Fuel Oil: High oil and gas supply | E33: 46-AEO2021.40.highogs-d120120a | F33: trillion Btu | G33: 4646.5361 | H33: 4739.6055 | I33: 4865.9512 | J33: 4911.9004 | K33: 4966.1875 | L33: 5012.8623 | M33: 5010.8218 | N33: 4980.105 | O33: 4943.7983 | P33: 4897.689 | Q33: 4856.916 | R33: 4818.606 | S33: 4785.043 | T33: 4750.1128 | U33: 4731.2397 | V33: 4733.5835 | W33: 4735.5938 | X33: 4738.0103 | Y33: 4748.0645 | Z33: 4764.2886 | AA33: 4777.7441 | AB33: 4801.1582 | AC33: 4832.4248 | AD33: 4875.8496 | AE33: 4908.9761 | AF33: 4944.8643 | AG33: 4969.9629 | AH33: 4992.2637 | AI33: 5020.248 | AJ33: 5051.4741 | AK33: 5087.9805 | AL33: 0.003
B34: TEF000:da_CompressedNat | C34: Compressed/Liquefied Natural Gas | D34: Transportation Energy Use: Freight Trucks: Natural Gas: High oil and gas supply | E34: 46-AEO2021.41.highogs-d120120a | F34: trillion Btu | G34: 47.95303 | H34: 49.845165 | I34: 51.532196 | J34: 51.778046 | K34: 51.581306 | L34: 51.004959 | M34: 49.846725 | N34: 48.452606 | O34: 47.096375 | P34: 45.74757 | Q34: 44.559383 | R34: 43.536999 | S34: 42.794006 | T34: 42.331425 | U34: 42.288651 | V34: 42.702831 | W34: 43.356659 | X34: 44.278358 | Y34: 45.496891 | Z34: 47.027119 | AA34: 48.86462 | AB34: 51.153294 | AC34: 53.854603 | AD34: 57.028568 | AE34: 60.461334 | AF34: 64.378845 | AG34: 68.65213 | AH34: 73.33432 | AI34: 78.528099 | AJ34: 84.369026 | AK34: 90.907669 | AL34: 0.022
B35: TEF000:da_LiquefiedPetr | C35: Propane | D35: Transportation Energy Use: Freight Trucks: Propane: High oil and gas supply | E35: 46-AEO2021.42.highogs-d120120a | F35: trillion Btu | G35: 1.628536 | H35: 1.777356 | I35: 1.945608 | J35: 2.0778 | K35: 2.206099 | L35: 2.324826 | M35: 2.417751 | N35: 2.495087 | O35: 2.573248 | P35: 2.648438 | Q35: 2.729501 | R35: 2.814783 | S35: 2.906544 | T35: 3.006199 | U35: 3.125526 | V35: 3.256397 | W35: 3.387739 | X35: 3.523169 | Y35: 3.671373 | Z35: 3.830482 | AA35: 3.991201 | AB35: 4.166406 | AC35: 4.351799 | AD35: 4.552161 | AE35: 4.748058 | AF35: 4.954965 | AG35: 5.160943 | AH35: 5.375611 | AI35: 5.610644 | AJ35: 5.854352 | AK35: 6.119965 | AL35: 0.045
B36: TEF000:ft_eeeeeeeeeee85 | C36: E85 | D36: Transportation Energy Use: Freight Trucks: E85: High oil and gas supply | E36: 46-AEO2021.43.highogs-d120120a | F36: trillion Btu | G36: 1.62769 | H36: 1.862727 | I36: 1.954987 | J36: 2.194217 | K36: 2.363616 | L36: 2.532255 | M36: 2.691204 | N36: 2.843764 | O36: 3.015896 | P36: 3.201768 | Q36: 3.400073 | R36: 3.62201 | S36: 3.849645 | T36: 4.081169 | U36: 4.32167 | V36: 4.6061 | W36: 4.882479 | X36: 5.17297 | Y36: 5.475552 | Z36: 5.813786 | AA36: 6.15594 | AB36: 6.532732 | AC36: 6.951177 | AD36: 7.400799 | AE36: 7.865906 | AF36: 8.341261 | AG36: 8.82087 | AH36: 9.388661 | AI36: 9.935701 | AJ36: 10.595716 | AK36: 11.273278 | AL36: 0.067
B37: TEF000:ft_electricity | C37: Electricity | D37: Transportation Energy Use: Freight Trucks: Electricity: High oil and gas supply | E37: 46-AEO2021.44.highogs-d120120a | F37: trillion Btu | G37: 0.104337 | H37: 0.187203 | I37: 0.284321 | J37: 0.382363 | K37: 0.482649 | L37: 0.582374 | M37: 0.674601 | N37: 0.760786 | O37: 0.846685 | P37: 0.931566 | Q37: 1.017084 | R37: 1.102792 | S37: 1.189097 | T37: 1.273934 | U37: 1.362117 | V37: 1.456227 | W37: 1.550566 | X37: 1.646846 | Y37: 1.750029 | Z37: 1.857691 | AA37: 1.967343 | AB37: 2.084979 | AC37: 2.209243 | AD37: 2.341451 | AE37: 2.471843 | AF37: 2.6085 | AG37: 2.745483 | AH37: 2.887781 | AI37: 3.041161 | AJ37: 3.203997 | AK37: 3.378948 | AL37: 0.123
B38: TEF000:ft_hydrogen | C38: Hydrogen | D38: Transportation Energy Use: Freight Trucks: Hydrogen: High oil and gas supply | E38: 46-AEO2021.45.highogs-d120120a | F38: trillion Btu | G38: 0.132792 | H38: 0.259926 | I38: 0.414272 | J38: 0.573951 | K38: 0.73886 | L38: 0.905071 | M38: 1.061502 | N38: 1.208407 | O38: 1.353147 | P38: 1.497632 | Q38: 1.645083 | R38: 1.794398 | S38: 1.946079 | T38: 2.0955 | U38: 2.249624 | V38: 2.412904 | W38: 2.577223 | X38: 2.743695 | Y38: 2.919212 | Z38: 3.103073 | AA38: 3.293179 | AB38: 3.498349 | AC38: 3.715147 | AD38: 3.94791 | AE38: 4.179563 | AF38: 4.42285 | AG38: 4.668613 | AH38: 4.922454 | AI38: 5.194296 | AJ38: 5.485666 | AK38: 5.799258 | AL38: 0.134
B39: TEF000:ea_Total | C39: Freight Rail | D39: Transportation Energy Use: Freight Rail: Total: High oil and gas supply | E39: 46-AEO2021.48.highogs-d120120a | F39: trillion Btu | G39: 432.32916 | H39: 455.80057 | I39: 457.32019 | J39: 454.81757 | K39: 451.84665 | L39: 435.03867 | M39: 437.54752 | N39: 434.49982 | O39: 437.06894 | P39: 438.99457 | Q39: 440.98004 | R39: 441.53027 | S39: 441.40082 | T39: 442.16769 | U39: 441.50205 | V39: 442.37979 | W39: 443.02426 | X39: 443.14713 | Y39: 441.33752 | Z39: 442.94101 | AA39: 441.56534 | AB39: 441.80859 | AC39: 443.27573 | AD39: 445.72418 | AE39: 443.77713 | AF39: 444.37201 | AG39: 443.88855 | AH39: 444.47339 | AI39: 444.99793 | AJ39: 445.72116 | AK39: 448.21558 | AL39: 0.001
B40: TEF000:ea_Distillate(di | C40: Distillate Fuel Oil (diesel) | D40: Transportation Energy Use: Freight Rail: Distillate Fuel Oil: High oil and gas supply | E40: 46-AEO2021.49.highogs-d120120a | F40: trillion Btu | G40: 431.86649 | H40: 455.31277 | I40: 455.853 | J40: 451.90289 | K40: 447.02918 | L40: 428.09738 | M40: 426.76123 | N40: 418.56616 | O40: 414.38458 | P40: 408.17917 | Q40: 400.68405 | R40: 392.03098 | S40: 382.96152 | T40: 374.84906 | U40: 365.70837 | V40: 358.02682 | W40: 350.32077 | X40: 342.37686 | Y40: 333.1543 | Z40: 326.69205 | AA40: 318.2041 | AB40: 311.07352 | AC40: 304.94458 | AD40: 299.59271 | AE40: 291.43927 | AF40: 285.1333 | AG40: 278.28723 | AH40: 272.25961 | AI40: 266.32596 | AJ40: 260.63748 | AK40: 256.08176 | AL40: -0.017
B41: TEF000:ea_ResidualOil | C41: Residual Fuel Oil | D41: Transportation Energy Use: Freight Rail: Residual Fuel Oil: High oil and gas supply | E41: 46-AEO2021.50.highogs-d120120a | F41: trillion Btu | G41: 0 | H41: 0 | I41: 0 | J41: 0 | K41: 0 | L41: 0 | M41: 0 | N41: 0 | O41: 0 | P41: 0 | Q41: 0 | R41: 0 | S41: 0 | T41: 0 | U41: 0 | V41: 0 | W41: 0 | X41: 0 | Y41: 0 | Z41: 0 | AA41: 0 | AB41: 0 | AC41: 0 | AD41: 0 | AE41: 0 | AF41: 0 | AG41: 0 | AH41: 0 | AI41: 0 | AJ41: 0 | AK41: 0 | AL41: - -
B42: TEF000:ea_SeeEnGee | C42: Compressed Natural Gas | D42: Transportation Energy Use: Freight Rail: CNG: High oil and gas supply | E42: 46-AEO2021.51.highogs-d120120a | F42: trillion Btu | G42: 0 | H42: 0 | I42: 0 | J42: 0 | K42: 0 | L42: 0 | M42: 0 | N42: 0 | O42: 0 | P42: 0 | Q42: 0 | R42: 0 | S42: 0 | T42: 0 | U42: 0 | V42: 0 | W42: 0 | X42: 0 | Y42: 0 | Z42: 0 | AA42: 0 | AB42: 0 | AC42: 0 | AD42: 0 | AE42: 0 | AF42: 0 | AG42: 0 | AH42: 0 | AI42: 0 | AJ42: 0 | AK42: 0 | AL42: - -
B43: TEF000:ea_LiquidNG | C43: Liquefied Natural Gas | D43: Transportation Energy Use: Freight Rail: LNG: High oil and gas supply | E43: 46-AEO2021.52.highogs-d120120a | F43: trillion Btu | G43: 0.462669 | H43: 0.487787 | I43: 1.467193 | J43: 2.914684 | K43: 4.817473 | L43: 6.941292 | M43: 10.786287 | N43: 15.933652 | O43: 22.684351 | P43: 30.815409 | Q43: 40.295998 | R43: 49.49931 | S43: 58.439316 | T43: 67.318634 | U43: 75.793678 | V43: 84.352966 | W43: 92.703484 | X43: 100.77026 | Y43: 108.18321 | Z43: 116.24895 | AA43: 123.36124 | AB43: 130.73509 | AC43: 138.33115 | AD43: 146.13145 | AE43: 152.33786 | AF43: 159.23871 | AG43: 165.60132 | AH43: 172.21379 | AI43: 178.67195 | AJ43: 185.08368 | AK43: 192.1338 | AL43: 0.223
B44: TEF000:fa_Total | C44: Domestic Shipping | D44: Transportation Energy Use: Domestic Shipping: Total: High oil and gas supply | E44: 46-AEO2021.54.highogs-d120120a | F44: trillion Btu | G44: 77.343407 | H44: 79.141403 | I44: 78.228264 | J44: 77.350044 | K44: 76.446533 | L44: 75.055573 | M44: 73.204681 | N44: 71.058418 | O44: 68.994972 | P44: 66.833633 | Q44: 64.753128 | R44: 63.638058 | S44: 62.605038 | T44: 61.510983 | U44: 60.561947 | V44: 59.665359 | W44: 58.721436 | X44: 57.711258 | Y44: 56.658974 | Z44: 55.745102 | AA44: 54.692238 | AB44: 54.265388 | AC44: 53.873783 | AD44: 53.634262 | AE44: 53.239914 | AF44: 52.87286 | AG44: 52.373196 | AH44: 51.890907 | AI44: 51.370388 | AJ44: 50.910122 | AK44: 50.533489 | AL44: -0.014
B45: TEF000:fa_Distillate(di | C45: Distillate Fuel Oil (diesel) | D45: Transportation Energy Use: Domestic Shipping: Distillate Fuel Oil: High oil and gas supply | E45: 46-AEO2021.55.highogs-d120120a | F45: trillion Btu | G45: 75.191635 | H45: 76.9589 | I45: 76.098526 | J45: 75.27037 | K45: 74.415176 | L45: 73.084763 | M45: 71.302963 | N45: 69.233093 | O45: 67.242203 | P45: 65.154495 | Q45: 63.145538 | R45: 62.077965 | S45: 61.089279 | T45: 60.040741 | U45: 59.13266 | V45: 58.274765 | W45: 57.367573 | X45: 56.396614 | Y45: 55.386253 | Z45: 54.511925 | AA45: 53.470909 | AB45: 52.990334 | AC45: 52.540813 | AD45: 52.235802 | AE45: 51.775986 | AF45: 51.33868 | AG45: 50.768425 | AH45: 50.210804 | AI45: 49.611866 | AJ45: 49.066448 | AK45: 48.596413 | AL45: -0.014
B46: TEF000:fa_ResidualOil | C46: Residual Oil | D46: Transportation Energy Use: Domestic Shipping: Residual Oil: High oil and gas supply | E46: 46-AEO2021.56.highogs-d120120a | F46: trillion Btu | G46: 1.746317 | H46: 1.71775 | I46: 1.622441 | J46: 1.531608 | K46: 1.445822 | L46: 1.353535 | M46: 1.262882 | N46: 1.167545 | O46: 1.07799 | P46: 0.990745 | Q46: 0.904859 | R46: 0.832536 | S46: 0.764581 | T46: 0.696267 | U46: 0.632926 | V46: 0.573231 | W46: 0.52168 | X46: 0.466675 | Y46: 0.406197 | Z46: 0.344452 | AA46: 0.289381 | AB46: 0.287048 | AC46: 0.284915 | AD46: 0.283605 | AE46: 0.281473 | AF46: 0.279448 | AG46: 0.276774 | AH46: 0.274219 | AI46: 0.271421 | AJ46: 0.268957 | AK46: 0.266958 | AL46: -0.061
B47: TEF000:fa_MotorGasoline | C47: Compressed Natural Gas | D47: Transportation Energy Use: Domestic Shipping: CNG: High oil and gas supply | E47: 46-AEO2021.57.highogs-d120120a | F47: trillion Btu | G47: 0 | H47: 0 | I47: 0 | J47: 0 | K47: 0 | L47: 0 | M47: 0 | N47: 0 | O47: 0 | P47: 0 | Q47: 0 | R47: 0 | S47: 0 | T47: 0 | U47: 0 | V47: 0 | W47: 0 | X47: 0 | Y47: 0 | Z47: 0 | AA47: 0 | AB47: 0 | AC47: 0 | AD47: 0 | AE47: 0 | AF47: 0 | AG47: 0 | AH47: 0 | AI47: 0 | AJ47: 0 | AK47: 0 | AL47: - -
B48: TEF000:fa_LiquidNG | C48: Liquefied Natural Gas | D48: Transportation Energy Use: Domestic Shipping: LNG: High oil and gas supply | E48: 46-AEO2021.58.highogs-d120120a | F48: trillion Btu | G48: 0.405453 | H48: 0.464749 | I48: 0.507295 | J48: 0.548069 | K48: 0.585534 | L48: 0.617282 | M48: 0.638841 | N48: 0.657785 | O48: 0.67478 | P48: 0.688391 | Q48: 0.702725 | R48: 0.727558 | S48: 0.75118 | T48: 0.773974 | U48: 0.796361 | V48: 0.817364 | W48: 0.832182 | X48: 0.847969 | Y48: 0.866524 | Z48: 0.888724 | AA48: 0.931948 | AB48: 0.988005 | AC48: 1.048056 | AD48: 1.114857 | AE48: 1.182455 | AF48: 1.254731 | AG48: 1.327997 | AH48: 1.405883 | AI48: 1.487103 | AJ48: 1.574717 | AK48: 1.67012 | AL48: 0.048
B49: TEF000:ga_Total | C49: International Shipping | D49: Transportation Energy Use: International Shipping: Total: High oil and gas supply | E49: 46-AEO2021.60.highogs-d120120a | F49: trillion Btu | G49: 855.88696 | H49: 881.46478 | I49: 973.99793 | J49: 992.19336 | K49: 941.40234 | L49: 944.55212 | M49: 956.48108 | N49: 933.81226 | O49: 934.80481 | P49: 926.79559 | Q49: 929.26013 | R49: 946.32806 | S49: 931.56586 | T49: 932.01617 | U49: 929.67706 | V49: 944.40857 | W49: 930.07336 | X49: 929.56103 | Y49: 939.66065 | Z49: 926.16309 | AA49: 924.4292 | AB49: 937.03516 | AC49: 921.13324 | AD49: 920.33997 | AE49: 913.82855 | AF49: 914.23267 | AG49: 910.46515 | AH49: 908.20612 | AI49: 908.68933 | AJ49: 907.3324 | AK49: 904.8645 | AL49: 0.002
B50: TEF000:ga_Distillate(di | C50: Distillate Fuel Oil (diesel) | D50: Transportation Energy Use: International Shipping: Distillate Fuel Oil: High oil and gas supply | E50: 46-AEO2021.61.highogs-d120120a | F50: trillion Btu | G50: 425.03616 | H50: 370.24561 | I50: 252.65312 | J50: 226.24582 | K50: 293.44659 | L50: 287.95435 | M50: 269.74573 | N50: 298.33557 | O50: 297.11917 | P50: 307.34467 | Q50: 308.88791 | R50: 287.65436 | S50: 306.24054 | T50: 305.51929 | U50: 308.33096 | V50: 291.13928 | W50: 309.98889 | X50: 310.40753 | Y50: 296.98941 | Z50: 313.76462 | AA50: 312.9325 | AB50: 296.40906 | AC50: 313.6619 | AD50: 313.04077 | AE50: 318.13922 | AF50: 314.39709 | AG50: 316.72891 | AH50: 317.82919 | AI50: 316.5968 | AJ50: 315.79706 | AK50: 316.30054 | AL50: -0.01
B51: TEF000:ga_ResidualOil | C51: Residual Oil | D51: Transportation Energy Use: International Shipping: Residual Oil: High oil and gas supply | E51: 46-AEO2021.62.highogs-d120120a | F51: trillion Btu | G51: 413.53491 | H51: 474.50049 | I51: 704.24414 | J51: 747.77252 | K51: 617.69501 | L51: 623.54443 | M51: 651.77942 | N51: 593.12518 | O51: 594.11493 | P51: 572.40936 | Q51: 577.09656 | R51: 618.646 | S51: 579.94849 | T51: 579.6532 | U51: 572.24396 | V51: 607.74536 | W51: 570.14923 | X51: 567.50324 | Y51: 591.57428 | Z51: 556.1377 | AA51: 550.32709 | AB51: 580.63721 | AC51: 539.14996 | AD51: 535.7085 | AE51: 517.95917 | AF51: 517.56464 | AG51: 506.65537 | AH51: 499.68573 | AI51: 499.52988 | AJ51: 494.73404 | AK51: 487.25003 | AL51: 0.005
B52: TEF000:ga_SeeEnGee | C52: Compressed Natural Gas | D52: Transportation Energy Use: International Shipping: CNG: High oil and gas supply | E52: 46-AEO2021.63.highogs-d120120a | F52: trillion Btu | G52: 0 | H52: 0 | I52: 0 | J52: 0 | K52: 0 | L52: 0 | M52: 0 | N52: 0 | O52: 0 | P52: 0 | Q52: 0 | R52: 0 | S52: 0 | T52: 0 | U52: 0 | V52: 0 | W52: 0 | X52: 0 | Y52: 0 | Z52: 0 | AA52: 0 | AB52: 0 | AC52: 0 | AD52: 0 | AE52: 0 | AF52: 0 | AG52: 0 | AH52: 0 | AI52: 0 | AJ52: 0 | AK52: 0 | AL52: - -
B53: TEF000:ga_LiquidNG | C53: Liquefied Natural Gas | D53: Transportation Energy Use: International Shipping: LNG: High oil and gas supply | E53: 46-AEO2021.64.highogs-d120120a | F53: trillion Btu | G53: 17.315903 | H53: 36.718674 | I53: 17.100639 | J53: 18.175018 | K53: 30.260731 | L53: 33.053322 | M53: 34.95594 | N53: 42.351486 | O53: 43.570652 | P53: 47.041565 | Q53: 43.27565 | R53: 40.027729 | S53: 45.376812 | T53: 46.843704 | U53: 49.102119 | V53: 45.52393 | W53: 49.935234 | X53: 51.650299 | Y53: 51.096954 | Z53: 56.260712 | AA53: 61.169594 | AB53: 59.98888 | AC53: 68.321358 | AD53: 71.590668 | AE53: 77.730148 | AF53: 82.270935 | AG53: 87.080887 | AH53: 90.6912 | AI53: 92.562622 | AJ53: 96.8013 | AK53: 101.314 | AL53: 0.061
B54: TEF000:ha_Total | C54: Air Transportation | D54: Transportation Energy Use: Air: Total: High oil and gas supply | E54: 46-AEO2021.66.highogs-d120120a | F54: trillion Btu | G54: 1860.4852 | H54: 2530.9844 | I54: 2826.3455 | J54: 2963.3054 | K54: 3051.7676 | L54: 3120.2192 | M54: 3144.2417 | N54: 3161.6292 | O54: 3182.792 | P54: 3201.8508 | Q54: 3222.4722 | R54: 3248.707 | S54: 3287.2993 | T54: 3325.2964 | U54: 3367.7898 | V54: 3416.8147 | W54: 3457.4729 | X54: 3492.2021 | Y54: 3528.9045 | Z54: 3570.2959 | AA54: 3622.022 | AB54: 3669.8467 | AC54: 3718.9998 | AD54: 3765.7593 | AE54: 3814.1924 | AF54: 3866.814 | AG54: 3914.7517 | AH54: 3951.3643 | AI54: 3990.626 | AJ54: 4026.4131 | AK54: 4062.8081 | AL54: 0.026
B55: TEF000:ha_JetFuel | C55: Jet Fuel | D55: Transportation Energy Use: Air: Jet Fuel: High oil and gas supply | E55: 46-AEO2021.67.highogs-d120120a | F55: trillion Btu | G55: 1838.0343 | H55: 2508.5496 | I55: 2803.9238 | J55: 2940.8948 | K55: 3029.366 | L55: 3097.8252 | M55: 3121.854 | N55: 3139.2466 | O55: 3160.4136 | P55: 3179.4758 | Q55: 3200.1001 | R55: 3226.3374 | S55: 3264.9316 | T55: 3302.9304 | U55: 3345.4253 | V55: 3394.4512 | W55: 3435.1104 | X55: 3469.8403 | Y55: 3506.5435 | Z55: 3547.9353 | AA55: 3599.6619 | AB55: 3647.4871 | AC55: 3696.6404 | AD55: 3743.4001 | AE55: 3791.8335 | AF55: 3844.4551 | AG55: 3892.3931 | AH55: 3929.0056 | AI55: 3968.2676 | AJ55: 4004.0547 | AK55: 4040.4497 | AL55: 0.027
B56: TEF000:ha_AviationGasol | C56: Aviation Gasoline | D56: Transportation Energy Use: Air: Aviation Gasoline: High oil and gas supply | E56: 46-AEO2021.68.highogs-d120120a | F56: trillion Btu | G56: 22.450933 | H56: 22.434891 | I56: 22.421618 | J56: 22.410635 | K56: 22.401548 | L56: 22.394032 | M56: 22.387812 | N56: 22.382666 | O56: 22.378407 | P56: 22.374884 | Q56: 22.371969 | R56: 22.369558 | S56: 22.367563 | T56: 22.365911 | U56: 22.364546 | V56: 22.363417 | W56: 22.36248 | X56: 22.361708 | Y56: 22.361067 | Z56: 22.360538 | AA56: 22.3601 | AB56: 22.359737 | AC56: 22.359438 | AD56: 22.35919 | AE56: 22.358984 | AF56: 22.358814 | AG56: 22.358673 | AH56: 22.358557 | AI56: 22.358461 | AJ56: 22.358381 | AK56: 22.358315 | AL56: 0
B57: TEF000:ia_Total | C57: Military Use | D57: Transportation Energy Use: Military: Total: High oil and gas supply | E57: 46-AEO2021.70.highogs-d120120a | F57: trillion Btu | G57: 535.96637 | H57: 545.01123 | I57: 545.74866 | J57: 532.56958 | K57: 523.88 | L57: 523.35651 | M57: 522.09973 | N57: 521.93036 | O57: 524.8078 | P57: 523.65002 | Q57: 521.6662 | R57: 521.5852 | S57: 522.42029 | T57: 523.2868 | U57: 524.16394 | V57: 525.04242 | W57: 525.95764 | X57: 526.90601 | Y57: 527.86682 | Z57: 528.83173 | AA57: 529.80688 | AB57: 530.79144 | AC57: 531.77478 | AD57: 532.76556 | AE57: 533.75751 | AF57: 534.75317 | AG57: 535.74884 | AH57: 536.74451 | AI57: 537.74036 | AJ57: 538.73468 | AK57: 539.72705 | AL57: 0
B58: TEF000:ia_JetFuel | C58: Jet Fuel and Aviation Gasoline | D58: Transportation Energy Use: Military: Jet Fuel: High oil and gas supply | E58: 46-AEO2021.71.highogs-d120120a | F58: trillion Btu | G58: 401.72967 | H58: 408.50488 | I58: 409.04373 | J58: 399.1633 | K58: 392.65555 | L58: 392.26257 | M58: 391.31888 | N58: 391.19495 | O58: 393.35147 | P58: 392.48471 | Q58: 390.99704 | R58: 390.9339 | S58: 391.56195 | T58: 392.2113 | U58: 392.86896 | V58: 393.52496 | W58: 394.21295 | X58: 394.92361 | Y58: 395.64215 | Z58: 396.36755 | AA58: 397.09851 | AB58: 397.83429 | AC58: 398.57382 | AD58: 399.31635 | AE58: 400.06104 | AF58: 400.80716 | AG58: 401.55408 | AH58: 402.30093 | AI58: 403.04748 | AJ58: 403.7933 | AK58: 404.53796 | AL58: 0
B59: TEF000:ia_ResidualFuel | C59: Residual Fuel Oil | D59: Transportation Energy Use: Military: Residual Fuel Oil: High oil and gas supply | E59: 46-AEO2021.72.highogs-d120120a | F59: trillion Btu | G59: 19.229748 | H59: 19.559748 | I59: 19.604057 | J59: 19.134007 | K59: 18.815207 | L59: 18.797192 | M59: 18.754284 | N59: 18.744331 | O59: 18.847855 | P59: 18.804949 | Q59: 18.734697 | R59: 18.734974 | S59: 18.762163 | T59: 18.793428 | U59: 18.824688 | V59: 18.859322 | W59: 18.889589 | X59: 18.923862 | Y59: 18.960432 | Z59: 18.992315 | AA59: 19.027205 | AB59: 19.065367 | AC59: 19.097477 | AD59: 19.133114 | AE59: 19.167227 | AF59: 19.203192 | AG59: 19.238092 | AH59: 19.273088 | AI59: 19.308661 | AJ59: 19.343632 | AK59: 19.378197 | AL59: 0
B60: TEF000:ia_Distillate | C60: Distillates and Diesel | D60: Transportation Energy Use: Military: Distillate Fuel Oil: High oil and gas supply | E60: 46-AEO2021.73.highogs-d120120a | F60: trillion Btu | G60: 115.00696 | H60: 116.94656 | I60: 117.10083 | J60: 114.27228 | K60: 112.40923 | L60: 112.29674 | M60: 112.02658 | N60: 111.99109 | O60: 112.60847 | P60: 112.36034 | Q60: 111.93445 | R60: 111.91635 | S60: 112.09616 | T60: 112.28206 | U60: 112.47034 | V60: 112.65813 | W60: 112.85508 | X60: 113.05853 | Y60: 113.26424 | Z60: 113.47189 | AA60: 113.68117 | AB60: 113.89179 | AC60: 114.10351 | AD60: 114.31609 | AE60: 114.52926 | AF60: 114.74286 | AG60: 114.95668 | AH60: 115.1705 | AI60: 115.38422 | AJ60: 115.59773 | AK60: 115.81091 | AL60: 0
B61: TEF000:ja_Total | C61: Bus Transportation | D61: Transportation Energy Use: Bus: High oil and gas supply | E61: 46-AEO2021.75.highogs-d120120a | F61: trillion Btu | G61: 123.24042 | H61: 154.78178 | I61: 177.56615 | J61: 194.20656 | K61: 206.4372 | L61: 215.22548 | M61: 221.68236 | N61: 226.56303 | O61: 228.95393 | P61: 230.64899 | Q61: 232.39394 | R61: 232.85582 | S61: 233.45077 | T61: 233.69122 | U61: 233.81995 | V61: 233.33958 | W61: 233.03294 | X61: 232.7027 | Y61: 232.2153 | Z61: 231.47563 | AA61: 230.83417 | AB61: 229.97171 | AC61: 229.01445 | AD61: 228.01459 | AE61: 226.97612 | AF61: 225.87607 | AG61: 224.61758 | AH61: 223.33368 | AI61: 221.78813 | AJ61: 220.1658 | AK61: 218.66513 | AL61: 0.019
B62: TEF000:bus_transit_tot | C62: Transit Bus | D62: Transportation Energy Use: Bus: Transit Bus: High oil and gas supply | E62: 46-AEO2021.76.highogs-d120120a | F62: trillion Btu | G62: 65.868385 | H62: 77.343925 | I62: 85.037193 | J62: 90.397377 | K62: 94.148392 | L62: 96.454201 | M62: 98.028534 | N62: 99.228485 | O62: 98.787506 | P62: 98.326218 | Q62: 98.456612 | R62: 97.730179 | S62: 97.429573 | T62: 97.078491 | U62: 96.865768 | V62: 96.19072 | W62: 95.827606 | X62: 95.546768 | Y62: 95.188217 | Z62: 94.635986 | AA62: 94.23497 | AB62: 93.65612 | AC62: 93.025208 | AD62: 92.393784 | AE62: 91.770996 | AF62: 91.134651 | AG62: 90.408363 | AH62: 89.765427 | AI62: 89.013596 | AJ62: 88.517876 | AK62: 88.092033 | AL62: 0.01
B63: TEF000:ja_TransitBus(mo | C63: Motor Gasoline | D63: Transportation Energy Use: Bus: Transit Bus: Motor Gasoline: High oil and gas supply | E63: 46-AEO2021.77.highogs-d120120a | F63: trillion Btu | G63: 8.213901 | H63: 9.676515 | I63: 10.66667 | J63: 11.35914 | K63: 11.848991 | L63: 12.157253 | M63: 12.373383 | N63: 12.542023 | O63: 12.501125 | P63: 12.457867 | Q63: 12.492733 | R63: 12.41523 | S63: 12.393853 | T63: 12.36493 | U63: 12.354593 | V63: 12.283155 | W63: 12.252656 | X63: 12.232264 | Y63: 12.202119 | Z63: 12.146736 | AA63: 12.111721 | AB63: 12.053454 | AC63: 11.987915 | AD63: 11.922503 | AE63: 11.858107 | AF63: 11.792482 | AG63: 11.713984 | AH63: 11.64586 | AI63: 11.563481 | AJ63: 11.514956 | AK63: 11.47515 | AL63: 0.011
B64: TEF000:bus_transit_e85 | C64: E85 | D64: Transportation Energy Use: Bus: Transit Bus: E85: High oil and gas supply | E64: 46-AEO2021.78.highogs-d120120a | F64: trillion Btu | G64: 0.004299 | H64: 0.004905 | I64: 0.005263 | J64: 0.005506 | K64: 0.005669 | L64: 0.005761 | M64: 0.005821 | N64: 0.005863 | O64: 0.005823 | P64: 0.00578 | Q64: 0.005764 | R64: 0.005706 | S64: 0.005665 | T64: 0.005623 | U64: 0.005586 | V64: 0.005525 | W64: 0.005482 | X64: 0.005445 | Y64: 0.005403 | Z64: 0.005349 | AA64: 0.005297 | AB64: 0.005237 | AC64: 0.005177 | AD64: 0.005117 | AE64: 0.005058 | AF64: 0.004994 | AG64: 0.00493 | AH64: 0.004871 | AI64: 0.004805 | AJ64: 0.004751 | AK64: 0.004702 | AL64: 0.003
... B70: TEF000:bus_inter_total | C70: Intercity Bus | D70: Transportation Energy Use: Bus: Intercity Bus: High oil and gas supply | E70: 46-AEO2021.84.highogs-d120120a | F70: trillion Btu | G70: 21.389296 | H70: 24.819853 | I70: 27.510082 | J70: 29.622658 | K70: 31.287823 | L70: 32.605827 | M70: 33.663296 | N70: 34.520813 | O70: 35.224197 | P70: 35.81303 | Q70: 36.317593 | R70: 36.759636 | S70: 37.152344 | T70: 37.510296 | U70: 37.844872 | V70: 38.157986 | W70: 38.449917 | X70: 38.72361 | Y70: 38.985104 | Z70: 39.238808 | AA70: 39.486942 | AB70: 39.72662 | AC70: 39.958668 | AD70: 40.184944 | AE70: 40.404293 | AF70: 40.622166 | AG70: 40.834713 | AH70: 41.040451 | AI70: 41.248081 | AJ70: 41.453495 | AK70: 41.657665 | AL70: 0.022
B71: TEF000:bus_inter_motor | C71: Motor Gasoline | D71: Transportation Energy Use: Bus: Intercity Bus: Motor Gasoline: High oil and gas supply | E71: 46-AEO2021.85.highogs-d120120a | F71: trillion Btu | G71: 0 | H71: 0 | I71: 0 | J71: 0 | K71: 0 | L71: 0 | M71: 0 | N71: 0 | O71: 0 | P71: 0 | Q71: 0 | R71: 0 | S71: 0 | T71: 0 | U71: 0 | V71: 0 | W71: 0 | X71: 0 | Y71: 0 | Z71: 0 | AA71: 0 | AB71: 0 | AC71: 0 | AD71: 0 | AE71: 0 | AF71: 0 | AG71: 0 | AH71: 0 | AI71: 0 | AJ71: 0 | AK71: 0 | AL71: - -
B72: TEF000:bus_inter_e85 | C72: E85 | D72: Transportation Energy Use: Bus: Intercity Bus: E85: High oil and gas supply | E72: 46-AEO2021.86.highogs-d120120a | F72: trillion Btu | G72: 0 | H72: 0 | I72: 0 | J72: 0 | K72: 0 | L72: 0 | M72: 0 | N72: 0 | O72: 0 | P72: 0 | Q72: 0 | R72: 0 | S72: 0 | T72: 0 | U72: 0 | V72: 0 | W72: 0 | X72: 0 | Y72: 0 | Z72: 0 | AA72: 0 | AB72: 0 | AC72: 0 | AD72: 0 | AE72: 0 | AF72: 0 | AG72: 0 | AH72: 0 | AI72: 0 | AJ72: 0 | AK72: 0 | AL72: - -
B73: TEF000:ja_IntercityBus( | C73: Distillate Fuel Oil (diesel) | D73: Transportation Energy Use: Bus: Intercity Bus: Distillate Fuel Oil: High oil and gas supply | E73: 46-AEO2021.87.highogs-d120120a | F73: trillion Btu | G73: 21.389296 | H73: 24.819853 | I73: 27.510082 | J73: 29.622658 | K73: 31.287823 | L73: 32.605827 | M73: 33.663296 | N73: 34.520813 | O73: 35.224197 | P73: 35.81303 | Q73: 36.317593 | R73: 36.759636 | S73: 37.152344 | T73: 37.510296 | U73: 37.844872 | V73: 38.157986 | W73: 38.449917 | X73: 38.72361 | Y73: 38.985104 | Z73: 39.238808 | AA73: 39.486942 | AB73: 39.72662 | AC73: 39.958668 | AD73: 40.184944 | AE73: 40.404293 | AF73: 40.622166 | AG73: 40.834713 | AH73: 41.040451 | AI73: 41.248081 | AJ73: 41.453495 | AK73: 41.657665 | AL73: 0.022
B74: TEF000:bus_inter_CNG | C74: Compressed/Liquefied Natural Gas | D74: Transportation Energy Use: Bus: Intercity Bus: Natural Gas: High oil and gas supply | E74: 46-AEO2021.88.highogs-d120120a | F74: trillion Btu | G74: 0 | H74: 0 | I74: 0 | J74: 0 | K74: 0 | L74: 0 | M74: 0 | N74: 0 | O74: 0 | P74: 0 | Q74: 0 | R74: 0 | S74: 0 | T74: 0 | U74: 0 | V74: 0 | W74: 0 | X74: 0 | Y74: 0 | Z74: 0 | AA74: 0 | AB74: 0 | AC74: 0 | AD74: 0 | AE74: 0 | AF74: 0 | AG74: 0 | AH74: 0 | AI74: 0 | AJ74: 0 | AK74: 0 | AL74: - -
B75: TEF000:bus_inter_LPG | C75: Propane | D75: Transportation Energy Use: Bus: Intercity Bus: Propane: High oil and gas supply | E75: 46-AEO2021.89.highogs-d120120a | F75: trillion Btu | G75: 0 | H75: 0 | I75: 0 | J75: 0 | K75: 0 | L75: 0 | M75: 0 | N75: 0 | O75: 0 | P75: 0 | Q75: 0 | R75: 0 | S75: 0 | T75: 0 | U75: 0 | V75: 0 | W75: 0 | X75: 0 | Y75: 0 | Z75: 0 | AA75: 0 | AB75: 0 | AC75: 0 | AD75: 0 | AE75: 0 | AF75: 0 | AG75: 0 | AH75: 0 | AI75: 0 | AJ75: 0 | AK75: 0 | AL75: - -
B76: TEF000:bus_inter_elec | C76: Electricity | D76: Transportation Energy Use: Bus: Intercity Bus: Electricity: High oil and gas supply | E76: 46-AEO2021.90.highogs-d120120a | F76: trillion Btu | G76: 0 | H76: 0 | I76: 0 | J76: 0 | K76: 0 | L76: 0 | M76: 0 | N76: 0 | O76: 0 | P76: 0 | Q76: 0 | R76: 0 | S76: 0 | T76: 0 | U76: 0 | V76: 0 | W76: 0 | X76: 0 | Y76: 0 | Z76: 0 | AA76: 0 | AB76: 0 | AC76: 0 | AD76: 0 | AE76: 0 | AF76: 0 | AG76: 0 | AH76: 0 | AI76: 0 | AJ76: 0 | AK76: 0 | AL76: - -
B77: TEF000:bus_inter_hydrog | C77: Hydrogen | D77: Transportation Energy Use: Bus: Intercity Bus: Hydrogen: High oil and gas supply | E77: 46-AEO2021.91.highogs-d120120a | F77: trillion Btu | G77: 0 | H77: 0 | I77: 0 | J77: 0 | K77: 0 | L77: 0 | M77: 0 | N77: 0 | O77: 0 | P77: 0 | Q77: 0 | R77: 0 | S77: 0 | T77: 0 | U77: 0 | V77: 0 | W77: 0 | X77: 0 | Y77: 0 | Z77: 0 | AA77: 0 | AB77: 0 | AC77: 0 | AD77: 0 | AE77: 0 | AF77: 0 | AG77: 0 | AH77: 0 | AI77: 0 | AJ77: 0 | AK77: 0 | AL77: - -
B78: TEF000:bus_school_total | C78: School Bus | D78: Transportation Energy Use: Bus: School Bus: High oil and gas supply | E78: 46-AEO2021.92.highogs-d120120a | F78: trillion Btu | G78: 36.342903 | H78: 53.065319 | I78: 65.539474 | J78: 74.77401 | K78: 81.650841 | L78: 86.872803 | M78: 90.754913 | N78: 93.637444 | O78: 95.815033 | P78: 97.436134 | Q78: 98.610291 | R78: 99.419357 | S78: 99.995285 | T78: 100.30936 | U78: 100.40678 | V78: 100.38309 | W78: 100.25748 | X78: 100.05856 | Y78: 99.805702 | Z78: 99.51545 | AA78: 99.200005 | AB78: 98.869118 | AC78: 98.529976 | AD78: 98.188255 | AE78: 97.849648 | AF78: 97.519051 | AG78: 97.198906 | AH78: 96.890816 | AI78: 96.596497 | AJ78: 96.315292 | AK78: 96.04538 | AL78: 0.033
B79: TEF000:ja_SchoolBus(mot | C79: Motor Gasoline | D79: Transportation Energy Use: Bus: School Bus: Motor Gasoline: High oil and gas supply | E79: 46-AEO2021.93.highogs-d120120a | F79: trillion Btu | G79: 4.033629 | H79: 5.889618 | I79: 7.274102 | J79: 8.299025 | K79: 9.062271 | L79: 9.641848 | M79: 10.072715 | N79: 10.392642 | O79: 10.634327 | P79: 10.814251 | Q79: 10.944569 | R79: 11.034365 | S79: 11.098286 | T79: 11.133143 | U79: 11.143956 | V79: 11.141327 | W79: 11.127387 | X79: 11.105309 | Y79: 11.077244 | Z79: 11.045029 | AA79: 11.01002 | AB79: 10.973294 | AC79: 10.935654 | AD79: 10.897727 | AE79: 10.860145 | AF79: 10.823454 | AG79: 10.787921 | AH79: 10.753726 | AI79: 10.72106 | AJ79: 10.689853 | AK79: 10.659893 | AL79: 0.033
B80: TEF000:bus_school_e85 | C80: E85 | D80: Transportation Energy Use: Bus: School Bus: E85: High oil and gas supply | E80: 46-AEO2021.94.highogs-d120120a | F80: trillion Btu | G80: 0 | H80: 0 | I80: 0 | J80: 0 | K80: 0 | L80: 0 | M80: 0 | N80: 0 | O80: 0 | P80: 0 | Q80: 0 | R80: 0 | S80: 0 | T80: 0 | U80: 0 | V80: 0 | W80: 0 | X80: 0 | Y80: 0 | Z80: 0 | AA80: 0 | AB80: 0 | AC80: 0 | AD80: 0 | AE80: 0 | AF80: 0 | AG80: 0 | AH80: 0 | AI80: 0 | AJ80: 0 | AK80: 0 | AL80: - -
B81: TEF000:ja_SchoolBus(die | C81: Distillate Fuel Oil (diesel) | D81: Transportation Energy Use: Bus: School Bus: Distillate Fuel Oil: High oil and gas supply | E81: 46-AEO2021.95.highogs-d120120a | F81: trillion Btu | G81: 31.980074 | H81: 46.693012 | I81: 57.664856 | J81: 65.781433 | K81: 71.820145 | L81: 76.401764 | M81: 79.802284 | N81: 82.321213 | O81: 84.219391 | P81: 85.626839 | Q81: 86.642899 | R81: 87.337814 | S81: 87.82769 | T81: 88.086739 | U81: 88.154968 | V81: 88.116951 | W81: 87.989807 | X81: 87.797562 | Y81: 87.557152 | Z81: 87.284401 | AA81: 86.988213 | AB81: 86.67804 | AC81: 86.360336 | AD81: 86.039955 | AE81: 85.72171 | AF81: 85.40979 | AG81: 85.106483 | AH81: 84.8134 | AI81: 84.531967 | AJ81: 84.261406 | AK81: 84.000237 | AL81: 0.033
B82: TEF000:bus_school_CNG | C82: Compressed/Liquefied Natural Gas | D82: Transportation Energy Use: Bus: School Bus: Natural Gas: High oil and gas supply | E82: 46-AEO2021.96.highogs-d120120a | F82: trillion Btu | G82: 0.298074 | H82: 0.437235 | I82: 0.544377 | J82: 0.6295 | K82: 0.698486 | L82: 0.754786 | M82: 0.802174 | N82: 0.843384 | O82: 0.879251 | P82: 0.91159 | Q82: 0.938358 | R82: 0.962019 | S82: 0.983655 | T82: 1.003554 | U82: 1.02184 | V82: 1.038826 | W82: 1.054412 | X82: 1.069992 | Y82: 1.085812 | Z82: 1.100785 | AA82: 1.116808 | AB82: 1.133098 | AC82: 1.149589 | AD82: 1.166471 | AE82: 1.183979 | AF82: 1.202275 | AG82: 1.221251 | AH82: 1.240699 | AI82: 1.260727 | AJ82: 1.281543 | AK82: 1.302984 | AL82: 0.05
B83: TEF000:bus_school_LPG | C83: Propane | D83: Transportation Energy Use: Bus: School Bus: Propane: High oil and gas supply | E83: 46-AEO2021.97.highogs-d120120a | F83: trillion Btu | G83: 0.031129 | H83: 0.045453 | I83: 0.056137 | J83: 0.064047 | K83: 0.069937 | L83: 0.07441 | M83: 0.077735 | N83: 0.080205 | O83: 0.08207 | P83: 0.083458 | Q83: 0.084464 | R83: 0.085157 | S83: 0.08565 | T83: 0.085919 | U83: 0.086003 | V83: 0.085982 | W83: 0.085875 | X83: 0.085704 | Y83: 0.085488 | Z83: 0.085239 | AA83: 0.084969 | AB83: 0.084686 | AC83: 0.084395 | AD83: 0.084102 | AE83: 0.083812 | AF83: 0.083529 | AG83: 0.083255 | AH83: 0.082991 | AI83: 0.082739 | AJ83: 0.082498 | AK83: 0.082267 | AL83: 0.033
B84: TEF000:bus_school_elec | C84: Electricity | D84: Transportation Energy Use: Bus: School Bus: Electricity: High oil and gas supply | E84: 46-AEO2021.98.highogs-d120120a | F84: trillion Btu | G84: 0 | H84: 0 | I84: 0 | J84: 0 | K84: 0 | L84: 0 | M84: 0 | N84: 0 | O84: 0 | P84: 0 | Q84: 0 | R84: 0 | S84: 0 | T84: 0 | U84: 0 | V84: 0 | W84: 0 | X84: 0 | Y84: 0 | Z84: 0 | AA84: 0 | AB84: 0 | AC84: 0 | AD84: 0 | AE84: 0 | AF84: 0 | AG84: 0 | AH84: 0 | AI84: 0 | AJ84: 0 | AK84: 0 | AL84: - -
B85: TEF000:bus_school_hydro | C85: Hydrogen | D85: Transportation Energy Use: Bus: School Bus: Hydrogen: High oil and gas supply | E85: 46-AEO2021.99.highogs-d120120a | F85: trillion Btu | G85: 0 | H85: 0 | I85: 0 | J85: 0 | K85: 0 | L85: 0 | M85: 0 | N85: 0 | O85: 0 | P85: 0 | Q85: 0 | R85: 0 | S85: 0 | T85: 0 | U85: 0 | V85: 0 | W85: 0 | X85: 0 | Y85: 0 | Z85: 0 | AA85: 0 | AB85: 0 | AC85: 0 | AD85: 0 | AE85: 0 | AF85: 0 | AG85: 0 | AH85: 0 | AI85: 0 | AJ85: 0 | AK85: 0 | AL85: - -
B86: TEF000:ma_Total | C86: Rail Transportation | D86: Transportation Energy Use: Rail: High oil and gas supply | E86: 46-AEO2021.100.highogs-d120120a | F86: trillion Btu | G86: 29.437216 | H86: 35.250797 | I86: 39.933895 | J86: 43.478256 | K86: 46.156216 | L86: 48.165981 | M86: 49.615047 | N86: 50.695496 | O86: 51.001202 | P86: 51.250046 | Q86: 51.751541 | R86: 52.018612 | S86: 52.57357 | T86: 53.110683 | U86: 53.764702 | V86: 54.329742 | W86: 54.952255 | X86: 55.549725 | Y86: 56.141464 | Z86: 56.752045 | AA86: 57.541695 | AB86: 58.267525 | AC86: 58.979057 | AD86: 59.712196 | AE86: 60.418358 | AF86: 61.202957 | AG86: 61.917824 | AH86: 62.563126 | AI86: 63.253716 | AJ86: 64.011559 | AK86: 64.756165 | AL86: 0.027
B87: TEF000:ka_IntercityRail | C87: Intercity Rail | D87: Transportation Energy Use: Rail: Intercity Rail: High oil and gas supply | E87: 46-AEO2021.101.highogs-d120120a | F87: trillion Btu | G87: 5.395889 | H87: 7.087016 | I87: 8.316939 | J87: 9.220778 | K87: 9.891589 | L87: 10.394148 | M87: 10.780244 | N87: 11.083335 | O87: 11.181947 | P87: 11.279499 | Q87: 11.376509 | R87: 11.472944 | S87: 11.567452 | T87: 11.662525 | U87: 11.758153 | V87: 11.852737 | W87: 11.946493 | X87: 12.039237 | Y87: 12.130905 | Z87: 12.22143 | AA87: 12.31078 | AB87: 12.398965 | AC87: 12.486036 | AD87: 12.572057 | AE87: 12.657108 | AF87: 12.741284 | AG87: 12.824713 | AH87: 12.907497 | AI87: 12.98976 | AJ87: 13.071688 | AK87: 13.153475 | AL87: 0.03
B88: TEF000:ka_InterElect | C88: Electricity | D88: Transportation Energy Use: Rail: Intercity Rail: Electricity: High oil and gas supply | E88: 46-AEO2021.102.highogs-d120120a | F88: trillion Btu | G88: 0.838523 | H88: 1.101325 | I88: 1.292456 | J88: 1.432913 | K88: 1.537157 | L88: 1.615254 | M88: 1.675254 | N88: 1.722355 | O88: 1.737679 | P88: 1.752839 | Q88: 1.767914 | R88: 1.7829 | S88: 1.797586 | T88: 1.812361 | U88: 1.827222 | V88: 1.84192 | W88: 1.85649 | X88: 1.870902 | Y88: 1.885147 | Z88: 1.899215 | AA88: 1.9131 | AB88: 1.926804 | AC88: 1.940335 | AD88: 1.953703 | AE88: 1.96692 | AF88: 1.98 | AG88: 1.992966 | AH88: 2.00583 | AI88: 2.018614 | AJ88: 2.031345 | AK88: 2.044055 | AL88: 0.03
B89: TEF000:la_InterDiesel | C89: Diesel | D89: Transportation Energy Use: Rail: Intercity Rail: Diesel: High oil and gas supply | E89: 46-AEO2021.103.highogs-d120120a | F89: trillion Btu | G89: 4.557366 | H89: 5.985691 | I89: 7.024484 | J89: 7.787866 | K89: 8.354432 | L89: 8.778893 | M89: 9.10499 | N89: 9.36098 | O89: 9.444268 | P89: 9.52666 | Q89: 9.608595 | R89: 9.690044 | S89: 9.769866 | T89: 9.850164 | U89: 9.930931 | V89: 10.010818 | W89: 10.090003 | X89: 10.168335 | Y89: 10.245758 | Z89: 10.322215 | AA89: 10.397679 | AB89: 10.472161 | AC89: 10.545701 | AD89: 10.618354 | AE89: 10.690188 | AF89: 10.761284 | AG89: 10.831747 | AH89: 10.901668 | AI89: 10.971147 | AJ89: 11.040342 | AK89: 11.10942 | AL89: 0.03
B90: TEF000:la_InterCNG | C90: Compressed Natural Gas | D90: Transportation Energy Use: Rail: Intercity Rail: CNG: High oil and gas supply | E90: 46-AEO2021.104.highogs-d120120a | F90: trillion Btu | G90: 0 | H90: 0 | I90: 0 | J90: 0 | K90: 0 | L90: 0 | M90: 0 | N90: 0 | O90: 0 | P90: 0 | Q90: 0 | R90: 0 | S90: 0 | T90: 0 | U90: 0 | V90: 0 | W90: 0 | X90: 0 | Y90: 0 | Z90: 0 | AA90: 0 | AB90: 0 | AC90: 0 | AD90: 0 | AE90: 0 | AF90: 0 | AG90: 0 | AH90: 0 | AI90: 0 | AJ90: 0 | AK90: 0 | AL90: - -
B91: TEF000:la_InterLNG | C91: Liquefied Natural Gas | D91: Transportation Energy Use: Rail: Intercity Rail: LNG: High oil and gas supply | E91: 46-AEO2021.105.highogs-d120120a | F91: trillion Btu | G91: 0 | H91: 0 | I91: 0 | J91: 0 | K91: 0 | L91: 0 | M91: 0 | N91: 0 | O91: 0 | P91: 0 | Q91: 0 | R91: 0 | S91: 0 | T91: 0 | U91: 0 | V91: 0 | W91: 0 | X91: 0 | Y91: 0 | Z91: 0 | AA91: 0 | AB91: 0 | AC91: 0 | AD91: 0 | AE91: 0 | AF91: 0 | AG91: 0 | AH91: 0 | AI91: 0 | AJ91: 0 | AK91: 0 | AL91: - -
B92: TEF000:la_TransitRail | C92: Transit Rail | D92: Transportation Energy Use: Rail: Transit Rail: High oil and gas supply | E92: 46-AEO2021.106.highogs-d120120a | F92: trillion Btu | G92: 10.374469 | H92: 12.459964 | I92: 14.173363 | J92: 15.449635 | K92: 16.417963 | L92: 17.135733 | M92: 17.650576 | N92: 18.041847 | O92: 18.133167 | P92: 18.20327 | Q92: 18.402081 | R92: 18.451336 | S92: 18.640221 | T92: 18.814421 | U92: 19.044952 | V92: 19.207932 | W92: 19.406109 | X92: 19.596359 | Y92: 19.780315 | Z92: 19.959137 | AA92: 20.216698 | AB92: 20.439466 | AC92: 20.648699 | AD92: 20.867985 | AE92: 21.078064 | AF92: 21.325676 | AG92: 21.544163 | AH92: 21.747824 | AI92: 21.97892 | AJ92: 22.264633 | AK92: 22.56337 | AL92: 0.026
B93: TEF000:la_TransitElect | C93: Electricity | D93: Transportation Energy Use: Rail: Transit Rail: Electricity: High oil and gas supply | E93: 46-AEO2021.107.highogs-d120120a | F93: trillion Btu | G93: 10.374469 | H93: 12.459964 | I93: 14.173363 | J93: 15.449635 | K93: 16.417963 | L93: 17.135733 | M93: 17.650576 | N93: 18.041847 | O93: 18.133167 | P93: 18.20327 | Q93: 18.402081 | R93: 18.451336 | S93: 18.640221 | T93: 18.814421 | U93: 19.044952 | V93: 19.207932 | W93: 19.406109 | X93: 19.596359 | Y93: 19.780315 | Z93: 19.959137 | AA93: 20.216698 | AB93: 20.439466 | AC93: 20.648699 | AD93: 20.867985 | AE93: 21.078064 | AF93: 21.325676 | AG93: 21.544163 | AH93: 21.747824 | AI93: 21.97892 | AJ93: 22.264633 | AK93: 22.56337 | AL93: 0.026
B94: TEF000:ma_CommuterRail | C94: Commuter Rail | D94: Transportation Energy Use: Rail: Commuter Rail: High oil and gas supply | E94: 46-AEO2021.108.highogs-d120120a | F94: trillion Btu | G94: 13.666859 | H94: 15.703818 | I94: 17.443592 | J94: 18.807842 | K94: 19.846664 | L94: 20.636099 | M94: 21.184227 | N94: 21.570311 | O94: 21.686089 | P94: 21.767277 | Q94: 21.972954 | R94: 22.094334 | S94: 22.365896 | T94: 22.633738 | U94: 22.961601 | V94: 23.269072 | W94: 23.599651 | X94: 23.914127 | Y94: 24.230244 | Z94: 24.57148 | AA94: 25.014217 | AB94: 25.429092 | AC94: 25.844322 | AD94: 26.272156 | AE94: 26.683189 | AF94: 27.136 | AG94: 27.548948 | AH94: 27.90781 | AI94: 28.285034 | AJ94: 28.67524 | AK94: 29.039318 | AL94: 0.025
B95: TEF000:ma_CommuteElect | C95: Electricity | D95: Transportation Energy Use: Rail: Commuter Rail: Electricity: High oil and gas supply | E95: 46-AEO2021.109.highogs-d120120a | F95: trillion Btu | G95: 4.51166 | H95: 5.008751 | I95: 5.473188 | J95: 5.84824 | K95: 6.13525 | L95: 6.361259 | M95: 6.514176 | N95: 6.616694 | O95: 6.666852 | P95: 6.703321 | Q95: 6.771784 | R95: 6.827151 | S95: 6.932632 | T95: 7.037734 | U95: 7.1615 | V95: 7.286537 | W95: 7.411777 | X95: 7.528294 | Y95: 7.645722 | Z95: 7.775413 | AA95: 7.939988 | AB95: 8.096106 | AC95: 8.251081 | AD95: 8.409151 | AE95: 8.558866 | AF95: 8.723728 | AG95: 8.8759 | AH95: 9.005876 | AI95: 9.146731 | AJ95: 9.288316 | AK95: 9.421024 | AL95: 0.025
B96: TEF000:ma_CommuteDiesel | C96: Diesel | D96: Transportation Energy Use: Rail: Commuter Rail: Diesel: High oil and gas supply | E96: 46-AEO2021.110.highogs-d120120a | F96: trillion Btu | G96: 9.155199 | H96: 10.695067 | I96: 11.970403 | J96: 12.959603 | K96: 13.711413 | L96: 14.27484 | M96: 14.670052 | N96: 14.953617 | O96: 15.019238 | P96: 15.063955 | Q96: 15.201169 | R96: 15.267181 | S96: 15.433265 | T96: 15.596004 | U96: 15.8001 | V96: 15.982534 | W96: 16.187874 | X96: 16.385834 | Y96: 16.584522 | Z96: 16.796066 | AA96: 17.07423 | AB96: 17.332987 | AC96: 17.593243 | AD96: 17.863005 | AE96: 18.124323 | AF96: 18.412271 | AG96: 18.673048 | AH96: 18.901934 | AI96: 19.138302 | AJ96: 19.386923 | AK96: 19.618294 | AL96: 0.026
B97: TEF000:ma_CommuteCNG | C97: Compressed Natural Gas | D97: Transportation Energy Use: Rail: Commuter Rail: CNG: High oil and gas supply | E97: 46-AEO2021.111.highogs-d120120a | F97: trillion Btu | G97: 0 | H97: 0 | I97: 0 | J97: 0 | K97: 0 | L97: 0 | M97: 0 | N97: 0 | O97: 0 | P97: 0 | Q97: 0 | R97: 0 | S97: 0 | T97: 0 | U97: 0 | V97: 0 | W97: 0 | X97: 0 | Y97: 0 | Z97: 0 | AA97: 0 | AB97: 0 | AC97: 0 | AD97: 0 | AE97: 0 | AF97: 0 | AG97: 0 | AH97: 0 | AI97: 0 | AJ97: 0 | AK97: 0 | AL97: - -
B98: TEF000:ma_CommuteLNG | C98: Liquefied Natural Gas | D98: Transportation Energy Use: Rail: Commuter Rail: LNG: High oil and gas supply | E98: 46-AEO2021.112.highogs-d120120a | F98: trillion Btu | G98: 0 | H98: 0 | I98: 0 | J98: 0 | K98: 0 | L98: 0 | M98: 0 | N98: 0 | O98: 0 | P98: 0 | Q98: 0 | R98: 0 | S98: 0 | T98: 0 | U98: 0 | V98: 0 | W98: 0 | X98: 0 | Y98: 0 | Z98: 0 | AA98: 0 | AB98: 0 | AC98: 0 | AD98: 0 | AE98: 0 | AF98: 0 | AG98: 0 | AH98: 0 | AI98: 0 | AJ98: 0 | AK98: 0 | AL98: - -
B99: TEF000:na_RecreationBoa | C99: Recreational Boats | D99: Transportation Energy Use: Recreation Boats: High oil and gas supply | E99: 46-AEO2021.114.highogs-d120120a | F99: trillion Btu | G99: 195.87843 | H99: 196.65694 | I99: 199.71631 | J99: 201.51434 | K99: 202.25748 | L99: 202.57369 | M99: 201.85445 | N99: 200.37804 | O99: 198.67445 | P99: 196.83032 | Q99: 195.06877 | R99: 193.55562 | S99: 192.48926 | T99: 191.38321 | U99: 190.48383 | V99: 189.81821 | W99: 188.91023 | X99: 187.75908 | Y99: 186.65848 | Z99: 185.8015 | AA99: 185.22307 | AB99: 184.58832 | AC99: 183.88181 | AD99: 183.17465 | AE99: 182.32883 | AF99: 181.67963 | AG99: 180.9055 | AH99: 179.87953 | AI99: 179.14038 | AJ99: 178.36557 | AK99: 177.57169 | AL99: -0.003
B100: TEF000:na_RecreateGas | C100: Gasoline | D100: Transportation Energy Use: Recreation Boats: Motor Gasoline: High oil and gas supply | E100: 46-AEO2021.115.highogs-d120120a | F100: trillion Btu | G100: 158.50087 | H100: 158.87814 | I100: 161.09187 | J100: 162.28059 | K100: 162.61517 | L100: 162.60378 | M100: 161.76044 | N100: 160.31189 | O100: 158.68449 | P100: 156.94826 | Q100: 155.2814 | R100: 153.8154 | S100: 152.70666 | T100: 151.56813 | U100: 150.59474 | V100: 149.80704 | W100: 148.82899 | X100: 147.66097 | Y100: 146.53458 | Z100: 145.60097 | AA100: 144.88641 | AB100: 144.1283 | AC100: 143.31483 | AD100: 142.50166 | AE100: 141.58164 | AF100: 140.81523 | AG100: 139.95287 | AH100: 138.8971 | AI100: 138.06416 | AJ100: 137.2048 | AK100: 136.33192 | AL100: -0.005
B101: TEF000:na_RecreateDies | C101: Distillate Fuel Oil (diesel) | D101: Transportation Energy Use: Recreation Boats: Distillate Fuel Oil: High oil and gas supply | E101: 46-AEO2021.116.highogs-d120120a | F101: trillion Btu | G101: 37.37756 | H101: 37.778793 | I101: 38.624439 | J101: 39.233746 | K101: 39.642311 | L101: 39.969906 | M101: 40.094009 | N101: 40.066147 | O101: 39.989956 | P101: 39.882061 | Q101: 39.787365 | R101: 39.740219 | S101: 39.782585 | T101: 39.815079 | U101: 39.889091 | V101: 40.011162 | W101: 40.081238 | X101: 40.098114 | Y101: 40.123894 | Z101: 40.200531 | AA101: 40.336651 | AB101: 40.460018 | AC101: 40.566975 | AD101: 40.672985 | AE101: 40.747196 | AF101: 40.864391 | AG101: 40.952633 | AH101: 40.982441 | AI101: 41.07621 | AJ101: 41.160763 | AK101: 41.239765 | AL101: 0.003
B102: TEF000:na_Lubricants | C102: Lubricants | D102: Transportation Energy Use: Lubricants: High oil and gas supply | E102: 46-AEO2021.118.highogs-d120120a | F102: trillion Btu | G102: 121.22439 | H102: 123.40012 | I102: 124.82059 | J102: 125.91473 | K102: 126.65642 | L102: 127.04057 | M102: 127.20718 | N102: 126.85352 | O102: 126.59703 | P102: 126.37843 | Q102: 126.07404 | R102: 125.8016 | S102: 125.58483 | T102: 125.40055 | U102: 125.28949 | V102: 125.20488 | W102: 125.08443 | X102: 124.93435 | Y102: 124.83044 | Z102: 124.75782 | AA102: 124.67342 | AB102: 124.58897 | AC102: 124.5218 | AD102: 124.43999 | AE102: 124.42282 | AF102: 124.4984 | AG102: 124.51592 | AH102: 124.47363 | AI102: 124.49622 | AJ102: 124.46999 | AK102: 124.38553 | AL102: 0.001
B103: TEF000:na_PipelineFuelN | C103: Pipeline Fuel Natural Gas | D103: Transportation Energy Use: Pipeline Fuel Natural Gas: High oil and gas supply | E103: 46-AEO2021.119.highogs-d120120a | F103: trillion Btu | G103: 706.25012 | H103: 765.14197 | I103: 755.34998 | J103: 731.63831 | K103: 723.20685 | L103: 724.60596 | M103: 691.04956 | N103: 701.14313 | O103: 701.06634 | P103: 701.03687 | Q103: 693.45966 | R103: 694.47479 | S103: 697.11835 | T103: 697.96668 | U103: 696.89435 | V103: 700.55658 | W103: 708.85254 | X103: 718.20209 | Y103: 725.97797 | Z103: 730.66339 | AA103: 734.56103 | AB103: 737.10724 | AC103: 741.27094 | AD103: 748.35034 | AE103: 759.38428 | AF103: 765.85901 | AG103: 773.89398 | AH103: 783.06421 | AI103: 778.31659 | AJ103: 777.42078 | AK103: 784.83752 | AL103: 0.004
B104: TEF000:pa_TotalConsumpt | C104: Total Consumption | D104: Transportation Energy Use: Total Use: High oil and gas supply | E104: 46-AEO2021.121.highogs-d120120a | F104: trillion Btu | G104: 24641.326 | H104: 26248.078 | I104: 26805.33 | J104: 27034.602 | K104: 27133.555 | L104: 27233.936 | M104: 27190.395 | N104: 27083.885 | O104: 26994.961 | P104: 26865.316 | Q104: 26747.643 | R104: 26658.848 | S104: 26571.893 | T104: 26518.625 | U104: 26496.607 | V104: 26552.078 | W104: 26585.184 | X104: 26629.648 | Y104: 26694.693 | Z104: 26765.23 | AA104: 26868.734 | AB104: 26997.643 | AC104: 27118.664 | AD104: 27275.537 | AE104: 27412.283 | AF104: 27561.635 | AG104: 27697.734 | AH104: 27817.297 | AI104: 27945.371 | AJ104: 28082.121 | AK104: 28236.771 | AL104: 0.005

Sheet AEO 38
B1: ORIGINAL EIA CODE | G1: 2020 | H1: 2021 | I1: 2022 | J1: 2023 | K1: 2024 | L1: 2025 | M1: 2026 | N1: 2027 | O1: 2028 | P1: 2029 | Q1: 2030 | R1: 2031 | S1: 2032 | T1: 2033 | U1: 2034 | V1: 2035 | W1: 2036 | X1: 2037 | Y1: 2038 | Z1: 2039 | AA1: 2040 | AB1: 2041 | AC1: 2042 | AD1: 2043 | AE1: 2044 | AF1: 2045 | AG1: 2046 | AH1: 2047 | AI1: 2048 | AJ1: 2049 | AK1: 2050 | AL1: Growth (2020-2050)
B10: TST000 | C10: Table 38. Light-Duty Vehicle Sales by Technology Type
C11: https://www.eia.gov/outlooks/aeo/data/browser/#/?id=48-AEO2021&region=1-0&cases=highogs&start=2020&end=2050&f=A&linechart=highogs-d120120a.4-48-AEO2021.1-0&map=highogs-d120120a.5-48-AEO2021.1-0&sourcekey=0
C12: Tue Mar 09 2021 12:43:15 GMT-0800 (Pacific Standard Time)
C13: Source: U.S. Energy Information Administration
D14: full name | E14: api key | F14: units | G14: 2020 | H14: 2021 | I14: 2022 | J14: 2023 | K14: 2024 | L14: 2025 | M14: 2026 | N14: 2027 | O14: 2028 | P14: 2029 | Q14: 2030 | R14: 2031 | S14: 2032 | T14: 2033 | U14: 2034 | V14: 2035 | W14: 2036 | X14: 2037 | Y14: 2038 | Z14: 2039 | AA14: 2040 | AB14: 2041 | AC14: 2042 | AD14: 2043 | AE14: 2044 | AF14: 2045 | AG14: 2046 | AH14: 2047 | AI14: 2048 | AJ14: 2049 | AK14: 2050 | AL14: Growth (2020-2050)
C15: New Car Sales | E15: 48-AEO2021.2.
C16: Conventional Cars | E16: 48-AEO2021.3.
A17: gasoline vehicle | B17: TST000:ba_GasolineICEVe | C17: Gasoline ICE Vehicles | D17: Light-Duty Vehicle Sales: Conventional Cars: Gasoline: High oil and gas supply | E17: 48-AEO2021.4.highogs-d120120a | F17: thousands | G17: 4430.54 | H17: 4768.9263 | I17: 5242.686 | J17: 5277.4258 | K17: 5332.4824 | L17: 5366.3647 | M17: 5276.0283 | N17: 5157.7227 | O17: 5160.4292 | P17: 5150.4785 | Q17: 5149.1211 | R17: 5129.0278 | S17: 5123.6499 | T17: 5107.165 | U17: 5106.6157 | V17: 5067.0293 | W17: 4988.6606 | X17: 4915.4424 | Y17: 4879.7422 | Z17: 4824.8184 | AA17: 4767.0156 | AB17: 4718.7866 | AC17: 4672.1494 | AD17: 4616.104 | AE17: 4570.187 | AF17: 4571.7012 | AG17: 4505.4287 | AH17: 4434.6743 | AI17: 4405.3608 | AJ17: 4332.688 | AK17: 4252.9243 | AL17: -0.001
A18: diesel vehicle | B18: TST000:ba_TDIDieselICE | C18: TDI Diesel ICE | D18: Light-Duty Vehicle Sales: Conventional Cars: TDI Diesel: High oil and gas supply | E18: 48-AEO2021.5.highogs-d120120a | F18: thousands | G18: 0.091703 | H18: 0.090031 | I18: 0.094424 | J18: 0.089815 | K18: 0.08771 | L18: 0.08925 | M18: 0.086431 | N18: 0.083304 | O18: 0.08455 | P18: 0.084075 | Q18: 0.083118 | R18: 0.084137 | S18: 0.083978 | T18: 0.083596 | U18: 0.084752 | V18: 0.084326 | W18: 0.083612 | X18: 0.081953 | Y18: 0.081093 | Z18: 0.081319 | AA18: 0.078959 | AB18: 0.078244 | AC18: 0.077311 | AD18: 0.076276 | AE18: 0.075326 | AF18: 0.075413 | AG18: 0.074002 | AH18: 0.072725 | AI18: 0.071912 | AJ18: 0.070517 | AK18: 0.069125 | AL18: -0.009
B19: TST000:ba_TotalConventi | C19: Total Conventional Cars | D19: Light-Duty Vehicle Sales: Conventional Cars: Total: High oil and gas supply | E19: 48-AEO2021.6.highogs-d120120a | F19: thousands | G19: 4430.6318 | H19: 4769.0161 | I19: 5242.7803 | J19: 5277.5156 | K19: 5332.5703 | L19: 5366.4541 | M19: 5276.1147 | N19: 5157.8062 | O19: 5160.5137 | P19: 5150.5625 | Q19: 5149.2041 | R19: 5129.1118 | S19: 5123.7339 | T19: 5107.2485 | U19: 5106.7007 | V19: 5067.1138 | W19: 4988.7441 | X19: 4915.5244 | Y19: 4879.8232 | Z19: 4824.8999 | AA19: 4767.0947 | AB19: 4718.8647 | AC19: 4672.2266 | AD19: 4616.1802 | AE19: 4570.2622 | AF19: 4571.7764 | AG19: 4505.5029 | AH19: 4434.7471 | AI19: 4405.4326 | AJ19: 4332.7583 | AK19: 4252.9937 | AL19: -0.001
C20: Alternative-Fuel Cars | E20: 48-AEO2021.8.
A21: gasoline vehicle | B21: TST000:ca_Ethanol-FlexF | C21: Ethanol-Flex Fuel ICE | D21: Light-Duty Vehicle Sales: Alternative-Fuel Cars: Ethanol-Flex Fuel ICE: High oil and gas supply | E21: 48-AEO2021.9.highogs-d120120a | F21: thousands | G21: 82.86573 | H21: 88.778244 | I21: 97.887756 | J21: 98.749519 | K21: 99.876137 | L21: 100.60027 | M21: 99.069313 | N21: 97.080338 | O21: 97.452324 | P21: 97.519157 | Q21: 97.80072 | R21: 97.808365 | S21: 98.015251 | T21: 98.066704 | U21: 98.425705 | V21: 98.079758 | W21: 96.899742 | X21: 95.840691 | Y21: 95.533234 | Z21: 94.846573 | AA21: 94.080093 | AB21: 93.468681 | AC21: 92.857796 | AD21: 92.05088 | AE21: 91.469421 | AF21: 91.848557 | AG21: 90.8843 | AH21: 89.801239 | AI21: 89.570892 | AJ21: 88.466881 | AK21: 87.250069 | AL21: 0.002
A22: battery electric vehicle | B22: TST000:ca_100mileEV | C22: 100 Mile Electric Vehicle | D22: Light-Duty Vehicle Sales: Alternative-Fuel Cars: 100 Mile Electric Vehicle: High oil and gas supply | E22: 48-AEO2021.10.highogs-d120120a | F22: thousands | G22: 2.014161 | H22: 2.116755 | I22: 2.187926 | J22: 2.115665 | K22: 2.1331 | L22: 2.187847 | M22: 2.250745 | N22: 2.319192 | O22: 2.463099 | P22: 2.616289 | Q22: 2.802221 | R22: 2.953589 | S22: 3.120451 | T22: 3.262651 | U22: 3.40547 | V22: 3.49672 | W22: 3.548795 | X22: 3.589806 | Y22: 3.646011 | Z22: 3.673913 | AA22: 3.693691 | AB22: 3.701219 | AC22: 3.707546 | AD22: 3.704162 | AE22: 3.70677 | AF22: 3.748243 | AG22: 3.730523 | AH22: 3.707829 | AI22: 3.718948 | AJ22: 3.697174 | AK22: 3.669234 | AL22: 0.02
A23: battery electric vehicle | B23: TST000:ca_ElectricVehic | C23: 200 Mile Electric Vehicle | D23: Light-Duty Vehicle Sales: Alternative-Fuel Cars: 200 Mile Electric Vehicle: High oil and gas supply | E23: 48-AEO2021.11.highogs-d120120a | F23: thousands | G23: 45.0984 | H23: 43.183132 | I23: 44.87886 | J23: 42.311188 | K23: 41.21912 | L23: 41.567673 | M23: 41.456791 | N23: 43.14045 | O23: 46.895927 | P23: 51.488796 | Q23: 58.315022 | R23: 64.530876 | S23: 72.045967 | T23: 79.581985 | U23: 87.853249 | V23: 94.674225 | W23: 100.86777 | X23: 107.29221 | Y23: 114.55816 | Z23: 120.88749 | AA23: 127.42668 | AB23: 133.08254 | AC23: 138.54511 | AD23: 144.04106 | AE23: 150.03532 | AF23: 158.08809 | AG23: 163.42651 | AH23: 168.74788 | AI23: 175.61302 | AJ23: 181.70338 | AK23: 187.48808 | AL23: 0.049
A24: battery electric vehicle | B24: TST000:ea_FuelCellGasol | C24: 300 Mile Electric Vehicle | D24: Light-Duty Vehicle Sales: Alternative-Fuel Cars: 300 Mile Electric Vehicle: High oil and gas supply | E24: 48-AEO2021.12.highogs-d120120a | F24: thousands | G24: 65.759254 | H24: 57.491383 | I24: 66.992439 | J24: 73.780128 | K24: 80.019737 | L24: 83.488007 | M24: 88.954521 | N24: 94.401581 | O24: 105.24663 | P24: 117.28207 | Q24: 132.60144 | R24: 153.49263 | S24: 173.61665 | T24: 198.33243 | U24: 225.30927 | V24: 254.45285 | W24: 278.03854 | X24: 303.48288 | Y24: 332.54962 | Z24: 360.70767 | AA24: 386.63501 | AB24: 406.61685 | AC24: 425.57904 | AD24: 443.11395 | AE24: 462.9602 | AF24: 488.96314 | AG24: 510.02222 | AH24: 528.28735 | AI24: 553.2616 | AJ24: 572.91254 | AK24: 594.61017 | AL24: 0.076
A25: plugin hybrid vehicle | B25: TST000:ca_Plug-inGasoli | C25: Plug-in 10 Gasoline Hybrid | D25: Light-Duty Vehicle Sales: Alternative-Fuel Cars: Plug-in 10 Gasoline Hybrid: High oil and gas supply | E25: 48-AEO2021.13.highogs-d120120a | F25: thousands | G25: 20.674416 | H25: 28.176989 | I25: 33.950932 | J25: 36.931286 | K25: 41.969532 | L25: 48.640995 | M25: 55.013874 | N25: 62.905365 | O25: 73.882957 | P25: 77.068756 | Q25: 80.696732 | R25: 81.135765 | S25: 83.302795 | T25: 84.292328 | U25: 85.728806 | V25: 84.681641 | W25: 83.560677 | X25: 82.382141 | Y25: 81.626305 | Z25: 79.956459 | AA25: 78.624977 | AB25: 76.511696 | AC25: 74.205223 | AD25: 72.000122 | AE25: 69.958206 | AF25: 68.774048 | AG25: 66.15274 | AH25: 63.704296 | AI25: 61.705101 | AJ25: 59.545723 | AK25: 57.139908 | AL25: 0.034
A26: plugin hybrid vehicle | B26: TST000:ca_Plug-in40Hybd | C26: Plug-in 40 Gasoline Hybrid | D26: Light-Duty Vehicle Sales: Alternative-Fuel Cars: Plug-in 40 Gasoline Hybrid: High oil and gas supply | E26: 48-AEO2021.14.highogs-d120120a | F26: thousands | G26: 5.310642 | H26: 5.630332 | I26: 5.241416 | J26: 4.634056 | K26: 4.410059 | L26: 4.339242 | M26: 4.392287 | N26: 4.544848 | O26: 4.886629 | P26: 5.32712 | Q26: 5.979389 | R26: 6.411442 | S26: 6.825327 | T26: 7.164952 | U26: 7.520013 | V26: 7.705092 | W26: 7.815033 | X26: 7.905196 | Y26: 8.024158 | Z26: 8.055717 | AA26: 8.079099 | AB26: 8.036082 | AC26: 7.969784 | AD26: 7.89343 | AE26: 7.831873 | AF26: 7.857708 | AG26: 7.742971 | AH26: 7.623875 | AI26: 7.568454 | AJ26: 7.464639 | AK26: 7.343002 | AL26: 0.011
A27: diesel vehicle | B27: TST000:ca_Electric-Dies | C27: Electric-Diesel Hybrid | D27: Light-Duty Vehicle Sales: Alternative-Fuel Cars: Electric-Diesel Hybrid: High oil and gas supply | E27: 48-AEO2021.15.highogs-d120120a | F27: thousands | G27: 0 | H27: 0 | I27: 0 | J27: 0 | K27: 0 | L27: 0 | M27: 0 | N27: 0 | O27: 0 | P27: 0 | Q27: 0 | R27: 0 | S27: 0 | T27: 0 | U27: 0 | V27: 0 | W27: 0 | X27: 0 | Y27: 0 | Z27: 0 | AA27: 0 | AB27: 0 | AC27: 0 | AD27: 0 | AE27: 0 | AF27: 0 | AG27: 0 | AH27: 0 | AI27: 0 | AJ27: 0 | AK27: 0 | AL27: - -
A28: gasoline vehicle | B28: TST000:ca_Electric-Gaso | C28: Electric-Gasoline Hybrid | D28: Light-Duty Vehicle Sales: Alternative-Fuel Cars: Electric-Gasoline Hybrid: High oil and gas supply | E28: 48-AEO2021.16.highogs-d120120a | F28: thousands | G28: 121.39723 | H28: 136.90977 | I28: 161.62053 | J28: 172.90016 | K28: 185.48763 | L28: 197.37852 | M28: 206.53253 | N28: 216.44562 | O28: 232.97336 | P28: 246.07936 | Q28: 261.67313 | R28: 274.52325 | S28: 287.88394 | T28: 300.89297 | U28: 315.42978 | V28: 326.46143 | W28: 334.92172 | X28: 344.05875 | Y28: 356.15479 | Z28: 366.53769 | AA28: 377.08914 | AB28: 390.3526 | AC28: 401.86212 | AD28: 413.0246 | AE28: 425.68555 | AF28: 443.7468 | AG28: 455.27057 | AH28: 466.522 | AI28: 482.34302 | AJ28: 494.32117 | AK28: 505.77969 | AL28: 0.049
A29: natural gas vehicle | B29: TST000:ca_CompressedNat | C29: Natural Gas ICE | D29: Light-Duty Vehicle Sales: Alternative-Fuel Cars: Natural Gas ICE: High oil and gas supply | E29: 48-AEO2021.17.highogs-d120120a | F29: thousands | G29: 0.436299 | H29: 0.446886 | I29: 0.548589 | J29: 0.607807 | K29: 0.654286 | L29: 0.681397 | M29: 0.675533 | N29: 0.660688 | O29: 0.663885 | P29: 0.659324 | Q29: 0.654316 | R29: 0.660209 | S29: 0.659287 | T29: 0.660811 | U29: 0.664577 | V29: 0.666657 | W29: 0.656994 | X29: 0.650827 | Y29: 0.651406 | Z29: 0.649305 | AA29: 0.644867 | AB29: 0.642947 | AC29: 0.64116 | AD29: 0.637366 | AE29: 0.635911 | AF29: 0.641543 | AG29: 0.638431 | AH29: 0.633144 | AI29: 0.634526 | AJ29: 0.629213 | AK29: 0.624813 | AL29: 0.012
A30: natural gas vehicle | B30: TST000:da_CompressedNat | C30: Natural Gas Bi-fuel | D30: Light-Duty Vehicle Sales: Alternative-Fuel Cars: Natural Gas Bi-fuel: High oil and gas supply | E30: 48-AEO2021.18.highogs-d120120a | F30: thousands | G30: 2.233771 | H30: 2.354919 | I30: 2.610208 | J30: 2.642015 | K30: 2.677342 | L30: 2.702859 | M30: 2.668197 | N30: 2.623082 | O30: 2.645067 | P30: 2.65579 | Q30: 2.670106 | R30: 2.683413 | S30: 2.699393 | T30: 2.713665 | U30: 2.737803 | V30: 2.741847 | W30: 2.720474 | X30: 2.704052 | Y30: 2.709671 | Z30: 2.704082 | AA30: 2.695708 | AB30: 2.690396 | AC30: 2.684189 | AD30: 2.672501 | AE30: 2.66801 | AF30: 2.692924 | AG30: 2.678834 | AH30: 2.660519 | AI30: 2.668229 | AJ30: 2.650469 | AK30: 2.630525 | AL30: 0.005
A31: LPG vehicle | B31: TST000:da_LiquefiedPetr | C31: Propane ICE | D31: Light-Duty Vehicle Sales: Alternative-Fuel Cars: Propane: High oil and gas supply | E31: 48-AEO2021.19.highogs-d120120a | F31: thousands | G31: 0.413892 | H31: 0.373083 | I31: 0.432242 | J31: 0.450286 | K31: 0.454892 | L31: 0.459537 | M31: 0.453937 | N31: 0.44736 | O31: 0.455217 | P31: 0.459614 | Q31: 0.460688 | R31: 0.475505 | S31: 0.478446 | T31: 0.485149 | U31: 0.491327 | V31: 0.499504 | W31: 0.495486 | X31: 0.49308 | Y31: 0.496612 | Z31: 0.499809 | AA31: 0.499778 | AB31: 0.502526 | AC31: 0.505401 | AD31: 0.506785 | AE31: 0.509286 | AF31: 0.517814 | AG31: 0.520073 | AH31: 0.519068 | AI31: 0.524132 | AJ31: 0.521896 | AK31: 0.521648 | AL31: 0.008
A32: LPG vehicle | B32: TST000:ea_LiquefiedPetr | C32: Propane Bi-fuel | D32: Light-Duty Vehicle Sales: Alternative-Fuel Cars: Propane: High oil and gas supply | E32: 48-AEO2021.20.highogs-d120120a | F32: thousands | G32: 0.553153 | H32: 0.584848 | I32: 0.647259 | J32: 0.655402 | K32: 0.663684 | L32: 0.669541 | M32: 0.661359 | N32: 0.650377 | O32: 0.655528 | P32: 0.658057 | Q32: 0.661973 | R32: 0.665104 | S32: 0.668828 | T32: 0.672042 | U32: 0.677631 | V32: 0.678035 | W32: 0.672155 | X32: 0.667307 | Y32: 0.668127 | Z32: 0.666227 | AA32: 0.663661 | AB32: 0.661948 | AC32: 0.660016 | AD32: 0.656961 | AE32: 0.655442 | AF32: 0.661266 | AG32: 0.65729 | AH32: 0.652311 | AI32: 0.653646 | AJ32: 0.648766 | AK32: 0.643394 | AL32: 0.005
A33: hydrogen vehicle | B33: TST000:ea_FuelCellMetha | C33: Fuel Cell Methanol | D33: Light-Duty Vehicle Sales: Alternative-Fuel Cars: Fuel Cell Methanol: High oil and gas supply | E33: 48-AEO2021.21.highogs-d120120a | F33: thousands | G33: 0 | H33: 0 | I33: 0 | J33: 0 | K33: 0 | L33: 0 | M33: 0 | N33: 0 | O33: 0 | P33: 0 | Q33: 0 | R33: 0 | S33: 0 | T33: 0 | U33: 0 | V33: 0 | W33: 0 | X33: 0 | Y33: 0 | Z33: 0 | AA33: 0 | AB33: 0 | AC33: 0 | AD33: 0 | AE33: 0 | AF33: 0 | AG33: 0 | AH33: 0 | AI33: 0 | AJ33: 0 | AK33: 0 | AL33: - -
A34: hydrogen vehicle | B34: TST000:ea_FuelCellHydro | C34: Fuel Cell Hydrogen | D34: Light-Duty Vehicle Sales: Alternative-Fuel cars: Fuel Cell Hydrogen: High oil and gas supply | E34: 48-AEO2021.22.highogs-d120120a | F34: thousands | G34: 0.178328 | H34: 0.184374 | I34: 0.21913 | J34: 0.247297 | K34: 0.283277 | L34: 0.331866 | M34: 0.375719 | N34: 0.421967 | O34: 0.482801 | P34: 0.545208 | Q34: 0.610859 | R34: 0.674256 | S34: 0.736383 | T34: 0.794171 | U34: 0.850429 | V34: 0.896305 | W34: 0.928802 | X34: 0.958282 | Y34: 0.992079 | Z34: 1.019459 | AA34: 1.043306 | AB34: 1.067578 | AC34: 1.090818 | AD34: 1.110843 | AE34: 1.133713 | AF34: 1.169284 | AG34: 1.188951 | AH34: 1.205626 | AI34: 1.234655 | AJ34: 1.250848 | AK34: 1.266985 | AL34: 0.068
B35: TST000:ea_TotalAlternat | C35: Total Alternative Cars | D35: Light-Duty Vehicle Sales: Alternative-Fuel Cars: Total: High oil and gas supply | E35: 48-AEO2021.23.highogs-d120120a | F35: thousands | G35: 346.93527 | H35: 366.23074 | I35: 417.21722 | J35: 436.02481 | K35: 459.84882 | L35: 483.04776 | M35: 502.50482 | N35: 525.64087 | O35: 568.70343 | P35: 602.35956 | Q35: 644.92664 | R35: 686.0144 | S35: 730.05273 | T35: 776.91992 | U35: 829.09399 | V35: 875.03412 | W35: 911.12616 | X35: 950.02515 | Y35: 997.61017 | Z35: 1040.2043 | AA35: 1081.1759 | AB35: 1117.3351 | AC35: 1150.3082 | AD35: 1181.4126 | AE35: 1217.2496 | AF35: 1268.7095 | AG35: 1302.9135 | AH35: 1334.0649 | AI35: 1379.4961 | AJ35: 1413.8126 | AK35: 1448.9677 | AL35: 0.049
B36: TST000:fa_PercentAltern | C36: Percent Alternative Car Sales | D36: Light-Duty Vehicle Sales: Percent Alternative Car: High oil and gas supply | E36: 48-AEO2021.25.highogs-d120120a | F36: percent | G36: 7.261757 | H36: 7.131706 | I36: 7.371333 | J36: 7.631429 | K36: 7.938805 | L36: 8.25793 | M36: 8.695931 | N36: 9.248628 | O36: 9.926372 | P36: 10.470497 | Q36: 11.130689 | R36: 11.797069 | S36: 12.471461 | T36: 13.203565 | U36: 13.967699 | V36: 14.725889 | W36: 15.443156 | X36: 16.196693 | Y36: 16.973568 | Z36: 17.735477 | AA36: 18.487104 | AB36: 19.144907 | AC36: 19.756144 | AD36: 20.37764 | AE36: 21.032349 | AF36: 21.72267 | AG36: 22.431475 | AH36: 23.125471 | AI36: 23.84638 | AJ36: 24.602718 | AK36: 25.411739 | AL36: 0.043
B37: TST000:fa_TotalNewCarSa | C37: Total New Car Sales | D37: Light-Duty Vehicle Sales: Total New Car: High oil and gas supply | E37: 48-AEO2021.26.highogs-d120120a | F37: thousands | G37: 4777.5669 | H37: 5135.2471 | I37: 5659.9976 | J37: 5713.5405 | K37: 5792.4189 | L37: 5849.502 | M37: 5778.6196 | N37: 5683.4473 | O37: 5729.2173 | P37: 5752.9219 | Q37: 5794.1309 | R37: 5815.126 | S37: 5853.7866 | T37: 5884.1685 | U37: 5935.7949 | V37: 5942.1479 | W37: 5899.8701 | X37: 5865.5498 | Y37: 5877.4336 | Z37: 5865.1045 | AA37: 5848.2705 | AB37: 5836.1997 | AC37: 5822.5347 | AD37: 5797.5928 | AE37: 5787.5117 | AF37: 5840.4858 | AG37: 5808.4165 | AH37: 5768.812 | AI37: 5784.9287 | AJ37: 5746.5708 | AK37: 5701.9614 | AL37: 0.006
C38: New Light Truck Sales | E38: 48-AEO2021.28.
C39: Conventional Light Trucks | E39: 48-AEO2021.29.
A40: gasoline vehicle | B40: TST000:ga_GasolineICEVe | C40: Gasoline ICE Vehicles | D40: Light-Duty Vehicle Sales: Conventional Light Trucks: Gasoline: High oil and gas supply | E40: 48-AEO2021.30.highogs-d120120a | F40: thousands | G40: 6511.5112 | H40: 7292.9346 | I40: 7525.9263 | J40: 7716.5991 | K40: 8010.6343 | L40: 8217.6807 | M40: 8112.4087 | N40: 7927.6226 | O40: 7939.8613 | P40: 7908.9395 | Q40: 7718.6572 | R40: 7683.6753 | S40: 7655.0903 | T40: 7618.3013 | U40: 7564.605 | V40: 7588.0215 | W40: 7548.6802 | X40: 7479.4258 | Y40: 7456.207 | Z40: 7444.9131 | AA40: 7408.1597 | AB40: 7379.0337 | AC40: 7367.5815 | AD40: 7330.853 | AE40: 7297.3506 | AF40: 7318.8364 | AG40: 7272.2656 | AH40: 7213.9648 | AI40: 7236.2163 | AJ40: 7160.7158 | AK40: 7073.6338 | AL40: 0.003
A41: diesel vehicle | B41: TST000:ga_TDIDieselICE | C41: TDI Diesel ICE | D41: Light-Duty Vehicle Sales: Conventional Light Trucks: TDI Diesel: High oil and gas supply | E41: 48-AEO2021.31.highogs-d120120a | F41: thousands | G41: 46.653286 | H41: 86.627808 | I41: 118.90294 | J41: 111.87041 | K41: 112.74366 | L41: 118.86602 | M41: 113.95782 | N41: 110.3395 | O41: 114.4775 | P41: 115.45842 | Q41: 113.54399 | R41: 113.89195 | S41: 115.92995 | T41: 115.80641 | U41: 118.98551 | V41: 119.19649 | W41: 121.28391 | X41: 120.20547 | Y41: 120.30798 | Z41: 122.68635 | AA41: 120.37798 | AB41: 120.40474 | AC41: 120.17378 | AD41: 119.90891 | AE41: 119.43106 | AF41: 120.89611 | AG41: 119.21642 | AH41: 118.31202 | AI41: 118.43898 | AJ41: 117.40183 | AK41: 115.73097 | AL41: 0.031
B42: TST000:ga_TotalConventi | C42: Total Conventional Light Trucks | D42: Light-Duty Vehicle Sales: Conventional Light Trucks: Total: High oil and gas supply | E42: 48-AEO2021.32.highogs-d120120a | F42: thousands | G42: 6558.1646 | H42: 7379.5625 | I42: 7644.8291 | J42: 7828.4697 | K42: 8123.3779 | L42: 8336.5469 | M42: 8226.3662 | N42: 8037.9619 | O42: 8054.3389 | P42: 8024.3979 | Q42: 7832.2012 | R42: 7797.5674 | S42: 7771.0205 | T42: 7734.1079 | U42: 7683.5903 | V42: 7707.2178 | W42: 7669.9639 | X42: 7599.6313 | Y42: 7576.5151 | Z42: 7567.5996 | AA42: 7528.5376 | AB42: 7499.4385 | AC42: 7487.7554 | AD42: 7450.7617 | AE42: 7416.7817 | AF42: 7439.7324 | AG42: 7391.4819 | AH42: 7332.2769 | AI42: 7354.6553 | AJ42: 7278.1177 | AK42: 7189.3647 | AL42: 0.003
C43: Alternative-Fuel Light Trucks | E43: 48-AEO2021.34.
A44: gasoline vehicle | B44: TST000:ha_Ethanol-FlexF | C44: Ethanol-Flex Fuel ICE | D44: Light-Duty Vehicle Sales: Alternative-Fuel Light Trucks: Ethanol-Flex Fuel ICE: High oil and gas supply | E44: 48-AEO2021.35.highogs-d120120a | F44: thousands | G44: 658.6604 | H44: 672.66931 | I44: 696.22937 | J44: 714.13098 | K44: 741.75299 | L44: 761.37091 | M44: 754.85303 | N44: 739.60461 | O44: 742.00177 | P44: 740.44989 | Q44: 724.60852 | R44: 722.61212 | S44: 721.50848 | T44: 719.58472 | U44: 716.46832 | V44: 719.96906 | W44: 717.42847 | X44: 712.79492 | Y44: 712.05939 | Z44: 712.29938 | AA44: 710.03509 | AB44: 708.38904 | AC44: 708.26019 | AD44: 705.70605 | AE44: 703.53607 | AF44: 706.8219 | AG44: 703.31671 | AH44: 698.72473 | AI44: 701.90131 | AJ44: 695.80841 | AK44: 688.55414 | AL44: 0.001
A45: battery electric vehicle | B45: TST000:ha_100mileEV | C45: 100 Mile Electric Vehicle | D45: Light-Duty Vehicle Sales: Alternative-Fuel Light Trucks: 100 Mile Electric Vehicle: High oil and gas supply | E45: 48-AEO2021.36.highogs-d120120a | F45: thousands | G45: 0 | H45: 0 | I45: 0 | J45: 0 | K45: 0 | L45: 0 | M45: 0 | N45: 0 | O45: 0 | P45: 0 | Q45: 0 | R45: 0 | S45: 0 | T45: 0 | U45: 0 | V45: 0 | W45: 0 | X45: 0 | Y45: 0 | Z45: 0 | AA45: 0 | AB45: 0 | AC45: 0 | AD45: 0 | AE45: 0 | AF45: 0 | AG45: 0 | AH45: 0 | AI45: 0 | AJ45: 0 | AK45: 0 | AL45: - -
A46: battery electric vehicle | B46: TST000:ha_ElectricVehic | C46: 200 Mile Electric Vehicle | D46: Light-Duty Vehicle Sales: Alternative-Fuel Light Trucks: 200 Mile Electric Vehicle: High oil and gas supply | E46: 48-AEO2021.37.highogs-d120120a | F46: thousands | G46: 11.011377 | H46: 12.580558 | I46: 13.856382 | J46: 14.729568 | K46: 17.766371 | L46: 20.60214 | M46: 23.901951 | N46: 26.800146 | O46: 30.963303 | P46: 35.67075 | Q46: 39.973484 | R46: 45.244709 | S46: 51.161358 | T46: 57.174721 | U46: 63.200184 | V46: 69.40493 | W46: 75.094666 | X46: 80.330345 | Y46: 85.896759 | Z46: 91.319008 | AA46: 96.360229 | AB46: 101.13458 | AC46: 106.0079 | AD46: 110.53382 | AE46: 115.07858 | AF46: 120.59669 | AG46: 124.79433 | AH46: 128.80905 | AI46: 134.22469 | AJ46: 138.1029 | AK46: 141.6815 | AL46: 0.089
A47: battery electric vehicle | B47: TST000:ja_FuelCellGasol | C47: 300 Mile Electric Vehicle | D47: Light-Duty Vehicle Sales: Alternative-Fuel Light Trucks: 300 Mile Electric Vehicle: High oil and gas supply | E47: 48-AEO2021.38.highogs-d120120a | F47: thousands | G47: 25.837799 | H47: 31.257812 | I47: 36.313629 | J47: 41.621761 | K47: 48.076756 | L47: 52.63586 | M47: 55.501873 | N47: 60.360519 | O47: 68.817986 | P47: 78.638527 | Q47: 91.469398 | R47: 104.87369 | S47: 121.0077 | T47: 137.83313 | U47: 156.39168 | V47: 175.18623 | W47: 193.61909 | X47: 212.34343 | Y47: 232.89964 | Z47: 252.66898 | AA47: 272.35217 | AB47: 286.00415 | AC47: 298.94357 | AD47: 311.78906 | AE47: 325.64084 | AF47: 343.58066 | AG47: 357.28461 | AH47: 370.97598 | AI47: 388.95462 | AJ47: 404.65668 | AK47: 419.97311 | AL47: 0.097
A48: plugin hybrid vehicle | B48: TST000:ha_Plug-inGasoli | C48: Plug-in 10 Gasoline Hybrid | D48: Light-Duty Vehicle Sales: Alternative-Fuel Light Trucks: Plug-in 10 Gasoline Hybrid: High oil and gas supply | E48: 48-AEO2021.39.highogs-d120120a | F48: thousands | G48: 3.735878 | H48: 4.15414 | I48: 4.319993 | J48: 4.489612 | K48: 4.84607 | L48: 5.018435 | M48: 5.088077 | N48: 5.61109 | O48: 6.357627 | P48: 7.138061 | Q48: 7.837564 | R48: 8.649984 | S48: 9.527521 | T48: 10.36993 | U48: 11.207824 | V48: 12.104683 | W48: 12.992331 | X48: 13.974369 | Y48: 15.18399 | Z48: 16.544401 | AA48: 18.060143 | AB48: 19.723482 | AC48: 21.642765 | AD48: 23.778744 | AE48: 26.269089 | AF48: 29.479753 | AG48: 32.905865 | AH48: 36.874756 | AI48: 41.898773 | AJ48: 47.256931 | AK48: 53.308647 | AL48: 0.093
A49: plugin hybrid vehicle | B49: TST000:ha_Plug-in40Hybd | C49: Plug-in 40 Gasoline Hybrid | D49: Light-Duty Vehicle Sales: Alternative-Fuel Light Trucks: Plug-in 40 Gasoline Hybrid: High oil and gas supply | E49: 48-AEO2021.40.highogs-d120120a | F49: thousands | G49: 20.528244 | H49: 24.63999 | I49: 24.848988 | J49: 23.036037 | K49: 21.596161 | L49: 39.537579 | M49: 117.66729 | N49: 136.5762 | O49: 138.54099 | P49: 138.30026 | Q49: 138.9269 | R49: 141.40266 | S49: 145.65279 | T49: 149.34206 | U49: 152.88683 | V49: 156.19411 | W49: 157.88142 | X49: 159.08707 | Y49: 161.10991 | Z49: 162.46274 | AA49: 163.21619 | AB49: 162.86559 | AC49: 162.49562 | AD49: 161.73109 | AE49: 161.12625 | AF49: 161.92609 | AG49: 160.60345 | AH49: 158.96166 | AI49: 158.86812 | AJ49: 157.11867 | AK49: 154.92442 | AL49: 0.07
A50: diesel vehicle | B50: TST000:ha_Electric-Dies | C50: Electric-Diesel Hybrid | D50: Light-Duty Vehicle Sales: Alternative-Fuel Light Trucks: Electric-Diesel Hybrid: High oil and gas supply | E50: 48-AEO2021.41.highogs-d120120a | F50: thousands | G50: 0 | H50: 0 | I50: 0 | J50: 0 | K50: 0 | L50: 0 | M50: 0 | N50: 0 | O50: 0 | P50: 0 | Q50: 0 | R50: 0 | S50: 0 | T50: 0 | U50: 0 | V50: 0 | W50: 0 | X50: 0 | Y50: 0 | Z50: 0 | AA50: 0 | AB50: 0 | AC50: 0 | AD50: 0 | AE50: 0 | AF50: 0 | AG50: 0 | AH50: 0 | AI50: 0 | AJ50: 0 | AK50: 0 | AL50: - -
A51: gasoline vehicle | B51: TST000:ha_Electric-Gaso | C51: Electric-Gasoline Hybrid | D51: Light-Duty Vehicle Sales: Alternative-Fuel Light Trucks: Electric-Gasoline Hybrid: High oil and gas supply | E51: 48-AEO2021.42.highogs-d120120a | F51: thousands | G51: 216.35252 | H51: 258.38602 | I51: 276.32822 | J51: 286.79895 | K51: 303.40158 | L51: 318.14313 | M51: 371.40854 | N51: 393.50906 | O51: 407.98377 | P51: 419.66553 | Q51: 430.00949 | R51: 443.32437 | S51: 459.16483 | T51: 473.46197 | U51: 488.19302 | V51: 503.16168 | W51: 514.92602 | X51: 525.28986 | Y51: 539.41119 | Z51: 552.56995 | AA51: 564.76416 | AB51: 576.14087 | AC51: 588.35791 | AD51: 599.37817 | AE51: 611.1803 | AF51: 628.86725 | AG51: 639.23828 | AH51: 649.35614 | AI51: 666.44373 | AJ51: 676.7312 | AK51: 685.68152 | AL51: 0.039
A52: natural gas vehicle | B52: TST000:ha_CompressedNat | C52: Natural Gas ICE | D52: Light-Duty Vehicle Sales: Alternative-Fuel Light Trucks: Natural Gas ICE: High oil and gas supply | E52: 48-AEO2021.43.highogs-d120120a | F52: thousands | G52: 0.87621 | H52: 0.99396 | I52: 1.051358 | J52: 1.104043 | K52: 1.17157 | L52: 1.219613 | M52: 1.229416 | N52: 1.212275 | O52: 1.219368 | P52: 1.217389 | Q52: 1.198273 | R52: 1.197488 | S52: 1.201549 | T52: 1.203048 | U52: 1.20606 | V52: 1.214379 | W52: 1.215034 | X52: 1.212165 | Y52: 1.217994 | Z52: 1.223647 | AA52: 1.226083 | AB52: 1.228431 | AC52: 1.232571 | AD52: 1.233757 | AE52: 1.236186 | AF52: 1.249331 | AG52: 1.248434 | AH52: 1.247343 | AI52: 1.25969 | AJ52: 1.257967 | AK52: 1.254231 | AL52: 0.012
A53: natural gas vehicle | B53: TST000:ia_CompressedNat | C53: Natural Gas Bi-fuel | D53: Light-Duty Vehicle Sales: Alternative-Fuel Light Trucks: Natural Gas Bi-fuel: High oil and gas supply | E53: 48-AEO2021.44.highogs-d120120a | F53: thousands | G53: 4.78173 | H53: 5.351117 | I53: 5.552428 | J53: 5.691225 | K53: 5.91367 | L53: 6.088209 | M53: 6.102009 | N53: 6.004095 | O53: 6.035657 | P53: 6.033197 | Q53: 5.919284 | R53: 5.918518 | S53: 5.928925 | T53: 5.931232 | U53: 5.925938 | V53: 5.971416 | W53: 5.971017 | X53: 5.947062 | Y53: 5.960375 | Z53: 5.981478 | AA53: 5.980885 | AB53: 5.981805 | AC53: 5.99493 | AD53: 5.989414 | AE53: 5.98766 | AF53: 6.03448 | AG53: 6.021496 | AH53: 6.00085 | AI53: 6.047012 | AJ53: 6.016849 | AK53: 5.976843 | AL53: 0.007
A54: LPG vehicle | B54: TST000:ia_LiquefiedPetr | C54: Propane ICE | D54: Light-Duty Vehicle Sales: Alternative-Fuel Light Trucks: Propane ICE: High oil and gas supply | E54: 48-AEO2021.45.highogs-d120120a | F54: thousands | G54: 0.896776 | H54: 1.05261 | I54: 1.111326 | J54: 1.151744 | K54: 1.203437 | L54: 1.242741 | M54: 1.266402 | N54: 1.268268 | O54: 1.290204 | P54: 1.307028 | Q54: 1.301395 | R54: 1.309787 | S54: 1.32857 | T54: 1.345282 | U54: 1.369719 | V54: 1.390582 | W54: 1.403345 | X54: 1.413517 | Y54: 1.437301 | Z54: 1.460814 | AA54: 1.48447 | AB54: 1.50961 | AC54: 1.535431 | AD54: 1.565146 | AE54: 1.59473 | AF54: 1.645246 | AG54: 1.670202 | AH54: 1.696109 | AI54: 1.738963 | AJ54: 1.768739 | AK54: 1.797183 | AL54: 0.023
A55: LPG vehicle | B55: TST000:ja_LiquefiedPetr | C55: Propane Bi-fuel | D55: Light-Duty Vehicle Sales: Alternative-Fuel Light Trucks: Propane Bi-fuel: High oil and gas supply | E55: 48-AEO2021.46.highogs-d120120a | F55: thousands | G55: 3.090303 | H55: 3.458326 | I55: 3.588009 | J55: 3.677521 | K55: 3.820937 | L55: 3.933555 | M55: 3.942421 | N55: 3.87901 | O55: 3.899145 | P55: 3.897336 | Q55: 3.82362 | R55: 3.822982 | S55: 3.829474 | T55: 3.830739 | U55: 3.82691 | V55: 3.85623 | W55: 3.855715 | X55: 3.839862 | Y55: 3.848069 | Z55: 3.861467 | AA55: 3.860712 | AB55: 3.860967 | AC55: 3.869175 | AD55: 3.865335 | AE55: 3.863787 | AF55: 3.893517 | AG55: 3.884741 | AH55: 3.870961 | AI55: 3.900309 | AJ55: 3.880196 | AK55: 3.853823 | AL55: 0.007
A56: hydrogen vehicle | B56: TST000:ja_FuelCellMetha | C56: Fuel Cell Methanol | D56: Light-Duty Vehicle Sales: Alternative-Fuel Light Trucks: Fuel Cell Methanol: High oil and gas supply | E56: 48-AEO2021.47.highogs-d120120a | F56: thousands | G56: 0 | H56: 0 | I56: 0 | J56: 0 | K56: 0 | L56: 0 | M56: 0 | N56: 0 | O56: 0 | P56: 0 | Q56: 0 | R56: 0 | S56: 0 | T56: 0 | U56: 0 | V56: 0 | W56: 0 | X56: 0 | Y56: 0 | Z56: 0 | AA56: 0 | AB56: 0 | AC56: 0 | AD56: 0 | AE56: 0 | AF56: 0 | AG56: 0 | AH56: 0 | AI56: 0 | AJ56: 0 | AK56: 0 | AL56: - -
A57: hydrogen vehicle | B57: TST000:ja_FuelCellHydro | C57: Fuel Cell Hydrogen | D57: Light-Duty Vehicle Sales: Alternative-Fuel Light Trucks: Fuel Cell Hydrogen: High oil and gas supply | E57: 48-AEO2021.48.highogs-d120120a | F57: thousands | G57: 0.005264 | H57: 0.007763 | I57: 0.010618 | J57: 0.014217 | K57: 0.01919 | L57: 0.02647 | M57: 0.033589 | N57: 0.04159 | O57: 0.05206 | P57: 0.063929 | Q57: 0.076158 | R57: 0.090309 | S57: 0.105613 | T57: 0.121169 | U57: 0.13674 | V57: 0.152821 | W57: 0.167339 | X57: 0.180473 | Y57: 0.193919 | Z57: 0.20664 | AA57: 0.218224 | AB57: 0.229347 | AC57: 0.24035 | AD57: 0.250425 | AE57: 0.260603 | AF57: 0.273087 | AG57: 0.28232 | AH57: 0.291079 | AI57: 0.302643 | AJ57: 0.310832 | AK57: 0.31805 | AL57: 0.146
B58: TST000:ja_TotalAlternat | C58: Total Alternative Light Trucks | D58: Light-Duty Vehicle Sales: Alternative-Fuel Light Trucks: Total: High oil and gas supply | E58: 48-AEO2021.49.highogs-d120120a | F58: thousands | G58: 945.77661 | H58: 1014.5516 | I58: 1063.2103 | J58: 1096.4454 | K58: 1149.5688 | L58: 1209.8187 | M58: 1340.9945 | N58: 1374.8669 | O58: 1407.1617 | P58: 1432.382 | Q58: 1445.144 | R58: 1478.4467 | S58: 1520.4169 | T58: 1560.198 | U58: 1600.8132 | V58: 1648.6062 | W58: 1684.5546 | X58: 1716.413 | Y58: 1759.2184 | Z58: 1800.5984 | AA58: 1837.5584 | AB58: 1867.068 | AC58: 1898.5803 | AD58: 1925.821 | AE58: 1955.7743 | AF58: 2004.368 | AG58: 2031.2504 | AH58: 2056.8086 | AI58: 2105.5398 | AJ58: 2132.9094 | AK58: 2157.3237 | AL58: 0.028
B59: TST000:ka_PercentAltern | C59: Percent Alternative Light Truck Sales | D59: Light-Duty Vehicle Sales: Percent Alternative Light Truck Sales: High oil and gas supply | E59: 48-AEO2021.51.highogs-d120120a | F59: percent | G59: 12.603731 | H59: 12.086465 | I59: 12.209526 | J59: 12.28522 | K59: 12.397017 | L59: 12.673083 | M59: 14.016348 | N59: 14.606309 | O59: 14.8725 | P59: 15.146613 | Q59: 15.577128 | R59: 15.938383 | S59: 16.363634 | T59: 16.7866 | U59: 17.241961 | V59: 17.621176 | W59: 18.007923 | X59: 18.424269 | Y59: 18.843922 | Z59: 19.220327 | AA59: 19.619257 | AB59: 19.933451 | AC59: 20.227066 | AD59: 20.538624 | AE59: 20.867033 | AF59: 21.223494 | AG59: 21.556913 | AH59: 21.906378 | AI59: 22.256832 | AJ59: 22.663937 | AK59: 23.081156 | AL59: 0.02
B60: TST000:ka_TotalNewTruck | C60: Total New Light Truck Sales | D60: Light-Duty Vehicle Sales: Total New Truck: High oil and gas supply | E60: 48-AEO2021.52.highogs-d120120a | F60: thousands | G60: 7503.9414 | H60: 8394.1143 | I60: 8708.0391 | J60: 8924.915 | K60: 9272.9473 | L60: 9546.3652 | M60: 9567.3604 | N60: 9412.8291 | O60: 9461.501 | P60: 9456.7803 | Q60: 9277.3457 | R60: 9276.0137 | S60: 9291.4375 | T60: 9294.3057 | U60: 9284.4033 | V60: 9355.8242 | W60: 9354.5186 | X60: 9316.0439 | Y60: 9335.7334 | Z60: 9368.1982 | AA60: 9366.0957 | AB60: 9366.5068 | AC60: 9386.3359 | AD60: 9376.583 | AE60: 9372.5557 | AF60: 9444.1006 | AG60: 9422.7324 | AH60: 9389.0859 | AI60: 9460.1953 | AJ60: 9411.0273 | AK60: 9346.6885 | AL60: 0.007
B61: TST000:la_PercentTotalA | C61: Percent Total Alternative Sales | D61: Light-Duty Vehicle Sales: Percent Total Alternative Sales: High oil and gas supply | E61: 48-AEO2021.54.highogs-d120120a | F61: percent | G61: 10.525676 | H61: 10.205821 | I61: 10.303618 | J61: 10.468798 | K61: 10.682898 | L61: 10.995588 | M61: 12.012916 | N61: 12.589248 | O61: 13.007057 | P61: 13.377918 | Q61: 13.867725 | R61: 14.342594 | S61: 14.859269 | T61: 15.397581 | U61: 15.965017 | V61: 16.496569 | W61: 17.015959 | X61: 17.563627 | Y61: 18.121334 | Z61: 18.648632 | AA61: 19.184069 | AB61: 19.630735 | AC61: 20.046778 | AD61: 20.477114 | AE61: 20.930143 | AF61: 21.414234 | AG61: 21.890434 | AH61: 22.370344 | AI61: 22.860004 | AJ61: 23.398972 | AK61: 23.964218 | AL61: 0.028
B62: TST000:la_EPACTLegislat | C62: EPACT Legislative Alternative Sales | D62: Light-Duty Vehicle Sales: EPACT Legislative Alternative Sales: High oil and gas supply | E62: 48-AEO2021.55.highogs-d120120a | F62: thousands | G62: 80.883011 | H62: 90.649094 | I62: 97.449028 | J62: 101.7138 | K62: 108.75757 | L62: 115.22839 | M62: 119.69295 | N62: 122.76823 | O62: 129.10582 | P62: 135.23233 | Q62: 139.99101 | R62: 146.33977 | S62: 152.87483 | T62: 158.91075 | U62: 164.60355 | V62: 170.33884 | W62: 174.24127 | X62: 177.27837 | Y62: 181.0916 | Z62: 184.44444 | AA62: 186.99703 | AB62: 189.37363 | AC62: 191.77718 | AD62: 193.48735 | AE62: 195.30904 | AF62: 198.80876 | AG62: 199.94949 | AH62: 200.75169 | AI62: 203.64053 | AJ62: 204.13632 | AK62: 204.28915 | AL62: 0.031
B63: TST000:la_ZEVPLegislati | C63: ZEVP Legislative Alternative Sales | D63: Light-Duty Vehicle Sales: ZEVP Legislative Alternative Sales: High oil and gas supply | E63: 48-AEO2021.56.highogs-d120120a | F63: thousands | G63: 0 | H63: 0 | I63: 0 | J63: 0 | K63: 0 | L63: 0 | M63: 0 | N63: 0 | O63: 0 | P63: 0 | Q63: 0 | R63: 0 | S63: 0 | T63: 0 | U63: 0 | V63: 0 | W63: 0 | X63: 0 | Y63: 0 | Z63: 0 | AA63: 0 | AB63: 0 | AC63: 0 | AD63: 0 | AE63: 0 | AF63: 0 | AG63: 0 | AH63: 0 | AI63: 0 | AJ63: 0 | AK63: 0 | AL63: - -
C64: Total Sales | D64: Cars and Light Trucks | F64: 48-AEO2021.58.
B65: TST000:ta_ConventionGas | C65: Conventional Gasoline | D65: Light-Duty Vehicle Sales: Total Sales, Cars and Light Trucks: Conventional Gasoline: High oil and gas supply | E65: 48-AEO2021.59.highogs-d120120a | F65: thousands | G65: 10942.051 | H65: 12061.861 | I65: 12768.612 | J65: 12994.024 | K65: 13343.117 | L65: 13584.045 | M65: 13388.438 | N65: 13085.346 | O65: 13100.29 | P65: 13059.418 | Q65: 12867.778 | R65: 12812.703 | S65: 12778.74 | T65: 12725.466 | U65: 12671.221 | V65: 12655.05 | W65: 12537.341 | X65: 12394.869 | Y65: 12335.949 | Z65: 12269.731 | AA65: 12175.175 | AB65: 12097.82 | AC65: 12039.73 | AD65: 11946.957 | AE65: 11867.537 | AF65: 11890.537 | AG65: 11777.694 | AH65: 11648.64 | AI65: 11641.577 | AJ65: 11493.403 | AK65: 11326.559 | AL65: 0.001
B66: TST000:ta_TDIDiesel | C66: TDI Diesel | D66: Light-Duty Vehicle Sales: Total Sales, Cars and Light Trucks: TDI Diesel: High oil and gas supply | E66: 48-AEO2021.60.highogs-d120120a | F66: thousands | G66: 46.744987 | H66: 86.717842 | I66: 118.99736 | J66: 111.96023 | K66: 112.83137 | L66: 118.95527 | M66: 114.04425 | N66: 110.42281 | O66: 114.56205 | P66: 115.5425 | Q66: 113.62711 | R66: 113.97608 | S66: 116.01392 | T66: 115.89001 | U66: 119.07026 | V66: 119.28082 | W66: 121.36752 | X66: 120.28741 | Y66: 120.38907 | Z66: 122.76766 | AA66: 120.45693 | AB66: 120.48299 | AC66: 120.25109 | AD66: 119.98519 | AE66: 119.50639 | AF66: 120.97152 | AG66: 119.29042 | AH66: 118.38474 | AI66: 118.5109 | AJ66: 117.47234 | AK66: 115.80009 | AL66: 0.031
B67: TST000:ta_Flex-Fuel | C67: Flex-Fuel | D67: Light-Duty Vehicle Sales: Total Sales, Cars and Light Trucks: Flex-Fuel: High oil and gas supply | E67: 48-AEO2021.61.highogs-d120120a | F67: thousands | G67: 741.52612 | H67: 761.44757 | I67: 794.11713 | J67: 812.88049 | K67: 841.62915 | L67: 861.97113 | M67: 853.9223 | N67: 836.68494 | O67: 839.4541 | P67: 837.96906 | Q67: 822.4093 | R67: 820.42053 | S67: 819.52374 | T67: 817.65137 | U67: 814.89404 | V67: 818.04877 | W67: 814.32819 | X67: 808.63562 | Y67: 807.59265 | Z67: 807.14594 | AA67: 804.11517 | AB67: 801.85773 | AC67: 801.11798 | AD67: 797.7569 | AE67: 795.00549 | AF67: 798.67047 | AG67: 794.20099 | AH67: 788.526 | AI67: 791.47217 | AJ67: 784.27527 | AK67: 775.80414 | AL67: 0.002
B68: TST000:ta_PlugElectric | C68: Electric | D68: Light-Duty Vehicle Sales: Total Sales, Cars and Light Trucks: Electric: High oil and gas supply | E68: 48-AEO2021.62.highogs-d120120a | F68: thousands | G68: 149.72099 | H68: 146.62964 | I68: 164.22925 | J68: 174.55832 | K68: 189.21509 | L68: 200.48154 | M68: 212.06589 | N68: 227.0219 | O68: 254.38696 | P68: 285.69641 | Q68: 325.16159 | R68: 371.09552 | S68: 420.95209 | T68: 476.18491 | U68: 536.15985 | V68: 597.21497 | W68: 651.16888 | X68: 707.03863 | Y68: 769.55023 | Z68: 829.25708 | AA68: 886.46777 | AB68: 930.53937 | AC68: 972.78314 | AD68: 1013.1821 | AE68: 1057.4216 | AF68: 1114.9769 | AG68: 1159.2582 | AH68: 1200.5282 | AI68: 1255.7728 | AJ68: 1301.0726 | AK68: 1347.4221 | AL68: 0.076
B69: TST000:ta_PluginHybrid | C69: Plug-in Electric Hybrid | D69: Light-Duty Vehicle Sales: Total Sales, Cars and Light Trucks: Plug-in Electric Hybrid: High oil and gas supply | E69: 48-AEO2021.63.highogs-d120120a | F69: thousands | G69: 50.24918 | H69: 62.601456 | I69: 68.361328 | J69: 69.090996 | K69: 72.821815 | L69: 97.536247 | M69: 182.16153 | N69: 209.63751 | O69: 223.66818 | P69: 227.8342 | Q69: 233.44058 | R69: 237.59985 | S69: 245.30843 | T69: 251.16927 | U69: 257.34348 | V69: 260.68552 | W69: 262.24948 | X69: 263.34875 | Y69: 265.94437 | Z69: 267.01932 | AA69: 267.98041 | AB69: 267.13684 | AC69: 266.31342 | AD69: 265.40338 | AE69: 265.18543 | AF69: 268.03763 | AG69: 267.40503 | AH69: 267.16458 | AI69: 270.04047 | AJ69: 271.38596 | AK69: 272.71597 | AL69: 0.058
B70: TST000:ta_ElectricHybrd | C70: Electric Hybrid | D70: Light-Duty Vehicle Sales: Total Sales, Cars and Light Trucks: Electric Hybrid: High oil and gas supply | E70: 48-AEO2021.64.highogs-d120120a | F70: thousands | G70: 337.74976 | H70: 395.29581 | I70: 437.94873 | J70: 459.6991 | K70: 488.88922 | L70: 515.52167 | M70: 577.94104 | N70: 609.95471 | O70: 640.95709 | P70: 665.74487 | Q70: 691.68256 | R70: 717.84759 | S70: 747.04871 | T70: 774.35492 | U70: 803.62286 | V70: 829.62311 | W70: 849.84772 | X70: 869.34857 | Y70: 895.56598 | Z70: 919.10761 | AA70: 941.85327 | AB70: 966.49347 | AC70: 990.22009 | AD70: 1012.4028 | AE70: 1036.8658 | AF70: 1072.614 | AG70: 1094.5089 | AH70: 1115.8781 | AI70: 1148.7867 | AJ70: 1171.0525 | AK70: 1191.4612 | AL70: 0.043
B71: TST000:ta_GassyGaseous | C71: Gaseous (Propane and Natural Gas) | D71: Light-Duty Vehicle Sales: Total Sales, Cars and Light Trucks: Gaseous: High oil and gas supply | E71: 48-AEO2021.65.highogs-d120120a | F71: thousands | G71: 13.282132 | H71: 14.615747 | I71: 15.541418 | J71: 15.980041 | K71: 16.559818 | L71: 16.997454 | M71: 16.999275 | N71: 16.745153 | O71: 16.864073 | P71: 16.887737 | Q71: 16.689655 | R71: 16.733006 | S71: 16.794474 | T71: 16.841969 | U71: 16.899963 | V71: 17.01865 | W71: 16.990221 | X71: 16.927872 | Y71: 16.989555 | Z71: 17.046829 | AA71: 17.056164 | AB71: 17.07863 | AC71: 17.122871 | AD71: 17.127266 | AE71: 17.151009 | AF71: 17.336123 | AG71: 17.319502 | AH71: 17.280302 | AI71: 17.426506 | AJ71: 17.374092 | AK71: 17.30246 | AL71: 0.009
B72: TST000:ta_FuelCell | C72: Fuel Cell | D72: Light-Duty Vehicle Sales: Total Sales, Cars and Light Trucks: Fuel Cell: High oil and gas supply | E72: 48-AEO2021.66.highogs-d120120a | F72: thousands | G72: 0.183592 | H72: 0.192137 | I72: 0.229748 | J72: 0.261514 | K72: 0.302468 | L72: 0.358335 | M72: 0.409308 | N72: 0.463558 | O72: 0.534861 | P72: 0.609137 | Q72: 0.687017 | R72: 0.764566 | S72: 0.841996 | T72: 0.91534 | U72: 0.987169 | V72: 1.049125 | W72: 1.096141 | X72: 1.138755 | Y72: 1.185998 | Z72: 1.226098 | AA72: 1.26153 | AB72: 1.296925 | AC72: 1.331168 | AD72: 1.361268 | AE72: 1.394316 | AF72: 1.442371 | AG72: 1.471271 | AH72: 1.496705 | AI72: 1.537298 | AJ72: 1.56168 | AK72: 1.585036 | AL72: 0.074
B73: TST000:ma_TotalVehicles | C73: Total Vehicles Sales | D73: Light-Duty Vehicle Sales: Total Vehicles Sales: High oil and gas supply | E73: 48-AEO2021.67.highogs-d120120a | F73: thousands | G73: 12281.508 | H73: 13529.361 | I73: 14368.037 | J73: 14638.455 | K73: 15065.366 | L73: 15395.867 | M73: 15345.98 | N73: 15096.276 | O73: 15190.719 | P73: 15209.702 | Q73: 15071.477 | R73: 15091.14 | S73: 15145.225 | T73: 15178.475 | U73: 15220.198 | V73: 15297.973 | W73: 15254.389 | X73: 15181.594 | Y73: 15213.167 | Z73: 15233.303 | AA73: 15214.366 | AB73: 15202.707 | AC73: 15208.871 | AD73: 15174.176 | AE73: 15160.067 | AF73: 15284.586 | AG73: 15231.148 | AH73: 15157.898 | AI73: 15245.124 | AJ73: 15157.598 | AK73: 15048.65 | AL73: 0.007
B74: TST000:mh_ConventionGas | C74: Conventional Gasoline Microhybrids | D74: Light-Duty Vehicle Sales: Microhybrids: Conventional Gasoline: High oil and gas supply | E74: 48-AEO2021.70.highogs-d120120a | F74: thousands | G74: 4206.5107 | H74: 5090.7202 | I74: 5831.457 | J74: 6484.8428 | K74: 7171.3462 | L74: 7545.5952 | M74: 7690.3438 | N74: 7513.686 | O74: 7519.2173 | P74: 7493.8716 | Q74: 7390.2344 | R74: 7354.2939 | S74: 7334.5723 | T74: 7308.4927 | U74: 7301.7461 | V74: 7328.3877 | W74: 7319.8413 | X74: 7302.4863 | Y74: 7266.2422 | Z74: 7249.9067 | AA74: 7218.2168 | AB74: 7191.5996 | AC74: 7154.7363 | AD74: 7123.269 | AE74: 7097.7935 | AF74: 7115.3486 | AG74: 7052.8403 | AH74: 7000.5347 | AI74: 7014.5352 | AJ74: 6932.793 | AK74: 6848.6294 | AL74: 0.016
B75: TST000:mh_TDIDiesel | C75: TDI Diesel Microhybrids | D75: Light-Duty Vehicle Sales: Microhybrids: TDI Diesel: High oil and gas supply | E75: 48-AEO2021.71.highogs-d120120a | F75: thousands | G75: 0 | H75: 0 | I75: 0 | J75: 0 | K75: 0 | L75: 0 | M75: 0 | N75: 0 | O75: 0 | P75: 0 | Q75: 0 | R75: 0 | S75: 0 | T75: 0 | U75: 0 | V75: 0 | W75: 0 | X75: 0 | Y75: 0 | Z75: 0 | AA75: 0 | AB75: 0 | AC75: 0 | AD75: 0 | AE75: 0 | AF75: 0 | AG75: 0 | AH75: 0 | AI75: 0 | AJ75: 0 | AK75: 0 | AL75: - -
B76: TST000: | C76: Total Alternative-Fueled Vehicle Sales | D76: Light-Duty Vehicle Sales: Alternative-Fueled Vehicles: High oil and gas supply | E76: 48-AEO2021.80.highogs-d120120a | F76: thousands | G76: 5545.9668 | H76: 6558.2207 | I76: 7430.8818 | J76: 8129.2725 | K76: 8893.5957 | L76: 9357.416 | M76: 9647.8867 | N76: 9524.6172 | O76: 9609.6436 | P76: 9644.1543 | Q76: 9593.9326 | R76: 9632.7305 | S76: 9701.0566 | T76: 9761.501 | U76: 9850.7246 | V76: 9971.3096 | W76: 10036.89 | X76: 10089.213 | Y76: 10143.461 | Z76: 10213.478 | AA76: 10257.407 | AB76: 10296.484 | AC76: 10323.875 | AD76: 10350.488 | AE76: 10390.324 | AF76: 10509.398 | AG76: 10506.294 | AH76: 10509.794 | AI76: 10618.083 | AJ76: 10596.987 | AK76: 10570.721 | AL76: 0.022

Sheet AEO 40
B1: ORIGINAL EIA CODE | G1: 2020 | H1: 2021 | I1: 2022 | J1: 2023 | K1: 2024 | L1: 2025 | M1: 2026 | N1: 2027 | O1: 2028 | P1: 2029 | Q1: 2030 | R1: 2031 | S1: 2032 | T1: 2033 | U1: 2034 | V1: 2035 | W1: 2036 | X1: 2037 | Y1: 2038 | Z1: 2039 | AA1: 2040 | AB1: 2041 | AC1: 2042 | AD1: 2043 | AE1: 2044 | AF1: 2045 | AG1: 2046 | AH1: 2047 | AI1: 2048 | AJ1: 2049 | AK1: 2050 | AL1: Growth (2020-2050)
B10: MPG000 | C10: Table 40. Light-Duty Vehicle Miles per Gallon by Technology Type
C11: https://www.eia.gov/outlooks/aeo/data/browser/#/?id=50-AEO2021&region=0-0&cases=highogs&start=2020&end=2050&f=A&linechart=highogs-d120120a.4-50-AEO2021&sourcekey=0
