Workbook

Sheet About
A1: DToPaSoVAbIC Domestic Taxes on Production as Share of Value Added by ISIC Code
A3: Source: | B3: 2020年全国投入产出表
B4: 国家统计局
B5: 2020
B6: https://data.stats.gov.cn/files/html/quickSearch/trcc/trcc01.html
A8: Notes
A9: “2020年全国投入产出表”是根据我国2020年全年投入产出表中竞争型和非竞争型两张表结合美国EPS模型总结出来42个部门的投入产出表。政府消费支出是根据“2020年全国投入产出表”中各行业政府消费支出数额乘以当年2020年人民币相对2012美元的汇率得出。
A10: 生产税净额占附加值的比重可以直接在“2020年全国投入产出表”求商得出。

Sheet 2020年全国投入产出表
A1: 2020年全国投入产出表
A2: (按当年生产者价格计算） （Data are calculated at producers' prices in 2020)
A3: 单位：万元
A4: 投入 产出 | C4: 部门名称 | AU4: 最终使用 | BE4: 进口 | BF4: 总产出
D5: 农林牧渔产品和服务 | E5: 煤炭开采和洗选产品 | F5: 石油和天然气开采产品 | G5: 金属矿采选产品&非金属矿 | H5: 开采辅助活动和其他采矿产品 | I5: 食品和烟草 | J5: 纺织品、纺织服装鞋帽皮革羽绒及其制品 | K5: 木材加工品和家具 | L5: 造纸印刷和文教体育用品 | M5: 石油、炼焦产品和核燃料加工品 | N5: 化学原料和化学制品制造业&化学纤维制造业 | O5: 医药制造业 | P5: 橡胶和塑料制品业 | Q5: 非金属矿物制品 | R5: 黑色金属冶炼和压延加工品 | S5: 有色金属冶炼和压延加工品 | T5: 金属制品 | U5: 通用设备 | V5: 专用设备 | W5: 汽车制造业 | X5: 铁路、船舶、航空航天和其他运输设备 | Y5: 电气机械和器材 | Z5: 通信设备、计算机和其他电子设备&仪器仪表 | AA5: 其他制造产品和废品废料、金属制品、机械和设备修理服务 | AB5: 电力、热力生产和供应 | AC5: 燃气生产和供应 | AD5: 水的生产和供应 | AE5: 建筑 | AF5: 批发和零售 | AG5: 交通运输、仓储和邮政 | AH5: 住宿和餐饮 | AI5: 信息传输、软件和信息技术服务 | AJ5: 金融 | AK5: 房地产 | AL5: 租赁和商务服务 | AM5: 研究和试验发展 | AN5: 综合技术服务 | AO5: 居民服务、修理和其他服务 | AP5: 教育 | AQ5: 卫生和社会工作 | AR5: 文化、体育和娱乐 | AS5: 水利、环境和公共设施管理、公共管理、社会保障和社会组织 | AT5: 中间使用合计 | AU5: 农村居民消费支出 | AV5: 城镇居民消费支出 | AW5: 居民消费支出 | AX5: 政府消费支出 | AY5: 消费支出合计 | AZ5: 固定资本形成总额 | BA5: 存货变动 | BB5: 资本形成总额 | BC5: 出口 | BD5: 最终使用合计
B6: 部门名称 | C6: 代码 | D6: ISIC 01T03 | E6: ISIC 05 | F6: ISIC 06 | G6: ISIC 07T08 | H6: ISIC 09 | I6: ISIC 10T12 | J6: ISIC 13T15 | K6: ISIC 16 | L6: ISIC 17T18 | M6: ISIC 19 | N6: ISIC 20 | O6: ISIC 21 | P6: ISIC 22 | Q6: ISIC 231 | R6: ISIC 241 | S6: ISIC 242 | T6: ISIC 25 | U6: ISIC 28 | V6: ISIC 239 | W6: ISIC 29 | X6: ISIC 30 | Y6: ISIC 27 | Z6: ISIC 26 | AA6: ISIC 31T33 | AB6: ISIC 351 | AC6: ISIC 352T353 | AD6: ISIC 36T39 | AE6: ISIC 41T43 | AF6: ISIC 45T47 | AG6: ISIC 49T53 | AH6: ISIC 55T56 | AI6: ISIC 58T60 | AJ6: ISIC 64T66 | AK6: ISIC 68 | AL6: ISIC 61 | AM6: ISIC 64T66 | AN6: ISIC 69T82 | AO6: ISIC 97T98 | AP6: ISIC 85 | AQ6: ISIC 86T88 | AR6: ISIC 90T96 | AS6: ISIC 84 | AT6: TIU | AU6: FU101 | AV6: FU102 | AW6: THC | AX6: FU103 | AY6: TC | AZ6: FU201 | BA6: FU202 | BB6: GCF | BC6: EX | BD6: TFU | BE6: IM | BF6: GO
A7: 增加值 | B7: 劳动者报酬 | C7: VA001 | D7: 8.2110938e+08 | E7: 49156976 | F7: 10684587 | G7: 34146732 | H7: 9070894.8 | I7: 92288060 | J7: 78070179 | K7: 25339701 | L7: 70607745 | M7: 12815275 | N7: 47509590 | O7: 30588661 | P7: 35944267 | Q7: 74959952 | R7: 39116759 | S7: 35418934 | T7: 57488356 | U7: 46988960 | V7: 51031136 | W7: 36758514 | X7: 17700419 | Y7: 47111754 | Z7: 1.0033013e+08 | AA7: 25541968 | AB7: 61395231 | AC7: 7256304.2 | AD7: 8632889.8 | AE7: 4.6964543e+08 | AF7: 5.197925e+08 | AG7: 2.3052393e+08 | AH7: 85067117 | AI7: 2.0697374e+08 | AJ7: 2.1528198e+08 | AK7: 1.9273312e+08 | AL7: 2.5275721e+08 | AM7: 65841577 | AN7: 1.1541846e+08 | AO7: 1.2768977e+08 | AP7: 2.8165049e+08 | AQ7: 1.7178319e+08 | AR7: 51172540 | AS7: 4.0760071e+08 | AT7: 5.2956554e+09
B8: 生产税净额 | C8: VA002 | D8: -45528241 | E8: 23728884 | F8: 26393586 | G8: 29203561 | H8: 1127941.3 | I8: 82927930 | J8: 1055456.5 | K8: 5439494.6 | L8: 11735860 | M8: 49155196 | N8: 37768625 | O8: 11543782 | P8: 9432919.7 | Q8: 23472867 | R8: 16809804 | S8: 20103753 | T8: 11219547 | U8: 16723538 | V8: 14548977 | W8: 41488606 | X8: 2028722 | Y8: 4541468.5 | Z8: -3678836.3 | AA8: 13432368 | AB8: 20698378 | AC8: 1010550.5 | AD8: 1860447.2 | AE8: 98116386 | AF8: 95383190 | AG8: 8513567.4 | AH8: 1360038.7 | AI8: 13092894 | AJ8: 82718116 | AK8: 1.2344272e+08 | AL8: 27690531 | AM8: 1588413.6 | AN8: 11715875 | AO8: 5023484.2 | AP8: 625840.59 | AQ8: 119102.01 | AR8: 1590021 | AS8: 2016363.5 | AT8: 8.9580223e+08
B9: 固定资产折旧 | C9: VA003 | D9: 23048580 | E9: 11857467 | F9: 23934532 | G9: 14045535 | H9: 881427.49 | I9: 30616039 | J9: 17159912 | K9: 7115541.2 | L9: 23476685 | M9: 11540323 | N9: 37261753 | O9: 7442373.5 | P9: 13681348 | Q9: 36252425 | R9: 31732256 | S9: 20256127 | T9: 17451920 | U9: 16689439 | V9: 12133973 | W9: 15404030 | X9: 3816835 | Y9: 15983410 | Z9: 35286960 | AA9: 6722131.4 | AB9: 97784316 | AC9: 5463404 | AD9: 6900167.1 | AE9: 27714364 | AF9: 1.1846713e+08 | AG9: 2.0022194e+08 | AH9: 46183808 | AI9: 1.2669418e+08 | AJ9: 36197644 | AK9: 70284261 | AL9: 35220354 | AM9: 20894697 | AN9: 47257246 | AO9: 18811001 | AP9: 77784703 | AQ9: 31476065 | AR9: 19443052 | AS9: 92345943 | AT9: 1.5058198e+09
B10: 营业盈余 | C10: VA004 | D10: 23117527 | E10: 35255171 | F10: 6711085 | G10: 26913765 | H10: -2541340.5 | I10: 1.0118166e+08 | J10: 48190809 | K10: 17706882 | L10: 55330297 | M10: 27079971 | N10: 75473751 | O10: 36261214 | P10: 27380722 | Q10: 95894758 | R10: 68635495 | S10: 43798631 | T10: 41037940 | U10: 43686016 | V10: 20237211 | W10: 51825291 | X10: 8695606.9 | Y10: 53690206 | Z10: 59374527 | AA10: 51110402 | AB10: 38471081 | AC10: 5841588 | AD10: 3105561.8 | AE10: 1.2461676e+08 | AF10: 2.1996059e+08 | AG10: 17515502 | AH10: 12909620 | AI10: 1.0125364e+08 | AJ10: 5.0197366e+08 | AK10: 3.8320744e+08 | AL10: 2859006.3 | AM10: 7602478.7 | AN10: 10750979 | AO10: 5752421.8 | AP10: 13231126 | AQ10: 4827324.6 | AR10: 5804782 | AS10: 8918362 | AT10: 2.4669426e+09
B11: 增加值合计 | C11: TVA | D11: 8.2174724e+08 | E11: 1.199985e+08 | F11: 67723790 | G11: 1.0430959e+08 | H11: 8538923.1 | I11: 3.0701369e+08 | J11: 1.4447636e+08 | K11: 55601618 | L11: 1.6115059e+08 | M11: 1.0059076e+08 | N11: 1.9801372e+08 | O11: 85836030 | P11: 86439257 | Q11: 2.3058e+08 | R11: 1.5629431e+08 | S11: 1.1957745e+08 | T11: 1.2719776e+08 | U11: 1.2408795e+08 | V11: 97951296 | W11: 1.4547644e+08 | X11: 32241583 | Y11: 1.2132684e+08 | Z11: 1.9131278e+08 | AA11: 96806870 | AB11: 2.1834901e+08 | AC11: 19571847 | AD11: 20499066 | AE11: 7.2009294e+08 | AF11: 9.5360341e+08 | AG11: 4.5677494e+08 | AH11: 1.4552058e+08 | AI11: 4.4801444e+08 | AJ11: 8.3617139e+08 | AK11: 7.6966754e+08 | AL11: 3.185271e+08 | AM11: 95927166 | AN11: 1.8514256e+08 | AO11: 1.5727667e+08 | AP11: 3.7329216e+08 | AQ11: 2.0820568e+08 | AR11: 78010395 | AS11: 5.1088137e+08 | AT11: 1.016422e+10

Sheet DToPaSoVAbIC
A1: Unit: dimensionless (%) | B1: ISIC 01T03 | C1: ISIC 05 | D1: ISIC 06 | E1: ISIC 07T08 | F1: ISIC 09 | G1: ISIC 10T12 | H1: ISIC 13T15 | I1: ISIC 16 | J1: ISIC 17T18 | K1: ISIC 19 | L1: ISIC 20 | M1: ISIC 21 | N1: ISIC 22 | O1: ISIC 231 | P1: ISIC 239 | Q1: ISIC 241 | R1: ISIC 242 | S1: ISIC 25 | T1: ISIC 26 | U1: ISIC 27 | V1: ISIC 28 | W1: ISIC 29 | X1: ISIC 30 | Y1: ISIC 31T33 | Z1: ISIC 351 | AA1: ISIC 352T353 | AB1: ISIC 36T39 | AC1: ISIC 41T43 | AD1: ISIC 45T47 | AE1: ISIC 49T53 | AF1: ISIC 55T56 | AG1: ISIC 58T60 | AH1: ISIC 61 | AI1: ISIC 62T63 | AJ1: ISIC 64T66 | AK1: ISIC 68 | AL1: ISIC 69T82 | AM1: ISIC 84 | AN1: ISIC 85 | AO1: ISIC 86T88 | AP1: ISIC 90T96 | AQ1: ISIC 97T98
A2: Domestic Taxes as Share of Value Added | B2: ='2020年全国投入产出表'!$D$8/'2020年全国投入产出表'!$D$11 -> -0.05540419 | C2: ='2020年全国投入产出表'!$E$8/'2020年全国投入产出表'!$E$11 -> 0.19774318 | D2: ='2020年全国投入产出表'!$F$8/'2020年全国投入产出表'!$F$11 -> 0.389724 | E2: ='2020年全国投入产出表'!$G$8/'2020年全国投入产出表'!$G$11 -> 0.27997004 | F2: ='2020年全国投入产出表'!$H$8/'2020年全国投入产出表'!$H$11 -> 0.13209409 | G2: ='2020年全国投入产出表'!$I$8/'2020年全国投入产出表'!$I$11 -> 0.27011151 | H2: ='2020年全国投入产出表'!$J$8/'2020年全国投入产出表'!$J$11 -> 0.0073053927 | I2: ='2020年全国投入产出表'!$K$8/'2020年全国投入产出表'!$K$11 -> 0.097829789 | J2: ='2020年全国投入产出表'!$L$8/'2020年全国投入产出表'!$L$11 -> 0.072825423 | K2: ='2020年全国投入产出表'!$M$8/'2020年全国投入产出表'!$M$11 -> 0.4886651 | L2: ='2020年全国投入产出表'!$N$8/'2020年全国投入产出表'!$N$11 -> 0.19073742 | M2: ='2020年全国投入产出表'!$O$8/'2020年全国投入产出表'!$O$11 -> 0.13448643 | N2: ='2020年全国投入产出表'!$P$8/'2020年全国投入产出表'!$P$11 -> 0.10912773 | O2: ='2020年全国投入产出表'!$Q$8/'2020年全国投入产出表'!$Q$11 -> 0.10179923 | P2: ='2020年全国投入产出表'!$V$8/'2020年全国投入产出表'!$V$11 -> 0.14853276 | Q2: ='2020年全国投入产出表'!$R$8/'2020年全国投入产出表'!$R$11 -> 0.10755224 | R2: ='2020年全国投入产出表'!$S$8/'2020年全国投入产出表'!$S$11 -> 0.16812328 | S2: ='2020年全国投入产出表'!$T$8/'2020年全国投入产出表'!$T$11 -> 0.088205537 | T2: ='2020年全国投入产出表'!$Z$8/'2020年全国投入产出表'!$Z$11 -> -0.019229433 | U2: ='2020年全国投入产出表'!$Y$8/'2020年全国投入产出表'!$Y$11 -> 0.037431689 | V2: ='2020年全国投入产出表'!$U$8/'2020年全国投入产出表'!$U$11 -> 0.13477165 | W2: ='2020年全国投入产出表'!$W$8/'2020年全国投入产出表'!$W$11 -> 0.28519124 | X2: ='2020年全国投入产出表'!$X$8/'2020年全国投入产出表'!$X$11 -> 0.06292253 | Y2: ='2020年全国投入产出表'!$AA$8/'2020年全国投入产出表'!$AA$11 -> 0.13875429 | Z2: ='2020年全国投入产出表'!$AB$8/'2020年全国投入产出表'!$AB$11 -> 0.094794925 | AA2: ='2020年全国投入产出表'!$AC$8/'2020年全国投入产出表'!$AC$11 -> 0.051632862 | AB2: ='2020年全国投入产出表'!$AD$8/'2020年全国投入产出表'!$AD$11 -> 0.090757657 | AC2: ='2020年全国投入产出表'!$AE$8/'2020年全国投入产出表'!$AE$11 -> 0.13625517 | AD2: ='2020年全国投入产出表'!$AF$8/'2020年全国投入产出表'!$AF$11 -> 0.10002396 | AE2: ='2020年全国投入产出表'!$AG$8/'2020年全国投入产出表'!$AG$11 -> 0.018638429 | AF2: ='2020年全国投入产出表'!$AH$8/'2020年全国投入产出表'!$AH$11 -> 0.0093460226 | AG2: ='2020年全国投入产出表'!$AI$8/'2020年全国投入产出表'!$AI$11 -> 0.029224269 | AH2: ='2020年全国投入产出表'!$AL$8/'2020年全国投入产出表'!$AL$11 -> 0.086933044 | AI2: ='2020年全国投入产出表'!$AM$8/'2020年全国投入产出表'!$AM$11 -> 0.016558537 | AJ2: ='2020年全国投入产出表'!$AJ$8/'2020年全国投入产出表'!$AJ$11 -> 0.098924834 | AK2: ='2020年全国投入产出表'!$AK$8/'2020年全国投入产出表'!$AK$11 -> 0.16038447 | AL2: ='2020年全国投入产出表'!$AN$8/'2020年全国投入产出表'!$AN$11 -> 0.06328029 | AM2: ='2020年全国投入产出表'!$AS$8/'2020年全国投入产出表'!$AS$11 -> 0.0039468331 | AN2: ='2020年全国投入产出表'!$AP$8/'2020年全国投入产出表'!$AP$11 -> 0.0016765436 | AO2: ='2020年全国投入产出表'!$AQ$8/'2020年全国投入产出表'!$AQ$11 -> 0.00057204015 | AP2: ='2020年全国投入产出表'!$AR$8/'2020年全国投入产出表'!$AR$11 -> 0.020382169 | AQ2: ='2020年全国投入产出表'!$AO$8/'2020年全国投入产出表'!$AO$11 -> 0.031940428
B3: 农林牧渔产品和服务 | C3: 煤炭开采和洗选产品 | D3: 石油和天然气开采产品 | E3: 金属矿采选产品&非金属矿 | F3: 开采辅助活动和其他采矿产品 | G3: 食品和烟草 | H3: 纺织品、纺织服装鞋帽皮革羽绒及其制品 | I3: 木材加工品和家具 | J3: 造纸印刷和文教体育用品 | K3: 石油、炼焦产品和核燃料加工品 | L3: 化学原料和化学制品制造业&化学纤维制造业 | M3: 医药制造业 | N3: 橡胶和塑料制品业 | O3: 非金属矿物制品 | P3: 专用设备 | Q3: 黑色金属冶炼和压延加工品 | R3: 有色金属冶炼和压延加工品 | S3: 金属制品 | T3: 通信设备、计算机和其他电子设备&仪器仪表 | U3: 电气机械和器材 | V3: 通用设备 | W3: 汽车制造业 | X3: 铁路、船舶、航空航天和其他运输设备 | Y3: 其他制造产品和废品废料、金属制品、机械和设备修理服务 | Z3: 电力、热力生产和供应 | AA3: 燃气生产和供应 | AB3: 水的生产和供应 | AC3: 建筑 | AD3: 批发和零售 | AE3: 交通运输、仓储和邮政 | AF3: 住宿和餐饮 | AG3: 信息传输、软件和信息技术服务 | AH3: 租赁和商务服务 | AI3: 研究和试验发展 | AJ3: 金融 | AK3: 房地产 | AL3: 综合技术服务 | AM3: 水利、环境和公共设施管理、公共管理、社会保障和社会组织 | AN3: 教育 | AO3: 卫生和社会工作 | AP3: 文化、体育和娱乐 | AQ3: 居民服务、修理和其他服务
