Workbook

Sheet About
A1: 低情景-制氢产业增加值预测
B2: 2019 | C2: 2020-2025 | D2: 2026-2035 | E2: 2036-2050 | F2: 数据来源
A3: 产业产值(亿元) | B3: 3000 | C3: 10000 | D3: 50000 | E3: 120000 | F3: 中国氢能联盟
A4: 氢气制取成本(元/公斤) | B4: <20 | C4: <20 | D4: <15 | E4: <10 | F4: 中国氢能联盟
A5: 终端销售价格(元/公斤) | B5: 35 | C5: 30 | D5: 30 | E5: 20 | F5: https://new.qq.com/rain/a/20220609A02TW900;《中国氢能产业发展报告2020》
A6: 成本/终端售价(%) | B6: =20/35 -> 0.57142857 | C6: =20/30 -> 0.66666667 | D6: =15/30 -> 0.5 | E6: =10/20 -> 0.5
A7: 增加值（亿元) | B7: =B3-B3*B6 -> 1285.7143 | C7: =C3-C3*C6 -> 3333.3333 | D7: =D3-D3*D6 -> 25000 | E7: =E3-E3*E6 -> 60000
A8: 增加值增量(亿元) | B8: 0 | C8: =C7-B7 -> 2047.619 | D8: =D7-C7 -> 21666.667 | E8: =E7-D7 -> 35000

Sheet 情景假设
A1: 假设1：实际GDP年均增速
B2: 2020-2025 | C2: 2025-2030 | D2: 2030-2035 | E2: 2035-2040 | F2: 2040-2045 | G2: 2045-2050 | H2: 2050-2055 | I2: 2055-2060
A3: 高情景 | B3: 0.053258208 | C3: 0.049592697 | D3: 0.036428571 | E3: 0.03 | F3: 0.029 | G3: 0.028 | H3: 0.0265 | I3: 0.025
A4: 中情景 | B4: 0.053554477 | C4: 0.051198243 | D4: 0.038396035 | E4: 0.033 | F4: 0.0315 | G4: 0.03 | H4: 0.0285 | I4: 0.0265
A5: 低情景 | B5: 0.053718794 | C5: 0.051812646 | D5: 0.040696755 | E5: 0.036 | F5: 0.034 | G5: 0.032 | H5: 0.03 | I5: 0.028
A7: 结果1：实际GDP | B7: 步骤1：根据假设1计算2025、2030、2035和2060年实际GDP。步骤2：:将数据粘贴至"数据平滑/输入/假设1：GDP-2020年不变价.xlsx"；通过运行python代码假设1；结果保存至"数据平滑/输出/结果1：GDP数据平滑.xlsx"。步骤3：将Python结果粘贴至“Python数据平滑"sheet的对应位置，下方列表会自动更新。
A8: GDP（2020年不变价） | B8: 2020 | C8: 2021 | D8: 2022 | E8: 2023 | F8: 2024 | G8: 2025 | H8: 2026 | I8: 2027 | J8: 2028 | K8: 2029 | L8: 2030 | M8: 2031 | N8: 2032 | O8: 2033 | P8: 2034 | Q8: 2035 | R8: 2036 | S8: 2037 | T8: 2038 | U8: 2039 | V8: 2040 | W8: 2041 | X8: 2042 | Y8: 2043 | Z8: 2044 | AA8: 2045 | AB8: 2046 | AC8: 2047 | AD8: 2048 | AE8: 2049 | AF8: 2050 | AG8: 2051 | AH8: 2052 | AI8: 2053 | AJ8: 2054 | AK8: 2055 | AL8: 2056 | AM8: 2057 | AN8: 2058 | AO8: 2059 | AP8: 2060
A9: 高情景 | B9: 1013567 | C9: 1098706.6 | D9: 1131667.8 | E9: =VLOOKUP($A9,Python数据平滑!$A$2:$AN$5,COLUMN(Python数据平滑!C$2),0) -> 1193070.7 | F9: =VLOOKUP($A9,Python数据平滑!$A$2:$AN$5,COLUMN(Python数据平滑!D$2),0) -> 1256709.5 | G9: =D9*(1+B3)^3 -> 1322280.3 | H9: =VLOOKUP($A9,Python数据平滑!$A$2:$AN$5,COLUMN(Python数据平滑!F$2),0) -> 1391094.7 | I9: =VLOOKUP($A9,Python数据平滑!$A$2:$AN$5,COLUMN(Python数据平滑!G$2),0) -> 1463691.4 | J9: =VLOOKUP($A9,Python数据平滑!$A$2:$AN$5,COLUMN(Python数据平滑!H$2),0) -> 1538282.7 | K9: =VLOOKUP($A9,Python数据平滑!$A$2:$AN$5,COLUMN(Python数据平滑!I$2),0) -> 1612689.6 | L9: =G9*(1+C3)^5 -> 1684331.3 | M9: =VLOOKUP($A9,Python数据平滑!$A$2:$AN$5,COLUMN(Python数据平滑!K$2),0) -> 1752648.1 | N9: =VLOOKUP($A9,Python数据平滑!$A$2:$AN$5,COLUMN(Python数据平滑!L$2),0) -> 1819256.8 | O9: =VLOOKUP($A9,Python数据平滑!$A$2:$AN$5,COLUMN(Python数据平滑!M$2),0) -> 1884644.2 | P9: =VLOOKUP($A9,Python数据平滑!$A$2:$AN$5,COLUMN(Python数据平滑!N$2),0) -> 1949417.4 | Q9: =L9*(1+D3)^5 -> 2014301.2 | R9: =VLOOKUP($A9,Python数据平滑!$A$2:$AN$5,COLUMN(Python数据平滑!P$2),0) -> 2078635.3 | S9: =VLOOKUP($A9,Python数据平滑!$A$2:$AN$5,COLUMN(Python数据平滑!Q$2),0) -> 2141814.9 | T9: =VLOOKUP($A9,Python数据平滑!$A$2:$AN$5,COLUMN(Python数据平滑!R$2),0) -> 2204840.9 | U9: =VLOOKUP($A9,Python数据平滑!$A$2:$AN$5,COLUMN(Python数据平滑!S$2),0) -> 2268851.9 | V9: =Q9*(1+E3)^5 -> 2335127.2 | W9: =VLOOKUP($A9,Python数据平滑!$A$2:$AN$5,COLUMN(Python数据平滑!U$2),0) -> 2403770.6 | X9: =VLOOKUP($A9,Python数据平滑!$A$2:$AN$5,COLUMN(Python数据平滑!V$2),0) -> 2473965.9 | Y9: =VLOOKUP($A9,Python数据平滑!$A$2:$AN$5,COLUMN(Python数据平滑!W$2),0) -> 2545721.3 | Z9: =VLOOKUP($A9,Python数据平滑!$A$2:$AN$5,COLUMN(Python数据平滑!X$2),0) -> 2619043.3 | AA9: =V9*(1+F3)^5 -> 2693936.8 | AB9: =VLOOKUP($A9,Python数据平滑!$A$2:$AN$5,COLUMN(Python数据平滑!Z$2),0) -> 2770546.3 | AC9: =VLOOKUP($A9,Python数据平滑!$A$2:$AN$5,COLUMN(Python数据平滑!AA$2),0) -> 2848914.1 | AD9: =VLOOKUP($A9,Python数据平滑!$A$2:$AN$5,COLUMN(Python数据平滑!AB$2),0) -> 2928875 | AE9: =VLOOKUP($A9,Python数据平滑!$A$2:$AN$5,COLUMN(Python数据平滑!AC$2),0) -> 3010242.7 | AF9: =AA9*(1+G3)^5 -> 3092808.1 | AG9: =VLOOKUP($A9,Python数据平滑!$A$2:$AN$5,COLUMN(Python数据平滑!AE$2),0) -> 3176593.4 | AH9: =VLOOKUP($A9,Python数据平滑!$A$2:$AN$5,COLUMN(Python数据平滑!AF$2),0) -> 3261743.4 | AI9: =VLOOKUP($A9,Python数据平滑!$A$2:$AN$5,COLUMN(Python数据平滑!AG$2),0) -> 3348213.3 | AJ9: =VLOOKUP($A9,Python数据平滑!$A$2:$AN$5,COLUMN(Python数据平滑!AH$2),0) -> 3435953.1 | AK9: =AF9*(1+H3)^5 -> 3524907.7 | AL9: =VLOOKUP($A9,Python数据平滑!$A$2:$AN$5,COLUMN(Python数据平滑!AJ$2),0) -> 3615095.8 | AM9: =VLOOKUP($A9,Python数据平滑!$A$2:$AN$5,COLUMN(Python数据平滑!AK$2),0) -> 3706550.8 | AN9: =VLOOKUP($A9,Python数据平滑!$A$2:$AN$5,COLUMN(Python数据平滑!AL$2),0) -> 3799233.8 | AO9: =VLOOKUP($A9,Python数据平滑!$A$2:$AN$5,COLUMN(Python数据平滑!AM$2),0) -> 3893102 | AP9: =AK9*(1+I3)^5 -> 3988109.5 | AQ9: =AP9/B9 -> 3.9347271
A10: 中情景 | B10: 1013567 | C10: 1098706.6 | D10: 1131667.8 | E10: =VLOOKUP($A10,Python数据平滑!$A$2:$AN$5,COLUMN(Python数据平滑!C$2),0) -> 1192997.2 | F10: =VLOOKUP($A10,Python数据平滑!$A$2:$AN$5,COLUMN(Python数据平滑!D$2),0) -> 1256946.5 | G10: =D10*(1+B4)^3 -> 1323396.4 | H10: =VLOOKUP($A10,Python数据平滑!$A$2:$AN$5,COLUMN(Python数据平滑!F$2),0) -> 1393766.9 | I10: =VLOOKUP($A10,Python数据平滑!$A$2:$AN$5,COLUMN(Python数据平滑!G$2),0) -> 1468542.8 | J10: =VLOOKUP($A10,Python数据平滑!$A$2:$AN$5,COLUMN(Python数据平滑!H$2),0) -> 1545878.3 | K10: =VLOOKUP($A10,Python数据平滑!$A$2:$AN$5,COLUMN(Python数据平滑!I$2),0) -> 1623499.4 | L10: =G10*(1+C4)^5 -> 1698685.9 | M10: =VLOOKUP($A10,Python数据平滑!$A$2:$AN$5,COLUMN(Python数据平滑!K$2),0) -> 1770660.5 | N10: =VLOOKUP($A10,Python数据平滑!$A$2:$AN$5,COLUMN(Python数据平滑!L$2),0) -> 1841070.2 | O10: =VLOOKUP($A10,Python数据平滑!$A$2:$AN$5,COLUMN(Python数据平滑!M$2),0) -> 1910626.4 | P10: =VLOOKUP($A10,Python数据平滑!$A$2:$AN$5,COLUMN(Python数据平滑!N$2),0) -> 1980200.7 | Q10: =L10*(1+D4)^5 -> 2050823.1 | R10: =VLOOKUP($A10,Python数据平滑!$A$2:$AN$5,COLUMN(Python数据平滑!P$2),0) -> 2122024.8 | S10: =VLOOKUP($A10,Python数据平滑!$A$2:$AN$5,COLUMN(Python数据平滑!Q$2),0) -> 2192996 | T10: =VLOOKUP($A10,Python数据平滑!$A$2:$AN$5,COLUMN(Python数据平滑!R$2),0) -> 2264458 | U10: =VLOOKUP($A10,Python数据平滑!$A$2:$AN$5,COLUMN(Python数据平滑!S$2),0) -> 2337241.7 | V10: =Q10*(1+E4)^5 -> 2412291.6 | W10: =VLOOKUP($A10,Python数据平滑!$A$2:$AN$5,COLUMN(Python数据平滑!U$2),0) -> 2489706.4 | X10: =VLOOKUP($A10,Python数据平滑!$A$2:$AN$5,COLUMN(Python数据平滑!V$2),0) -> 2568890.5 | Y10: =VLOOKUP($A10,Python数据平滑!$A$2:$AN$5,COLUMN(Python数据平滑!W$2),0) -> 2649832.9 | Z10: =VLOOKUP($A10,Python数据平滑!$A$2:$AN$5,COLUMN(Python数据平滑!X$2),0) -> 2732518.9 | AA10: =V10*(1+F4)^5 -> 2816929.4 | AB10: =VLOOKUP($A10,Python数据平滑!$A$2:$AN$5,COLUMN(Python数据平滑!Z$2),0) -> 2903103.3 | AC10: =VLOOKUP($A10,Python数据平滑!$A$2:$AN$5,COLUMN(Python数据平滑!AA$2),0) -> 2991081.3 | AD10: =VLOOKUP($A10,Python数据平滑!$A$2:$AN$5,COLUMN(Python数据平滑!AB$2),0) -> 3080841.1 | AE10: =VLOOKUP($A10,Python数据平滑!$A$2:$AN$5,COLUMN(Python数据平滑!AC$2),0) -> 3172355.6 | AF10: =AA10*(1+G4)^5 -> 3265593.3 | AG10: =VLOOKUP($A10,Python数据平滑!$A$2:$AN$5,COLUMN(Python数据平滑!AE$2),0) -> 3360731.8 | AH10: =VLOOKUP($A10,Python数据平滑!$A$2:$AN$5,COLUMN(Python数据平滑!AF$2),0) -> 3457824.4 | AI10: =VLOOKUP($A10,Python数据平滑!$A$2:$AN$5,COLUMN(Python数据平滑!AG$2),0) -> 3556626.7 | AJ10: =VLOOKUP($A10,Python数据平滑!$A$2:$AN$5,COLUMN(Python数据平滑!AH$2),0) -> 3656864.3 | AK10: =AF10*(1+H4)^5 -> 3758231.9 | AL10: =VLOOKUP($A10,Python数据平滑!$A$2:$AN$5,COLUMN(Python数据平滑!AJ$2),0) -> 3860743.6 | AM10: =VLOOKUP($A10,Python数据平滑!$A$2:$AN$5,COLUMN(Python数据平滑!AK$2),0) -> 3964585.3 | AN10: =VLOOKUP($A10,Python数据平滑!$A$2:$AN$5,COLUMN(Python数据平滑!AL$2),0) -> 4069680.9 | AO10: =VLOOKUP($A10,Python数据平滑!$A$2:$AN$5,COLUMN(Python数据平滑!AM$2),0) -> 4175948.1 | AP10: =AK10*(1+I4)^5 -> 4283298.5 | AQ10: =AP10/B10 -> 4.2259648
A11: 低情景 | B11: 1013567 | C11: 1098706.6 | D11: 1131667.8 | E11: =VLOOKUP($A11,Python数据平滑!$A$2:$AN$5,COLUMN(Python数据平滑!C$2),0) -> 1193043.8 | F11: =VLOOKUP($A11,Python数据平滑!$A$2:$AN$5,COLUMN(Python数据平滑!D$2),0) -> 1257179.2 | G11: =D11*(1+B5)^3 -> 1324015.7 | H11: =VLOOKUP($A11,Python数据平滑!$A$2:$AN$5,COLUMN(Python数据平滑!F$2),0) -> 1394801 | I11: =VLOOKUP($A11,Python数据平滑!$A$2:$AN$5,COLUMN(Python数据平滑!G$2),0) -> 1469972.4 | J11: =VLOOKUP($A11,Python数据平滑!$A$2:$AN$5,COLUMN(Python数据平滑!H$2),0) -> 1547981.5 | K11: =VLOOKUP($A11,Python数据平滑!$A$2:$AN$5,COLUMN(Python数据平滑!I$2),0) -> 1626911.1 | L11: =G11*(1+C5)^5 -> 1704453.2 | M11: =VLOOKUP($A11,Python数据平滑!$A$2:$AN$5,COLUMN(Python数据平滑!K$2),0) -> 1779831.6 | N11: =VLOOKUP($A11,Python数据平滑!$A$2:$AN$5,COLUMN(Python数据平滑!L$2),0) -> 1854381.9 | O11: =VLOOKUP($A11,Python数据平滑!$A$2:$AN$5,COLUMN(Python数据平滑!M$2),0) -> 1928788.7 | P11: =VLOOKUP($A11,Python数据平滑!$A$2:$AN$5,COLUMN(Python数据平滑!N$2),0) -> 2003890.8 | Q11: =L11*(1+D5)^5 -> 2080683.8 | R11: =VLOOKUP($A11,Python数据平滑!$A$2:$AN$5,COLUMN(Python数据平滑!P$2),0) -> 2158866.1 | S11: =VLOOKUP($A11,Python数据平滑!$A$2:$AN$5,COLUMN(Python数据平滑!Q$2),0) -> 2237676.8 | T11: =VLOOKUP($A11,Python数据平滑!$A$2:$AN$5,COLUMN(Python数据平滑!R$2),0) -> 2317603.2 | U11: =VLOOKUP($A11,Python数据平滑!$A$2:$AN$5,COLUMN(Python数据平滑!S$2),0) -> 2399213.6 | V11: =Q11*(1+E5)^5 -> 2483160.9 | W11: =VLOOKUP($A11,Python数据平滑!$A$2:$AN$5,COLUMN(Python数据平滑!U$2),0) -> 2569541.8 | X11: =VLOOKUP($A11,Python数据平滑!$A$2:$AN$5,COLUMN(Python数据平滑!V$2),0) -> 2657953.6 | Y11: =VLOOKUP($A11,Python数据平滑!$A$2:$AN$5,COLUMN(Python数据平滑!W$2),0) -> 2748362.2 | Z11: =VLOOKUP($A11,Python数据平滑!$A$2:$AN$5,COLUMN(Python数据平滑!X$2),0) -> 2840726.1 | AA11: =V11*(1+F5)^5 -> 2934996.3 | AB11: =VLOOKUP($A11,Python数据平滑!$A$2:$AN$5,COLUMN(Python数据平滑!Z$2),0) -> 3031222.7 | AC11: =VLOOKUP($A11,Python数据平滑!$A$2:$AN$5,COLUMN(Python数据平滑!AA$2),0) -> 3129458.9 | AD11: =VLOOKUP($A11,Python数据平滑!$A$2:$AN$5,COLUMN(Python数据平滑!AB$2),0) -> 3229649.3 | AE11: =VLOOKUP($A11,Python数据平滑!$A$2:$AN$5,COLUMN(Python数据平滑!AC$2),0) -> 3331729.8 | AF11: =AA11*(1+G5)^5 -> 3435627.3 | AG11: =VLOOKUP($A11,Python数据平滑!$A$2:$AN$5,COLUMN(Python数据平滑!AE$2),0) -> 3541393 | AH11: =VLOOKUP($A11,Python数据平滑!$A$2:$AN$5,COLUMN(Python数据平滑!AF$2),0) -> 3649082 | AI11: =VLOOKUP($A11,Python数据平滑!$A$2:$AN$5,COLUMN(Python数据平滑!AG$2),0) -> 3758613.8 | AJ11: =VLOOKUP($A11,Python数据平滑!$A$2:$AN$5,COLUMN(Python数据平滑!AH$2),0) -> 3869897.8 | AK11: =AF11*(1+H5)^5 -> 3982833.7 | AL11: =VLOOKUP($A11,Python数据平滑!$A$2:$AN$5,COLUMN(Python数据平滑!AJ$2),0) -> 4097450.8 | AM11: =VLOOKUP($A11,Python数据平滑!$A$2:$AN$5,COLUMN(Python数据平滑!AK$2),0) -> 4213806 | AN11: =VLOOKUP($A11,Python数据平滑!$A$2:$AN$5,COLUMN(Python数据平滑!AL$2),0) -> 4331826.9 | AO11: =VLOOKUP($A11,Python数据平滑!$A$2:$AN$5,COLUMN(Python数据平滑!AM$2),0) -> 4451434.4 | AP11: =AK11*(1+I5)^5 -> 4572542.4 | AQ11: =AP11/B11 -> 4.5113371
A15: 假设2：三次产业结构 | V15: 高情景年均增速 | AB15: 中情景年均增速 | AH15: 低情景年均增速
A16: 高情景 | B16: 2025 | C16: 2030 | D16: 2035 | E16: 2050 | F16: 2060 | G16: 2022 | H16: 中情景 | I16: 2025 | J16: 2030 | K16: 2035 | L16: 2050 | M16: 2060 | O16: 低情景 | P16: 2025 | Q16: 2030 | R16: 2035 | S16: 2050 | T16: 2060 | V16: 2025 | W16: 2030 | X16: 2035 | Y16: 2050 | Z16: 2060 | AB16: 2025 | AC16: 2030 | AD16: 2035 | AE16: 2050 | AF16: 2060 | AH16: 2025 | AI16: 2030 | AJ16: 2035 | AK16: 2050 | AL16: 2060
A17: 农业 | B17: 0.075 | C17: 0.0715 | D17: 0.069 | E17: 0.0645 | F17: 0.063 | G17: =D27/$D$9 -> 0.07650128 | H17: 农业 | I17: =B17*0.4+P17*0.6 -> 0.075 | J17: =C17*0.4+Q17*0.6 -> 0.0715 | K17: =D17*0.4+R17*0.6 -> 0.0684 | L17: =E17*0.4+S17*0.6 -> 0.0624 | M17: =F17*0.4+T17*0.6 -> 0.0606 | O17: 农业 | P17: 0.075 | Q17: 0.0715 | R17: 0.068 | S17: 0.061 | T17: 0.059 | V17: =(G27/D27)^(1/3)-1 -> 0.046322841 | W17: =(L27/G27)^0.2-1 -> 0.039608342 | X17: =(Q27/L27)^0.2-1 -> 0.029077272 | Y17: =(AF27/Q27)^(1/15)-1 -> 0.024383591 | Z17: =(AP27/AF27)^0.1-1 -> 0.023338923 | AB17: =(G33/D33)^(1/3)-1 -> 0.046617159 | AC17: =(L33/G33)^0.2-1 -> 0.041198616 | AD17: =(Q33/L33)^0.2-1 -> 0.029231414 | AE17: =(AF33/Q33)^(1/15)-1 -> 0.025205259 | AF17: =(AP33/AF33)^0.1-1 -> 0.02449638 | AH17: =(G39/D39)^(1/3)-1 -> 0.046780394 | AI17: =(L39/G39)^0.2-1 -> 0.041807174 | AJ17: =(Q39/L39)^0.2-1 -> 0.03030255 | AK17: =(AF39/Q39)^(1/15)-1 -> 0.026537278 | AL17: =(AP39/AF39)^0.1-1 -> 0.025574909
A18: 工业 | B18: 0.315 | C18: 0.29 | D18: 0.273 | E18: 0.23 | F18: 0.21 | G18: =D28/$D$9 -> 0.33188061 | H18: 工业 | I18: =B18*0.4+P18*0.6 -> 0.3138 | J18: =C18*0.4+Q18*0.6 -> 0.287 | K18: =D18*0.4+R18*0.6 -> 0.2706 | L18: =E18*0.4+S18*0.6 -> 0.2228 | M18: =F18*0.4+T18*0.6 -> 0.2028 | O18: 工业 | P18: 0.313 | Q18: 0.285 | R18: 0.269 | S18: 0.218 | T18: 0.198 | V18: =(G28/D28)^(1/3)-1 -> 0.035089123 | W18: =(L28/G28)^0.2-1 -> 0.032376925 | X18: =(Q28/L28)^0.2-1 -> 0.023981962 | Y18: =(AF28/Q28)^(1/15)-1 -> 0.017309072 | Z18: =(AP28/AF28)^0.1-1 -> 0.016460615 | AB18: =(G34/D34)^(1/3)-1 -> 0.03406384 | AC18: =(L34/G34)^0.2-1 -> 0.032595951 | AD18: =(Q34/L34)^0.2-1 -> 0.026247708 | AE18: =(AF34/Q34)^(1/15)-1 -> 0.018219521 | AF18: =(AP34/AF34)^0.1-1 -> 0.01788075 | AH18: =(G40/D40)^(1/3)-1 -> 0.033345486 | AI18: =(L40/G40)^0.2-1 -> 0.032282328 | AJ18: =(Q40/L40)^0.2-1 -> 0.028740137 | AK18: =(AF40/Q40)^(1/15)-1 -> 0.019608885 | AL18: =(AP40/AF40)^0.1-1 -> 0.019145144
A19: 建筑业 | B19: 0.068 | C19: 0.063 | D19: 0.059 | E19: 0.052 | F19: 0.048 | G19: =D29/$D$9 -> 0.068899855 | H19: 建筑业 | I19: =B19*0.4+P19*0.6 -> 0.0668 | J19: =C19*0.4+Q19*0.6 -> 0.0612 | K19: =D19*0.4+R19*0.6 -> 0.0566 | L19: =E19*0.4+S19*0.6 -> 0.0478 | M19: =F19*0.4+T19*0.6 -> 0.0432 | O19: 建筑业 | P19: 0.066 | Q19: 0.06 | R19: 0.055 | S19: 0.045 | T19: 0.04 | V19: =(G29/D29)^(1/3)-1 -> 0.048652802 | W19: =(L29/G29)^0.2-1 -> 0.033682414 | X19: =(Q29/L29)^0.2-1 -> 0.022919998 | Y19: =(AF29/Q29)^(1/15)-1 -> 0.0203723 | Z19: =(AP29/AF29)^0.1-1 -> 0.017572119 | AB19: =(G35/D35)^(1/3)-1 -> 0.042740839 | AC19: =(L35/G35)^0.2-1 -> 0.032950757 | AD19: =(Q35/L35)^0.2-1 -> 0.022294497 | AE19: =(AF35/Q35)^(1/15)-1 -> 0.01994407 | AF19: =(AP35/AF35)^0.1-1 -> 0.017155168 | AH19: =(G41/D41)^(1/3)-1 -> 0.03872345 | AI19: =(L41/G41)^0.2-1 -> 0.031952841 | AJ19: =(Q41/L41)^0.2-1 -> 0.022742935 | AK19: =(AF41/Q41)^(1/15)-1 -> 0.020257945 | AL19: =(AP41/AF41)^0.1-1 -> 0.016950742
A20: 服务业 | B20: =1-SUM(B17:B19) -> 0.542 | C20: =1-SUM(C17:C19) -> 0.5755 | D20: =1-SUM(D17:D19) -> 0.599 | E20: =1-SUM(E17:E19) -> 0.6535 | F20: =1-SUM(F17:F19) -> 0.679 | G20: =D30/$D$9 -> 0.52271826 | H20: 服务业 | I20: =B20*0.4+P20*0.6 -> 0.5444 | J20: =C20*0.4+Q20*0.6 -> 0.5803 | K20: =D20*0.4+R20*0.6 -> 0.6044 | L20: =E20*0.4+S20*0.6 -> 0.667 | M20: =F20*0.4+T20*0.6 -> 0.6934 | O20: 服务业 | P20: =1-SUM(P17:P19) -> 0.546 | Q20: =1-SUM(Q17:Q19) -> 0.5835 | R20: =1-SUM(R17:R19) -> 0.608 | S20: =1-SUM(S17:S19) -> 0.676 | T20: =1-SUM(T17:T19) -> 0.703 | V20: =(G30/D30)^(1/3)-1 -> 0.066052823 | W20: =(L30/G30)^0.2-1 -> 0.062257995 | X20: =(Q30/L30)^0.2-1 -> 0.044757928 | Y20: =(AF30/Q30)^(1/15)-1 -> 0.0349908 | Z20: =(AP30/AF30)^0.1-1 -> 0.029683676 | AB20: =(G36/D36)^(1/3)-1 -> 0.067924325 | AC20: =(L36/G36)^0.2-1 -> 0.064710451 | AD20: =(Q36/L36)^0.2-1 -> 0.046881194 | AE20: =(AF36/Q36)^(1/15)-1 -> 0.038298798 | AF20: =(AP36/AF36)^0.1-1 -> 0.031495708 | AH20: =(G42/D42)^(1/3)-1 -> 0.069136238 | AI20: =(L42/G42)^0.2-1 -> 0.065879309 | AJ20: =(Q42/L42)^0.2-1 -> 0.049292924 | AK20: =(AF42/Q42)^(1/15)-1 -> 0.041332777 | AL20: =(AP42/AF42)^0.1-1 -> 0.033037371
D21: 20.4
D22: 0.068
A23: 二产 | D23: 0.35 | F23: 0.3
A25: 结果2：农、工、建筑和服务业增加值
A26: 高情景 | B26: 2020 | C26: 2021 | D26: 2022 | E26: 2023 | F26: 2024 | G26: 2025 | H26: 2026 | I26: 2027 | J26: 2028 | K26: 2029 | L26: 2030 | M26: 2031 | N26: 2032 | O26: 2033 | P26: 2034 | Q26: 2035 | R26: 2036 | S26: 2037 | T26: 2038 | U26: 2039 | V26: 2040 | W26: 2041 | X26: 2042 | Y26: 2043 | Z26: 2044 | AA26: 2045 | AB26: 2046 | AC26: 2047 | AD26: 2048 | AE26: 2049 | AF26: 2050 | AG26: 2051 | AH26: 2052 | AI26: 2053 | AJ26: 2054 | AK26: 2055 | AL26: 2056 | AM26: 2057 | AN26: 2058 | AO26: 2059 | AP26: 2060
A27: 农业-高情景 | B27: ='高情景（2001-2060, 2020RMB）'!U3 -> 81396.5 | C27: ='高情景（2001-2060, 2020RMB）'!V3 -> 82959.622 | D27: ='高情景（2001-2060, 2020RMB）'!W3 -> 86574.037 | E27: =VLOOKUP($A27,Python数据平滑!$A$9:$AN$21,COLUMN(Python数据平滑!C$9),0)/SUM(Python数据平滑!C$10:C$13)*情景假设!E$9 -> 90742.731 | F27: =VLOOKUP($A27,Python数据平滑!$A$9:$AN$21,COLUMN(Python数据平滑!D$9),0)/SUM(Python数据平滑!D$10:D$13)*情景假设!F$9 -> 94959.47 | G27: =G$9*B17 -> 99171.022 | H27: =VLOOKUP($A27,Python数据平滑!$A$9:$AN$21,COLUMN(Python数据平滑!F$9),0)/SUM(Python数据平滑!F$10:F$13)*情景假设!H$9 -> 103422.66 | I27: =VLOOKUP($A27,Python数据平滑!$A$9:$AN$21,COLUMN(Python数据平滑!G$9),0)/SUM(Python数据平滑!G$10:G$13)*情景假设!I$9 -> 107753.21 | J27: =VLOOKUP($A27,Python数据平滑!$A$9:$AN$21,COLUMN(Python数据平滑!H$9),0)/SUM(Python数据平滑!H$10:H$13)*情景假设!J$9 -> 112087.45 | K27: =VLOOKUP($A27,Python数据平滑!$A$9:$AN$21,COLUMN(Python数据平滑!I$9),0)/SUM(Python数据平滑!I$10:I$13)*情景假设!K$9 -> 116342.73 | L27: =L$9*C17 -> 120429.69 | M27: =VLOOKUP($A27,Python数据平滑!$A$9:$AN$21,COLUMN(Python数据平滑!K$9),0)/SUM(Python数据平滑!K$10:K$13)*情景假设!M$9 -> 124312.56 | N27: =VLOOKUP($A27,Python数据平滑!$A$9:$AN$21,COLUMN(Python数据平滑!L$9),0)/SUM(Python数据平滑!L$10:L$13)*情景假设!N$9 -> 128050.95 | O27: =VLOOKUP($A27,Python数据平滑!$A$9:$AN$21,COLUMN(Python数据平滑!M$9),0)/SUM(Python数据平滑!M$10:M$13)*情景假设!O$9 -> 131699.95 | P27: =VLOOKUP($A27,Python数据平滑!$A$9:$AN$21,COLUMN(Python数据平滑!N$9),0)/SUM(Python数据平滑!N$10:N$13)*情景假设!P$9 -> 135322.05 | Q27: =Q$9*D17 -> 138986.78 | R27: =VLOOKUP($A27,Python数据平滑!$A$9:$AN$21,COLUMN(Python数据平滑!P$9),0)/SUM(Python数据平滑!P$10:P$13)*情景假设!R$9 -> 142625.93 | S27: =VLOOKUP($A27,Python数据平滑!$A$9:$AN$21,COLUMN(Python数据平滑!Q$9),0)/SUM(Python数据平滑!Q$10:Q$13)*情景假设!S$9 -> 146164.82 | T27: =VLOOKUP($A27,Python数据平滑!$A$9:$AN$21,COLUMN(Python数据平滑!R$9),0)/SUM(Python数据平滑!R$10:R$13)*情景假设!T$9 -> 149674.57 | U27: =VLOOKUP($A27,Python数据平滑!$A$9:$AN$21,COLUMN(Python数据平滑!S$9),0)/SUM(Python数据平滑!S$10:S$13)*情景假设!U$9 -> 153234.1 | V27: =VLOOKUP($A27,Python数据平滑!$A$9:$AN$21,COLUMN(Python数据平滑!T$9),0)/SUM(Python数据平滑!T$10:T$13)*情景假设!V$9 -> 156930.24 | W27: =VLOOKUP($A27,Python数据平滑!$A$9:$AN$21,COLUMN(Python数据平滑!U$9),0)/SUM(Python数据平滑!U$10:U$13)*情景假设!W$9 -> 160769.58 | X27: =VLOOKUP($A27,Python数据平滑!$A$9:$AN$21,COLUMN(Python数据平滑!V$9),0)/SUM(Python数据平滑!V$10:V$13)*情景假设!X$9 -> 164697.48 | Y27: =VLOOKUP($A27,Python数据平滑!$A$9:$AN$21,COLUMN(Python数据平滑!W$9),0)/SUM(Python数据平滑!W$10:W$13)*情景假设!Y$9 -> 168715.04 | ... AE27: =VLOOKUP($A27,Python数据平滑!$A$9:$AN$21,COLUMN(Python数据平滑!AC$9),0)/SUM(Python数据平滑!AC$10:AC$13)*情景假设!AE$9 -> 194825.29 | AF27: =E17*$AF$9 -> 199486.13 | AG27: =VLOOKUP($A27,Python数据平滑!$A$9:$AN$21,COLUMN(Python数据平滑!AE$9),0)/SUM(Python数据平滑!AE$10:AE$13)*情景假设!AG$9 -> 204227.06 | AH27: =VLOOKUP($A27,Python数据平滑!$A$9:$AN$21,COLUMN(Python数据平滑!AF$9),0)/SUM(Python数据平滑!AF$10:AF$13)*情景假设!AH$9 -> 209064.08 | AI27: =VLOOKUP($A27,Python数据平滑!$A$9:$AN$21,COLUMN(Python数据平滑!AG$9),0)/SUM(Python数据平滑!AG$10:AG$13)*情景假设!AI$9 -> 213996.56 | AJ27: =VLOOKUP($A27,Python数据平滑!$A$9:$AN$21,COLUMN(Python数据平滑!AH$9),0)/SUM(Python数据平滑!AH$10:AH$13)*情景假设!AJ$9 -> 219023.64 | AK27: =VLOOKUP($A27,Python数据平滑!$A$9:$AN$21,COLUMN(Python数据平滑!AI$9),0)/SUM(Python数据平滑!AI$10:AI$13)*情景假设!AK$9 -> 224144.22 | AL27: =VLOOKUP($A27,Python数据平滑!$A$9:$AN$21,COLUMN(Python数据平滑!AJ$9),0)/SUM(Python数据平滑!AJ$10:AJ$13)*情景假设!AL$9 -> 229361.95 | AM27: =VLOOKUP($A27,Python数据平滑!$A$9:$AN$21,COLUMN(Python数据平滑!AK$9),0)/SUM(Python数据平滑!AK$10:AK$13)*情景假设!AM$9 -> 234681.48 | AN27: =VLOOKUP($A27,Python数据平滑!$A$9:$AN$21,COLUMN(Python数据平滑!AL$9),0)/SUM(Python数据平滑!AL$10:AL$13)*情景假设!AN$9 -> 240102.89 | AO27: =VLOOKUP($A27,Python数据平滑!$A$9:$AN$21,COLUMN(Python数据平滑!AM$9),0)/SUM(Python数据平滑!AM$10:AM$13)*情景假设!AO$9 -> 245626.11 | AP27: =AP$9*F17 -> 251250.9
A28: 工业-高情景 | B28: ='高情景（2001-2060, 2020RMB）'!U4 -> 312902.9 | C28: ='高情景（2001-2060, 2020RMB）'!V4 -> 356193.68 | D28: ='高情景（2001-2060, 2020RMB）'!W4 -> 375578.61 | E28: =VLOOKUP($A28,Python数据平滑!$A$9:$AN$21,COLUMN(Python数据平滑!C$9),0)/SUM(Python数据平滑!C$10:C$13)*情景假设!E$9 -> 389021.39 | F28: =VLOOKUP($A28,Python数据平滑!$A$9:$AN$21,COLUMN(Python数据平滑!D$9),0)/SUM(Python数据平滑!D$10:D$13)*情景假设!F$9 -> 402682.28 | G28: =G$9*B18 -> 416518.29 | H28: =VLOOKUP($A28,Python数据平滑!$A$9:$AN$21,COLUMN(Python数据平滑!F$9),0)/SUM(Python数据平滑!F$10:F$13)*情景假设!H$9 -> 430756.29 | I28: =VLOOKUP($A28,Python数据平滑!$A$9:$AN$21,COLUMN(Python数据平滑!G$9),0)/SUM(Python数据平滑!G$10:G$13)*情景假设!I$9 -> 445436.87 | J28: =VLOOKUP($A28,Python数据平滑!$A$9:$AN$21,COLUMN(Python数据平滑!H$9),0)/SUM(Python数据平滑!H$10:H$13)*情景假设!J$9 -> 460207.79 | K28: =VLOOKUP($A28,Python数据平滑!$A$9:$AN$21,COLUMN(Python数据平滑!I$9),0)/SUM(Python数据平滑!I$10:I$13)*情景假设!K$9 -> 474685.21 | L28: =L$9*C18 -> 488456.09 | M28: =VLOOKUP($A28,Python数据平滑!$A$9:$AN$21,COLUMN(Python数据平滑!K$9),0)/SUM(Python数据平滑!K$10:K$13)*情景假设!M$9 -> 501530.51 | N28: =VLOOKUP($A28,Python数据平滑!$A$9:$AN$21,COLUMN(Python数据平滑!L$9),0)/SUM(Python数据平滑!L$10:L$13)*情景假设!N$9 -> 514208.9 | O28: =VLOOKUP($A28,Python数据平滑!$A$9:$AN$21,COLUMN(Python数据平滑!M$9),0)/SUM(Python数据平滑!M$10:M$13)*情景假设!O$9 -> 526494.48 | P28: =VLOOKUP($A28,Python数据平滑!$A$9:$AN$21,COLUMN(Python数据平滑!N$9),0)/SUM(Python数据平滑!N$10:N$13)*情景假设!P$9 -> 538391.31 | Q28: =Q$9*D18 -> 549904.23 | R28: =VLOOKUP($A28,Python数据平滑!$A$9:$AN$21,COLUMN(Python数据平滑!P$9),0)/SUM(Python数据平滑!P$10:P$13)*情景假设!R$9 -> 560802.44 | S28: =VLOOKUP($A28,Python数据平滑!$A$9:$AN$21,COLUMN(Python数据平滑!Q$9),0)/SUM(Python数据平滑!Q$10:Q$13)*情景假设!S$9 -> 571034.03 | T28: =VLOOKUP($A28,Python数据平滑!$A$9:$AN$21,COLUMN(Python数据平滑!R$9),0)/SUM(Python数据平滑!R$10:R$13)*情景假设!T$9 -> 580892.06 | U28: =VLOOKUP($A28,Python数据平滑!$A$9:$AN$21,COLUMN(Python数据平滑!S$9),0)/SUM(Python数据平滑!S$10:S$13)*情景假设!U$9 -> 590693.75 | V28: =VLOOKUP($A28,Python数据平滑!$A$9:$AN$21,COLUMN(Python数据平滑!T$9),0)/SUM(Python数据平滑!T$10:T$13)*情景假设!V$9 -> 600779.3 | W28: =VLOOKUP($A28,Python数据平滑!$A$9:$AN$21,COLUMN(Python数据平滑!U$9),0)/SUM(Python数据平滑!U$10:U$13)*情景假设!W$9 -> 611175.71 | X28: =VLOOKUP($A28,Python数据平滑!$A$9:$AN$21,COLUMN(Python数据平滑!V$9),0)/SUM(Python数据平滑!V$10:V$13)*情景假设!X$9 -> 621679.02 | Y28: =VLOOKUP($A28,Python数据平滑!$A$9:$AN$21,COLUMN(Python数据平滑!W$9),0)/SUM(Python数据平滑!W$10:W$13)*情景假设!Y$9 -> 632301.1 | ... AE28: =VLOOKUP($A28,Python数据平滑!$A$9:$AN$21,COLUMN(Python数据平滑!AC$9),0)/SUM(Python数据平滑!AC$10:AC$13)*情景假设!AE$9 -> 699531.94 | AF28: =E18*$AF$9 -> 711345.87 | AG28: =VLOOKUP($A28,Python数据平滑!$A$9:$AN$21,COLUMN(Python数据平滑!AE$9),0)/SUM(Python数据平滑!AE$10:AE$13)*情景假设!AG$9 -> 723301.31 | AH28: =VLOOKUP($A28,Python数据平滑!$A$9:$AN$21,COLUMN(Python数据平滑!AF$9),0)/SUM(Python数据平滑!AF$10:AF$13)*情景假设!AH$9 -> 735413.25 | AI28: =VLOOKUP($A28,Python数据平滑!$A$9:$AN$21,COLUMN(Python数据平滑!AG$9),0)/SUM(Python数据平滑!AG$10:AG$13)*情景假设!AI$9 -> 747674.84 | AJ28: =VLOOKUP($A28,Python数据平滑!$A$9:$AN$21,COLUMN(Python数据平滑!AH$9),0)/SUM(Python数据平滑!AH$10:AH$13)*情景假设!AJ$9 -> 760078.57 | AK28: =VLOOKUP($A28,Python数据平滑!$A$9:$AN$21,COLUMN(Python数据平滑!AI$9),0)/SUM(Python数据平滑!AI$10:AI$13)*情景假设!AK$9 -> 772616.25 | AL28: =VLOOKUP($A28,Python数据平滑!$A$9:$AN$21,COLUMN(Python数据平滑!AJ$9),0)/SUM(Python数据平滑!AJ$10:AJ$13)*情景假设!AL$9 -> 785296.1 | AM28: =VLOOKUP($A28,Python数据平滑!$A$9:$AN$21,COLUMN(Python数据平滑!AK$9),0)/SUM(Python数据平滑!AK$10:AK$13)*情景假设!AM$9 -> 798129.42 | AN28: =VLOOKUP($A28,Python数据平滑!$A$9:$AN$21,COLUMN(Python数据平滑!AL$9),0)/SUM(Python数据平滑!AL$10:AL$13)*情景假设!AN$9 -> 811111.73 | AO28: =VLOOKUP($A28,Python数据平滑!$A$9:$AN$21,COLUMN(Python数据平滑!AM$9),0)/SUM(Python数据平滑!AM$10:AM$13)*情景假设!AO$9 -> 824238.07 | AP28: =AP$9*F18 -> 837503
A29: 建筑业-高情景 | B29: ='高情景（2001-2060, 2020RMB）'!U5 -> 72444.7 | C29: ='高情景（2001-2060, 2020RMB）'!V5 -> 76614.92 | D29: ='高情景（2001-2060, 2020RMB）'!W5 -> 77971.749 | E29: =VLOOKUP($A29,Python数据平滑!$A$9:$AN$21,COLUMN(Python数据平滑!C$9),0)/SUM(Python数据平滑!C$10:C$13)*情景假设!E$9 -> 82102.135 | F29: =VLOOKUP($A29,Python数据平滑!$A$9:$AN$21,COLUMN(Python数据平滑!D$9),0)/SUM(Python数据平滑!D$10:D$13)*情景假设!F$9 -> 86141.36 | G29: =G$9*B19 -> 89915.06 | H29: =VLOOKUP($A29,Python数据平滑!$A$9:$AN$21,COLUMN(Python数据平滑!F$9),0)/SUM(Python数据平滑!F$10:F$13)*情景假设!H$9 -> 93435.146 | I29: =VLOOKUP($A29,Python数据平滑!$A$9:$AN$21,COLUMN(Python数据平滑!G$9),0)/SUM(Python数据平滑!G$10:G$13)*情景假设!I$9 -> 96828.844 | J29: =VLOOKUP($A29,Python数据平滑!$A$9:$AN$21,COLUMN(Python数据平滑!H$9),0)/SUM(Python数据平滑!H$10:H$13)*情景假设!J$9 -> 100079.88 | K29: =VLOOKUP($A29,Python数据平滑!$A$9:$AN$21,COLUMN(Python数据平滑!I$9),0)/SUM(Python数据平滑!I$10:I$13)*情景假设!K$9 -> 103176.7 | L29: =L$9*C19 -> 106112.87 | M29: =VLOOKUP($A29,Python数据平滑!$A$9:$AN$21,COLUMN(Python数据平滑!K$9),0)/SUM(Python数据平滑!K$10:K$13)*情景假设!M$9 -> 108856.54 | N29: =VLOOKUP($A29,Python数据平滑!$A$9:$AN$21,COLUMN(Python数据平滑!L$9),0)/SUM(Python数据平滑!L$10:L$13)*情景假设!N$9 -> 111423.28 | O29: =VLOOKUP($A29,Python数据平滑!$A$9:$AN$21,COLUMN(Python数据平滑!M$9),0)/SUM(Python数据平滑!M$10:M$13)*情景假设!O$9 -> 113887.68 | P29: =VLOOKUP($A29,Python数据平滑!$A$9:$AN$21,COLUMN(Python数据平滑!N$9),0)/SUM(Python数据平滑!N$10:N$13)*情景假设!P$9 -> 116331.6 | Q29: =Q$9*D19 -> 118843.77 | R29: =VLOOKUP($A29,Python数据平滑!$A$9:$AN$21,COLUMN(Python数据平滑!P$9),0)/SUM(Python数据平滑!P$10:P$13)*情景假设!R$9 -> 121370.51 | S29: =VLOOKUP($A29,Python数据平滑!$A$9:$AN$21,COLUMN(Python数据平滑!Q$9),0)/SUM(Python数据平滑!Q$10:Q$13)*情景假设!S$9 -> 123831.03 | T29: =VLOOKUP($A29,Python数据平滑!$A$9:$AN$21,COLUMN(Python数据平滑!R$9),0)/SUM(Python数据平滑!R$10:R$13)*情景假设!T$9 -> 126282.3 | U29: =VLOOKUP($A29,Python数据平滑!$A$9:$AN$21,COLUMN(Python数据平滑!S$9),0)/SUM(Python数据平滑!S$10:S$13)*情景假设!U$9 -> 128786.2 | V29: =VLOOKUP($A29,Python数据平滑!$A$9:$AN$21,COLUMN(Python数据平滑!T$9),0)/SUM(Python数据平滑!T$10:T$13)*情景假设!V$9 -> 131409.64 | W29: =VLOOKUP($A29,Python数据平滑!$A$9:$AN$21,COLUMN(Python数据平滑!U$9),0)/SUM(Python数据平滑!U$10:U$13)*情景假设!W$9 -> 134151.08 | X29: =VLOOKUP($A29,Python数据平滑!$A$9:$AN$21,COLUMN(Python数据平滑!V$9),0)/SUM(Python数据平滑!V$10:V$13)*情景假设!X$9 -> 136957.45 | Y29: =VLOOKUP($A29,Python数据平滑!$A$9:$AN$21,COLUMN(Python数据平滑!W$9),0)/SUM(Python数据平滑!W$10:W$13)*情景假设!Y$9 -> 139821.94 | ... AE29: =VLOOKUP($A29,Python数据平滑!$A$9:$AN$21,COLUMN(Python数据平滑!AC$9),0)/SUM(Python数据平滑!AC$10:AC$13)*情景假设!AE$9 -> 157814.03 | AF29: =E19*$AF$9 -> 160826.02 | AG29: =VLOOKUP($A29,Python数据平滑!$A$9:$AN$21,COLUMN(Python数据平滑!AE$9),0)/SUM(Python数据平滑!AE$10:AE$13)*情景假设!AG$9 -> 163825.73 | AH29: =VLOOKUP($A29,Python数据平滑!$A$9:$AN$21,COLUMN(Python数据平滑!AF$9),0)/SUM(Python数据平滑!AF$10:AF$13)*情景假设!AH$9 -> 166843.57 | AI29: =VLOOKUP($A29,Python数据平滑!$A$9:$AN$21,COLUMN(Python数据平滑!AG$9),0)/SUM(Python数据平滑!AG$10:AG$13)*情景假设!AI$9 -> 169877.1 | AJ29: =VLOOKUP($A29,Python数据平滑!$A$9:$AN$21,COLUMN(Python数据平滑!AH$9),0)/SUM(Python数据平滑!AH$10:AH$13)*情景假设!AJ$9 -> 172923.67 | AK29: =VLOOKUP($A29,Python数据平滑!$A$9:$AN$21,COLUMN(Python数据平滑!AI$9),0)/SUM(Python数据平滑!AI$10:AI$13)*情景假设!AK$9 -> 175980.48 | AL29: =VLOOKUP($A29,Python数据平滑!$A$9:$AN$21,COLUMN(Python数据平滑!AJ$9),0)/SUM(Python数据平滑!AJ$10:AJ$13)*情景假设!AL$9 -> 179048.49 | AM29: =VLOOKUP($A29,Python数据平滑!$A$9:$AN$21,COLUMN(Python数据平滑!AK$9),0)/SUM(Python数据平滑!AK$10:AK$13)*情景假设!AM$9 -> 182129.36 | AN29: =VLOOKUP($A29,Python数据平滑!$A$9:$AN$21,COLUMN(Python数据平滑!AL$9),0)/SUM(Python数据平滑!AL$10:AL$13)*情景假设!AN$9 -> 185221.15 | AO29: =VLOOKUP($A29,Python数据平滑!$A$9:$AN$21,COLUMN(Python数据平滑!AM$9),0)/SUM(Python数据平滑!AM$10:AM$13)*情景假设!AO$9 -> 188321.83 | AP29: =AP$9*F19 -> 191429.26
A30: 服务业-高情景 | B30: ='高情景（2001-2060, 2020RMB）'!U56 -> 546822.9 | C30: ='高情景（2001-2060, 2020RMB）'!V56 -> 582938.41 | D30: ='高情景（2001-2060, 2020RMB）'!W56 -> 591543.44 | E30: =VLOOKUP($A30,Python数据平滑!$A$9:$AN$21,COLUMN(Python数据平滑!C$9),0)/SUM(Python数据平滑!C$10:C$13)*情景假设!E$9 -> 631204.49 | F30: =VLOOKUP($A30,Python数据平滑!$A$9:$AN$21,COLUMN(Python数据平滑!D$9),0)/SUM(Python数据平滑!D$10:D$13)*情景假设!F$9 -> 672926.43 | G30: =G$9*B20 -> 716675.92 | H30: =VLOOKUP($A30,Python数据平滑!$A$9:$AN$21,COLUMN(Python数据平滑!F$9),0)/SUM(Python数据平滑!F$10:F$13)*情景假设!H$9 -> 763480.56 | I30: =VLOOKUP($A30,Python数据平滑!$A$9:$AN$21,COLUMN(Python数据平滑!G$9),0)/SUM(Python数据平滑!G$10:G$13)*情景假设!I$9 -> 813672.46 | J30: =VLOOKUP($A30,Python数据平滑!$A$9:$AN$21,COLUMN(Python数据平滑!H$9),0)/SUM(Python数据平滑!H$10:H$13)*情景假设!J$9 -> 865907.62 | K30: =VLOOKUP($A30,Python数据平滑!$A$9:$AN$21,COLUMN(Python数据平滑!I$9),0)/SUM(Python数据平滑!I$10:I$13)*情景假设!K$9 -> 918484.99 | L30: =L$9*C20 -> 969332.68 | M30: =VLOOKUP($A30,Python数据平滑!$A$9:$AN$21,COLUMN(Python数据平滑!K$9),0)/SUM(Python数据平滑!K$10:K$13)*情景假设!M$9 -> 1017948.5 | N30: =VLOOKUP($A30,Python数据平滑!$A$9:$AN$21,COLUMN(Python数据平滑!L$9),0)/SUM(Python数据平滑!L$10:L$13)*情景假设!N$9 -> 1065573.7 | O30: =VLOOKUP($A30,Python数据平滑!$A$9:$AN$21,COLUMN(Python数据平滑!M$9),0)/SUM(Python数据平滑!M$10:M$13)*情景假设!O$9 -> 1112562.1 | P30: =VLOOKUP($A30,Python数据平滑!$A$9:$AN$21,COLUMN(Python数据平滑!N$9),0)/SUM(Python数据平滑!N$10:N$13)*情景假设!P$9 -> 1159372.4 | Q30: =Q$9*D20 -> 1206566.4 | R30: =VLOOKUP($A30,Python数据平滑!$A$9:$AN$21,COLUMN(Python数据平滑!P$9),0)/SUM(Python数据平滑!P$10:P$13)*情景假设!R$9 -> 1253836.4 | S30: =VLOOKUP($A30,Python数据平滑!$A$9:$AN$21,COLUMN(Python数据平滑!Q$9),0)/SUM(Python数据平滑!Q$10:Q$13)*情景假设!S$9 -> 1300785 | T30: =VLOOKUP($A30,Python数据平滑!$A$9:$AN$21,COLUMN(Python数据平滑!R$9),0)/SUM(Python数据平滑!R$10:R$13)*情景假设!T$9 -> 1347991.9 | U30: =VLOOKUP($A30,Python数据平滑!$A$9:$AN$21,COLUMN(Python数据平滑!S$9),0)/SUM(Python数据平滑!S$10:S$13)*情景假设!U$9 -> 1396137.8 | V30: =VLOOKUP($A30,Python数据平滑!$A$9:$AN$21,COLUMN(Python数据平滑!T$9),0)/SUM(Python数据平滑!T$10:T$13)*情景假设!V$9 -> 1446008 | W30: =VLOOKUP($A30,Python数据平滑!$A$9:$AN$21,COLUMN(Python数据平滑!U$9),0)/SUM(Python数据平滑!U$10:U$13)*情景假设!W$9 -> 1497674.2 | X30: =VLOOKUP($A30,Python数据平滑!$A$9:$AN$21,COLUMN(Python数据平滑!V$9),0)/SUM(Python数据平滑!V$10:V$13)*情景假设!X$9 -> 1550631.9 | Y30: =VLOOKUP($A30,Python数据平滑!$A$9:$AN$21,COLUMN(Python数据平滑!W$9),0)/SUM(Python数据平滑!W$10:W$13)*情景假设!Y$9 -> 1604883.2 | ... AE30: =VLOOKUP($A30,Python数据平滑!$A$9:$AN$21,COLUMN(Python数据平滑!AC$9),0)/SUM(Python数据平滑!AC$10:AC$13)*情景假设!AE$9 -> 1958071.4 | AF30: =E20*$AF$9 -> 2021150.1 | AG30: =VLOOKUP($A30,Python数据平滑!$A$9:$AN$21,COLUMN(Python数据平滑!AE$9),0)/SUM(Python数据平滑!AE$10:AE$13)*情景假设!AG$9 -> 2085239.3 | AH30: =VLOOKUP($A30,Python数据平滑!$A$9:$AN$21,COLUMN(Python数据平滑!AF$9),0)/SUM(Python数据平滑!AF$10:AF$13)*情景假设!AH$9 -> 2150422.5 | AI30: =VLOOKUP($A30,Python数据平滑!$A$9:$AN$21,COLUMN(Python数据平滑!AG$9),0)/SUM(Python数据平滑!AG$10:AG$13)*情景假设!AI$9 -> 2216664.8 | AJ30: =VLOOKUP($A30,Python数据平滑!$A$9:$AN$21,COLUMN(Python数据平滑!AH$9),0)/SUM(Python数据平滑!AH$10:AH$13)*情景假设!AJ$9 -> 2283927.2 | AK30: =VLOOKUP($A30,Python数据平滑!$A$9:$AN$21,COLUMN(Python数据平滑!AI$9),0)/SUM(Python数据平滑!AI$10:AI$13)*情景假设!AK$9 -> 2352166.8 | AL30: =VLOOKUP($A30,Python数据平滑!$A$9:$AN$21,COLUMN(Python数据平滑!AJ$9),0)/SUM(Python数据平滑!AJ$10:AJ$13)*情景假设!AL$9 -> 2421389.2 | AM30: =VLOOKUP($A30,Python数据平滑!$A$9:$AN$21,COLUMN(Python数据平滑!AK$9),0)/SUM(Python数据平滑!AK$10:AK$13)*情景假设!AM$9 -> 2491610.5 | AN30: =VLOOKUP($A30,Python数据平滑!$A$9:$AN$21,COLUMN(Python数据平滑!AL$9),0)/SUM(Python数据平滑!AL$10:AL$13)*情景假设!AN$9 -> 2562798 | AO30: =VLOOKUP($A30,Python数据平滑!$A$9:$AN$21,COLUMN(Python数据平滑!AM$9),0)/SUM(Python数据平滑!AM$10:AM$13)*情景假设!AO$9 -> 2634916 | AP30: =AP$9*F20 -> 2707926.4
A32: 中情景 | B32: 2020 | C32: 2021 | D32: 2022 | E32: 2023 | F32: 2024 | G32: 2025 | H32: 2026 | I32: 2027 | J32: 2028 | K32: 2029 | L32: 2030 | M32: 2031 | N32: 2032 | O32: 2033 | P32: 2034 | Q32: 2035 | R32: 2036 | S32: 2037 | T32: 2038 | U32: 2039 | V32: 2040 | W32: 2041 | X32: 2042 | Y32: 2043 | Z32: 2044 | AA32: 2045 | AB32: 2046 | AC32: 2047 | AD32: 2048 | AE32: 2049 | AF32: 2050 | AG32: 2051 | AH32: 2052 | AI32: 2053 | AJ32: 2054 | AK32: 2055 | AL32: 2056 | AM32: 2057 | AN32: 2058 | AO32: 2059 | AP32: 2060
A33: 农业-中情景 | B33: ='高情景（2001-2060, 2020RMB）'!U3 -> 81396.5 | C33: ='高情景（2001-2060, 2020RMB）'!V3 -> 82959.622 | D33: ='高情景（2001-2060, 2020RMB）'!W3 -> 86574.037 | E33: =VLOOKUP($A33,Python数据平滑!$A$9:$AN$21,COLUMN(Python数据平滑!C$9),0)/SUM(Python数据平滑!C$14:C$17)*情景假设!E$10 -> 90737.474 | F33: =VLOOKUP($A33,Python数据平滑!$A$9:$AN$21,COLUMN(Python数据平滑!D$9),0)/SUM(Python数据平滑!D$14:D$17)*情景假设!F$10 -> 94977.09 | G33: =G$10*I17 -> 99254.733 | H33: =VLOOKUP($A33,Python数据平滑!$A$9:$AN$21,COLUMN(Python数据平滑!F$9),0)/SUM(Python数据平滑!F$14:F$17)*情景假设!H$10 -> 103642.1 | I33: =VLOOKUP($A33,Python数据平滑!$A$9:$AN$21,COLUMN(Python数据平滑!G$9),0)/SUM(Python数据平滑!G$14:G$17)*情景假设!I$10 -> 108173.01 | J33: =VLOOKUP($A33,Python数据平滑!$A$9:$AN$21,COLUMN(Python数据平滑!H$9),0)/SUM(Python数据平滑!H$14:H$17)*情景假设!J$10 -> 112737.28 | K33: =VLOOKUP($A33,Python数据平滑!$A$9:$AN$21,COLUMN(Python数据平滑!I$9),0)/SUM(Python数据平滑!I$14:I$17)*情景假设!K$10 -> 117210.75 | L33: =L$10*J17 -> 121456.04 | M33: =VLOOKUP($A33,Python数据平滑!$A$9:$AN$21,COLUMN(Python数据平滑!K$9),0)/SUM(Python数据平滑!K$14:K$17)*情景假设!M$10 -> 125414.64 | N33: =VLOOKUP($A33,Python数据平滑!$A$9:$AN$21,COLUMN(Python数据平滑!L$9),0)/SUM(Python数据平滑!L$14:L$17)*情景假设!N$10 -> 129180.11 | O33: =VLOOKUP($A33,Python数据平滑!$A$9:$AN$21,COLUMN(Python数据平滑!M$9),0)/SUM(Python数据平滑!M$14:M$17)*情景假设!O$10 -> 132842.91 | P33: =VLOOKUP($A33,Python数据平滑!$A$9:$AN$21,COLUMN(Python数据平滑!N$9),0)/SUM(Python数据平滑!N$14:N$17)*情景假设!P$10 -> 136504.38 | Q33: =Q$10*K17 -> 140276.3 | R33: =VLOOKUP($A33,Python数据平滑!$A$9:$AN$21,COLUMN(Python数据平滑!P$9),0)/SUM(Python数据平滑!P$14:P$17)*情景假设!R$10 -> 144096.86 | S33: =VLOOKUP($A33,Python数据平滑!$A$9:$AN$21,COLUMN(Python数据平滑!Q$9),0)/SUM(Python数据平滑!Q$14:Q$17)*情景假设!S$10 -> 147855.94 | T33: =VLOOKUP($A33,Python数据平滑!$A$9:$AN$21,COLUMN(Python数据平滑!R$9),0)/SUM(Python数据平滑!R$14:R$17)*情景假设!T$10 -> 151605.36 | U33: =VLOOKUP($A33,Python数据平滑!$A$9:$AN$21,COLUMN(Python数据平滑!S$9),0)/SUM(Python数据平滑!S$14:S$17)*情景假设!U$10 -> 155403.15 | V33: =VLOOKUP($A33,Python数据平滑!$A$9:$AN$21,COLUMN(Python数据平滑!T$9),0)/SUM(Python数据平滑!T$14:T$17)*情景假设!V$10 -> 159313.66 | W33: =VLOOKUP($A33,Python数据平滑!$A$9:$AN$21,COLUMN(Python数据平滑!U$9),0)/SUM(Python数据平滑!U$14:U$17)*情景假设!W$10 -> 163344.49 | X33: =VLOOKUP($A33,Python数据平滑!$A$9:$AN$21,COLUMN(Python数据平滑!V$9),0)/SUM(Python数据平滑!V$14:V$17)*情景假设!X$10 -> 167458.32 | Y33: =VLOOKUP($A33,Python数据平滑!$A$9:$AN$21,COLUMN(Python数据平滑!W$9),0)/SUM(Python数据平滑!W$14:W$17)*情景假设!Y$10 -> 171657.22 | ... AE33: =VLOOKUP($A33,Python数据平滑!$A$9:$AN$21,COLUMN(Python数据平滑!AC$9),0)/SUM(Python数据平滑!AC$14:AC$17)*情景假设!AE$10 -> 198856.1 | AF33: =$AF$10*L17 -> 203773.02 | AG33: =VLOOKUP($A33,Python数据平滑!$A$9:$AN$21,COLUMN(Python数据平滑!AE$9),0)/SUM(Python数据平滑!AE$14:AE$17)*情景假设!AG$10 -> 208822.17 | AH33: =VLOOKUP($A33,Python数据平滑!$A$9:$AN$21,COLUMN(Python数据平滑!AF$9),0)/SUM(Python数据平滑!AF$14:AF$17)*情景假设!AH$10 -> 214007.73 | AI33: =VLOOKUP($A33,Python数据平滑!$A$9:$AN$21,COLUMN(Python数据平滑!AG$9),0)/SUM(Python数据平滑!AG$14:AG$17)*情景假设!AI$10 -> 219318.28 | AJ33: =VLOOKUP($A33,Python数据平滑!$A$9:$AN$21,COLUMN(Python数据平滑!AH$9),0)/SUM(Python数据平滑!AH$14:AH$17)*情景假设!AJ$10 -> 224740.94 | AK33: =VLOOKUP($A33,Python数据平滑!$A$9:$AN$21,COLUMN(Python数据平滑!AI$9),0)/SUM(Python数据平滑!AI$14:AI$17)*情景假设!AK$10 -> 230261.3 | AL33: =VLOOKUP($A33,Python数据平滑!$A$9:$AN$21,COLUMN(Python数据平滑!AJ$9),0)/SUM(Python数据平滑!AJ$14:AJ$17)*情景假设!AL$10 -> 235884.75 | AM33: =VLOOKUP($A33,Python数据平滑!$A$9:$AN$21,COLUMN(Python数据平滑!AK$9),0)/SUM(Python数据平滑!AK$14:AK$17)*情景假设!AM$10 -> 241627.25 | AN33: =VLOOKUP($A33,Python数据平滑!$A$9:$AN$21,COLUMN(Python数据平滑!AL$9),0)/SUM(Python数据平滑!AL$14:AL$17)*情景假设!AN$10 -> 247488.81 | AO33: =VLOOKUP($A33,Python数据平滑!$A$9:$AN$21,COLUMN(Python数据平滑!AM$9),0)/SUM(Python数据平滑!AM$14:AM$17)*情景假设!AO$10 -> 253469.18 | AP33: =AP$10*M17 -> 259567.89
A34: 工业-中情景 | B34: ='高情景（2001-2060, 2020RMB）'!U4 -> 312902.9 | C34: ='高情景（2001-2060, 2020RMB）'!V4 -> 356193.68 | D34: ='高情景（2001-2060, 2020RMB）'!W4 -> 375578.61 | E34: =VLOOKUP($A34,Python数据平滑!$A$9:$AN$21,COLUMN(Python数据平滑!C$9),0)/SUM(Python数据平滑!C$14:C$17)*情景假设!E$10 -> 388513.47 | F34: =VLOOKUP($A34,Python数据平滑!$A$9:$AN$21,COLUMN(Python数据平滑!D$9),0)/SUM(Python数据平滑!D$14:D$17)*情景假设!F$10 -> 401748.08 | G34: =G$10*I18 -> 415281.8 | H34: =VLOOKUP($A34,Python数据平滑!$A$9:$AN$21,COLUMN(Python数据平滑!F$9),0)/SUM(Python数据平滑!F$14:F$17)*情景假设!H$10 -> 429303.7 | I34: =VLOOKUP($A34,Python数据平滑!$A$9:$AN$21,COLUMN(Python数据平滑!G$9),0)/SUM(Python数据平滑!G$14:G$17)*情景假设!I$10 -> 443827.99 | J34: =VLOOKUP($A34,Python数据平滑!$A$9:$AN$21,COLUMN(Python数据平滑!H$9),0)/SUM(Python数据平滑!H$14:H$17)*情景假设!J$10 -> 458575.41 | K34: =VLOOKUP($A34,Python数据平滑!$A$9:$AN$21,COLUMN(Python数据平滑!I$9),0)/SUM(Python数据平滑!I$14:I$17)*情景假设!K$10 -> 473246.64 | L34: =L$10*J18 -> 487522.86 | M34: =VLOOKUP($A34,Python数据平滑!$A$9:$AN$21,COLUMN(Python数据平滑!K$9),0)/SUM(Python数据平滑!K$14:K$17)*情景假设!M$10 -> 501468.86 | N34: =VLOOKUP($A34,Python数据平滑!$A$9:$AN$21,COLUMN(Python数据平滑!L$9),0)/SUM(Python数据平滑!L$14:L$17)*情景假设!N$10 -> 515305.72 | O34: =VLOOKUP($A34,Python数据平滑!$A$9:$AN$21,COLUMN(Python数据平滑!M$9),0)/SUM(Python数据平滑!M$14:M$17)*情景假设!O$10 -> 528921.12 | P34: =VLOOKUP($A34,Python数据平滑!$A$9:$AN$21,COLUMN(Python数据平滑!N$9),0)/SUM(Python数据平滑!N$14:N$17)*情景假设!P$10 -> 542185.53 | Q34: =Q$10*K18 -> 554952.73 | R34: =VLOOKUP($A34,Python数据平滑!$A$9:$AN$21,COLUMN(Python数据平滑!P$9),0)/SUM(Python数据平滑!P$14:P$17)*情景假设!R$10 -> 567031.37 | S34: =VLOOKUP($A34,Python数据平滑!$A$9:$AN$21,COLUMN(Python数据平滑!Q$9),0)/SUM(Python数据平滑!Q$14:Q$17)*情景假设!S$10 -> 578472.33 | T34: =VLOOKUP($A34,Python数据平滑!$A$9:$AN$21,COLUMN(Python数据平滑!R$9),0)/SUM(Python数据平滑!R$14:R$17)*情景假设!T$10 -> 589497.96 | U34: =VLOOKUP($A34,Python数据平滑!$A$9:$AN$21,COLUMN(Python数据平滑!S$9),0)/SUM(Python数据平滑!S$14:S$17)*情景假设!U$10 -> 600352.77 | V34: =VLOOKUP($A34,Python数据平滑!$A$9:$AN$21,COLUMN(Python数据平滑!T$9),0)/SUM(Python数据平滑!T$14:T$17)*情景假设!V$10 -> 611302.25 | W34: =VLOOKUP($A34,Python数据平滑!$A$9:$AN$21,COLUMN(Python数据平滑!U$9),0)/SUM(Python数据平滑!U$14:U$17)*情景假设!W$10 -> 622391.17 | X34: =VLOOKUP($A34,Python数据平滑!$A$9:$AN$21,COLUMN(Python数据平滑!V$9),0)/SUM(Python数据平滑!V$14:V$17)*情景假设!X$10 -> 633495.62 | Y34: =VLOOKUP($A34,Python数据平滑!$A$9:$AN$21,COLUMN(Python数据平滑!W$9),0)/SUM(Python数据平滑!W$14:W$17)*情景假设!Y$10 -> 644645.87 | ... AE34: =VLOOKUP($A34,Python数据平滑!$A$9:$AN$21,COLUMN(Python数据平滑!AC$9),0)/SUM(Python数据平滑!AC$14:AC$17)*情景假设!AE$10 -> 714845.3 | AF34: =$AF$10*L18 -> 727574.18 | AG34: =VLOOKUP($A34,Python数据平滑!$A$9:$AN$21,COLUMN(Python数据平滑!AE$9),0)/SUM(Python数据平滑!AE$14:AE$17)*情景假设!AG$10 -> 740679.47 | AH34: =VLOOKUP($A34,Python数据平滑!$A$9:$AN$21,COLUMN(Python数据平滑!AF$9),0)/SUM(Python数据平滑!AF$14:AF$17)*情景假设!AH$10 -> 754087.55 | AI34: =VLOOKUP($A34,Python数据平滑!$A$9:$AN$21,COLUMN(Python数据平滑!AG$9),0)/SUM(Python数据平滑!AG$14:AG$17)*情景假设!AI$10 -> 767751.61 | AJ34: =VLOOKUP($A34,Python数据平滑!$A$9:$AN$21,COLUMN(Python数据平滑!AH$9),0)/SUM(Python数据平滑!AH$14:AH$17)*情景假设!AJ$10 -> 781620.86 | AK34: =VLOOKUP($A34,Python数据平滑!$A$9:$AN$21,COLUMN(Python数据平滑!AI$9),0)/SUM(Python数据平滑!AI$14:AI$17)*情景假设!AK$10 -> 795640.41 | AL34: =VLOOKUP($A34,Python数据平滑!$A$9:$AN$21,COLUMN(Python数据平滑!AJ$9),0)/SUM(Python数据平滑!AJ$14:AJ$17)*情景假设!AL$10 -> 809824.77 | AM34: =VLOOKUP($A34,Python数据平滑!$A$9:$AN$21,COLUMN(Python数据平滑!AK$9),0)/SUM(Python数据平滑!AK$14:AK$17)*情景假设!AM$10 -> 824223.98 | AN34: =VLOOKUP($A34,Python数据平滑!$A$9:$AN$21,COLUMN(Python数据平滑!AL$9),0)/SUM(Python数据平滑!AL$14:AL$17)*情景假设!AN$10 -> 838832.63 | AO34: =VLOOKUP($A34,Python数据平滑!$A$9:$AN$21,COLUMN(Python数据平滑!AM$9),0)/SUM(Python数据平滑!AM$14:AM$17)*情景假设!AO$10 -> 853644.58 | AP34: =AP$10*M18 -> 868652.93
A35: 建筑业-中情景 | B35: ='高情景（2001-2060, 2020RMB）'!U5 -> 72444.7 | C35: ='高情景（2001-2060, 2020RMB）'!V5 -> 76614.92 | D35: ='高情景（2001-2060, 2020RMB）'!W5 -> 77971.749 | E35: =VLOOKUP($A35,Python数据平滑!$A$9:$AN$21,COLUMN(Python数据平滑!C$9),0)/SUM(Python数据平滑!C$14:C$17)*情景假设!E$10 -> 81519.684 | F35: =VLOOKUP($A35,Python数据平滑!$A$9:$AN$21,COLUMN(Python数据平滑!D$9),0)/SUM(Python数据平滑!D$14:D$17)*情景假设!F$10 -> 85027.663 | G35: =G$10*I19 -> 88402.882 | H35: =VLOOKUP($A35,Python数据平滑!$A$9:$AN$21,COLUMN(Python数据平滑!F$9),0)/SUM(Python数据平滑!F$14:F$17)*情景假设!H$10 -> 91679.592 | I35: =VLOOKUP($A35,Python数据平滑!$A$9:$AN$21,COLUMN(Python数据平滑!G$9),0)/SUM(Python数据平滑!G$14:G$17)*情景假设!I$10 -> 94926.186 | J35: =VLOOKUP($A35,Python数据平滑!$A$9:$AN$21,COLUMN(Python数据平滑!H$9),0)/SUM(Python数据平滑!H$14:H$17)*情景假设!J$10 -> 98090.684 | K35: =VLOOKUP($A35,Python数据平滑!$A$9:$AN$21,COLUMN(Python数据平滑!I$9),0)/SUM(Python数据平滑!I$14:I$17)*情景假设!K$10 -> 101119.77 | L35: =L$10*J19 -> 103959.58 | M35: =VLOOKUP($A35,Python数据平滑!$A$9:$AN$21,COLUMN(Python数据平滑!K$9),0)/SUM(Python数据平滑!K$14:K$17)*情景假设!M$10 -> 106569.51 | N35: =VLOOKUP($A35,Python数据平滑!$A$9:$AN$21,COLUMN(Python数据平滑!L$9),0)/SUM(Python数据平滑!L$14:L$17)*情景假设!N$10 -> 108997.71 | O35: =VLOOKUP($A35,Python数据平滑!$A$9:$AN$21,COLUMN(Python数据平滑!M$9),0)/SUM(Python数据平滑!M$14:M$17)*情景假设!O$10 -> 111329.15 | P35: =VLOOKUP($A35,Python数据平滑!$A$9:$AN$21,COLUMN(Python数据平滑!N$9),0)/SUM(Python数据平滑!N$14:N$17)*情景假设!P$10 -> 113655.88 | Q35: =Q$10*K19 -> 116076.59 | R35: =VLOOKUP($A35,Python数据平滑!$A$9:$AN$21,COLUMN(Python数据平滑!P$9),0)/SUM(Python数据平滑!P$14:P$17)*情景假设!R$10 -> 118545.54 | S35: =VLOOKUP($A35,Python数据平滑!$A$9:$AN$21,COLUMN(Python数据平滑!Q$9),0)/SUM(Python数据平滑!Q$14:Q$17)*情景假设!S$10 -> 120972.04 | T35: =VLOOKUP($A35,Python数据平滑!$A$9:$AN$21,COLUMN(Python数据平滑!R$9),0)/SUM(Python数据平滑!R$14:R$17)*情景假设!T$10 -> 123395.05 | U35: =VLOOKUP($A35,Python数据平滑!$A$9:$AN$21,COLUMN(Python数据平滑!S$9),0)/SUM(Python数据平滑!S$14:S$17)*情景假设!U$10 -> 125857.06 | V35: =VLOOKUP($A35,Python数据平滑!$A$9:$AN$21,COLUMN(Python数据平滑!T$9),0)/SUM(Python数据平滑!T$14:T$17)*情景假设!V$10 -> 128404.19 | W35: =VLOOKUP($A35,Python数据平滑!$A$9:$AN$21,COLUMN(Python数据平滑!U$9),0)/SUM(Python数据平滑!U$14:U$17)*情景假设!W$10 -> 131035.58 | X35: =VLOOKUP($A35,Python数据平滑!$A$9:$AN$21,COLUMN(Python数据平滑!V$9),0)/SUM(Python数据平滑!V$14:V$17)*情景假设!X$10 -> 133713.83 | Y35: =VLOOKUP($A35,Python数据平滑!$A$9:$AN$21,COLUMN(Python数据平滑!W$9),0)/SUM(Python数据平滑!W$14:W$17)*情景假设!Y$10 -> 136432.89 | ... AE35: =VLOOKUP($A35,Python数据平滑!$A$9:$AN$21,COLUMN(Python数据平滑!AC$9),0)/SUM(Python数据平滑!AC$14:AC$17)*情景假设!AE$10 -> 153264.86 | AF35: =$AF$10*L19 -> 156095.36 | AG35: =VLOOKUP($A35,Python数据平滑!$A$9:$AN$21,COLUMN(Python数据平滑!AE$9),0)/SUM(Python数据平滑!AE$14:AE$17)*情景假设!AG$10 -> 158939.12 | AH35: =VLOOKUP($A35,Python数据平滑!$A$9:$AN$21,COLUMN(Python数据平滑!AF$9),0)/SUM(Python数据平滑!AF$14:AF$17)*情景假设!AH$10 -> 161814.52 | AI35: =VLOOKUP($A35,Python数据平滑!$A$9:$AN$21,COLUMN(Python数据平滑!AG$9),0)/SUM(Python数据平滑!AG$14:AG$17)*情景假设!AI$10 -> 164710.28 | AJ35: =VLOOKUP($A35,Python数据平滑!$A$9:$AN$21,COLUMN(Python数据平滑!AH$9),0)/SUM(Python数据平滑!AH$14:AH$17)*情景假设!AJ$10 -> 167614.27 | AK35: =VLOOKUP($A35,Python数据平滑!$A$9:$AN$21,COLUMN(Python数据平滑!AI$9),0)/SUM(Python数据平滑!AI$14:AI$17)*情景假设!AK$10 -> 170513.5 | AL35: =VLOOKUP($A35,Python数据平滑!$A$9:$AN$21,COLUMN(Python数据平滑!AJ$9),0)/SUM(Python数据平滑!AJ$14:AJ$17)*情景假设!AL$10 -> 173409.88 | AM35: =VLOOKUP($A35,Python数据平滑!$A$9:$AN$21,COLUMN(Python数据平滑!AK$9),0)/SUM(Python数据平滑!AK$14:AK$17)*情景假设!AM$10 -> 176312.97 | AN35: =VLOOKUP($A35,Python数据平滑!$A$9:$AN$21,COLUMN(Python数据平滑!AL$9),0)/SUM(Python数据平滑!AL$14:AL$17)*情景假设!AN$10 -> 179220.43 | AO35: =VLOOKUP($A35,Python数据平滑!$A$9:$AN$21,COLUMN(Python数据平滑!AM$9),0)/SUM(Python数据平滑!AM$14:AM$17)*情景假设!AO$10 -> 182129.8 | AP35: =AP$10*M19 -> 185038.49
A36: 服务业-中情景 | B36: ='高情景（2001-2060, 2020RMB）'!U56 -> 546822.9 | C36: ='高情景（2001-2060, 2020RMB）'!V56 -> 582938.41 | D36: ='高情景（2001-2060, 2020RMB）'!W56 -> 591543.44 | E36: =VLOOKUP($A36,Python数据平滑!$A$9:$AN$21,COLUMN(Python数据平滑!C$9),0)/SUM(Python数据平滑!C$14:C$17)*情景假设!E$10 -> 632226.57 | F36: =VLOOKUP($A36,Python数据平滑!$A$9:$AN$21,COLUMN(Python数据平滑!D$9),0)/SUM(Python数据平滑!D$14:D$17)*情景假设!F$10 -> 675193.64 | G36: =G$10*I20 -> 720457.02 | H36: =VLOOKUP($A36,Python数据平滑!$A$9:$AN$21,COLUMN(Python数据平滑!F$9),0)/SUM(Python数据平滑!F$14:F$17)*情景假设!H$10 -> 769141.55 | I36: =VLOOKUP($A36,Python数据平滑!$A$9:$AN$21,COLUMN(Python数据平滑!G$9),0)/SUM(Python数据平滑!G$14:G$17)*情景假设!I$10 -> 821615.66 | J36: =VLOOKUP($A36,Python数据平滑!$A$9:$AN$21,COLUMN(Python数据平滑!H$9),0)/SUM(Python数据平滑!H$14:H$17)*情景假设!J$10 -> 876474.9 | K36: =VLOOKUP($A36,Python数据平滑!$A$9:$AN$21,COLUMN(Python数据平滑!I$9),0)/SUM(Python数据平滑!I$14:I$17)*情景假设!K$10 -> 931922.24 | L36: =L$10*J20 -> 985747.45 | M36: =VLOOKUP($A36,Python数据平滑!$A$9:$AN$21,COLUMN(Python数据平滑!K$9),0)/SUM(Python数据平滑!K$14:K$17)*情景假设!M$10 -> 1037207.5 | N36: =VLOOKUP($A36,Python数据平滑!$A$9:$AN$21,COLUMN(Python数据平滑!L$9),0)/SUM(Python数据平滑!L$14:L$17)*情景假设!N$10 -> 1087586.6 | O36: =VLOOKUP($A36,Python数据平滑!$A$9:$AN$21,COLUMN(Python数据平滑!M$9),0)/SUM(Python数据平滑!M$14:M$17)*情景假设!O$10 -> 1137533.2 | P36: =VLOOKUP($A36,Python数据平滑!$A$9:$AN$21,COLUMN(Python数据平滑!N$9),0)/SUM(Python数据平滑!N$14:N$17)*情景假设!P$10 -> 1187854.9 | Q36: =Q$10*K20 -> 1239517.5 | R36: =VLOOKUP($A36,Python数据平滑!$A$9:$AN$21,COLUMN(Python数据平滑!P$9),0)/SUM(Python数据平滑!P$14:P$17)*情景假设!R$10 -> 1292351 | S36: =VLOOKUP($A36,Python数据平滑!$A$9:$AN$21,COLUMN(Python数据平滑!Q$9),0)/SUM(Python数据平滑!Q$14:Q$17)*情景假设!S$10 -> 1345695.7 | T36: =VLOOKUP($A36,Python数据平滑!$A$9:$AN$21,COLUMN(Python数据平滑!R$9),0)/SUM(Python数据平滑!R$14:R$17)*情景假设!T$10 -> 1399959.6 | U36: =VLOOKUP($A36,Python数据平滑!$A$9:$AN$21,COLUMN(Python数据平滑!S$9),0)/SUM(Python数据平滑!S$14:S$17)*情景假设!U$10 -> 1455628.7 | V36: =VLOOKUP($A36,Python数据平滑!$A$9:$AN$21,COLUMN(Python数据平滑!T$9),0)/SUM(Python数据平滑!T$14:T$17)*情景假设!V$10 -> 1513271.5 | W36: =VLOOKUP($A36,Python数据平滑!$A$9:$AN$21,COLUMN(Python数据平滑!U$9),0)/SUM(Python数据平滑!U$14:U$17)*情景假设!W$10 -> 1572935.2 | X36: =VLOOKUP($A36,Python数据平滑!$A$9:$AN$21,COLUMN(Python数据平滑!V$9),0)/SUM(Python数据平滑!V$14:V$17)*情景假设!X$10 -> 1634222.7 | Y36: =VLOOKUP($A36,Python数据平滑!$A$9:$AN$21,COLUMN(Python数据平滑!W$9),0)/SUM(Python数据平滑!W$14:W$17)*情景假设!Y$10 -> 1697096.9 | ... AE36: =VLOOKUP($A36,Python数据平滑!$A$9:$AN$21,COLUMN(Python数据平滑!AC$9),0)/SUM(Python数据平滑!AC$14:AC$17)*情景假设!AE$10 -> 2105389.4 | AF36: =$AF$10*L20 -> 2178150.7 | AG36: =VLOOKUP($A36,Python数据平滑!$A$9:$AN$21,COLUMN(Python数据平滑!AE$9),0)/SUM(Python数据平滑!AE$14:AE$17)*情景假设!AG$10 -> 2252291.1 | AH36: =VLOOKUP($A36,Python数据平滑!$A$9:$AN$21,COLUMN(Python数据平滑!AF$9),0)/SUM(Python数据平滑!AF$14:AF$17)*情景假设!AH$10 -> 2327914.6 | AI36: =VLOOKUP($A36,Python数据平滑!$A$9:$AN$21,COLUMN(Python数据平滑!AG$9),0)/SUM(Python数据平滑!AG$14:AG$17)*情景假设!AI$10 -> 2404846.5 | AJ36: =VLOOKUP($A36,Python数据平滑!$A$9:$AN$21,COLUMN(Python数据平滑!AH$9),0)/SUM(Python数据平滑!AH$14:AH$17)*情景假设!AJ$10 -> 2482888.2 | AK36: =VLOOKUP($A36,Python数据平滑!$A$9:$AN$21,COLUMN(Python数据平滑!AI$9),0)/SUM(Python数据平滑!AI$14:AI$17)*情景假设!AK$10 -> 2561816.7 | AL36: =VLOOKUP($A36,Python数据平滑!$A$9:$AN$21,COLUMN(Python数据平滑!AJ$9),0)/SUM(Python数据平滑!AJ$14:AJ$17)*情景假设!AL$10 -> 2641624.2 | AM36: =VLOOKUP($A36,Python数据平滑!$A$9:$AN$21,COLUMN(Python数据平滑!AK$9),0)/SUM(Python数据平滑!AK$14:AK$17)*情景假设!AM$10 -> 2722421.1 | AN36: =VLOOKUP($A36,Python数据平滑!$A$9:$AN$21,COLUMN(Python数据平滑!AL$9),0)/SUM(Python数据平滑!AL$14:AL$17)*情景假设!AN$10 -> 2804139 | AO36: =VLOOKUP($A36,Python数据平滑!$A$9:$AN$21,COLUMN(Python数据平滑!AM$9),0)/SUM(Python数据平滑!AM$14:AM$17)*情景假设!AO$10 -> 2886704.6 | AP36: =AP$10*M20 -> 2970039.2
A38: 低情景 | B38: 2020 | C38: 2021 | D38: 2022 | E38: 2023 | F38: 2024 | G38: 2025 | H38: 2026 | I38: 2027 | J38: 2028 | K38: 2029 | L38: 2030 | M38: 2031 | N38: 2032 | O38: 2033 | P38: 2034 | Q38: 2035 | R38: 2036 | S38: 2037 | T38: 2038 | U38: 2039 | V38: 2040 | W38: 2041 | X38: 2042 | Y38: 2043 | Z38: 2044 | AA38: 2045 | AB38: 2046 | AC38: 2047 | AD38: 2048 | AE38: 2049 | AF38: 2050 | AG38: 2051 | AH38: 2052 | AI38: 2053 | AJ38: 2054 | AK38: 2055 | AL38: 2056 | AM38: 2057 | AN38: 2058 | AO38: 2059 | AP38: 2060
A39: 农业-低情景 | B39: ='高情景（2001-2060, 2020RMB）'!U3 -> 81396.5 | C39: ='高情景（2001-2060, 2020RMB）'!V3 -> 82959.622 | D39: ='高情景（2001-2060, 2020RMB）'!W3 -> 86574.037 | E39: =VLOOKUP($A39,Python数据平滑!$A$9:$AN$21,COLUMN(Python数据平滑!C$9),0)/SUM(Python数据平滑!C$18:C$21)*情景假设!E$11 -> 90741.676 | F39: =VLOOKUP($A39,Python数据平滑!$A$9:$AN$21,COLUMN(Python数据平滑!D$9),0)/SUM(Python数据平滑!D$18:D$21)*情景假设!F$11 -> 94995.041 | G39: =G$11*P17 -> 99301.18 | H39: =VLOOKUP($A39,Python数据平滑!$A$9:$AN$21,COLUMN(Python数据平滑!F$9),0)/SUM(Python数据平滑!F$18:F$21)*情景假设!H$11 -> 103731.16 | I39: =VLOOKUP($A39,Python数据平滑!$A$9:$AN$21,COLUMN(Python数据平滑!G$9),0)/SUM(Python数据平滑!G$18:G$21)*情景假设!I$11 -> 108316.24 | J39: =VLOOKUP($A39,Python数据平滑!$A$9:$AN$21,COLUMN(Python数据平滑!H$9),0)/SUM(Python数据平滑!H$18:H$21)*情景假设!J$11 -> 112949.74 | K39: =VLOOKUP($A39,Python数据平滑!$A$9:$AN$21,COLUMN(Python数据平滑!I$9),0)/SUM(Python数据平滑!I$18:I$21)*情景假设!K$11 -> 117511.49 | L39: =L$11*Q17 -> 121868.41 | M39: =VLOOKUP($A39,Python数据平滑!$A$9:$AN$21,COLUMN(Python数据平滑!K$9),0)/SUM(Python数据平滑!K$18:K$21)*情景假设!M$11 -> 125950.92 | N39: =VLOOKUP($A39,Python数据平滑!$A$9:$AN$21,COLUMN(Python数据平滑!L$9),0)/SUM(Python数据平滑!L$18:L$21)*情景假设!N$11 -> 129846.01 | O39: =VLOOKUP($A39,Python数据平滑!$A$9:$AN$21,COLUMN(Python数据平滑!M$9),0)/SUM(Python数据平滑!M$18:M$21)*情景假设!O$11 -> 133655.73 | P39: =VLOOKUP($A39,Python数据平滑!$A$9:$AN$21,COLUMN(Python数据平滑!N$9),0)/SUM(Python数据平滑!N$18:N$21)*情景假设!P$11 -> 137494.04 | Q39: =Q$11*R17 -> 141486.5 | R39: =VLOOKUP($A39,Python数据平滑!$A$9:$AN$21,COLUMN(Python数据平滑!P$9),0)/SUM(Python数据平滑!P$18:P$21)*情景假设!R$11 -> 145577.48 | S39: =VLOOKUP($A39,Python数据平滑!$A$9:$AN$21,COLUMN(Python数据平滑!Q$9),0)/SUM(Python数据平滑!Q$18:Q$21)*情景假设!S$11 -> 149643.09 | T39: =VLOOKUP($A39,Python数据平滑!$A$9:$AN$21,COLUMN(Python数据平滑!R$9),0)/SUM(Python数据平滑!R$18:R$21)*情景假设!T$11 -> 153718.85 | U39: =VLOOKUP($A39,Python数据平滑!$A$9:$AN$21,COLUMN(Python数据平滑!S$9),0)/SUM(Python数据平滑!S$18:S$21)*情景假设!U$11 -> 157845.09 | V39: =VLOOKUP($A39,Python数据平滑!$A$9:$AN$21,COLUMN(Python数据平滑!T$9),0)/SUM(Python数据平滑!T$18:T$21)*情景假设!V$11 -> 162067.08 | W39: =VLOOKUP($A39,Python数据平滑!$A$9:$AN$21,COLUMN(Python数据平滑!U$9),0)/SUM(Python数据平滑!U$18:U$21)*情景假设!W$11 -> 166393.45 | X39: =VLOOKUP($A39,Python数据平滑!$A$9:$AN$21,COLUMN(Python数据平滑!V$9),0)/SUM(Python数据平滑!V$18:V$21)*情景假设!X$11 -> 170801.37 | Y39: =VLOOKUP($A39,Python数据平滑!$A$9:$AN$21,COLUMN(Python数据平滑!W$9),0)/SUM(Python数据平滑!W$18:W$21)*情景假设!Y$11 -> 175293.19 | ... AE39: =VLOOKUP($A39,Python数据平滑!$A$9:$AN$21,COLUMN(Python数据平滑!AC$9),0)/SUM(Python数据平滑!AC$18:AC$21)*情景假设!AE$11 -> 204316.07 | AF39: =$AF$11*S17 -> 209573.27 | AG39: =VLOOKUP($A39,Python数据平滑!$A$9:$AN$21,COLUMN(Python数据平滑!AE$9),0)/SUM(Python数据平滑!AE$18:AE$21)*情景假设!AG$11 -> 214965.7 | AH39: =VLOOKUP($A39,Python数据平滑!$A$9:$AN$21,COLUMN(Python数据平滑!AF$9),0)/SUM(Python数据平滑!AF$18:AF$21)*情景假设!AH$11 -> 220491.71 | AI39: =VLOOKUP($A39,Python数据平滑!$A$9:$AN$21,COLUMN(Python数据平滑!AG$9),0)/SUM(Python数据平滑!AG$18:AG$21)*情景假设!AI$11 -> 226151.87 | AJ39: =VLOOKUP($A39,Python数据平滑!$A$9:$AN$21,COLUMN(Python数据平滑!AH$9),0)/SUM(Python数据平滑!AH$18:AH$21)*情景假设!AJ$11 -> 231946.47 | AK39: =VLOOKUP($A39,Python数据平滑!$A$9:$AN$21,COLUMN(Python数据平滑!AI$9),0)/SUM(Python数据平滑!AI$18:AI$21)*情景假设!AK$11 -> 237875.5 | AL39: =VLOOKUP($A39,Python数据平滑!$A$9:$AN$21,COLUMN(Python数据平滑!AJ$9),0)/SUM(Python数据平滑!AJ$18:AJ$21)*情景假设!AL$11 -> 243947.01 | AM39: =VLOOKUP($A39,Python数据平滑!$A$9:$AN$21,COLUMN(Python数据平滑!AK$9),0)/SUM(Python数据平滑!AK$18:AK$21)*情景假设!AM$11 -> 250170.87 | AN39: =VLOOKUP($A39,Python数据平滑!$A$9:$AN$21,COLUMN(Python数据平滑!AL$9),0)/SUM(Python数据平滑!AL$18:AL$21)*情景假设!AN$11 -> 256549.48 | AO39: =VLOOKUP($A39,Python数据平滑!$A$9:$AN$21,COLUMN(Python数据平滑!AM$9),0)/SUM(Python数据平滑!AM$18:AM$21)*情景假设!AO$11 -> 263085.14 | AP39: =AP$11*T17 -> 269780
A40: 工业-低情景 | B40: ='高情景（2001-2060, 2020RMB）'!U4 -> 312902.9 | C40: ='高情景（2001-2060, 2020RMB）'!V4 -> 356193.68 | D40: ='高情景（2001-2060, 2020RMB）'!W4 -> 375578.61 | E40: =VLOOKUP($A40,Python数据平滑!$A$9:$AN$21,COLUMN(Python数据平滑!C$9),0)/SUM(Python数据平滑!C$18:C$21)*情景假设!E$11 -> 388206.51 | F40: =VLOOKUP($A40,Python数据平滑!$A$9:$AN$21,COLUMN(Python数据平滑!D$9),0)/SUM(Python数据平滑!D$18:D$21)*情景假设!F$11 -> 401148.42 | G40: =G$11*P18 -> 414416.93 | H40: =VLOOKUP($A40,Python数据平滑!$A$9:$AN$21,COLUMN(Python数据平滑!F$9),0)/SUM(Python数据平滑!F$18:F$21)*情景假设!H$11 -> 428110.04 | I40: =VLOOKUP($A40,Python数据平滑!$A$9:$AN$21,COLUMN(Python数据平滑!G$9),0)/SUM(Python数据平滑!G$18:G$21)*情景假设!I$11 -> 442226.52 | J40: =VLOOKUP($A40,Python数据平滑!$A$9:$AN$21,COLUMN(Python数据平滑!H$9),0)/SUM(Python数据平滑!H$18:H$21)*情景假设!J$11 -> 456631.11 | K40: =VLOOKUP($A40,Python数据平滑!$A$9:$AN$21,COLUMN(Python数据平滑!I$9),0)/SUM(Python数据平滑!I$18:I$21)*情景假设!K$11 -> 471189.68 | L40: =L$11*Q18 -> 485769.17 | M40: =VLOOKUP($A40,Python数据平滑!$A$9:$AN$21,COLUMN(Python数据平滑!K$9),0)/SUM(Python数据平滑!K$18:K$21)*情景假设!M$11 -> 500532.46 | N40: =VLOOKUP($A40,Python数据平滑!$A$9:$AN$21,COLUMN(Python数据平滑!L$9),0)/SUM(Python数据平滑!L$18:L$21)*情景假设!N$11 -> 515582.37 | O40: =VLOOKUP($A40,Python数据平滑!$A$9:$AN$21,COLUMN(Python数据平滑!M$9),0)/SUM(Python数据平滑!M$18:M$21)*情景假设!O$11 -> 530664.45 | P40: =VLOOKUP($A40,Python数据平滑!$A$9:$AN$21,COLUMN(Python数据平滑!N$9),0)/SUM(Python数据平滑!N$18:N$21)*情景假设!P$11 -> 545483.5 | Q40: =Q$11*R18 -> 559703.95 | R40: =VLOOKUP($A40,Python数据平滑!$A$9:$AN$21,COLUMN(Python数据平滑!P$9),0)/SUM(Python数据平滑!P$18:P$21)*情景假设!R$11 -> 573162.07 | S40: =VLOOKUP($A40,Python数据平滑!$A$9:$AN$21,COLUMN(Python数据平滑!Q$9),0)/SUM(Python数据平滑!Q$18:Q$21)*情景假设!S$11 -> 586034.15 | T40: =VLOOKUP($A40,Python数据平滑!$A$9:$AN$21,COLUMN(Python数据平滑!R$9),0)/SUM(Python数据平滑!R$18:R$21)*情景假设!T$11 -> 598480.12 | U40: =VLOOKUP($A40,Python数据平滑!$A$9:$AN$21,COLUMN(Python数据平滑!S$9),0)/SUM(Python数据平滑!S$18:S$21)*情景假设!U$11 -> 610679.86 | V40: =VLOOKUP($A40,Python数据平滑!$A$9:$AN$21,COLUMN(Python数据平滑!T$9),0)/SUM(Python数据平滑!T$18:T$21)*情景假设!V$11 -> 622832.24 | W40: =VLOOKUP($A40,Python数据平滑!$A$9:$AN$21,COLUMN(Python数据平滑!U$9),0)/SUM(Python数据平滑!U$18:U$21)*情景假设!W$11 -> 634995.03 | X40: =VLOOKUP($A40,Python数据平滑!$A$9:$AN$21,COLUMN(Python数据平滑!V$9),0)/SUM(Python数据平滑!V$18:V$21)*情景假设!X$11 -> 647109.24 | Y40: =VLOOKUP($A40,Python数据平滑!$A$9:$AN$21,COLUMN(Python数据平滑!W$9),0)/SUM(Python数据平滑!W$18:W$21)*情景假设!Y$11 -> 659216.31 | ... AE40: =VLOOKUP($A40,Python数据平滑!$A$9:$AN$21,COLUMN(Python数据平滑!AC$9),0)/SUM(Python数据平滑!AC$18:AC$21)*情景假设!AE$11 -> 735079.11 | AF40: =$AF$11*S18 -> 748966.75 | AG40: =VLOOKUP($A40,Python数据平滑!$A$9:$AN$21,COLUMN(Python数据平滑!AE$9),0)/SUM(Python数据平滑!AE$18:AE$21)*情景假设!AG$11 -> 763272.62 | AH40: =VLOOKUP($A40,Python数据平滑!$A$9:$AN$21,COLUMN(Python数据平滑!AF$9),0)/SUM(Python数据平滑!AF$18:AF$21)*情景假设!AH$11 -> 777870.53 | AI40: =VLOOKUP($A40,Python数据平滑!$A$9:$AN$21,COLUMN(Python数据平滑!AG$9),0)/SUM(Python数据平滑!AG$18:AG$21)*情景假设!AI$11 -> 792756.4 | AJ40: =VLOOKUP($A40,Python数据平滑!$A$9:$AN$21,COLUMN(Python数据平滑!AH$9),0)/SUM(Python数据平滑!AH$18:AH$21)*情景假设!AJ$11 -> 807925.21 | AK40: =VLOOKUP($A40,Python数据平滑!$A$9:$AN$21,COLUMN(Python数据平滑!AI$9),0)/SUM(Python数据平滑!AI$18:AI$21)*情景假设!AK$11 -> 823370.96 | AL40: =VLOOKUP($A40,Python数据平滑!$A$9:$AN$21,COLUMN(Python数据平滑!AJ$9),0)/SUM(Python数据平滑!AJ$18:AJ$21)*情景假设!AL$11 -> 839115.42 | AM40: =VLOOKUP($A40,Python数据平滑!$A$9:$AN$21,COLUMN(Python数据平滑!AK$9),0)/SUM(Python数据平滑!AK$18:AK$21)*情景假设!AM$11 -> 855185.91 | AN40: =VLOOKUP($A40,Python数据平滑!$A$9:$AN$21,COLUMN(Python数据平滑!AL$9),0)/SUM(Python数据平滑!AL$18:AL$21)*情景假设!AN$11 -> 871583.69 | AO40: =VLOOKUP($A40,Python数据平滑!$A$9:$AN$21,COLUMN(Python数据平滑!AM$9),0)/SUM(Python数据平滑!AM$18:AM$21)*情景假设!AO$11 -> 888309.48 | AP40: =AP$11*T18 -> 905363.4
A41: 建筑业-低情景 | B41: ='高情景（2001-2060, 2020RMB）'!U5 -> 72444.7 | C41: ='高情景（2001-2060, 2020RMB）'!V5 -> 76614.92 | D41: ='高情景（2001-2060, 2020RMB）'!W5 -> 77971.749 | E41: =VLOOKUP($A41,Python数据平滑!$A$9:$AN$21,COLUMN(Python数据平滑!C$9),0)/SUM(Python数据平滑!C$18:C$21)*情景假设!E$11 -> 81138.16 | F41: =VLOOKUP($A41,Python数据平滑!$A$9:$AN$21,COLUMN(Python数据平滑!D$9),0)/SUM(Python数据平滑!D$18:D$21)*情景假设!F$11 -> 84293.695 | G41: =G$11*P19 -> 87385.039 | H41: =VLOOKUP($A41,Python数据平滑!$A$9:$AN$21,COLUMN(Python数据平滑!F$9),0)/SUM(Python数据平滑!F$18:F$21)*情景假设!H$11 -> 90448.119 | I41: =VLOOKUP($A41,Python数据平滑!$A$9:$AN$21,COLUMN(Python数据平滑!G$9),0)/SUM(Python数据平滑!G$18:G$21)*情景假设!I$11 -> 93522.801 | J41: =VLOOKUP($A41,Python数据平滑!$A$9:$AN$21,COLUMN(Python数据平滑!H$9),0)/SUM(Python数据平滑!H$18:H$21)*情景假设!J$11 -> 96555.102 | K41: =VLOOKUP($A41,Python数据平滑!$A$9:$AN$21,COLUMN(Python数据平滑!I$9),0)/SUM(Python数据平滑!I$18:I$21)*情景假设!K$11 -> 99489.047 | L41: =L$11*Q19 -> 102267.19 | M41: =VLOOKUP($A41,Python数据平滑!$A$9:$AN$21,COLUMN(Python数据平滑!K$9),0)/SUM(Python数据平滑!K$18:K$21)*情景假设!M$11 -> 104844.8 | N41: =VLOOKUP($A41,Python数据平滑!$A$9:$AN$21,COLUMN(Python数据平滑!L$9),0)/SUM(Python数据平滑!L$18:L$21)*情景假设!N$11 -> 107266.74 | O41: =VLOOKUP($A41,Python数据平滑!$A$9:$AN$21,COLUMN(Python数据平滑!M$9),0)/SUM(Python数据平滑!M$18:M$21)*情景假设!O$11 -> 109613.91 | P41: =VLOOKUP($A41,Python数据平滑!$A$9:$AN$21,COLUMN(Python数据平滑!N$9),0)/SUM(Python数据平滑!N$18:N$21)*情景假设!P$11 -> 111973.27 | Q41: =Q$11*R19 -> 114437.61 | R41: =VLOOKUP($A41,Python数据平滑!$A$9:$AN$21,COLUMN(Python数据平滑!P$9),0)/SUM(Python数据平滑!P$18:P$21)*情景假设!R$11 -> 116968.15 | S41: =VLOOKUP($A41,Python数据平滑!$A$9:$AN$21,COLUMN(Python数据平滑!Q$9),0)/SUM(Python数据平滑!Q$18:Q$21)*情景假设!S$11 -> 119476.51 | T41: =VLOOKUP($A41,Python数据平滑!$A$9:$AN$21,COLUMN(Python数据平滑!R$9),0)/SUM(Python数据平滑!R$18:R$21)*情景假设!T$11 -> 121987.31 | U41: =VLOOKUP($A41,Python数据平滑!$A$9:$AN$21,COLUMN(Python数据平滑!S$9),0)/SUM(Python数据平滑!S$18:S$21)*情景假设!U$11 -> 124527.69 | V41: =VLOOKUP($A41,Python数据平滑!$A$9:$AN$21,COLUMN(Python数据平滑!T$9),0)/SUM(Python数据平滑!T$18:T$21)*情景假设!V$11 -> 127127.41 | W41: =VLOOKUP($A41,Python数据平滑!$A$9:$AN$21,COLUMN(Python数据平滑!U$9),0)/SUM(Python数据平滑!U$18:U$21)*情景假设!W$11 -> 129786.28 | X41: =VLOOKUP($A41,Python数据平滑!$A$9:$AN$21,COLUMN(Python数据平滑!V$9),0)/SUM(Python数据平滑!V$18:V$21)*情景假设!X$11 -> 132479.06 | Y41: =VLOOKUP($A41,Python数据平滑!$A$9:$AN$21,COLUMN(Python数据平滑!W$9),0)/SUM(Python数据平滑!W$18:W$21)*情景假设!Y$11 -> 135199.72 | ... AE41: =VLOOKUP($A41,Python数据平滑!$A$9:$AN$21,COLUMN(Python数据平滑!AC$9),0)/SUM(Python数据平滑!AC$18:AC$21)*情景假设!AE$11 -> 151826.68 | AF41: =$AF$11*S19 -> 154603.23 | AG41: =VLOOKUP($A41,Python数据平滑!$A$9:$AN$21,COLUMN(Python数据平滑!AE$9),0)/SUM(Python数据平滑!AE$18:AE$21)*情景假设!AG$11 -> 157381.15 | AH41: =VLOOKUP($A41,Python数据平滑!$A$9:$AN$21,COLUMN(Python数据平滑!AF$9),0)/SUM(Python数据平滑!AF$18:AF$21)*情景假设!AH$11 -> 160174.5 | AI41: =VLOOKUP($A41,Python数据平滑!$A$9:$AN$21,COLUMN(Python数据平滑!AG$9),0)/SUM(Python数据平滑!AG$18:AG$21)*情景假设!AI$11 -> 162980.67 | AJ41: =VLOOKUP($A41,Python数据平滑!$A$9:$AN$21,COLUMN(Python数据平滑!AH$9),0)/SUM(Python数据平滑!AH$18:AH$21)*情景假设!AJ$11 -> 165796.85 | AK41: =VLOOKUP($A41,Python数据平滑!$A$9:$AN$21,COLUMN(Python数据平滑!AI$9),0)/SUM(Python数据平滑!AI$18:AI$21)*情景假设!AK$11 -> 168620.02 | AL41: =VLOOKUP($A41,Python数据平滑!$A$9:$AN$21,COLUMN(Python数据平滑!AJ$9),0)/SUM(Python数据平滑!AJ$18:AJ$21)*情景假设!AL$11 -> 171452.85 | AM41: =VLOOKUP($A41,Python数据平滑!$A$9:$AN$21,COLUMN(Python数据平滑!AK$9),0)/SUM(Python数据平滑!AK$18:AK$21)*情景假设!AM$11 -> 174299.1 | AN41: =VLOOKUP($A41,Python数据平滑!$A$9:$AN$21,COLUMN(Python数据平滑!AL$9),0)/SUM(Python数据平滑!AL$18:AL$21)*情景假设!AN$11 -> 177157.16 | AO41: =VLOOKUP($A41,Python数据平滑!$A$9:$AN$21,COLUMN(Python数据平滑!AM$9),0)/SUM(Python数据平滑!AM$18:AM$21)*情景假设!AO$11 -> 180025.31 | AP41: =AP$11*T19 -> 182901.7
A42: 服务业-低情景 | B42: ='高情景（2001-2060, 2020RMB）'!U56 -> 546822.9 | C42: ='高情景（2001-2060, 2020RMB）'!V56 -> 582938.41 | D42: ='高情景（2001-2060, 2020RMB）'!W56 -> 591543.44 | E42: =VLOOKUP($A42,Python数据平滑!$A$9:$AN$21,COLUMN(Python数据平滑!C$9),0)/SUM(Python数据平滑!C$18:C$21)*情景假设!E$11 -> 632957.41 | F42: =VLOOKUP($A42,Python数据平滑!$A$9:$AN$21,COLUMN(Python数据平滑!D$9),0)/SUM(Python数据平滑!D$18:D$21)*情景假设!F$11 -> 676742.05 | G42: =G$11*P20 -> 722912.59 | H42: =VLOOKUP($A42,Python数据平滑!$A$9:$AN$21,COLUMN(Python数据平滑!F$9),0)/SUM(Python数据平滑!F$18:F$21)*情景假设!H$11 -> 772511.66 | I42: =VLOOKUP($A42,Python数据平滑!$A$9:$AN$21,COLUMN(Python数据平滑!G$9),0)/SUM(Python数据平滑!G$18:G$21)*情景假设!I$11 -> 825906.86 | J42: =VLOOKUP($A42,Python数据平滑!$A$9:$AN$21,COLUMN(Python数据平滑!H$9),0)/SUM(Python数据平滑!H$18:H$21)*情景假设!J$11 -> 881845.59 | K42: =VLOOKUP($A42,Python数据平滑!$A$9:$AN$21,COLUMN(Python数据平滑!I$9),0)/SUM(Python数据平滑!I$18:I$21)*情景假设!K$11 -> 938720.85 | L42: =L$11*Q20 -> 994548.46 | M42: =VLOOKUP($A42,Python数据平滑!$A$9:$AN$21,COLUMN(Python数据平滑!K$9),0)/SUM(Python数据平滑!K$18:K$21)*情景假设!M$11 -> 1048503.4 | N42: =VLOOKUP($A42,Python数据平滑!$A$9:$AN$21,COLUMN(Python数据平滑!L$9),0)/SUM(Python数据平滑!L$18:L$21)*情景假设!N$11 -> 1101686.8 | O42: =VLOOKUP($A42,Python数据平滑!$A$9:$AN$21,COLUMN(Python数据平滑!M$9),0)/SUM(Python数据平滑!M$18:M$21)*情景假设!O$11 -> 1154854.6 | P42: =VLOOKUP($A42,Python数据平滑!$A$9:$AN$21,COLUMN(Python数据平滑!N$9),0)/SUM(Python数据平滑!N$18:N$21)*情景假设!P$11 -> 1208940 | Q42: =Q$11*R20 -> 1265055.8 | R42: =VLOOKUP($A42,Python数据平滑!$A$9:$AN$21,COLUMN(Python数据平滑!P$9),0)/SUM(Python数据平滑!P$18:P$21)*情景假设!R$11 -> 1323158.4 | S42: =VLOOKUP($A42,Python数据平滑!$A$9:$AN$21,COLUMN(Python数据平滑!Q$9),0)/SUM(Python数据平滑!Q$18:Q$21)*情景假设!S$11 -> 1382523.1 | T42: =VLOOKUP($A42,Python数据平滑!$A$9:$AN$21,COLUMN(Python数据平滑!R$9),0)/SUM(Python数据平滑!R$18:R$21)*情景假设!T$11 -> 1443417 | U42: =VLOOKUP($A42,Python数据平滑!$A$9:$AN$21,COLUMN(Python数据平滑!S$9),0)/SUM(Python数据平滑!S$18:S$21)*情景假设!U$11 -> 1506161 | V42: =VLOOKUP($A42,Python数据平滑!$A$9:$AN$21,COLUMN(Python数据平滑!T$9),0)/SUM(Python数据平滑!T$18:T$21)*情景假设!V$11 -> 1571134.2 | W42: =VLOOKUP($A42,Python数据平滑!$A$9:$AN$21,COLUMN(Python数据平滑!U$9),0)/SUM(Python数据平滑!U$18:U$21)*情景假设!W$11 -> 1638367 | X42: =VLOOKUP($A42,Python数据平滑!$A$9:$AN$21,COLUMN(Python数据平滑!V$9),0)/SUM(Python数据平滑!V$18:V$21)*情景假设!X$11 -> 1707563.9 | Y42: =VLOOKUP($A42,Python数据平滑!$A$9:$AN$21,COLUMN(Python数据平滑!W$9),0)/SUM(Python数据平滑!W$18:W$21)*情景假设!Y$11 -> 1778653 | ... AE42: =VLOOKUP($A42,Python数据平滑!$A$9:$AN$21,COLUMN(Python数据平滑!AC$9),0)/SUM(Python数据平滑!AC$18:AC$21)*情景假设!AE$11 -> 2240507.9 | AF42: =$AF$11*S20 -> 2322484.1 | AG42: =VLOOKUP($A42,Python数据平滑!$A$9:$AN$21,COLUMN(Python数据平滑!AE$9),0)/SUM(Python数据平滑!AE$18:AE$21)*情景假设!AG$11 -> 2405773.5 | AH42: =VLOOKUP($A42,Python数据平滑!$A$9:$AN$21,COLUMN(Python数据平滑!AF$9),0)/SUM(Python数据平滑!AF$18:AF$21)*情景假设!AH$11 -> 2490545.3 | AI42: =VLOOKUP($A42,Python数据平滑!$A$9:$AN$21,COLUMN(Python数据平滑!AG$9),0)/SUM(Python数据平滑!AG$18:AG$21)*情景假设!AI$11 -> 2576724.8 | AJ42: =VLOOKUP($A42,Python数据平滑!$A$9:$AN$21,COLUMN(Python数据平滑!AH$9),0)/SUM(Python数据平滑!AH$18:AH$21)*情景假设!AJ$11 -> 2664229.3 | AK42: =VLOOKUP($A42,Python数据平滑!$A$9:$AN$21,COLUMN(Python数据平滑!AI$9),0)/SUM(Python数据平滑!AI$18:AI$21)*情景假设!AK$11 -> 2752967.2 | AL42: =VLOOKUP($A42,Python数据平滑!$A$9:$AN$21,COLUMN(Python数据平滑!AJ$9),0)/SUM(Python数据平滑!AJ$18:AJ$21)*情景假设!AL$11 -> 2842935.5 | AM42: =VLOOKUP($A42,Python数据平滑!$A$9:$AN$21,COLUMN(Python数据平滑!AK$9),0)/SUM(Python数据平滑!AK$18:AK$21)*情景假设!AM$11 -> 2934150.1 | AN42: =VLOOKUP($A42,Python数据平滑!$A$9:$AN$21,COLUMN(Python数据平滑!AL$9),0)/SUM(Python数据平滑!AL$18:AL$21)*情景假设!AN$11 -> 3026536.6 | AO42: =VLOOKUP($A42,Python数据平滑!$A$9:$AN$21,COLUMN(Python数据平滑!AM$9),0)/SUM(Python数据平滑!AM$18:AM$21)*情景假设!AO$11 -> 3120014.5 | AP42: =AP$11*T20 -> 3214497.3
A46: 假设3：产业大类结构 | X46: 高情景年均增速 | AD46: 中情景年均增速 | AJ46: 低情景年均增速
A47: 高情景 | B47: 2019 | C47: 2022 | D47: 2025 | E47: 2030 | F47: 2035 | G47: 2050 | H47: 2060 | J47: 中情景 | K47: 2025 | L47: 2030 | M47: 2035 | N47: 2050 | O47: 2060 | Q47: 低情景 | R47: 2025 | S47: 2030 | T47: 2035 | U47: 2050 | V47: 2060 | X47: 2025 | Y47: 2030 | Z47: 2035 | AA47: 2050 | AB47: 2060 | AD47: 2025 | AE47: 2030 | AF47: 2035 | AG47: 2050 | AH47: 2060 | AJ47: 2025 | AK47: 2030 | AL47: 2035 | AM47: 2050 | AN47: 2060
A48: 能源产业 | B48: =SUM('高情景（2001-2060, 2020RMB）'!T14:T15,'高情景（2001-2060, 2020RMB）'!T33,'高情景（2001-2060, 2020RMB）'!T53:T54)/'高情景（2001-2060, 2020RMB）'!T13 -> 0.11241444 | C48: =SUM('高情景（2001-2060, 2020RMB）'!W14:W15,'高情景（2001-2060, 2020RMB）'!W33,'高情景（2001-2060, 2020RMB）'!W53:W54)/'高情景（2001-2060, 2020RMB）'!W13 -> 0.10728573 | D48: 0.105 | E48: 0.098 | F48: 0.091 | G48: 0.078 | H48: 0.07 | J48: 能源产业 | K48: =(D48*0.4+R48*0.6) -> 0.1032 | L48: =(E48*0.4+S48*0.6) -> 0.0938 | M48: =(F48*0.4+T48*0.6) -> 0.0847 | N48: =(G48*0.4+U48*0.6) -> 0.069 | O48: =(H48*0.4+V48*0.6) -> 0.0598 | Q48: 能源产业 | R48: 0.102 | S48: 0.091 | T48: 0.0805 | U48: 0.063 | V48: 0.053 | X48: =(G64/D64)^(1/3)-1 -> 0.027685407 | Y48: =(L64/G64)^0.2-1 -> 0.018229428 | Z48: =(Q64/L64)^0.2-1 -> 0.0089168371 | AA48: =(AF64/Q64)^(1/15)-1 -> 0.0069080153 | AB48: =(AP64/AF64)^0.1-1 -> 0.0055204305 | AD48: =(G77/D77)^(1/3)-1 -> 0.020766939 | AE48: =(L77/G77)^0.2-1 -> 0.013059716 | AF48: =(Q77/L77)^0.2-1 -> 0.0055144469 | AG48: =(AF77/Q77)^(1/15)-1 -> 0.0043979042 | AH48: =(AP77/AF77)^0.1-1 -> 0.0034185156 | AJ48: =(G90/D90)^(1/3)-1 -> 0.016088686 | AK48: =(L90/G90)^0.2-1 -> 0.0089897089 | AL48: =(Q90/L90)^0.2-1 -> 0.003821705 | AM48: =(AF90/Q90)^(1/15)-1 -> 0.0030823514 | AN48: =(AP90/AF90)^0.1-1 -> 0.001681312
A49: 电力与热力产业 | B49: ='高情景（2001-2060, 2020RMB）'!T52/'高情景（2001-2060, 2020RMB）'!T13 -> 0.045856952 | C49: ='高情景（2001-2060, 2020RMB）'!W52/'高情景（2001-2060, 2020RMB）'!W13 -> 0.046516835 | D49: 0.0525 | E49: 0.062 | F49: 0.065 | G49: 0.08 | H49: 0.087 | J49: 电力与热力产业 | K49: =(D49*0.4+R49*0.6) -> 0.0528 | L49: =(E49*0.4+S49*0.6) -> 0.0626 | M49: =(F49*0.4+T49*0.6) -> 0.068 | N49: =(G49*0.4+U49*0.6) -> 0.0854 | O49: =(H49*0.4+V49*0.6) -> 0.0948 | Q49: 电力与热力产业 | R49: 0.053 | S49: 0.063 | T49: 0.07 | U49: 0.089 | V49: 0.1 | X49: =(G65/D65)^(1/3)-1 -> 0.077690678 | Y49: =(L65/G65)^0.2-1 -> 0.067295716 | Z49: =(Q65/L65)^0.2-1 -> 0.033705054 | AA49: =(AF65/Q65)^(1/15)-1 -> 0.031489218 | AB49: =(AP65/AF65)^0.1-1 -> 0.025022697 | AD49: =(G78/D78)^(1/3)-1 -> 0.078670014 | AE49: =(L78/G78)^0.2-1 -> 0.068362166 | AF49: =(Q78/L78)^0.2-1 -> 0.043371852 | AG49: =(AF78/Q78)^(1/15)-1 -> 0.033803543 | AH49: =(AP78/AF78)^0.1-1 -> 0.028565488 | AJ49: =(G91/D91)^(1/3)-1 -> 0.079279969 | AK49: =(L91/G91)^0.2-1 -> 0.068590795 | AL49: =(Q91/L91)^0.2-1 -> 0.050647865 | AM49: =(AF91/Q91)^(1/15)-1 -> 0.036063584 | AN49: =(AP91/AF91)^0.1-1 -> 0.031091101
A50: 制氢 | B50: 0 | C50: 0 | D50: 0.002 | E50: 0.005 | F50: 0.012 | G50: 0.023 | H50: 0.026 | J50: 制氢 | K50: =(D50*0.4+R50*0.6) -> 0.0037645783 | L50: =(E50*0.4+S50*0.6) -> 0.011 | M50: =(F50*0.4+T50*0.6) -> 0.028026565 | N50: =(G50*0.4+U50*0.6) -> 0.037238628 | O50: =(H50*0.4+V50*0.6) -> 0.0404 | Q50: 制氢 | R50: =About!C8/情景假设!G40 -> 0.0049409638 | S50: 0.015 | T50: =About!D8/情景假设!Q40 -> 0.038710941 | U50: =About!E8/情景假设!AF40 -> 0.046731046 | V50: 0.05 | X50: =(G66/D66)^(1/3)-1 -> 8.4092432 | Y50: =(L66/G66)^0.2-1 -> 0.24001315 | Z50: =(Q66/L66)^0.2-1 -> 0.219929 | AA50: =(AF66/Q66)^(1/15)-1 -> 0.062403167 | AB50: =(AP66/AF66)^0.1-1 -> 0.028999365 | AD50: =(G79/D79)^(1/3)-1 -> 10.606103 | AE50: =(L79/G79)^0.2-1 -> 0.27957483 | AF50: =(Q79/L79)^0.2-1 -> 0.23733597 | AG50: =(AF79/Q79)^(1/15)-1 -> 0.037694876 | AH50: =(AP79/AF79)^0.1-1 -> 0.02620865 | AJ50: =(G92/D92)^(1/3)-1 -> 11.698421 | AK50: =(L92/G92)^0.2-1 -> 0.28900443 | AL50: =(Q92/L92)^0.2-1 -> 0.24352402 | AM50: =(AF92/Q92)^(1/15)-1 -> 0.032488119 | AN50: =(AP92/AF92)^0.1-1 -> 0.026059367
A51: 传统高耗能产业 | B51: =SUM('高情景（2001-2060, 2020RMB）'!T25:T26,'高情景（2001-2060, 2020RMB）'!T30,'高情景（2001-2060, 2020RMB）'!T34,'高情景（2001-2060, 2020RMB）'!T36:T37,'高情景（2001-2060, 2020RMB）'!T38:T40)/'高情景（2001-2060, 2020RMB）'!T13 -> 0.28901451 | C51: =SUM('高情景（2001-2060, 2020RMB）'!W25:W26,'高情景（2001-2060, 2020RMB）'!W30,'高情景（2001-2060, 2020RMB）'!W34,'高情景（2001-2060, 2020RMB）'!W36:W37,'高情景（2001-2060, 2020RMB）'!W38:W40)/'高情景（2001-2060, 2020RMB）'!W13 -> 0.27105648 | D51: 0.265 | E51: 0.256 | F51: 0.242 | G51: 0.212 | H51: 0.195 | J51: 传统高耗能产业 | K51: =(D51*0.4+R51*0.6) -> 0.2608 | L51: =(E51*0.4+S51*0.6) -> 0.2428 | M51: =(F51*0.4+T51*0.6) -> 0.2222 | N51: =(G51*0.4+U51*0.6) -> 0.1868 | O51: =(H51*0.4+V51*0.6) -> 0.1668 | Q51: 传统高耗能产业 | R51: 0.258 | S51: 0.234 | T51: 0.209 | U51: 0.17 | V51: 0.148 | X51: =(G67/D67)^(1/3)-1 -> 0.027321645 | Y51: =(L67/G67)^0.2-1 -> 0.025267303 | Z51: =(Q67/L67)^0.2-1 -> 0.012528804 | AA51: =(AF67/Q67)^(1/15)-1 -> 0.0083724003 | AB51: =(AP67/AF67)^0.1-1 -> 0.0079997641 | AD51: =(G80/D80)^(1/3)-1 -> 0.020853172 | AE51: =(L80/G80)^0.2-1 -> 0.017931695 | AF51: =(Q80/L80)^0.2-1 -> 0.0082106364 | AG51: =(AF80/Q80)^(1/15)-1 -> 0.0065073259 | AH51: =(AP80/AF80)^0.1-1 -> 0.0064189805 | AJ51: =(G93/D93)^(1/3)-1 -> 0.016480029 | AK51: =(L93/G93)^0.2-1 -> 0.01231978 | AL51: =(Q93/L93)^0.2-1 -> 0.0057540037 | AM51: =(AF93/Q93)^(1/15)-1 -> 0.0056660452 | AN51: =(AP93/AF93)^0.1-1 -> 0.0051186207
A52: 装备制造业 | B52: =SUM('高情景（2001-2060, 2020RMB）'!T41:T46)/'高情景（2001-2060, 2020RMB）'!T13 -> 0.25386829 | C52: =SUM('高情景（2001-2060, 2020RMB）'!W41:W46)/'高情景（2001-2060, 2020RMB）'!W13 -> 0.2703341 | D52: 0.272 | E52: 0.276 | F52: 0.282 | G52: 0.292 | H52: 0.299 | J52: 装备制造业 | K52: =(D52*0.4+R52*0.6) -> 0.2744 | L52: =(E52*0.4+S52*0.6) -> 0.2814 | M52: =(F52*0.4+T52*0.6) -> 0.2892 | N52: =(G52*0.4+U52*0.6) -> 0.3046 | O52: =(H52*0.4+V52*0.6) -> 0.3128 | Q52: 装备制造业 | R52: 0.276 | S52: 0.285 | T52: 0.294 | U52: 0.313 | V52: 0.322 | X52: =(G68/D68)^(1/3)-1 -> 0.037210972 | Y52: =(L68/G68)^0.2-1 -> 0.035395623 | Z52: =(Q68/L68)^0.2-1 -> 0.028395841 | AA52: =(AF68/Q68)^(1/15)-1 -> 0.019675145 | AB52: =(AP68/AF68)^0.1-1 -> 0.018871441 | AD52: =(G81/D81)^(1/3)-1 -> 0.039222265 | AE52: =(L81/G81)^0.2-1 -> 0.037811348 | AF52: =(Q81/L81)^0.2-1 -> 0.031874879 | AG52: =(AF81/Q81)^(1/15)-1 -> 0.021747365 | AH52: =(AP81/AF81)^0.1-1 -> 0.020588301 | AJ52: =(G94/D94)^(1/3)-1 -> 0.040514882 | AK52: =(L94/G94)^0.2-1 -> 0.038928472 | AL52: =(Q94/L94)^0.2-1 -> 0.035156893 | AM52: =(AF94/Q94)^(1/15)-1 -> 0.023874543 | AN52: =(AP94/AF94)^0.1-1 -> 0.022038351
A53: 高技术产业 | B53: =SUM('高情景（2001-2060, 2020RMB）'!T47:T48,'高情景（2001-2060, 2020RMB）'!T35)/'高情景（2001-2060, 2020RMB）'!T13 -> 0.12956589 | C53: =SUM('高情景（2001-2060, 2020RMB）'!W47:W48,'高情景（2001-2060, 2020RMB）'!W35)/'高情景（2001-2060, 2020RMB）'!W13 -> 0.14591243 | D53: 0.1515 | E53: 0.161 | F53: 0.172 | G53: 0.191 | H53: 0.206 | J53: 高技术产业 | K53: =(D53*0.4+R53*0.6) -> 0.1536 | L53: =(E53*0.4+S53*0.6) -> 0.167 | M53: =(F53*0.4+T53*0.6) -> 0.1768 | N53: =(G53*0.4+U53*0.6) -> 0.2036 | O53: =(H53*0.4+V53*0.6) -> 0.2222 | Q53: 高技术产业 | R53: 0.155 | S53: 0.171 | T53: 0.18 | U53: 0.212 | V53: 0.233 | X53: =(G69/D69)^(1/3)-1 -> 0.048136537 | Y53: =(L69/G69)^0.2-1 -> 0.045011182 | Z53: =(Q69/L69)^0.2-1 -> 0.037606827 | AA53: =(AF69/Q69)^(1/15)-1 -> 0.024440121 | AB53: =(AP69/AF69)^0.1-1 -> 0.024174458 | AD53: =(G82/D82)^(1/3)-1 -> 0.051914224 | AE53: =(L82/G82)^0.2-1 -> 0.050014917 | AF53: =(Q82/L82)^0.2-1 -> 0.038019132 | AG53: =(AF82/Q82)^(1/15)-1 -> 0.027845377 | AH53: =(AP82/AF82)^0.1-1 -> 0.026818133 | AJ53: =(G95/D95)^(1/3)-1 -> 0.054367515 | AK53: =(L95/G95)^0.2-1 -> 0.052764847 | AL53: =(Q95/L95)^0.2-1 -> 0.039347949 | AM53: =(AF95/Q95)^(1/15)-1 -> 0.030792306 | AN53: =(AP95/AF95)^0.1-1 -> 0.028816795
A54: 其他产业 | B54: =SUM('高情景（2001-2060, 2020RMB）'!T16:T24,'高情景（2001-2060, 2020RMB）'!T27:T29,'高情景（2001-2060, 2020RMB）'!T31:T32,'高情景（2001-2060, 2020RMB）'!T49:T51)/'高情景（2001-2060, 2020RMB）'!T13 -> 0.16927992 | C54: =SUM('高情景（2001-2060, 2020RMB）'!W16:W24,'高情景（2001-2060, 2020RMB）'!W27:W29,'高情景（2001-2060, 2020RMB）'!W31:W32,'高情景（2001-2060, 2020RMB）'!W49:W51)/'高情景（2001-2060, 2020RMB）'!W13 -> 0.15889442 | D54: =D55-SUM(D48:D53) -> 0.152 | E54: =E55-SUM(E48:E53) -> 0.142 | F54: =F55-SUM(F48:F53) -> 0.136 | G54: =G55-SUM(G48:G53) -> 0.124 | H54: =H55-SUM(H48:H53) -> 0.117 | J54: 其他产业 | K54: =(D54*0.4+R54*0.6) -> 0.15143542 | L54: =(E54*0.4+S54*0.6) -> 0.1414 | M54: =(F54*0.4+T54*0.6) -> 0.13107344 | N54: =(G54*0.4+U54*0.6) -> 0.11336137 | O54: =(H54*0.4+V54*0.6) -> 0.1032 | Q54: 其他产业 | R54: =R55-SUM(R48:R53) -> 0.15105904 | S54: =S55-SUM(S48:S53) -> 0.141 | T54: =T55-SUM(T48:T53) -> 0.12778906 | U54: =U55-SUM(U48:U53) -> 0.10626895 | V54: =V55-SUM(V48:V53) -> 0.094 | X54: =(G70/D70)^(1/3)-1 -> 0.019896393 | Y54: =(L70/G70)^0.2-1 -> 0.018420752 | Z54: =(Q70/L70)^0.2-1 -> 0.015178518 | AA54: =(AF70/Q70)^(1/15)-1 -> 0.011063508 | AB54: =(AP70/AF70)^0.1-1 -> 0.01057133 | AD54: =(G83/D83)^(1/3)-1 -> 0.0176231 | AE54: =(L83/G83)^0.2-1 -> 0.018532299 | AF54: =(Q83/L83)^0.2-1 -> 0.01080005 | AG54: =(AF83/Q83)^(1/15)-1 -> 0.0084122513 | AH54: =(AP83/AF83)^0.1-1 -> 0.0083663896 | AJ54: =(G96/D96)^(1/3)-1 -> 0.016072969 | AK54: =(L96/G96)^0.2-1 -> 0.018152831 | AL54: =(Q96/L96)^0.2-1 -> 0.0086966906 | AM54: =(AF96/Q96)^(1/15)-1 -> 0.0071507033 | AN54: =(AP96/AF96)^0.1-1 -> 0.0067188122
A55: 工业合计 | B55: =SUM(B48:B54) -> 1 | C55: =SUM(C48:C54) -> 1 | D55: 1 | E55: 1 | F55: 1 | G55: 1 | H55: 1 | J55: 工业合计 | K55: =SUM(K48:K54) -> 1 | L55: =SUM(L48:L54) -> 1 | M55: =SUM(M48:M54) -> 1 | N55: =SUM(N48:N54) -> 1 | O55: =SUM(O48:O54) -> 1 | Q55: 工业合计 | R55: 1 | S55: 1 | T55: 1 | U55: 1 | V55: 1
X56: =(G72/D72)^(1/3)-1 -> 0.063678929 | Y56: =(L72/G72)^0.2-1 -> 0.056753771 | Z56: =(Q72/L72)^0.2-1 -> 0.036376434 | AA56: =(AF72/Q72)^(1/15)-1 -> 0.025951814 | AB56: =(AP72/AF72)^0.1-1 -> 0.023059648 | AD56: =(G85/D85)^(1/3)-1 -> 0.057285884 | AE56: =(L85/G85)^0.2-1 -> 0.053872898 | AF56: =(Q85/L85)^0.2-1 -> 0.039846641 | AG56: =(AF85/Q85)^(1/15)-1 -> 0.028138474 | AH56: =(AP85/AF85)^0.1-1 -> 0.025536724 | AJ56: =(G98/D98)^(1/3)-1 -> 0.052899943 | AK56: =(L98/G98)^0.2-1 -> 0.051272701 | AL56: =(Q98/L98)^0.2-1 -> 0.04322724 | AM56: =(AF98/Q98)^(1/15)-1 -> 0.030348501 | AN56: =(AP98/AF98)^0.1-1 -> 0.027565471
A57: 交通运输业 | B57: ='高情景（2001-2060, 2020RMB）'!T57/'高情景（2001-2060, 2020RMB）'!T56 -> 0.080059913 | C57: ='高情景（2001-2060, 2020RMB）'!W57/'高情景（2001-2060, 2020RMB）'!W56 -> 0.078523402 | D57: 0.078 | E57: 0.076 | F57: 0.073 | G57: 0.064 | H57: 0.06 | J57: 交通运输业 | K57: =(D57*0.4+R57*0.6) -> 0.0762 | L57: =(E57*0.4+S57*0.6) -> 0.0724 | M57: =(F57*0.4+T57*0.6) -> 0.07 | N57: =(G57*0.4+U57*0.6) -> 0.0604 | O57: =(H57*0.4+V57*0.6) -> 0.057 | Q57: 交通运输业 | R57: 0.075 | S57: 0.07 | T57: 0.068 | U57: 0.058 | V57: 0.055 | X57: =(G73/D73)^(1/3)-1 -> 0.058780681 | Y57: =(L73/G73)^0.2-1 -> 0.057024942 | Z57: =(Q73/L73)^0.2-1 -> 0.038412775 | AA57: =(AF73/Q73)^(1/15)-1 -> 0.030215973 | AB57: =(AP73/AF73)^0.1-1 -> 0.027964154 | AD57: =(G86/D86)^(1/3)-1 -> 0.058565826 | AE57: =(L86/G86)^0.2-1 -> 0.056217159 | AF57: =(Q86/L86)^0.2-1 -> 0.039726438 | AG57: =(AF86/Q86)^(1/15)-1 -> 0.030268484 | AH57: =(AP86/AF86)^0.1-1 -> 0.028893756 | AJ57: =(G99/D99)^(1/3)-1 -> 0.058378624 | AK57: =(L99/G99)^0.2-1 -> 0.055164778 | AL57: =(Q99/L99)^0.2-1 -> 0.041568582 | AM57: =(AF99/Q99)^(1/15)-1 -> 0.03093197 | AN57: =(AP99/AF99)^0.1-1 -> 0.029762812
A58: 传统服务业 | B58: =SUM('高情景（2001-2060, 2020RMB）'!T58:T59)/'高情景（2001-2060, 2020RMB）'!T56 -> 0.21407854 | C58: =SUM('高情景（2001-2060, 2020RMB）'!W58:W59)/'高情景（2001-2060, 2020RMB）'!W56 -> 0.20925315 | D58: 0.205 | E58: 0.2 | F58: 0.194 | G58: 0.181 | H58: 0.178 | J58: 传统服务业 | K58: =(D58*0.4+R58*0.6) -> 0.2038 | L58: =(E58*0.4+S58*0.6) -> 0.1958 | M58: =(F58*0.4+T58*0.6) -> 0.1892 | N58: =(G58*0.4+U58*0.6) -> 0.1684 | O58: =(H58*0.4+V58*0.6) -> 0.1642 | Q58: 传统服务业 | R58: 0.203 | S58: 0.193 | T58: 0.186 | U58: 0.16 | V58: 0.155 | X58: =(G74/D74)^(1/3)-1 -> 0.06843069 | Y58: =(L74/G74)^0.2-1 -> 0.064324086 | Z58: =(Q74/L74)^0.2-1 -> 0.047342573 | AA58: =(AF74/Q74)^(1/15)-1 -> 0.037033266 | AB58: =(AP74/AF74)^0.1-1 -> 0.03063439 | AD58: =(G87/D87)^(1/3)-1 -> 0.071797046 | AE58: =(L87/G87)^0.2-1 -> 0.06817768 | AF58: =(Q87/L87)^0.2-1 -> 0.049443621 | AG58: =(AF87/Q87)^(1/15)-1 -> 0.041086355 | AH58: =(AP87/AF87)^0.1-1 -> 0.032507743 | AJ58: =(G100/D100)^(1/3)-1 -> 0.074005966 | AK58: =(L100/G100)^0.2-1 -> 0.070271818 | AL58: =(Q100/L100)^0.2-1 -> 0.05184322 | AM58: =(AF100/Q100)^(1/15)-1 -> 0.04460973 | AN58: =(AP100/AF100)^0.1-1 -> 0.034089352
A59: 现代服务业 | B59: =SUM('高情景（2001-2060, 2020RMB）'!T60:T70)/'高情景（2001-2060, 2020RMB）'!T56 -> 0.70586155 | C59: =SUM('高情景（2001-2060, 2020RMB）'!W60:W70)/'高情景（2001-2060, 2020RMB）'!W56 -> 0.71222345 | D59: =D60-D57-D58 -> 0.717 | E59: =E60-E57-E58 -> 0.724 | F59: =F60-F57-F58 -> 0.733 | G59: =G60-G57-G58 -> 0.755 | H59: =H60-H57-H58 -> 0.762 | J59: 现代服务业 | K59: =(D59*0.4+R59*0.6) -> 0.72 | L59: =(E59*0.4+S59*0.6) -> 0.7318 | M59: =(F59*0.4+T59*0.6) -> 0.7408 | N59: =(G59*0.4+U59*0.6) -> 0.7712 | O59: =(H59*0.4+V59*0.6) -> 0.7788 | Q59: 现代服务业 | R59: =R60-R57-R58 -> 0.722 | S59: =S60-S57-S58 -> 0.737 | T59: =T60-T57-T58 -> 0.746 | U59: =U60-U57-U58 -> 0.782 | V59: =V60-V57-V58 -> 0.79
A60: 服务业合计 | B60: =SUM(B57:B59) -> 1 | C60: =SUM(C57:C59) -> 1 | D60: 1 | E60: 1 | F60: 1 | G60: 1 | H60: 1 | J60: 服务业合计 | K60: =(D60*0.4+R60*0.6) -> 1 | L60: =(E60*0.4+S60*0.6) -> 1 | M60: =(F60*0.4+T60*0.6) -> 1 | N60: =(G60*0.4+U60*0.6) -> 1 | O60: =(H60*0.4+V60*0.6) -> 1 | Q60: 服务业合计 | R60: 1 | S60: 1 | T60: 1 | U60: 1 | V60: 1
A62: 结果3：
A63: 高情景 | B63: 2020 | C63: 2021 | D63: 2022 | E63: 2023 | F63: 2024 | G63: 2025 | H63: 2026 | I63: 2027 | J63: 2028 | K63: 2029 | L63: 2030 | M63: 2031 | N63: 2032 | O63: 2033 | P63: 2034 | Q63: 2035 | R63: 2036 | S63: 2037 | T63: 2038 | U63: 2039 | V63: 2040 | W63: 2041 | X63: 2042 | Y63: 2043 | Z63: 2044 | AA63: 2045 | AB63: 2046 | AC63: 2047 | AD63: 2048 | AE63: 2049 | AF63: 2050 | AG63: 2051 | AH63: 2052 | AI63: 2053 | AJ63: 2054 | AK63: 2055 | AL63: 2056 | AM63: 2057 | AN63: 2058 | AO63: 2059 | AP63: 2060
A64: 能源产业-高情景 | B64: =SUM('高情景（2001-2060, 2020RMB）'!U14:U15,'高情景（2001-2060, 2020RMB）'!U33,'高情景（2001-2060, 2020RMB）'!U53:U54) -> 34486.847 | C64: =SUM('高情景（2001-2060, 2020RMB）'!V14:V15,'高情景（2001-2060, 2020RMB）'!V33,'高情景（2001-2060, 2020RMB）'!V53:V54) -> 37878.28 | D64: =SUM('高情景（2001-2060, 2020RMB）'!W14:W15,'高情景（2001-2060, 2020RMB）'!W33,'高情景（2001-2060, 2020RMB）'!W53:W54) -> 40294.225 | E64: =VLOOKUP($A64,Python数据平滑!$A$25:$AN$52,COLUMN(Python数据平滑!C$25),0)/SUM(Python数据平滑!C$26:C$32)*情景假设!E$28 -> 41545.53 | F64: =VLOOKUP($A64,Python数据平滑!$A$25:$AN$52,COLUMN(Python数据平滑!D$25),0)/SUM(Python数据平滑!D$26:D$32)*情景假设!F$28 -> 42714.88 | G64: =G$28*D48 -> 43734.421 | H64: =VLOOKUP($A64,Python数据平滑!$A$25:$AN$52,COLUMN(Python数据平滑!F$25),0)/SUM(Python数据平滑!F$26:F$32)*情景假设!H$28 -> 44689.347 | I64: =VLOOKUP($A64,Python数据平滑!$A$25:$AN$52,COLUMN(Python数据平滑!G$25),0)/SUM(Python数据平滑!G$26:G$32)*情景假设!I$28 -> 45597.786 | J64: =VLOOKUP($A64,Python数据平滑!$A$25:$AN$52,COLUMN(Python数据平滑!H$25),0)/SUM(Python数据平滑!H$26:H$32)*情景假设!J$28 -> 46443.84 | K64: =VLOOKUP($A64,Python数据平滑!$A$25:$AN$52,COLUMN(Python数据平滑!I$25),0)/SUM(Python数据平滑!I$26:I$32)*情景假设!K$28 -> 47208.248 | L64: =L$28*E48 -> 47868.696 | M64: =VLOOKUP($A64,Python数据平滑!$A$25:$AN$52,COLUMN(Python数据平滑!K$25),0)/SUM(Python数据平滑!K$26:K$32)*情景假设!M$28 -> 48416.907 | N64: =VLOOKUP($A64,Python数据平滑!$A$25:$AN$52,COLUMN(Python数据平滑!L$25),0)/SUM(Python数据平滑!L$26:L$32)*情景假设!N$28 -> 48877.253 | O64: =VLOOKUP($A64,Python数据平滑!$A$25:$AN$52,COLUMN(Python数据平滑!M$25),0)/SUM(Python数据平滑!M$26:M$32)*情景假设!O$28 -> 49276.768 | P64: =VLOOKUP($A64,Python数据平滑!$A$25:$AN$52,COLUMN(Python数据平滑!N$25),0)/SUM(Python数据平滑!N$26:N$32)*情景假设!P$28 -> 49650.233 | Q64: =Q$28*F48 -> 50041.285 | R64: =VLOOKUP($A64,Python数据平滑!$A$25:$AN$52,COLUMN(Python数据平滑!P$25),0)/SUM(Python数据平滑!P$26:P$32)*情景假设!R$28 -> 50423.854 | S64: =VLOOKUP($A64,Python数据平滑!$A$25:$AN$52,COLUMN(Python数据平滑!Q$25),0)/SUM(Python数据平滑!Q$26:Q$32)*情景假设!S$28 -> 50756.156 | T64: =VLOOKUP($A64,Python数据平滑!$A$25:$AN$52,COLUMN(Python数据平滑!R$25),0)/SUM(Python数据平滑!R$26:R$32)*情景假设!T$28 -> 51064.192 | U64: =VLOOKUP($A64,Python数据平滑!$A$25:$AN$52,COLUMN(Python数据平滑!S$25),0)/SUM(Python数据平滑!S$26:S$32)*情景假设!U$28 -> 51374.575 | V64: =VLOOKUP($A64,Python数据平滑!$A$25:$AN$52,COLUMN(Python数据平滑!T$25),0)/SUM(Python数据平滑!T$26:T$32)*情景假设!V$28 -> 51714.465 | W64: =VLOOKUP($A64,Python数据平滑!$A$25:$AN$52,COLUMN(Python数据平滑!U$25),0)/SUM(Python数据平滑!U$26:U$32)*情景假设!W$28 -> 52082.95 | X64: =VLOOKUP($A64,Python数据平滑!$A$25:$AN$52,COLUMN(Python数据平滑!V$25),0)/SUM(Python数据平滑!V$26:V$32)*情景假设!X$28 -> 52459.386 | Y64: =VLOOKUP($A64,Python数据平滑!$A$25:$AN$52,COLUMN(Python数据平滑!W$25),0)/SUM(Python数据平滑!W$26:W$32)*情景假设!Y$28 -> 52841.668 | ... AE64: =VLOOKUP($A64,Python数据平滑!$A$25:$AN$52,COLUMN(Python数据平滑!AC$25),0)/SUM(Python数据平滑!AC$26:AC$32)*情景假设!AE$28 -> 55138.008 | AF64: =$AF$28*G48 -> 55484.978 | AG64: =VLOOKUP($A64,Python数据平滑!$A$25:$AN$52,COLUMN(Python数据平滑!AE$25),0)/SUM(Python数据平滑!AE$26:AE$32)*情景假设!AG$28 -> 55817.65 | AH64: =VLOOKUP($A64,Python数据平滑!$A$25:$AN$52,COLUMN(Python数据平滑!AF$25),0)/SUM(Python数据平滑!AF$26:AF$32)*情景假设!AH$28 -> 56146.212 | AI64: =VLOOKUP($A64,Python数据平滑!$A$25:$AN$52,COLUMN(Python数据平滑!AG$25),0)/SUM(Python数据平滑!AG$26:AG$32)*情景假设!AI$28 -> 56470.356 | AJ64: =VLOOKUP($A64,Python数据平滑!$A$25:$AN$52,COLUMN(Python数据平滑!AH$25),0)/SUM(Python数据平滑!AH$26:AH$32)*情景假设!AJ$28 -> 56789.773 | AK64: =VLOOKUP($A64,Python数据平滑!$A$25:$AN$52,COLUMN(Python数据平滑!AI$25),0)/SUM(Python数据平滑!AI$26:AI$32)*情景假设!AK$28 -> 57104.147 | AL64: =VLOOKUP($A64,Python数据平滑!$A$25:$AN$52,COLUMN(Python数据平滑!AJ$25),0)/SUM(Python数据平滑!AJ$26:AJ$32)*情景假设!AL$28 -> 57414.409 | AM64: =VLOOKUP($A64,Python数据平滑!$A$25:$AN$52,COLUMN(Python数据平滑!AK$25),0)/SUM(Python数据平滑!AK$26:AK$32)*情景假设!AM$28 -> 57721.691 | AN64: =VLOOKUP($A64,Python数据平滑!$A$25:$AN$52,COLUMN(Python数据平滑!AL$25),0)/SUM(Python数据平滑!AL$26:AL$32)*情景假设!AN$28 -> 58025.964 | AO64: =VLOOKUP($A64,Python数据平滑!$A$25:$AN$52,COLUMN(Python数据平滑!AM$25),0)/SUM(Python数据平滑!AM$26:AM$32)*情景假设!AO$28 -> 58327.168 | AP64: =AP$28*H48 -> 58625.21
A65: 电力与热力产业-高情景 | B65: ='高情景（2001-2060, 2020RMB）'!U52 -> 14171.805 | C65: ='高情景（2001-2060, 2020RMB）'!V52 -> 16363.885 | D65: ='高情景（2001-2060, 2020RMB）'!W52 -> 17470.728 | E65: =VLOOKUP($A65,Python数据平滑!$A$25:$AN$52,COLUMN(Python数据平滑!C$25),0)/SUM(Python数据平滑!C$26:C$32)*情景假设!E$28 -> 18889.449 | F65: =VLOOKUP($A65,Python数据平滑!$A$25:$AN$52,COLUMN(Python数据平滑!D$25),0)/SUM(Python数据平滑!D$26:D$32)*情景假设!F$28 -> 20363.493 | G65: =G$28*D49 -> 21867.21 | H65: =VLOOKUP($A65,Python数据平滑!$A$25:$AN$52,COLUMN(Python数据平滑!F$25),0)/SUM(Python数据平滑!F$26:F$32)*情景假设!H$28 -> 23490.722 | I65: =VLOOKUP($A65,Python数据平滑!$A$25:$AN$52,COLUMN(Python数据平滑!G$25),0)/SUM(Python数据平滑!G$26:G$32)*情景假设!I$28 -> 25246.086 | J65: =VLOOKUP($A65,Python数据平滑!$A$25:$AN$52,COLUMN(Python数据平滑!H$25),0)/SUM(Python数据平滑!H$26:H$32)*情景假设!J$28 -> 27045.484 | K65: =VLOOKUP($A65,Python数据平滑!$A$25:$AN$52,COLUMN(Python数据平滑!I$25),0)/SUM(Python数据平滑!I$26:I$32)*情景假设!K$28 -> 28772.793 | L65: =L$28*E49 -> 30284.277 | M65: =VLOOKUP($A65,Python数据平滑!$A$25:$AN$52,COLUMN(Python数据平滑!K$25),0)/SUM(Python数据平滑!K$26:K$32)*情景假设!M$28 -> 31539.786 | N65: =VLOOKUP($A65,Python数据平滑!$A$25:$AN$52,COLUMN(Python数据平滑!L$25),0)/SUM(Python数据平滑!L$26:L$32)*情景假设!N$28 -> 32641.919 | O65: =VLOOKUP($A65,Python数据平滑!$A$25:$AN$52,COLUMN(Python数据平滑!M$25),0)/SUM(Python数据平滑!M$26:M$32)*情景假设!O$28 -> 33654.325 | P65: =VLOOKUP($A65,Python数据平滑!$A$25:$AN$52,COLUMN(Python数据平滑!N$25),0)/SUM(Python数据平滑!N$26:N$32)*情景假设!P$28 -> 34656.429 | Q65: =Q$28*F49 -> 35743.775 | R65: =VLOOKUP($A65,Python数据平滑!$A$25:$AN$52,COLUMN(Python数据平滑!P$25),0)/SUM(Python数据平滑!P$26:P$32)*情景假设!R$28 -> 36908.712 | S65: =VLOOKUP($A65,Python数据平滑!$A$25:$AN$52,COLUMN(Python数据平滑!Q$25),0)/SUM(Python数据平滑!Q$26:Q$32)*情景假设!S$28 -> 38081.83 | T65: =VLOOKUP($A65,Python数据平滑!$A$25:$AN$52,COLUMN(Python数据平滑!R$25),0)/SUM(Python数据平滑!R$26:R$32)*情景假设!T$28 -> 39279.479 | U65: =VLOOKUP($A65,Python数据平滑!$A$25:$AN$52,COLUMN(Python数据平滑!S$25),0)/SUM(Python数据平滑!S$26:S$32)*情景假设!U$28 -> 40520.066 | V65: =VLOOKUP($A65,Python数据平滑!$A$25:$AN$52,COLUMN(Python数据平滑!T$25),0)/SUM(Python数据平滑!T$26:T$32)*情景假设!V$28 -> 41824.201 | W65: =VLOOKUP($A65,Python数据平滑!$A$25:$AN$52,COLUMN(Python数据平滑!U$25),0)/SUM(Python数据平滑!U$26:U$32)*情景假设!W$28 -> 43191.126 | X65: =VLOOKUP($A65,Python数据平滑!$A$25:$AN$52,COLUMN(Python数据平滑!V$25),0)/SUM(Python数据平滑!V$26:V$32)*情景假设!X$28 -> 44602.959 | Y65: =VLOOKUP($A65,Python数据平滑!$A$25:$AN$52,COLUMN(Python数据平滑!W$25),0)/SUM(Python数据平滑!W$26:W$32)*情景假设!Y$28 -> 46055.899 | ... AE65: =VLOOKUP($A65,Python数据平滑!$A$25:$AN$52,COLUMN(Python数据平滑!AC$25),0)/SUM(Python数据平滑!AC$26:AC$32)*情景假设!AE$28 -> 55344.064 | AF65: =$AF$28*G49 -> 56907.67 | AG65: =VLOOKUP($A65,Python数据平滑!$A$25:$AN$52,COLUMN(Python数据平滑!AE$25),0)/SUM(Python数据平滑!AE$26:AE$32)*情景假设!AG$28 -> 58464.953 | AH65: =VLOOKUP($A65,Python数据平滑!$A$25:$AN$52,COLUMN(Python数据平滑!AF$25),0)/SUM(Python数据平滑!AF$26:AF$32)*情景假设!AH$28 -> 60033.666 | AI65: =VLOOKUP($A65,Python数据平滑!$A$25:$AN$52,COLUMN(Python数据平滑!AG$25),0)/SUM(Python数据平滑!AG$26:AG$32)*情景假设!AI$28 -> 61612.425 | AJ65: =VLOOKUP($A65,Python数据平滑!$A$25:$AN$52,COLUMN(Python数据平滑!AH$25),0)/SUM(Python数据平滑!AH$26:AH$32)*情景假设!AJ$28 -> 63199.797 | AK65: =VLOOKUP($A65,Python数据平滑!$A$25:$AN$52,COLUMN(Python数据平滑!AI$25),0)/SUM(Python数据平滑!AI$26:AI$32)*情景假设!AK$28 -> 64794.291 | AL65: =VLOOKUP($A65,Python数据平滑!$A$25:$AN$52,COLUMN(Python数据平滑!AJ$25),0)/SUM(Python数据平滑!AJ$26:AJ$32)*情景假设!AL$28 -> 66395.81 | AM65: =VLOOKUP($A65,Python数据平滑!$A$25:$AN$52,COLUMN(Python数据平滑!AK$25),0)/SUM(Python数据平滑!AK$26:AK$32)*情景假设!AM$28 -> 68004.556 | AN65: =VLOOKUP($A65,Python数据平滑!$A$25:$AN$52,COLUMN(Python数据平滑!AL$25),0)/SUM(Python数据平滑!AL$26:AL$32)*情景假设!AN$28 -> 69619.417 | AO65: =VLOOKUP($A65,Python数据平滑!$A$25:$AN$52,COLUMN(Python数据平滑!AM$25),0)/SUM(Python数据平滑!AM$26:AM$32)*情景假设!AO$28 -> 71239.228 | AP65: =AP$28*H49 -> 72862.761
A66: 制氢-高情景 | B66: 0 | C66: 0 | D66: 1 | E66: =VLOOKUP($A66,Python数据平滑!$A$25:$AN$52,COLUMN(Python数据平滑!C$25),0)/SUM(Python数据平滑!C$26:C$32)*情景假设!E$28 -> 19.776807 | F66: =VLOOKUP($A66,Python数据平滑!$A$25:$AN$52,COLUMN(Python数据平滑!D$25),0)/SUM(Python数据平滑!D$26:D$32)*情景假设!F$28 -> 235.536 | G66: =G$28*D50 -> 833.03659 | H66: =VLOOKUP($A66,Python数据平滑!$A$25:$AN$52,COLUMN(Python数据平滑!F$25),0)/SUM(Python数据平滑!F$26:F$32)*情景假设!H$28 -> 1180.4173 | I66: =VLOOKUP($A66,Python数据平滑!$A$25:$AN$52,COLUMN(Python数据平滑!G$25),0)/SUM(Python数据平滑!G$26:G$32)*情景假设!I$28 -> 1491.799 | J66: =VLOOKUP($A66,Python数据平滑!$A$25:$AN$52,COLUMN(Python数据平滑!H$25),0)/SUM(Python数据平滑!H$26:H$32)*情景假设!J$28 -> 1763.6994 | K66: =VLOOKUP($A66,Python数据平滑!$A$25:$AN$52,COLUMN(Python数据平滑!I$25),0)/SUM(Python数据平滑!I$26:I$32)*情景假设!K$28 -> 2045.9257 | L66: =L$28*E50 -> 2442.2804 | M66: =VLOOKUP($A66,Python数据平滑!$A$25:$AN$52,COLUMN(Python数据平滑!K$25),0)/SUM(Python数据平滑!K$26:K$32)*情景假设!M$28 -> 3042.481 | N66: =VLOOKUP($A66,Python数据平滑!$A$25:$AN$52,COLUMN(Python数据平滑!L$25),0)/SUM(Python数据平滑!L$26:L$32)*情景假设!N$28 -> 3831.0937 | O66: =VLOOKUP($A66,Python数据平滑!$A$25:$AN$52,COLUMN(Python数据平滑!M$25),0)/SUM(Python数据平滑!M$26:M$32)*情景假设!O$28 -> 4773.5282 | P66: =VLOOKUP($A66,Python数据平滑!$A$25:$AN$52,COLUMN(Python数据平滑!N$25),0)/SUM(Python数据平滑!N$26:N$32)*情景假设!P$28 -> 5762.2738 | Q66: =Q$28*F50 -> 6598.8507 | R66: =VLOOKUP($A66,Python数据平滑!$A$25:$AN$52,COLUMN(Python数据平滑!P$25),0)/SUM(Python数据平滑!P$26:P$32)*情景假设!R$28 -> 7276.2164 | S66: =VLOOKUP($A66,Python数据平滑!$A$25:$AN$52,COLUMN(Python数据平滑!Q$25),0)/SUM(Python数据平滑!Q$26:Q$32)*情景假设!S$28 -> 7956.0683 | T66: =VLOOKUP($A66,Python数据平滑!$A$25:$AN$52,COLUMN(Python数据平滑!R$25),0)/SUM(Python数据平滑!R$26:R$32)*情景假设!T$28 -> 8635.5725 | U66: =VLOOKUP($A66,Python数据平滑!$A$25:$AN$52,COLUMN(Python数据平滑!S$25),0)/SUM(Python数据平滑!S$26:S$32)*情景假设!U$28 -> 9313.7941 | V66: =VLOOKUP($A66,Python数据平滑!$A$25:$AN$52,COLUMN(Python数据平滑!T$25),0)/SUM(Python数据平滑!T$26:T$32)*情景假设!V$28 -> 9991.8786 | W66: =VLOOKUP($A66,Python数据平滑!$A$25:$AN$52,COLUMN(Python数据平滑!U$25),0)/SUM(Python数据平滑!U$26:U$32)*情景假设!W$28 -> 10667.301 | X66: =VLOOKUP($A66,Python数据平滑!$A$25:$AN$52,COLUMN(Python数据平滑!V$25),0)/SUM(Python数据平滑!V$26:V$32)*情景假设!X$28 -> 11334.109 | Y66: =VLOOKUP($A66,Python数据平滑!$A$25:$AN$52,COLUMN(Python数据平滑!W$25),0)/SUM(Python数据平滑!W$26:W$32)*情景假设!Y$28 -> 11990.614 | ... AE66: =VLOOKUP($A66,Python数据平滑!$A$25:$AN$52,COLUMN(Python数据平滑!AC$25),0)/SUM(Python数据平滑!AC$26:AC$32)*情景假设!AE$28 -> 15744.127 | AF66: =$AF$28*G50 -> 16360.955 | AG66: =VLOOKUP($A66,Python数据平滑!$A$25:$AN$52,COLUMN(Python数据平滑!AE$25),0)/SUM(Python数据平滑!AE$26:AE$32)*情景假设!AG$28 -> 16982.17 | AH66: =VLOOKUP($A66,Python数据平滑!$A$25:$AN$52,COLUMN(Python数据平滑!AF$25),0)/SUM(Python数据平滑!AF$26:AF$32)*情景假设!AH$28 -> 17602.665 | AI66: =VLOOKUP($A66,Python数据平滑!$A$25:$AN$52,COLUMN(Python数据平滑!AG$25),0)/SUM(Python数据平滑!AG$26:AG$32)*情景假设!AI$28 -> 18216.829 | AJ66: =VLOOKUP($A66,Python数据平滑!$A$25:$AN$52,COLUMN(Python数据平滑!AH$25),0)/SUM(Python数据平滑!AH$26:AH$32)*情景假设!AJ$28 -> 18818.484 | AK66: =VLOOKUP($A66,Python数据平滑!$A$25:$AN$52,COLUMN(Python数据平滑!AI$25),0)/SUM(Python数据平滑!AI$26:AI$32)*情景假设!AK$28 -> 19400.921 | AL66: =VLOOKUP($A66,Python数据平滑!$A$25:$AN$52,COLUMN(Python数据平滑!AJ$25),0)/SUM(Python数据平滑!AJ$26:AJ$32)*情景假设!AL$28 -> 19957.392 | AM66: =VLOOKUP($A66,Python数据平滑!$A$25:$AN$52,COLUMN(Python数据平滑!AK$25),0)/SUM(Python数据平滑!AK$26:AK$32)*情景假设!AM$28 -> 20480.855 | AN66: =VLOOKUP($A66,Python数据平滑!$A$25:$AN$52,COLUMN(Python数据平滑!AL$25),0)/SUM(Python数据平滑!AL$26:AL$32)*情景假设!AN$28 -> 20963.583 | AO66: =VLOOKUP($A66,Python数据平滑!$A$25:$AN$52,COLUMN(Python数据平滑!AM$25),0)/SUM(Python数据平滑!AM$26:AM$32)*情景假设!AO$28 -> 21397.652 | AP66: =AP$28*H50 -> 21775.078
A67: 传统高耗能产业-高情景 | B67: =SUM('高情景（2001-2060, 2020RMB）'!U25:U26,'高情景（2001-2060, 2020RMB）'!U30,'高情景（2001-2060, 2020RMB）'!U34,'高情景（2001-2060, 2020RMB）'!U36:U37,'高情景（2001-2060, 2020RMB）'!U38:U40) -> 90023.293 | C67: =SUM('高情景（2001-2060, 2020RMB）'!V25:V26,'高情景（2001-2060, 2020RMB）'!V30,'高情景（2001-2060, 2020RMB）'!V34,'高情景（2001-2060, 2020RMB）'!V36:V37,'高情景（2001-2060, 2020RMB）'!V38:V40) -> 98562.089 | D67: =SUM('高情景（2001-2060, 2020RMB）'!W25:W26,'高情景（2001-2060, 2020RMB）'!W30,'高情景（2001-2060, 2020RMB）'!W34,'高情景（2001-2060, 2020RMB）'!W36:W37,'高情景（2001-2060, 2020RMB）'!W38:W40) -> 101803.01 | E67: =VLOOKUP($A67,Python数据平滑!$A$25:$AN$52,COLUMN(Python数据平滑!C$25),0)/SUM(Python数据平滑!C$26:C$32)*情景假设!E$28 -> 104702.18 | F67: =VLOOKUP($A67,Python数据平滑!$A$25:$AN$52,COLUMN(Python数据平滑!D$25),0)/SUM(Python数据平滑!D$26:D$32)*情景假设!F$28 -> 107574.8 | G67: =G$28*D51 -> 110377.35 | H67: =VLOOKUP($A67,Python数据平滑!$A$25:$AN$52,COLUMN(Python数据平滑!F$25),0)/SUM(Python数据平滑!F$26:F$32)*情景假设!H$28 -> 113387.95 | I67: =VLOOKUP($A67,Python数据平滑!$A$25:$AN$52,COLUMN(Python数据平滑!G$25),0)/SUM(Python数据平滑!G$26:G$32)*情景假设!I$28 -> 116545.76 | J67: =VLOOKUP($A67,Python数据平滑!$A$25:$AN$52,COLUMN(Python数据平滑!H$25),0)/SUM(Python数据平滑!H$26:H$32)*情景假设!J$28 -> 119677.71 | K67: =VLOOKUP($A67,Python数据平滑!$A$25:$AN$52,COLUMN(Python数据平滑!I$25),0)/SUM(Python数据平滑!I$26:I$32)*情景假设!K$28 -> 122584.93 | L67: =L$28*E51 -> 125044.76 | M67: =VLOOKUP($A67,Python数据平滑!$A$25:$AN$52,COLUMN(Python数据平滑!K$25),0)/SUM(Python数据平滑!K$26:K$32)*情景假设!M$28 -> 127045.53 | N67: =VLOOKUP($A67,Python数据平滑!$A$25:$AN$52,COLUMN(Python数据平滑!L$25),0)/SUM(Python数据平滑!L$26:L$32)*情景假设!N$28 -> 128772.4 | O67: =VLOOKUP($A67,Python数据平滑!$A$25:$AN$52,COLUMN(Python数据平滑!M$25),0)/SUM(Python数据平滑!M$26:M$32)*情景假设!O$28 -> 130290.78 | P67: =VLOOKUP($A67,Python数据平滑!$A$25:$AN$52,COLUMN(Python数据平滑!N$25),0)/SUM(Python数据平滑!N$26:N$32)*情景假设!P$28 -> 131688.11 | Q67: =Q$28*F51 -> 133076.82 | R67: =VLOOKUP($A67,Python数据平滑!$A$25:$AN$52,COLUMN(Python数据平滑!P$25),0)/SUM(Python数据平滑!P$26:P$32)*情景假设!R$28 -> 134395.64 | S67: =VLOOKUP($A67,Python数据平滑!$A$25:$AN$52,COLUMN(Python数据平滑!Q$25),0)/SUM(Python数据平滑!Q$26:Q$32)*情景假设!S$28 -> 135545.6 | T67: =VLOOKUP($A67,Python数据平滑!$A$25:$AN$52,COLUMN(Python数据平滑!R$25),0)/SUM(Python数据平滑!R$26:R$32)*情景假设!T$28 -> 136600.18 | U67: =VLOOKUP($A67,Python数据平滑!$A$25:$AN$52,COLUMN(Python数据平滑!S$25),0)/SUM(Python数据平滑!S$26:S$32)*情景假设!U$28 -> 137635.28 | V67: =VLOOKUP($A67,Python数据平滑!$A$25:$AN$52,COLUMN(Python数据平滑!T$25),0)/SUM(Python数据平滑!T$26:T$32)*情景假设!V$28 -> 138728.93 | W67: =VLOOKUP($A67,Python数据平滑!$A$25:$AN$52,COLUMN(Python数据平滑!U$25),0)/SUM(Python数据平滑!U$26:U$32)*情景假设!W$28 -> 139884.25 | X67: =VLOOKUP($A67,Python数据平滑!$A$25:$AN$52,COLUMN(Python数据平滑!V$25),0)/SUM(Python数据平滑!V$26:V$32)*情景假设!X$28 -> 141051.48 | Y67: =VLOOKUP($A67,Python数据平滑!$A$25:$AN$52,COLUMN(Python数据平滑!W$25),0)/SUM(Python数据平滑!W$26:W$32)*情景假设!Y$28 -> 142230.65 | ... AE67: =VLOOKUP($A67,Python数据平滑!$A$25:$AN$52,COLUMN(Python数据平滑!AC$25),0)/SUM(Python数据平滑!AC$26:AC$32)*情景假设!AE$28 -> 149574.01 | AF67: =$AF$28*G51 -> 150805.33 | AG67: =VLOOKUP($A67,Python数据平滑!$A$25:$AN$52,COLUMN(Python数据平滑!AE$25),0)/SUM(Python数据平滑!AE$26:AE$32)*情景假设!AG$28 -> 152028.87 | AH67: =VLOOKUP($A67,Python数据平滑!$A$25:$AN$52,COLUMN(Python数据平滑!AF$25),0)/SUM(Python数据平滑!AF$26:AF$32)*情景假设!AH$28 -> 153257.83 | AI67: =VLOOKUP($A67,Python数据平滑!$A$25:$AN$52,COLUMN(Python数据平滑!AG$25),0)/SUM(Python数据平滑!AG$26:AG$32)*情景假设!AI$28 -> 154491.63 | AJ67: =VLOOKUP($A67,Python数据平滑!$A$25:$AN$52,COLUMN(Python数据平滑!AH$25),0)/SUM(Python数据平滑!AH$26:AH$32)*情景假设!AJ$28 -> 155729.69 | AK67: =VLOOKUP($A67,Python数据平滑!$A$25:$AN$52,COLUMN(Python数据平滑!AI$25),0)/SUM(Python数据平滑!AI$26:AI$32)*情景假设!AK$28 -> 156971.41 | AL67: =VLOOKUP($A67,Python数据平滑!$A$25:$AN$52,COLUMN(Python数据平滑!AJ$25),0)/SUM(Python数据平滑!AJ$26:AJ$32)*情景假设!AL$28 -> 158219.62 | AM67: =VLOOKUP($A67,Python数据平滑!$A$25:$AN$52,COLUMN(Python数据平滑!AK$25),0)/SUM(Python数据平滑!AK$26:AK$32)*情景假设!AM$28 -> 159477.71 | AN67: =VLOOKUP($A67,Python数据平滑!$A$25:$AN$52,COLUMN(Python数据平滑!AL$25),0)/SUM(Python数据平滑!AL$26:AL$32)*情景假设!AN$28 -> 160745.91 | AO67: =VLOOKUP($A67,Python数据平滑!$A$25:$AN$52,COLUMN(Python数据平滑!AM$25),0)/SUM(Python数据平滑!AM$26:AM$32)*情景假设!AO$28 -> 162024.35 | AP67: =AP$28*H51 -> 163313.08
A68: 装备制造业-高情景 | B68: =SUM('高情景（2001-2060, 2020RMB）'!U41:U46) -> 81720.66 | C68: =SUM('高情景（2001-2060, 2020RMB）'!V41:V46) -> 95333.93 | D68: =SUM('高情景（2001-2060, 2020RMB）'!W41:W46) -> 101531.7 | E68: =VLOOKUP($A68,Python数据平滑!$A$25:$AN$52,COLUMN(Python数据平滑!C$25),0)/SUM(Python数据平滑!C$26:C$32)*情景假设!E$28 -> 105420.88 | F68: =VLOOKUP($A68,Python数据平滑!$A$25:$AN$52,COLUMN(Python数据平滑!D$25),0)/SUM(Python数据平滑!D$26:D$32)*情景假设!F$28 -> 109354.95 | G68: =G$28*D52 -> 113292.98 | H68: =VLOOKUP($A68,Python数据平滑!$A$25:$AN$52,COLUMN(Python数据平滑!F$25),0)/SUM(Python数据平滑!F$26:F$32)*情景假设!H$28 -> 117437.78 | I68: =VLOOKUP($A68,Python数据平滑!$A$25:$AN$52,COLUMN(Python数据平滑!G$25),0)/SUM(Python数据平滑!G$26:G$32)*情景假设!I$28 -> 121721.05 | J68: =VLOOKUP($A68,Python数据平滑!$A$25:$AN$52,COLUMN(Python数据平滑!H$25),0)/SUM(Python数据平滑!H$26:H$32)*情景假设!J$28 -> 126091.67 | K68: =VLOOKUP($A68,Python数据平滑!$A$25:$AN$52,COLUMN(Python数据平滑!I$25),0)/SUM(Python数据平滑!I$26:I$32)*情景假设!K$28 -> 130483.34 | L68: =L$28*E52 -> 134813.88 | M68: =VLOOKUP($A68,Python数据平滑!$A$25:$AN$52,COLUMN(Python数据平滑!K$25),0)/SUM(Python数据平滑!K$26:K$32)*情景假设!M$28 -> 139064.97 | N68: =VLOOKUP($A68,Python数据平滑!$A$25:$AN$52,COLUMN(Python数据平滑!L$25),0)/SUM(Python数据平滑!L$26:L$32)*情景假设!N$28 -> 143251.46 | O68: =VLOOKUP($A68,Python数据平滑!$A$25:$AN$52,COLUMN(Python数据平滑!M$25),0)/SUM(Python数据平滑!M$26:M$32)*情景假设!O$28 -> 147329.48 | P68: =VLOOKUP($A68,Python数据平滑!$A$25:$AN$52,COLUMN(Python数据平滑!N$25),0)/SUM(Python数据平滑!N$26:N$32)*情景假设!P$28 -> 151271.56 | Q68: =Q$28*F52 -> 155072.99 | R68: =VLOOKUP($A68,Python数据平滑!$A$25:$AN$52,COLUMN(Python数据平滑!P$25),0)/SUM(Python数据平滑!P$26:P$32)*情景假设!R$28 -> 158672.91 | S68: =VLOOKUP($A68,Python数据平滑!$A$25:$AN$52,COLUMN(Python数据平滑!Q$25),0)/SUM(Python数据平滑!Q$26:Q$32)*情景假设!S$28 -> 162056.67 | T68: =VLOOKUP($A68,Python数据平滑!$A$25:$AN$52,COLUMN(Python数据平滑!R$25),0)/SUM(Python数据平滑!R$26:R$32)*情景假设!T$28 -> 165310.17 | U68: =VLOOKUP($A68,Python数据平滑!$A$25:$AN$52,COLUMN(Python数据平滑!S$25),0)/SUM(Python数据平滑!S$26:S$32)*情景假设!U$28 -> 168527.51 | V68: =VLOOKUP($A68,Python数据平滑!$A$25:$AN$52,COLUMN(Python数据平滑!T$25),0)/SUM(Python数据平滑!T$26:T$32)*情景假设!V$28 -> 171810.51 | W68: =VLOOKUP($A68,Python数据平滑!$A$25:$AN$52,COLUMN(Python数据平滑!U$25),0)/SUM(Python数据平滑!U$26:U$32)*情景假设!W$28 -> 175172.17 | X68: =VLOOKUP($A68,Python数据平滑!$A$25:$AN$52,COLUMN(Python数据平滑!V$25),0)/SUM(Python数据平滑!V$26:V$32)*情景假设!X$28 -> 178559.27 | Y68: =VLOOKUP($A68,Python数据平滑!$A$25:$AN$52,COLUMN(Python数据平滑!W$25),0)/SUM(Python数据平滑!W$26:W$32)*情景假设!Y$28 -> 181980.26 | ... AE68: =VLOOKUP($A68,Python数据平滑!$A$25:$AN$52,COLUMN(Python数据平滑!AC$25),0)/SUM(Python数据平滑!AC$26:AC$32)*情景假设!AE$28 -> 203801.81 | AF68: =$AF$28*G52 -> 207713 | AG68: =VLOOKUP($A68,Python数据平滑!$A$25:$AN$52,COLUMN(Python数据平滑!AE$25),0)/SUM(Python数据平滑!AE$26:AE$32)*情景假设!AG$28 -> 211692.73 | AH68: =VLOOKUP($A68,Python数据平滑!$A$25:$AN$52,COLUMN(Python数据平滑!AF$25),0)/SUM(Python数据平滑!AF$26:AF$32)*情景假设!AH$28 -> 215733.38 | AI68: =VLOOKUP($A68,Python数据平滑!$A$25:$AN$52,COLUMN(Python数据平滑!AG$25),0)/SUM(Python数据平滑!AG$26:AG$32)*情景假设!AI$28 -> 219835.05 | AJ68: =VLOOKUP($A68,Python数据平滑!$A$25:$AN$52,COLUMN(Python数据平滑!AH$25),0)/SUM(Python数据平滑!AH$26:AH$32)*情景假设!AJ$28 -> 223997.87 | AK68: =VLOOKUP($A68,Python数据平滑!$A$25:$AN$52,COLUMN(Python数据平滑!AI$25),0)/SUM(Python数据平滑!AI$26:AI$32)*情景假设!AK$28 -> 228221.89 | AL68: =VLOOKUP($A68,Python数据平滑!$A$25:$AN$52,COLUMN(Python数据平滑!AJ$25),0)/SUM(Python数据平滑!AJ$26:AJ$32)*情景假设!AL$28 -> 232512.19 | AM68: =VLOOKUP($A68,Python数据平滑!$A$25:$AN$52,COLUMN(Python数据平滑!AK$25),0)/SUM(Python数据平滑!AK$26:AK$32)*情景假设!AM$28 -> 236874.91 | AN68: =VLOOKUP($A68,Python数据平滑!$A$25:$AN$52,COLUMN(Python数据平滑!AL$25),0)/SUM(Python数据平滑!AL$26:AL$32)*情景假设!AN$28 -> 241311.68 | AO68: =VLOOKUP($A68,Python数据平滑!$A$25:$AN$52,COLUMN(Python数据平滑!AM$25),0)/SUM(Python数据平滑!AM$26:AM$32)*情景假设!AO$28 -> 245824.03 | AP68: =AP$28*H52 -> 250413.4
A69: 高技术产业-高情景 | B69: =SUM('高情景（2001-2060, 2020RMB）'!U47:U48,'高情景（2001-2060, 2020RMB）'!U35) -> 42058.738 | C69: =SUM('高情景（2001-2060, 2020RMB）'!V47:V48,'高情景（2001-2060, 2020RMB）'!V35) -> 51422.622 | D69: =SUM('高情景（2001-2060, 2020RMB）'!W47:W48,'高情景（2001-2060, 2020RMB）'!W35) -> 54801.587 | E69: =VLOOKUP($A69,Python数据平滑!$A$25:$AN$52,COLUMN(Python数据平滑!C$25),0)/SUM(Python数据平滑!C$26:C$32)*情景假设!E$28 -> 57519.548 | F69: =VLOOKUP($A69,Python数据平滑!$A$25:$AN$52,COLUMN(Python数据平滑!D$25),0)/SUM(Python数据平滑!D$26:D$32)*情景假设!F$28 -> 60296.292 | G69: =G$28*D53 -> 63102.521 | H69: =VLOOKUP($A69,Python数据平滑!$A$25:$AN$52,COLUMN(Python数据平滑!F$25),0)/SUM(Python数据平滑!F$26:F$32)*情景假设!H$28 -> 66046.837 | I69: =VLOOKUP($A69,Python数据平滑!$A$25:$AN$52,COLUMN(Python数据平滑!G$25),0)/SUM(Python数据平滑!G$26:G$32)*情景假设!I$28 -> 69097.445 | J69: =VLOOKUP($A69,Python数据平滑!$A$25:$AN$52,COLUMN(Python数据平滑!H$25),0)/SUM(Python数据平滑!H$26:H$32)*情景假设!J$28 -> 72234.037 | K69: =VLOOKUP($A69,Python数据平滑!$A$25:$AN$52,COLUMN(Python数据平滑!I$25),0)/SUM(Python数据平滑!I$26:I$32)*情景假设!K$28 -> 75427.939 | L69: =L$28*E53 -> 78641.43 | M69: =VLOOKUP($A69,Python数据平滑!$A$25:$AN$52,COLUMN(Python数据平滑!K$25),0)/SUM(Python数据平滑!K$26:K$32)*情景假设!M$28 -> 81890.035 | N69: =VLOOKUP($A69,Python数据平滑!$A$25:$AN$52,COLUMN(Python数据平滑!L$25),0)/SUM(Python数据平滑!L$26:L$32)*情景假设!N$28 -> 85176.423 | O69: =VLOOKUP($A69,Python数据平滑!$A$25:$AN$52,COLUMN(Python数据平滑!M$25),0)/SUM(Python数据平滑!M$26:M$32)*情景假设!O$28 -> 88431.102 | P69: =VLOOKUP($A69,Python数据平滑!$A$25:$AN$52,COLUMN(Python数据平滑!N$25),0)/SUM(Python数据平滑!N$26:N$32)*情景假设!P$28 -> 91586.861 | Q69: =Q$28*F53 -> 94583.527 | R69: =VLOOKUP($A69,Python数据平滑!$A$25:$AN$52,COLUMN(Python数据平滑!P$25),0)/SUM(Python数据平滑!P$26:P$32)*情景假设!R$28 -> 97390.95 | S69: =VLOOKUP($A69,Python数据平滑!$A$25:$AN$52,COLUMN(Python数据平滑!Q$25),0)/SUM(Python数据平滑!Q$26:Q$32)*情景假设!S$28 -> 100047.8 | T69: =VLOOKUP($A69,Python数据平滑!$A$25:$AN$52,COLUMN(Python数据平滑!R$25),0)/SUM(Python数据平滑!R$26:R$32)*情景假设!T$28 -> 102607.41 | U69: =VLOOKUP($A69,Python数据平滑!$A$25:$AN$52,COLUMN(Python数据平滑!S$25),0)/SUM(Python数据平滑!S$26:S$32)*情景假设!U$28 -> 105130.22 | V69: =VLOOKUP($A69,Python数据平滑!$A$25:$AN$52,COLUMN(Python数据平滑!T$25),0)/SUM(Python数据平滑!T$26:T$32)*情景假设!V$28 -> 107683.37 | W69: =VLOOKUP($A69,Python数据平滑!$A$25:$AN$52,COLUMN(Python数据平滑!U$25),0)/SUM(Python数据平滑!U$26:U$32)*情景假设!W$28 -> 110279.81 | X69: =VLOOKUP($A69,Python数据平滑!$A$25:$AN$52,COLUMN(Python数据平滑!V$25),0)/SUM(Python数据平滑!V$26:V$32)*情景假设!X$28 -> 112891.31 | Y69: =VLOOKUP($A69,Python数据平滑!$A$25:$AN$52,COLUMN(Python数据平滑!W$25),0)/SUM(Python数据平滑!W$26:W$32)*情景假设!Y$28 -> 115528.8 | ... AE69: =VLOOKUP($A69,Python数据平滑!$A$25:$AN$52,COLUMN(Python数据平滑!AC$25),0)/SUM(Python数据平滑!AC$26:AC$32)*情景假设!AE$28 -> 132670.89 | AF69: =$AF$28*G53 -> 135867.06 | AG69: =VLOOKUP($A69,Python数据平滑!$A$25:$AN$52,COLUMN(Python数据平滑!AE$25),0)/SUM(Python数据平滑!AE$26:AE$32)*情景假设!AG$28 -> 139161.3 | AH69: =VLOOKUP($A69,Python数据平滑!$A$25:$AN$52,COLUMN(Python数据平滑!AF$25),0)/SUM(Python数据平滑!AF$26:AF$32)*情景假设!AH$28 -> 142532.66 | AI69: =VLOOKUP($A69,Python数据平滑!$A$25:$AN$52,COLUMN(Python数据平滑!AG$25),0)/SUM(Python数据平滑!AG$26:AG$32)*情景假设!AI$28 -> 145982.33 | AJ69: =VLOOKUP($A69,Python数据平滑!$A$25:$AN$52,COLUMN(Python数据平滑!AH$25),0)/SUM(Python数据平滑!AH$26:AH$32)*情景假设!AJ$28 -> 149511.49 | AK69: =VLOOKUP($A69,Python数据平滑!$A$25:$AN$52,COLUMN(Python数据平滑!AI$25),0)/SUM(Python数据平滑!AI$26:AI$32)*情景假设!AK$28 -> 153121.31 | AL69: =VLOOKUP($A69,Python数据平滑!$A$25:$AN$52,COLUMN(Python数据平滑!AJ$25),0)/SUM(Python数据平滑!AJ$26:AJ$32)*情景假设!AL$28 -> 156816.34 | AM69: =VLOOKUP($A69,Python数据平滑!$A$25:$AN$52,COLUMN(Python数据平滑!AK$25),0)/SUM(Python数据平滑!AK$26:AK$32)*情景假设!AM$28 -> 160601.94 | AN69: =VLOOKUP($A69,Python数据平滑!$A$25:$AN$52,COLUMN(Python数据平滑!AL$25),0)/SUM(Python数据平滑!AL$26:AL$32)*情景假设!AN$28 -> 164480.46 | AO69: =VLOOKUP($A69,Python数据平滑!$A$25:$AN$52,COLUMN(Python数据平滑!AM$25),0)/SUM(Python数据平滑!AM$26:AM$32)*情景假设!AO$28 -> 168454.26 | AP69: =AP$28*H53 -> 172525.62
A70: 其他产业-高情景 | B70: =SUM('高情景（2001-2060, 2020RMB）'!U16:U24,'高情景（2001-2060, 2020RMB）'!U27:U29,'高情景（2001-2060, 2020RMB）'!U31:U32,'高情景（2001-2060, 2020RMB）'!U49:U51) -> 50441.557 | C70: =SUM('高情景（2001-2060, 2020RMB）'!V16:V24,'高情景（2001-2060, 2020RMB）'!V27:V29,'高情景（2001-2060, 2020RMB）'!V31:V32,'高情景（2001-2060, 2020RMB）'!V49:V51) -> 56632.87 | D70: =SUM('高情景（2001-2060, 2020RMB）'!W16:W24,'高情景（2001-2060, 2020RMB）'!W27:W29,'高情景（2001-2060, 2020RMB）'!W31:W32,'高情景（2001-2060, 2020RMB）'!W49:W51) -> 59677.346 | E70: =VLOOKUP($A70,Python数据平滑!$A$25:$AN$52,COLUMN(Python数据平滑!C$25),0)/SUM(Python数据平滑!C$26:C$32)*情景假设!E$28 -> 60924.024 | F70: =VLOOKUP($A70,Python数据平滑!$A$25:$AN$52,COLUMN(Python数据平滑!D$25),0)/SUM(Python数据平滑!D$26:D$32)*情景假设!F$28 -> 62142.324 | G70: =G$28*D54 -> 63310.781 | H70: =VLOOKUP($A70,Python数据平滑!$A$25:$AN$52,COLUMN(Python数据平滑!F$25),0)/SUM(Python数据平滑!F$26:F$32)*情景假设!H$28 -> 64523.247 | I70: =VLOOKUP($A70,Python数据平滑!$A$25:$AN$52,COLUMN(Python数据平滑!G$25),0)/SUM(Python数据平滑!G$26:G$32)*情景假设!I$28 -> 65736.95 | J70: =VLOOKUP($A70,Python数据平滑!$A$25:$AN$52,COLUMN(Python数据平滑!H$25),0)/SUM(Python数据平滑!H$26:H$32)*情景假设!J$28 -> 66951.35 | K70: =VLOOKUP($A70,Python数据平滑!$A$25:$AN$52,COLUMN(Python数据平滑!I$25),0)/SUM(Python数据平滑!I$26:I$32)*情景假设!K$28 -> 68162.032 | L70: =L$28*E54 -> 69360.764 | M70: =VLOOKUP($A70,Python数据平滑!$A$25:$AN$52,COLUMN(Python数据平滑!K$25),0)/SUM(Python数据平滑!K$26:K$32)*情景假设!M$28 -> 70530.797 | N70: =VLOOKUP($A70,Python数据平滑!$A$25:$AN$52,COLUMN(Python数据平滑!L$25),0)/SUM(Python数据平滑!L$26:L$32)*情景假设!N$28 -> 71658.348 | O70: =VLOOKUP($A70,Python数据平滑!$A$25:$AN$52,COLUMN(Python数据平滑!M$25),0)/SUM(Python数据平滑!M$26:M$32)*情景假设!O$28 -> 72738.486 | P70: =VLOOKUP($A70,Python数据平滑!$A$25:$AN$52,COLUMN(Python数据平滑!N$25),0)/SUM(Python数据平滑!N$26:N$32)*情景假设!P$28 -> 73775.839 | Q70: =Q$28*F54 -> 74786.975 | R70: =VLOOKUP($A70,Python数据平滑!$A$25:$AN$52,COLUMN(Python数据平滑!P$25),0)/SUM(Python数据平滑!P$26:P$32)*情景假设!R$28 -> 75734.16 | S70: =VLOOKUP($A70,Python数据平滑!$A$25:$AN$52,COLUMN(Python数据平滑!Q$25),0)/SUM(Python数据平滑!Q$26:Q$32)*情景假设!S$28 -> 76589.908 | T70: =VLOOKUP($A70,Python数据平滑!$A$25:$AN$52,COLUMN(Python数据平滑!R$25),0)/SUM(Python数据平滑!R$26:R$32)*情景假设!T$28 -> 77395.06 | U70: =VLOOKUP($A70,Python数据平滑!$A$25:$AN$52,COLUMN(Python数据平滑!S$25),0)/SUM(Python数据平滑!S$26:S$32)*情景假设!U$28 -> 78192.293 | V70: =VLOOKUP($A70,Python数据平滑!$A$25:$AN$52,COLUMN(Python数据平滑!T$25),0)/SUM(Python数据平滑!T$26:T$32)*情景假设!V$28 -> 79025.955 | W70: =VLOOKUP($A70,Python数据平滑!$A$25:$AN$52,COLUMN(Python数据平滑!U$25),0)/SUM(Python数据平滑!U$26:U$32)*情景假设!W$28 -> 79898.101 | X70: =VLOOKUP($A70,Python数据平滑!$A$25:$AN$52,COLUMN(Python数据平滑!V$25),0)/SUM(Python数据平滑!V$26:V$32)*情景假设!X$28 -> 80780.497 | Y70: =VLOOKUP($A70,Python数据平滑!$A$25:$AN$52,COLUMN(Python数据平滑!W$25),0)/SUM(Python数据平滑!W$26:W$32)*情景假设!Y$28 -> 81673.208 | ... AE70: =VLOOKUP($A70,Python数据平滑!$A$25:$AN$52,COLUMN(Python数据平滑!AC$25),0)/SUM(Python数据平滑!AC$26:AC$32)*情景假设!AE$28 -> 87259.025 | AF70: =$AF$28*G54 -> 88206.888 | AG70: =VLOOKUP($A70,Python数据平滑!$A$25:$AN$52,COLUMN(Python数据平滑!AE$25),0)/SUM(Python数据平滑!AE$26:AE$32)*情景假设!AG$28 -> 89153.636 | AH70: =VLOOKUP($A70,Python数据平滑!$A$25:$AN$52,COLUMN(Python数据平滑!AF$25),0)/SUM(Python数据平滑!AF$26:AF$32)*情景假设!AH$28 -> 90106.847 | AI70: =VLOOKUP($A70,Python数据平滑!$A$25:$AN$52,COLUMN(Python数据平滑!AG$25),0)/SUM(Python数据平滑!AG$26:AG$32)*情景假设!AI$28 -> 91066.226 | AJ70: =VLOOKUP($A70,Python数据平滑!$A$25:$AN$52,COLUMN(Python数据平滑!AH$25),0)/SUM(Python数据平滑!AH$26:AH$32)*情景假设!AJ$28 -> 92031.475 | AK70: =VLOOKUP($A70,Python数据平滑!$A$25:$AN$52,COLUMN(Python数据平滑!AI$25),0)/SUM(Python数据平滑!AI$26:AI$32)*情景假设!AK$28 -> 93002.276 | AL70: =VLOOKUP($A70,Python数据平滑!$A$25:$AN$52,COLUMN(Python数据平滑!AJ$25),0)/SUM(Python数据平滑!AJ$26:AJ$32)*情景假设!AL$28 -> 93980.343 | AM70: =VLOOKUP($A70,Python数据平滑!$A$25:$AN$52,COLUMN(Python数据平滑!AK$25),0)/SUM(Python数据平滑!AK$26:AK$32)*情景假设!AM$28 -> 94967.757 | AN70: =VLOOKUP($A70,Python数据平滑!$A$25:$AN$52,COLUMN(Python数据平滑!AL$25),0)/SUM(Python数据平滑!AL$26:AL$32)*情景假设!AN$28 -> 95964.718 | AO70: =VLOOKUP($A70,Python数据平滑!$A$25:$AN$52,COLUMN(Python数据平滑!AM$25),0)/SUM(Python数据平滑!AM$26:AM$32)*情景假设!AO$28 -> 96971.383 | AP70: =AP$28*H54 -> 97987.851
A72: 交通运输业-高情景 | B72: ='高情景（2001-2060, 2020RMB）'!U57 -> 40582.9 | C72: ='高情景（2001-2060, 2020RMB）'!V57 -> 44991.984 | D72: ='高情景（2001-2060, 2020RMB）'!W57 -> 46450.003 | E72: =VLOOKUP($A72,Python数据平滑!$A$25:$AN$52,COLUMN(Python数据平滑!C$25),0)/SUM(Python数据平滑!C$33:C$35)*情景假设!E$30 -> 49494.866 | F72: =VLOOKUP($A72,Python数据平滑!$A$25:$AN$52,COLUMN(Python数据平滑!D$25),0)/SUM(Python数据平滑!D$33:D$35)*情景假设!F$30 -> 52653.188 | G72: =G$30*D57 -> 55900.722 | H72: =VLOOKUP($A72,Python数据平滑!$A$25:$AN$52,COLUMN(Python数据平滑!F$25),0)/SUM(Python数据平滑!F$33:F$35)*情景假设!H$30 -> 59319.394 | I72: =VLOOKUP($A72,Python数据平滑!$A$25:$AN$52,COLUMN(Python数据平滑!G$25),0)/SUM(Python数据平滑!G$33:G$35)*情景假设!I$30 -> 62942.044 | J72: =VLOOKUP($A72,Python数据平滑!$A$25:$AN$52,COLUMN(Python数据平滑!H$25),0)/SUM(Python数据平滑!H$33:H$35)*情景假设!J$30 -> 66646.257 | K72: =VLOOKUP($A72,Python数据平滑!$A$25:$AN$52,COLUMN(Python数据平滑!I$25),0)/SUM(Python数据平滑!I$33:I$35)*情景假设!K$30 -> 70281.422 | L72: =L$30*E57 -> 73669.284 | M72: =VLOOKUP($A72,Python数据平滑!$A$25:$AN$52,COLUMN(Python数据平滑!K$25),0)/SUM(Python数据平滑!K$33:K$35)*情景假设!M$30 -> 76785.162 | N72: =VLOOKUP($A72,Python数据平滑!$A$25:$AN$52,COLUMN(Python数据平滑!L$25),0)/SUM(Python数据平滑!L$33:L$35)*情景假设!N$30 -> 79751.111 | O72: =VLOOKUP($A72,Python数据平滑!$A$25:$AN$52,COLUMN(Python数据平滑!M$25),0)/SUM(Python数据平滑!M$33:M$35)*情景假设!O$30 -> 82596.354 | P72: =VLOOKUP($A72,Python数据平滑!$A$25:$AN$52,COLUMN(Python数据平滑!N$25),0)/SUM(Python数据平滑!N$33:N$35)*情景假设!P$30 -> 85357.767 | Q72: =Q$30*F57 -> 88079.348 | R72: =VLOOKUP($A72,Python数据平滑!$A$25:$AN$52,COLUMN(Python数据平滑!P$25),0)/SUM(Python数据平滑!P$33:P$35)*情景假设!R$30 -> 90737.533 | S72: =VLOOKUP($A72,Python数据平滑!$A$25:$AN$52,COLUMN(Python数据平滑!Q$25),0)/SUM(Python数据平滑!Q$33:Q$35)*情景假设!S$30 -> 93302.788 | T72: =VLOOKUP($A72,Python数据平滑!$A$25:$AN$52,COLUMN(Python数据平滑!R$25),0)/SUM(Python数据平滑!R$33:R$35)*情景假设!T$30 -> 95820.018 | U72: =VLOOKUP($A72,Python数据平滑!$A$25:$AN$52,COLUMN(Python数据平滑!S$25),0)/SUM(Python数据平滑!S$33:S$35)*情景假设!U$30 -> 98340.222 | V72: =VLOOKUP($A72,Python数据平滑!$A$25:$AN$52,COLUMN(Python数据平滑!T$25),0)/SUM(Python数据平滑!T$33:T$35)*情景假设!V$30 -> 100920.39 | W72: =VLOOKUP($A72,Python数据平滑!$A$25:$AN$52,COLUMN(Python数据平滑!U$25),0)/SUM(Python数据平滑!U$33:U$35)*情景假设!W$30 -> 103566.62 | X72: =VLOOKUP($A72,Python数据平滑!$A$25:$AN$52,COLUMN(Python数据平滑!V$25),0)/SUM(Python数据平滑!V$33:V$35)*情景假设!X$30 -> 106245.82 | Y72: =VLOOKUP($A72,Python数据平滑!$A$25:$AN$52,COLUMN(Python数据平滑!W$25),0)/SUM(Python数据平滑!W$33:W$35)*情景假设!Y$30 -> 108961.06 | ... AE72: =VLOOKUP($A72,Python数据平滑!$A$25:$AN$52,COLUMN(Python数据平滑!AC$25),0)/SUM(Python数据平滑!AC$33:AC$35)*情景假设!AE$30 -> 126273.64 | AF72: =$AF$30*G57 -> 129353.61 | AG72: =VLOOKUP($A72,Python数据平滑!$A$25:$AN$52,COLUMN(Python数据平滑!AE$25),0)/SUM(Python数据平滑!AE$33:AE$35)*情景假设!AG$30 -> 132481.4 | AH72: =VLOOKUP($A72,Python数据平滑!$A$25:$AN$52,COLUMN(Python数据平滑!AF$25),0)/SUM(Python数据平滑!AF$33:AF$35)*情景假设!AH$30 -> 135651.98 | AI72: =VLOOKUP($A72,Python数据平滑!$A$25:$AN$52,COLUMN(Python数据平滑!AG$25),0)/SUM(Python数据平滑!AG$33:AG$35)*情景假设!AI$30 -> 138864.06 | AJ72: =VLOOKUP($A72,Python数据平滑!$A$25:$AN$52,COLUMN(Python数据平滑!AH$25),0)/SUM(Python数据平滑!AH$33:AH$35)*情景假设!AJ$30 -> 142116.26 | AK72: =VLOOKUP($A72,Python数据平滑!$A$25:$AN$52,COLUMN(Python数据平滑!AI$25),0)/SUM(Python数据平滑!AI$33:AI$35)*情景假设!AK$30 -> 145407 | AL72: =VLOOKUP($A72,Python数据平滑!$A$25:$AN$52,COLUMN(Python数据平滑!AJ$25),0)/SUM(Python数据平滑!AJ$33:AJ$35)*情景假设!AL$30 -> 148737.83 | AM72: =VLOOKUP($A72,Python数据平滑!$A$25:$AN$52,COLUMN(Python数据平滑!AK$25),0)/SUM(Python数据平滑!AK$33:AK$35)*情景假设!AM$30 -> 152110.93 | AN72: =VLOOKUP($A72,Python数据平滑!$A$25:$AN$52,COLUMN(Python数据平滑!AL$25),0)/SUM(Python数据平滑!AL$33:AL$35)*情景假设!AN$30 -> 155525.51 | AO72: =VLOOKUP($A72,Python数据平滑!$A$25:$AN$52,COLUMN(Python数据平滑!AM$25),0)/SUM(Python数据平滑!AM$33:AM$35)*情景假设!AO$30 -> 158980.71 | AP72: =AP$30*H57 -> 162475.58
A73: 传统服务业-高情景 | B73: =SUM('高情景（2001-2060, 2020RMB）'!U58:U59) -> 111371.5 | C73: =SUM('高情景（2001-2060, 2020RMB）'!V58:V59) -> 122702.13 | D73: =SUM('高情景（2001-2060, 2020RMB）'!W58:W59) -> 123782.33 | E73: =VLOOKUP($A73,Python数据平滑!$A$25:$AN$52,COLUMN(Python数据平滑!C$25),0)/SUM(Python数据平滑!C$33:C$35)*情景假设!E$30 -> 131112.45 | F73: =VLOOKUP($A73,Python数据平滑!$A$25:$AN$52,COLUMN(Python数据平滑!D$25),0)/SUM(Python数据平滑!D$33:D$35)*情景假设!F$30 -> 138818.81 | G73: =G$30*D58 -> 146918.56 | H73: =VLOOKUP($A73,Python数据平滑!$A$25:$AN$52,COLUMN(Python数据平滑!F$25),0)/SUM(Python数据平滑!F$33:F$35)*情景假设!H$30 -> 155666.31 | I73: =VLOOKUP($A73,Python数据平滑!$A$25:$AN$52,COLUMN(Python数据平滑!G$25),0)/SUM(Python数据平滑!G$33:G$35)*情景假设!I$30 -> 165116.9 | J73: =VLOOKUP($A73,Python数据平滑!$A$25:$AN$52,COLUMN(Python数据平滑!H$25),0)/SUM(Python数据平滑!H$33:H$35)*情景假设!J$30 -> 174930.53 | K73: =VLOOKUP($A73,Python数据平滑!$A$25:$AN$52,COLUMN(Python数据平滑!I$25),0)/SUM(Python数据平滑!I$33:I$35)*情景假设!K$30 -> 184683.54 | L73: =L$30*E58 -> 193866.54 | M73: =VLOOKUP($A73,Python数据平滑!$A$25:$AN$52,COLUMN(Python数据平滑!K$25),0)/SUM(Python数据平滑!K$33:K$35)*情景假设!M$30 -> 202361.84 | N73: =VLOOKUP($A73,Python数据平滑!$A$25:$AN$52,COLUMN(Python数据平滑!L$25),0)/SUM(Python数据平滑!L$33:L$35)*情景假设!N$30 -> 210497.24 | O73: =VLOOKUP($A73,Python数据平滑!$A$25:$AN$52,COLUMN(Python数据平滑!M$25),0)/SUM(Python数据平滑!M$33:M$35)*情景假设!O$30 -> 218392.48 | P73: =VLOOKUP($A73,Python数据平滑!$A$25:$AN$52,COLUMN(Python数据平滑!N$25),0)/SUM(Python数据平滑!N$33:N$35)*情景假设!P$30 -> 226194.02 | Q73: =Q$30*F58 -> 234073.88 | R73: =VLOOKUP($A73,Python数据平滑!$A$25:$AN$52,COLUMN(Python数据平滑!P$25),0)/SUM(Python数据平滑!P$33:P$35)*情景假设!R$30 -> 241944.17 | S73: =VLOOKUP($A73,Python数据平滑!$A$25:$AN$52,COLUMN(Python数据平滑!Q$25),0)/SUM(Python数据平滑!Q$33:Q$35)*情景假设!S$30 -> 249659.88 | T73: =VLOOKUP($A73,Python数据平滑!$A$25:$AN$52,COLUMN(Python数据平滑!R$25),0)/SUM(Python数据平滑!R$33:R$35)*情景假设!T$30 -> 257339.75 | U73: =VLOOKUP($A73,Python数据平滑!$A$25:$AN$52,COLUMN(Python数据平滑!S$25),0)/SUM(Python数据平滑!S$33:S$35)*情景假设!U$30 -> 265120.15 | V73: =VLOOKUP($A73,Python数据平滑!$A$25:$AN$52,COLUMN(Python数据平滑!T$25),0)/SUM(Python数据平滑!T$33:T$35)*情景假设!V$30 -> 273155.41 | W73: =VLOOKUP($A73,Python数据平滑!$A$25:$AN$52,COLUMN(Python数据平滑!U$25),0)/SUM(Python数据平滑!U$33:U$35)*情景假设!W$30 -> 281463.66 | X73: =VLOOKUP($A73,Python数据平滑!$A$25:$AN$52,COLUMN(Python数据平滑!V$25),0)/SUM(Python数据平滑!V$33:V$35)*情景假设!X$30 -> 289956.09 | Y73: =VLOOKUP($A73,Python数据平滑!$A$25:$AN$52,COLUMN(Python数据平滑!W$25),0)/SUM(Python数据平滑!W$33:W$35)*情景假设!Y$30 -> 298641.2 | ... AE73: =VLOOKUP($A73,Python数据平滑!$A$25:$AN$52,COLUMN(Python数据平滑!AC$25),0)/SUM(Python数据平滑!AC$33:AC$35)*情景假设!AE$30 -> 355502.21 | AF73: =$AF$30*G58 -> 365828.17 | AG73: =VLOOKUP($A73,Python数据平滑!$A$25:$AN$52,COLUMN(Python数据平滑!AE$25),0)/SUM(Python数据平滑!AE$33:AE$35)*情景假设!AG$30 -> 376383.46 | AH73: =VLOOKUP($A73,Python数据平滑!$A$25:$AN$52,COLUMN(Python数据平滑!AF$25),0)/SUM(Python数据平滑!AF$33:AF$35)*情景假设!AH$30 -> 387169.47 | AI73: =VLOOKUP($A73,Python数据平滑!$A$25:$AN$52,COLUMN(Python数据平滑!AG$25),0)/SUM(Python数据平滑!AG$33:AG$35)*情景假设!AI$30 -> 398186.51 | AJ73: =VLOOKUP($A73,Python数据平滑!$A$25:$AN$52,COLUMN(Python数据平滑!AH$25),0)/SUM(Python数据平滑!AH$33:AH$35)*情景假设!AJ$30 -> 409434.47 | AK73: =VLOOKUP($A73,Python数据平滑!$A$25:$AN$52,COLUMN(Python数据平滑!AI$25),0)/SUM(Python数据平滑!AI$33:AI$35)*情景假设!AK$30 -> 420912.79 | AL73: =VLOOKUP($A73,Python数据平滑!$A$25:$AN$52,COLUMN(Python数据平滑!AJ$25),0)/SUM(Python数据平滑!AJ$33:AJ$35)*情景假设!AL$30 -> 432629.94 | AM73: =VLOOKUP($A73,Python数据平滑!$A$25:$AN$52,COLUMN(Python数据平滑!AK$25),0)/SUM(Python数据平滑!AK$33:AK$35)*情景假设!AM$30 -> 444596.4 | AN73: =VLOOKUP($A73,Python数据平滑!$A$25:$AN$52,COLUMN(Python数据平滑!AL$25),0)/SUM(Python数据平滑!AL$33:AL$35)*情景假设!AN$30 -> 456814.21 | AO73: =VLOOKUP($A73,Python数据平滑!$A$25:$AN$52,COLUMN(Python数据平滑!AM$25),0)/SUM(Python数据平滑!AM$33:AM$35)*情景假设!AO$30 -> 469285.18 | AP73: =AP$30*H58 -> 482010.89
A74: 现代服务业-高情景 | B74: =SUM('高情景（2001-2060, 2020RMB）'!U60:U70) -> 394868.3 | C74: =SUM('高情景（2001-2060, 2020RMB）'!V60:V70) -> 415244.29 | D74: =SUM('高情景（2001-2060, 2020RMB）'!W60:W70) -> 421311.1 | E74: =VLOOKUP($A74,Python数据平滑!$A$25:$AN$52,COLUMN(Python数据平滑!C$25),0)/SUM(Python数据平滑!C$33:C$35)*情景假设!E$30 -> 450597.17 | F74: =VLOOKUP($A74,Python数据平滑!$A$25:$AN$52,COLUMN(Python数据平滑!D$25),0)/SUM(Python数据平滑!D$33:D$35)*情景假设!F$30 -> 481454.43 | G74: =G$30*D59 -> 513856.63 | H74: =VLOOKUP($A74,Python数据平滑!$A$25:$AN$52,COLUMN(Python数据平滑!F$25),0)/SUM(Python数据平滑!F$33:F$35)*情景假设!H$30 -> 548494.86 | I74: =VLOOKUP($A74,Python数据平滑!$A$25:$AN$52,COLUMN(Python数据平滑!G$25),0)/SUM(Python数据平滑!G$33:G$35)*情景假设!I$30 -> 585613.51 | J74: =VLOOKUP($A74,Python数据平滑!$A$25:$AN$52,COLUMN(Python数据平滑!H$25),0)/SUM(Python数据平滑!H$33:H$35)*情景假设!J$30 -> 624330.84 | K74: =VLOOKUP($A74,Python数据平滑!$A$25:$AN$52,COLUMN(Python数据平滑!I$25),0)/SUM(Python数据平滑!I$33:I$35)*情景假设!K$30 -> 663520.02 | L74: =L$30*E59 -> 701796.86 | M74: =VLOOKUP($A74,Python数据平滑!$A$25:$AN$52,COLUMN(Python数据平滑!K$25),0)/SUM(Python数据平滑!K$33:K$35)*情景假设!M$30 -> 738801.52 | N74: =VLOOKUP($A74,Python数据平滑!$A$25:$AN$52,COLUMN(Python数据平滑!L$25),0)/SUM(Python数据平滑!L$33:L$35)*情景假设!N$30 -> 775325.32 | O74: =VLOOKUP($A74,Python数据平滑!$A$25:$AN$52,COLUMN(Python数据平滑!M$25),0)/SUM(Python数据平滑!M$33:M$35)*情景假设!O$30 -> 811573.24 | P74: =VLOOKUP($A74,Python数据平滑!$A$25:$AN$52,COLUMN(Python数据平滑!N$25),0)/SUM(Python数据平滑!N$33:N$35)*情景假设!P$30 -> 847820.62 | Q74: =Q$30*F59 -> 884413.18 | R74: =VLOOKUP($A74,Python数据平滑!$A$25:$AN$52,COLUMN(Python数据平滑!P$25),0)/SUM(Python数据平滑!P$33:P$35)*情景假设!R$30 -> 921154.69 | S74: =VLOOKUP($A74,Python数据平滑!$A$25:$AN$52,COLUMN(Python数据平滑!Q$25),0)/SUM(Python数据平滑!Q$33:Q$35)*情景假设!S$30 -> 957822.36 | T74: =VLOOKUP($A74,Python数据平滑!$A$25:$AN$52,COLUMN(Python数据平滑!R$25),0)/SUM(Python数据平滑!R$33:R$35)*情景假设!T$30 -> 994832.18 | U74: =VLOOKUP($A74,Python数据平滑!$A$25:$AN$52,COLUMN(Python数据平滑!S$25),0)/SUM(Python数据平滑!S$33:S$35)*情景假设!U$30 -> 1032677.5 | V74: =VLOOKUP($A74,Python数据平滑!$A$25:$AN$52,COLUMN(Python数据平滑!T$25),0)/SUM(Python数据平滑!T$33:T$35)*情景假设!V$30 -> 1071932.2 | W74: =VLOOKUP($A74,Python数据平滑!$A$25:$AN$52,COLUMN(Python数据平滑!U$25),0)/SUM(Python数据平滑!U$33:U$35)*情景假设!W$30 -> 1112643.9 | X74: =VLOOKUP($A74,Python数据平滑!$A$25:$AN$52,COLUMN(Python数据平滑!V$25),0)/SUM(Python数据平滑!V$33:V$35)*情景假设!X$30 -> 1154430 | Y74: =VLOOKUP($A74,Python数据平滑!$A$25:$AN$52,COLUMN(Python数据平滑!W$25),0)/SUM(Python数据平滑!W$33:W$35)*情景假设!Y$30 -> 1197280.9 | ... AE74: =VLOOKUP($A74,Python数据平滑!$A$25:$AN$52,COLUMN(Python数据平滑!AC$25),0)/SUM(Python数据平滑!AC$33:AC$35)*情景假设!AE$30 -> 1476295.5 | AF74: =$AF$30*G59 -> 1525968.3 | AG74: =VLOOKUP($A74,Python数据平滑!$A$25:$AN$52,COLUMN(Python数据平滑!AE$25),0)/SUM(Python数据平滑!AE$33:AE$35)*情景假设!AG$30 -> 1576374.4 | AH74: =VLOOKUP($A74,Python数据平滑!$A$25:$AN$52,COLUMN(Python数据平滑!AF$25),0)/SUM(Python数据平滑!AF$33:AF$35)*情景假设!AH$30 -> 1627601 | AI74: =VLOOKUP($A74,Python数据平滑!$A$25:$AN$52,COLUMN(Python数据平滑!AG$25),0)/SUM(Python数据平滑!AG$33:AG$35)*情景假设!AI$30 -> 1679614.2 | AJ74: =VLOOKUP($A74,Python数据平滑!$A$25:$AN$52,COLUMN(Python数据平滑!AH$25),0)/SUM(Python数据平滑!AH$33:AH$35)*情景假设!AJ$30 -> 1732376.5 | AK74: =VLOOKUP($A74,Python数据平滑!$A$25:$AN$52,COLUMN(Python数据平滑!AI$25),0)/SUM(Python数据平滑!AI$33:AI$35)*情景假设!AK$30 -> 1785847 | AL74: =VLOOKUP($A74,Python数据平滑!$A$25:$AN$52,COLUMN(Python数据平滑!AJ$25),0)/SUM(Python数据平滑!AJ$33:AJ$35)*情景假设!AL$30 -> 1840021.4 | AM74: =VLOOKUP($A74,Python数据平滑!$A$25:$AN$52,COLUMN(Python数据平滑!AK$25),0)/SUM(Python数据平滑!AK$33:AK$35)*情景假设!AM$30 -> 1894903.2 | AN74: =VLOOKUP($A74,Python数据平滑!$A$25:$AN$52,COLUMN(Python数据平滑!AL$25),0)/SUM(Python数据平滑!AL$33:AL$35)*情景假设!AN$30 -> 1950458.3 | AO74: =VLOOKUP($A74,Python数据平滑!$A$25:$AN$52,COLUMN(Python数据平滑!AM$25),0)/SUM(Python数据平滑!AM$33:AM$35)*情景假设!AO$30 -> 2006650.1 | AP74: =AP$30*H59 -> 2063439.9
A76: 中情景 | B76: 2020 | C76: 2021 | D76: 2022 | E76: 2023 | F76: 2024 | G76: 2025 | H76: 2026 | I76: 2027 | J76: 2028 | K76: 2029 | L76: 2030 | M76: 2031 | N76: 2032 | O76: 2033 | P76: 2034 | Q76: 2035 | R76: 2036 | S76: 2037 | T76: 2038 | U76: 2039 | V76: 2040 | W76: 2041 | X76: 2042 | Y76: 2043 | Z76: 2044 | AA76: 2045 | AB76: 2046 | AC76: 2047 | AD76: 2048 | AE76: 2049 | AF76: 2050 | AG76: 2051 | AH76: 2052 | AI76: 2053 | AJ76: 2054 | AK76: 2055 | AL76: 2056 | AM76: 2057 | AN76: 2058 | AO76: 2059 | AP76: 2060
A77: 能源产业-中情景 | B77: =SUM('高情景（2001-2060, 2020RMB）'!U14:U15,'高情景（2001-2060, 2020RMB）'!U33,'高情景（2001-2060, 2020RMB）'!U53:U54) -> 34486.847 | C77: =SUM('高情景（2001-2060, 2020RMB）'!V14:V15,'高情景（2001-2060, 2020RMB）'!V33,'高情景（2001-2060, 2020RMB）'!V53:V54) -> 37878.28 | D77: =SUM('高情景（2001-2060, 2020RMB）'!W14:W15,'高情景（2001-2060, 2020RMB）'!W33,'高情景（2001-2060, 2020RMB）'!W53:W54) -> 40294.225 | E77: =VLOOKUP($A77,Python数据平滑!$A$25:$AN$52,COLUMN(Python数据平滑!C$25),0)/SUM(Python数据平滑!C$36:C$42)*情景假设!E$34 -> 41267.251 | F77: =VLOOKUP($A77,Python数据平滑!$A$25:$AN$52,COLUMN(Python数据平滑!D$25),0)/SUM(Python数据平滑!D$36:D$42)*情景假设!F$34 -> 42149.866 | G77: =G$34*K48 -> 42857.082 | H77: =VLOOKUP($A77,Python数据平滑!$A$25:$AN$52,COLUMN(Python数据平滑!F$25),0)/SUM(Python数据平滑!F$36:F$42)*情景假设!H$34 -> 43529.562 | I77: =VLOOKUP($A77,Python数据平滑!$A$25:$AN$52,COLUMN(Python数据平滑!G$25),0)/SUM(Python数据平滑!G$36:G$42)*情景假设!I$34 -> 44162.105 | J77: =VLOOKUP($A77,Python数据平滑!$A$25:$AN$52,COLUMN(Python数据平滑!H$25),0)/SUM(Python数据平滑!H$36:H$42)*情景假设!J$34 -> 44750.896 | K77: =VLOOKUP($A77,Python数据平滑!$A$25:$AN$52,COLUMN(Python数据平滑!I$25),0)/SUM(Python数据平滑!I$36:I$42)*情景假设!K$34 -> 45281.653 | L77: =L$34*L48 -> 45729.645 | M77: =VLOOKUP($A77,Python数据平滑!$A$25:$AN$52,COLUMN(Python数据平滑!K$25),0)/SUM(Python数据平滑!K$36:K$42)*情景假设!M$34 -> 46082.371 | N77: =VLOOKUP($A77,Python数据平滑!$A$25:$AN$52,COLUMN(Python数据平滑!L$25),0)/SUM(Python数据平滑!L$36:L$42)*情景假设!N$34 -> 46356.009 | O77: =VLOOKUP($A77,Python数据平滑!$A$25:$AN$52,COLUMN(Python数据平滑!M$25),0)/SUM(Python数据平滑!M$36:M$42)*情景假设!O$34 -> 46569.183 | P77: =VLOOKUP($A77,Python数据平滑!$A$25:$AN$52,COLUMN(Python数据平滑!N$25),0)/SUM(Python数据平滑!N$36:N$42)*情景假设!P$34 -> 46763.37 | Q77: =Q$34*M48 -> 47004.496 | R77: =VLOOKUP($A77,Python数据平滑!$A$25:$AN$52,COLUMN(Python数据平滑!P$25),0)/SUM(Python数据平滑!P$36:P$42)*情景假设!R$34 -> 47267.117 | S77: =VLOOKUP($A77,Python数据平滑!$A$25:$AN$52,COLUMN(Python数据平滑!Q$25),0)/SUM(Python数据平滑!Q$36:Q$42)*情景假设!S$34 -> 47487.504 | T77: =VLOOKUP($A77,Python数据平滑!$A$25:$AN$52,COLUMN(Python数据平滑!R$25),0)/SUM(Python数据平滑!R$36:R$42)*情景假设!T$34 -> 47684.391 | U77: =VLOOKUP($A77,Python数据平滑!$A$25:$AN$52,COLUMN(Python数据平滑!S$25),0)/SUM(Python数据平滑!S$36:S$42)*情景假设!U$34 -> 47876.604 | V77: =VLOOKUP($A77,Python数据平滑!$A$25:$AN$52,COLUMN(Python数据平滑!T$25),0)/SUM(Python数据平滑!T$36:T$42)*情景假设!V$34 -> 48083.034 | W77: =VLOOKUP($A77,Python数据平滑!$A$25:$AN$52,COLUMN(Python数据平滑!U$25),0)/SUM(Python数据平滑!U$36:U$42)*情景假设!W$34 -> 48303.937 | X77: =VLOOKUP($A77,Python数据平滑!$A$25:$AN$52,COLUMN(Python数据平滑!V$25),0)/SUM(Python数据平滑!V$36:V$42)*情景假设!X$34 -> 48526.169 | Y77: =VLOOKUP($A77,Python数据平滑!$A$25:$AN$52,COLUMN(Python数据平滑!W$25),0)/SUM(Python数据平滑!W$36:W$42)*情景假设!Y$34 -> 48748.478 | ... AE77: =VLOOKUP($A77,Python数据平滑!$A$25:$AN$52,COLUMN(Python数据平滑!AC$25),0)/SUM(Python数据平滑!AC$36:AC$42)*情景假设!AE$34 -> 50015.169 | AF77: =$AF$34*N48 -> 50202.618 | AG77: =VLOOKUP($A77,Python数据平滑!$A$25:$AN$52,COLUMN(Python数据平滑!AE$25),0)/SUM(Python数据平滑!AE$36:AE$42)*情景假设!AG$34 -> 50387.419 | AH77: =VLOOKUP($A77,Python数据平滑!$A$25:$AN$52,COLUMN(Python数据平滑!AF$25),0)/SUM(Python数据平滑!AF$36:AF$42)*情景假设!AH$34 -> 50575.737 | AI77: =VLOOKUP($A77,Python数据平滑!$A$25:$AN$52,COLUMN(Python数据平滑!AG$25),0)/SUM(Python数据平滑!AG$36:AG$42)*情景假设!AI$34 -> 50764.058 | AJ77: =VLOOKUP($A77,Python数据平滑!$A$25:$AN$52,COLUMN(Python数据平滑!AH$25),0)/SUM(Python数据平滑!AH$36:AH$42)*情景假设!AJ$34 -> 50948.797 | AK77: =VLOOKUP($A77,Python数据平滑!$A$25:$AN$52,COLUMN(Python数据平滑!AI$25),0)/SUM(Python数据平滑!AI$36:AI$42)*情景假设!AK$34 -> 51126.296 | AL77: =VLOOKUP($A77,Python数据平滑!$A$25:$AN$52,COLUMN(Python数据平滑!AJ$25),0)/SUM(Python数据平滑!AJ$36:AJ$42)*情景假设!AL$34 -> 51297.5 | AM77: =VLOOKUP($A77,Python数据平滑!$A$25:$AN$52,COLUMN(Python数据平滑!AK$25),0)/SUM(Python数据平滑!AK$36:AK$42)*情景假设!AM$34 -> 51465.515 | AN77: =VLOOKUP($A77,Python数据平滑!$A$25:$AN$52,COLUMN(Python数据平滑!AL$25),0)/SUM(Python数据平滑!AL$36:AL$42)*情景假设!AN$34 -> 51629.855 | AO77: =VLOOKUP($A77,Python数据平滑!$A$25:$AN$52,COLUMN(Python数据平滑!AM$25),0)/SUM(Python数据平滑!AM$36:AM$42)*情景假设!AO$34 -> 51790.01 | AP77: =AP$34*O48 -> 51945.445
A78: 电力与热力产业-中情景 | B78: ='高情景（2001-2060, 2020RMB）'!U52 -> 14171.805 | C78: ='高情景（2001-2060, 2020RMB）'!V52 -> 16363.885 | D78: ='高情景（2001-2060, 2020RMB）'!W52 -> 17470.728 | E78: =VLOOKUP($A78,Python数据平滑!$A$25:$AN$52,COLUMN(Python数据平滑!C$25),0)/SUM(Python数据平滑!C$36:C$42)*情景假设!E$34 -> 18915.564 | F78: =VLOOKUP($A78,Python数据平滑!$A$25:$AN$52,COLUMN(Python数据平滑!D$25),0)/SUM(Python数据平滑!D$36:D$42)*情景假设!F$34 -> 20414.366 | G78: =G$34*K49 -> 21926.879 | H78: =VLOOKUP($A78,Python数据平滑!$A$25:$AN$52,COLUMN(Python数据平滑!F$25),0)/SUM(Python数据平滑!F$36:F$42)*情景假设!H$34 -> 23545.834 | I78: =VLOOKUP($A78,Python数据平滑!$A$25:$AN$52,COLUMN(Python数据平滑!G$25),0)/SUM(Python数据平滑!G$36:G$42)*情景假设!I$34 -> 25269.313 | J78: =VLOOKUP($A78,Python数据平滑!$A$25:$AN$52,COLUMN(Python数据平滑!H$25),0)/SUM(Python数据平滑!H$36:H$42)*情景假设!J$34 -> 27052.864 | K78: =VLOOKUP($A78,Python数据平滑!$A$25:$AN$52,COLUMN(Python数据平滑!I$25),0)/SUM(Python数据平滑!I$36:I$42)*情景假设!K$34 -> 28831.763 | L78: =L$34*L49 -> 30518.931 | M78: =VLOOKUP($A78,Python数据平滑!$A$25:$AN$52,COLUMN(Python数据平滑!K$25),0)/SUM(Python数据平滑!K$36:K$42)*情景假设!M$34 -> 32075.977 | N78: =VLOOKUP($A78,Python数据平滑!$A$25:$AN$52,COLUMN(Python数据平滑!L$25),0)/SUM(Python数据平滑!L$36:L$42)*情景假设!N$34 -> 33541.618 | O78: =VLOOKUP($A78,Python数据平滑!$A$25:$AN$52,COLUMN(Python数据平滑!M$25),0)/SUM(Python数据平滑!M$36:M$42)*情景假设!O$34 -> 34938.004 | P78: =VLOOKUP($A78,Python数据平滑!$A$25:$AN$52,COLUMN(Python数据平滑!N$25),0)/SUM(Python数据平滑!N$36:N$42)*情景假设!P$34 -> 36311.541 | Q78: =Q$34*M49 -> 37736.786 | R78: =VLOOKUP($A78,Python数据平滑!$A$25:$AN$52,COLUMN(Python数据平滑!P$25),0)/SUM(Python数据平滑!P$36:P$42)*情景假设!R$34 -> 39208.558 | S78: =VLOOKUP($A78,Python数据平滑!$A$25:$AN$52,COLUMN(Python数据平滑!Q$25),0)/SUM(Python数据平滑!Q$36:Q$42)*情景假设!S$34 -> 40669.098 | T78: =VLOOKUP($A78,Python数据平滑!$A$25:$AN$52,COLUMN(Python数据平滑!R$25),0)/SUM(Python数据平滑!R$36:R$42)*情景假设!T$34 -> 42132.187 | U78: =VLOOKUP($A78,Python数据平滑!$A$25:$AN$52,COLUMN(Python数据平滑!S$25),0)/SUM(Python数据平滑!S$36:S$42)*情景假设!U$34 -> 43613.881 | V78: =VLOOKUP($A78,Python数据平滑!$A$25:$AN$52,COLUMN(Python数据平滑!T$25),0)/SUM(Python数据平滑!T$36:T$42)*情景假设!V$34 -> 45132.555 | W78: =VLOOKUP($A78,Python数据平滑!$A$25:$AN$52,COLUMN(Python数据平滑!U$25),0)/SUM(Python数据平滑!U$36:U$42)*情景假设!W$34 -> 46690.895 | X78: =VLOOKUP($A78,Python数据平滑!$A$25:$AN$52,COLUMN(Python数据平滑!V$25),0)/SUM(Python数据平滑!V$36:V$42)*情景假设!X$34 -> 48278.549 | Y78: =VLOOKUP($A78,Python数据平滑!$A$25:$AN$52,COLUMN(Python数据平滑!W$25),0)/SUM(Python数据平滑!W$36:W$42)*情景假设!Y$34 -> 49896.105 | ... AE78: =VLOOKUP($A78,Python数据平滑!$A$25:$AN$52,COLUMN(Python数据平滑!AC$25),0)/SUM(Python数据平滑!AC$36:AC$42)*情景假设!AE$34 -> 60280.471 | AF78: =$AF$34*N49 -> 62134.835 | AG78: =VLOOKUP($A78,Python数据平滑!$A$25:$AN$52,COLUMN(Python数据平滑!AE$25),0)/SUM(Python数据平滑!AE$36:AE$42)*情景假设!AG$34 -> 64027.516 | AH78: =VLOOKUP($A78,Python数据平滑!$A$25:$AN$52,COLUMN(Python数据平滑!AF$25),0)/SUM(Python数据平滑!AF$36:AF$42)*情景假设!AH$34 -> 65957.068 | AI78: =VLOOKUP($A78,Python数据平滑!$A$25:$AN$52,COLUMN(Python数据平滑!AG$25),0)/SUM(Python数据平滑!AG$36:AG$42)*情景假设!AI$34 -> 67919.136 | AJ78: =VLOOKUP($A78,Python数据平滑!$A$25:$AN$52,COLUMN(Python数据平滑!AH$25),0)/SUM(Python数据平滑!AH$36:AH$42)*情景假设!AJ$34 -> 69908.799 | AK78: =VLOOKUP($A78,Python数据平滑!$A$25:$AN$52,COLUMN(Python数据平滑!AI$25),0)/SUM(Python数据平滑!AI$36:AI$42)*情景假设!AK$34 -> 71920.548 | AL78: =VLOOKUP($A78,Python数据平滑!$A$25:$AN$52,COLUMN(Python数据平滑!AJ$25),0)/SUM(Python数据平滑!AJ$36:AJ$42)*情景假设!AL$34 -> 73955.002 | AM78: =VLOOKUP($A78,Python数据平滑!$A$25:$AN$52,COLUMN(Python数据平滑!AK$25),0)/SUM(Python数据平滑!AK$36:AK$42)*情景假设!AM$34 -> 76016.101 | AN78: =VLOOKUP($A78,Python数据平滑!$A$25:$AN$52,COLUMN(Python数据平滑!AL$25),0)/SUM(Python数据平滑!AL$36:AL$42)*情景假设!AN$34 -> 78102.799 | AO78: =VLOOKUP($A78,Python数据平滑!$A$25:$AN$52,COLUMN(Python数据平滑!AM$25),0)/SUM(Python数据平滑!AM$36:AM$42)*情景假设!AO$34 -> 80213.947 | AP78: =AP$34*O49 -> 82348.298
A79: 制氢-中情景 | B79: 0 | C79: 0 | D79: 1 | E79: =VLOOKUP($A79,Python数据平滑!$A$25:$AN$52,COLUMN(Python数据平滑!C$25),0)/SUM(Python数据平滑!C$36:C$42)*情景假设!E$34 -> 25.99913 | F79: =VLOOKUP($A79,Python数据平滑!$A$25:$AN$52,COLUMN(Python数据平滑!D$25),0)/SUM(Python数据平滑!D$36:D$42)*情景假设!F$34 -> 389.19143 | G79: =G$34*K50 -> 1563.3609 | H79: =VLOOKUP($A79,Python数据平滑!$A$25:$AN$52,COLUMN(Python数据平滑!F$25),0)/SUM(Python数据平滑!F$36:F$42)*情景假设!H$34 -> 2329.9059 | I79: =VLOOKUP($A79,Python数据平滑!$A$25:$AN$52,COLUMN(Python数据平滑!G$25),0)/SUM(Python数据平滑!G$36:G$42)*情景假设!I$34 -> 3053.7446 | J79: =VLOOKUP($A79,Python数据平滑!$A$25:$AN$52,COLUMN(Python数据平滑!H$25),0)/SUM(Python数据平滑!H$36:H$42)*情景假设!J$34 -> 3709.1137 | K79: =VLOOKUP($A79,Python数据平滑!$A$25:$AN$52,COLUMN(Python数据平滑!I$25),0)/SUM(Python数据平滑!I$36:I$42)*情景假设!K$34 -> 4398.2299 | L79: =L$34*L50 -> 5362.7515 | M79: =VLOOKUP($A79,Python数据平滑!$A$25:$AN$52,COLUMN(Python数据平滑!K$25),0)/SUM(Python数据平滑!K$36:K$42)*情景假设!M$34 -> 6860.058 | N79: =VLOOKUP($A79,Python数据平滑!$A$25:$AN$52,COLUMN(Python数据平滑!L$25),0)/SUM(Python数据平滑!L$36:L$42)*情景假设!N$34 -> 8893.1954 | O79: =VLOOKUP($A79,Python数据平滑!$A$25:$AN$52,COLUMN(Python数据平滑!M$25),0)/SUM(Python数据平滑!M$36:M$42)*情景假设!O$34 -> 11335.935 | P79: =VLOOKUP($A79,Python数据平滑!$A$25:$AN$52,COLUMN(Python数据平滑!N$25),0)/SUM(Python数据平滑!N$36:N$42)*情景假设!P$34 -> 13791.514 | Q79: =Q$34*M50 -> 15553.419 | R79: =VLOOKUP($A79,Python数据平滑!$A$25:$AN$52,COLUMN(Python数据平滑!P$25),0)/SUM(Python数据平滑!P$36:P$42)*情景假设!R$34 -> 16648.807 | S79: =VLOOKUP($A79,Python数据平滑!$A$25:$AN$52,COLUMN(Python数据平滑!Q$25),0)/SUM(Python数据平滑!Q$36:Q$42)*情景假设!S$34 -> 17672.851 | T79: =VLOOKUP($A79,Python数据平滑!$A$25:$AN$52,COLUMN(Python数据平滑!R$25),0)/SUM(Python数据平滑!R$36:R$42)*情景假设!T$34 -> 18624.782 | U79: =VLOOKUP($A79,Python数据平滑!$A$25:$AN$52,COLUMN(Python数据平滑!S$25),0)/SUM(Python数据平滑!S$36:S$42)*情景假设!U$34 -> 19508.731 | V79: =VLOOKUP($A79,Python数据平滑!$A$25:$AN$52,COLUMN(Python数据平滑!T$25),0)/SUM(Python数据平滑!T$36:T$42)*情景假设!V$34 -> 20333.4 | W79: =VLOOKUP($A79,Python数据平滑!$A$25:$AN$52,COLUMN(Python数据平滑!U$25),0)/SUM(Python数据平滑!U$36:U$42)*情景假设!W$34 -> 21103.454 | X79: =VLOOKUP($A79,Python数据平滑!$A$25:$AN$52,COLUMN(Python数据平滑!V$25),0)/SUM(Python数据平滑!V$36:V$42)*情景假设!X$34 -> 21820.211 | Y79: =VLOOKUP($A79,Python数据平滑!$A$25:$AN$52,COLUMN(Python数据平滑!W$25),0)/SUM(Python数据平滑!W$36:W$42)*情景假设!Y$34 -> 22492.289 | ... AE79: =VLOOKUP($A79,Python数据平滑!$A$25:$AN$52,COLUMN(Python数据平滑!AC$25),0)/SUM(Python数据平滑!AC$36:AC$42)*情景假设!AE$34 -> 26326.304 | AF79: =$AF$34*N50 -> 27093.864 | AG79: =VLOOKUP($A79,Python数据平滑!$A$25:$AN$52,COLUMN(Python数据平滑!AE$25),0)/SUM(Python数据平滑!AE$36:AE$42)*情景假设!AG$34 -> 27907.844 | AH79: =VLOOKUP($A79,Python数据平滑!$A$25:$AN$52,COLUMN(Python数据平滑!AF$25),0)/SUM(Python数据平滑!AF$36:AF$42)*情景假设!AH$34 -> 28726.812 | AI79: =VLOOKUP($A79,Python数据平滑!$A$25:$AN$52,COLUMN(Python数据平滑!AG$25),0)/SUM(Python数据平滑!AG$36:AG$42)*情景假设!AI$34 -> 29547.314 | AJ79: =VLOOKUP($A79,Python数据平滑!$A$25:$AN$52,COLUMN(Python数据平滑!AH$25),0)/SUM(Python数据平滑!AH$36:AH$42)*情景假设!AJ$34 -> 30365.57 | AK79: =VLOOKUP($A79,Python数据平滑!$A$25:$AN$52,COLUMN(Python数据平滑!AI$25),0)/SUM(Python数据平滑!AI$36:AI$42)*情景假设!AK$34 -> 31177.477 | AL79: =VLOOKUP($A79,Python数据平滑!$A$25:$AN$52,COLUMN(Python数据平滑!AJ$25),0)/SUM(Python数据平滑!AJ$36:AJ$42)*情景假设!AL$34 -> 31981.53 | AM79: =VLOOKUP($A79,Python数据平滑!$A$25:$AN$52,COLUMN(Python数据平滑!AK$25),0)/SUM(Python数据平滑!AK$36:AK$42)*情景假设!AM$34 -> 32777.585 | AN79: =VLOOKUP($A79,Python数据平滑!$A$25:$AN$52,COLUMN(Python数据平滑!AL$25),0)/SUM(Python数据平滑!AL$36:AL$42)*情景假设!AN$34 -> 33563.272 | AO79: =VLOOKUP($A79,Python数据平滑!$A$25:$AN$52,COLUMN(Python数据平滑!AM$25),0)/SUM(Python数据平滑!AM$36:AM$42)*情景假设!AO$34 -> 34336.123 | AP79: =AP$34*O50 -> 35093.578
A80: 传统高耗能产业-中情景 | B80: =SUM('高情景（2001-2060, 2020RMB）'!U25:U26,'高情景（2001-2060, 2020RMB）'!U30,'高情景（2001-2060, 2020RMB）'!U34,'高情景（2001-2060, 2020RMB）'!U36:U37,'高情景（2001-2060, 2020RMB）'!U38:U40) -> 90023.293 | C80: =SUM('高情景（2001-2060, 2020RMB）'!V25:V26,'高情景（2001-2060, 2020RMB）'!V30,'高情景（2001-2060, 2020RMB）'!V34,'高情景（2001-2060, 2020RMB）'!V36:V37,'高情景（2001-2060, 2020RMB）'!V38:V40) -> 98562.089 | D80: =SUM('高情景（2001-2060, 2020RMB）'!W25:W26,'高情景（2001-2060, 2020RMB）'!W30,'高情景（2001-2060, 2020RMB）'!W34,'高情景（2001-2060, 2020RMB）'!W36:W37,'高情景（2001-2060, 2020RMB）'!W38:W40) -> 101803.01 | E80: =VLOOKUP($A80,Python数据平滑!$A$25:$AN$52,COLUMN(Python数据平滑!C$25),0)/SUM(Python数据平滑!C$36:C$42)*情景假设!E$34 -> 104120.7 | F80: =VLOOKUP($A80,Python数据平滑!$A$25:$AN$52,COLUMN(Python数据平滑!D$25),0)/SUM(Python数据平滑!D$36:D$42)*情景假设!F$34 -> 106329.35 | G80: =G$34*K51 -> 108305.49 | H80: =VLOOKUP($A80,Python数据平滑!$A$25:$AN$52,COLUMN(Python数据平滑!F$25),0)/SUM(Python数据平滑!F$36:F$42)*情景假设!H$34 -> 110430.56 | I80: =VLOOKUP($A80,Python数据平滑!$A$25:$AN$52,COLUMN(Python数据平滑!G$25),0)/SUM(Python数据平滑!G$36:G$42)*情景假设!I$34 -> 112605.53 | J80: =VLOOKUP($A80,Python数据平滑!$A$25:$AN$52,COLUMN(Python数据平滑!H$25),0)/SUM(Python数据平滑!H$36:H$42)*情景假设!J$34 -> 114741.33 | K80: =VLOOKUP($A80,Python数据平滑!$A$25:$AN$52,COLUMN(Python数据平滑!I$25),0)/SUM(Python数据平滑!I$36:I$42)*情景假设!K$34 -> 116715.15 | L80: =L$34*L51 -> 118370.55 | M80: =VLOOKUP($A80,Python数据平滑!$A$25:$AN$52,COLUMN(Python数据平滑!K$25),0)/SUM(Python数据平滑!K$36:K$42)*情景假设!M$34 -> 119669.85 | N80: =VLOOKUP($A80,Python数据平滑!$A$25:$AN$52,COLUMN(Python数据平滑!L$25),0)/SUM(Python数据平滑!L$36:L$42)*情景假设!N$34 -> 120721.62 | O80: =VLOOKUP($A80,Python数据平滑!$A$25:$AN$52,COLUMN(Python数据平滑!M$25),0)/SUM(Python数据平滑!M$36:M$42)*情景假设!O$34 -> 121586.74 | P80: =VLOOKUP($A80,Python数据平滑!$A$25:$AN$52,COLUMN(Python数据平滑!N$25),0)/SUM(Python数据平滑!N$36:N$42)*情景假设!P$34 -> 122387.14 | Q80: =Q$34*M51 -> 123310.5 | R80: =VLOOKUP($A80,Python数据平滑!$A$25:$AN$52,COLUMN(Python数据平滑!P$25),0)/SUM(Python数据平滑!P$36:P$42)*情景假设!R$34 -> 124288.6 | S80: =VLOOKUP($A80,Python数据平滑!$A$25:$AN$52,COLUMN(Python数据平滑!Q$25),0)/SUM(Python数据平滑!Q$36:Q$42)*情景假设!S$34 -> 125143.04 | T80: =VLOOKUP($A80,Python数据平滑!$A$25:$AN$52,COLUMN(Python数据平滑!R$25),0)/SUM(Python数据平滑!R$36:R$42)*情景假设!T$34 -> 125925.05 | U80: =VLOOKUP($A80,Python数据平滑!$A$25:$AN$52,COLUMN(Python数据平滑!S$25),0)/SUM(Python数据平滑!S$36:S$42)*情景假设!U$34 -> 126686.64 | V80: =VLOOKUP($A80,Python数据平滑!$A$25:$AN$52,COLUMN(Python数据平滑!T$25),0)/SUM(Python数据平滑!T$36:T$42)*情景假设!V$34 -> 127480.47 | W80: =VLOOKUP($A80,Python数据平滑!$A$25:$AN$52,COLUMN(Python数据平滑!U$25),0)/SUM(Python数据平滑!U$36:U$42)*情景假设!W$34 -> 128310.17 | X80: =VLOOKUP($A80,Python数据平滑!$A$25:$AN$52,COLUMN(Python数据平滑!V$25),0)/SUM(Python数据平滑!V$36:V$42)*情景假设!X$34 -> 129143.76 | Y80: =VLOOKUP($A80,Python数据平滑!$A$25:$AN$52,COLUMN(Python数据平滑!W$25),0)/SUM(Python数据平滑!W$36:W$42)*情景假设!Y$34 -> 129980.79 | ... AE80: =VLOOKUP($A80,Python数据平滑!$A$25:$AN$52,COLUMN(Python数据平滑!AC$25),0)/SUM(Python数据平滑!AC$36:AC$42)*情景假设!AE$34 -> 135059.39 | AF80: =$AF$34*N51 -> 135910.86 | AG80: =VLOOKUP($A80,Python数据平滑!$A$25:$AN$52,COLUMN(Python数据平滑!AE$25),0)/SUM(Python数据平滑!AE$36:AE$42)*情景假设!AG$34 -> 136775.42 | AH80: =VLOOKUP($A80,Python数据平滑!$A$25:$AN$52,COLUMN(Python数据平滑!AF$25),0)/SUM(Python数据平滑!AF$36:AF$42)*情景假设!AH$34 -> 137662.95 | AI80: =VLOOKUP($A80,Python数据平滑!$A$25:$AN$52,COLUMN(Python数据平滑!AG$25),0)/SUM(Python数据平滑!AG$36:AG$42)*情景假设!AI$34 -> 138564.14 | AJ80: =VLOOKUP($A80,Python数据平滑!$A$25:$AN$52,COLUMN(Python数据平滑!AH$25),0)/SUM(Python数据平滑!AH$36:AH$42)*情景假设!AJ$34 -> 139469.38 | AK80: =VLOOKUP($A80,Python数据平滑!$A$25:$AN$52,COLUMN(Python数据平滑!AI$25),0)/SUM(Python数据平滑!AI$36:AI$42)*情景假设!AK$34 -> 140368.77 | AL80: =VLOOKUP($A80,Python数据平滑!$A$25:$AN$52,COLUMN(Python数据平滑!AJ$25),0)/SUM(Python数据平滑!AJ$36:AJ$42)*情景假设!AL$34 -> 141264.94 | AM80: =VLOOKUP($A80,Python数据平滑!$A$25:$AN$52,COLUMN(Python数据平滑!AK$25),0)/SUM(Python数据平滑!AK$36:AK$42)*情景假设!AM$34 -> 142166.54 | AN80: =VLOOKUP($A80,Python数据平滑!$A$25:$AN$52,COLUMN(Python数据平滑!AL$25),0)/SUM(Python数据平滑!AL$36:AL$42)*情景假设!AN$34 -> 143072.34 | AO80: =VLOOKUP($A80,Python数据平滑!$A$25:$AN$52,COLUMN(Python数据平滑!AM$25),0)/SUM(Python数据平滑!AM$36:AM$42)*情景假设!AO$34 -> 143981.06 | AP80: =AP$34*O51 -> 144891.31
A81: 装备制造业-中情景 | B81: =SUM('高情景（2001-2060, 2020RMB）'!U41:U46) -> 81720.66 | C81: =SUM('高情景（2001-2060, 2020RMB）'!V41:V46) -> 95333.93 | D81: =SUM('高情景（2001-2060, 2020RMB）'!W41:W46) -> 101531.7 | E81: =VLOOKUP($A81,Python数据平滑!$A$25:$AN$52,COLUMN(Python数据平滑!C$25),0)/SUM(Python数据平滑!C$36:C$42)*情景假设!E$34 -> 105666.75 | F81: =VLOOKUP($A81,Python数据平滑!$A$25:$AN$52,COLUMN(Python数据平滑!D$25),0)/SUM(Python数据平滑!D$36:D$42)*情景假设!F$34 -> 109844.5 | G81: =G$34*K52 -> 113953.33 | H81: =VLOOKUP($A81,Python数据平滑!$A$25:$AN$52,COLUMN(Python数据平滑!F$25),0)/SUM(Python数据平滑!F$36:F$42)*情景假设!H$34 -> 118338.02 | I81: =VLOOKUP($A81,Python数据平滑!$A$25:$AN$52,COLUMN(Python数据平滑!G$25),0)/SUM(Python数据平滑!G$36:G$42)*情景假设!I$34 -> 122881.95 | J81: =VLOOKUP($A81,Python数据平滑!$A$25:$AN$52,COLUMN(Python数据平滑!H$25),0)/SUM(Python数据平滑!H$36:H$42)*情景假设!J$34 -> 127574.03 | K81: =VLOOKUP($A81,Python数据平滑!$A$25:$AN$52,COLUMN(Python数据平滑!I$25),0)/SUM(Python数据平滑!I$36:I$42)*情景假设!K$34 -> 132370.15 | L81: =L$34*L52 -> 137188.93 | M81: =VLOOKUP($A81,Python数据平滑!$A$25:$AN$52,COLUMN(Python数据平滑!K$25),0)/SUM(Python数据平滑!K$36:K$42)*情景假设!M$34 -> 142010.34 | N81: =VLOOKUP($A81,Python数据平滑!$A$25:$AN$52,COLUMN(Python数据平滑!L$25),0)/SUM(Python数据平滑!L$36:L$42)*情景假设!N$34 -> 146814.97 | O81: =VLOOKUP($A81,Python数据平滑!$A$25:$AN$52,COLUMN(Python数据平滑!M$25),0)/SUM(Python数据平滑!M$36:M$42)*情景假设!O$34 -> 151505.88 | P81: =VLOOKUP($A81,Python数据平滑!$A$25:$AN$52,COLUMN(Python数据平滑!N$25),0)/SUM(Python数据平滑!N$36:N$42)*情景假设!P$34 -> 156049.66 | Q81: =Q$34*M52 -> 160492.33 | R81: =VLOOKUP($A81,Python数据平滑!$A$25:$AN$52,COLUMN(Python数据平滑!P$25),0)/SUM(Python数据平滑!P$36:P$42)*情景假设!R$34 -> 164785.34 | S81: =VLOOKUP($A81,Python数据平滑!$A$25:$AN$52,COLUMN(Python数据平滑!Q$25),0)/SUM(Python数据平滑!Q$36:Q$42)*情景假设!S$34 -> 168866.24 | T81: =VLOOKUP($A81,Python数据平滑!$A$25:$AN$52,COLUMN(Python数据平滑!R$25),0)/SUM(Python数据平滑!R$36:R$42)*情景假设!T$34 -> 172803.25 | U81: =VLOOKUP($A81,Python数据平滑!$A$25:$AN$52,COLUMN(Python数据平滑!S$25),0)/SUM(Python数据平滑!S$36:S$42)*情景假设!U$34 -> 176672.12 | V81: =VLOOKUP($A81,Python数据平滑!$A$25:$AN$52,COLUMN(Python数据平滑!T$25),0)/SUM(Python数据平滑!T$36:T$42)*情景假设!V$34 -> 180555.65 | W81: =VLOOKUP($A81,Python数据平滑!$A$25:$AN$52,COLUMN(Python数据平滑!U$25),0)/SUM(Python数据平滑!U$36:U$42)*情景假设!W$34 -> 184472.02 | X81: =VLOOKUP($A81,Python数据平滑!$A$25:$AN$52,COLUMN(Python数据平滑!V$25),0)/SUM(Python数据平滑!V$36:V$42)*情景假设!X$34 -> 188389.05 | Y81: =VLOOKUP($A81,Python数据平滑!$A$25:$AN$52,COLUMN(Python数据平滑!W$25),0)/SUM(Python数据平滑!W$36:W$42)*情景假设!Y$34 -> 192319.79 | ... AE81: =VLOOKUP($A81,Python数据平滑!$A$25:$AN$52,COLUMN(Python数据平滑!AC$25),0)/SUM(Python数据平滑!AC$36:AC$42)*情景假设!AE$34 -> 217107.43 | AF81: =$AF$34*N52 -> 221619.09 | AG81: =VLOOKUP($A81,Python数据平滑!$A$25:$AN$52,COLUMN(Python数据平滑!AE$25),0)/SUM(Python数据平滑!AE$36:AE$42)*情景假设!AG$34 -> 226264.22 | AH81: =VLOOKUP($A81,Python数据平滑!$A$25:$AN$52,COLUMN(Python数据平滑!AF$25),0)/SUM(Python数据平滑!AF$36:AF$42)*情景假设!AH$34 -> 231012.35 | AI81: =VLOOKUP($A81,Python数据平滑!$A$25:$AN$52,COLUMN(Python数据平滑!AG$25),0)/SUM(Python数据平滑!AG$36:AG$42)*情景假设!AI$34 -> 235850.19 | AJ81: =VLOOKUP($A81,Python数据平滑!$A$25:$AN$52,COLUMN(Python数据平滑!AH$25),0)/SUM(Python数据平滑!AH$36:AH$42)*情景假设!AJ$34 -> 240763.08 | AK81: =VLOOKUP($A81,Python数据平滑!$A$25:$AN$52,COLUMN(Python数据平滑!AI$25),0)/SUM(Python数据平滑!AI$36:AI$42)*情景假设!AK$34 -> 245734.96 | AL81: =VLOOKUP($A81,Python数据平滑!$A$25:$AN$52,COLUMN(Python数据平滑!AJ$25),0)/SUM(Python数据平滑!AJ$36:AJ$42)*情景假设!AL$34 -> 250771.12 | AM81: =VLOOKUP($A81,Python数据平滑!$A$25:$AN$52,COLUMN(Python数据平滑!AK$25),0)/SUM(Python数据平滑!AK$36:AK$42)*情景假设!AM$34 -> 255887.95 | AN81: =VLOOKUP($A81,Python数据平滑!$A$25:$AN$52,COLUMN(Python数据平滑!AL$25),0)/SUM(Python数据平滑!AL$36:AL$42)*情景假设!AN$34 -> 261084.78 | AO81: =VLOOKUP($A81,Python数据平滑!$A$25:$AN$52,COLUMN(Python数据平滑!AM$25),0)/SUM(Python数据平滑!AM$36:AM$42)*情景假设!AO$34 -> 266360.72 | AP81: =AP$34*O52 -> 271714.64
A82: 高技术产业-中情景 | B82: =SUM('高情景（2001-2060, 2020RMB）'!U47:U48,'高情景（2001-2060, 2020RMB）'!U35) -> 42058.738 | C82: =SUM('高情景（2001-2060, 2020RMB）'!V47:V48,'高情景（2001-2060, 2020RMB）'!V35) -> 51422.622 | D82: =SUM('高情景（2001-2060, 2020RMB）'!W47:W48,'高情景（2001-2060, 2020RMB）'!W35) -> 54801.587 | E82: =VLOOKUP($A82,Python数据平滑!$A$25:$AN$52,COLUMN(Python数据平滑!C$25),0)/SUM(Python数据平滑!C$36:C$42)*情景假设!E$34 -> 57737.026 | F82: =VLOOKUP($A82,Python数据平滑!$A$25:$AN$52,COLUMN(Python数据平滑!D$25),0)/SUM(Python数据平滑!D$36:D$42)*情景假设!F$34 -> 60753.357 | G82: =G$34*K53 -> 63787.285 | H82: =VLOOKUP($A82,Python数据平滑!$A$25:$AN$52,COLUMN(Python数据平滑!F$25),0)/SUM(Python数据平滑!F$36:F$42)*情景假设!H$34 -> 67067.376 | I82: =VLOOKUP($A82,Python数据平滑!$A$25:$AN$52,COLUMN(Python数据平滑!G$25),0)/SUM(Python数据平滑!G$36:G$42)*情景假设!I$34 -> 70539.665 | J82: =VLOOKUP($A82,Python数据平滑!$A$25:$AN$52,COLUMN(Python数据平滑!H$25),0)/SUM(Python数据平滑!H$36:H$42)*情景假设!J$34 -> 74150.561 | K82: =VLOOKUP($A82,Python数据平滑!$A$25:$AN$52,COLUMN(Python数据平滑!I$25),0)/SUM(Python数据平滑!I$36:I$42)*情景假设!K$34 -> 77815.813 | L82: =L$34*L53 -> 81416.318 | M82: =VLOOKUP($A82,Python数据平滑!$A$25:$AN$52,COLUMN(Python数据平滑!K$25),0)/SUM(Python数据平滑!K$36:K$42)*情景假设!M$34 -> 84904.626 | N82: =VLOOKUP($A82,Python数据平滑!$A$25:$AN$52,COLUMN(Python数据平滑!L$25),0)/SUM(Python数据平滑!L$36:L$42)*情景假设!N$34 -> 88311.343 | O82: =VLOOKUP($A82,Python数据平滑!$A$25:$AN$52,COLUMN(Python数据平滑!M$25),0)/SUM(Python数据平滑!M$36:M$42)*情景假设!O$34 -> 91619.951 | P82: =VLOOKUP($A82,Python数据平滑!$A$25:$AN$52,COLUMN(Python数据平滑!N$25),0)/SUM(Python数据平滑!N$36:N$42)*情景假设!P$34 -> 94859.613 | Q82: =Q$34*M53 -> 98115.642 | R82: =VLOOKUP($A82,Python数据平滑!$A$25:$AN$52,COLUMN(Python数据平滑!P$25),0)/SUM(Python数据平滑!P$36:P$42)*情景假设!R$34 -> 101355.71 | S82: =VLOOKUP($A82,Python数据平滑!$A$25:$AN$52,COLUMN(Python数据平滑!Q$25),0)/SUM(Python数据平滑!Q$36:Q$42)*情景假设!S$34 -> 104495.36 | T82: =VLOOKUP($A82,Python数据平滑!$A$25:$AN$52,COLUMN(Python数据平滑!R$25),0)/SUM(Python数据平滑!R$36:R$42)*情景假设!T$34 -> 107575.24 | U82: =VLOOKUP($A82,Python数据平滑!$A$25:$AN$52,COLUMN(Python数据平滑!S$25),0)/SUM(Python数据平滑!S$36:S$42)*情景假设!U$34 -> 110641.82 | V82: =VLOOKUP($A82,Python数据平滑!$A$25:$AN$52,COLUMN(Python数据平滑!T$25),0)/SUM(Python数据平滑!T$36:T$42)*情景假设!V$34 -> 113747.19 | W82: =VLOOKUP($A82,Python数据平滑!$A$25:$AN$52,COLUMN(Python数据平滑!U$25),0)/SUM(Python数据平滑!U$36:U$42)*情景假设!W$34 -> 116903.8 | X82: =VLOOKUP($A82,Python数据平滑!$A$25:$AN$52,COLUMN(Python数据平滑!V$25),0)/SUM(Python数据平滑!V$36:V$42)*情景假设!X$34 -> 120092.39 | Y82: =VLOOKUP($A82,Python数据平滑!$A$25:$AN$52,COLUMN(Python数据平滑!W$25),0)/SUM(Python数据平滑!W$36:W$42)*情景假设!Y$34 -> 123322.26 | ... AE82: =VLOOKUP($A82,Python数据平滑!$A$25:$AN$52,COLUMN(Python数据平滑!AC$25),0)/SUM(Python数据平滑!AC$36:AC$42)*情景假设!AE$34 -> 144249.16 | AF82: =$AF$34*N53 -> 148134.1 | AG82: =VLOOKUP($A82,Python数据平滑!$A$25:$AN$52,COLUMN(Python数据平滑!AE$25),0)/SUM(Python数据平滑!AE$36:AE$42)*情景假设!AG$34 -> 152154.41 | AH82: =VLOOKUP($A82,Python数据平滑!$A$25:$AN$52,COLUMN(Python数据平滑!AF$25),0)/SUM(Python数据平滑!AF$36:AF$42)*情景假设!AH$34 -> 156289.49 | AI82: =VLOOKUP($A82,Python数据平滑!$A$25:$AN$52,COLUMN(Python数据平滑!AG$25),0)/SUM(Python数据平滑!AG$36:AG$42)*情景假设!AI$34 -> 160532.05 | AJ82: =VLOOKUP($A82,Python数据平滑!$A$25:$AN$52,COLUMN(Python数据平滑!AH$25),0)/SUM(Python数据平滑!AH$36:AH$42)*情景假设!AJ$34 -> 164873.69 | AK82: =VLOOKUP($A82,Python数据平滑!$A$25:$AN$52,COLUMN(Python数据平滑!AI$25),0)/SUM(Python数据平滑!AI$36:AI$42)*情景假设!AK$34 -> 169304.79 | AL82: =VLOOKUP($A82,Python数据平滑!$A$25:$AN$52,COLUMN(Python数据平滑!AJ$25),0)/SUM(Python数据平滑!AJ$36:AJ$42)*情景假设!AL$34 -> 173830.3 | AM82: =VLOOKUP($A82,Python数据平滑!$A$25:$AN$52,COLUMN(Python数据平滑!AK$25),0)/SUM(Python数据平滑!AK$36:AK$42)*情景假设!AM$34 -> 178463.01 | AN82: =VLOOKUP($A82,Python数据平滑!$A$25:$AN$52,COLUMN(Python数据平滑!AL$25),0)/SUM(Python数据平滑!AL$36:AL$42)*情景假设!AN$34 -> 183204.03 | AO82: =VLOOKUP($A82,Python数据平滑!$A$25:$AN$52,COLUMN(Python数据平滑!AM$25),0)/SUM(Python数据平滑!AM$36:AM$42)*情景假设!AO$34 -> 188054.32 | AP82: =AP$34*O53 -> 193014.68
A83: 其他产业-中情景 | B83: =SUM('高情景（2001-2060, 2020RMB）'!U16:U24,'高情景（2001-2060, 2020RMB）'!U27:U29,'高情景（2001-2060, 2020RMB）'!U31:U32,'高情景（2001-2060, 2020RMB）'!U49:U51) -> 50441.557 | C83: =SUM('高情景（2001-2060, 2020RMB）'!V16:V24,'高情景（2001-2060, 2020RMB）'!V27:V29,'高情景（2001-2060, 2020RMB）'!V31:V32,'高情景（2001-2060, 2020RMB）'!V49:V51) -> 56632.87 | D83: =SUM('高情景（2001-2060, 2020RMB）'!W16:W24,'高情景（2001-2060, 2020RMB）'!W27:W29,'高情景（2001-2060, 2020RMB）'!W31:W32,'高情景（2001-2060, 2020RMB）'!W49:W51) -> 59677.346 | E83: =VLOOKUP($A83,Python数据平滑!$A$25:$AN$52,COLUMN(Python数据平滑!C$25),0)/SUM(Python数据平滑!C$36:C$42)*情景假设!E$34 -> 60780.182 | F83: =VLOOKUP($A83,Python数据平滑!$A$25:$AN$52,COLUMN(Python数据平滑!D$25),0)/SUM(Python数据平滑!D$36:D$42)*情景假设!F$34 -> 61867.458 | G83: =G$34*K54 -> 62888.375 | H83: =VLOOKUP($A83,Python数据平滑!$A$25:$AN$52,COLUMN(Python数据平滑!F$25),0)/SUM(Python数据平滑!F$36:F$42)*情景假设!H$34 -> 64062.437 | I83: =VLOOKUP($A83,Python数据平滑!$A$25:$AN$52,COLUMN(Python数据平滑!G$25),0)/SUM(Python数据平滑!G$36:G$42)*情景假设!I$34 -> 65315.683 | J83: =VLOOKUP($A83,Python数据平滑!$A$25:$AN$52,COLUMN(Python数据平滑!H$25),0)/SUM(Python数据平滑!H$36:H$42)*情景假设!J$34 -> 66596.618 | K83: =VLOOKUP($A83,Python数据平滑!$A$25:$AN$52,COLUMN(Python数据平滑!I$25),0)/SUM(Python数据平滑!I$36:I$42)*情景假设!K$34 -> 67833.879 | L83: =L$34*L54 -> 68935.733 | M83: =VLOOKUP($A83,Python数据平滑!$A$25:$AN$52,COLUMN(Python数据平滑!K$25),0)/SUM(Python数据平滑!K$36:K$42)*情景假设!M$34 -> 69865.643 | N83: =VLOOKUP($A83,Python数据平滑!$A$25:$AN$52,COLUMN(Python数据平滑!L$25),0)/SUM(Python数据平滑!L$36:L$42)*情景假设!N$34 -> 70666.964 | O83: =VLOOKUP($A83,Python数据平滑!$A$25:$AN$52,COLUMN(Python数据平滑!M$25),0)/SUM(Python数据平滑!M$36:M$42)*情景假设!O$34 -> 71365.43 | P83: =VLOOKUP($A83,Python数据平滑!$A$25:$AN$52,COLUMN(Python数据平滑!N$25),0)/SUM(Python数据平滑!N$36:N$42)*情景假设!P$34 -> 72022.691 | Q83: =Q$34*M54 -> 72739.56 | R83: =VLOOKUP($A83,Python数据平滑!$A$25:$AN$52,COLUMN(Python数据平滑!P$25),0)/SUM(Python数据平滑!P$36:P$42)*情景假设!R$34 -> 73477.248 | S83: =VLOOKUP($A83,Python数据平滑!$A$25:$AN$52,COLUMN(Python数据平滑!Q$25),0)/SUM(Python数据平滑!Q$36:Q$42)*情景假设!S$34 -> 74138.242 | T83: =VLOOKUP($A83,Python数据平滑!$A$25:$AN$52,COLUMN(Python数据平滑!R$25),0)/SUM(Python数据平滑!R$36:R$42)*情景假设!T$34 -> 74753.059 | U83: =VLOOKUP($A83,Python数据平滑!$A$25:$AN$52,COLUMN(Python数据平滑!S$25),0)/SUM(Python数据平滑!S$36:S$42)*情景假设!U$34 -> 75352.98 | V83: =VLOOKUP($A83,Python数据平滑!$A$25:$AN$52,COLUMN(Python数据平滑!T$25),0)/SUM(Python数据平滑!T$36:T$42)*情景假设!V$34 -> 75969.952 | W83: =VLOOKUP($A83,Python数据平滑!$A$25:$AN$52,COLUMN(Python数据平滑!U$25),0)/SUM(Python数据平滑!U$36:U$42)*情景假设!W$34 -> 76606.895 | X83: =VLOOKUP($A83,Python数据平滑!$A$25:$AN$52,COLUMN(Python数据平滑!V$25),0)/SUM(Python数据平滑!V$36:V$42)*情景假设!X$34 -> 77245.487 | Y83: =VLOOKUP($A83,Python数据平滑!$A$25:$AN$52,COLUMN(Python数据平滑!W$25),0)/SUM(Python数据平滑!W$36:W$42)*情景假设!Y$34 -> 77886.161 | ... AE83: =VLOOKUP($A83,Python数据平滑!$A$25:$AN$52,COLUMN(Python数据平滑!AC$25),0)/SUM(Python数据平滑!AC$36:AC$42)*情景假设!AE$34 -> 81807.386 | AF83: =$AF$34*N54 -> 82478.807 | AG83: =VLOOKUP($A83,Python数据平滑!$A$25:$AN$52,COLUMN(Python数据平滑!AE$25),0)/SUM(Python数据平滑!AE$36:AE$42)*情景假设!AG$34 -> 83162.647 | AH83: =VLOOKUP($A83,Python数据平滑!$A$25:$AN$52,COLUMN(Python数据平滑!AF$25),0)/SUM(Python数据平滑!AF$36:AF$42)*情景假设!AH$34 -> 83863.152 | AI83: =VLOOKUP($A83,Python数据平滑!$A$25:$AN$52,COLUMN(Python数据平滑!AG$25),0)/SUM(Python数据平滑!AG$36:AG$42)*情景假设!AI$34 -> 84574.728 | AJ83: =VLOOKUP($A83,Python数据平滑!$A$25:$AN$52,COLUMN(Python数据平滑!AH$25),0)/SUM(Python数据平滑!AH$36:AH$42)*情景假设!AJ$34 -> 85291.551 | AK83: =VLOOKUP($A83,Python数据平滑!$A$25:$AN$52,COLUMN(Python数据平滑!AI$25),0)/SUM(Python数据平滑!AI$36:AI$42)*情景假设!AK$34 -> 86007.566 | AL83: =VLOOKUP($A83,Python数据平滑!$A$25:$AN$52,COLUMN(Python数据平滑!AJ$25),0)/SUM(Python数据平滑!AJ$36:AJ$42)*情景假设!AL$34 -> 86724.372 | AM83: =VLOOKUP($A83,Python数据平滑!$A$25:$AN$52,COLUMN(Python数据平滑!AK$25),0)/SUM(Python数据平滑!AK$36:AK$42)*情景假设!AM$34 -> 87447.274 | AN83: =VLOOKUP($A83,Python数据平滑!$A$25:$AN$52,COLUMN(Python数据平滑!AL$25),0)/SUM(Python数据平滑!AL$36:AL$42)*情景假设!AN$34 -> 88175.543 | AO83: =VLOOKUP($A83,Python数据平滑!$A$25:$AN$52,COLUMN(Python数据平滑!AM$25),0)/SUM(Python数据平滑!AM$36:AM$42)*情景假设!AO$34 -> 88908.395 | AP83: =AP$34*O54 -> 89644.983
A85: 交通运输业-中情景 | B85: ='高情景（2001-2060, 2020RMB）'!U57 -> 40582.9 | C85: ='高情景（2001-2060, 2020RMB）'!V57 -> 44991.984 | D85: ='高情景（2001-2060, 2020RMB）'!W57 -> 46450.003 | E85: =VLOOKUP($A85,Python数据平滑!$A$25:$AN$52,COLUMN(Python数据平滑!C$25),0)/SUM(Python数据平滑!C$43:C$45)*情景假设!E$36 -> 49153.13 | F85: =VLOOKUP($A85,Python数据平滑!$A$25:$AN$52,COLUMN(Python数据平滑!D$25),0)/SUM(Python数据平滑!D$43:D$45)*情景假设!F$36 -> 51970.894 | G85: =G$36*K57 -> 54898.825 | H85: =VLOOKUP($A85,Python数据平滑!$A$25:$AN$52,COLUMN(Python数据平滑!F$25),0)/SUM(Python数据平滑!F$43:F$45)*情景假设!H$36 -> 57997.043 | I85: =VLOOKUP($A85,Python数据平滑!$A$25:$AN$52,COLUMN(Python数据平滑!G$25),0)/SUM(Python数据平滑!G$43:G$45)*情景假设!I$36 -> 61283.056 | J85: =VLOOKUP($A85,Python数据平滑!$A$25:$AN$52,COLUMN(Python数据平滑!H$25),0)/SUM(Python数据平滑!H$43:H$45)*情景假设!J$36 -> 64675.359 | K85: =VLOOKUP($A85,Python数据平滑!$A$25:$AN$52,COLUMN(Python数据平滑!I$25),0)/SUM(Python数据平滑!I$43:I$45)*情景假设!K$36 -> 68075.574 | L85: =L$36*L57 -> 71368.115 | M85: =VLOOKUP($A85,Python数据平滑!$A$25:$AN$52,COLUMN(Python数据平滑!K$25),0)/SUM(Python数据平滑!K$43:K$45)*情景假设!M$36 -> 74542.868 | N85: =VLOOKUP($A85,Python数据平滑!$A$25:$AN$52,COLUMN(Python数据平滑!L$25),0)/SUM(Python数据平滑!L$43:L$45)*情景假设!N$36 -> 77672.973 | O85: =VLOOKUP($A85,Python数据平滑!$A$25:$AN$52,COLUMN(Python数据平滑!M$25),0)/SUM(Python数据平滑!M$43:M$45)*情景假设!O$36 -> 80755.41 | P85: =VLOOKUP($A85,Python数据平滑!$A$25:$AN$52,COLUMN(Python数据平滑!N$25),0)/SUM(Python数据平滑!N$43:N$45)*情景假设!P$36 -> 83787.385 | Q85: =Q$36*M57 -> 86766.223 | R85: =VLOOKUP($A85,Python数据平滑!$A$25:$AN$52,COLUMN(Python数据平滑!P$25),0)/SUM(Python数据平滑!P$43:P$45)*情景假设!R$36 -> 89671.015 | S85: =VLOOKUP($A85,Python数据平滑!$A$25:$AN$52,COLUMN(Python数据平滑!Q$25),0)/SUM(Python数据平滑!Q$43:Q$45)*情景假设!S$36 -> 92501.127 | T85: =VLOOKUP($A85,Python数据平滑!$A$25:$AN$52,COLUMN(Python数据平滑!R$25),0)/SUM(Python数据平滑!R$43:R$45)*情景假设!T$36 -> 95288.334 | U85: =VLOOKUP($A85,Python数据平滑!$A$25:$AN$52,COLUMN(Python数据平滑!S$25),0)/SUM(Python数据平滑!S$43:S$45)*情景假设!U$36 -> 98069.814 | V85: =VLOOKUP($A85,Python数据平滑!$A$25:$AN$52,COLUMN(Python数据平滑!T$25),0)/SUM(Python数据平滑!T$43:T$45)*情景假设!V$36 -> 100888.11 | W85: =VLOOKUP($A85,Python数据平滑!$A$25:$AN$52,COLUMN(Python数据平滑!U$25),0)/SUM(Python数据平滑!U$43:U$45)*情景假设!W$36 -> 103750.95 | X85: =VLOOKUP($A85,Python数据平滑!$A$25:$AN$52,COLUMN(Python数据平滑!V$25),0)/SUM(Python数据平滑!V$43:V$45)*情景假设!X$36 -> 106638.2 | Y85: =VLOOKUP($A85,Python数据平滑!$A$25:$AN$52,COLUMN(Python数据平滑!W$25),0)/SUM(Python数据平滑!W$43:W$45)*情景假设!Y$36 -> 109555.33 | ... AE85: =VLOOKUP($A85,Python数据平滑!$A$25:$AN$52,COLUMN(Python数据平滑!AC$25),0)/SUM(Python数据平滑!AC$43:AC$45)*情景假设!AE$36 -> 128166.17 | AF85: =$AF$36*N57 -> 131560.3 | AG85: =VLOOKUP($A85,Python数据平滑!$A$25:$AN$52,COLUMN(Python数据平滑!AE$25),0)/SUM(Python数据平滑!AE$43:AE$45)*情景假设!AG$36 -> 135051.68 | AH85: =VLOOKUP($A85,Python数据平滑!$A$25:$AN$52,COLUMN(Python数据平滑!AF$25),0)/SUM(Python数据平滑!AF$43:AF$45)*情景假设!AH$36 -> 138618.44 | AI85: =VLOOKUP($A85,Python数据平滑!$A$25:$AN$52,COLUMN(Python数据平滑!AG$25),0)/SUM(Python数据平滑!AG$43:AG$45)*情景假设!AI$36 -> 142252.92 | AJ85: =VLOOKUP($A85,Python数据平滑!$A$25:$AN$52,COLUMN(Python数据平滑!AH$25),0)/SUM(Python数据平滑!AH$43:AH$45)*情景假设!AJ$36 -> 145946.45 | AK85: =VLOOKUP($A85,Python数据平滑!$A$25:$AN$52,COLUMN(Python数据平滑!AI$25),0)/SUM(Python数据平滑!AI$43:AI$45)*情景假设!AK$36 -> 149689.36 | AL85: =VLOOKUP($A85,Python数据平滑!$A$25:$AN$52,COLUMN(Python数据平滑!AJ$25),0)/SUM(Python数据平滑!AJ$43:AJ$45)*情景假设!AL$36 -> 153484.88 | AM85: =VLOOKUP($A85,Python数据平滑!$A$25:$AN$52,COLUMN(Python数据平滑!AK$25),0)/SUM(Python数据平滑!AK$43:AK$45)*情景假设!AM$36 -> 157343.16 | AN85: =VLOOKUP($A85,Python数据平滑!$A$25:$AN$52,COLUMN(Python数据平滑!AL$25),0)/SUM(Python数据平滑!AL$43:AL$45)*情景假设!AN$36 -> 161264.03 | AO85: =VLOOKUP($A85,Python数据平滑!$A$25:$AN$52,COLUMN(Python数据平滑!AM$25),0)/SUM(Python数据平滑!AM$43:AM$45)*情景假设!AO$36 -> 165247.19 | AP85: =AP$36*O57 -> 169292.23
A86: 传统服务业-中情景 | B86: =SUM('高情景（2001-2060, 2020RMB）'!U58:U59) -> 111371.5 | C86: =SUM('高情景（2001-2060, 2020RMB）'!V58:V59) -> 122702.13 | D86: =SUM('高情景（2001-2060, 2020RMB）'!W58:W59) -> 123782.33 | E86: =VLOOKUP($A86,Python数据平滑!$A$25:$AN$52,COLUMN(Python数据平滑!C$25),0)/SUM(Python数据平滑!C$43:C$45)*情景假设!E$36 -> 131107.93 | F86: =VLOOKUP($A86,Python数据平滑!$A$25:$AN$52,COLUMN(Python数据平滑!D$25),0)/SUM(Python数据平滑!D$43:D$45)*情景假设!F$36 -> 138788.27 | G86: =G$36*K58 -> 146829.14 | H86: =VLOOKUP($A86,Python数据平滑!$A$25:$AN$52,COLUMN(Python数据平滑!F$25),0)/SUM(Python数据平滑!F$43:F$45)*情景假设!H$36 -> 155446.12 | I86: =VLOOKUP($A86,Python数据平滑!$A$25:$AN$52,COLUMN(Python数据平滑!G$25),0)/SUM(Python数据平滑!G$43:G$45)*情景假设!I$36 -> 164691.5 | J86: =VLOOKUP($A86,Python数据平滑!$A$25:$AN$52,COLUMN(Python数据平滑!H$25),0)/SUM(Python数据平滑!H$43:H$45)*情景假设!J$36 -> 174279.55 | K86: =VLOOKUP($A86,Python数据平滑!$A$25:$AN$52,COLUMN(Python数据平滑!I$25),0)/SUM(Python数据平滑!I$43:I$45)*情景假设!K$36 -> 183858.61 | L86: =L$36*L58 -> 193009.35 | M86: =VLOOKUP($A86,Python数据平滑!$A$25:$AN$52,COLUMN(Python数据平滑!K$25),0)/SUM(Python数据平滑!K$43:K$45)*情景假设!M$36 -> 201637.78 | N86: =VLOOKUP($A86,Python数据平滑!$A$25:$AN$52,COLUMN(Python数据平滑!L$25),0)/SUM(Python数据平滑!L$43:L$45)*情景假设!N$36 -> 210009.16 | O86: =VLOOKUP($A86,Python数据平滑!$A$25:$AN$52,COLUMN(Python数据平滑!M$25),0)/SUM(Python数据平滑!M$43:M$45)*情景假设!O$36 -> 218208.4 | P86: =VLOOKUP($A86,Python数据平滑!$A$25:$AN$52,COLUMN(Python数据平滑!N$25),0)/SUM(Python数据平滑!N$43:N$45)*情景假设!P$36 -> 226337.92 | Q86: =Q$36*M58 -> 234516.71 | R86: =VLOOKUP($A86,Python数据平滑!$A$25:$AN$52,COLUMN(Python数据平滑!P$25),0)/SUM(Python数据平滑!P$43:P$45)*情景假设!R$36 -> 242665.5 | S86: =VLOOKUP($A86,Python数据平滑!$A$25:$AN$52,COLUMN(Python数据平滑!Q$25),0)/SUM(Python数据平滑!Q$43:Q$45)*情景假设!S$36 -> 250668.56 | T86: =VLOOKUP($A86,Python数据平滑!$A$25:$AN$52,COLUMN(Python数据平滑!R$25),0)/SUM(Python数据平滑!R$43:R$45)*情景假设!T$36 -> 258613.26 | U86: =VLOOKUP($A86,Python数据平滑!$A$25:$AN$52,COLUMN(Python数据平滑!S$25),0)/SUM(Python数据平滑!S$43:S$45)*情景假设!U$36 -> 266601.9 | V86: =VLOOKUP($A86,Python数据平滑!$A$25:$AN$52,COLUMN(Python数据平滑!T$25),0)/SUM(Python数据平滑!T$43:T$45)*情景假设!V$36 -> 274751.82 | W86: =VLOOKUP($A86,Python数据平滑!$A$25:$AN$52,COLUMN(Python数据平滑!U$25),0)/SUM(Python数据平滑!U$43:U$45)*情景假设!W$36 -> 283086.12 | X86: =VLOOKUP($A86,Python数据平滑!$A$25:$AN$52,COLUMN(Python数据平滑!V$25),0)/SUM(Python数据平滑!V$43:V$45)*情景假设!X$36 -> 291551.76 | Y86: =VLOOKUP($A86,Python数据平滑!$A$25:$AN$52,COLUMN(Python数据平滑!W$25),0)/SUM(Python数据平滑!W$43:W$45)*情景假设!Y$36 -> 300165.33 | ... AE86: =VLOOKUP($A86,Python数据平滑!$A$25:$AN$52,COLUMN(Python数据平滑!AC$25),0)/SUM(Python数据平滑!AC$43:AC$45)*情景假设!AE$36 -> 356365.88 | AF86: =$AF$36*N58 -> 366800.58 | AG86: =VLOOKUP($A86,Python数据平滑!$A$25:$AN$52,COLUMN(Python数据平滑!AE$25),0)/SUM(Python数据平滑!AE$43:AE$45)*情景假设!AG$36 -> 377593.73 | AH86: =VLOOKUP($A86,Python数据平滑!$A$25:$AN$52,COLUMN(Python数据平滑!AF$25),0)/SUM(Python数据平滑!AF$43:AF$45)*情景假设!AH$36 -> 388697.94 | AI86: =VLOOKUP($A86,Python数据平滑!$A$25:$AN$52,COLUMN(Python数据平滑!AG$25),0)/SUM(Python数据平滑!AG$43:AG$45)*情景假设!AI$36 -> 400096.48 | AJ86: =VLOOKUP($A86,Python数据平滑!$A$25:$AN$52,COLUMN(Python数据平滑!AH$25),0)/SUM(Python数据平滑!AH$43:AH$45)*情景假设!AJ$36 -> 411769.7 | AK86: =VLOOKUP($A86,Python数据平滑!$A$25:$AN$52,COLUMN(Python数据平滑!AI$25),0)/SUM(Python数据平滑!AI$43:AI$45)*情景假设!AK$36 -> 423694.82 | AL86: =VLOOKUP($A86,Python数据平滑!$A$25:$AN$52,COLUMN(Python数据平滑!AJ$25),0)/SUM(Python数据平滑!AJ$43:AJ$45)*情景假设!AL$36 -> 435885.44 | AM86: =VLOOKUP($A86,Python数据平滑!$A$25:$AN$52,COLUMN(Python数据平滑!AK$25),0)/SUM(Python数据平滑!AK$43:AK$45)*情景假设!AM$36 -> 448375.04 | AN86: =VLOOKUP($A86,Python数据平滑!$A$25:$AN$52,COLUMN(Python数据平滑!AL$25),0)/SUM(Python数据平滑!AL$43:AL$45)*情景假设!AN$36 -> 461168.02 | AO86: =VLOOKUP($A86,Python数据平滑!$A$25:$AN$52,COLUMN(Python数据平滑!AM$25),0)/SUM(Python数据平滑!AM$43:AM$45)*情景假设!AO$36 -> 474268.53 | AP86: =AP$36*O58 -> 487680.43
A87: 现代服务业-中情景 | B87: =SUM('高情景（2001-2060, 2020RMB）'!U60:U70) -> 394868.3 | C87: =SUM('高情景（2001-2060, 2020RMB）'!V60:V70) -> 415244.29 | D87: =SUM('高情景（2001-2060, 2020RMB）'!W60:W70) -> 421311.1 | E87: =VLOOKUP($A87,Python数据平滑!$A$25:$AN$52,COLUMN(Python数据平滑!C$25),0)/SUM(Python数据平滑!C$43:C$45)*情景假设!E$36 -> 451965.51 | F87: =VLOOKUP($A87,Python数据平滑!$A$25:$AN$52,COLUMN(Python数据平滑!D$25),0)/SUM(Python数据平滑!D$43:D$45)*情景假设!F$36 -> 484434.48 | G87: =G$36*K59 -> 518729.05 | H87: =VLOOKUP($A87,Python数据平滑!$A$25:$AN$52,COLUMN(Python数据平滑!F$25),0)/SUM(Python数据平滑!F$43:F$45)*情景假设!H$36 -> 555698.39 | I87: =VLOOKUP($A87,Python数据平滑!$A$25:$AN$52,COLUMN(Python数据平滑!G$25),0)/SUM(Python数据平滑!G$43:G$45)*情景假设!I$36 -> 595641.11 | J87: =VLOOKUP($A87,Python数据平滑!$A$25:$AN$52,COLUMN(Python数据平滑!H$25),0)/SUM(Python数据平滑!H$43:H$45)*情景假设!J$36 -> 637519.99 | K87: =VLOOKUP($A87,Python数据平滑!$A$25:$AN$52,COLUMN(Python数据平滑!I$25),0)/SUM(Python数据平滑!I$43:I$45)*情景假设!K$36 -> 679988.06 | L87: =L$36*L59 -> 721369.98 | M87: =VLOOKUP($A87,Python数据平滑!$A$25:$AN$52,COLUMN(Python数据平滑!K$25),0)/SUM(Python数据平滑!K$43:K$45)*情景假设!M$36 -> 761026.88 | N87: =VLOOKUP($A87,Python数据平滑!$A$25:$AN$52,COLUMN(Python数据平滑!L$25),0)/SUM(Python数据平滑!L$43:L$45)*情景假设!N$36 -> 799904.5 | O87: =VLOOKUP($A87,Python数据平滑!$A$25:$AN$52,COLUMN(Python数据平滑!M$25),0)/SUM(Python数据平滑!M$43:M$45)*情景假设!O$36 -> 838569.43 | P87: =VLOOKUP($A87,Python数据平滑!$A$25:$AN$52,COLUMN(Python数据平滑!N$25),0)/SUM(Python数据平滑!N$43:N$45)*情景假设!P$36 -> 877729.58 | Q87: =Q$36*M59 -> 918234.55 | R87: =VLOOKUP($A87,Python数据平滑!$A$25:$AN$52,COLUMN(Python数据平滑!P$25),0)/SUM(Python数据平滑!P$43:P$45)*情景假设!R$36 -> 960014.46 | S87: =VLOOKUP($A87,Python数据平滑!$A$25:$AN$52,COLUMN(Python数据平滑!Q$25),0)/SUM(Python数据平滑!Q$43:Q$45)*情景假设!S$36 -> 1002526 | T87: =VLOOKUP($A87,Python数据平滑!$A$25:$AN$52,COLUMN(Python数据平滑!R$25),0)/SUM(Python数据平滑!R$43:R$45)*情景假设!T$36 -> 1046058 | U87: =VLOOKUP($A87,Python数据平滑!$A$25:$AN$52,COLUMN(Python数据平滑!S$25),0)/SUM(Python数据平滑!S$43:S$45)*情景假设!U$36 -> 1090957 | V87: =VLOOKUP($A87,Python数据平滑!$A$25:$AN$52,COLUMN(Python数据平滑!T$25),0)/SUM(Python数据平滑!T$43:T$45)*情景假设!V$36 -> 1137631.6 | W87: =VLOOKUP($A87,Python数据平滑!$A$25:$AN$52,COLUMN(Python数据平滑!U$25),0)/SUM(Python数据平滑!U$43:U$45)*情景假设!W$36 -> 1186098.1 | X87: =VLOOKUP($A87,Python数据平滑!$A$25:$AN$52,COLUMN(Python数据平滑!V$25),0)/SUM(Python数据平滑!V$43:V$45)*情景假设!X$36 -> 1236032.8 | Y87: =VLOOKUP($A87,Python数据平滑!$A$25:$AN$52,COLUMN(Python数据平滑!W$25),0)/SUM(Python数据平滑!W$43:W$45)*情景假设!Y$36 -> 1287376.2 | ... AE87: =VLOOKUP($A87,Python数据平滑!$A$25:$AN$52,COLUMN(Python数据平滑!AC$25),0)/SUM(Python数据平滑!AC$43:AC$45)*情景假设!AE$36 -> 1620857.3 | AF87: =$AF$36*N59 -> 1679789.8 | AG87: =VLOOKUP($A87,Python数据平滑!$A$25:$AN$52,COLUMN(Python数据平滑!AE$25),0)/SUM(Python数据平滑!AE$43:AE$45)*情景假设!AG$36 -> 1739645.6 | AH87: =VLOOKUP($A87,Python数据平滑!$A$25:$AN$52,COLUMN(Python数据平滑!AF$25),0)/SUM(Python数据平滑!AF$43:AF$45)*情景假设!AH$36 -> 1800598.2 | AI87: =VLOOKUP($A87,Python数据平滑!$A$25:$AN$52,COLUMN(Python数据平滑!AG$25),0)/SUM(Python数据平滑!AG$43:AG$45)*情景假设!AI$36 -> 1862497.1 | AJ87: =VLOOKUP($A87,Python数据平滑!$A$25:$AN$52,COLUMN(Python数据平滑!AH$25),0)/SUM(Python数据平滑!AH$43:AH$45)*情景假设!AJ$36 -> 1925172.1 | AK87: =VLOOKUP($A87,Python数据平滑!$A$25:$AN$52,COLUMN(Python数据平滑!AI$25),0)/SUM(Python数据平滑!AI$43:AI$45)*情景假设!AK$36 -> 1988432.5 | AL87: =VLOOKUP($A87,Python数据平滑!$A$25:$AN$52,COLUMN(Python数据平滑!AJ$25),0)/SUM(Python数据平滑!AJ$43:AJ$45)*情景假设!AL$36 -> 2052253.9 | AM87: =VLOOKUP($A87,Python数据平滑!$A$25:$AN$52,COLUMN(Python数据平滑!AK$25),0)/SUM(Python数据平滑!AK$43:AK$45)*情景假设!AM$36 -> 2116702.9 | AN87: =VLOOKUP($A87,Python数据平滑!$A$25:$AN$52,COLUMN(Python数据平滑!AL$25),0)/SUM(Python数据平滑!AL$43:AL$45)*情景假设!AN$36 -> 2181707 | AO87: =VLOOKUP($A87,Python数据平滑!$A$25:$AN$52,COLUMN(Python数据平滑!AM$25),0)/SUM(Python数据平滑!AM$43:AM$45)*情景假设!AO$36 -> 2247188.9 | AP87: =AP$36*O59 -> 2313066.5
A89: 低情景 | B89: 2020 | C89: 2021 | D89: 2022 | E89: 2023 | F89: 2024 | G89: 2025 | H89: 2026 | I89: 2027 | J89: 2028 | K89: 2029 | L89: 2030 | M89: 2031 | N89: 2032 | O89: 2033 | P89: 2034 | Q89: 2035 | R89: 2036 | S89: 2037 | T89: 2038 | U89: 2039 | V89: 2040 | W89: 2041 | X89: 2042 | Y89: 2043 | Z89: 2044 | AA89: 2045 | AB89: 2046 | AC89: 2047 | AD89: 2048 | AE89: 2049 | AF89: 2050 | AG89: 2051 | AH89: 2052 | AI89: 2053 | AJ89: 2054 | AK89: 2055 | AL89: 2056 | AM89: 2057 | AN89: 2058 | AO89: 2059 | AP89: 2060
A90: 能源产业-低情景 | B90: =SUM('高情景（2001-2060, 2020RMB）'!U14:U15,'高情景（2001-2060, 2020RMB）'!U33,'高情景（2001-2060, 2020RMB）'!U53:U54) -> 34486.847 | C90: =SUM('高情景（2001-2060, 2020RMB）'!V14:V15,'高情景（2001-2060, 2020RMB）'!V33,'高情景（2001-2060, 2020RMB）'!V53:V54) -> 37878.28 | D90: =SUM('高情景（2001-2060, 2020RMB）'!W14:W15,'高情景（2001-2060, 2020RMB）'!W33,'高情景（2001-2060, 2020RMB）'!W53:W54) -> 40294.225 | E90: =VLOOKUP($A90,Python数据平滑!$A$25:$AN$52,COLUMN(Python数据平滑!C$25),0)/SUM(Python数据平滑!C$46:C$52)*情景假设!E$40 -> 41086.104 | F90: =VLOOKUP($A90,Python数据平滑!$A$25:$AN$52,COLUMN(Python数据平滑!D$25),0)/SUM(Python数据平滑!D$46:D$52)*情景假设!F$40 -> 41779.035 | G90: =G$40*R48 -> 42270.526 | H90: =VLOOKUP($A90,Python数据平滑!$A$25:$AN$52,COLUMN(Python数据平滑!F$25),0)/SUM(Python数据平滑!F$46:F$52)*情景假设!H$40 -> 42733.072 | I90: =VLOOKUP($A90,Python数据平滑!$A$25:$AN$52,COLUMN(Python数据平滑!G$25),0)/SUM(Python数据平滑!G$46:G$52)*情景假设!I$40 -> 43149.88 | J90: =VLOOKUP($A90,Python数据平滑!$A$25:$AN$52,COLUMN(Python数据平滑!H$25),0)/SUM(Python数据平滑!H$46:H$52)*情景假设!J$40 -> 43536.026 | K90: =VLOOKUP($A90,Python数据平滑!$A$25:$AN$52,COLUMN(Python数据平滑!I$25),0)/SUM(Python数据平滑!I$46:I$52)*情景假设!K$40 -> 43892.295 | L90: =L$40*S48 -> 44204.994 | M90: =VLOOKUP($A90,Python数据平滑!$A$25:$AN$52,COLUMN(Python数据平滑!K$25),0)/SUM(Python数据平滑!K$46:K$52)*情景假设!M$40 -> 44454.332 | N90: =VLOOKUP($A90,Python数据平滑!$A$25:$AN$52,COLUMN(Python数据平滑!L$25),0)/SUM(Python数据平滑!L$46:L$52)*情景假设!N$40 -> 44636.138 | O90: =VLOOKUP($A90,Python数据平滑!$A$25:$AN$52,COLUMN(Python数据平滑!M$25),0)/SUM(Python数据平滑!M$46:M$52)*情景假设!O$40 -> 44761.457 | P90: =VLOOKUP($A90,Python数据平滑!$A$25:$AN$52,COLUMN(Python数据平滑!N$25),0)/SUM(Python数据平滑!N$46:N$52)*情景假设!P$40 -> 44874.961 | Q90: =Q$40*T48 -> 45056.168 | R90: =VLOOKUP($A90,Python数据平滑!$A$25:$AN$52,COLUMN(Python数据平滑!P$25),0)/SUM(Python数据平滑!P$46:P$52)*情景假设!R$40 -> 45279.05 | S90: =VLOOKUP($A90,Python数据平滑!$A$25:$AN$52,COLUMN(Python数据平滑!Q$25),0)/SUM(Python数据平滑!Q$46:Q$52)*情景假设!S$40 -> 45465.051 | T90: =VLOOKUP($A90,Python数据平滑!$A$25:$AN$52,COLUMN(Python数据平滑!R$25),0)/SUM(Python数据平滑!R$46:R$52)*情景假设!T$40 -> 45627.157 | U90: =VLOOKUP($A90,Python数据平滑!$A$25:$AN$52,COLUMN(Python数据平滑!S$25),0)/SUM(Python数据平滑!S$46:S$52)*情景假设!U$40 -> 45778.246 | V90: =VLOOKUP($A90,Python数据平滑!$A$25:$AN$52,COLUMN(Python数据平滑!T$25),0)/SUM(Python数据平滑!T$46:T$52)*情景假设!V$40 -> 45931.089 | W90: =VLOOKUP($A90,Python数据平滑!$A$25:$AN$52,COLUMN(Python数据平滑!U$25),0)/SUM(Python数据平滑!U$46:U$52)*情景假设!W$40 -> 46086.793 | X90: =VLOOKUP($A90,Python数据平滑!$A$25:$AN$52,COLUMN(Python数据平滑!V$25),0)/SUM(Python数据平滑!V$46:V$52)*情景假设!X$40 -> 46237.489 | Y90: =VLOOKUP($A90,Python数据平滑!$A$25:$AN$52,COLUMN(Python数据平滑!W$25),0)/SUM(Python数据平滑!W$46:W$52)*情景假设!Y$40 -> 46382.325 | ... AE90: =VLOOKUP($A90,Python数据平滑!$A$25:$AN$52,COLUMN(Python数据平滑!AC$25),0)/SUM(Python数据平滑!AC$46:AC$52)*情景假设!AE$40 -> 47096.614 | AF90: =$AF$40*U48 -> 47184.906 | AG90: =VLOOKUP($A90,Python数据平滑!$A$25:$AN$52,COLUMN(Python数据平滑!AE$25),0)/SUM(Python数据平滑!AE$46:AE$52)*情景假设!AG$40 -> 47268.133 | AH90: =VLOOKUP($A90,Python数据平滑!$A$25:$AN$52,COLUMN(Python数据平滑!AF$25),0)/SUM(Python数据平滑!AF$46:AF$52)*情景假设!AH$40 -> 47352.213 | AI90: =VLOOKUP($A90,Python数据平滑!$A$25:$AN$52,COLUMN(Python数据平滑!AG$25),0)/SUM(Python数据平滑!AG$46:AG$52)*情景假设!AI$40 -> 47436.211 | AJ90: =VLOOKUP($A90,Python数据平滑!$A$25:$AN$52,COLUMN(Python数据平滑!AH$25),0)/SUM(Python数据平滑!AH$46:AH$52)*情景假设!AJ$40 -> 47519.157 | AK90: =VLOOKUP($A90,Python数据平滑!$A$25:$AN$52,COLUMN(Python数据平滑!AI$25),0)/SUM(Python数据平滑!AI$46:AI$52)*情景假设!AK$40 -> 47600.054 | AL90: =VLOOKUP($A90,Python数据平滑!$A$25:$AN$52,COLUMN(Python数据平滑!AJ$25),0)/SUM(Python数据平滑!AJ$46:AJ$52)*情景假设!AL$40 -> 47679.51 | AM90: =VLOOKUP($A90,Python数据平滑!$A$25:$AN$52,COLUMN(Python数据平滑!AK$25),0)/SUM(Python数据平滑!AK$46:AK$52)*情景假设!AM$40 -> 47758.364 | AN90: =VLOOKUP($A90,Python数据平滑!$A$25:$AN$52,COLUMN(Python数据平滑!AL$25),0)/SUM(Python数据平滑!AL$46:AL$52)*情景假设!AN$40 -> 47835.923 | AO90: =VLOOKUP($A90,Python数据平滑!$A$25:$AN$52,COLUMN(Python数据平滑!AM$25),0)/SUM(Python数据平滑!AM$46:AM$52)*情景假设!AO$40 -> 47911.469 | AP90: =AP$40*V48 -> 47984.26
A91: 电力与热力产业-低情景 | B91: ='高情景（2001-2060, 2020RMB）'!U52 -> 14171.805 | C91: ='高情景（2001-2060, 2020RMB）'!V52 -> 16363.885 | D91: ='高情景（2001-2060, 2020RMB）'!W52 -> 17470.728 | E91: =VLOOKUP($A91,Python数据平滑!$A$25:$AN$52,COLUMN(Python数据平滑!C$25),0)/SUM(Python数据平滑!C$46:C$52)*情景假设!E$40 -> 18934.133 | F91: =VLOOKUP($A91,Python数据平滑!$A$25:$AN$52,COLUMN(Python数据平滑!D$25),0)/SUM(Python数据平滑!D$46:D$52)*情景假设!F$40 -> 20448.981 | G91: =G$40*R49 -> 21964.097 | H91: =VLOOKUP($A91,Python数据平滑!$A$25:$AN$52,COLUMN(Python数据平滑!F$25),0)/SUM(Python数据平滑!F$46:F$52)*情景假设!H$40 -> 23572.962 | I91: =VLOOKUP($A91,Python数据平滑!$A$25:$AN$52,COLUMN(Python数据平滑!G$25),0)/SUM(Python数据平滑!G$46:G$52)*情景假设!I$40 -> 25262.769 | J91: =VLOOKUP($A91,Python数据平滑!$A$25:$AN$52,COLUMN(Python数据平滑!H$25),0)/SUM(Python数据平滑!H$46:H$52)*情景假设!J$40 -> 27019.458 | K91: =VLOOKUP($A91,Python数据平滑!$A$25:$AN$52,COLUMN(Python数据平滑!I$25),0)/SUM(Python数据平滑!I$46:I$52)*情景假设!K$40 -> 28814.826 | L91: =L$40*S49 -> 30603.458 | M91: =VLOOKUP($A91,Python数据平滑!$A$25:$AN$52,COLUMN(Python数据平滑!K$25),0)/SUM(Python数据平滑!K$46:K$52)*情景假设!M$40 -> 32363.617 | N91: =VLOOKUP($A91,Python数据平滑!$A$25:$AN$52,COLUMN(Python数据平滑!L$25),0)/SUM(Python数据平滑!L$46:L$52)*情景假设!N$40 -> 34099.604 | O91: =VLOOKUP($A91,Python数据平滑!$A$25:$AN$52,COLUMN(Python数据平滑!M$25),0)/SUM(Python数据平滑!M$46:M$52)*情景假设!O$40 -> 35798.522 | P91: =VLOOKUP($A91,Python数据平滑!$A$25:$AN$52,COLUMN(Python数据平滑!N$25),0)/SUM(Python数据平滑!N$46:N$52)*情景假设!P$40 -> 37475.2 | Q91: =Q$40*T49 -> 39179.276 | R91: =VLOOKUP($A91,Python数据平滑!$A$25:$AN$52,COLUMN(Python数据平滑!P$25),0)/SUM(Python数据平滑!P$46:P$52)*情景假设!R$40 -> 40907.149 | S91: =VLOOKUP($A91,Python数据平滑!$A$25:$AN$52,COLUMN(Python数据平滑!Q$25),0)/SUM(Python数据平滑!Q$46:Q$52)*情景假设!S$40 -> 42616.054 | T91: =VLOOKUP($A91,Python数据平滑!$A$25:$AN$52,COLUMN(Python数据平滑!R$25),0)/SUM(Python数据平滑!R$46:R$52)*情景假设!T$40 -> 44316.181 | U91: =VLOOKUP($A91,Python数据平滑!$A$25:$AN$52,COLUMN(Python数据平滑!S$25),0)/SUM(Python数据平滑!S$46:S$52)*情景假设!U$40 -> 46020.035 | V91: =VLOOKUP($A91,Python数据平滑!$A$25:$AN$52,COLUMN(Python数据平滑!T$25),0)/SUM(Python数据平滑!T$46:T$52)*情景假设!V$40 -> 47742.453 | W91: =VLOOKUP($A91,Python数据平滑!$A$25:$AN$52,COLUMN(Python数据平滑!U$25),0)/SUM(Python数据平滑!U$46:U$52)*情景假设!W$40 -> 49488.216 | X91: =VLOOKUP($A91,Python数据平滑!$A$25:$AN$52,COLUMN(Python数据平滑!V$25),0)/SUM(Python数据平滑!V$46:V$52)*情景假设!X$40 -> 51253.059 | Y91: =VLOOKUP($A91,Python数据平滑!$A$25:$AN$52,COLUMN(Python数据平滑!W$25),0)/SUM(Python数据平滑!W$46:W$52)*情景假设!Y$40 -> 53040.432 | ... AE91: =VLOOKUP($A91,Python数据平滑!$A$25:$AN$52,COLUMN(Python数据平滑!AC$25),0)/SUM(Python数据平滑!AC$46:AC$52)*情景假设!AE$40 -> 64542.61 | AF91: =$AF$40*U49 -> 66658.041 | AG91: =VLOOKUP($A91,Python数据平滑!$A$25:$AN$52,COLUMN(Python数据平滑!AE$25),0)/SUM(Python数据平滑!AE$46:AE$52)*情景假设!AG$40 -> 68834.874 | AH91: =VLOOKUP($A91,Python数据平滑!$A$25:$AN$52,COLUMN(Python数据平滑!AF$25),0)/SUM(Python数据平滑!AF$46:AF$52)*情景假设!AH$40 -> 71058.301 | AI91: =VLOOKUP($A91,Python数据平滑!$A$25:$AN$52,COLUMN(Python数据平滑!AG$25),0)/SUM(Python数据平滑!AG$46:AG$52)*情景假设!AI$40 -> 73327.935 | AJ91: =VLOOKUP($A91,Python数据平滑!$A$25:$AN$52,COLUMN(Python数据平滑!AH$25),0)/SUM(Python数据平滑!AH$46:AH$52)*情景假设!AJ$40 -> 75643.258 | AK91: =VLOOKUP($A91,Python数据平滑!$A$25:$AN$52,COLUMN(Python数据平滑!AI$25),0)/SUM(Python数据平滑!AI$46:AI$52)*情景假设!AK$40 -> 78003.612 | AL91: =VLOOKUP($A91,Python数据平滑!$A$25:$AN$52,COLUMN(Python数据平滑!AJ$25),0)/SUM(Python数据平滑!AJ$46:AJ$52)*情景假设!AL$40 -> 80410.948 | AM91: =VLOOKUP($A91,Python数据平滑!$A$25:$AN$52,COLUMN(Python数据平滑!AK$25),0)/SUM(Python数据平滑!AK$46:AK$52)*情景假设!AM$40 -> 82867.828 | AN91: =VLOOKUP($A91,Python数据平滑!$A$25:$AN$52,COLUMN(Python数据平滑!AL$25),0)/SUM(Python数据平滑!AL$46:AL$52)*情景假设!AN$40 -> 85374.351 | AO91: =VLOOKUP($A91,Python数据平滑!$A$25:$AN$52,COLUMN(Python数据平滑!AM$25),0)/SUM(Python数据平滑!AM$46:AM$52)*情景假设!AO$40 -> 87930.54 | AP91: =AP$40*V49 -> 90536.34
A92: 制氢-低情景 | B92: 0 | C92: 0 | D92: 1 | E92: =VLOOKUP($A92,Python数据平滑!$A$25:$AN$52,COLUMN(Python数据平滑!C$25),0)/SUM(Python数据平滑!C$46:C$52)*情景假设!E$40 -> 29.336194 | F92: =VLOOKUP($A92,Python数据平滑!$A$25:$AN$52,COLUMN(Python数据平滑!D$25),0)/SUM(Python数据平滑!D$46:D$52)*情景假设!F$40 -> 485.29547 | G92: =G$40*R50 -> 2047.619 | H92: =VLOOKUP($A92,Python数据平滑!$A$25:$AN$52,COLUMN(Python数据平滑!F$25),0)/SUM(Python数据平滑!F$46:F$52)*情景假设!H$40 -> 3088.8447 | I92: =VLOOKUP($A92,Python数据平滑!$A$25:$AN$52,COLUMN(Python数据平滑!G$25),0)/SUM(Python数据平滑!G$46:G$52)*情景假设!I$40 -> 4081.877 | J92: =VLOOKUP($A92,Python数据平滑!$A$25:$AN$52,COLUMN(Python数据平滑!H$25),0)/SUM(Python数据平滑!H$46:H$52)*情景假设!J$40 -> 4987.1343 | K92: =VLOOKUP($A92,Python数据平滑!$A$25:$AN$52,COLUMN(Python数据平滑!I$25),0)/SUM(Python数据平滑!I$46:I$52)*情景假设!K$40 -> 5943.3574 | L92: =L$40*S50 -> 7286.5375 | M92: =VLOOKUP($A92,Python数据平滑!$A$25:$AN$52,COLUMN(Python数据平滑!K$25),0)/SUM(Python数据平滑!K$46:K$52)*情景假设!M$40 -> 9393.8632 | N92: =VLOOKUP($A92,Python数据平滑!$A$25:$AN$52,COLUMN(Python数据平滑!L$25),0)/SUM(Python数据平滑!L$46:L$52)*情景假设!N$40 -> 12289.435 | O92: =VLOOKUP($A92,Python数据平滑!$A$25:$AN$52,COLUMN(Python数据平滑!M$25),0)/SUM(Python数据平滑!M$46:M$52)*情景假设!O$40 -> 15784.229 | P92: =VLOOKUP($A92,Python数据平滑!$A$25:$AN$52,COLUMN(Python数据平滑!N$25),0)/SUM(Python数据平滑!N$46:N$52)*情景假设!P$40 -> 19269.902 | Q92: =Q$40*T50 -> 21666.667 | R92: =VLOOKUP($A92,Python数据平滑!$A$25:$AN$52,COLUMN(Python数据平滑!P$25),0)/SUM(Python数据平滑!P$46:P$52)*情景假设!R$40 -> 23035.462 | S92: =VLOOKUP($A92,Python数据平滑!$A$25:$AN$52,COLUMN(Python数据平滑!Q$25),0)/SUM(Python数据平滑!Q$46:Q$52)*情景假设!S$40 -> 24294.226 | T92: =VLOOKUP($A92,Python数据平滑!$A$25:$AN$52,COLUMN(Python数据平滑!R$25),0)/SUM(Python数据平滑!R$46:R$52)*情景假设!T$40 -> 25443.069 | U92: =VLOOKUP($A92,Python数据平滑!$A$25:$AN$52,COLUMN(Python数据平滑!S$25),0)/SUM(Python数据平滑!S$46:S$52)*情景假设!U$40 -> 26488.161 | V92: =VLOOKUP($A92,Python数据平滑!$A$25:$AN$52,COLUMN(Python数据平滑!T$25),0)/SUM(Python数据平滑!T$46:T$52)*情景假设!V$40 -> 27441.182 | W92: =VLOOKUP($A92,Python数据平滑!$A$25:$AN$52,COLUMN(Python数据平滑!U$25),0)/SUM(Python数据平滑!U$46:U$52)*情景假设!W$40 -> 28311.557 | X92: =VLOOKUP($A92,Python数据平滑!$A$25:$AN$52,COLUMN(Python数据平滑!V$25),0)/SUM(Python数据平滑!V$46:V$52)*情景假设!X$40 -> 29106.597 | Y92: =VLOOKUP($A92,Python数据平滑!$A$25:$AN$52,COLUMN(Python数据平滑!W$25),0)/SUM(Python数据平滑!W$46:W$52)*情景假设!Y$40 -> 29840.722 | ... AE92: =VLOOKUP($A92,Python数据平滑!$A$25:$AN$52,COLUMN(Python数据平滑!AC$25),0)/SUM(Python数据平滑!AC$46:AC$52)*情景假设!AE$40 -> 34086.363 | AF92: =$AF$40*U50 -> 35000 | AG92: =VLOOKUP($A92,Python数据平滑!$A$25:$AN$52,COLUMN(Python数据平滑!AE$25),0)/SUM(Python数据平滑!AE$46:AE$52)*情景假设!AG$40 -> 35983.3 | AH92: =VLOOKUP($A92,Python数据平滑!$A$25:$AN$52,COLUMN(Python数据平滑!AF$25),0)/SUM(Python数据平滑!AF$46:AF$52)*情景假设!AH$40 -> 36978.049 | AI92: =VLOOKUP($A92,Python数据平滑!$A$25:$AN$52,COLUMN(Python数据平滑!AG$25),0)/SUM(Python数据平滑!AG$46:AG$52)*情景假设!AI$40 -> 37983.359 | AJ92: =VLOOKUP($A92,Python数据平滑!$A$25:$AN$52,COLUMN(Python数据平滑!AH$25),0)/SUM(Python数据平滑!AH$46:AH$52)*情景假设!AJ$40 -> 38998.259 | AK92: =VLOOKUP($A92,Python数据平滑!$A$25:$AN$52,COLUMN(Python数据平滑!AI$25),0)/SUM(Python数据平滑!AI$46:AI$52)*情景假设!AK$40 -> 40021.691 | AL92: =VLOOKUP($A92,Python数据平滑!$A$25:$AN$52,COLUMN(Python数据平滑!AJ$25),0)/SUM(Python数据平滑!AJ$46:AJ$52)*情景假设!AL$40 -> 41053.917 | AM92: =VLOOKUP($A92,Python数据平滑!$A$25:$AN$52,COLUMN(Python数据平滑!AK$25),0)/SUM(Python数据平滑!AK$46:AK$52)*情景假设!AM$40 -> 42095.468 | AN92: =VLOOKUP($A92,Python数据平滑!$A$25:$AN$52,COLUMN(Python数据平滑!AL$25),0)/SUM(Python数据平滑!AL$46:AL$52)*情景假设!AN$40 -> 43145.584 | AO92: =VLOOKUP($A92,Python数据平滑!$A$25:$AN$52,COLUMN(Python数据平滑!AM$25),0)/SUM(Python数据平滑!AM$46:AM$52)*情景假设!AO$40 -> 44203.444 | AP92: =AP$40*V50 -> 45268.17
A93: 传统高耗能产业-低情景 | B93: =SUM('高情景（2001-2060, 2020RMB）'!U25:U26,'高情景（2001-2060, 2020RMB）'!U30,'高情景（2001-2060, 2020RMB）'!U34,'高情景（2001-2060, 2020RMB）'!U36:U37,'高情景（2001-2060, 2020RMB）'!U38:U40) -> 90023.293 | C93: =SUM('高情景（2001-2060, 2020RMB）'!V25:V26,'高情景（2001-2060, 2020RMB）'!V30,'高情景（2001-2060, 2020RMB）'!V34,'高情景（2001-2060, 2020RMB）'!V36:V37,'高情景（2001-2060, 2020RMB）'!V38:V40) -> 98562.089 | D93: =SUM('高情景（2001-2060, 2020RMB）'!W25:W26,'高情景（2001-2060, 2020RMB）'!W30,'高情景（2001-2060, 2020RMB）'!W34,'高情景（2001-2060, 2020RMB）'!W36:W37,'高情景（2001-2060, 2020RMB）'!W38:W40) -> 101803.01 | E93: =VLOOKUP($A93,Python数据平滑!$A$25:$AN$52,COLUMN(Python数据平滑!C$25),0)/SUM(Python数据平滑!C$46:C$52)*情景假设!E$40 -> 103746.24 | F93: =VLOOKUP($A93,Python数据平滑!$A$25:$AN$52,COLUMN(Python数据平滑!D$25),0)/SUM(Python数据平滑!D$46:D$52)*情景假设!F$40 -> 105514.31 | G93: =G$40*R51 -> 106919.57 | H93: =VLOOKUP($A93,Python数据平滑!$A$25:$AN$52,COLUMN(Python数据平滑!F$25),0)/SUM(Python数据平滑!F$46:F$52)*情景假设!H$40 -> 108400.41 | I93: =VLOOKUP($A93,Python数据平滑!$A$25:$AN$52,COLUMN(Python数据平滑!G$25),0)/SUM(Python数据平滑!G$46:G$52)*情景假设!I$40 -> 109840.53 | J93: =VLOOKUP($A93,Python数据平滑!$A$25:$AN$52,COLUMN(Python数据平滑!H$25),0)/SUM(Python数据平滑!H$46:H$52)*情景假设!J$40 -> 111234.59 | K93: =VLOOKUP($A93,Python数据平滑!$A$25:$AN$52,COLUMN(Python数据平滑!I$25),0)/SUM(Python数据平滑!I$46:I$52)*情景假设!K$40 -> 112538.78 | L93: =L$40*S51 -> 113669.99 | M93: =VLOOKUP($A93,Python数据平滑!$A$25:$AN$52,COLUMN(Python数据平滑!K$25),0)/SUM(Python数据平滑!K$46:K$52)*情景假设!M$40 -> 114565.22 | N93: =VLOOKUP($A93,Python数据平滑!$A$25:$AN$52,COLUMN(Python数据平滑!L$25),0)/SUM(Python数据平滑!L$46:L$52)*情景假设!N$40 -> 115248.78 | O93: =VLOOKUP($A93,Python数据平滑!$A$25:$AN$52,COLUMN(Python数据平滑!M$25),0)/SUM(Python数据平滑!M$46:M$52)*情景假设!O$40 -> 115771.18 | P93: =VLOOKUP($A93,Python数据平滑!$A$25:$AN$52,COLUMN(Python数据平滑!N$25),0)/SUM(Python数据平滑!N$46:N$52)*情景假设!P$40 -> 116270.89 | Q93: =Q$40*T51 -> 116978.12 | R93: =VLOOKUP($A93,Python数据平滑!$A$25:$AN$52,COLUMN(Python数据平滑!P$25),0)/SUM(Python数据平滑!P$46:P$52)*情景假设!R$40 -> 117819.96 | S93: =VLOOKUP($A93,Python数据平滑!$A$25:$AN$52,COLUMN(Python数据平滑!Q$25),0)/SUM(Python数据平滑!Q$46:Q$52)*情景假设!S$40 -> 118570.36 | T93: =VLOOKUP($A93,Python数据平滑!$A$25:$AN$52,COLUMN(Python数据平滑!R$25),0)/SUM(Python数据平滑!R$46:R$52)*情景假设!T$40 -> 119263.62 | U93: =VLOOKUP($A93,Python数据平滑!$A$25:$AN$52,COLUMN(Python数据平滑!S$25),0)/SUM(Python数据平滑!S$46:S$52)*情景假设!U$40 -> 119934.06 | V93: =VLOOKUP($A93,Python数据平滑!$A$25:$AN$52,COLUMN(Python数据平滑!T$25),0)/SUM(Python数据平滑!T$46:T$52)*情景假设!V$40 -> 120616.06 | W93: =VLOOKUP($A93,Python数据平滑!$A$25:$AN$52,COLUMN(Python数据平滑!U$25),0)/SUM(Python数据平滑!U$46:U$52)*情景假设!W$40 -> 121313.63 | X93: =VLOOKUP($A93,Python数据平滑!$A$25:$AN$52,COLUMN(Python数据平滑!V$25),0)/SUM(Python数据平滑!V$46:V$52)*情景假设!X$40 -> 122007.14 | Y93: =VLOOKUP($A93,Python数据平滑!$A$25:$AN$52,COLUMN(Python数据平滑!W$25),0)/SUM(Python数据平滑!W$46:W$52)*情景假设!Y$40 -> 122695.35 | ... AE93: =VLOOKUP($A93,Python数据平滑!$A$25:$AN$52,COLUMN(Python数据平滑!AC$25),0)/SUM(Python数据平滑!AC$46:AC$52)*情景假设!AE$40 -> 126686.06 | AF93: =$AF$40*U51 -> 127324.35 | AG93: =VLOOKUP($A93,Python数据平滑!$A$25:$AN$52,COLUMN(Python数据平滑!AE$25),0)/SUM(Python数据平滑!AE$46:AE$52)*情景假设!AG$40 -> 127960.78 | AH93: =VLOOKUP($A93,Python数据平滑!$A$25:$AN$52,COLUMN(Python数据平滑!AF$25),0)/SUM(Python数据平滑!AF$46:AF$52)*情景假设!AH$40 -> 128605.41 | AI93: =VLOOKUP($A93,Python数据平滑!$A$25:$AN$52,COLUMN(Python数据平滑!AG$25),0)/SUM(Python数据平滑!AG$46:AG$52)*情景假设!AI$40 -> 129256.77 | AJ93: =VLOOKUP($A93,Python数据平滑!$A$25:$AN$52,COLUMN(Python数据平滑!AH$25),0)/SUM(Python数据平滑!AH$46:AH$52)*情景假设!AJ$40 -> 129913.3 | AK93: =VLOOKUP($A93,Python数据平滑!$A$25:$AN$52,COLUMN(Python数据平滑!AI$25),0)/SUM(Python数据平滑!AI$46:AI$52)*情景假设!AK$40 -> 130573.35 | AL93: =VLOOKUP($A93,Python数据平滑!$A$25:$AN$52,COLUMN(Python数据平滑!AJ$25),0)/SUM(Python数据平滑!AJ$46:AJ$52)*情景假设!AL$40 -> 131239.66 | AM93: =VLOOKUP($A93,Python数据平滑!$A$25:$AN$52,COLUMN(Python数据平滑!AK$25),0)/SUM(Python数据平滑!AK$46:AK$52)*情景假设!AM$40 -> 131915.65 | AN93: =VLOOKUP($A93,Python数据平滑!$A$25:$AN$52,COLUMN(Python数据平滑!AL$25),0)/SUM(Python数据平滑!AL$46:AL$52)*情景假设!AN$40 -> 132600.58 | AO93: =VLOOKUP($A93,Python数据平滑!$A$25:$AN$52,COLUMN(Python数据平滑!AM$25),0)/SUM(Python数据平滑!AM$46:AM$52)*情景假设!AO$40 -> 133293.59 | AP93: =AP$40*V51 -> 133993.78
A94: 装备制造业-低情景 | B94: =SUM('高情景（2001-2060, 2020RMB）'!U41:U46) -> 81720.66 | C94: =SUM('高情景（2001-2060, 2020RMB）'!V41:V46) -> 95333.93 | D94: =SUM('高情景（2001-2060, 2020RMB）'!W41:W46) -> 101531.7 | E94: =VLOOKUP($A94,Python数据平滑!$A$25:$AN$52,COLUMN(Python数据平滑!C$25),0)/SUM(Python数据平滑!C$46:C$52)*情景假设!E$40 -> 105836.49 | F94: =VLOOKUP($A94,Python数据平滑!$A$25:$AN$52,COLUMN(Python数据平滑!D$25),0)/SUM(Python数据平滑!D$46:D$52)*情景假设!F$40 -> 110173.22 | G94: =G$40*R52 -> 114379.07 | H94: =VLOOKUP($A94,Python数据平滑!$A$25:$AN$52,COLUMN(Python数据平滑!F$25),0)/SUM(Python数据平滑!F$46:F$52)*情景假设!H$40 -> 118878.5 | I94: =VLOOKUP($A94,Python数据平滑!$A$25:$AN$52,COLUMN(Python数据平滑!G$25),0)/SUM(Python数据平滑!G$46:G$52)*情景假设!I$40 -> 123513.32 | J94: =VLOOKUP($A94,Python数据平滑!$A$25:$AN$52,COLUMN(Python数据平滑!H$25),0)/SUM(Python数据平滑!H$46:H$52)*情景假设!J$40 -> 128325.3 | K94: =VLOOKUP($A94,Python数据平滑!$A$25:$AN$52,COLUMN(Python数据平滑!I$25),0)/SUM(Python数据平滑!I$46:I$52)*情景假设!K$40 -> 133316.84 | L94: =L$40*S52 -> 138444.21 | M94: =VLOOKUP($A94,Python数据平滑!$A$25:$AN$52,COLUMN(Python数据平滑!K$25),0)/SUM(Python数据平滑!K$46:K$52)*情景假设!M$40 -> 143709.69 | N94: =VLOOKUP($A94,Python数据平滑!$A$25:$AN$52,COLUMN(Python数据平滑!L$25),0)/SUM(Python数据平滑!L$46:L$52)*情景假设!N$40 -> 149054.62 | O94: =VLOOKUP($A94,Python数据平滑!$A$25:$AN$52,COLUMN(Python数据平滑!M$25),0)/SUM(Python数据平滑!M$46:M$52)*情景假设!O$40 -> 154326.49 | P94: =VLOOKUP($A94,Python数据平滑!$A$25:$AN$52,COLUMN(Python数据平滑!N$25),0)/SUM(Python数据平滑!N$46:N$52)*情景假设!P$40 -> 159470.54 | Q94: =Q$40*T52 -> 164552.96 | R94: =VLOOKUP($A94,Python数据平滑!$A$25:$AN$52,COLUMN(Python数据平滑!P$25),0)/SUM(Python数据平滑!P$46:P$52)*情景假设!R$40 -> 169526.91 | S94: =VLOOKUP($A94,Python数据平滑!$A$25:$AN$52,COLUMN(Python数据平滑!Q$25),0)/SUM(Python数据平滑!Q$46:Q$52)*情景假设!S$40 -> 174298.46 | T94: =VLOOKUP($A94,Python数据平滑!$A$25:$AN$52,COLUMN(Python数据平滑!R$25),0)/SUM(Python数据平滑!R$46:R$52)*情景假设!T$40 -> 178918.55 | U94: =VLOOKUP($A94,Python数据平滑!$A$25:$AN$52,COLUMN(Python数据平滑!S$25),0)/SUM(Python数据平滑!S$46:S$52)*情景假设!U$40 -> 183444.95 | V94: =VLOOKUP($A94,Python数据平滑!$A$25:$AN$52,COLUMN(Python数据平滑!T$25),0)/SUM(Python数据平滑!T$46:T$52)*情景假设!V$40 -> 187941.86 | W94: =VLOOKUP($A94,Python数据平滑!$A$25:$AN$52,COLUMN(Python数据平滑!U$25),0)/SUM(Python数据平滑!U$46:U$52)*情景假设!W$40 -> 192431.38 | X94: =VLOOKUP($A94,Python数据平滑!$A$25:$AN$52,COLUMN(Python数据平滑!V$25),0)/SUM(Python数据平滑!V$46:V$52)*情景假设!X$40 -> 196900.01 | Y94: =VLOOKUP($A94,Python数据平滑!$A$25:$AN$52,COLUMN(Python数据平滑!W$25),0)/SUM(Python数据平滑!W$46:W$52)*情景假设!Y$40 -> 201364.31 | ... AE94: =VLOOKUP($A94,Python数据平滑!$A$25:$AN$52,COLUMN(Python数据平滑!AC$25),0)/SUM(Python数据平滑!AC$46:AC$52)*情景假设!AE$40 -> 229316.41 | AF94: =$AF$40*U52 -> 234426.59 | AG94: =VLOOKUP($A94,Python数据平滑!$A$25:$AN$52,COLUMN(Python数据平滑!AE$25),0)/SUM(Python数据平滑!AE$46:AE$52)*情景假设!AG$40 -> 239684.2 | AH94: =VLOOKUP($A94,Python数据平滑!$A$25:$AN$52,COLUMN(Python数据平滑!AF$25),0)/SUM(Python数据平滑!AF$46:AF$52)*情景假设!AH$40 -> 245039.62 | AI94: =VLOOKUP($A94,Python数据平滑!$A$25:$AN$52,COLUMN(Python数据平滑!AG$25),0)/SUM(Python数据平滑!AG$46:AG$52)*情景假设!AI$40 -> 250492.06 | AJ94: =VLOOKUP($A94,Python数据平滑!$A$25:$AN$52,COLUMN(Python数据平滑!AH$25),0)/SUM(Python数据平滑!AH$46:AH$52)*情景假设!AJ$40 -> 256040.42 | AK94: =VLOOKUP($A94,Python数据平滑!$A$25:$AN$52,COLUMN(Python数据平滑!AI$25),0)/SUM(Python数据平滑!AI$46:AI$52)*情景假设!AK$40 -> 261683.27 | AL94: =VLOOKUP($A94,Python数据平滑!$A$25:$AN$52,COLUMN(Python数据平滑!AJ$25),0)/SUM(Python数据平滑!AJ$46:AJ$52)*情景假设!AL$40 -> 267428 | AM94: =VLOOKUP($A94,Python数据平滑!$A$25:$AN$52,COLUMN(Python数据平滑!AK$25),0)/SUM(Python数据平滑!AK$46:AK$52)*情景假设!AM$40 -> 273283.85 | AN94: =VLOOKUP($A94,Python数据平滑!$A$25:$AN$52,COLUMN(Python数据平滑!AL$25),0)/SUM(Python数据平滑!AL$46:AL$52)*情景假设!AN$40 -> 279251.8 | AO94: =VLOOKUP($A94,Python数据平滑!$A$25:$AN$52,COLUMN(Python数据平滑!AM$25),0)/SUM(Python数据平滑!AM$46:AM$52)*情景假设!AO$40 -> 285332.65 | AP94: =AP$40*V52 -> 291527.01
A95: 高技术产业-低情景 | B95: =SUM('高情景（2001-2060, 2020RMB）'!U47:U48,'高情景（2001-2060, 2020RMB）'!U35) -> 42058.738 | C95: =SUM('高情景（2001-2060, 2020RMB）'!V47:V48,'高情景（2001-2060, 2020RMB）'!V35) -> 51422.622 | D95: =SUM('高情景（2001-2060, 2020RMB）'!W47:W48,'高情景（2001-2060, 2020RMB）'!W35) -> 54801.587 | E95: =VLOOKUP($A95,Python数据平滑!$A$25:$AN$52,COLUMN(Python数据平滑!C$25),0)/SUM(Python数据平滑!C$46:C$52)*情景假设!E$40 -> 57885.488 | F95: =VLOOKUP($A95,Python数据平滑!$A$25:$AN$52,COLUMN(Python数据平滑!D$25),0)/SUM(Python数据平滑!D$46:D$52)*情景假设!F$40 -> 61059.554 | G95: =G$40*R53 -> 64234.623 | H95: =VLOOKUP($A95,Python数据平滑!$A$25:$AN$52,COLUMN(Python数据平滑!F$25),0)/SUM(Python数据平滑!F$46:F$52)*情景假设!H$40 -> 67709.327 | I95: =VLOOKUP($A95,Python数据平滑!$A$25:$AN$52,COLUMN(Python数据平滑!G$25),0)/SUM(Python数据平滑!G$46:G$52)*情景假设!I$40 -> 71409.775 | J95: =VLOOKUP($A95,Python数据平滑!$A$25:$AN$52,COLUMN(Python数据平滑!H$25),0)/SUM(Python数据平滑!H$46:H$52)*情景假设!J$40 -> 75277.714 | K95: =VLOOKUP($A95,Python数据平滑!$A$25:$AN$52,COLUMN(Python数据平滑!I$25),0)/SUM(Python数据平滑!I$46:I$52)*情景假设!K$40 -> 79213 | L95: =L$40*S53 -> 83066.528 | M95: =VLOOKUP($A95,Python数据平滑!$A$25:$AN$52,COLUMN(Python数据平滑!K$25),0)/SUM(Python数据平滑!K$46:K$52)*情景假设!M$40 -> 86761.017 | N95: =VLOOKUP($A95,Python数据平滑!$A$25:$AN$52,COLUMN(Python数据平滑!L$25),0)/SUM(Python数据平滑!L$46:L$52)*情景假设!N$40 -> 90331.282 | O95: =VLOOKUP($A95,Python数据平滑!$A$25:$AN$52,COLUMN(Python数据平滑!M$25),0)/SUM(Python数据平滑!M$46:M$52)*情景假设!O$40 -> 93782.344 | P95: =VLOOKUP($A95,Python数据平滑!$A$25:$AN$52,COLUMN(Python数据平滑!N$25),0)/SUM(Python数据平滑!N$46:N$52)*情景假设!P$40 -> 97196.272 | Q95: =Q$40*T53 -> 100746.71 | R95: =VLOOKUP($A95,Python数据平滑!$A$25:$AN$52,COLUMN(Python数据平滑!P$25),0)/SUM(Python数据平滑!P$46:P$52)*情景假设!R$40 -> 104400.29 | S95: =VLOOKUP($A95,Python数据平滑!$A$25:$AN$52,COLUMN(Python数据平滑!Q$25),0)/SUM(Python数据平滑!Q$46:Q$52)*情景假设!S$40 -> 107995.16 | T95: =VLOOKUP($A95,Python数据平滑!$A$25:$AN$52,COLUMN(Python数据平滑!R$25),0)/SUM(Python数据平滑!R$46:R$52)*情景假设!T$40 -> 111560.64 | U95: =VLOOKUP($A95,Python数据平滑!$A$25:$AN$52,COLUMN(Python数据平滑!S$25),0)/SUM(Python数据平滑!S$46:S$52)*情景假设!U$40 -> 115130.64 | V95: =VLOOKUP($A95,Python数据平滑!$A$25:$AN$52,COLUMN(Python数据平滑!T$25),0)/SUM(Python数据平滑!T$46:T$52)*情景假设!V$40 -> 118743.6 | W95: =VLOOKUP($A95,Python数据平滑!$A$25:$AN$52,COLUMN(Python数据平滑!U$25),0)/SUM(Python数据平滑!U$46:U$52)*情景假设!W$40 -> 122411.88 | X95: =VLOOKUP($A95,Python数据平滑!$A$25:$AN$52,COLUMN(Python数据平滑!V$25),0)/SUM(Python数据平滑!V$46:V$52)*情景假设!X$40 -> 126125 | Y95: =VLOOKUP($A95,Python数据平滑!$A$25:$AN$52,COLUMN(Python数据平滑!W$25),0)/SUM(Python数据平滑!W$46:W$52)*情景假设!Y$40 -> 129891.27 | ... AE95: =VLOOKUP($A95,Python数据平滑!$A$25:$AN$52,COLUMN(Python数据平滑!AC$25),0)/SUM(Python数据平滑!AC$46:AC$52)*情景假设!AE$40 -> 154275.81 | AF95: =$AF$40*U53 -> 158780.95 | AG95: =VLOOKUP($A95,Python数据平滑!$A$25:$AN$52,COLUMN(Python数据平滑!AE$25),0)/SUM(Python数据平滑!AE$46:AE$52)*情景假设!AG$40 -> 163427.61 | AH95: =VLOOKUP($A95,Python数据平滑!$A$25:$AN$52,COLUMN(Python数据平滑!AF$25),0)/SUM(Python数据平滑!AF$46:AF$52)*情景假设!AH$40 -> 168194.07 | AI95: =VLOOKUP($A95,Python数据平滑!$A$25:$AN$52,COLUMN(Python数据平滑!AG$25),0)/SUM(Python数据平滑!AG$46:AG$52)*情景假设!AI$40 -> 173081.61 | AJ95: =VLOOKUP($A95,Python数据平滑!$A$25:$AN$52,COLUMN(Python数据平滑!AH$25),0)/SUM(Python数据平滑!AH$46:AH$52)*情景假设!AJ$40 -> 178091.26 | AK95: =VLOOKUP($A95,Python数据平滑!$A$25:$AN$52,COLUMN(Python数据平滑!AI$25),0)/SUM(Python数据平滑!AI$46:AI$52)*情景假设!AK$40 -> 183223.85 | AL95: =VLOOKUP($A95,Python数据平滑!$A$25:$AN$52,COLUMN(Python数据平滑!AJ$25),0)/SUM(Python数据平滑!AJ$46:AJ$52)*情景假设!AL$40 -> 188486.43 | AM95: =VLOOKUP($A95,Python数据平滑!$A$25:$AN$52,COLUMN(Python数据平滑!AK$25),0)/SUM(Python数据平滑!AK$46:AK$52)*情景假设!AM$40 -> 193887.51 | AN95: =VLOOKUP($A95,Python数据平滑!$A$25:$AN$52,COLUMN(Python数据平滑!AL$25),0)/SUM(Python数据平滑!AL$46:AL$52)*情景假设!AN$40 -> 199429.92 | AO95: =VLOOKUP($A95,Python数据平滑!$A$25:$AN$52,COLUMN(Python数据平滑!AM$25),0)/SUM(Python数据平滑!AM$46:AM$52)*情景假设!AO$40 -> 205116.43 | AP95: =AP$40*V53 -> 210949.67
A96: 其他产业-低情景 | B96: =SUM('高情景（2001-2060, 2020RMB）'!U16:U24,'高情景（2001-2060, 2020RMB）'!U27:U29,'高情景（2001-2060, 2020RMB）'!U31:U32,'高情景（2001-2060, 2020RMB）'!U49:U51) -> 50441.557 | C96: =SUM('高情景（2001-2060, 2020RMB）'!V16:V24,'高情景（2001-2060, 2020RMB）'!V27:V29,'高情景（2001-2060, 2020RMB）'!V31:V32,'高情景（2001-2060, 2020RMB）'!V49:V51) -> 56632.87 | D96: =SUM('高情景（2001-2060, 2020RMB）'!W16:W24,'高情景（2001-2060, 2020RMB）'!W27:W29,'高情景（2001-2060, 2020RMB）'!W31:W32,'高情景（2001-2060, 2020RMB）'!W49:W51) -> 59677.346 | E96: =VLOOKUP($A96,Python数据平滑!$A$25:$AN$52,COLUMN(Python数据平滑!C$25),0)/SUM(Python数据平滑!C$46:C$52)*情景假设!E$40 -> 60688.709 | F96: =VLOOKUP($A96,Python数据平滑!$A$25:$AN$52,COLUMN(Python数据平滑!D$25),0)/SUM(Python数据平滑!D$46:D$52)*情景假设!F$40 -> 61688.022 | G96: =G$40*R54 -> 62601.421 | H96: =VLOOKUP($A96,Python数据平滑!$A$25:$AN$52,COLUMN(Python数据平滑!F$25),0)/SUM(Python数据平滑!F$46:F$52)*情景假设!H$40 -> 63726.92 | I96: =VLOOKUP($A96,Python数据平滑!$A$25:$AN$52,COLUMN(Python数据平滑!G$25),0)/SUM(Python数据平滑!G$46:G$52)*情景假设!I$40 -> 64968.373 | J96: =VLOOKUP($A96,Python数据平滑!$A$25:$AN$52,COLUMN(Python数据平滑!H$25),0)/SUM(Python数据平滑!H$46:H$52)*情景假设!J$40 -> 66250.893 | K96: =VLOOKUP($A96,Python数据平滑!$A$25:$AN$52,COLUMN(Python数据平滑!I$25),0)/SUM(Python数据平滑!I$46:I$52)*情景假设!K$40 -> 67470.582 | L96: =L$40*S54 -> 68493.453 | M96: =VLOOKUP($A96,Python数据平滑!$A$25:$AN$52,COLUMN(Python数据平滑!K$25),0)/SUM(Python数据平滑!K$46:K$52)*情景假设!M$40 -> 69284.723 | N96: =VLOOKUP($A96,Python数据平滑!$A$25:$AN$52,COLUMN(Python数据平滑!L$25),0)/SUM(Python数据平滑!L$46:L$52)*情景假设!N$40 -> 69922.51 | O96: =VLOOKUP($A96,Python数据平滑!$A$25:$AN$52,COLUMN(Python数据平滑!M$25),0)/SUM(Python数据平滑!M$46:M$52)*情景假设!O$40 -> 70440.234 | P96: =VLOOKUP($A96,Python数据平滑!$A$25:$AN$52,COLUMN(Python数据平滑!N$25),0)/SUM(Python数据平滑!N$46:N$52)*情景假设!P$40 -> 70925.734 | Q96: =Q$40*T54 -> 71524.04 | R96: =VLOOKUP($A96,Python数据平滑!$A$25:$AN$52,COLUMN(Python数据平滑!P$25),0)/SUM(Python数据平滑!P$46:P$52)*情景假设!R$40 -> 72193.242 | S96: =VLOOKUP($A96,Python数据平滑!$A$25:$AN$52,COLUMN(Python数据平滑!Q$25),0)/SUM(Python数据平滑!Q$46:Q$52)*情景假设!S$40 -> 72794.842 | T96: =VLOOKUP($A96,Python数据平滑!$A$25:$AN$52,COLUMN(Python数据平滑!R$25),0)/SUM(Python数据平滑!R$46:R$52)*情景假设!T$40 -> 73350.903 | U96: =VLOOKUP($A96,Python数据平滑!$A$25:$AN$52,COLUMN(Python数据平滑!S$25),0)/SUM(Python数据平滑!S$46:S$52)*情景假设!U$40 -> 73883.762 | V96: =VLOOKUP($A96,Python数据平滑!$A$25:$AN$52,COLUMN(Python数据平滑!T$25),0)/SUM(Python数据平滑!T$46:T$52)*情景假设!V$40 -> 74415.99 | W96: =VLOOKUP($A96,Python数据平滑!$A$25:$AN$52,COLUMN(Python数据平滑!U$25),0)/SUM(Python数据平滑!U$46:U$52)*情景假设!W$40 -> 74951.574 | X96: =VLOOKUP($A96,Python数据平滑!$A$25:$AN$52,COLUMN(Python数据平滑!V$25),0)/SUM(Python数据平滑!V$46:V$52)*情景假设!X$40 -> 75479.942 | Y96: =VLOOKUP($A96,Python数据平滑!$A$25:$AN$52,COLUMN(Python数据平滑!W$25),0)/SUM(Python数据平滑!W$46:W$52)*情景假设!Y$40 -> 76001.891 | ... AE96: =VLOOKUP($A96,Python数据平滑!$A$25:$AN$52,COLUMN(Python数据平滑!AC$25),0)/SUM(Python数据平滑!AC$46:AC$52)*情景假设!AE$40 -> 79075.234 | AF96: =$AF$40*U54 -> 79591.913 | AG96: =VLOOKUP($A96,Python数据平滑!$A$25:$AN$52,COLUMN(Python数据平滑!AE$25),0)/SUM(Python数据平滑!AE$46:AE$52)*情景假设!AG$40 -> 80113.725 | AH96: =VLOOKUP($A96,Python数据平滑!$A$25:$AN$52,COLUMN(Python数据平滑!AF$25),0)/SUM(Python数据平滑!AF$46:AF$52)*情景假设!AH$40 -> 80642.867 | AI96: =VLOOKUP($A96,Python数据平滑!$A$25:$AN$52,COLUMN(Python数据平滑!AG$25),0)/SUM(Python数据平滑!AG$46:AG$52)*情景假设!AI$40 -> 81178.457 | AJ96: =VLOOKUP($A96,Python数据平滑!$A$25:$AN$52,COLUMN(Python数据平滑!AH$25),0)/SUM(Python数据平滑!AH$46:AH$52)*情景假设!AJ$40 -> 81719.55 | AK96: =VLOOKUP($A96,Python数据平滑!$A$25:$AN$52,COLUMN(Python数据平滑!AI$25),0)/SUM(Python数据平滑!AI$46:AI$52)*情景假设!AK$40 -> 82265.134 | AL96: =VLOOKUP($A96,Python数据平滑!$A$25:$AN$52,COLUMN(Python数据平滑!AJ$25),0)/SUM(Python数据平滑!AJ$46:AJ$52)*情景假设!AL$40 -> 82816.964 | AM96: =VLOOKUP($A96,Python数据平滑!$A$25:$AN$52,COLUMN(Python数据平滑!AK$25),0)/SUM(Python数据平滑!AK$46:AK$52)*情景假设!AM$40 -> 83377.243 | AN96: =VLOOKUP($A96,Python数据平滑!$A$25:$AN$52,COLUMN(Python数据平滑!AL$25),0)/SUM(Python数据平滑!AL$46:AL$52)*情景假设!AN$40 -> 83945.536 | AO96: =VLOOKUP($A96,Python数据平滑!$A$25:$AN$52,COLUMN(Python数据平滑!AM$25),0)/SUM(Python数据平滑!AM$46:AM$52)*情景假设!AO$40 -> 84521.354 | AP96: =AP$40*V54 -> 85104.16
A98: 交通运输业-低情景 | B98: ='高情景（2001-2060, 2020RMB）'!U57 -> 40582.9 | C98: ='高情景（2001-2060, 2020RMB）'!V57 -> 44991.984 | D98: ='高情景（2001-2060, 2020RMB）'!W57 -> 46450.003 | E98: =VLOOKUP($A98,Python数据平滑!$A$25:$AN$55,COLUMN(Python数据平滑!C$25),0)/SUM(Python数据平滑!C$53:C$55)*情景假设!E$42 -> 48927.229 | F98: =VLOOKUP($A98,Python数据平滑!$A$25:$AN$55,COLUMN(Python数据平滑!D$25),0)/SUM(Python数据平滑!D$53:D$55)*情景假设!F$42 -> 51515.328 | G98: =G$42*R57 -> 54218.444 | H98: =VLOOKUP($A98,Python数据平滑!$A$25:$AN$55,COLUMN(Python数据平滑!F$25),0)/SUM(Python数据平滑!F$53:F$55)*情景假设!H$42 -> 57072.718 | I98: =VLOOKUP($A98,Python数据平滑!$A$25:$AN$55,COLUMN(Python数据平滑!G$25),0)/SUM(Python数据平滑!G$53:G$55)*情景假设!I$42 -> 60086.113 | J98: =VLOOKUP($A98,Python数据平滑!$A$25:$AN$55,COLUMN(Python数据平滑!H$25),0)/SUM(Python数据平滑!H$53:H$55)*情景假设!J$42 -> 63215.806 | K98: =VLOOKUP($A98,Python数据平滑!$A$25:$AN$55,COLUMN(Python数据平滑!I$25),0)/SUM(Python数据平滑!I$53:I$55)*情景假设!K$42 -> 66412.168 | L98: =L$42*S57 -> 69618.392 | M98: =VLOOKUP($A98,Python数据平滑!$A$25:$AN$55,COLUMN(Python数据平滑!K$25),0)/SUM(Python数据平滑!K$53:K$55)*情景假设!M$42 -> 72850.473 | N98: =VLOOKUP($A98,Python数据平滑!$A$25:$AN$55,COLUMN(Python数据平滑!L$25),0)/SUM(Python数据平滑!L$53:L$55)*情景假设!N$42 -> 76146.408 | O98: =VLOOKUP($A98,Python数据平滑!$A$25:$AN$55,COLUMN(Python数据平滑!M$25),0)/SUM(Python数据平滑!M$53:M$55)*情景假设!O$42 -> 79470.834 | P98: =VLOOKUP($A98,Python数据平滑!$A$25:$AN$55,COLUMN(Python数据平滑!N$25),0)/SUM(Python数据平滑!N$53:N$55)*情景假设!P$42 -> 82780.451 | Q98: =Q$42*T57 -> 86023.792 | R98: =VLOOKUP($A98,Python数据平滑!$A$25:$AN$55,COLUMN(Python数据平滑!P$25),0)/SUM(Python数据平滑!P$53:P$55)*情景假设!R$42 -> 89180.677 | S98: =VLOOKUP($A98,Python数据平滑!$A$25:$AN$55,COLUMN(Python数据平滑!Q$25),0)/SUM(Python数据平滑!Q$53:Q$55)*情景假设!S$42 -> 92281.193 | T98: =VLOOKUP($A98,Python数据平滑!$A$25:$AN$55,COLUMN(Python数据平滑!R$25),0)/SUM(Python数据平滑!R$53:R$55)*情景假设!T$42 -> 95346.347 | U98: =VLOOKUP($A98,Python数据平滑!$A$25:$AN$55,COLUMN(Python数据平滑!S$25),0)/SUM(Python数据平滑!S$53:S$55)*情景假设!U$42 -> 98401.796 | V98: =VLOOKUP($A98,Python数据平滑!$A$25:$AN$55,COLUMN(Python数据平滑!T$25),0)/SUM(Python数据平滑!T$53:T$55)*情景假设!V$42 -> 101477.88 | W98: =VLOOKUP($A98,Python数据平滑!$A$25:$AN$55,COLUMN(Python数据平滑!U$25),0)/SUM(Python数据平滑!U$53:U$55)*情景假设!W$42 -> 104583.43 | X98: =VLOOKUP($A98,Python数据平滑!$A$25:$AN$55,COLUMN(Python数据平滑!V$25),0)/SUM(Python数据平滑!V$53:V$55)*情景假设!X$42 -> 107708.56 | Y98: =VLOOKUP($A98,Python数据平滑!$A$25:$AN$55,COLUMN(Python数据平滑!W$25),0)/SUM(Python数据平滑!W$53:W$55)*情景假设!Y$42 -> 110860.23 | ... AE98: =VLOOKUP($A98,Python数据平滑!$A$25:$AN$55,COLUMN(Python数据平滑!AC$25),0)/SUM(Python数据平滑!AC$53:AC$55)*情景假设!AE$42 -> 130991.33 | AF98: =$AF$42*U57 -> 134704.08 | AG98: =VLOOKUP($A98,Python数据平滑!$A$25:$AN$55,COLUMN(Python数据平滑!AE$25),0)/SUM(Python数据平滑!AE$53:AE$55)*情景假设!AG$42 -> 138530.27 | AH98: =VLOOKUP($A98,Python数据平滑!$A$25:$AN$55,COLUMN(Python数据平滑!AF$25),0)/SUM(Python数据平滑!AF$53:AF$55)*情景假设!AH$42 -> 142437.03 | AI98: =VLOOKUP($A98,Python数据平滑!$A$25:$AN$55,COLUMN(Python数据平滑!AG$25),0)/SUM(Python数据平滑!AG$53:AG$55)*情景假设!AI$42 -> 146424.88 | AJ98: =VLOOKUP($A98,Python数据平滑!$A$25:$AN$55,COLUMN(Python数据平滑!AH$25),0)/SUM(Python数据平滑!AH$53:AH$55)*情景假设!AJ$42 -> 150494.2 | AK98: =VLOOKUP($A98,Python数据平滑!$A$25:$AN$55,COLUMN(Python数据平滑!AI$25),0)/SUM(Python数据平滑!AI$53:AI$55)*情景假设!AK$42 -> 154645.25 | AL98: =VLOOKUP($A98,Python数据平滑!$A$25:$AN$55,COLUMN(Python数据平滑!AJ$25),0)/SUM(Python数据平滑!AJ$53:AJ$55)*情景假设!AL$42 -> 158883.54 | AM98: =VLOOKUP($A98,Python数据平滑!$A$25:$AN$55,COLUMN(Python数据平滑!AK$25),0)/SUM(Python数据平滑!AK$53:AK$55)*情景假设!AM$42 -> 163215.88 | AN98: =VLOOKUP($A98,Python数据平滑!$A$25:$AN$55,COLUMN(Python数据平滑!AL$25),0)/SUM(Python数据平滑!AL$53:AL$55)*情景假设!AN$42 -> 167644.3 | AO98: =VLOOKUP($A98,Python数据平滑!$A$25:$AN$55,COLUMN(Python数据平滑!AM$25),0)/SUM(Python数据平滑!AM$53:AM$55)*情景假设!AO$42 -> 172170.8 | AP98: =AP$42*V57 -> 176797.35
A99: 传统服务业-低情景 | B99: =SUM('高情景（2001-2060, 2020RMB）'!U58:U59) -> 111371.5 | C99: =SUM('高情景（2001-2060, 2020RMB）'!V58:V59) -> 122702.13 | D99: =SUM('高情景（2001-2060, 2020RMB）'!W58:W59) -> 123782.33 | E99: =VLOOKUP($A99,Python数据平滑!$A$25:$AN$55,COLUMN(Python数据平滑!C$25),0)/SUM(Python数据平滑!C$53:C$55)*情景假设!E$42 -> 131115.69 | F99: =VLOOKUP($A99,Python数据平滑!$A$25:$AN$55,COLUMN(Python数据平滑!D$25),0)/SUM(Python数据平滑!D$53:D$55)*情景假设!F$42 -> 138774.4 | G99: =G$42*R58 -> 146751.26 | H99: =VLOOKUP($A99,Python数据平滑!$A$25:$AN$55,COLUMN(Python数据平滑!F$25),0)/SUM(Python数据平滑!F$53:F$55)*情景假设!H$42 -> 155205.91 | I99: =VLOOKUP($A99,Python数据平滑!$A$25:$AN$55,COLUMN(Python数据平滑!G$25),0)/SUM(Python数据平滑!G$53:G$55)*情景假设!I$42 -> 164184.63 | J99: =VLOOKUP($A99,Python数据平滑!$A$25:$AN$55,COLUMN(Python数据平滑!H$25),0)/SUM(Python数据平滑!H$53:H$55)*情景假设!J$42 -> 173477.34 | K99: =VLOOKUP($A99,Python数据平滑!$A$25:$AN$55,COLUMN(Python数据平滑!I$25),0)/SUM(Python数据平滑!I$53:I$55)*情景假设!K$42 -> 182830.91 | L99: =L$42*S58 -> 191947.85 | M99: =VLOOKUP($A99,Python数据平滑!$A$25:$AN$55,COLUMN(Python数据平滑!K$25),0)/SUM(Python数据平滑!K$53:K$55)*情景假设!M$42 -> 200766.41 | N99: =VLOOKUP($A99,Python数据平滑!$A$25:$AN$55,COLUMN(Python数据平滑!L$25),0)/SUM(Python数据平滑!L$53:L$55)*情景假设!N$42 -> 209468.13 | O99: =VLOOKUP($A99,Python数据平滑!$A$25:$AN$55,COLUMN(Python数据平滑!M$25),0)/SUM(Python数据平滑!M$53:M$55)*情景假设!O$42 -> 218092.61 | P99: =VLOOKUP($A99,Python数据平滑!$A$25:$AN$55,COLUMN(Python数据平滑!N$25),0)/SUM(Python数据平滑!N$53:N$55)*情景假设!P$42 -> 226686 | Q99: =Q$42*T58 -> 235300.37 | R99: =VLOOKUP($A99,Python数据平滑!$A$25:$AN$55,COLUMN(Python数据平滑!P$25),0)/SUM(Python数据平滑!P$53:P$55)*情景假设!R$42 -> 243863.15 | S99: =VLOOKUP($A99,Python数据平滑!$A$25:$AN$55,COLUMN(Python数据平滑!Q$25),0)/SUM(Python数据平滑!Q$53:Q$55)*情景假设!S$42 -> 252298.87 | T99: =VLOOKUP($A99,Python数据平滑!$A$25:$AN$55,COLUMN(Python数据平滑!R$25),0)/SUM(Python数据平滑!R$53:R$55)*情景假设!T$42 -> 260668.02 | U99: =VLOOKUP($A99,Python数据平滑!$A$25:$AN$55,COLUMN(Python数据平滑!S$25),0)/SUM(Python数据平滑!S$53:S$55)*情景假设!U$42 -> 269043.66 | V99: =VLOOKUP($A99,Python数据平滑!$A$25:$AN$55,COLUMN(Python数据平滑!T$25),0)/SUM(Python数据平滑!T$53:T$55)*情景假设!V$42 -> 277511.67 | W99: =VLOOKUP($A99,Python数据平滑!$A$25:$AN$55,COLUMN(Python数据平滑!U$25),0)/SUM(Python数据平滑!U$53:U$55)*情景假设!W$42 -> 286099.09 | X99: =VLOOKUP($A99,Python数据平滑!$A$25:$AN$55,COLUMN(Python数据平滑!V$25),0)/SUM(Python数据平滑!V$53:V$55)*情景假设!X$42 -> 294781.87 | Y99: =VLOOKUP($A99,Python数据平滑!$A$25:$AN$55,COLUMN(Python数据平滑!W$25),0)/SUM(Python数据平滑!W$53:W$55)*情景假设!Y$42 -> 303582.05 | ... AE99: =VLOOKUP($A99,Python数据平滑!$A$25:$AN$55,COLUMN(Python数据平滑!AC$25),0)/SUM(Python数据平滑!AC$53:AC$55)*情景假设!AE$42 -> 360850.13 | AF99: =$AF$42*U58 -> 371597.45 | AG99: =VLOOKUP($A99,Python数据平滑!$A$25:$AN$55,COLUMN(Python数据平滑!AE$25),0)/SUM(Python数据平滑!AE$53:AE$55)*情景假设!AG$42 -> 382737.22 | AH99: =VLOOKUP($A99,Python数据平滑!$A$25:$AN$55,COLUMN(Python数据平滑!AF$25),0)/SUM(Python数据平滑!AF$53:AF$55)*情景假设!AH$42 -> 394189.58 | AI99: =VLOOKUP($A99,Python数据平滑!$A$25:$AN$55,COLUMN(Python数据平滑!AG$25),0)/SUM(Python数据平滑!AG$53:AG$55)*情景假设!AI$42 -> 405960.86 | AJ99: =VLOOKUP($A99,Python数据平滑!$A$25:$AN$55,COLUMN(Python数据平滑!AH$25),0)/SUM(Python数据平滑!AH$53:AH$55)*情景假设!AJ$42 -> 418057.12 | AK99: =VLOOKUP($A99,Python数据平滑!$A$25:$AN$55,COLUMN(Python数据平滑!AI$25),0)/SUM(Python数据平滑!AI$53:AI$55)*情景假设!AK$42 -> 430484.11 | AL99: =VLOOKUP($A99,Python数据平滑!$A$25:$AN$55,COLUMN(Python数据平滑!AJ$25),0)/SUM(Python数据平滑!AJ$53:AJ$55)*情景假设!AL$42 -> 443262.46 | AM99: =VLOOKUP($A99,Python数据平滑!$A$25:$AN$55,COLUMN(Python数据平滑!AK$25),0)/SUM(Python数据平滑!AK$53:AK$55)*情景假设!AM$42 -> 456416.58 | AN99: =VLOOKUP($A99,Python数据平滑!$A$25:$AN$55,COLUMN(Python数据平滑!AL$25),0)/SUM(Python数据平滑!AL$53:AL$55)*情景假设!AN$42 -> 469957.76 | AO99: =VLOOKUP($A99,Python数据平滑!$A$25:$AN$55,COLUMN(Python数据平滑!AM$25),0)/SUM(Python数据平滑!AM$53:AM$55)*情景假设!AO$42 -> 483897.43 | AP99: =AP$42*V58 -> 498247.09
A100: 现代服务业-低情景 | B100: =SUM('高情景（2001-2060, 2020RMB）'!U60:U70) -> 394868.3 | C100: =SUM('高情景（2001-2060, 2020RMB）'!V60:V70) -> 415244.29 | D100: =SUM('高情景（2001-2060, 2020RMB）'!W60:W70) -> 421311.1 | E100: =VLOOKUP($A100,Python数据平滑!$A$25:$AN$55,COLUMN(Python数据平滑!C$25),0)/SUM(Python数据平滑!C$53:C$55)*情景假设!E$42 -> 452914.49 | F100: =VLOOKUP($A100,Python数据平滑!$A$25:$AN$55,COLUMN(Python数据平滑!D$25),0)/SUM(Python数据平滑!D$53:D$55)*情景假设!F$42 -> 486452.32 | G100: =G$42*R59 -> 521942.89 | H100: =VLOOKUP($A100,Python数据平滑!$A$25:$AN$55,COLUMN(Python数据平滑!F$25),0)/SUM(Python数据平滑!F$53:F$55)*情景假设!H$42 -> 560233.03 | I100: =VLOOKUP($A100,Python数据平滑!$A$25:$AN$55,COLUMN(Python数据平滑!G$25),0)/SUM(Python数据平滑!G$53:G$55)*情景假设!I$42 -> 601636.12 | J100: =VLOOKUP($A100,Python数据平滑!$A$25:$AN$55,COLUMN(Python数据平滑!H$25),0)/SUM(Python数据平滑!H$53:H$55)*情景假设!J$42 -> 645152.45 | K100: =VLOOKUP($A100,Python数据平滑!$A$25:$AN$55,COLUMN(Python数据平滑!I$25),0)/SUM(Python数据平滑!I$53:I$55)*情景假设!K$42 -> 689477.78 | L100: =L$42*S59 -> 732982.21 | M100: =VLOOKUP($A100,Python数据平滑!$A$25:$AN$55,COLUMN(Python数据平滑!K$25),0)/SUM(Python数据平滑!K$53:K$55)*情景假设!M$42 -> 774886.5 | N100: =VLOOKUP($A100,Python数据平滑!$A$25:$AN$55,COLUMN(Python数据平滑!L$25),0)/SUM(Python数据平滑!L$53:L$55)*情景假设!N$42 -> 816072.26 | O100: =VLOOKUP($A100,Python数据平滑!$A$25:$AN$55,COLUMN(Python数据平滑!M$25),0)/SUM(Python数据平滑!M$53:M$55)*情景假设!O$42 -> 857291.19 | P100: =VLOOKUP($A100,Python数据平滑!$A$25:$AN$55,COLUMN(Python数据平滑!N$25),0)/SUM(Python数据平滑!N$53:N$55)*情景假设!P$42 -> 899473.53 | Q100: =Q$42*T59 -> 943731.6 | R100: =VLOOKUP($A100,Python数据平滑!$A$25:$AN$55,COLUMN(Python数据平滑!P$25),0)/SUM(Python数据平滑!P$53:P$55)*情景假设!R$42 -> 990114.58 | S100: =VLOOKUP($A100,Python数据平滑!$A$25:$AN$55,COLUMN(Python数据平滑!Q$25),0)/SUM(Python数据平滑!Q$53:Q$55)*情景假设!S$42 -> 1037943 | T100: =VLOOKUP($A100,Python数据平滑!$A$25:$AN$55,COLUMN(Python数据平滑!R$25),0)/SUM(Python数据平滑!R$53:R$55)*情景假设!T$42 -> 1087402.6 | U100: =VLOOKUP($A100,Python数据平滑!$A$25:$AN$55,COLUMN(Python数据平滑!S$25),0)/SUM(Python数据平滑!S$53:S$55)*情景假设!U$42 -> 1138715.5 | V100: =VLOOKUP($A100,Python数据平滑!$A$25:$AN$55,COLUMN(Python数据平滑!T$25),0)/SUM(Python数据平滑!T$53:T$55)*情景假设!V$42 -> 1192144.7 | W100: =VLOOKUP($A100,Python数据平滑!$A$25:$AN$55,COLUMN(Python数据平滑!U$25),0)/SUM(Python数据平滑!U$53:U$55)*情景假设!W$42 -> 1247684.5 | X100: =VLOOKUP($A100,Python数据平滑!$A$25:$AN$55,COLUMN(Python数据平滑!V$25),0)/SUM(Python数据平滑!V$53:V$55)*情景假设!X$42 -> 1305073.5 | Y100: =VLOOKUP($A100,Python数据平滑!$A$25:$AN$55,COLUMN(Python数据平滑!W$25),0)/SUM(Python数据平滑!W$53:W$55)*情景假设!Y$42 -> 1364210.7 | ... AE100: =VLOOKUP($A100,Python数据平滑!$A$25:$AN$55,COLUMN(Python数据平滑!AC$25),0)/SUM(Python数据平滑!AC$53:AC$55)*情景假设!AE$42 -> 1748666.4 | AF100: =$AF$42*U59 -> 1816182.5 | AG100: =VLOOKUP($A100,Python数据平滑!$A$25:$AN$55,COLUMN(Python数据平滑!AE$25),0)/SUM(Python数据平滑!AE$53:AE$55)*情景假设!AG$42 -> 1884506 | AH100: =VLOOKUP($A100,Python数据平滑!$A$25:$AN$55,COLUMN(Python数据平滑!AF$25),0)/SUM(Python数据平滑!AF$53:AF$55)*情景假设!AH$42 -> 1953918.6 | AI100: =VLOOKUP($A100,Python数据平滑!$A$25:$AN$55,COLUMN(Python数据平滑!AG$25),0)/SUM(Python数据平滑!AG$53:AG$55)*情景假设!AI$42 -> 2024339.1 | AJ100: =VLOOKUP($A100,Python数据平滑!$A$25:$AN$55,COLUMN(Python数据平滑!AH$25),0)/SUM(Python数据平滑!AH$53:AH$55)*情景假设!AJ$42 -> 2095678 | AK100: =VLOOKUP($A100,Python数据平滑!$A$25:$AN$55,COLUMN(Python数据平滑!AI$25),0)/SUM(Python数据平滑!AI$53:AI$55)*情景假设!AK$42 -> 2167837.8 | AL100: =VLOOKUP($A100,Python数据平滑!$A$25:$AN$55,COLUMN(Python数据平滑!AJ$25),0)/SUM(Python数据平滑!AJ$53:AJ$55)*情景假设!AL$42 -> 2240789.5 | AM100: =VLOOKUP($A100,Python数据平滑!$A$25:$AN$55,COLUMN(Python数据平滑!AK$25),0)/SUM(Python数据平滑!AK$53:AK$55)*情景假设!AM$42 -> 2314517.6 | AN100: =VLOOKUP($A100,Python数据平滑!$A$25:$AN$55,COLUMN(Python数据平滑!AL$25),0)/SUM(Python数据平滑!AL$53:AL$55)*情景假设!AN$42 -> 2388934.5 | AO100: =VLOOKUP($A100,Python数据平滑!$A$25:$AN$55,COLUMN(Python数据平滑!AM$25),0)/SUM(Python数据平滑!AM$53:AM$55)*情景假设!AO$42 -> 2463946.2 | AP100: =AP$42*V59 -> 2539452.9
A104: 假设4-1：高情景细分产业
B105: 2016-2019年均增速 | C105: 2019-2022年均增速 | D105: 十四五衰减系数 | E105: 十五五衰减系数 | F105: 十六五衰减系数 | G105: 2035-2050衰减系数 | H105: 2051-2060衰减系数 | I105: 十四五年均增速 | J105: 十五五年均增速 | K105: 十六五年均增速 | L105: 2035-2050年均增速 | M105: 2051-2060年均增速 | N105: 2025增加值 | O105: 2030增加值 | P105: 2035增加值 | Q105: 2050增加值 | R105: 2060增加值 | S105: 2022增加值 | T105: 十四五增加值调整 | U105: 十五五增加值调整 | V105: 十六五增加值调整 | W105: 2050增加值调整 | X105: 2060增加值调整
A106: 能源产业
A107: 煤炭开采和洗选业 | B107: =(VLOOKUP(A107,'高情景（2001-2060, 2020RMB）'!$A$14:$W$54,20,0)/VLOOKUP(A107,'高情景（2001-2060, 2020RMB）'!$A$14:$W$54,17,0))^(1/3)-1 -> 0.0085070768 | C107: =(VLOOKUP(A107,'高情景（2001-2060, 2020RMB）'!$A$14:$W$54,23,0)/VLOOKUP(A107,'高情景（2001-2060, 2020RMB）'!$A$14:$W$54,20,0))^(1/3)-1 -> 0.062061126 | D107: 0.9 | E107: 0.8 | F107: 0.6 | G107: 0.35 | H107: 0.3 | I107: =AVERAGE($B107:$C107)*D107 -> 0.031755691 | J107: =AVERAGE($B107:$C107)*E107 -> 0.028227281 | K107: =AVERAGE($B107:$C107)*F107 -> 0.021170461 | L107: =AVERAGE($B107:$C107)*G107 -> 0.012349436 | M107: =AVERAGE($B107:$C107)*H107 -> 0.01058523 | N107: =VLOOKUP($A107,'高情景（2001-2060, 2020RMB）'!$A$14:$W$54,23,0)*(1+情景假设!I107)^3 -> 19772.103 | O107: =N107*(1+情景假设!J107)^5 -> 22724.716 | P107: =O107*(1+情景假设!K107)^5 -> 25234.208 | Q107: =P107*(1+L107)^15 -> 30335.165 | R107: =Q107*(1+情景假设!M107)^10 -> 33703.564 | S107: =VLOOKUP($A107,'高情景（2001-2060, 2020RMB）'!$A$14:$W$70,23,0) -> 18002.061 | T107: =N107/SUM(N$107:N$111)*$G$64 -> 19579.678 | U107: =O107/SUM(O$107:O$111)*$L$64 -> 21442.826 | V107: =P107/SUM(P$107:P$111)*$Q$64 -> 22042.938 | W107: =Q107/SUM(Q$107:Q$111)*$AF$64 -> 21752.612 | X107: =R107/SUM(R$107:R$111)*$AP$64 -> 20519.467
A108: 石油和天然气开采业 | B108: =(VLOOKUP(A108,'高情景（2001-2060, 2020RMB）'!$A$14:$W$54,20,0)/VLOOKUP(A108,'高情景（2001-2060, 2020RMB）'!$A$14:$W$54,17,0))^(1/3)-1 -> 3.2675208e-05 | C108: =(VLOOKUP(A108,'高情景（2001-2060, 2020RMB）'!$A$14:$W$54,23,0)/VLOOKUP(A108,'高情景（2001-2060, 2020RMB）'!$A$14:$W$54,20,0))^(1/3)-1 -> 0.041028014 | D108: 0.9 | E108: 0.8 | F108: 0.7 | G108: 0.55 | H108: 0.5 | I108: =AVERAGE($B108:$C108)*D108 -> 0.01847731 | J108: =AVERAGE($B108:$C108)*E108 -> 0.016424276 | K108: =AVERAGE($B108:$C108)*F108 -> 0.014371241 | L108: =AVERAGE($B108:$C108)*G108 -> 0.011291689 | M108: =AVERAGE($B108:$C108)*H108 -> 0.010265172 | N108: =VLOOKUP($A108,'高情景（2001-2060, 2020RMB）'!$A$14:$W$54,23,0)*(1+情景假设!I108)^3 -> 12998.886 | O108: =N108*(1+情景假设!J108)^5 -> 14102.019 | P108: =O108*(1+情景假设!K108)^5 -> 15144.883 | Q108: =P108*(1+L108)^15 -> 17923.074 | R108: =Q108*(1+情景假设!M108)^10 -> 19850.265 | S108: =VLOOKUP($A108,'高情景（2001-2060, 2020RMB）'!$A$14:$W$70,23,0) -> 12304.163 | T108: =N108/SUM(N$107:N$111)*$G$64 -> 12872.379 | U108: =O108/SUM(O$107:O$111)*$L$64 -> 13306.53 | V108: =P108/SUM(P$107:P$111)*$Q$64 -> 13229.57 | W108: =Q108/SUM(Q$107:Q$111)*$AF$64 -> 12852.202 | X108: =R108/SUM(R$107:R$111)*$AP$64 -> 12085.276
A109: 石油、煤炭及其他燃料加工业 | B109: =(VLOOKUP(A109,'高情景（2001-2060, 2020RMB）'!$A$14:$W$54,20,0)/VLOOKUP(A109,'高情景（2001-2060, 2020RMB）'!$A$14:$W$54,17,0))^(1/3)-1 -> 0.043953138 | C109: =(VLOOKUP(A109,'高情景（2001-2060, 2020RMB）'!$A$14:$W$54,23,0)/VLOOKUP(A109,'高情景（2001-2060, 2020RMB）'!$A$14:$W$54,20,0))^(1/3)-1 -> -0.0048253327 | D109: 1 | E109: 0.6 | F109: 0.5 | G109: 0.35 | H109: 0.3 | I109: =AVERAGE($B109:$C109)*D109 -> 0.019563903 | J109: =AVERAGE($B109:$C109)*E109 -> 0.011738342 | K109: =AVERAGE($B109:$C109)*F109 -> 0.0097819514 | L109: =AVERAGE($B109:$C109)*G109 -> 0.006847366 | M109: =AVERAGE($B109:$C109)*H109 -> 0.0058691708 | N109: =VLOOKUP($A109,'高情景（2001-2060, 2020RMB）'!$A$14:$W$54,23,0)*(1+情景假设!I109)^3 -> 6596.928 | O109: =N109*(1+情景假设!J109)^5 -> 6993.3101 | P109: =O109*(1+情景假设!K109)^5 -> 7342.1086 | Q109: =P109*(1+L109)^15 -> 8133.4608 | R109: =Q109*(1+情景假设!M109)^10 -> 8623.6348 | S109: =VLOOKUP($A109,'高情景（2001-2060, 2020RMB）'!$A$14:$W$70,23,0) -> 6224.4128 | T109: =N109/SUM(N$107:N$111)*$G$64 -> 6532.7258 | U109: =O109/SUM(O$107:O$111)*$L$64 -> 6598.8208 | V109: =P109/SUM(P$107:P$111)*$Q$64 -> 6413.5814 | W109: =Q109/SUM(Q$107:Q$111)*$AF$64 -> 5832.3078 | X109: =R109/SUM(R$107:R$111)*$AP$64 -> 5250.2575
A110: 燃气生产和供应业 | B110: =(VLOOKUP(A110,'高情景（2001-2060, 2020RMB）'!$A$14:$W$54,20,0)/VLOOKUP(A110,'高情景（2001-2060, 2020RMB）'!$A$14:$W$54,17,0))^(1/3)-1 -> 0.12785054 | C110: =(VLOOKUP(A110,'高情景（2001-2060, 2020RMB）'!$A$14:$W$54,23,0)/VLOOKUP(A110,'高情景（2001-2060, 2020RMB）'!$A$14:$W$54,20,0))^(1/3)-1 -> 0.087030245 | D110: 0.9 | E110: 0.8 | F110: 0.7 | G110: 0.55 | H110: 0.5 | I110: =AVERAGE($B110:$C110)*D110 -> 0.096696353 | J110: =AVERAGE($B110:$C110)*E110 -> 0.085952314 | K110: =AVERAGE($B110:$C110)*F110 -> 0.075208275 | L110: =AVERAGE($B110:$C110)*G110 -> 0.059092216 | M110: =AVERAGE($B110:$C110)*H110 -> 0.053720196 | N110: =VLOOKUP($A110,'高情景（2001-2060, 2020RMB）'!$A$14:$W$54,23,0)*(1+情景假设!I110)^3 -> 3251.4307 | O110: =N110*(1+情景假设!J110)^5 -> 4910.529 | P110: =O110*(1+情景假设!K110)^5 -> 7056.5312 | Q110: =P110*(1+L110)^15 -> 16695.442 | R110: =Q110*(1+情景假设!M110)^10 -> 28174.158 | S110: =VLOOKUP($A110,'高情景（2001-2060, 2020RMB）'!$A$14:$W$70,23,0) -> 2464.9908 | T110: =N110/SUM(N$107:N$111)*$G$64 -> 3219.7873 | U110: =O110/SUM(O$107:O$111)*$L$64 -> 4633.5283 | V110: =P110/SUM(P$107:P$111)*$Q$64 -> 6164.1198 | W110: =Q110/SUM(Q$107:Q$111)*$AF$64 -> 11971.897 | X110: =R110/SUM(R$107:R$111)*$AP$64 -> 17153.044
A111: 水的生产和供应业 | B111: =(VLOOKUP(A111,'高情景（2001-2060, 2020RMB）'!$A$14:$W$54,20,0)/VLOOKUP(A111,'高情景（2001-2060, 2020RMB）'!$A$14:$W$54,17,0))^(1/3)-1 -> 0.067720747 | C111: =(VLOOKUP(A111,'高情景（2001-2060, 2020RMB）'!$A$14:$W$54,23,0)/VLOOKUP(A111,'高情景（2001-2060, 2020RMB）'!$A$14:$W$54,20,0))^(1/3)-1 -> 0.064716353 | D111: 0.9 | E111: 0.8 | F111: 0.7 | G111: 0.55 | H111: 0.5 | I111: =AVERAGE($B111:$C111)*D111 -> 0.059596695 | J111: =AVERAGE($B111:$C111)*E111 -> 0.05297484 | K111: =AVERAGE($B111:$C111)*F111 -> 0.046352985 | L111: =AVERAGE($B111:$C111)*G111 -> 0.036420202 | M111: =AVERAGE($B111:$C111)*H111 -> 0.033109275 | N111: =VLOOKUP($A111,'高情景（2001-2060, 2020RMB）'!$A$14:$W$54,23,0)*(1+情景假设!I111)^3 -> 1544.8858 | O111: =N111*(1+情景假设!J111)^5 -> 1999.799 | P111: =O111*(1+情景假设!K111)^5 -> 2508.2882 | Q111: =P111*(1+L111)^15 -> 4289.587 | R111: =Q111*(1+情景假设!M111)^10 -> 5941.2536 | S111: =VLOOKUP($A111,'高情景（2001-2060, 2020RMB）'!$A$14:$W$70,23,0) -> 1298.5976 | T111: =N111/SUM(N$107:N$111)*$G$64 -> 1529.8507 | U111: =O111/SUM(O$107:O$111)*$L$64 -> 1886.9913 | V111: =P111/SUM(P$107:P$111)*$Q$64 -> 2191.075 | W111: =Q111/SUM(Q$107:Q$111)*$AF$64 -> 3075.959 | X111: =R111/SUM(R$107:R$111)*$AP$64 -> 3617.1652
A112: 传统高耗能产业
A113: 纺织业 | B113: =(VLOOKUP(A113,'高情景（2001-2060, 2020RMB）'!$A$14:$W$54,20,0)/VLOOKUP(A113,'高情景（2001-2060, 2020RMB）'!$A$14:$W$54,17,0))^(1/3)-1 -> 0.011202933 | C113: =(VLOOKUP(A113,'高情景（2001-2060, 2020RMB）'!$A$14:$W$54,23,0)/VLOOKUP(A113,'高情景（2001-2060, 2020RMB）'!$A$14:$W$54,20,0))^(1/3)-1 -> 0.0054812952 | D113: 0.7 | E113: 0.6 | F113: 0.5 | G113: 0.33 | H113: 0.3 | I113: =AVERAGE($B113:$C113)*D113 -> 0.0058394797 | J113: =AVERAGE($B113:$C113)*E113 -> 0.0050052683 | K113: =AVERAGE($B113:$C113)*F113 -> 0.0041710569 | L113: =AVERAGE($B113:$C113)*G113 -> 0.0027528976 | M113: =AVERAGE($B113:$C113)*H113 -> 0.0025026342 | N113: =VLOOKUP($A113,'高情景（2001-2060, 2020RMB）'!$A$14:$W$54,23,0)*(1+情景假设!I113)^3 -> 8262.9153 | O113: =N113*(1+情景假设!J113)^5 -> 8471.7863 | P113: =O113*(1+情景假设!K113)^5 -> 8649.9478 | Q113: =P113*(1+L113)^15 -> 9014.1 | R113: =Q113*(1+情景假设!M113)^10 -> 9242.2476 | S113: =VLOOKUP($A113,'高情景（2001-2060, 2020RMB）'!$A$14:$W$70,23,0) -> 8119.8361 | T113: =N113/SUM(N$113:N$121)*$G$67 -> 8353.3088 | U113: =O113/SUM(O$113:O$121)*$L$67 -> 8873.065 | V113: =P113/SUM(P$113:P$121)*$Q$67 -> 9161.7228 | W113: =Q113/SUM(Q$113:Q$121)*$AF$67 -> 10195.615 | X113: =R113/SUM(R$113:R$121)*$AP$67 -> 10857.01
