Workbook

Sheet 分行业工业增加值（当年人民币）
A1: 全国（单位：亿元） | B1: 2019 | C1: 2020 | D1: 2021 | E1: 2022 | F1: 2023 | G1: 2024 | H1: 2025 | I1: 2026 | J1: 2027 | K1: 2028 | L1: 2029 | M1: 2030 | N1: 2031 | O1: 2032 | P1: 2033 | Q1: 2034 | R1: 2035 | S1: 2036 | T1: 2037 | U1: 2038 | V1: 2039 | W1: 2040 | X1: 2041 | Y1: 2042 | Z1: 2043 | AA1: 2044 | AB1: 2045 | AC1: 2046 | AD1: 2047 | AE1: 2048 | AF1: 2049 | AG1: 2050 | AH1: 2051 | AI1: 2052 | AJ1: 2053 | AK1: 2054 | AL1: 2055 | AM1: 2056 | AN1: 2057 | AO1: 2058 | AP1: 2059 | AQ1: 2060
A2: 地区生产总值 | B2: 982320.5 | C2: 1081134.6 | D2: 1169287.4 | E2: 1260898.9 | F2: 1356078.3 | G2: 1454268.8 | H2: 1556518.1 | I2: 1662039.5 | J2: 1770957.4 | K2: 1883818.3 | L2: 1999892.7 | M2: 2119738.5 | N2: 2243328.1 | O2: 2370251.9 | P2: 2501196.1 | Q2: 2635776.3 | R2: 2773804.6 | S2: 2916069.9 | T2: 3061915.7 | U2: 3212067.3 | V2: 3366153.4 | W2: 3523990.4 | X2: 3686274.5 | Y2: 3852797.5 | Z2: 4023521.8 | AA2: 4198628.9 | AB2: 4378278.9 | AC2: 4562763.8 | AD2: 4751741.8 | AE2: 4945364.6 | AF2: 5144486.9 | AG2: 5348376.4 | AH2: 5557591.5 | AI2: 5772275.4 | AJ2: 5992276.8 | AK2: 6218329.8 | AL2: 6450282.8 | AM2: 6688426.5 | AN2: 6933021.1 | AO2: 7184130.3 | AP2: 7442387 | AQ2: 7707658.2
A3: 农业 | B3: 73576.8 | C3: 81084.1 | D3: 86775.6 | E3: 92057.213 | F3: 97462.356 | G3: 102971.12 | H3: 108656.26 | I3: 114453.55 | J3: 120377.03 | K3: 126447.17 | L3: 132633.1 | M3: 138978.5 | N3: 145445.46 | O3: 152023.06 | P3: 158754.86 | Q3: 165608.08 | R3: 172572.11 | S3: 179676.88 | T3: 186898.79 | U3: 194283.67 | V3: 201788.05 | W3: 209402.38 | X3: 217169.55 | Y3: 225069.79 | Z3: 233095.75 | AA3: 241256.56 | AB3: 249561.41 | AC3: 258030.95 | AD3: 266636.86 | AE3: 275387.1 | AF3: 284326.32 | AG3: 293411.36 | AH3: 302677.82 | AI3: 312134.26 | AJ3: 321767.93 | AK3: 331614.6 | AL3: 341683.33 | AM3: 351986.8 | AN3: 362544.12 | AO3: 373357.5 | AP3: 384469.58 | AQ3: 395882.24
A4: 工业 | B4: 312419.9 | C4: 312866.3 | D4: 368569.7 | E4: 386900.01 | F4: 405000.62 | G4: 422886.84 | H4: 440581.01 | I4: 458110.24 | J4: 475504.51 | K4: 492795.29 | L4: 510014.47 | M4: 527193.66 | N4: 544363.63 | O4: 561554.04 | P4: 578793.25 | Q4: 596108.19 | R4: 613524.43 | S4: 631066.12 | T4: 648756.12 | U4: 666616.07 | V4: 684666.49 | W4: 702926.85 | X4: 721415.72 | Y4: 740150.83 | Z4: 759149.18 | AA4: 778427.13 | AB4: 798000.48 | AC4: 817884.53 | AD4: 838094.2 | AE4: 858644.01 | AF4: 879548.22 | AG4: 900820.85 | AH4: 922475.72 | AI4: 944526.48 | AJ4: 966986.72 | AK4: 989869.93 | AL4: 1013189.5 | AM4: 1036959 | AN4: 1061191.9 | AO4: 1085901.5 | AP4: 1111101.6 | AQ4: 1136805.8
A5: 建筑业 | B5: 70613.1 | C5: 73028.6 | D5: 80072.9 | E5: 85981.803 | F5: 92122.496 | G5: 98460.911 | H5: 105064.29 | I5: 111878.73 | J5: 118923.45 | K5: 126218.57 | L5: 133727.07 | M5: 141493.56 | N5: 149498.98 | O5: 157721.37 | P5: 166210.55 | Q5: 174939.55 | R5: 183897 | S5: 193120.64 | T5: 202587.34 | U5: 212332.89 | V5: 222325.28 | W5: 232563.02 | X5: 243082.31 | Y5: 253869.8 | Z5: 264931.3 | AA5: 276262.05 | AB5: 287887.56 | AC5: 299820.58 | AD5: 312036.5 | AE5: 324556.54 | AF5: 337422.52 | AG5: 350605.13 | AH5: 364139.62 | AI5: 378035.26 | AJ5: 392299.68 | AK5: 406968.24 | AL5: 422060.78 | AM5: 437608.29 | AN5: 453619.73 | AO5: 470138.68 | AP5: 487209.01 | AQ5: 504847.58
A6: 交运仓邮 | B6: 42852.8 | C6: 41590.3 | D6: 46748.7 | E6: 49571.436 | F6: 52454.766 | G6: 55386.594 | H6: 58398.458 | I6: 61466.791 | J6: 64591.12 | K6: 67787.09 | L6: 71035.669 | M6: 74350.123 | N6: 77727.933 | O6: 81156.438 | P6: 84653.559 | Q6: 88210.978 | R6: 91821.997 | S6: 95503.389 | T6: 99237.858 | U6: 103046.98 | V6: 106917.9 | W6: 110838.45 | X6: 114833.98 | Y6: 118898.6 | Z6: 123024.93 | AA6: 127219.16 | AB6: 131485.68 | AC6: 135827.57 | AD6: 140235.03 | AE6: 144714.49 | AF6: 149285.74 | AG6: 153927.21 | AH6: 158652.32 | AI6: 163467.79 | AJ6: 168364.26 | AK6: 173360.27 | AL6: 178454.44 | AM6: 183651.31 | AN6: 188958.1 | AO6: 194375.81 | AP6: 199922.33 | AQ6: 205591.2
A7: 批发零售 | B7: 95138.9 | C7: 95047.9 | D7: 110280 | E7: 118836.75 | F7: 127731.67 | G7: 136908.53 | H7: 146453.7 | I7: 156310.35 | J7: 166476.45 | K7: 177019.98 | L7: 187862.74 | M7: 199051.1 | N7: 210601.09 | O7: 222456.6 | P7: 234690.47 | Q7: 247269.51 | R7: 260165.62 | S7: 273466.74 | T7: 287105.83 | U7: 301143.11 | V7: 315558.84 | W7: 330325.8 | X7: 345508.6 | Y7: 361092.79 | Z7: 377069.21 | AA7: 393464.04 | AB7: 410285.37 | AC7: 427554.81 | AD7: 445251.24 | AE7: 463384.22 | AF7: 482040.34 | AG7: 501142.65 | AH7: 520751.71 | AI7: 540879.36 | AJ7: 561504.19 | AK7: 582712.9 | AL7: 604479.33 | AM7: 626833.87 | AN7: 649817.19 | AO7: 673421.17 | AP7: 697722.94 | AQ7: 722710.81
A8: 餐饮住宿 | B8: 17953.1 | C8: 15896.1 | D8: 17821.2 | E8: 19511.611 | F8: 21300.469 | G8: 23179.927 | H8: 25170.41 | I8: 27260.402 | J8: 29453.554 | K8: 31761.269 | L8: 34174.173 | M8: 36704.021 | N8: 39349.66 | O8: 42105.169 | P8: 44988.925 | Q8: 47994.641 | R8: 51116.123 | S8: 54373.326 | T8: 57757.202 | U8: 61283.098 | V8: 64942.415 | W8: 68735.023 | X8: 72677.751 | Y8: 76767.68 | Z8: 81005.033 | AA8: 85394.829 | AB8: 89944.542 | AC8: 94663.433 | AD8: 99548.313 | AE8: 104601.06 | AF8: 109849.2 | AG8: 115278.15 | AH8: 120906.48 | AI8: 126742.18 | AJ8: 132785.05 | AK8: 139060.12 | AL8: 145574.62 | AM8: 152340.74 | AN8: 159377.16 | AO8: 166692.11 | AP8: 174316.16 | AQ8: 182264.6
A9: 金融业 | B9: 76691.7 | C9: 84280.5 | D9: 91083.2 | E9: 100929.79 | F9: 111451.29 | G9: 122579.85 | H9: 134446.5 | I9: 146997.06 | J9: 160247.83 | K9: 174310.04 | L9: 189087.18 | M9: 204663.44 | N9: 221088.85 | O9: 238311.63 | P9: 256440.67 | Q9: 275470.02 | R9: 295373.01 | S9: 316316.13 | T9: 338205.51 | U9: 361167.02 | V9: 385200.11 | W9: 410290.38 | X9: 436566.85 | Y9: 464044.28 | Z9: 492725.08 | AA9: 522704.72 | AB9: 554002.9 | AC9: 586717.77 | AD9: 620827.6 | AE9: 656369.21 | AF9: 693549.69 | AG9: 732243.32 | AH9: 772583.62 | AI9: 814632.25 | AJ9: 858370.98 | AK9: 903986.11 | AL9: 951430.46 | AM9: 1000779.7 | AN9: 1052115.3 | AO9: 1105431.5 | AP9: 1160899.4 | AQ9: 1218426.3
A10: 房地产 | B10: 69436.5 | C10: 74547.7 | D10: 77516.4 | E10: 83624.512 | F10: 90001.797 | G10: 96616.651 | H10: 103540.35 | I10: 110732.13 | J10: 118196.6 | K10: 125967.34 | L10: 134005.24 | M10: 142345.59 | N10: 150994.13 | O10: 159922.27 | P10: 169174.6 | Q10: 178733.27 | R10: 188590.5 | S10: 198791.5 | T10: 209299.18 | U10: 220160.59 | V10: 231362.36 | W10: 242884.91 | X10: 254778.26 | Y10: 267033.78 | Z10: 279649.42 | AA10: 292639.15 | AB10: 306019 | AC10: 319808.89 | AD10: 333986.06 | AE10: 348577.22 | AF10: 363635.92 | AG10: 379117.46 | AH10: 395066.39 | AI10: 411504.49 | AJ10: 428426.88 | AK10: 445890.44 | AL10: 463899.81 | AM10: 482485.1 | AN10: 501684 | AO10: 521511.95 | AP10: 542027.33 | AQ10: 563251.86
A11: 其他三产 | B11: 223637.7 | C11: 302793.12 | D11: 290419.66 | E11: 323485.78 | F11: 358552.82 | G11: 395278.33 | H11: 434207.15 | I11: 474830.29 | J11: 517186.85 | K11: 561511.53 | L11: 607353.1 | M11: 654958.55 | N11: 704258.4 | O11: 755001.29 | P11: 807489.23 | Q11: 861442.08 | R11: 916743.85 | S11: 973755.21 | T11: 1032067.9 | U11: 1092033.9 | V11: 1153392 | W11: 1216023.6 | X11: 1280241.5 | Y11: 1345870 | Z11: 1412871.9 | AA11: 1481261.2 | AB11: 1551091.9 | AC11: 1622455.3 | AD11: 1695126 | AE11: 1769130.8 | AF11: 1844829 | AG11: 1921830.3 | AH11: 2000337.9 | AI11: 2080353.3 | AJ11: 2161771.1 | AK11: 2244867.2 | AL11: 2329510.5 | AM11: 2415781.6 | AN11: 2503713.6 | AO11: 2593300.1 | AP11: 2684718.6 | AQ11: 2777877.7
A13: 工业 | B13: 312419.9 | C13: 312866.3 | D13: 368569.7 | E13: 386900.01 | F13: 405000.62 | G13: 422886.84 | H13: 440581.01 | I13: 458110.24 | J13: 475504.51 | K13: 492795.29 | L13: 510014.47 | M13: 527193.66 | N13: 544363.63 | O13: 561554.04 | P13: 578793.25 | Q13: 596108.19 | R13: 613524.43 | S13: 631066.12 | T13: 648756.12 | U13: 666616.07 | V13: 684666.49 | W13: 702926.85 | X13: 721415.72 | Y13: 740150.83 | Z13: 759149.18 | AA13: 778427.13 | AB13: 798000.48 | AC13: 817884.53 | AD13: 838094.2 | AE13: 858644.01 | AF13: 879548.22 | AG13: 900820.85 | AH13: 922475.72 | AI13: 944526.48 | AJ13: 966986.72 | AK13: 989869.93 | AL13: 1013189.5 | AM13: 1036959 | AN13: 1061191.9 | AO13: 1085901.5 | AP13: 1111101.6 | AQ13: 1136805.8
... A54: 公共管理、社会保障和社会组织 | B54: 36437.514 | C54: 47083.393 | D54: 42219.521 | E54: 47061.047 | F54: 52204.852 | G54: 57619.809 | H54: 63377.017 | I54: 69405.888 | J54: 75717.926 | K54: 82332.301 | L54: 89197.261 | M54: 96341.219 | N54: 103757.67 | O54: 111411.59 | P54: 119335.05 | Q54: 127495.17 | R54: 135880.87 | S54: 144525.05 | T54: 153377.92 | U54: 162492.19 | V54: 171830.33 | W54: 181366.46 | X54: 191147.68 | Y54: 201155.59 | Z54: 211375.57 | AA54: 221807.69 | AB54: 232472.87 | AC54: 243374.16 | AD54: 254483.62 | AE54: 265805.52 | AF54: 277394 | AG54: 289193.58 | AH54: 301227.88 | AI54: 313522.63 | AJ54: 326052.92 | AK54: 338853.95 | AL54: 351931.78 | AM54: 365296.96 | AN54: 378965.84 | AO54: 392949.56 | AP54: 407272.04 | AQ54: 421942.91

Sheet About
A1: BPCiObIC BAU Percent Change in Output by ISIC Code
A3: Source:
B5: 2020年全国投入产出表
B6: 国家统计局
B7: 2020
B8: https://data.stats.gov.cn/files/html/quickSearch/trcc/trcc01.html
A10: Notes
A11: “2020年全国投入产出表”是根据我国2020年全年投入产出表中竞争型和非竞争型两张表结合美国EPS模型总结出来42个部门的投入产出表。政府消费支出是根据“2020年全国投入产出表”中各行业政府消费支出数额乘以当年2020年人民币相对2012美元的汇率得出。
A12: 默认分行业产出年变化率即为分行业工业增加值年变化率。先将分行业工业增加值拆分合并至EPS中42行业，再计算其年变化率即可。

Sheet 分行业工业增加值（2012年美元）
A1: 全国 | B1: 2019 | C1: 2020 | D1: 2021 | E1: 2022 | F1: 2023 | G1: 2024 | H1: 2025 | I1: 2026 | J1: 2027 | K1: 2028 | L1: 2029 | M1: 2030 | N1: 2031 | O1: 2032 | P1: 2033 | Q1: 2034 | R1: 2035 | S1: 2036 | T1: 2037 | U1: 2038 | V1: 2039 | W1: 2040 | X1: 2041 | Y1: 2042 | Z1: 2043 | AA1: 2044 | AB1: 2045 | AC1: 2046 | AD1: 2047 | AE1: 2048 | AF1: 2049 | AG1: 2050 | AH1: 2051 | AI1: 2052 | AJ1: 2053 | AK1: 2054 | AL1: 2055 | AM1: 2056 | AN1: 2057 | AO1: 2058 | AP1: 2059 | AQ1: 2060 | AR1: 100000000
A2: 地区生产总值 | B2: =('分行业工业增加值（当年人民币）'!B2*汇率!$B$2)*100000000 -> 1.3606245e+13 | C2: =('分行业工业增加值（当年人民币）'!C2*汇率!$C$2)*100000000 -> 1.4881891e+13 | D2: =('分行业工业增加值（当年人民币）'!D2*汇率!$D$2)*100000000 -> 1.5748845e+13 | E2: =('分行业工业增加值（当年人民币）'!E2*汇率!$E$2)*100000000 -> 16617161179164 | F2: =('分行业工业增加值（当年人民币）'!F2*汇率!$F$2)*100000000 -> 17486803562025 | G2: =('分行业工业增加值（当年人民币）'!G2*汇率!$G$2)*100000000 -> 1.8349298e+13 | H2: =('分行业工业增加值（当年人民币）'!H2*汇率!$H$2)*100000000 -> 1.9216667e+13 | I2: =('分行业工业增加值（当年人民币）'!I2*汇率!$I$2)*100000000 -> 2.0077717e+13 | J2: =('分行业工业增加值（当年人民币）'!J2*汇率!$J$2)*100000000 -> 2.0932939e+13 | K2: =('分行业工业增加值（当年人民币）'!K2*汇率!$K$2)*100000000 -> 2.178764e+13 | L2: =('分行业工业增加值（当年人民币）'!L2*汇率!$L$2)*100000000 -> 2.2632212e+13 | M2: =('分行业工业增加值（当年人民币）'!M2*汇率!$M$2)*100000000 -> 2.3472086e+13 | N2: =('分行业工业增加值（当年人民币）'!N2*汇率!$N$2)*100000000 -> 2.4305877e+13 | O2: =('分行业工业增加值（当年人民币）'!O2*汇率!$O$2)*100000000 -> 2.5128242e+13 | P2: =('分行业工业增加值（当年人民币）'!P2*汇率!$P$2)*100000000 -> 2.5945644e+13 | Q2: =('分行业工业增加值（当年人民币）'!Q2*汇率!$Q$2)*100000000 -> 2.6753116e+13 | R2: =('分行业工业增加值（当年人民币）'!R2*汇率!$R$2)*100000000 -> 2.7548045e+13 | S2: =('分行业工业增加值（当年人民币）'!S2*汇率!$S$2)*100000000 -> 2.8337528e+13 | T2: =('分行业工业增加值（当年人民币）'!T2*汇率!$T$2)*100000000 -> 2.9114301e+13 | U2: =('分行业工业增加值（当年人民币）'!U2*汇率!$U$2)*100000000 -> 29884560304797 | V2: =('分行业工业增加值（当年人民币）'!V2*汇率!$V$2)*100000000 -> 3.0643985e+13 | W2: =('分行业工业增加值（当年人民币）'!W2*汇率!$W$2)*100000000 -> 3.1390277e+13 | X2: =('分行业工业增加值（当年人民币）'!X2*汇率!$X$2)*100000000 -> 3.2129e+13 | Y2: =('分行业工业增加值（当年人民币）'!Y2*汇率!$Y$2)*100000000 -> 3.2857524e+13 | Z2: =('分行业工业增加值（当年人民币）'!Z2*汇率!$Z$2)*100000000 -> 3.3574853e+13 | AA2: =('分行业工业增加值（当年人民币）'!AA2*汇率!$AA$2)*100000000 -> 3.4281857e+13 | AB2: =('分行业工业增加值（当年人民币）'!AB2*汇率!$AB$2)*100000000 -> 3.497916e+13 | AC2: =('分行业工业增加值（当年人民币）'!AC2*汇率!$AC$2)*100000000 -> 3.5668353e+13 | AD2: =('分行业工业增加值（当年人民币）'!AD2*汇率!$AD$2)*100000000 -> 3.6346032e+13 | AE2: =('分行业工业增加值（当年人民币）'!AE2*汇率!$AE$2)*100000000 -> 3.701277e+13 | AF2: =('分行业工业增加值（当年人民币）'!AF2*汇率!$AF$2)*100000000 -> 37674235192435 | AG2: =('分行业工业增加值（当年人民币）'!AG2*汇率!$AG$2)*100000000 -> 3.8324231e+13 | AH2: =('分行业工业增加值（当年人民币）'!AH2*汇率!$AH$2)*100000000 -> 3.8966124e+13 | AI2: =('分行业工业增加值（当年人民币）'!AI2*汇率!$AI$2)*100000000 -> 3.9600141e+13 | AJ2: =('分行业工业增加值（当年人民币）'!AJ2*汇率!$AJ$2)*100000000 -> 4.02245e+13 | AK2: =('分行业工业增加值（当年人民币）'!AK2*汇率!$AK$2)*100000000 -> 4.0843378e+13 | AL2: =('分行业工业增加值（当年人民币）'!AL2*汇率!$AL$2)*100000000 -> 4.1454889e+13 | AM2: =('分行业工业增加值（当年人民币）'!AM2*汇率!$AM$2)*100000000 -> 4.2060077e+13 | AN2: =('分行业工业增加值（当年人民币）'!AN2*汇率!$AN$2)*100000000 -> 4.2659694e+13 | AO2: =('分行业工业增加值（当年人民币）'!AO2*汇率!$AO$2)*100000000 -> 4.3253227e+13 | AP2: =('分行业工业增加值（当年人民币）'!AP2*汇率!$AP$2)*100000000 -> 4.3843545e+13 | AQ2: =('分行业工业增加值（当年人民币）'!AQ2*汇率!$AQ$2)*100000000 -> 4.4428839e+13
A3: 农业 | B3: =('分行业工业增加值（当年人民币）'!B3*汇率!$B$2)*100000000 -> 1.0191215e+12 | C3: =('分行业工业增加值（当年人民币）'!C3*汇率!$C$2)*100000000 -> 1.1161281e+12 | D3: =('分行业工业增加值（当年人民币）'!D3*汇率!$D$2)*100000000 -> 1.1687593e+12 | E3: =('分行业工业增加值（当年人民币）'!E3*汇率!$E$2)*100000000 -> 1.2132055e+12 | F3: =('分行业工业增加值（当年人民币）'!F3*汇率!$F$2)*100000000 -> 1.2567896e+12 | G3: =('分行业工业增加值（当年人民币）'!G3*汇率!$G$2)*100000000 -> 1.2992424e+12 | H3: =('分行业工业增加值（当年人民币）'!H3*汇率!$H$2)*100000000 -> 1.3414628e+12 | I3: =('分行业工业增加值（当年人民币）'!I3*汇率!$I$2)*100000000 -> 1.3826182e+12 | J3: =('分行业工业增加值（当年人民币）'!J3*汇率!$J$2)*100000000 -> 1.4228716e+12 | K3: =('分行业工业增加值（当年人民币）'!K3*汇率!$K$2)*100000000 -> 1.4624476e+12 | L3: =('分行业工业增加值（当年人民币）'!L3*汇率!$L$2)*100000000 -> 1.5009707e+12 | M3: =('分行业工业增加值（当年人民币）'!M3*汇率!$M$2)*100000000 -> 1.5389234e+12 | N3: =('分行业工业增加值（当年人民币）'!N3*汇率!$N$2)*100000000 -> 1.5758637e+12 | O3: =('分行业工业增加值（当年人民币）'!O3*汇率!$O$2)*100000000 -> 1.6116736e+12 | P3: =('分行业工业增加值（当年人民币）'!P3*汇率!$P$2)*100000000 -> 1.6468109e+12 | Q3: =('分行业工业增加值（当年人民币）'!Q3*汇率!$Q$2)*100000000 -> 1.6809211e+12 | R3: =('分行业工业增加值（当年人民币）'!R3*汇率!$R$2)*100000000 -> 1.7139002e+12 | S3: =('分行业工业增加值（当年人民币）'!S3*汇率!$S$2)*100000000 -> 1.7460482e+12 | T3: =('分行业工业增加值（当年人民币）'!T3*汇率!$T$2)*100000000 -> 1.7771317e+12 | U3: =('分行业工业增加值（当年人民币）'!U3*汇率!$U$2)*100000000 -> 1.8075842e+12 | V3: =('分行业工业增加值（当年人民币）'!V3*汇率!$V$2)*100000000 -> 1.8369899e+12 | W3: =('分行业工业增加值（当年人民币）'!W3*汇率!$W$2)*100000000 -> 1.8652715e+12 | X3: =('分行业工业增加值（当年人民币）'!X3*汇率!$X$2)*100000000 -> 1.8928163e+12 | Y3: =('分行业工业增加值（当年人民币）'!Y3*汇率!$Y$2)*100000000 -> 1.9194458e+12 | Z3: =('分行业工业增加值（当年人民币）'!Z3*汇率!$Z$2)*100000000 -> 1.9451008e+12 | AA3: =('分行业工业增加值（当年人民币）'!AA3*汇率!$AA$2)*100000000 -> 1.9698629e+12 | AB3: =('分行业工业增加值（当年人民币）'!AB3*汇率!$AB$2)*100000000 -> 1.9938083e+12 | AC3: =('分行业工业增加值（当年人民币）'!AC3*汇率!$AC$2)*100000000 -> 2.0170974e+12 | AD3: =('分行业工业增加值（当年人民币）'!AD3*汇率!$AD$2)*100000000 -> 2.039503e+12 | AE3: =('分行业工业增加值（当年人民币）'!AE3*汇率!$AE$2)*100000000 -> 2.0610896e+12 | AF3: =('分行业工业增加值（当年人民币）'!AF3*汇率!$AF$2)*100000000 -> 2.0821856e+12 | AG3: =('分行业工业增加值（当年人民币）'!AG3*汇率!$AG$2)*100000000 -> 2.1024632e+12 | AH3: =('分行业工业增加值（当年人民币）'!AH3*汇率!$AH$2)*100000000 -> 2.1221749e+12 | AI3: =('分行业工业增加值（当年人民币）'!AI3*汇率!$AI$2)*100000000 -> 2.1413671e+12 | AJ3: =('分行业工业增加值（当年人民币）'!AJ3*汇率!$AJ$2)*100000000 -> 2.1599393e+12 | AK3: =('分行业工业增加值（当年人民币）'!AK3*汇率!$AK$2)*100000000 -> 2.1781187e+12 | AL3: =('分行业工业增加值（当年人民币）'!AL3*汇率!$AL$2)*100000000 -> 2.1959416e+12 | AM3: =('分行业工业增加值（当年人民币）'!AM3*汇率!$AM$2)*100000000 -> 2.2134641e+12 | AN3: =('分行业工业增加值（当年人民币）'!AN3*汇率!$AN$2)*100000000 -> 2.2307766e+12 | AO3: =('分行业工业增加值（当年人民币）'!AO3*汇率!$AO$2)*100000000 -> 2.2478597e+12 | AP3: =('分行业工业增加值（当年人民币）'!AP3*汇率!$AP$2)*100000000 -> 2.2649332e+12 | AQ3: =('分行业工业增加值（当年人民币）'!AQ3*汇率!$AQ$2)*100000000 -> 2.2819627e+12
A4: 工业 | B4: =('分行业工业增加值（当年人民币）'!B4*汇率!$B$2)*100000000 -> 4.3273675e+12 | C4: =('分行业工业增加值（当年人民币）'!C4*汇率!$C$2)*100000000 -> 4.3066258e+12 | D4: =('分行业工业增加值（当年人民币）'!D4*汇率!$D$2)*100000000 -> 4.9641751e+12 | E4: =('分行业工业增加值（当年人民币）'!E4*汇率!$E$2)*100000000 -> 5.098886e+12 | F4: =('分行业工业增加值（当年人民币）'!F4*汇率!$F$2)*100000000 -> 5.222535e+12 | G4: =('分行业工业增加值（当年人民币）'!G4*汇率!$G$2)*100000000 -> 5.3357926e+12 | H4: =('分行业工业增加值（当年人民币）'!H4*汇率!$H$2)*100000000 -> 5.4393831e+12 | I4: =('分行业工业增加值（当年人民币）'!I4*汇率!$I$2)*100000000 -> 5.5340487e+12 | J4: =('分行业工业增加值（当年人民币）'!J4*汇率!$J$2)*100000000 -> 5.6205229e+12 | K4: =('分行业工业增加值（当年人民币）'!K4*汇率!$K$2)*100000000 -> 5.6995128e+12 | L4: =('分行业工业增加值（当年人民币）'!L4*汇率!$L$2)*100000000 -> 5.7716873e+12 | M4: =('分行业工业增加值（当年人民币）'!M4*汇率!$M$2)*100000000 -> 5.8376704e+12 | N4: =('分行业工业增加值（当年人民币）'!N4*汇率!$N$2)*100000000 -> 5.8980385e+12 | O4: =('分行业工业增加值（当年人民币）'!O4*汇率!$O$2)*100000000 -> 5.9533191e+12 | P4: =('分行业工业增加值（当年人民币）'!P4*汇率!$P$2)*100000000 -> 6.0039928e+12 | Q4: =('分行业工业增加值（当年人民币）'!Q4*汇率!$Q$2)*100000000 -> 6.050495e+12 | R4: =('分行业工业增加值（当年人民币）'!R4*汇率!$R$2)*100000000 -> 6.0932188e+12 | S4: =('分行业工业增加值（当年人民币）'!S4*汇率!$S$2)*100000000 -> 6.1325187e+12 | T4: =('分行业工业增加值（当年人民币）'!T4*汇率!$T$2)*100000000 -> 6.1687134e+12 | U4: =('分行业工业增加值（当年人民币）'!U4*汇率!$U$2)*100000000 -> 6.2020893e+12 | V4: =('分行业工业增加值（当年人民币）'!V4*汇率!$V$2)*100000000 -> 6.2329036e+12 | W4: =('分行业工业增加值（当年人民币）'!W4*汇率!$W$2)*100000000 -> 6.2613874e+12 | X4: =('分行业工业增加值（当年人民币）'!X4*汇率!$X$2)*100000000 -> 6.2877482e+12 | Y4: =('分行业工业增加值（当年人民币）'!Y4*汇率!$Y$2)*100000000 -> 6.3121728e+12 | Z4: =('分行业工业增加值（当年人民币）'!Z4*汇率!$Z$2)*100000000 -> 6.3348287e+12 | AA4: =('分行业工业增加值（当年人民币）'!AA4*汇率!$AA$2)*100000000 -> 6.3558673e+12 | AB4: =('分行业工业增加值（当年人民币）'!AB4*汇率!$AB$2)*100000000 -> 6.3754245e+12 | AC4: =('分行业工业增加值（当年人民币）'!AC4*汇率!$AC$2)*100000000 -> 6.3936235e+12 | AD4: =('分行业工业增加值（当年人民币）'!AD4*汇率!$AD$2)*100000000 -> 6.4105752e+12 | AE4: =('分行业工业增加值（当年人民币）'!AE4*汇率!$AE$2)*100000000 -> 6.4263802e+12 | AF4: =('分行业工业增加值（当年人民币）'!AF4*汇率!$AF$2)*100000000 -> 6.4411295e+12 | AG4: =('分行业工业增加值（当年人民币）'!AG4*汇率!$AG$2)*100000000 -> 6.4549058e+12 | AH4: =('分行业工业增加值（当年人民币）'!AH4*汇率!$AH$2)*100000000 -> 6.4677843e+12 | AI4: =('分行业工业增加值（当年人民币）'!AI4*汇率!$AI$2)*100000000 -> 6.4798332e+12 | AJ4: =('分行业工业增加值（当年人民币）'!AJ4*汇率!$AJ$2)*100000000 -> 6.491115e+12 | AK4: =('分行业工业增加值（当年人民币）'!AK4*汇率!$AK$2)*100000000 -> 6.5016865e+12 | AL4: =('分行业工业增加值（当年人民币）'!AL4*汇率!$AL$2)*100000000 -> 6.5115998e+12 | AM4: =('分行业工业增加值（当年人民币）'!AM4*汇率!$AM$2)*100000000 -> 6.5209025e+12 | AN4: =('分行业工业增加值（当年人民币）'!AN4*汇率!$AN$2)*100000000 -> 6.5296382e+12 | AO4: =('分行业工业增加值（当年人民币）'!AO4*汇率!$AO$2)*100000000 -> 6.537847e+12 | AP4: =('分行业工业增加值（当年人民币）'!AP4*汇率!$AP$2)*100000000 -> 6.5455659e+12 | AQ4: =('分行业工业增加值（当年人民币）'!AQ4*汇率!$AQ$2)*100000000 -> 6.5528286e+12
A5: 建筑业 | B5: =('分行业工业增加值（当年人民币）'!B5*汇率!$B$2)*100000000 -> 9.7807096e+11 | C5: =('分行业工业增加值（当年人民币）'!C5*汇率!$C$2)*100000000 -> 1.0052436e+12 | D5: =('分行业工业增加值（当年人民币）'!D5*汇率!$D$2)*100000000 -> 1.0784823e+12 | E5: =('分行业工业增加值（当年人民币）'!E5*汇率!$E$2)*100000000 -> 1.1331388e+12 | F5: =('分行业工业增加值（当年人民币）'!F5*汇率!$F$2)*100000000 -> 1.1879314e+12 | G5: =('分行业工业增加值（当年人民币）'!G5*汇率!$G$2)*100000000 -> 1.2423347e+12 | H5: =('分行业工业增加值（当年人民币）'!H5*汇率!$H$2)*100000000 -> 1.2971166e+12 | I5: =('分行业工业增加值（当年人民币）'!I5*汇率!$I$2)*100000000 -> 1.3515139e+12 | J5: =('分行业工业增加值（当年人民币）'!J5*汇率!$J$2)*100000000 -> 1.4056901e+12 | K5: =('分行业工业增加值（当年人民币）'!K5*汇率!$K$2)*100000000 -> 1.4598036e+12 | L5: =('分行业工业增加值（当年人民币）'!L5*汇率!$L$2)*100000000 -> 1.5133508e+12 | M5: =('分行业工业增加值（当年人民币）'!M5*汇率!$M$2)*100000000 -> 1.566773e+12 | N5: =('分行业工业增加值（当年人民币）'!N5*汇率!$N$2)*100000000 -> 1.6197826e+12 | O5: =('分行业工业增加值（当年人民币）'!O5*汇率!$O$2)*100000000 -> 1.6720842e+12 | P5: =('分行业工业增加值（当年人民币）'!P5*汇率!$P$2)*100000000 -> 1.724151e+12 | Q5: =('分行业工业增加值（当年人民币）'!Q5*汇率!$Q$2)*100000000 -> 1.7756355e+12 | R5: =('分行业工业增加值（当年人民币）'!R5*汇率!$R$2)*100000000 -> 1.8263734e+12 | S5: =('分行业工业增加值（当年人民币）'!S5*汇率!$S$2)*100000000 -> 1.8766908e+12 | T5: =('分行业工业增加值（当年人民币）'!T5*汇率!$T$2)*100000000 -> 1.9263066e+12 | U5: =('分行业工业增加值（当年人民币）'!U5*汇率!$U$2)*100000000 -> 1.9755112e+12 | V5: =('分行业工业增加值（当年人民币）'!V5*汇率!$V$2)*100000000 -> 2.0239519e+12 | W5: =('分行业工业增加值（当年人民币）'!W5*汇率!$W$2)*100000000 -> 2.0715771e+12 | X5: =('分行业工业增加值（当年人民币）'!X5*汇率!$X$2)*100000000 -> 2.1186679e+12 | Y5: =('分行业工业增加值（当年人民币）'!Y5*汇率!$Y$2)*100000000 -> 2.1650587e+12 | Z5: =('分行业工业增加值（当年人民币）'!Z5*汇率!$Z$2)*100000000 -> 2.2107571e+12 | AA5: =('分行业工业增加值（当年人民币）'!AA5*汇率!$AA$2)*100000000 -> 2.2556831e+12 | AB5: =('分行业工业增加值（当年人民币）'!AB5*汇率!$AB$2)*100000000 -> 2.3000054e+12 | AC5: =('分行业工业增加值（当年人民币）'!AC5*汇率!$AC$2)*100000000 -> 2.3437782e+12 | AD5: =('分行业工业增加值（当年人民币）'!AD5*汇率!$AD$2)*100000000 -> 2.3867645e+12 | AE5: =('分行业工业增加值（当年人民币）'!AE5*汇率!$AE$2)*100000000 -> 2.4290902e+12 | AF5: =('分行业工业增加值（当年人民币）'!AF5*汇率!$AF$2)*100000000 -> 2.4710211e+12 | AG5: =('分行业工业增加值（当年人民币）'!AG5*汇率!$AG$2)*100000000 -> 2.5122898e+12 | AH5: =('分行业工业增加值（当年人民币）'!AH5*汇率!$AH$2)*100000000 -> 2.5531041e+12 | AI5: =('分行业工业增加值（当年人民币）'!AI5*汇率!$AI$2)*100000000 -> 2.5934746e+12 | AJ5: =('分行业工业增加值（当年人民币）'!AJ5*汇率!$AJ$2)*100000000 -> 2.6333995e+12 | AK5: =('分行业工业增加值（当年人民币）'!AK5*汇率!$AK$2)*100000000 -> 2.6730582e+12 | AL5: =('分行业工业增加值（当年人民币）'!AL5*汇率!$AL$2)*100000000 -> 2.7125141e+12 | AM5: =('分行业工业增加值（当年人民币）'!AM5*汇率!$AM$2)*100000000 -> 2.7518936e+12 | AN5: =('分行业工业增加值（当年人民币）'!AN5*汇率!$AN$2)*100000000 -> 2.7911755e+12 | AO5: =('分行业工业增加值（当年人民币）'!AO5*汇率!$AO$2)*100000000 -> 2.8305465e+12 | AP5: =('分行业工业增加值（当年人民币）'!AP5*汇率!$AP$2)*100000000 -> 2.8701774e+12 | AQ5: =('分行业工业增加值（当年人民币）'!AQ5*汇率!$AQ$2)*100000000 -> 2.9100658e+12
A6: 交运仓邮 | B6: =('分行业工业增加值（当年人民币）'!B6*汇率!$B$2)*100000000 -> 5.9355954e+11 | C6: =('分行业工业增加值（当年人民币）'!C6*汇率!$C$2)*100000000 -> 5.724933e+11 | D6: =('分行业工业增加值（当年人民币）'!D6*汇率!$D$2)*100000000 -> 6.296468e+11 | E6: =('分行业工业增加值（当年人民币）'!E6*汇率!$E$2)*100000000 -> 6.5329309e+11 | F6: =('分行业工业增加值（当年人民币）'!F6*汇率!$F$2)*100000000 -> 6.7641094e+11 | G6: =('分行业工业增加值（当年人民币）'!G6*汇率!$G$2)*100000000 -> 6.988427e+11 | H6: =('分行业工业增加值（当年人民币）'!H6*汇率!$H$2)*100000000 -> 7.2098339e+11 | I6: =('分行业工业增加值（当年人民币）'!I6*汇率!$I$2)*100000000 -> 7.4252917e+11 | J6: =('分行业工业增加值（当年人民币）'!J6*汇率!$J$2)*100000000 -> 7.6347514e+11 | K6: =('分行业工业增加值（当年人民币）'!K6*汇率!$K$2)*100000000 -> 7.8400382e+11 | L6: =('分行业工业增加值（当年人民币）'!L6*汇率!$L$2)*100000000 -> 8.0389026e+11 | M6: =('分行业工业增加值（当年人民币）'!M6*汇率!$M$2)*100000000 -> 8.2328668e+11 | N6: =('分行业工业增加值（当年人民币）'!N6*汇率!$N$2)*100000000 -> 8.4216195e+11 | O6: =('分行业工业增加值（当年人民币）'!O6*汇率!$O$2)*100000000 -> 8.6038055e+11 | P6: =('分行业工业增加值（当年人民币）'!P6*汇率!$P$2)*100000000 -> 8.781363e+11 | Q6: =('分行业工业增加值（当年人民币）'!Q6*汇率!$Q$2)*100000000 -> 8.9534096e+11 | R6: =('分行业工业增加值（当年人民币）'!R6*汇率!$R$2)*100000000 -> 9.1193031e+11 | S6: =('分行业工业增加值（当年人民币）'!S6*汇率!$S$2)*100000000 -> 9.2807442e+11 | T6: =('分行业工业增加值（当年人民币）'!T6*汇率!$T$2)*100000000 -> 9.436056e+11 | U6: =('分行业工业增加值（当年人民币）'!U6*汇率!$U$2)*100000000 -> 9.5873263e+11 | V6: =('分行业工业增加值（当年人民币）'!V6*汇率!$V$2)*100000000 -> 9.7333368e+11 | W6: =('分行业工业增加值（当年人民币）'!W6*汇率!$W$2)*100000000 -> 9.87304e+11 | X6: =('分行业工业增加值（当年人民币）'!X6*汇率!$X$2)*100000000 -> 1.0008753e+12 | Y6: =('分行业工业增加值（当年人民币）'!Y6*汇率!$Y$2)*100000000 -> 1.013994e+12 | Z6: =('分行业工业增加值（当年人民币）'!Z6*汇率!$Z$2)*100000000 -> 1.0265991e+12 | AA6: =('分行业工业增加值（当年人民币）'!AA6*汇率!$AA$2)*100000000 -> 1.038746e+12 | AB6: =('分行业工业增加值（当年人民币）'!AB6*汇率!$AB$2)*100000000 -> 1.0504719e+12 | AC6: =('分行业工业增加值（当年人民币）'!AC6*汇率!$AC$2)*100000000 -> 1.0618006e+12 | AD6: =('分行业工业增加值（当年人民币）'!AD6*汇率!$AD$2)*100000000 -> 1.0726565e+12 | AE6: =('分行业工业增加值（当年人民币）'!AE6*汇率!$AE$2)*100000000 -> 1.0830918e+12 | AF6: =('分行业工业增加值（当年人民币）'!AF6*汇率!$AF$2)*100000000 -> 1.093253e+12 | AG6: =('分行业工业增加值（当年人民币）'!AG6*汇率!$AG$2)*100000000 -> 1.1029781e+12 | AH6: =('分行业工业增加值（当年人民币）'!AH6*汇率!$AH$2)*100000000 -> 1.1123642e+12 | AI6: =('分行业工业增加值（当年人民币）'!AI6*汇率!$AI$2)*100000000 -> 1.121455e+12 | AJ6: =('分行业工业增加值（当年人民币）'!AJ6*汇率!$AJ$2)*100000000 -> 1.1301828e+12 | AK6: =('分行业工业增加值（当年人民币）'!AK6*汇率!$AK$2)*100000000 -> 1.1386689e+12 | AL6: =('分行业工业增加值（当年人民币）'!AL6*汇率!$AL$2)*100000000 -> 1.1468969e+12 | AM6: =('分行业工业增加值（当年人民币）'!AM6*汇率!$AM$2)*100000000 -> 1.1548887e+12 | AN6: =('分行业工业增加值（当年人民币）'!AN6*汇率!$AN$2)*100000000 -> 1.1626814e+12 | AO6: =('分行业工业增加值（当年人民币）'!AO6*汇率!$AO$2)*100000000 -> 1.1702713e+12 | AP6: =('分行业工业增加值（当年人民币）'!AP6*汇率!$AP$2)*100000000 -> 1.1777544e+12 | AQ6: =('分行业工业增加值（当年人民币）'!AQ6*汇率!$AQ$2)*100000000 -> 1.1850783e+12
A7: 批发零售 | B7: =('分行业工业增加值（当年人民币）'!B7*汇率!$B$2)*100000000 -> 1.3177809e+12 | C7: =('分行业工业增加值（当年人民币）'!C7*汇率!$C$2)*100000000 -> 1.3083408e+12 | D7: =('分行业工业增加值（当年人民币）'!D7*汇率!$D$2)*100000000 -> 1.4853343e+12 | E7: =('分行业工业增加值（当年人民币）'!E7*汇率!$E$2)*100000000 -> 1.5661282e+12 | F7: =('分行业工业增加值（当年人民币）'!F7*汇率!$F$2)*100000000 -> 1.6471163e+12 | G7: =('分行业工业增加值（当年人民币）'!G7*汇率!$G$2)*100000000 -> 1.7274492e+12 | H7: =('分行业工业增加值（当年人民币）'!H7*汇率!$H$2)*100000000 -> 1.8081074e+12 | I7: =('分行业工业增加值（当年人民币）'!I7*汇率!$I$2)*100000000 -> 1.8882553e+12 | J7: =('分行业工业增加值（当年人民币）'!J7*汇率!$J$2)*100000000 -> 1.9677725e+12 | K7: =('分行业工业增加值（当年人民币）'!K7*汇率!$K$2)*100000000 -> 2.0473566e+12 | L7: =('分行业工业增加值（当年人民币）'!L7*汇率!$L$2)*100000000 -> 2.1259887e+12 | M7: =('分行业工业增加值（当年人民币）'!M7*汇率!$M$2)*100000000 -> 2.2041136e+12 | N7: =('分行业工业增加值（当年人民币）'!N7*汇率!$N$2)*100000000 -> 2.2818081e+12 | O7: =('分行业工业增加值（当年人民币）'!O7*汇率!$O$2)*100000000 -> 2.3583752e+12 | P7: =('分行业工业增加值（当年人民币）'!P7*汇率!$P$2)*100000000 -> 2.4345134e+12 | Q7: =('分行业工业增加值（当年人民币）'!Q7*汇率!$Q$2)*100000000 -> 2.5097842e+12 | R7: =('分行业工业增加值（当年人民币）'!R7*汇率!$R$2)*100000000 -> 2.5838353e+12 | S7: =('分行业工业增加值（当年人民币）'!S7*汇率!$S$2)*100000000 -> 2.657471e+12 | T7: =('分行业工业增加值（当年人民币）'!T7*汇率!$T$2)*100000000 -> 2.7299528e+12 | U7: =('分行业工业增加值（当年人民币）'!U7*汇率!$U$2)*100000000 -> 2.8017873e+12 | V7: =('分行业工业增加值（当年人民币）'!V7*汇率!$V$2)*100000000 -> 2.8727093e+12 | W7: =('分行业工业增加值（当年人民币）'!W7*汇率!$W$2)*100000000 -> 2.9424082e+12 | X7: =('分行业工业增加值（当年人民币）'!X7*汇率!$X$2)*100000000 -> 3.0113997e+12 | Y7: =('分行业工业增加值（当年人民币）'!Y7*汇率!$Y$2)*100000000 -> 3.0794805e+12 | Z7: =('分行业工业增加值（当年人民币）'!Z7*汇率!$Z$2)*100000000 -> 3.1465079e+12 | AA7: =('分行业工业增加值（当年人民币）'!AA7*汇率!$AA$2)*100000000 -> 3.2126388e+12 | AB7: =('分行业工业增加值（当年人民币）'!AB7*汇率!$AB$2)*100000000 -> 3.277872e+12 | AC7: =('分行业工业增加值（当年人民币）'!AC7*汇率!$AC$2)*100000000 -> 3.342311e+12 | AD7: =('分行业工业增加值（当年人民币）'!AD7*汇率!$AD$2)*100000000 -> 3.4057229e+12 | AE7: =('分行业工业增加值（当年人民币）'!AE7*汇率!$AE$2)*100000000 -> 3.4681232e+12 | AF7: =('分行业工业增加值（当年人民币）'!AF7*汇率!$AF$2)*100000000 -> 3.5300899e+12 | AG7: =('分行业工业增加值（当年人民币）'!AG7*汇率!$AG$2)*100000000 -> 3.5909789e+12 | AH7: =('分行业工业增加值（当年人民币）'!AH7*汇率!$AH$2)*100000000 -> 3.6511636e+12 | AI7: =('分行业工业增加值（当年人民币）'!AI7*汇率!$AI$2)*100000000 -> 3.7106509e+12 | AJ7: =('分行业工业增加值（当年人民币）'!AJ7*汇率!$AJ$2)*100000000 -> 3.7692227e+12 | AK7: =('分行业工业增加值（当年人民币）'!AK7*汇率!$AK$2)*100000000 -> 3.8273883e+12 | AL7: =('分行业工业增加值（当年人民币）'!AL7*汇率!$AL$2)*100000000 -> 3.8848876e+12 | AM7: =('分行业工业增加值（当年人民币）'!AM7*汇率!$AM$2)*100000000 -> 3.9418361e+12 | AN7: =('分行业工业增加值（当年人民币）'!AN7*汇率!$AN$2)*100000000 -> 3.9984016e+12 | AO7: =('分行业工业增加值（当年人民币）'!AO7*汇率!$AO$2)*100000000 -> 4.0544419e+12 | AP7: =('分行业工业增加值（当年人民币）'!AP7*汇率!$AP$2)*100000000 -> 4.1103275e+12 | AQ7: =('分行业工业增加值（当年人民币）'!AQ7*汇率!$AQ$2)*100000000 -> 4.165883e+12
A8: 餐饮住宿 | B8: =('分行业工业增加值（当年人民币）'!B8*汇率!$B$2)*100000000 -> 2.4867065e+11 | C8: =('分行业工业增加值（当年人民币）'!C8*汇率!$C$2)*100000000 -> 2.1881089e+11 | D8: =('分行业工业增加值（当年人民币）'!D8*汇率!$D$2)*100000000 -> 2.4002938e+11 | E8: =('分行业工业增加值（当年人民币）'!E8*汇率!$E$2)*100000000 -> 2.5714004e+11 | F8: =('分行业工业增加值（当年人民币）'!F8*汇率!$F$2)*100000000 -> 2.7467229e+11 | G8: =('分行业工业增加值（当年人民币）'!G8*汇率!$G$2)*100000000 -> 2.9247372e+11 | H8: =('分行业工业增加值（当年人民币）'!H8*汇率!$H$2)*100000000 -> 3.1075217e+11 | I8: =('分行业工业增加值（当年人民币）'!I8*汇率!$I$2)*100000000 -> 3.2931024e+11 | J8: =('分行业工业增加值（当年人民币）'!J8*汇率!$J$2)*100000000 -> 3.481447e+11 | K8: =('分行业工业增加值（当年人民币）'!K8*汇率!$K$2)*100000000 -> 3.6734068e+11 | L8: =('分行业工业增加值（当年人民币）'!L8*汇率!$L$2)*100000000 -> 3.867393e+11 | M8: =('分行业工业增加值（当年人民币）'!M8*汇率!$M$2)*100000000 -> 4.0642746e+11 | N8: =('分行业工业增加值（当年人民币）'!N8*汇率!$N$2)*100000000 -> 4.2634334e+11 | O8: =('分行业工业增加值（当年人民币）'!O8*汇率!$O$2)*100000000 -> 4.4637825e+11 | P8: =('分行业工业增加值（当年人民币）'!P8*汇率!$P$2)*100000000 -> 4.6668337e+11 | Q8: =('分行业工业增加值（当年人民币）'!Q8*汇率!$Q$2)*100000000 -> 4.8714535e+11 | R8: =('分行业工业增加值（当年人民币）'!R8*汇率!$R$2)*100000000 -> 5.0765986e+11 | S8: =('分行业工业增加值（当年人民币）'!S8*汇率!$S$2)*100000000 -> 5.2838432e+11 | T8: =('分行业工业增加值（当年人民币）'!T8*汇率!$T$2)*100000000 -> 5.4918577e+11 | U8: =('分行业工业增加值（当年人民币）'!U8*汇率!$U$2)*100000000 -> 5.7016814e+11 | V8: =('分行业工业增加值（当年人民币）'!V8*汇率!$V$2)*100000000 -> 5.9120727e+11 | W8: =('分行业工业增加值（当年人民币）'!W8*汇率!$W$2)*100000000 -> 6.1226371e+11 | X8: =('分行业工业增加值（当年人民币）'!X8*汇率!$X$2)*100000000 -> 6.3344808e+11 | Y8: =('分行业工业增加值（当年人民币）'!Y8*汇率!$Y$2)*100000000 -> 6.5469204e+11 | Z8: =('分行业工业增加值（当年人民币）'!Z8*汇率!$Z$2)*100000000 -> 6.7595806e+11 | AA8: =('分行业工业增加值（当年人民币）'!AA8*汇率!$AA$2)*100000000 -> 6.9724985e+11 | AB8: =('分行业工业增加值（当年人民币）'!AB8*汇率!$AB$2)*100000000 -> 7.1858934e+11 | AC8: =('分行业工业增加值（当年人民币）'!AC8*汇率!$AC$2)*100000000 -> 7.4000953e+11 | AD8: =('分行业工业增加值（当年人民币）'!AD8*汇率!$AD$2)*100000000 -> 7.6144419e+11 | AE8: =('分行业工业增加值（当年人民币）'!AE8*汇率!$AE$2)*100000000 -> 7.8286946e+11 | AF8: =('分行业工业增加值（当年人民币）'!AF8*汇率!$AF$2)*100000000 -> 8.0445042e+11 | AG8: =('分行业工业增加值（当年人民币）'!AG8*汇率!$AG$2)*100000000 -> 8.2603504e+11 | AH8: =('分行业工业增加值（当年人民币）'!AH8*汇率!$AH$2)*100000000 -> 8.4771554e+11 | AI8: =('分行业工业增加值（当年人民币）'!AI8*汇率!$AI$2)*100000000 -> 8.6950257e+11 | AJ8: =('分行业工业增加值（当年人民币）'!AJ8*汇率!$AJ$2)*100000000 -> 8.9134941e+11 | AK8: =('分行业工业增加值（当年人民币）'!AK8*汇率!$AK$2)*100000000 -> 9.1337788e+11 | AL8: =('分行业工业增加值（当年人民币）'!AL8*汇率!$AL$2)*100000000 -> 9.3558376e+11 | AM8: =('分行业工业增加值（当年人民币）'!AM8*汇率!$AM$2)*100000000 -> 9.5799265e+11 | AN8: =('分行业工业增加值（当年人民币）'!AN8*汇率!$AN$2)*100000000 -> 9.806664e+11 | AO8: =('分行业工业增加值（当年人民币）'!AO8*汇率!$AO$2)*100000000 -> 1.003597e+12 | AP8: =('分行业工业增加值（当年人民币）'!AP8*汇率!$AP$2)*100000000 -> 1.0269069e+12 | AQ8: =('分行业工业增加值（当年人民币）'!AQ8*汇率!$AQ$2)*100000000 -> 1.050618e+12
A9: 金融业 | B9: =('分行业工业增加值（当年人民币）'!B9*汇率!$B$2)*100000000 -> 1.0622664e+12 | C9: =('分行业工业增加值（当年人民币）'!C9*汇率!$C$2)*100000000 -> 1.1601268e+12 | D9: =('分行业工业增加值（当年人民币）'!D9*汇率!$D$2)*100000000 -> 1.2267773e+12 | E9: =('分行业工业增加值（当年人民币）'!E9*汇率!$E$2)*100000000 -> 1.3301357e+12 | F9: =('分行业工业增加值（当年人民币）'!F9*汇率!$F$2)*100000000 -> 1.4371787e+12 | G9: =('分行业工业增加值（当年人民币）'!G9*汇率!$G$2)*100000000 -> 1.5466565e+12 | H9: =('分行业工业增加值（当年人民币）'!H9*汇率!$H$2)*100000000 -> 1.6598674e+12 | I9: =('分行业工业增加值（当年人民币）'!I9*汇率!$I$2)*100000000 -> 1.7757492e+12 | J9: =('分行业工业增加值（当年人民币）'!J9*汇率!$J$2)*100000000 -> 1.8941494e+12 | K9: =('分行业工业增加值（当年人民币）'!K9*汇率!$K$2)*100000000 -> 2.0160142e+12 | L9: =('分行业工业增加值（当年人民币）'!L9*汇率!$L$2)*100000000 -> 2.1398453e+12 | M9: =('分行业工业增加值（当年人民币）'!M9*汇率!$M$2)*100000000 -> 2.2662596e+12 | N9: =('分行业工业增加值（当年人民币）'!N9*汇率!$N$2)*100000000 -> 2.3954402e+12 | O9: =('分行业工业增加值（当年人民币）'!O9*汇率!$O$2)*100000000 -> 2.5264624e+12 | P9: =('分行业工业增加值（当年人民币）'!P9*汇率!$P$2)*100000000 -> 2.6601346e+12 | Q9: =('分行业工业增加值（当年人民币）'!Q9*汇率!$Q$2)*100000000 -> 2.7960193e+12 | R9: =('分行业工业增加值（当年人民币）'!R9*汇率!$R$2)*100000000 -> 2.9334975e+12 | S9: =('分行业工业增加值（当年人民币）'!S9*汇率!$S$2)*100000000 -> 3.0738691e+12 | T9: =('分行业工业增加值（当年人民币）'!T9*汇率!$T$2)*100000000 -> 3.2158353e+12 | U9: =('分行业工业增加值（当年人民币）'!U9*汇率!$U$2)*100000000 -> 3.3602401e+12 | V9: =('分行业工业增加值（当年人民币）'!V9*汇率!$V$2)*100000000 -> 3.5066929e+12 | W9: =('分行业工业增加值（当年人民币）'!W9*汇率!$W$2)*100000000 -> 3.6547003e+12 | X9: =('分行业工业增加值（当年人民币）'!X9*汇率!$X$2)*100000000 -> 3.8050493e+12 | Y9: =('分行业工业增加值（当年人民币）'!Y9*汇率!$Y$2)*100000000 -> 3.957474e+12 | Z9: =('分行业工业增加值（当年人民币）'!Z9*汇率!$Z$2)*100000000 -> 4.1116148e+12 | AA9: =('分行业工业增加值（当年人民币）'!AA9*汇率!$AA$2)*100000000 -> 4.2678906e+12 | AB9: =('分行业工业增加值（当年人民币）'!AB9*汇率!$AB$2)*100000000 -> 4.4260671e+12 | AC9: =('分行业工业增加值（当年人民币）'!AC9*汇率!$AC$2)*100000000 -> 4.5865307e+12 | AD9: =('分行业工业增加值（当年人民币）'!AD9*汇率!$AD$2)*100000000 -> 4.7487049e+12 | AE9: =('分行业工业增加值（当年人民币）'!AE9*汇率!$AE$2)*100000000 -> 4.9124877e+12 | AF9: =('分行业工业增加值（当年人民币）'!AF9*汇率!$AF$2)*100000000 -> 5.0790204e+12 | AG9: =('分行业工业增加值（当年人民币）'!AG9*汇率!$AG$2)*100000000 -> 5.2469497e+12 | AH9: =('分行业工业增加值（当年人民币）'!AH9*汇率!$AH$2)*100000000 -> 5.4168409e+12 | AI9: =('分行业工业增加值（当年人民币）'!AI9*汇率!$AI$2)*100000000 -> 5.5887063e+12 | AJ9: =('分行业工业增加值（当年人民币）'!AJ9*汇率!$AJ$2)*100000000 -> 5.7620075e+12 | AK9: =('分行业工业增加值（当年人民币）'!AK9*汇率!$AK$2)*100000000 -> 5.9375825e+12 | AL9: =('分行业工业增加值（当年人民币）'!AL9*汇率!$AL$2)*100000000 -> 6.1146845e+12 | AM9: =('分行业工业增加值（当年人民币）'!AM9*汇率!$AM$2)*100000000 -> 6.2933895e+12 | AN9: =('分行业工业增加值（当年人民币）'!AN9*汇率!$AN$2)*100000000 -> 6.4737889e+12 | AO9: =('分行业工业增加值（当年人民币）'!AO9*汇率!$AO$2)*100000000 -> 6.6554304e+12 | AP9: =('分行业工业增加值（当年人民币）'!AP9*汇率!$AP$2)*100000000 -> 6.8389275e+12 | AQ9: =('分行业工业增加值（当年人民币）'!AQ9*汇率!$AQ$2)*100000000 -> 7.0233092e+12
A10: 房地产 | B10: =('分行业工业增加值（当年人民币）'!B10*汇率!$B$2)*100000000 -> 9.6177372e+11 | C10: =('分行业工业增加值（当年人民币）'!C10*汇率!$C$2)*100000000 -> 1.0261541e+12 | D10: =('分行业工业增加值（当年人民币）'!D10*汇率!$D$2)*100000000 -> 1.0440494e+12 | E10: =('分行业工业增加值（当年人民币）'!E10*汇率!$E$2)*100000000 -> 1.1020725e+12 | F10: =('分行业工业增加值（当年人民币）'!F10*汇率!$F$2)*100000000 -> 1.1605847e+12 | G10: =('分行业工业增加值（当年人民币）'!G10*汇率!$G$2)*100000000 -> 1.2190647e+12 | H10: =('分行业工业增加值（当年人民币）'!H10*汇率!$H$2)*100000000 -> 1.2783021e+12 | I10: =('分行业工业增加值（当年人民币）'!I10*汇率!$I$2)*100000000 -> 1.3376627e+12 | J10: =('分行业工业增加值（当年人民币）'!J10*汇率!$J$2)*100000000 -> 1.3970986e+12 | K10: =('分行业工业增加值（当年人民币）'!K10*汇率!$K$2)*100000000 -> 1.456898e+12 | L10: =('分行业工业增加值（当年人民币）'!L10*汇率!$L$2)*100000000 -> 1.5164988e+12 | M10: =('分行业工业增加值（当年人民币）'!M10*汇率!$M$2)*100000000 -> 1.5762076e+12 | N10: =('分行业工业增加值（当年人民币）'!N10*汇率!$N$2)*100000000 -> 1.6359821e+12 | O10: =('分行业工业增加值（当年人民币）'!O10*汇率!$O$2)*100000000 -> 1.6954171e+12 | P10: =('分行业工业增加值（当年人民币）'!P10*汇率!$P$2)*100000000 -> 1.754898e+12 | Q10: =('分行业工业增加值（当年人民币）'!Q10*汇率!$Q$2)*100000000 -> 1.8141417e+12 | R10: =('分行业工业增加值（当年人民币）'!R10*汇率!$R$2)*100000000 -> 1.8729868e+12 | S10: =('分行业工业增加值（当年人民币）'!S10*汇率!$S$2)*100000000 -> 1.9317985e+12 | T10: =('分行业工业增加值（当年人民币）'!T10*汇率!$T$2)*100000000 -> 1.9901264e+12 | U10: =('分行业工业增加值（当年人民币）'!U10*汇率!$U$2)*100000000 -> 2.0483389e+12 | V10: =('分行业工业增加值（当年人民币）'!V10*汇率!$V$2)*100000000 -> 2.1062215e+12 | W10: =('分行业工业增加值（当年人民币）'!W10*汇率!$W$2)*100000000 -> 2.1635203e+12 | X10: =('分行业工业增加值（当年人民币）'!X10*汇率!$X$2)*100000000 -> 2.2206081e+12 | Y10: =('分行业工业增加值（当年人民币）'!Y10*汇率!$Y$2)*100000000 -> 2.2773241e+12 | Z10: =('分行业工业增加值（当年人民币）'!Z10*汇率!$Z$2)*100000000 -> 2.3335745e+12 | AA10: =('分行业工业增加值（当年人民币）'!AA10*汇率!$AA$2)*100000000 -> 2.3894024e+12 | AB10: =('分行业工业增加值（当年人民币）'!AB10*汇率!$AB$2)*100000000 -> 2.444862e+12 | AC10: =('分行业工业增加值（当年人民币）'!AC10*汇率!$AC$2)*100000000 -> 2.5000321e+12 | AD10: =('分行业工业增加值（当年人民币）'!AD10*汇率!$AD$2)*100000000 -> 2.5546564e+12 | AE10: =('分行业工业增加值（当年人民币）'!AE10*汇率!$AE$2)*100000000 -> 2.608869e+12 | AF10: =('分行业工业增加值（当年人民币）'!AF10*汇率!$AF$2)*100000000 -> 2.6629876e+12 | AG10: =('分行业工业增加值（当年人民币）'!AG10*汇率!$AG$2)*100000000 -> 2.7165973e+12 | AH10: =('分行业工业增加值（当年人民币）'!AH10*汇率!$AH$2)*100000000 -> 2.7699419e+12 | AI10: =('分行业工业增加值（当年人民币）'!AI10*汇率!$AI$2)*100000000 -> 2.8230871e+12 | AJ10: =('分行业工业增加值（当年人民币）'!AJ10*汇率!$AJ$2)*100000000 -> 2.8759114e+12 | AK10: =('分行业工业增加值（当年人民币）'!AK10*汇率!$AK$2)*100000000 -> 2.9287079e+12 | AL10: =('分行业工业增加值（当年人民币）'!AL10*汇率!$AL$2)*100000000 -> 2.9814065e+12 | AM10: =('分行业工业增加值（当年人民币）'!AM10*汇率!$AM$2)*100000000 -> 3.0341009e+12 | AN10: =('分行业工业增加值（当年人民币）'!AN10*汇率!$AN$2)*100000000 -> 3.0869206e+12 | AO10: =('分行业工业增加值（当年人民币）'!AO10*汇率!$AO$2)*100000000 -> 3.1398477e+12 | AP10: =('分行业工业增加值（当年人民币）'!AP10*汇率!$AP$2)*100000000 -> 3.1931153e+12 | AQ10: =('分行业工业增加值（当年人民币）'!AQ10*汇率!$AQ$2)*100000000 -> 3.2467224e+12
A11: 其他三产 | B11: =('分行业工业增加值（当年人民币）'!B11*汇率!$B$2)*100000000 -> 3.097634e+12 | C11: =('分行业工业增加值（当年人民币）'!C11*汇率!$C$2)*100000000 -> 4.1679679e+12 | D11: =('分行业工业增加值（当年人民币）'!D11*汇率!$D$2)*100000000 -> 3.9115913e+12 | E11: =('分行业工业增加值（当年人民币）'!E11*汇率!$E$2)*100000000 -> 4.2631613e+12 | F11: =('分行业工业增加值（当年人民币）'!F11*汇率!$F$2)*100000000 -> 4.6235846e+12 | G11: =('分行业工业增加值（当年人民币）'!G11*汇率!$G$2)*100000000 -> 4.9874411e+12 | H11: =('分行业工业增加值（当年人民币）'!H11*汇率!$H$2)*100000000 -> 5.3606919e+12 | I11: =('分行业工业增加值（当年人民币）'!I11*汇率!$I$2)*100000000 -> 5.7360297e+12 | J11: =('分行业工业增加值（当年人民币）'!J11*汇率!$J$2)*100000000 -> 6.1132135e+12 | K11: =('分行业工业增加值（当年人民币）'!K11*汇率!$K$2)*100000000 -> 6.4942629e+12 | L11: =('分行业工业增加值（当年人民币）'!L11*汇率!$L$2)*100000000 -> 6.8732406e+12 | M11: =('分行业工业增加值（当年人民币）'!M11*汇率!$M$2)*100000000 -> 7.2524244e+12 | N11: =('分行业工业增加值（当年人民币）'!N11*汇率!$N$2)*100000000 -> 7.6304568e+12 | O11: =('分行业工业增加值（当年人民币）'!O11*汇率!$O$2)*100000000 -> 8.0041514e+12 | P11: =('分行业工业增加值（当年人民币）'!P11*汇率!$P$2)*100000000 -> 8.3763236e+12 | Q11: =('分行业工业增加值（当年人民币）'!Q11*汇率!$Q$2)*100000000 -> 8743632496775 | R11: =('分行业工业增加值（当年人民币）'!R11*汇率!$R$2)*100000000 -> 9.104643e+12 | S11: =('分行业工业增加值（当年人民币）'!S11*汇率!$S$2)*100000000 -> 9.4626727e+12 | T11: =('分行业工业增加值（当年人民币）'!T11*汇率!$T$2)*100000000 -> 9.8134429e+12 | U11: =('分行业工业增加值（当年人民币）'!U11*汇率!$U$2)*100000000 -> 10160108529873 | V11: =('分行业工业增加值（当年人民币）'!V11*汇率!$V$2)*100000000 -> 1.0499975e+13 | W11: =('分行业工业增加值（当年人民币）'!W11*汇率!$W$2)*100000000 -> 1.0831845e+13 | X11: =('分行业工业增加值（当年人民币）'!X11*汇率!$X$2)*100000000 -> 1.1158388e+13 | Y11: =('分行业工业增加值（当年人民币）'!Y11*汇率!$Y$2)*100000000 -> 1.1477882e+13 | Z11: =('分行业工业增加值（当年人民币）'!Z11*汇率!$Z$2)*100000000 -> 1.1789912e+13 | AA11: =('分行业工业增加值（当年人民币）'!AA11*汇率!$AA$2)*100000000 -> 1.2094517e+13 | AB11: =('分行业工业增加值（当年人民币）'!AB11*汇率!$AB$2)*100000000 -> 1.239206e+13 | AC11: =('分行业工业增加值（当年人民币）'!AC11*汇率!$AC$2)*100000000 -> 1.268317e+13 | AD11: =('分行业工业增加值（当年人民币）'!AD11*汇率!$AD$2)*100000000 -> 1.2966004e+13 | AE11: =('分行业工业增加值（当年人民币）'!AE11*汇率!$AE$2)*100000000 -> 1.3240769e+13 | AF11: =('分行业工业增加值（当年人民币）'!AF11*汇率!$AF$2)*100000000 -> 1.3510098e+13 | AG11: =('分行业工业增加值（当年人民币）'!AG11*汇率!$AG$2)*100000000 -> 1.3771033e+13 | AH11: =('分行业工业增加值（当年人民币）'!AH11*汇率!$AH$2)*100000000 -> 1.4025034e+13 | AI11: =('分行业工业增加值（当年人民币）'!AI11*汇率!$AI$2)*100000000 -> 1.4272064e+13 | AJ11: =('分行业工业增加值（当年人民币）'!AJ11*汇率!$AJ$2)*100000000 -> 1.4511373e+13 | AK11: =('分行业工业增加值（当年人民币）'!AK11*汇率!$AK$2)*100000000 -> 1.4744789e+13 | AL11: =('分行业工业增加值（当年人民币）'!AL11*汇率!$AL$2)*100000000 -> 1.4971374e+13 | AM11: =('分行业工业增加值（当年人民币）'!AM11*汇率!$AM$2)*100000000 -> 1.5191609e+13 | AN11: =('分行业工业增加值（当年人民币）'!AN11*汇率!$AN$2)*100000000 -> 1.5405644e+13 | AO11: =('分行业工业增加值（当年人民币）'!AO11*汇率!$AO$2)*100000000 -> 1.5613386e+13 | AP11: =('分行业工业增加值（当年人民币）'!AP11*汇率!$AP$2)*100000000 -> 1.5815837e+13 | AQ11: =('分行业工业增加值（当年人民币）'!AQ11*汇率!$AQ$2)*100000000 -> 16012371254583
A13: 工业 | B13: =('分行业工业增加值（当年人民币）'!B13*汇率!$B$2)*100000000 -> 4.3273675e+12 | C13: =('分行业工业增加值（当年人民币）'!C13*汇率!$C$2)*100000000 -> 4.3066258e+12 | D13: =('分行业工业增加值（当年人民币）'!D13*汇率!$D$2)*100000000 -> 4.9641751e+12 | E13: =('分行业工业增加值（当年人民币）'!E13*汇率!$E$2)*100000000 -> 5.098886e+12 | F13: =('分行业工业增加值（当年人民币）'!F13*汇率!$F$2)*100000000 -> 5.222535e+12 | G13: =('分行业工业增加值（当年人民币）'!G13*汇率!$G$2)*100000000 -> 5.3357926e+12 | H13: =('分行业工业增加值（当年人民币）'!H13*汇率!$H$2)*100000000 -> 5.4393831e+12 | I13: =('分行业工业增加值（当年人民币）'!I13*汇率!$I$2)*100000000 -> 5.5340487e+12 | J13: =('分行业工业增加值（当年人民币）'!J13*汇率!$J$2)*100000000 -> 5.6205229e+12 | K13: =('分行业工业增加值（当年人民币）'!K13*汇率!$K$2)*100000000 -> 5.6995128e+12 | L13: =('分行业工业增加值（当年人民币）'!L13*汇率!$L$2)*100000000 -> 5.7716873e+12 | M13: =('分行业工业增加值（当年人民币）'!M13*汇率!$M$2)*100000000 -> 5.8376704e+12 | N13: =('分行业工业增加值（当年人民币）'!N13*汇率!$N$2)*100000000 -> 5.8980385e+12 | O13: =('分行业工业增加值（当年人民币）'!O13*汇率!$O$2)*100000000 -> 5.9533191e+12 | P13: =('分行业工业增加值（当年人民币）'!P13*汇率!$P$2)*100000000 -> 6.0039928e+12 | Q13: =('分行业工业增加值（当年人民币）'!Q13*汇率!$Q$2)*100000000 -> 6.050495e+12 | R13: =('分行业工业增加值（当年人民币）'!R13*汇率!$R$2)*100000000 -> 6.0932188e+12 | S13: =('分行业工业增加值（当年人民币）'!S13*汇率!$S$2)*100000000 -> 6.1325187e+12 | T13: =('分行业工业增加值（当年人民币）'!T13*汇率!$T$2)*100000000 -> 6.1687134e+12 | U13: =('分行业工业增加值（当年人民币）'!U13*汇率!$U$2)*100000000 -> 6.2020893e+12 | V13: =('分行业工业增加值（当年人民币）'!V13*汇率!$V$2)*100000000 -> 6.2329036e+12 | W13: =('分行业工业增加值（当年人民币）'!W13*汇率!$W$2)*100000000 -> 6.2613874e+12 | X13: =('分行业工业增加值（当年人民币）'!X13*汇率!$X$2)*100000000 -> 6.2877482e+12 | Y13: =('分行业工业增加值（当年人民币）'!Y13*汇率!$Y$2)*100000000 -> 6.3121728e+12 | Z13: =('分行业工业增加值（当年人民币）'!Z13*汇率!$Z$2)*100000000 -> 6.3348287e+12 | AA13: =('分行业工业增加值（当年人民币）'!AA13*汇率!$AA$2)*100000000 -> 6.3558673e+12 | AB13: =('分行业工业增加值（当年人民币）'!AB13*汇率!$AB$2)*100000000 -> 6.3754245e+12 | AC13: =('分行业工业增加值（当年人民币）'!AC13*汇率!$AC$2)*100000000 -> 6.3936235e+12 | AD13: =('分行业工业增加值（当年人民币）'!AD13*汇率!$AD$2)*100000000 -> 6.4105752e+12 | AE13: =('分行业工业增加值（当年人民币）'!AE13*汇率!$AE$2)*100000000 -> 6.4263802e+12 | AF13: =('分行业工业增加值（当年人民币）'!AF13*汇率!$AF$2)*100000000 -> 6.4411295e+12 | AG13: =('分行业工业增加值（当年人民币）'!AG13*汇率!$AG$2)*100000000 -> 6.4549058e+12 | AH13: =('分行业工业增加值（当年人民币）'!AH13*汇率!$AH$2)*100000000 -> 6.4677843e+12 | AI13: =('分行业工业增加值（当年人民币）'!AI13*汇率!$AI$2)*100000000 -> 6.4798332e+12 | AJ13: =('分行业工业增加值（当年人民币）'!AJ13*汇率!$AJ$2)*100000000 -> 6.491115e+12 | AK13: =('分行业工业增加值（当年人民币）'!AK13*汇率!$AK$2)*100000000 -> 6.5016865e+12 | AL13: =('分行业工业增加值（当年人民币）'!AL13*汇率!$AL$2)*100000000 -> 6.5115998e+12 | AM13: =('分行业工业增加值（当年人民币）'!AM13*汇率!$AM$2)*100000000 -> 6.5209025e+12 | AN13: =('分行业工业增加值（当年人民币）'!AN13*汇率!$AN$2)*100000000 -> 6.5296382e+12 | AO13: =('分行业工业增加值（当年人民币）'!AO13*汇率!$AO$2)*100000000 -> 6.537847e+12 | AP13: =('分行业工业增加值（当年人民币）'!AP13*汇率!$AP$2)*100000000 -> 6.5455659e+12 | AQ13: =('分行业工业增加值（当年人民币）'!AQ13*汇率!$AQ$2)*100000000 -> 6.5528286e+12
A14: 煤炭采选产品 | B14: =('分行业工业增加值（当年人民币）'!B14*汇率!$B$2)*100000000 -> 1.2104576e+11 | C14: =('分行业工业增加值（当年人民币）'!C14*汇率!$C$2)*100000000 -> 1.4374983e+11 | D14: =('分行业工业增加值（当年人民币）'!D14*汇率!$D$2)*100000000 -> 1.4549003e+11 | E14: =('分行业工业增加值（当年人民币）'!E14*汇率!$E$2)*100000000 -> 1.4704644e+11 | F14: =('分行业工业增加值（当年人民币）'!F14*汇率!$F$2)*100000000 -> 1.4834443e+11 | G14: =('分行业工业增加值（当年人民币）'!G14*汇率!$G$2)*100000000 -> 1.4941017e+11 | H14: =('分行业工业增加值（当年人民币）'!H14*汇率!$H$2)*100000000 -> 1.502693e+11 | I14: =('分行业工业增加值（当年人民币）'!I14*汇率!$I$2)*100000000 -> 1.5094615e+11 | J14: =('分行业工业增加值（当年人民币）'!J14*汇率!$J$2)*100000000 -> 1.5146334e+11 | K14: =('分行业工业增加值（当年人民币）'!K14*汇率!$K$2)*100000000 -> 1.5184151e+11 | L14: =('分行业工业增加值（当年人民币）'!L14*汇率!$L$2)*100000000 -> 1.5209928e+11 | M14: =('分行业工业增加值（当年人民币）'!M14*汇率!$M$2)*100000000 -> 1.5225325e+11 | N14: =('分行业工业增加值（当年人民币）'!N14*汇率!$N$2)*100000000 -> 1.5231809e+11 | O14: =('分行业工业增加值（当年人民币）'!O14*汇率!$O$2)*100000000 -> 1.5230671e+11 | P14: =('分行业工业增加值（当年人民币）'!P14*汇率!$P$2)*100000000 -> 1.5223041e+11 | Q14: =('分行业工业增加值（当年人民币）'!Q14*汇率!$Q$2)*100000000 -> 1.5209903e+11 | R14: =('分行业工业增加值（当年人民币）'!R14*汇率!$R$2)*100000000 -> 1.519211e+11 | S14: =('分行业工业增加值（当年人民币）'!S14*汇率!$S$2)*100000000 -> 1.5170403e+11 | T14: =('分行业工业增加值（当年人民币）'!T14*汇率!$T$2)*100000000 -> 1.5145421e+11 | U14: =('分行业工业增加值（当年人民币）'!U14*汇率!$U$2)*100000000 -> 1.5117716e+11 | V14: =('分行业工业增加值（当年人民币）'!V14*汇率!$V$2)*100000000 -> 1.5087764e+11 | W14: =('分行业工业增加值（当年人民币）'!W14*汇率!$W$2)*100000000 -> 1.5055973e+11 | X14: =('分行业工业增加值（当年人民币）'!X14*汇率!$X$2)*100000000 -> 1.5022696e+11 | Y14: =('分行业工业增加值（当年人民币）'!Y14*汇率!$Y$2)*100000000 -> 1.4988236e+11 | Z14: =('分行业工业增加值（当年人民币）'!Z14*汇率!$Z$2)*100000000 -> 1.4952852e+11 | AA14: =('分行业工业增加值（当年人民币）'!AA14*汇率!$AA$2)*100000000 -> 1.4916766e+11 | AB14: =('分行业工业增加值（当年人民币）'!AB14*汇率!$AB$2)*100000000 -> 1.4880171e+11 | AC14: =('分行业工业增加值（当年人民币）'!AC14*汇率!$AC$2)*100000000 -> 1.484323e+11 | AD14: =('分行业工业增加值（当年人民币）'!AD14*汇率!$AD$2)*100000000 -> 1.4806082e+11 | AE14: =('分行业工业增加值（当年人民币）'!AE14*汇率!$AE$2)*100000000 -> 1.4768847e+11 | AF14: =('分行业工业增加值（当年人民币）'!AF14*汇率!$AF$2)*100000000 -> 1.4731627e+11 | AG14: =('分行业工业增加值（当年人民币）'!AG14*汇率!$AG$2)*100000000 -> 1.4694508e+11 | AH14: =('分行业工业增加值（当年人民币）'!AH14*汇率!$AH$2)*100000000 -> 1.4657565e+11 | AI14: =('分行业工业增加值（当年人民币）'!AI14*汇率!$AI$2)*100000000 -> 1.462086e+11 | AJ14: =('分行业工业增加值（当年人民币）'!AJ14*汇率!$AJ$2)*100000000 -> 1.4584445e+11 | AK14: =('分行业工业增加值（当年人民币）'!AK14*汇率!$AK$2)*100000000 -> 1.4548364e+11 | AL14: =('分行业工业增加值（当年人民币）'!AL14*汇率!$AL$2)*100000000 -> 1.4512655e+11 | AM14: =('分行业工业增加值（当年人民币）'!AM14*汇率!$AM$2)*100000000 -> 1.4477349e+11 | AN14: =('分行业工业增加值（当年人民币）'!AN14*汇率!$AN$2)*100000000 -> 1.444247e+11 | AO14: =('分行业工业增加值（当年人民币）'!AO14*汇率!$AO$2)*100000000 -> 1.4408039e+11 | AP14: =('分行业工业增加值（当年人民币）'!AP14*汇率!$AP$2)*100000000 -> 1.4374073e+11 | AQ14: =('分行业工业增加值（当年人民币）'!AQ14*汇率!$AQ$2)*100000000 -> 1.4340585e+11
... A54: 公共管理、社会保障和社会组织 | B54: =('分行业工业增加值（当年人民币）'!B54*汇率!$B$2)*100000000 -> 5.0470061e+11 | C54: =('分行业工业增加值（当年人民币）'!C54*汇率!$C$2)*100000000 -> 6.481061e+11 | D54: =('分行业工业增加值（当年人民币）'!D54*汇率!$D$2)*100000000 -> 5.6864439e+11 | E54: =('分行业工业增加值（当年人民币）'!E54*汇率!$E$2)*100000000 -> 6.2020912e+11 | F54: =('分行业工业增加值（当年人民币）'!F54*汇率!$F$2)*100000000 -> 6.7318826e+11 | G54: =('分行业工业增加值（当年人民币）'!G54*汇率!$G$2)*100000000 -> 7.2702039e+11 | H54: =('分行业工业增加值（当年人民币）'!H54*汇率!$H$2)*100000000 -> 7.8244834e+11 | I54: =('分行业工业增加值（当年人民币）'!I54*汇率!$I$2)*100000000 -> 8.384348e+11 | J54: =('分行业工业增加值（当年人民币）'!J54*汇率!$J$2)*100000000 -> 8.9499539e+11 | K54: =('分行业工业增加值（当年人民币）'!K54*汇率!$K$2)*100000000 -> 9.5222908e+11 | L54: =('分行业工业增加值（当年人民币）'!L54*汇率!$L$2)*100000000 -> 1.0094198e+12 | M54: =('分行业工业增加值（当年人民币）'!M54*汇率!$M$2)*100000000 -> 1.0667964e+12 | N54: =('分行业工业增加值（当年人民币）'!N54*汇率!$N$2)*100000000 -> 1.1241874e+12 | O54: =('分行业工业增加值（当年人民币）'!O54*汇率!$O$2)*100000000 -> 1.1811308e+12 | P54: =('分行业工业增加值（当年人民币）'!P54*汇率!$P$2)*100000000 -> 1.2378976e+12 | Q54: =('分行业工业增加值（当年人民币）'!Q54*汇率!$Q$2)*100000000 -> 1.2940753e+12 | R54: =('分行业工业增加值（当年人民币）'!R54*汇率!$R$2)*100000000 -> 1.349501e+12 | S54: =('分行业工业增加值（当年人民币）'!S54*汇率!$S$2)*100000000 -> 1.4044528e+12 | T54: =('分行业工业增加值（当年人民币）'!T54*汇率!$T$2)*100000000 -> 1.4583977e+12 | U54: =('分行业工业增加值（当年人民币）'!U54*汇率!$U$2)*100000000 -> 1.5118014e+12 | V54: =('分行业工业增加值（当年人民币）'!V54*汇率!$V$2)*100000000 -> 1.564268e+12 | W54: =('分行业工业增加值（当年人民币）'!W54*汇率!$W$2)*100000000 -> 1.6155389e+12 | X54: =('分行业工业增加值（当年人民币）'!X54*汇率!$X$2)*100000000 -> 1.6660137e+12 | Y54: =('分行业工业增加值（当年人民币）'!Y54*汇率!$Y$2)*100000000 -> 1.7155001e+12 | Z54: =('分行业工业增加值（当年人民币）'!Z54*汇率!$Z$2)*100000000 -> 1.7638536e+12 | AA54: =('分行业工业增加值（当年人民币）'!AA54*汇率!$AA$2)*100000000 -> 1.8110625e+12 | AB54: =('分行业工业增加值（当年人民币）'!AB54*汇率!$AB$2)*100000000 -> 1.8572837e+12 | AC54: =('分行业工业增加值（当年人民币）'!AC54*汇率!$AC$2)*100000000 -> 1.9025213e+12 | AD54: =('分行业工业增加值（当年人民币）'!AD54*汇率!$AD$2)*100000000 -> 1.946543e+12 | AE54: =('分行业工业增加值（当年人民币）'!AE54*汇率!$AE$2)*100000000 -> 1.9893778e+12 | AF54: =('分行业工业增加值（当年人民币）'!AF54*汇率!$AF$2)*100000000 -> 2.0314187e+12 | AG54: =('分行业工业增加值（当年人民币）'!AG54*汇率!$AG$2)*100000000 -> 2.0722403e+12 | AH54: =('分行业工业增加值（当年人民币）'!AH54*汇率!$AH$2)*100000000 -> 2.112009e+12 | AI54: =('分行业工业增加值（当年人民币）'!AI54*汇率!$AI$2)*100000000 -> 2.1508919e+12 | AJ54: =('分行业工业增加值（当年人民币）'!AJ54*汇率!$AJ$2)*100000000 -> 2.1887033e+12 | AK54: =('分行业工业增加值（当年人民币）'!AK54*汇率!$AK$2)*100000000 -> 2.2256683e+12 | AL54: =('分行业工业增加值（当年人民币）'!AL54*汇率!$AL$2)*100000000 -> 2.2618067e+12 | AM54: =('分行业工业增加值（当年人民币）'!AM54*汇率!$AM$2)*100000000 -> 2.2971648e+12 | AN54: =('分行业工业增加值（当年人民币）'!AN54*汇率!$AN$2)*100000000 -> 2.3318214e+12 | AO54: =('分行业工业增加值（当年人民币）'!AO54*汇率!$AO$2)*100000000 -> 2.3658169e+12 | AP54: =('分行业工业增加值（当年人民币）'!AP54*汇率!$AP$2)*100000000 -> 2.3992639e+12 | AQ54: =('分行业工业增加值（当年人民币）'!AQ54*汇率!$AQ$2)*100000000 -> 2.4321828e+12

Sheet 汇率
A1: 人民币年份 | B1: 2019 | C1: 2020 | D1: 2021 | E1: 2022 | F1: 2023 | G1: 2024 | H1: 2025 | I1: 2026 | J1: 2027 | K1: 2028 | L1: 2029 | M1: 2030 | N1: 2031 | O1: 2032 | P1: 2033 | Q1: 2034 | R1: 2035 | S1: 2036 | T1: 2037 | U1: 2038 | V1: 2039 | W1: 2040 | X1: 2041 | Y1: 2042 | Z1: 2043 | AA1: 2044 | AB1: 2045 | AC1: 2046 | AD1: 2047 | AE1: 2048 | AF1: 2049 | AG1: 2050 | AH1: 2051 | AI1: 2052 | AJ1: 2053 | AK1: 2054 | AL1: 2055 | AM1: 2056 | AN1: 2057 | AO1: 2058 | AP1: 2059 | AQ1: 2060
A2: 当年人民币相对2012美元 | B2: 0.13851126 | C2: 0.13765068 | D2: 0.13468755 | E2: 0.13178821 | F2: 0.12895128 | G2: 0.12617542 | H2: 0.12345932 | I2: 0.12080168 | J2: 0.11820125 | K2: 0.1156568 | L2: 0.11316713 | M2: 0.11073104 | N2: 0.1083474 | O2: 0.10601507 | P2: 0.10373295 | Q2: 0.10149995 | R2: 0.099315016 | S2: 0.09717712 | T2: 0.095085244 | U2: 0.093038399 | V2: 0.091035616 | W2: 0.089075945 | X2: 0.087158459 | Y2: 0.085282249 | Z2: 0.083446428 | AA2: 0.081650125 | AB2: 0.079892491 | AC2: 0.078172691 | AD2: 0.076489913 | AE2: 0.074843359 | AF2: 0.07323225 | AG2: 0.071655822 | AH2: 0.070113329 | AI2: 0.06860404 | AJ2: 0.06712724 | AK2: 0.065682231 | AL2: 0.064268328 | AM2: 0.062884861 | AN2: 0.061531175 | AO2: 0.060206629 | AP2: 0.058910596 | AQ2: 0.057642462

Sheet 2020年全国投入产出表
A1: 2020年全国投入产出表
A2: (按当年生产者价格计算） （Data are calculated at producers' prices in 2020)
A3: 单位：万元
A4: 投入 产出 | C4: 部门名称 | AU4: 最终使用 | BE4: 进口 | BF4: 总产出
D5: 农林牧渔产品和服务 | E5: 煤炭开采和洗选产品 | F5: 石油和天然气开采产品 | G5: 金属矿采选产品&非金属矿 | H5: 开采辅助活动和其他采矿产品 | I5: 食品和烟草 | J5: 纺织品、纺织服装鞋帽皮革羽绒及其制品 | K5: 木材加工品和家具 | L5: 造纸印刷和文教体育用品 | M5: 石油、炼焦产品和核燃料加工品 | N5: 化学原料和化学制品制造业&化学纤维制造业 | O5: 医药制造业 | P5: 橡胶和塑料制品业 | Q5: 非金属矿物制品 | R5: 黑色金属冶炼和压延加工品 | S5: 有色金属冶炼和压延加工品 | T5: 金属制品 | U5: 通用设备 | V5: 专用设备 | W5: 汽车制造业 | X5: 铁路、船舶、航空航天和其他运输设备 | Y5: 电气机械和器材 | Z5: 通信设备、计算机和其他电子设备&仪器仪表 | AA5: 其他制造产品和废品废料、金属制品、机械和设备修理服务 | AB5: 电力、热力生产和供应 | AC5: 燃气生产和供应 | AD5: 水的生产和供应 | AE5: 建筑 | AF5: 批发和零售 | AG5: 交通运输、仓储和邮政 | AH5: 住宿和餐饮 | AI5: 信息传输、软件和信息技术服务 | AJ5: 金融 | AK5: 房地产 | AL5: 租赁和商务服务 | AM5: 研究和试验发展 | AN5: 综合技术服务 | AO5: 居民服务、修理和其他服务 | AP5: 教育 | AQ5: 卫生和社会工作 | AR5: 文化、体育和娱乐 | AS5: 水利、环境和公共设施管理、公共管理、社会保障和社会组织 | AT5: 中间使用合计 | AU5: 农村居民消费支出 | AV5: 城镇居民消费支出 | AW5: 居民消费支出 | AX5: 政府消费支出 | AY5: 消费支出合计 | AZ5: 固定资本形成总额 | BA5: 存货变动 | BB5: 资本形成总额 | BC5: 出口 | BD5: 最终使用合计
B6: 部门名称 | C6: 代码 | D6: ISIC 01T03 | E6: ISIC 05 | F6: ISIC 06 | G6: ISIC 07T08 | H6: ISIC 09 | I6: ISIC 10T12 | J6: ISIC 13T15 | K6: ISIC 16 | L6: ISIC 17T18 | M6: ISIC 19 | N6: ISIC 20 | O6: ISIC 21 | P6: ISIC 22 | Q6: ISIC 231 | R6: ISIC 241 | S6: ISIC 242 | T6: ISIC 25 | U6: ISIC 28 | V6: ISIC 239 | W6: ISIC 29 | X6: ISIC 30 | Y6: ISIC 27 | Z6: ISIC 26 | AA6: ISIC 31T33 | AB6: ISIC 351 | AC6: ISIC 352T353 | AD6: ISIC 36T39 | AE6: ISIC 41T43 | AF6: ISIC 45T47 | AG6: ISIC 49T53 | AH6: ISIC 55T56 | AI6: ISIC 58T60 | AJ6: ISIC 64T66 | AK6: ISIC 68 | AL6: ISIC 61 | AM6: ISIC 64T66 | AN6: ISIC 69T82 | AO6: ISIC 97T98 | AP6: ISIC 85 | AQ6: ISIC 86T88 | AR6: ISIC 90T96 | AS6: ISIC 84 | AT6: TIU | AU6: FU101 | AV6: FU102 | AW6: THC | AX6: FU103 | AY6: TC | AZ6: FU201 | BA6: FU202 | BB6: GCF | BC6: EX | BD6: TFU | BE6: IM | BF6: GO
B7: 农林牧渔产品和服务 | C7: ISIC 01T03 | D7: 1.8313377e+08 | E7: 203490.68 | F7: 2231.1266 | G7: 30366.118 | H7: 118.5489 | I7: 4.6758672e+08 | J7: 82006169 | K7: 31973463 | L7: 53736067 | M7: 15804.36 | N7: 11513733 | O7: 44821825 | P7: 7680873.6 | Q7: 218881.19 | R7: 20627.162 | S7: 15998.126 | T7: 97311.762 | U7: 27411.881 | V7: 79539.685 | W7: 26629.608 | X7: 12565.824 | Y7: 68073.761 | Z7: 2175.5736 | AA7: 3451035.2 | AB7: 101721.23 | AC7: 1310.7869 | AD7: 0 | AE7: 18834172 | AF7: 13768.593 | AG7: 154389.97 | AH7: 53857079 | AI7: 509534.92 | AJ7: 67279.739 | AK7: 336941.13 | AL7: 7363183.4 | AM7: 4230391.8 | AN7: 1149759.6 | AO7: 2268491.1 | AP7: 612269.39 | AQ7: 605609.6 | AR7: 477755.87 | AS7: 9519615.7 | AT7: 9.5485469e+08 | AU7: 1.0974545e+08 | AV7: 2.21055e+08 | AW7: 3.3080046e+08 | AX7: 19639628 | AY7: 3.5044008e+08 | AZ7: 17577340 | BA7: 54901502 | BB7: 72478841 | BC7: 18171672 | BD7: 4.410906e+08 | BE7: 64262038 | BF7: 1.3316833e+09
B8: 煤炭开采和洗选产品 | C8: ISIC 05 | D8: 601665.54 | E8: 36204794 | F8: 63785.09 | G8: 1725453.9 | H8: 60512.779 | I8: 2167450.2 | J8: 1809485.7 | K8: 280086.13 | L8: 3698845.9 | M8: 22001120 | N8: 21794626 | O8: 436019.62 | P8: 562146.69 | Q8: 34167884 | R8: 21281683 | S8: 3302161.3 | T8: 494727.51 | U8: 360707.78 | V8: 252507.67 | W8: 48318.135 | X8: 49904.046 | Y8: 214230.21 | Z8: 20070.619 | AA8: 178085.14 | AB8: 93800322 | AC8: 2360515.5 | AD8: 0 | AE8: 843243.22 | AF8: 45563.861 | AG8: 128090.52 | AH8: 50429.81 | AI8: 0 | AJ8: 17218.23 | AK8: 63307.69 | AL8: 64.301927 | AM8: 234549.27 | AN8: 170081.94 | AO8: 326757.73 | AP8: 607785.82 | AQ8: 360760.39 | AR8: 41612.685 | AS8: 603682.15 | AT8: 2.5115017e+08 | AU8: 753293.48 | AV8: 468986.1 | AW8: 1222279.6 | AX8: 0 | AY8: 1222279.6 | AZ8: 0 | BA8: -2627614.6 | BB8: -2627614.6 | BC8: 260795.54 | BD8: -1144539.5 | BE8: 14933018 | BF8: 2.3507261e+08
B9: 石油和天然气开采产品 | C9: ISIC 06 | D9: 0 | E9: 44377.409 | F9: 535454.39 | G9: 31524.519 | H9: 15664.728 | I9: 0 | J9: 0 | K9: 0 | L9: 59261.943 | M9: 1.8788629e+08 | N9: 16889360 | O9: 26683.811 | P9: 822898.06 | Q9: 1363725.2 | R9: 372310.78 | S9: 752409.26 | T9: 586961.7 | U9: 564473.99 | V9: 372468.27 | W9: 425241.53 | X9: 143883.1 | Y9: 68067.405 | Z9: 0 | AA9: 0 | AB9: 6735286.1 | AC9: 33825564 | AD9: 0 | AE9: 0 | AF9: 0 | AG9: 487.91953 | AH9: 0 | AI9: 0 | AJ9: 0 | AK9: 0 | AL9: 0 | AM9: 2507.1572 | AN9: 0 | AO9: 0 | AP9: 0 | AQ9: 34579.89 | AR9: 1756.0257 | AS9: 48307.892 | AT9: 2.5160955e+08 | AU9: 0 | AV9: 0 | AW9: 0 | AX9: 0 | AY9: 0 | AZ9: 0 | BA9: 288640.91 | BB9: 288640.91 | BC9: 1085317.4 | BD9: 1373958.3 | BE9: 1.4529394e+08 | BF9: 1.0768957e+08
B10: 金属矿采选产品&非金属矿 | C10: ISIC 07T08 | D10: 2307.8115 | E10: 45270.046 | F10: 20550.068 | G10: 12059565 | H10: 74468.261 | I10: 62486.304 | J10: 20915.922 | K10: 14130.601 | L10: 917816.89 | M10: 351666.07 | N10: 13663939 | O10: 218560.81 | P10: 57763.344 | Q10: 51091549 | R10: 1.3243884e+08 | S10: 78502943 | T10: 6503772.5 | U10: 64839.412 | V10: 122513 | W10: 165447.68 | X10: 51425.009 | Y10: 614877.85 | Z10: 90520.249 | AA10: 56747.979 | AB10: 106588.82 | AC10: 0 | AD10: 0 | AE10: 24113819 | AF10: 60555.457 | AG10: 179268.15 | AH10: 4016.8528 | AI10: 87.113672 | AJ10: 747.23883 | AK10: 376.87524 | AL10: 1678.8514 | AM10: 333550.56 | AN10: 3880.5923 | AO10: 3727.6437 | AP10: 2965.1177 | AQ10: 1023.0554 | AR10: 5435.0281 | AS10: 31541.554 | AT10: 3.2204805e+08 | AU10: 0 | AV10: 0 | AW10: 0 | AX10: 0 | AY10: 0 | AZ10: 0 | BA10: 2801192.3 | BB10: 2801192.3 | BC10: 3333103.9 | BD10: 6134296.2 | BE10: 1.3464774e+08 | BF10: 1.935346e+08
B11: 开采辅助活动和其他采矿产品 | C11: ISIC 09 | D11: 0 | E11: 1372272.6 | F11: 16942467 | G11: 1047957.7 | H11: 177012.62 | I11: 466046.59 | J11: 0 | K11: 0 | L11: 0 | M11: 0 | N11: 0 | O11: 0 | P11: 0 | Q11: 0 | R11: 0 | S11: 0 | T11: 0 | U11: 0 | V11: 0 | W11: 0 | X11: 0 | Y11: 0 | Z11: 12.672237 | AA11: 0 | AB11: 231004.91 | AC11: 0 | AD11: 0 | AE11: 0 | AF11: 0 | AG11: 0 | AH11: 0 | AI11: 0 | AJ11: 0 | AK11: 0 | AL11: 0 | AM11: 0 | AN11: 0 | AO11: 0 | AP11: 0 | AQ11: 0 | AR11: 0 | AS11: 0 | AT11: 20236774 | AU11: 0 | AV11: 0 | AW11: 0 | AX11: 0 | AY11: 0 | AZ11: 0 | BA11: 0 | BB11: 0 | BC11: 0 | BD11: 0 | BE11: 0 | BF11: 20236774
B12: 食品和烟草 | C12: ISIC 10T12 | D12: 1.0818487e+08 | E12: 413271.66 | F12: 79328.127 | G12: 942010.65 | H12: 15471.043 | I12: 2.4937249e+08 | J12: 14128692 | K12: 1247437.6 | L12: 3016090.2 | M12: 3256002.6 | N12: 25114335 | O12: 7560676.1 | P12: 750764.12 | Q12: 1766033.1 | R12: 3822314.4 | S12: 4171930.4 | T12: 2846827.7 | U12: 4402856.9 | V12: 2451141.6 | W12: 2157646.4 | X12: 1244965.2 | Y12: 4524092.6 | Z12: 7303684.3 | AA12: 618269.9 | AB12: 5006459.1 | AC12: 538269.51 | AD12: 432454.55 | AE12: 5743107.4 | AF12: 2301664 | AG12: 7651112.8 | AH12: 1.2774375e+08 | AI12: 5595412.7 | AJ12: 2856239.9 | AK12: 4673588.7 | AL12: 16568941 | AM12: 4782871.6 | AN12: 3289851.4 | AO12: 7513197.7 | AP12: 12503171 | AQ12: 7006157.7 | AR12: 9671567.6 | AS12: 7647553.5 | AT12: 6.7966914e+08 | AU12: 1.5618843e+08 | AV12: 4.5232673e+08 | AW12: 6.0851517e+08 | AX12: 0 | AY12: 6.0851517e+08 | AZ12: 0 | BA12: 8525640.2 | BB12: 8525640.2 | BC12: 35833494 | BD12: 6.528743e+08 | BE12: 81180640 | BF12: 1.2513628e+09
B13: 纺织品、纺织服装鞋帽皮革羽绒及其制品 | C13: ISIC 13T15 | D13: 255022.54 | E13: 1536716.5 | F13: 172891.15 | G13: 431377.15 | H13: 299060.73 | I13: 3696564.2 | J13: 3.1484617e+08 | K13: 8109575.9 | L13: 21141410 | M13: 892568.3 | N13: 3692227 | O13: 4066224.9 | P13: 3366898.1 | Q13: 4050298.9 | R13: 649060.66 | S13: 445858.55 | T13: 2025532.9 | U13: 1951908.6 | V13: 1960493.2 | W13: 5639280.4 | X13: 1374959.5 | Y13: 3039653 | Z13: 3035965.5 | AA13: 4187381.8 | AB13: 864761.17 | AC13: 343622.09 | AD13: 391871.28 | AE13: 4541077.5 | AF13: 3219495.3 | AG13: 5114728.6 | AH13: 3509705.2 | AI13: 999494.99 | AJ13: 4708210.4 | AK13: 2106065.8 | AL13: 16680635 | AM13: 2606793.1 | AN13: 1524598.3 | AO13: 2503390.6 | AP13: 1549810.4 | AQ13: 9533818.8 | AR13: 4734179.3 | AS13: 25315084 | AT13: 4.7300487e+08 | AU13: 23013748 | AV13: 1.0819378e+08 | AW13: 1.3120753e+08 | AX13: 0 | AY13: 1.3120753e+08 | AZ13: 0 | BA13: -3571111.2 | BB13: -3571111.2 | BC13: 1.8680114e+08 | BD13: 3.1443756e+08 | BE13: 30055498 | BF13: 7.5738693e+08
B14: 木材加工品和家具 | C14: ISIC 16 | D14: 336188.95 | E14: 3559037.5 | F14: 156891.3 | G14: 254624.37 | H14: 6327.7151 | I14: 845240.04 | J14: 918481.02 | K14: 81780667 | L14: 90084970 | M14: 186690.2 | N14: 1302287.3 | O14: 114696.06 | P14: 708459.64 | Q14: 1957227.2 | R14: 49068.256 | S14: 185262.26 | T14: 4792477.8 | U14: 931517.23 | V14: 637156.81 | W14: 5926683.2 | X14: 652732.73 | Y14: 1177748.8 | Z14: 1019650 | AA14: 1295524.2 | AB14: 201717.8 | AC14: 4011.8598 | AD14: 3316.5085 | AE14: 57246609 | AF14: 423651.48 | AG14: 934919.87 | AH14: 196032.43 | AI14: 922455.74 | AJ14: 474744.04 | AK14: 546486.36 | AL14: 599781.95 | AM14: 50562.204 | AN14: 401102.15 | AO14: 635895.59 | AP14: 342879.72 | AQ14: 75136.026 | AR14: 319747.38 | AS14: 3983063.1 | AT14: 1.8446106e+08 | AU14: 5007508 | AV14: 17646337 | AW14: 22653845 | AX14: 0 | AY14: 22653845 | AZ14: 21595789 | BA14: 1674063.1 | BB14: 23269852 | BC14: 44765297 | BD14: 90688994 | BE14: 9736870.7 | BF14: 2.6541318e+08
B15: 造纸印刷和文教体育用品 | C15: ISIC 17T18 | D15: 1025682.3 | E15: 31068.882 | F15: 9688.6354 | G15: 315134.03 | H15: 18042.408 | I15: 13214440 | J15: 3599305.4 | K15: 2513515.7 | L15: 1.0517187e+08 | M15: 357515.63 | N15: 4061404.6 | O15: 4907967.4 | P15: 1782237.4 | Q15: 8915729.5 | R15: 89427.25 | S15: 336660.37 | T15: 1916810.8 | U15: 1926288.9 | V15: 1841924.1 | W15: 1597372.5 | X15: 344645.46 | Y15: 5512884.5 | Z15: 5349964.6 | AA15: 807927.26 | AB15: 458088.57 | AC15: 13078.613 | AD15: 21179.986 | AE15: 5313847 | AF15: 8789370.8 | AG15: 4327923.9 | AH15: 1732626.8 | AI15: 27520721 | AJ15: 20038604 | AK15: 5345538.8 | AL15: 69510376 | AM15: 2605460.1 | AN15: 5513422.2 | AO15: 1759661.7 | AP15: 12646201 | AQ15: 288424.63 | AR15: 7453946.6 | AS15: 20046565 | AT15: 3.5651903e+08 | AU15: 6120942 | AV15: 29346782 | AW15: 35467724 | AX15: 0 | AY15: 35467724 | AZ15: 4281134.6 | BA15: -8038986.6 | BB15: -3757852 | BC15: 66074535 | BD15: 97784407 | BE15: 25910671 | BF15: 4.2839277e+08
B16: 石油、炼焦产品和核燃料加工品 | C16: ISIC 19 | D16: 4991926.8 | E16: 700362.55 | F16: 395976.19 | G16: 7776692.3 | H16: 799185.8 | I16: 1015050.6 | J16: 1120310.3 | K16: 1004346.3 | L16: 1858172.8 | M16: 22688076 | N16: 63847205 | O16: 474305.06 | P16: 2190479.3 | Q16: 19987604 | R16: 42144147 | S16: 7221065.2 | T16: 3078282.8 | U16: 2035296.8 | V16: 1035075.2 | W16: 1106854 | X16: 444478.82 | Y16: 1121539.9 | Z16: 1058861.3 | AA16: 836932.65 | AB16: 10310485 | AC16: 1882494.5 | AD16: 38463.432 | AE16: 37120733 | AF16: 3295901.8 | AG16: 96331786 | AH16: 1029117.6 | AI16: 1116149.6 | AJ16: 3729490.6 | AK16: 1528256.1 | AL16: 19256951 | AM16: 1475382.6 | AN16: 12374899 | AO16: 1218116.8 | AP16: 2786127.9 | AQ16: 239725.61 | AR16: 469119.18 | AS16: 5767314 | AT16: 3.8789839e+08 | AU16: 5745628.2 | AV16: 28313585 | AW16: 34059213 | AX16: 0 | AY16: 34059213 | AZ16: 0 | BA16: -5955399.2 | BB16: -5955399.2 | BC16: 15981224 | BD16: 44085038 | BE16: 22650148 | BF16: 4.0933328e+08
B17: 化学原料和化学制品制造业&化学纤维制造业 | C17: ISIC 20 | D17: 75932742 | E17: 2724058.2 | F17: 3946860.5 | G17: 9732267.1 | H17: 1246400.1 | I17: 5072727.7 | J17: 54593583 | K17: 16223100 | L17: 51348513 | M17: 14670765 | N17: 2.9296505e+08 | O17: 11936419 | P17: 1.1027181e+08 | Q17: 31280002 | R17: 3761259 | S17: 9341339.8 | T17: 10641344 | U17: 4653059.2 | V17: 2243331.6 | W17: 6970340.2 | X17: 2118210.8 | Y17: 26478745 | Z17: 15451768 | AA17: 5086887.6 | AB17: 221438.67 | AC17: 31293.166 | AD17: 2463333.3 | AE17: 75178170 | AF17: 101065.7 | AG17: 988410.01 | AH17: 2502380.8 | AI17: 1218070.3 | AJ17: 301378.84 | AK17: 339047.64 | AL17: 4302489.1 | AM17: 14442889 | AN17: 20348720 | AO17: 13522936 | AP17: 7517280.1 | AQ17: 538883.13 | AR17: 1609725.6 | AS17: 8727065.8 | AT17: 9.0682206e+08 | AU17: 2773014.2 | AV17: 19771297 | AW17: 22544311 | AX17: 0 | AY17: 22544311 | AZ17: 0 | BA17: -17407692 | BB17: -17407692 | BC17: 66207878 | BD17: 71344496 | BE17: 1.2306996e+08 | BF17: 8.5509659e+08
B18: 医药制造业 | C18: ISIC 21 | D18: 6070961.4 | E18: 41905.124 | F18: 18810.369 | G18: 6112.285 | H18: 670.13328 | I18: 812022.34 | J18: 88147.315 | K18: 2763.5262 | L18: 656674.07 | M18: 14976.676 | N18: 1196871 | O18: 61912202 | P18: 81220.679 | Q18: 569294.79 | R18: 104789.23 | S18: 14108.632 | T18: 174018.27 | U18: 7811.941 | V18: 424487.47 | W18: 10204.664 | X18: 10869.323 | Y18: 124300.88 | Z18: 501241.91 | AA18: 124963.88 | AB18: 16580.568 | AC18: 375.41193 | AD18: 16573.363 | AE18: 2238386.7 | AF18: 10825.857 | AG18: 152802.04 | AH18: 814.26546 | AI18: 302859.27 | AJ18: 71563.525 | AK18: 15249.379 | AL18: 178518.28 | AM18: 1060731.9 | AN18: 2592341.8 | AO18: 184325.83 | AP18: 710406.22 | AQ18: 1.6382985e+08 | AR18: 24625.037 | AS18: 264315.07 | AT18: 2.4463781e+08 | AU18: 16266751 | AV18: 47595954 | AW18: 63862704 | AX18: 0 | AY18: 63862704 | AZ18: 0 | BA18: -336221.76 | BB18: -336221.76 | BC18: 22931108 | BD18: 86457591 | BE18: 31039262 | BF18: 3.0005614e+08
... B49: 中间投入合计 | C49: TII | D49: 5.0993601e+08 | E49: 1.1507411e+08 | F49: 39965777 | G49: 89225006 | H49: 11697851 | I49: 9.4434911e+08 | J49: 6.1291057e+08 | K49: 2.0981156e+08 | L49: 5.3265536e+08 | M49: 3.0874252e+08 | N49: 6.5708287e+08 | O49: 2.1422011e+08 | P49: 2.7175232e+08 | Q49: 5.0245189e+08 | R49: 5.2721563e+08 | S49: 4.0509258e+08 | T49: 3.9228391e+08 | U49: 4.0882303e+08 | V49: 2.8939979e+08 | W49: 5.6098102e+08 | X49: 1.2377234e+08 | Y49: 5.7633942e+08 | Z49: 9.9720917e+08 | AA49: 67374684 | AB49: 4.8115356e+08 | AC49: 61699159 | AD49: 20179486 | AE49: 2.140212e+09 | AF49: 5.4491128e+08 | AG49: 7.4239633e+08 | AH49: 2.8646918e+08 | AI49: 5.1722835e+08 | AJ49: 3.9319876e+08 | AK49: 2.9696594e+08 | AL49: 6.440355e+08 | AM49: 1.356294e+08 | AN49: 3.3464331e+08 | AO49: 1.4306091e+08 | AP49: 1.591954e+08 | AQ49: 2.9186652e+08 | AR49: 77833015 | AS49: 3.9682481e+08 | AT49: 1.6826058e+10 | AU49: 8.1664287e+08 | AV49: 3.0234403e+09 | AW49: 3.8400831e+09 | AX49: 1.7362538e+09 | AY49: 5.5763369e+09 | AZ49: 4.243704e+09 | BA49: 91509938 | BB49: 4.3352139e+09 | BC49: 1.8792607e+09 | BD49: 1.1790812e+10 | BE49: 1.6265915e+09 | BF49: 2.6990278e+10
A50: 增加值 | B50: 劳动者报酬 | C50: VA001 | D50: 8.2110938e+08 | E50: 49156976 | F50: 10684587 | G50: 34146732 | H50: 9070894.8 | I50: 92288060 | J50: 78070179 | K50: 25339701 | L50: 70607745 | M50: 12815275 | N50: 47509590 | O50: 30588661 | P50: 35944267 | Q50: 74959952 | R50: 39116759 | S50: 35418934 | T50: 57488356 | U50: 46988960 | V50: 51031136 | W50: 36758514 | X50: 17700419 | Y50: 47111754 | Z50: 1.0033013e+08 | AA50: 25541968 | AB50: 61395231 | AC50: 7256304.2 | AD50: 8632889.8 | AE50: 4.6964543e+08 | AF50: 5.197925e+08 | AG50: 2.3052393e+08 | AH50: 85067117 | AI50: 2.0697374e+08 | AJ50: 2.1528198e+08 | AK50: 1.9273312e+08 | AL50: 2.5275721e+08 | AM50: 65841577 | AN50: 1.1541846e+08 | AO50: 1.2768977e+08 | AP50: 2.8165049e+08 | AQ50: 1.7178319e+08 | AR50: 51172540 | AS50: 4.0760071e+08 | AT50: 5.2956554e+09
B51: 生产税净额 | C51: VA002 | D51: -45528241 | E51: 23728884 | F51: 26393586 | G51: 29203561 | H51: 1127941.3 | I51: 82927930 | J51: 1055456.5 | K51: 5439494.6 | L51: 11735860 | M51: 49155196 | N51: 37768625 | O51: 11543782 | P51: 9432919.7 | Q51: 23472867 | R51: 16809804 | S51: 20103753 | T51: 11219547 | U51: 16723538 | V51: 14548977 | W51: 41488606 | X51: 2028722 | Y51: 4541468.5 | Z51: -3678836.3 | AA51: 13432368 | AB51: 20698378 | AC51: 1010550.5 | AD51: 1860447.2 | AE51: 98116386 | AF51: 95383190 | AG51: 8513567.4 | AH51: 1360038.7 | AI51: 13092894 | AJ51: 82718116 | AK51: 1.2344272e+08 | AL51: 27690531 | AM51: 1588413.6 | AN51: 11715875 | AO51: 5023484.2 | AP51: 625840.59 | AQ51: 119102.01 | AR51: 1590021 | AS51: 2016363.5 | AT51: 8.9580223e+08
B52: 固定资产折旧 | C52: VA003 | D52: 23048580 | E52: 11857467 | F52: 23934532 | G52: 14045535 | H52: 881427.49 | I52: 30616039 | J52: 17159912 | K52: 7115541.2 | L52: 23476685 | M52: 11540323 | N52: 37261753 | O52: 7442373.5 | P52: 13681348 | Q52: 36252425 | R52: 31732256 | S52: 20256127 | T52: 17451920 | U52: 16689439 | V52: 12133973 | W52: 15404030 | X52: 3816835 | Y52: 15983410 | Z52: 35286960 | AA52: 6722131.4 | AB52: 97784316 | AC52: 5463404 | AD52: 6900167.1 | AE52: 27714364 | AF52: 1.1846713e+08 | AG52: 2.0022194e+08 | AH52: 46183808 | AI52: 1.2669418e+08 | AJ52: 36197644 | AK52: 70284261 | AL52: 35220354 | AM52: 20894697 | AN52: 47257246 | AO52: 18811001 | AP52: 77784703 | AQ52: 31476065 | AR52: 19443052 | AS52: 92345943 | AT52: 1.5058198e+09
B53: 营业盈余 | C53: VA004 | D53: 23117527 | E53: 35255171 | F53: 6711085 | G53: 26913765 | H53: -2541340.5 | I53: 1.0118166e+08 | J53: 48190809 | K53: 17706882 | L53: 55330297 | M53: 27079971 | N53: 75473751 | O53: 36261214 | P53: 27380722 | Q53: 95894758 | R53: 68635495 | S53: 43798631 | T53: 41037940 | U53: 43686016 | V53: 20237211 | W53: 51825291 | X53: 8695606.9 | Y53: 53690206 | Z53: 59374527 | AA53: 51110402 | AB53: 38471081 | AC53: 5841588 | AD53: 3105561.8 | AE53: 1.2461676e+08 | AF53: 2.1996059e+08 | AG53: 17515502 | AH53: 12909620 | AI53: 1.0125364e+08 | AJ53: 5.0197366e+08 | AK53: 3.8320744e+08 | AL53: 2859006.3 | AM53: 7602478.7 | AN53: 10750979 | AO53: 5752421.8 | AP53: 13231126 | AQ53: 4827324.6 | AR53: 5804782 | AS53: 8918362 | AT53: 2.4669426e+09
B54: 增加值合计 | C54: TVA | D54: 8.2174724e+08 | E54: 1.199985e+08 | F54: 67723790 | G54: 1.0430959e+08 | H54: 8538923.1 | I54: 3.0701369e+08 | J54: 1.4447636e+08 | K54: 55601618 | L54: 1.6115059e+08 | M54: 1.0059076e+08 | N54: 1.9801372e+08 | O54: 85836030 | P54: 86439257 | Q54: 2.3058e+08 | R54: 1.5629431e+08 | S54: 1.1957745e+08 | T54: 1.2719776e+08 | U54: 1.2408795e+08 | V54: 97951296 | W54: 1.4547644e+08 | X54: 32241583 | Y54: 1.2132684e+08 | Z54: 1.9131278e+08 | AA54: 96806870 | AB54: 2.1834901e+08 | AC54: 19571847 | AD54: 20499066 | AE54: 7.2009294e+08 | AF54: 9.5360341e+08 | AG54: 4.5677494e+08 | AH54: 1.4552058e+08 | AI54: 4.4801444e+08 | AJ54: 8.3617139e+08 | AK54: 7.6966754e+08 | AL54: 3.185271e+08 | AM54: 95927166 | AN54: 1.8514256e+08 | AO54: 1.5727667e+08 | AP54: 3.7329216e+08 | AQ54: 2.0820568e+08 | AR54: 78010395 | AS54: 5.1088137e+08 | AT54: 1.016422e+10
A55: 总投入 | C55: TI | D55: 1.3316833e+09 | E55: 2.3507261e+08 | F55: 1.0768957e+08 | G55: 1.935346e+08 | H55: 20236774 | I55: 1.2513628e+09 | J55: 7.5738693e+08 | K55: 2.6541318e+08 | L55: 6.9380595e+08 | M55: 4.0933328e+08 | N55: 8.5509659e+08 | O55: 3.0005614e+08 | P55: 3.5819158e+08 | Q55: 7.3303189e+08 | R55: 6.8350994e+08 | S55: 5.2467002e+08 | T55: 5.1948167e+08 | U55: 5.3291099e+08 | V55: 3.8735108e+08 | W55: 7.0645746e+08 | X55: 1.5601392e+08 | Y55: 6.9766625e+08 | Z55: 1.188522e+09 | AA55: 1.6418155e+08 | AB55: 6.9950257e+08 | AC55: 81271005 | AD55: 40678552 | AE55: 2.860305e+09 | AF55: 1.4985147e+09 | AG55: 1.1991713e+09 | AH55: 4.3198976e+08 | AI55: 9.6524279e+08 | AJ55: 1.2293702e+09 | AK55: 1.0666335e+09 | AL55: 9.625626e+08 | AM55: 2.3155657e+08 | AN55: 5.1978587e+08 | AO55: 3.0033759e+08 | AP55: 5.3248756e+08 | AQ55: 5.000722e+08 | AR55: 1.5584341e+08 | AS55: 9.0770619e+08 | AT55: 2.6990278e+10
B57: 增加值合计 | C57: TVA | D57: 8.2174724e+08 | E57: 1.199985e+08 | F57: 67723790 | G57: 1.0430959e+08 | H57: 8538923.1 | I57: 3.0701369e+08 | J57: 1.4447636e+08 | K57: 55601618 | L57: 1.6115059e+08 | M57: 1.0059076e+08 | N57: 1.9801372e+08 | O57: 85836030 | P57: 86439257 | Q57: 2.3058e+08 | R57: 1.5629431e+08 | S57: 1.1957745e+08 | T57: 1.2719776e+08 | U57: 1.2408795e+08 | V57: 97951296 | W57: 1.4547644e+08 | X57: 32241583 | Y57: 1.2132684e+08 | Z57: 1.9131278e+08 | AA57: 96806870 | AB57: 2.1834901e+08 | AC57: 19571847 | AD57: 20499066 | AE57: 7.2009294e+08 | AF57: 9.5360341e+08 | AG57: 4.5677494e+08 | AH57: 1.4552058e+08 | AI57: 4.4801444e+08 | AJ57: 8.3617139e+08 | AK57: 7.6966754e+08 | AL57: 3.185271e+08 | AM57: 95927166 | AN57: 1.8514256e+08 | AO57: 1.5727667e+08 | AP57: 3.7329216e+08 | AQ57: 2.0820568e+08 | AR57: 78010395 | AS57: 5.1088137e+08 | AT57: 1.016422e+10
G59: =G57/(G57+H57) -> 0.92433287 | H59: =H57/(G57+H57) -> 0.075667128 | N59: =N57/(N57+O57+P57) -> 0.53475452 | O59: =O57/(N57+O57+P57) -> 0.23180821 | P59: =P57/(N57+O57+P57) -> 0.23343728 | R59: =R57/(R57+S57) -> 0.56654699 | S59: =S57/(R57+S57) -> 0.43345301 | W59: =W57/(W57+X57) -> 0.81858012 | X59: =X57/(W57+X57) -> 0.18141988 | AM59: =AM57/(AM57+AN57) -> 0.34129313 | AN59: =AN57/(AM57+AN57) -> 0.65870687

Sheet 分42行业工业增加值（2012年美元）
C1: 2019 | D1: 2020 | E1: 2021 | F1: 2022 | G1: 2023 | H1: 2024 | I1: 2025 | J1: 2026 | K1: 2027 | L1: 2028 | M1: 2029 | N1: 2030 | O1: 2031 | P1: 2032 | Q1: 2033 | R1: 2034 | S1: 2035 | T1: 2036 | U1: 2037 | V1: 2038 | W1: 2039 | X1: 2040 | Y1: 2041 | Z1: 2042 | AA1: 2043 | AB1: 2044 | AC1: 2045 | AD1: 2046 | AE1: 2047 | AF1: 2048 | AG1: 2049 | AH1: 2050 | AI1: 2051 | AJ1: 2052 | AK1: 2053 | AL1: 2054 | AM1: 2055 | AN1: 2056 | AO1: 2057 | AP1: 2058 | AQ1: 2059 | AR1: 2060
A2: 农林牧渔产品和服务 | B2: ISIC 01T03 | C2: 1.0191215e+12 | D2: 1.1161281e+12 | E2: 1.1687593e+12 | F2: 1.2132055e+12 | G2: 1.2567896e+12 | H2: 1.2992424e+12 | I2: 1.3414628e+12 | J2: 1.3826182e+12 | K2: 1.4228716e+12 | L2: 1.4624476e+12 | M2: 1.5009707e+12 | N2: 1.5389234e+12 | O2: 1.5758637e+12 | P2: 1.6116736e+12 | Q2: 1.6468109e+12 | R2: 1.6809211e+12 | S2: 1.7139002e+12 | T2: 1.7460482e+12 | U2: 1.7771317e+12 | V2: 1.8075842e+12 | W2: 1.8369899e+12 | X2: 1.8652715e+12 | Y2: 1.8928163e+12 | Z2: 1.9194458e+12 | AA2: 1.9451008e+12 | AB2: 1.9698629e+12 | AC2: 1.9938083e+12 | AD2: 2.0170974e+12 | AE2: 2.039503e+12 | AF2: 2.0610896e+12 | AG2: 2.0821856e+12 | AH2: 2.1024632e+12 | AI2: 2.1221749e+12 | AJ2: 2.1413671e+12 | AK2: 2.1599393e+12 | AL2: 2.1781187e+12 | AM2: 2.1959416e+12 | AN2: 2.2134641e+12 | AO2: 2.2307766e+12 | AP2: 2.2478597e+12 | AQ2: 2.2649332e+12 | AR2: 2.2819627e+12
A3: 煤炭开采和洗选产品 | B3: ISIC 05 | C3: 1.2104576e+11 | D3: 1.4374983e+11 | E3: 1.4549003e+11 | F3: 1.4704644e+11 | G3: 1.4834443e+11 | H3: 1.4941017e+11 | I3: 1.502693e+11 | J3: 1.5094615e+11 | K3: 1.5146334e+11 | L3: 1.5184151e+11 | M3: 1.5209928e+11 | N3: 1.5225325e+11 | O3: 1.5231809e+11 | P3: 1.5230671e+11 | Q3: 1.5223041e+11 | R3: 1.5209903e+11 | S3: 1.519211e+11 | T3: 1.5170403e+11 | U3: 1.5145421e+11 | V3: 1.5117716e+11 | W3: 1.5087764e+11 | X3: 1.5055973e+11 | Y3: 1.5022696e+11 | Z3: 1.4988236e+11 | AA3: 1.4952852e+11 | AB3: 1.4916766e+11 | AC3: 1.4880171e+11 | AD3: 1.484323e+11 | AE3: 1.4806082e+11 | AF3: 1.4768847e+11 | AG3: 1.4731627e+11 | AH3: 1.4694508e+11 | AI3: 1.4657565e+11 | AJ3: 1.462086e+11 | AK3: 1.4584445e+11 | AL3: 1.4548364e+11 | AM3: 1.4512655e+11 | AN3: 1.4477349e+11 | AO3: 1.444247e+11 | AP3: 1.4408039e+11 | AQ3: 1.4374073e+11 | AR3: 1.4340585e+11
A4: 石油和天然气开采产品 | B4: ISIC 06 | C4: 7.1468967e+10 | D4: 5.2662595e+10 | E4: 5.7479073e+10 | F4: 5.6763857e+10 | G4: 5.5983137e+10 | H4: 5.5150874e+10 | I4: 5.4279638e+10 | J4: 5.338049e+10 | K4: 5.2462985e+10 | L4: 5.1535237e+10 | M4: 5.0604045e+10 | N4: 4.9675024e+10 | O4: 4.8752749e+10 | P4: 4.78409e+10 | Q4: 4.6942385e+10 | R4: 4.6059465e+10 | S4: 4.5193857e+10 | T4: 4.4346822e+10 | U4: 4.3519248e+10 | V4: 4.2711716e+10 | W4: 4.1924556e+10 | X4: 4.1157897e+10 | Y4: 4.0411705e+10 | Z4: 3.9685816e+10 | AA4: 3.8979966e+10 | AB4: 3.8293812e+10 | AC4: 3.7626949e+10 | AD4: 3.6978931e+10 | AE4: 3.6349278e+10 | AF4: 3.5737488e+10 | AG4: 3.5143046e+10 | AH4: 3.456543e+10 | AI4: 3.4004116e+10 | AJ4: 3.3458584e+10 | AK4: 3.2928318e+10 | AL4: 3.2412811e+10 | AM4: 3.1911568e+10 | AN4: 3.1424104e+10 | AO4: 3.0949948e+10 | AP4: 3.0488642e+10 | AQ4: 3.0039744e+10 | AR4: 2.9602824e+10
A5: 金属矿采选产品&非金属矿 | B5: ISIC 07T08 | C5: =('分行业工业增加值（2012年美元）'!B16+'分行业工业增加值（2012年美元）'!B17)*'2020年全国投入产出表'!$G$57/('2020年全国投入产出表'!$G$57+'2020年全国投入产出表'!$H$57) -> 6.7597143e+10 | D5: =('分行业工业增加值（2012年美元）'!C16+'分行业工业增加值（2012年美元）'!C17)*'2020年全国投入产出表'!$G$57/('2020年全国投入产出表'!$G$57+'2020年全国投入产出表'!$H$57) -> 6.5470147e+10 | E5: =('分行业工业增加值（2012年美元）'!D16+'分行业工业增加值（2012年美元）'!D17)*'2020年全国投入产出表'!$G$57/('2020年全国投入产出表'!$G$57+'2020年全国投入产出表'!$H$57) -> 7.1457993e+10 | F5: =('分行业工业增加值（2012年美元）'!E16+'分行业工业增加值（2012年美元）'!E17)*'2020年全国投入产出表'!$G$57/('2020年全国投入产出表'!$G$57+'2020年全国投入产出表'!$H$57) -> 7.0568836e+10 | G5: =('分行业工业增加值（2012年美元）'!F16+'分行业工业增加值（2012年美元）'!F17)*'2020年全国投入产出表'!$G$57/('2020年全国投入产出表'!$G$57+'2020年全国投入产出表'!$H$57) -> 6.9598245e+10 | H5: =('分行业工业增加值（2012年美元）'!G16+'分行业工业增加值（2012年美元）'!G17)*'2020年全国投入产出表'!$G$57/('2020年全国投入产出表'!$G$57+'2020年全国投入产出表'!$H$57) -> 6.8563575e+10 | I5: =('分行业工业增加值（2012年美元）'!H16+'分行业工业增加值（2012年美元）'!H17)*'2020年全国投入产出表'!$G$57/('2020年全国投入产出表'!$G$57+'2020年全国投入产出表'!$H$57) -> 6.7480455e+10 | J5: =('分行业工业增加值（2012年美元）'!I16+'分行业工业增加值（2012年美元）'!I17)*'2020年全国投入产出表'!$G$57/('2020年全国投入产出表'!$G$57+'2020年全国投入产出表'!$H$57) -> 6.6362635e+10 | ... AR5: =('分行业工业增加值（2012年美元）'!AQ16+'分行业工业增加值（2012年美元）'!AQ17)*'2020年全国投入产出表'!$G$57/('2020年全国投入产出表'!$G$57+'2020年全国投入产出表'!$H$57) -> 3.6802236e+10
A6: 开采辅助活动和其他采矿产品 | B6: ISIC 09 | C6: =('分行业工业增加值（2012年美元）'!B16+'分行业工业增加值（2012年美元）'!B17)*'2020年全国投入产出表'!$H$57/('2020年全国投入产出表'!$G$57+'2020年全国投入产出表'!$H$57) -> 5.5335928e+09 | D6: =('分行业工业增加值（2012年美元）'!C16+'分行业工业增加值（2012年美元）'!C17)*'2020年全国投入产出表'!$H$57/('2020年全国投入产出表'!$G$57+'2020年全国投入产出表'!$H$57) -> 5.3594739e+09 | E6: =('分行业工业增加值（2012年美元）'!D16+'分行业工业增加值（2012年美元）'!D17)*'2020年全国投入产出表'!$H$57/('2020年全国投入产出表'!$G$57+'2020年全国投入产出表'!$H$57) -> 5.8496471e+09 | F6: =('分行业工业增加值（2012年美元）'!E16+'分行业工业增加值（2012年美元）'!E17)*'2020年全国投入产出表'!$H$57/('2020年全国投入产出表'!$G$57+'2020年全国投入产出表'!$H$57) -> 5.7768595e+09 | G6: =('分行业工业增加值（2012年美元）'!F16+'分行业工业增加值（2012年美元）'!F17)*'2020年全国投入产出表'!$H$57/('2020年全国投入产出表'!$G$57+'2020年全国投入产出表'!$H$57) -> 5.6974056e+09 | H6: =('分行业工业增加值（2012年美元）'!G16+'分行业工业增加值（2012年美元）'!G17)*'2020年全国投入产出表'!$H$57/('2020年全国投入产出表'!$G$57+'2020年全国投入产出表'!$H$57) -> 5.6127062e+09 | I6: =('分行业工业增加值（2012年美元）'!H16+'分行业工业增加值（2012年美元）'!H17)*'2020年全国投入产出表'!$H$57/('2020年全国投入产出表'!$G$57+'2020年全国投入产出表'!$H$57) -> 5.5240404e+09 | J6: =('分行业工业增加值（2012年美元）'!I16+'分行业工业增加值（2012年美元）'!I17)*'2020年全国投入产出表'!$H$57/('2020年全国投入产出表'!$G$57+'2020年全国投入产出表'!$H$57) -> 5.4325342e+09 | ... AR6: =('分行业工业增加值（2012年美元）'!AQ16+'分行业工业增加值（2012年美元）'!AQ17)*'2020年全国投入产出表'!$H$57/('2020年全国投入产出表'!$G$57+'2020年全国投入产出表'!$H$57) -> 3.0126803e+09
A7: 食品和烟草 | B7: ISIC 10T12 | C7: 3.9921843e+11 | D7: 3.954455e+11 | E7: 4.5408002e+11 | F7: 4.6052429e+11 | G7: 4.6611839e+11 | H7: 4.7093967e+11 | I7: 4.7506521e+11 | J7: 4.7856925e+11 | K7: 4.8152163e+11 | L7: 4.8398685e+11 | M7: 4.8602365e+11 | N7: 4.8768495e+11 | O7: 4.8901804e+11 | P7: 4.9006491e+11 | Q7: 4.9086265e+11 | R7: 4.914439e+11 | S7: 4.9183731e+11 | T7: 4.9206794e+11 | U7: 4.9215771e+11 | V7: 4.9212575e+11 | W7: 4.9198874e+11 | X7: 4.9176126e+11 | Y7: 4.9145597e+11 | Z7: 4.9108395e+11 | AA7: 4.9065484e+11 | AB7: 4.9017705e+11 | AC7: 4.8965793e+11 | AD7: 4.8910389e+11 | AE7: 4.8852052e+11 | AF7: 4.8791272e+11 | AG7: 4.8728476e+11 | AH7: 4.8664037e+11 | AI7: 4.8598284e+11 | AJ7: 4.8531503e+11 | AK7: 4.8463943e+11 | AL7: 4.8395825e+11 | AM7: 4.832734e+11 | AN7: 4.8258657e+11 | AO7: 4.8189922e+11 | AP7: 4.8121264e+11 | AQ7: 4.8052796e+11 | AR7: 4.7984614e+11
A8: 纺织品、纺织服装鞋帽皮革羽绒及其制品 | B8: ISIC 13T15 | C8: ='分行业工业增加值（2012年美元）'!B19+'分行业工业增加值（2012年美元）'!B20 -> 1.9860428e+11 | D8: ='分行业工业增加值（2012年美元）'!C19+'分行业工业增加值（2012年美元）'!C20 -> 1.7641567e+11 | E8: ='分行业工业增加值（2012年美元）'!D19+'分行业工业增加值（2012年美元）'!D20 -> 1.9255051e+11 | F8: ='分行业工业增加值（2012年美元）'!E19+'分行业工业增加值（2012年美元）'!E20 -> 1.9015459e+11 | G8: ='分行业工业增加值（2012年美元）'!F19+'分行业工业增加值（2012年美元）'!F20 -> 1.8753924e+11 | H8: ='分行业工业增加值（2012年美元）'!G19+'分行业工业增加值（2012年美元）'!G20 -> 1.8475122e+11 | I8: ='分行业工业增加值（2012年美元）'!H19+'分行业工业增加值（2012年美元）'!H20 -> 1.8183265e+11 | J8: ='分行业工业增加值（2012年美元）'!I19+'分行业工业增加值（2012年美元）'!I20 -> 1.7882057e+11 | ... AR8: ='分行业工业增加值（2012年美元）'!AQ19+'分行业工业增加值（2012年美元）'!AQ20 -> 9.9167202e+10
A9: 木材加工品和家具 | B9: ISIC 16 | C9: 7.2724991e+10 | D9: 6.7232207e+10 | E9: 7.8201548e+10 | F9: 7.7530363e+10 | G9: 7.6761756e+10 | H9: 7.5913896e+10 | I9: 7.5003332e+10 | J9: 7.4044785e+10 | K9: 7.3051111e+10 | L9: 7.2033362e+10 | M9: 7.1000913e+10 | N9: 6.9961616e+10 | O9: 6.8921975e+10 | P9: 6.7887319e+10 | Q9: 6.6861956e+10 | R9: 6.5849333e+10 | S9: 6.485216e+10 | T9: 6.387253e+10 | U9: 6.2912024e+10 | V9: 6.1971795e+10 | W9: 6.1052645e+10 | X9: 6.0155085e+10 | Y9: 5.9279393e+10 | Z9: 5.8425655e+10 | AA9: 5.7593803e+10 | AB9: 5.6783649e+10 | AC9: 5.5994907e+10 | AD9: 5.5227215e+10 | AE9: 5.4480156e+10 | AF9: 5.3753268e+10 | AG9: 5.3046058e+10 | AH9: 5.2358012e+10 | AI9: 5.1688603e+10 | AJ9: 5.1037297e+10 | AK9: 5.0403556e+10 | AL9: 4.9786846e+10 | AM9: 4.9186638e+10 | AN9: 4.860241e+10 | AO9: 4.8033651e+10 | AP9: 4.747986e+10 | AQ9: 4.6940551e+10 | AR9: 4.6415248e+10
A10: 造纸印刷和文教体育用品 | B10: ISIC 17T18 | C10: 1.3659338e+11 | D10: 1.3268003e+11 | E10: 1.5519989e+11 | F10: 1.5800115e+11 | G10: 1.6049536e+11 | H10: 1.6270733e+11 | I10: 1.646623e+11 | J10: 1.6638501e+11 | K10: 1.6789903e+11 | L10: 1.6922644e+11 | M10: 1.7038756e+11 | N10: 1.714009e+11 | O10: 1.7228317e+11 | P10: 1.7304938e+11 | Q10: 1.7371289e+11 | R10: 1.7428559e+11 | S10: 1.7477802e+11 | T10: 1.7519949e+11 | U10: 1.7555824e+11 | V10: 1.7586151e+11 | W10: 1.7611572e+11 | X10: 1.7632651e+11 | Y10: 1.7649885e+11 | Z10: 1.7663713e+11 | AA10: 1.7674525e+11 | AB10: 1.7682661e+11 | AC10: 1.7688426e+11 | AD10: 1.7692087e+11 | AE10: 1.7693883e+11 | AF10: 1.7694024e+11 | AG10: 1.7692698e+11 | AH10: 1.7690072e+11 | AI10: 1.7686293e+11 | AJ10: 1.7681495e+11 | AK10: 1.7675795e+11 | AL10: 1.76693e+11 | AM10: 1.7662104e+11 | AN10: 1.7654291e+11 | AO10: 1.7645937e+11 | AP10: 1.7637111e+11 | AQ10: 1.7627874e+11 | AR10: 1.7618281e+11
A11: 石油、炼焦产品和核燃料加工品 | B11: ISIC 19 | C11: 1.5693475e+11 | D11: 1.4488329e+11 | E11: 1.8531164e+11 | F11: 1.9339027e+11 | G11: 2.0097205e+11 | H11: 2.0807372e+11 | I11: 2.1471672e+11 | J11: 2.2092542e+11 | K11: 2.2672581e+11 | L11: 2.3214436e+11 | M11: 2.3720732e+11 | N11: 2.4194014e+11 | O11: 2.4636714e+11 | P11: 2.5051129e+11 | Q11: 2.5439407e+11 | R11: 2.5803547e+11 | S11: 2.6145398e+11 | T11: 2.6466661e+11 | U11: 2.6768904e+11 | V11: 2.7053562e+11 | W11: 2.732195e+11 | X11: 2.7575272e+11 | Y11: 2.7814631e+11 | Z11: 2.8041034e+11 | AA11: 2.8255403e+11 | AB11: 2.8458583e+11 | AC11: 2.8651348e+11 | AD11: 2.8834408e+11 | AE11: 2.9008413e+11 | AF11: 2.9173964e+11 | AG11: 2.9331609e+11 | AH11: 2.9481856e+11 | AI11: 2.9625171e+11 | AJ11: 2.9761987e+11 | AK11: 2.9892702e+11 | AL11: 3.0017685e+11 | AM11: 3.0137276e+11 | AN11: 3.0251792e+11 | AO11: 3.0361528e+11 | AP11: 3.0466757e+11 | AQ11: 3.0567733e+11 | AR11: 3.0664692e+11
A12: 化学原料和化学制品制造业&化学纤维制造业 | B12: ISIC 20 | C12: ='分行业工业增加值（2012年美元）'!B24*'2020年全国投入产出表'!$N$57/('2020年全国投入产出表'!$N$57+'2020年全国投入产出表'!$O$57+'2020年全国投入产出表'!$P$57) -> 2.8098844e+11 | D12: ='分行业工业增加值（2012年美元）'!C24*'2020年全国投入产出表'!$N$57/('2020年全国投入产出表'!$N$57+'2020年全国投入产出表'!$O$57+'2020年全国投入产出表'!$P$57) -> 2.7555969e+11 | E12: ='分行业工业增加值（2012年美元）'!D24*'2020年全国投入产出表'!$N$57/('2020年全国投入产出表'!$N$57+'2020年全国投入产出表'!$O$57+'2020年全国投入产出表'!$P$57) -> 3.2813085e+11 | F12: ='分行业工业增加值（2012年美元）'!E24*'2020年全国投入产出表'!$N$57/('2020年全国投入产出表'!$N$57+'2020年全国投入产出表'!$O$57+'2020年全国投入产出表'!$P$57) -> 3.3586195e+11 | G12: ='分行业工业增加值（2012年美元）'!F24*'2020年全国投入产出表'!$N$57/('2020年全国投入产出表'!$N$57+'2020年全国投入产出表'!$O$57+'2020年全国投入产出表'!$P$57) -> 3.4289413e+11 | H12: ='分行业工业增加值（2012年美元）'!G24*'2020年全国投入产出表'!$N$57/('2020年全国投入产出表'!$N$57+'2020年全国投入产出表'!$O$57+'2020年全国投入产出表'!$P$57) -> 3.4927491e+11 | I12: ='分行业工业增加值（2012年美元）'!H24*'2020年全国投入产出表'!$N$57/('2020年全国投入产出表'!$N$57+'2020年全国投入产出表'!$O$57+'2020年全国投入产出表'!$P$57) -> 3.5505433e+11 | J12: ='分行业工业增加值（2012年美元）'!I24*'2020年全国投入产出表'!$N$57/('2020年全国投入产出表'!$N$57+'2020年全国投入产出表'!$O$57+'2020年全国投入产出表'!$P$57) -> 3.6028271e+11 | ... AR12: ='分行业工业增加值（2012年美元）'!AQ24*'2020年全国投入产出表'!$N$57/('2020年全国投入产出表'!$N$57+'2020年全国投入产出表'!$O$57+'2020年全国投入产出表'!$P$57) -> 4.0927768e+11
A13: 医药制造业 | B13: ISIC 21 | C13: ='分行业工业增加值（2012年美元）'!B24*'2020年全国投入产出表'!$O$57/('2020年全国投入产出表'!$N$57+'2020年全国投入产出表'!$O$57+'2020年全国投入产出表'!$P$57) -> 1.2180435e+11 | D13: ='分行业工业增加值（2012年美元）'!C24*'2020年全国投入产出表'!$O$57/('2020年全国投入产出表'!$N$57+'2020年全国投入产出表'!$O$57+'2020年全国投入产出表'!$P$57) -> 1.1945107e+11 | E13: ='分行业工业增加值（2012年美元）'!D24*'2020年全国投入产出表'!$O$57/('2020年全国投入产出表'!$N$57+'2020年全国投入产出表'!$O$57+'2020年全国投入产出表'!$P$57) -> 1.4223989e+11 | F13: ='分行业工业增加值（2012年美元）'!E24*'2020年全国投入产出表'!$O$57/('2020年全国投入产出表'!$N$57+'2020年全国投入产出表'!$O$57+'2020年全国投入产出表'!$P$57) -> 1.4559121e+11 | G13: ='分行业工业增加值（2012年美元）'!F24*'2020年全国投入产出表'!$O$57/('2020年全国投入产出表'!$N$57+'2020年全国投入产出表'!$O$57+'2020年全国投入产出表'!$P$57) -> 1.4863955e+11 | H13: ='分行业工业增加值（2012年美元）'!G24*'2020年全国投入产出表'!$O$57/('2020年全国投入产出表'!$N$57+'2020年全国投入产出表'!$O$57+'2020年全国投入产出表'!$P$57) -> 1.5140553e+11 | I13: ='分行业工业增加值（2012年美元）'!H24*'2020年全国投入产出表'!$O$57/('2020年全国投入产出表'!$N$57+'2020年全国投入产出表'!$O$57+'2020年全国投入产出表'!$P$57) -> 1.5391082e+11 | J13: ='分行业工业增加值（2012年美元）'!I24*'2020年全国投入产出表'!$O$57/('2020年全国投入产出表'!$N$57+'2020年全国投入产出表'!$O$57+'2020年全国投入产出表'!$P$57) -> 1.5617725e+11 | ... AR13: ='分行业工业增加值（2012年美元）'!AQ24*'2020年全国投入产出表'!$O$57/('2020年全国投入产出表'!$N$57+'2020年全国投入产出表'!$O$57+'2020年全国投入产出表'!$P$57) -> 1.7741585e+11
A14: 橡胶和塑料制品业 | B14: ISIC 22 | C14: ='分行业工业增加值（2012年美元）'!B24*'2020年全国投入产出表'!$P$57/('2020年全国投入产出表'!$N$57+'2020年全国投入产出表'!$O$57+'2020年全国投入产出表'!$P$57) -> 1.2266035e+11 | D14: ='分行业工业增加值（2012年美元）'!C24*'2020年全国投入产出表'!$P$57/('2020年全国投入产出表'!$N$57+'2020年全国投入产出表'!$O$57+'2020年全国投入产出表'!$P$57) -> 1.2029053e+11 | E14: ='分行业工业增加值（2012年美元）'!D24*'2020年全国投入产出表'!$P$57/('2020年全国投入产出表'!$N$57+'2020年全国投入产出表'!$O$57+'2020年全国投入产出表'!$P$57) -> 1.432395e+11 | F14: ='分行业工业增加值（2012年美元）'!E24*'2020年全国投入产出表'!$P$57/('2020年全国投入产出表'!$N$57+'2020年全国投入产出表'!$O$57+'2020年全国投入产出表'!$P$57) -> 1.4661437e+11 | G14: ='分行业工业增加值（2012年美元）'!F24*'2020年全国投入产出表'!$P$57/('2020年全国投入产出表'!$N$57+'2020年全国投入产出表'!$O$57+'2020年全国投入产出表'!$P$57) -> 1.4968414e+11 | H14: ='分行业工业增加值（2012年美元）'!G24*'2020年全国投入产出表'!$P$57/('2020年全国投入产出表'!$N$57+'2020年全国投入产出表'!$O$57+'2020年全国投入产出表'!$P$57) -> 1.5246956e+11 | I14: ='分行业工业增加值（2012年美元）'!H24*'2020年全国投入产出表'!$P$57/('2020年全国投入产出表'!$N$57+'2020年全国投入产出表'!$O$57+'2020年全国投入产出表'!$P$57) -> 1.5499245e+11 | J14: ='分行业工业增加值（2012年美元）'!I24*'2020年全国投入产出表'!$P$57/('2020年全国投入产出表'!$N$57+'2020年全国投入产出表'!$O$57+'2020年全国投入产出表'!$P$57) -> 1.5727481e+11 | ... AR14: ='分行业工业增加值（2012年美元）'!AQ24*'2020年全国投入产出表'!$P$57/('2020年全国投入产出表'!$N$57+'2020年全国投入产出表'!$O$57+'2020年全国投入产出表'!$P$57) -> 1.7866267e+11
A15: 非金属矿物制品 | B15: ISIC 231 | C15: 2.5096673e+11 | D15: 2.3842282e+11 | E15: 2.8166432e+11 | F15: 2.9105099e+11 | G15: 2.9976206e+11 | H15: 3.0783082e+11 | I15: 3.1529517e+11 | J15: 3.2219533e+11 | K15: 3.2857211e+11 | L15: 3.3446568e+11 | M15: 3.3991471e+11 | N15: 3.4495586e+11 | O15: 3.4962341e+11 | P15: 3.5394919e+11 | Q15: 3.5796248e+11 | R15: 3.6169012e+11 | S15: 3.6515659e+11 | T15: 3.6838418e+11 | U15: 3.7139311e+11 | V15: 3.7420174e+11 | W15: 3.768267e+11 | X15: 3.7928303e+11 | Y15: 3.8158439e+11 | Z15: 3.8374315e+11 | AA15: 3.8577052e+11 | AB15: 3.8767667e+11 | AC15: 3.8947085e+11 | AD15: 3.9116146e+11 | AE15: 3.9275618e+11 | AF15: 3.9426196e+11 | AG15: 3.9568519e+11 | AH15: 3.9703168e+11 | AI15: 3.9830677e+11 | AJ15: 3.9951535e+11 | AK15: 4.0066189e+11 | AL15: 4.0175052e+11 | AM15: 4.0278503e+11 | AN15: 4.0376892e+11 | AO15: 4.0470541e+11 | AP15: 4.0559749e+11 | AQ15: 4.0644791e+11 | AR15: 4.0725923e+11
A16: 专用设备 | B16: ISIC 239 | C16: 1.4571489e+11 | D16: 1.6474511e+11 | E16: 1.7342079e+11 | F16: 1.7758186e+11 | G16: 1.8137149e+11 | H16: 1.8481456e+11 | I16: 1.8793741e+11 | J16: 1.9076653e+11 | K16: 1.9332782e+11 | L16: 1.9564595e+11 | M16: 1.9774406e+11 | N16: 1.9964358e+11 | O16: 2.0136413e+11 | P16: 2.0292356e+11 | Q16: 2.0433803e+11 | R16: 2.0562207e+11 | S16: 2.0678874e+11 | T16: 2.0784975e+11 | U16: 2.0881555e+11 | V16: 2.0969549e+11 | W16: 2.1049794e+11 | X16: 2.1123035e+11 | Y16: 2.1189938e+11 | Z16: 2.12511e+11 | AA16: 2.1307055e+11 | AB16: 2.1358279e+11 | AC16: 2.1405202e+11 | AD16: 2.1448208e+11 | AE16: 2.1487643e+11 | AF16: 2.1523817e+11 | AG16: 2.1557012e+11 | AH16: 2.1587481e+11 | AI16: 2.1615453e+11 | AJ16: 2.1641135e+11 | AK16: 2.1664715e+11 | AL16: 2.1686365e+11 | AM16: 2.1706239e+11 | AN16: 2.172448e+11 | AO16: 2.1741216e+11 | AP16: 2.1756566e+11 | AQ16: 2.1770637e+11 | AR16: 2.1783528e+11
A17: 黑色金属冶炼和压延加工品 | B17: ISIC 241 | C17: ='分行业工业增加值（2012年美元）'!B26*'2020年全国投入产出表'!$R$57/('2020年全国投入产出表'!$R$57+'2020年全国投入产出表'!$S$57) -> 2.076147e+11 | D17: ='分行业工业增加值（2012年美元）'!C26*'2020年全国投入产出表'!$R$57/('2020年全国投入产出表'!$R$57+'2020年全国投入产出表'!$S$57) -> 2.0576027e+11 | E17: ='分行业工业增加值（2012年美元）'!D26*'2020年全国投入产出表'!$R$57/('2020年全国投入产出表'!$R$57+'2020年全国投入产出表'!$S$57) -> 2.3206687e+11 | F17: ='分行业工业增加值（2012年美元）'!E26*'2020年全国投入产出表'!$R$57/('2020年全国投入产出表'!$R$57+'2020年全国投入产出表'!$S$57) -> 2.3765177e+11 | G17: ='分行业工业增加值（2012年美元）'!F26*'2020年全国投入产出表'!$R$57/('2020年全国投入产出表'!$R$57+'2020年全国投入产出表'!$S$57) -> 2.4273914e+11 | H17: ='分行业工业增加值（2012年美元）'!G26*'2020年全国投入产出表'!$R$57/('2020年全国投入产出表'!$R$57+'2020年全国投入产出表'!$S$57) -> 2.4736227e+11 | I17: ='分行业工业增加值（2012年美元）'!H26*'2020年全国投入产出表'!$R$57/('2020年全国投入产出表'!$R$57+'2020年全国投入产出表'!$S$57) -> 2.5155634e+11 | J17: ='分行业工业增加值（2012年美元）'!I26*'2020年全国投入产出表'!$R$57/('2020年全国投入产出表'!$R$57+'2020年全国投入产出表'!$S$57) -> 2.5535681e+11 | ... AR17: ='分行业工业增加值（2012年美元）'!AQ26*'2020年全国投入产出表'!$R$57/('2020年全国投入产出表'!$R$57+'2020年全国投入产出表'!$S$57) -> 2.9184001e+11
A18: 有色金属冶炼和压延加工品 | B18: ISIC 242 | C18: ='分行业工业增加值（2012年美元）'!B26*'2020年全国投入产出表'!$S$57/('2020年全国投入产出表'!$R$57+'2020年全国投入产出表'!$S$57) -> 1.5884158e+11 | D18: ='分行业工业增加值（2012年美元）'!C26*'2020年全国投入产出表'!$S$57/('2020年全国投入产出表'!$R$57+'2020年全国投入产出表'!$S$57) -> 1.574228e+11 | E18: ='分行业工业增加值（2012年美元）'!D26*'2020年全国投入产出表'!$S$57/('2020年全国投入产出表'!$R$57+'2020年全国投入产出表'!$S$57) -> 1.7754941e+11 | F18: ='分行业工业增加值（2012年美元）'!E26*'2020年全国投入产出表'!$S$57/('2020年全国投入产出表'!$R$57+'2020年全国投入产出表'!$S$57) -> 1.818223e+11 | G18: ='分行业工业增加值（2012年美元）'!F26*'2020年全国投入产出表'!$S$57/('2020年全国投入产出表'!$R$57+'2020年全国投入产出表'!$S$57) -> 1.8571454e+11 | H18: ='分行业工业增加值（2012年美元）'!G26*'2020年全国投入产出表'!$S$57/('2020年全国投入产出表'!$R$57+'2020年全国投入产出表'!$S$57) -> 1.892516e+11 | I18: ='分行业工业增加值（2012年美元）'!H26*'2020年全国投入产出表'!$S$57/('2020年全国投入产出表'!$R$57+'2020年全国投入产出表'!$S$57) -> 1.9246039e+11 | J18: ='分行业工业增加值（2012年美元）'!I26*'2020年全国投入产出表'!$S$57/('2020年全国投入产出表'!$R$57+'2020年全国投入产出表'!$S$57) -> 1.9536805e+11 | ... AR18: ='分行业工业增加值（2012年美元）'!AQ26*'2020年全国投入产出表'!$S$57/('2020年全国投入产出表'!$R$57+'2020年全国投入产出表'!$S$57) -> 2.2328056e+11
A19: 金属制品 | B19: ISIC 25 | C19: 1.4220559e+11 | D19: 1.4161073e+11 | E19: 1.592049e+11 | F19: 1.6239659e+11 | G19: 1.6526457e+11 | H19: 1.678334e+11 | I19: 1.701284e+11 | J19: 1.7217458e+11 | K19: 1.7399601e+11 | L19: 1.7561532e+11 | M19: 1.7705349e+11 | N19: 1.7832974e+11 | O19: 1.7946151e+11 | P19: 1.8046452e+11 | Q19: 1.8135286e+11 | R19: 1.8213911e+11 | S19: 1.8283448e+11 | T19: 1.8344892e+11 | U19: 1.8399126e+11 | V19: 1.8446934e+11 | W19: 1.8489008e+11 | X19: 1.8525964e+11 | Y19: 1.8558347e+11 | Z19: 1.8586638e+11 | AA19: 1.8611268e+11 | AB19: 1.8632617e+11 | AC19: 1.8651023e+11 | AD19: 1.8666788e+11 | AE19: 1.8680181e+11 | AF19: 1.869144e+11 | AG19: 1.8700781e+11 | AH19: 1.8708395e+11 | AI19: 1.8714454e+11 | AJ19: 1.8719112e+11 | AK19: 1.8722508e+11 | AL19: 1.8724766e+11 | AM19: 1.8725999e+11 | AN19: 1.8726308e+11 | AO19: 1.8725784e+11 | AP19: 1.8724511e+11 | AQ19: 1.8722563e+11 | AR19: 1.8720008e+11
A20: 通信设备、计算机和其他电子设备&仪器仪表 | B20: ISIC 26 | C20: ='分行业工业增加值（2012年美元）'!B32+'分行业工业增加值（2012年美元）'!B33 -> 4.2488482e+11 | D20: ='分行业工业增加值（2012年美元）'!C32+'分行业工业增加值（2012年美元）'!C33 -> 4.4834648e+11 | E20: ='分行业工业增加值（2012年美元）'!D32+'分行业工业增加值（2012年美元）'!D33 -> 5.2538253e+11 | F20: ='分行业工业增加值（2012年美元）'!E32+'分行业工业增加值（2012年美元）'!E33 -> 5.5270946e+11 | G20: ='分行业工业增加值（2012年美元）'!F32+'分行业工业增加值（2012年美元）'!F33 -> 5.7850613e+11 | H20: ='分行业工业增加值（2012年美元）'!G32+'分行业工业增加值（2012年美元）'!G33 -> 6.0280791e+11 | I20: ='分行业工业增加值（2012年美元）'!H32+'分行业工业增加值（2012年美元）'!H33 -> 6.2566742e+11 | J20: ='分行业工业增加值（2012年美元）'!I32+'分行业工业增加值（2012年美元）'!I33 -> 6.4714903e+11 | ... AR20: ='分行业工业增加值（2012年美元）'!AQ32+'分行业工业增加值（2012年美元）'!AQ33 -> 9.593422e+11
A21: 电气机械和器材 | B21: ISIC 27 | C21: 2.6096698e+11 | D21: 2.70549e+11 | E21: 3.1628975e+11 | F21: 3.2680121e+11 | G21: 3.3655482e+11 | H21: 3.4558804e+11 | I21: 3.5394349e+11 | J21: 3.6166635e+11 | K21: 3.6880247e+11 | L21: 3.7539695e+11 | M21: 3.8149322e+11 | N21: 3.8713241e+11 | O21: 3.92353e+11 | P21: 3.9719068e+11 | Q21: 4.0167832e+11 | R21: 4.05846e+11 | S21: 4.097212e+11 | T21: 4.1332889e+11 | U21: 4.1669175e+11 | V21: 4.1983037e+11 | W21: 4.2276336e+11 | X21: 4.2550762e+11 | Y21: 4.2807843e+11 | Z21: 4.3048965e+11 | AA21: 4.3275385e+11 | AB21: 4.3488242e+11 | AC21: 4.3688573e+11 | AD21: 4.3877318e+11 | AE21: 4.4055336e+11 | AF21: 4.4223408e+11 | AG21: 4.4382247e+11 | AH21: 4.4532505e+11 | AI21: 4.4674779e+11 | AJ21: 4.4809617e+11 | AK21: 4.493752e+11 | AL21: 4.5058948e+11 | AM21: 4.5174328e+11 | AN21: 4.528405e+11 | AO21: 4.5388476e+11 | AP21: 4.5487938e+11 | AQ21: 4.5582745e+11 | AR21: 4.5673183e+11
A22: 通用设备 | B22: ISIC 28 | C22: 1.755779e+11 | D22: 1.7883121e+11 | E22: 1.9744431e+11 | F22: 2.0055218e+11 | G22: 2.0328197e+11 | H22: 2.0566647e+11 | I22: 2.0773865e+11 | J22: 2.0953044e+11 | K22: 2.1107209e+11 | L22: 2.1239163e+11 | M22: 2.1351474e+11 | N22: 2.1446465e+11 | O22: 2.1526221e+11 | P22: 2.1592599e+11 | Q22: 2.1647248e+11 | R22: 2.1691625e+11 | S22: 2.1727013e+11 | T22: 2.1754541e+11 | U22: 2.17752e+11 | V22: 2.1789857e+11 | W22: 2.1799274e+11 | X22: 2.1804119e+11 | Y22: 2.1804975e+11 | Z22: 2.1802356e+11 | AA22: 2.1796709e+11 | AB22: 2.178843e+11 | AC22: 2.1777863e+11 | AD22: 2.1765313e+11 | AE22: 2.1751048e+11 | AF22: 2.1735301e+11 | AG22: 2.171828e+11 | AH22: 2.1700168e+11 | AI22: 2.1681125e+11 | AJ22: 2.1661294e+11 | AK22: 2.16408e+11 | AL22: 2.1619754e+11 | AM22: 2.1598254e+11 | AN22: 2.1576388e+11 | AO22: 2.1554233e+11 | AP22: 2.1531856e+11 | AQ22: 2.1509319e+11 | AR22: 2.1486675e+11
A23: 汽车制造业 | B23: ISIC 29 | C23: ='分行业工业增加值（2012年美元）'!B30*'2020年全国投入产出表'!$W$57/('2020年全国投入产出表'!$W$57+'2020年全国投入产出表'!$X$57) -> 3.0236911e+11 | D23: ='分行业工业增加值（2012年美元）'!C30*'2020年全国投入产出表'!$W$57/('2020年全国投入产出表'!$W$57+'2020年全国投入产出表'!$X$57) -> 2.9147996e+11 | E23: ='分行业工业增加值（2012年美元）'!D30*'2020年全国投入产出表'!$W$57/('2020年全国投入产出表'!$W$57+'2020年全国投入产出表'!$X$57) -> 3.5672841e+11 | F23: ='分行业工业增加值（2012年美元）'!E30*'2020年全国投入产出表'!$W$57/('2020年全国投入产出表'!$W$57+'2020年全国投入产出表'!$X$57) -> 3.6887346e+11 | G23: ='分行业工业增加值（2012年美元）'!F30*'2020年全国投入产出表'!$W$57/('2020年全国投入产出表'!$W$57+'2020年全国投入产出表'!$X$57) -> 3.8015579e+11 | H23: ='分行业工业增加值（2012年美元）'!G30*'2020年全国投入产出表'!$W$57/('2020年全国投入产出表'!$W$57+'2020年全国投入产出表'!$X$57) -> 3.9061688e+11 | I23: ='分行业工业增加值（2012年美元）'!H30*'2020年全国投入产出表'!$W$57/('2020年全国投入产出表'!$W$57+'2020年全国投入产出表'!$X$57) -> 4.0030425e+11 | J23: ='分行业工业增加值（2012年美元）'!I30*'2020年全国投入产出表'!$W$57/('2020年全国投入产出表'!$W$57+'2020年全国投入产出表'!$X$57) -> 4.0926854e+11 | ... AR23: ='分行业工业增加值（2012年美元）'!AQ30*'2020年全国投入产出表'!$W$57/('2020年全国投入产出表'!$W$57+'2020年全国投入产出表'!$X$57) -> 5.2101787e+11
A24: 铁路、船舶、航空航天和其他运输设备 | B24: ISIC 30 | C24: ='分行业工业增加值（2012年美元）'!B30*'2020年全国投入产出表'!$X$57/('2020年全国投入产出表'!$W$57+'2020年全国投入产出表'!$X$57) -> 6.7013316e+10 | D24: ='分行业工业增加值（2012年美元）'!C30*'2020年全国投入产出表'!$X$57/('2020年全国投入产出表'!$W$57+'2020年全国投入产出表'!$X$57) -> 6.4599982e+10 | E24: ='分行业工业增加值（2012年美元）'!D30*'2020年全国投入产出表'!$X$57/('2020年全国投入产出表'!$W$57+'2020年全国投入产出表'!$X$57) -> 7.9060834e+10 | F24: ='分行业工业增加值（2012年美元）'!E30*'2020年全国投入产出表'!$X$57/('2020年全国投入产出表'!$W$57+'2020年全国投入产出表'!$X$57) -> 8.1752511e+10 | G24: ='分行业工业增加值（2012年美元）'!F30*'2020年全国投入产出表'!$X$57/('2020年全国投入产出表'!$W$57+'2020年全国投入产出表'!$X$57) -> 8.4252986e+10 | H24: ='分行业工业增加值（2012年美元）'!G30*'2020年全国投入产出表'!$X$57/('2020年全国投入产出表'!$W$57+'2020年全国投入产出表'!$X$57) -> 8.6571451e+10 | I24: ='分行业工业增加值（2012年美元）'!H30*'2020年全国投入产出表'!$X$57/('2020年全国投入产出表'!$W$57+'2020年全国投入产出表'!$X$57) -> 8.8718438e+10 | J24: ='分行业工业增加值（2012年美元）'!I30*'2020年全国投入产出表'!$X$57/('2020年全国投入产出表'!$W$57+'2020年全国投入产出表'!$X$57) -> 9.0705174e+10 | ... AR24: ='分行业工业增加值（2012年美元）'!AQ30*'2020年全国投入产出表'!$X$57/('2020年全国投入产出表'!$W$57+'2020年全国投入产出表'!$X$57) -> 1.154719e+11
A25: 其他制造产品和废品废料、金属制品、机械和设备修理服务 | B25: ISIC 31T33 | C25: ='分行业工业增加值（2012年美元）'!B34+'分行业工业增加值（2012年美元）'!B35 -> 5.4514348e+10 | D25: ='分行业工业增加值（2012年美元）'!C34+'分行业工业增加值（2012年美元）'!C35 -> 5.7424604e+10 | E25: ='分行业工业增加值（2012年美元）'!D34+'分行业工业增加值（2012年美元）'!D35 -> 6.037338e+10 | F25: ='分行业工业增加值（2012年美元）'!E34+'分行业工业增加值（2012年美元）'!E35 -> 6.156845e+10 | G25: ='分行业工业增加值（2012年美元）'!F34+'分行业工业增加值（2012年美元）'!F35 -> 6.2641179e+10 | H25: ='分行业工业增加值（2012年美元）'!G34+'分行业工业增加值（2012年美元）'!G35 -> 6.3600931e+10 | I25: ='分行业工业增加值（2012年美元）'!H34+'分行业工业增加值（2012年美元）'!H35 -> 6.4457329e+10 | J25: ='分行业工业增加值（2012年美元）'!I34+'分行业工业增加值（2012年美元）'!I35 -> 6.521988e+10 | ... AR25: ='分行业工业增加值（2012年美元）'!AQ34+'分行业工业增加值（2012年美元）'!AQ35 -> 7.0678908e+10
A26: 电力、热力生产和供应 | B26: ISIC 351 | C26: 3.028634e+11 | D26: 3.082222e+11 | E26: 3.5172454e+11 | F26: 3.6767491e+11 | G26: 3.8266531e+11 | H26: 3.9672579e+11 | I26: 4.0989591e+11 | J26: 4.2222128e+11 | K26: 4.3375091e+11 | L26: 4.4453509e+11 | M26: 4.5462387e+11 | N26: 4.6406602e+11 | O26: 4.7290826e+11 | P26: 4.8119483e+11 | Q26: 4.8896724e+11 | R26: 4.9626417e+11 | S26: 5.0312148e+11 | T26: 5.0957226e+11 | U26: 5.1564699e+11 | V26: 5.2137367e+11 | W26: 5.2677798e+11 | X26: 5.3188347e+11 | Y26: 5.367117e+11 | Z26: 5.4128243e+11 | AA26: 5.4561378e+11 | AB26: 5.4972233e+11 | AC26: 5.5362333e+11 | AD26: 5.5733073e+11 | AE26: 5.608574e+11 | AF26: 5.6421513e+11 | AG26: 5.674148e+11 | AH26: 5.7046643e+11 | AI26: 5.7337927e+11 | AJ26: 5.7616186e+11 | AK26: 5.7882209e+11 | AL26: 5.8136729e+11 | AM26: 5.8380422e+11 | AN26: 5.8613919e+11 | AO26: 5.8837803e+11 | AP26: 5.9052618e+11 | AQ26: 5.925887e+11 | AR26: 5.9457031e+11
A27: 燃气生产和供应 | B27: ISIC 352T353 | C27: 5.5490659e+10 | D27: 5.3534136e+10 | E27: 6.6447654e+10 | F27: 7.1702316e+10 | G27: 7.6713968e+10 | H27: 8.148218e+10 | I27: 8.6010306e+10 | J27: 9.0304531e+10 | K27: 9.4373069e+10 | L27: 9.822549e+10 | M27: 1.0187219e+11 | N27: 1.0532395e+11 | O27: 1.0859169e+11 | P27: 1.1168614e+11 | Q27: 1.1461777e+11 | R27: 1.1739662e+11 | S27: 1.2003226e+11 | T27: 1.2253374e+11 | U27: 1.2490958e+11 | V27: 1.2716777e+11 | W27: 1.2931577e+11 | X27: 1.3136053e+11 | Y27: 1.3330853e+11 | Z27: 1.3516579e+11 | AA27: 1.3693791e+11 | AB27: 1.3863009e+11 | AC27: 1.4024715e+11 | AD27: 1.4179358e+11 | AE27: 1.4327354e+11 | AF27: 1.4469091e+11 | AG27: 1.4604928e+11 | AH27: 1.4735201e+11 | AI27: 1.4860222e+11 | AJ27: 1.498028e+11 | AK27: 1.5095649e+11 | AL27: 1.5206579e+11 | AM27: 1.5313308e+11 | AN27: 1.5416057e+11 | AO27: 1.5515032e+11 | AP27: 156104264399 | AQ27: 1.5702422e+11 | AR27: 1.5791188e+11
A28: 水的生产和供应 | B28: ISIC 36T39 | C28: 2.3169001e+10 | D28: 2.6476477e+10 | E28: 2.7586764e+10 | F28: 2.8923832e+10 | G28: 3.0183239e+10 | H28: 3.136711e+10 | I28: 3.2478388e+10 | J28: 3.3520557e+10 | K28: 3.4497422e+10 | L28: 3.5412928e+10 | M28: 3.6271039e+10 | N28: 3.7075639e+10 | O28: 3.7830473e+10 | P28: 3.8539102e+10 | Q28: 3.9204883e+10 | R28: 3.9830954e+10 | S28: 4.0420235e+10 | T28: 4.0975429e+10 | U28: 4.1499033e+10 | V28: 4.1993346e+10 | W28: 4.2460482e+10 | X28: 4.2902386e+10 | Y28: 4.3320839e+10 | Z28: 4.3717481e+10 | AA28: 4.4093814e+10 | AB28: 4.4451221e+10 | AC28: 4.479097e+10 | AD28: 4.5114228e+10 | AE28: 4.5422068e+10 | AF28: 4.5715482e+10 | AG28: 4.5995379e+10 | AH28: 4.6262604e+10 | AI28: 4.6517932e+10 | AJ28: 4.6762085e+10 | AK28: 4.6995728e+10 | AL28: 4.7219479e+10 | AM28: 4.7433911e+10 | AN28: 4.7639558e+10 | AO28: 4.7836913e+10 | AP28: 4.8026438e+10 | AQ28: 4.8208563e+10 | AR28: 4.838369e+10
A29: 建筑 | B29: ISIC 41T43 | C29: 9.7807096e+11 | D29: 1.0052436e+12 | E29: 1.0784823e+12 | F29: 1.1331388e+12 | G29: 1.1879314e+12 | H29: 1.2423347e+12 | I29: 1.2971166e+12 | J29: 1.3515139e+12 | K29: 1.4056901e+12 | L29: 1.4598036e+12 | M29: 1.5133508e+12 | N29: 1.566773e+12 | O29: 1.6197826e+12 | P29: 1.6720842e+12 | Q29: 1.724151e+12 | R29: 1.7756355e+12 | S29: 1.8263734e+12 | T29: 1.8766908e+12 | U29: 1.9263066e+12 | V29: 1.9755112e+12 | W29: 2.0239519e+12 | X29: 2.0715771e+12 | Y29: 2.1186679e+12 | Z29: 2.1650587e+12 | AA29: 2.2107571e+12 | AB29: 2.2556831e+12 | AC29: 2.3000054e+12 | AD29: 2.3437782e+12 | AE29: 2.3867645e+12 | AF29: 2.4290902e+12 | AG29: 2.4710211e+12 | AH29: 2.5122898e+12 | AI29: 2.5531041e+12 | AJ29: 2.5934746e+12 | AK29: 2.6333995e+12 | AL29: 2.6730582e+12 | AM29: 2.7125141e+12 | AN29: 2.7518936e+12 | AO29: 2.7911755e+12 | AP29: 2.8305465e+12 | AQ29: 2.8701774e+12 | AR29: 2.9100658e+12
A30: 批发和零售 | B30: ISIC 45T47 | C30: 1.3177809e+12 | D30: 1.3083408e+12 | E30: 1.4853343e+12 | F30: 1.5661282e+12 | G30: 1.6471163e+12 | H30: 1.7274492e+12 | I30: 1.8081074e+12 | J30: 1.8882553e+12 | K30: 1.9677725e+12 | L30: 2.0473566e+12 | M30: 2.1259887e+12 | N30: 2.2041136e+12 | O30: 2.2818081e+12 | P30: 2.3583752e+12 | Q30: 2.4345134e+12 | R30: 2.5097842e+12 | S30: 2.5838353e+12 | T30: 2.657471e+12 | U30: 2.7299528e+12 | V30: 2.8017873e+12 | W30: 2.8727093e+12 | X30: 2.9424082e+12 | Y30: 3.0113997e+12 | Z30: 3.0794805e+12 | AA30: 3.1465079e+12 | AB30: 3.2126388e+12 | AC30: 3.277872e+12 | AD30: 3.342311e+12 | AE30: 3.4057229e+12 | AF30: 3.4681232e+12 | AG30: 3.5300899e+12 | AH30: 3.5909789e+12 | AI30: 3.6511636e+12 | AJ30: 3.7106509e+12 | AK30: 3.7692227e+12 | AL30: 3.8273883e+12 | AM30: 3.8848876e+12 | AN30: 3.9418361e+12 | AO30: 3.9984016e+12 | AP30: 4.0544419e+12 | AQ30: 4.1103275e+12 | AR30: 4.165883e+12
A31: 交通运输、仓储和邮政 | B31: ISIC 49T53 | C31: 5.9355954e+11 | D31: 5.724933e+11 | E31: 6.296468e+11 | F31: 6.5329309e+11 | G31: 6.7641094e+11 | H31: 6.988427e+11 | I31: 7.2098339e+11 | J31: 7.4252917e+11 | K31: 7.6347514e+11 | L31: 7.8400382e+11 | M31: 8.0389026e+11 | N31: 8.2328668e+11 | O31: 8.4216195e+11 | P31: 8.6038055e+11 | Q31: 8.781363e+11 | R31: 8.9534096e+11 | S31: 9.1193031e+11 | T31: 9.2807442e+11 | U31: 9.436056e+11 | V31: 9.5873263e+11 | W31: 9.7333368e+11 | X31: 9.87304e+11 | Y31: 1.0008753e+12 | Z31: 1.013994e+12 | AA31: 1.0265991e+12 | AB31: 1.038746e+12 | AC31: 1.0504719e+12 | AD31: 1.0618006e+12 | AE31: 1.0726565e+12 | AF31: 1.0830918e+12 | AG31: 1.093253e+12 | AH31: 1.1029781e+12 | AI31: 1.1123642e+12 | AJ31: 1.121455e+12 | AK31: 1.1301828e+12 | AL31: 1.1386689e+12 | AM31: 1.1468969e+12 | AN31: 1.1548887e+12 | AO31: 1.1626814e+12 | AP31: 1.1702713e+12 | AQ31: 1.1777544e+12 | AR31: 1.1850783e+12
A32: 住宿和餐饮 | B32: ISIC 55T56 | C32: 2.4867065e+11 | D32: 2.1881089e+11 | E32: 2.4002938e+11 | F32: 2.5714004e+11 | G32: 2.7467229e+11 | H32: 2.9247372e+11 | I32: 3.1075217e+11 | J32: 3.2931024e+11 | K32: 3.481447e+11 | L32: 3.6734068e+11 | M32: 3.867393e+11 | N32: 4.0642746e+11 | O32: 4.2634334e+11 | P32: 4.4637825e+11 | Q32: 4.6668337e+11 | R32: 4.8714535e+11 | S32: 5.0765986e+11 | T32: 5.2838432e+11 | U32: 5.4918577e+11 | V32: 5.7016814e+11 | W32: 5.9120727e+11 | X32: 6.1226371e+11 | Y32: 6.3344808e+11 | Z32: 6.5469204e+11 | AA32: 6.7595806e+11 | AB32: 6.9724985e+11 | AC32: 7.1858934e+11 | AD32: 7.4000953e+11 | AE32: 7.6144419e+11 | AF32: 7.8286946e+11 | AG32: 8.0445042e+11 | AH32: 8.2603504e+11 | AI32: 8.4771554e+11 | AJ32: 8.6950257e+11 | AK32: 8.9134941e+11 | AL32: 9.1337788e+11 | AM32: 9.3558376e+11 | AN32: 9.5799265e+11 | AO32: 9.806664e+11 | AP32: 1.003597e+12 | AQ32: 1.0269069e+12 | AR32: 1.050618e+12
A33: 信息传输、软件和信息技术服务 | B33: ISIC 58T60 | C33: 4.6864129e+11 | D33: 6.2225192e+11 | E33: 5.8279002e+11 | F33: 6.347674e+11 | G33: 6.8763866e+11 | H33: 7.4062226e+11 | I33: 7.9461084e+11 | J33: 8.4865867e+11 | K33: 9.0272563e+11 | L33: 9.5699302e+11 | M33: 1010747846292 | N33: 1.0642948e+12 | O33: 1.1174892e+12 | P33: 1.1699234e+12 | Q33: 1.221952e+12 | R33: 1.2732685e+12 | S33: 1.3235873e+12 | T33: 1.373361e+12 | U33: 1.4220654e+12 | V33: 1.4701138e+12 | W33: 1.5171401e+12 | X33: 1.5630395e+12 | Y33: 1.608115e+12 | Z33: 1.6521956e+12 | AA33: 1.6951845e+12 | AB33: 1.7371229e+12 | AC33: 1.7780306e+12 | AD33: 1.8179852e+12 | AE33: 1.8567834e+12 | AF33: 1.89442e+12 | AG33: 1.9312409e+12 | AH33: 1.9668169e+12 | AI33: 2.0013744e+12 | AJ33: 2.0348792e+12 | AK33: 2.0672085e+12 | AL33: 2.0985838e+12 | AM33: 2.1288958e+12 | AN33: 2.158123e+12 | AO33: 2.186296e+12 | AP33: 2.2133876e+12 | AQ33: 2.2394892e+12 | AR33: 2.2644828e+12
A34: 租赁和商务服务 | B34: ISIC 61 | C34: 5.5223884e+11 | D34: 7.6926918e+11 | E34: 7.4593773e+11 | F34: 8.1025751e+11 | G34: 8.766353e+11 | H34: 9.4376179e+11 | I34: 1.0125239e+12 | J34: 1.0819538e+12 | K34: 1.15159e+12 | L34: 1.22223e+12 | M34: 1.2924674e+12 | N34: 1.3625929e+12 | O34: 1.4327018e+12 | P34: 1.5018691e+12 | Q34: 1.5707799e+12 | R34: 1.6388294e+12 | S34: 1.7054855e+12 | T34: 1.7716971e+12 | U34: 1.8365007e+12 | V34: 1.9003874e+12 | W34: 1.9630466e+12 | X34: 2.0240404e+12 | Y34: 2.0840174e+12 | Z34: 2.1426319e+12 | AA34: 2.1997761e+12 | AB34: 2.2555286e+12 | AC34: 2.3098435e+12 | AD34: 2.3628406e+12 | AE34: 2.4143387e+12 | AF34: 2.4642213e+12 | AG34: 2.5130713e+12 | AH34: 2.5603417e+12 | AI34: 2.6063005e+12 | AJ34: 2.650894e+12 | AK34: 2.6940189e+12 | AL34: 2.7361689e+12 | AM34: 2.7769654e+12 | AN34: 2.8166328e+12 | AO34: 2.8552401e+12 | AP34: 2.8925958e+12 | AQ34: 2.9291261e+12 | AR34: 2.9646853e+12
A35: 研究和试验发展 | B35: ISIC 62T63 | C35: ='分行业工业增加值（2012年美元）'!B48*'2020年全国投入产出表'!$AM$57/('2020年全国投入产出表'!$AM$57+'2020年全国投入产出表'!$AN$57) -> 1.2488446e+11 | D35: ='分行业工业增加值（2012年美元）'!C48*'2020年全国投入产出表'!$AM$57/('2020年全国投入产出表'!$AM$57+'2020年全国投入产出表'!$AN$57) -> 1.7596162e+11 | E35: ='分行业工业增加值（2012年美元）'!D48*'2020年全国投入产出表'!$AM$57/('2020年全国投入产出表'!$AM$57+'2020年全国投入产出表'!$AN$57) -> 1.7834324e+11 | F35: ='分行业工业增加值（2012年美元）'!E48*'2020年全国投入产出表'!$AM$57/('2020年全国投入产出表'!$AM$57+'2020年全国投入产出表'!$AN$57) -> 1.9468965e+11 | G35: ='分行业工业增加值（2012年美元）'!F48*'2020年全国投入产出表'!$AM$57/('2020年全国投入产出表'!$AM$57+'2020年全国投入产出表'!$AN$57) -> 2.1136991e+11 | H35: ='分行业工业增加值（2012年美元）'!G48*'2020年全国投入产出表'!$AM$57/('2020年全国投入产出表'!$AM$57+'2020年全国投入产出表'!$AN$57) -> 2.2810068e+11 | I35: ='分行业工业增加值（2012年美元）'!H48*'2020年全国投入产出表'!$AM$57/('2020年全国投入产出表'!$AM$57+'2020年全国投入产出表'!$AN$57) -> 2.4519197e+11 | J35: ='分行业工业增加值（2012年美元）'!I48*'2020年全国投入产出表'!$AM$57/('2020年全国投入产出表'!$AM$57+'2020年全国投入产出表'!$AN$57) -> 2.6224512e+11 | ... AR35: ='分行业工业增加值（2012年美元）'!AQ48*'2020年全国投入产出表'!$AM$57/('2020年全国投入产出表'!$AM$57+'2020年全国投入产出表'!$AN$57) -> 7.1862596e+11
A36: 金融 | B36: ISIC 64T66 | C36: 1.0622664e+12 | D36: 1.1601268e+12 | E36: 1.2267773e+12 | F36: 1.3301357e+12 | G36: 1.4371787e+12 | H36: 1.5466565e+12 | I36: 1.6598674e+12 | J36: 1.7757492e+12 | K36: 1.8941494e+12 | L36: 2.0160142e+12 | M36: 2.1398453e+12 | N36: 2.2662596e+12 | O36: 2.3954402e+12 | P36: 2.5264624e+12 | Q36: 2.6601346e+12 | R36: 2.7960193e+12 | S36: 2.9334975e+12 | T36: 3.0738691e+12 | U36: 3.2158353e+12 | V36: 3.3602401e+12 | W36: 3.5066929e+12 | X36: 3.6547003e+12 | Y36: 3.8050493e+12 | Z36: 3.957474e+12 | AA36: 4.1116148e+12 | AB36: 4.2678906e+12 | AC36: 4.4260671e+12 | AD36: 4.5865307e+12 | AE36: 4.7487049e+12 | AF36: 4.9124877e+12 | AG36: 5.0790204e+12 | AH36: 5.2469497e+12 | AI36: 5.4168409e+12 | AJ36: 5.5887063e+12 | AK36: 5.7620075e+12 | AL36: 5.9375825e+12 | AM36: 6.1146845e+12 | AN36: 6.2933895e+12 | AO36: 6.4737889e+12 | AP36: 6.6554304e+12 | AQ36: 6.8389275e+12 | AR36: 7.0233092e+12
A37: 房地产 | B37: ISIC 68 | C37: 9.6177372e+11 | D37: 1.0261541e+12 | E37: 1.0440494e+12 | F37: 1.1020725e+12 | G37: 1.1605847e+12 | H37: 1.2190647e+12 | I37: 1.2783021e+12 | J37: 1.3376627e+12 | K37: 1.3970986e+12 | L37: 1.456898e+12 | M37: 1.5164988e+12 | N37: 1.5762076e+12 | O37: 1.6359821e+12 | P37: 1.6954171e+12 | Q37: 1.754898e+12 | R37: 1.8141417e+12 | S37: 1.8729868e+12 | T37: 1.9317985e+12 | U37: 1.9901264e+12 | V37: 2.0483389e+12 | W37: 2.1062215e+12 | X37: 2.1635203e+12 | Y37: 2.2206081e+12 | Z37: 2.2773241e+12 | AA37: 2.3335745e+12 | AB37: 2.3894024e+12 | AC37: 2.444862e+12 | AD37: 2.5000321e+12 | AE37: 2.5546564e+12 | AF37: 2.608869e+12 | AG37: 2.6629876e+12 | AH37: 2.7165973e+12 | AI37: 2.7699419e+12 | AJ37: 2.8230871e+12 | AK37: 2.8759114e+12 | AL37: 2.9287079e+12 | AM37: 2.9814065e+12 | AN37: 3.0341009e+12 | AO37: 3.0869206e+12 | AP37: 3.1398477e+12 | AQ37: 3.1931153e+12 | AR37: 3.2467224e+12
A38: 综合技术服务 | B38: ISIC 69T82 | C38: ='分行业工业增加值（2012年美元）'!B48*'2020年全国投入产出表'!$AN$57/('2020年全国投入产出表'!$AM$57+'2020年全国投入产出表'!$AN$57) -> 2.4103107e+11 | D38: ='分行业工业增加值（2012年美元）'!C48*'2020年全国投入产出表'!$AN$57/('2020年全国投入产出表'!$AM$57+'2020年全国投入产出表'!$AN$57) -> 3.3961165e+11 | E38: ='分行业工业增加值（2012年美元）'!D48*'2020年全国投入产出表'!$AN$57/('2020年全国投入产出表'!$AM$57+'2020年全国投入产出表'!$AN$57) -> 3.4420827e+11 | F38: ='分行业工业增加值（2012年美元）'!E48*'2020年全国投入产出表'!$AN$57/('2020年全国投入产出表'!$AM$57+'2020年全国投入产出表'!$AN$57) -> 3.7575736e+11 | G38: ='分行业工业增加值（2012年美元）'!F48*'2020年全国投入产出表'!$AN$57/('2020年全国投入产出表'!$AM$57+'2020年全国投入产出表'!$AN$57) -> 4.0795081e+11 | H38: ='分行业工业增加值（2012年美元）'!G48*'2020年全国投入产出表'!$AN$57/('2020年全国投入产出表'!$AM$57+'2020年全国投入产出表'!$AN$57) -> 4.4024174e+11 | I38: ='分行业工业增加值（2012年美元）'!H48*'2020年全国投入产出表'!$AN$57/('2020年全国投入产出表'!$AM$57+'2020年全国投入产出表'!$AN$57) -> 4.7322849e+11 | J38: ='分行业工业增加值（2012年美元）'!I48*'2020年全国投入产出表'!$AN$57/('2020年全国投入产出表'!$AM$57+'2020年全国投入产出表'!$AN$57) -> 5.0614163e+11 | ... AR38: ='分行业工业增加值（2012年美元）'!AQ48*'2020年全国投入产出表'!$AN$57/('2020年全国投入产出表'!$AM$57+'2020年全国投入产出表'!$AN$57) -> 1.3869715e+12
A39: 水利、环境和公共设施管理、公共管理、社会保障和社会组织 | B39: ISIC 84 | C39: ='分行业工业增加值（2012年美元）'!B49+'分行业工业增加值（2012年美元）'!B54 -> 5.8306159e+11 | D39: ='分行业工业增加值（2012年美元）'!C49+'分行业工业增加值（2012年美元）'!C54 -> 7.5300009e+11 | E39: ='分行业工业增加值（2012年美元）'!D49+'分行业工业增加值（2012年美元）'!D54 -> 6.6582874e+11 | F39: ='分行业工业增加值（2012年美元）'!E49+'分行业工业增加值（2012年美元）'!E54 -> 7.265482e+11 | G39: ='分行业工业增加值（2012年美元）'!F49+'分行业工业增加值（2012年美元）'!F54 -> 7.8892127e+11 | H39: ='分行业工业增加值（2012年美元）'!G49+'分行业工业增加值（2012年美元）'!G54 -> 8.5225422e+11 | I39: ='分行业工业增加值（2012年美元）'!H49+'分行业工业增加值（2012年美元）'!H54 -> 9.1749008e+11 | J39: ='分行业工业增加值（2012年美元）'!I49+'分行业工业增加值（2012年美元）'!I54 -> 9.8332628e+11 | ... AR39: ='分行业工业增加值（2012年美元）'!AQ49+'分行业工业增加值（2012年美元）'!AQ54 -> 2.8496712e+12
A40: 教育 | B40: ISIC 85 | C40: 3.9653044e+11 | D40: 5.1559247e+11 | E40: 4.6058736e+11 | F40: 5.0184461e+11 | G40: 5.4429895e+11 | H40: 5.8727435e+11 | I40: 6.3147888e+11 | J40: 6.759034e+11 | K40: 7.206904e+11 | L40: 7.6600318e+11 | M40: 8.1107407e+11 | N40: 8.5627859e+11 | O40: 9.0135783e+11 | P40: 9.4597037e+11 | Q40: 9.9040982e+11 | R40: 1.0342195e+12 | S40: 1.0773493e+12 | T40: 1.1200849e+12 | U40: 1.1619411e+12 | V40: 1.2033301e+12 | W40: 1.2439252e+12 | X40: 1.2835833e+12 | Y40: 1.3225847e+12 | Z40: 1.3607089e+12 | AA40: 1.3979692e+12 | AB40: 1.4343112e+12 | AC40: 1.4698185e+12 | AD40: 1.5045947e+12 | AE40: 1.5383261e+12 | AF40: 1.5711124e+12 | AG40: 1.6032621e+12 | AH40: 1.6343843e+12 | AI40: 1.6646866e+12 | AJ40: 1.6941779e+12 | AK40: 1.7227492e+12 | AL40: 1.7505901e+12 | AM40: 1.7776359e+12 | AN40: 1.8039482e+12 | AO40: 1.8295168e+12 | AP40: 1.8543798e+12 | AQ40: 1.8785923e+12 | AR40: 1.9021005e+12
A41: 卫生和社会工作 | B41: ISIC 86T88 | C41: 2.7688519e+11 | D41: 3.6662007e+11 | E41: 3.3546715e+11 | F41: 3.6617751e+11 | G41: 3.9761738e+11 | H41: 4.2925489e+11 | I41: 4.6167111e+11 | J41: 4.9424352e+11 | K41: 5.269487e+11 | L41: 5.5994889e+11 | M41: 5.9270582e+11 | N41: 6.2548252e+11 | O41: 6.5818237e+11 | P41: 6.9044882e+11 | Q41: 7.2256778e+11 | R41: 7.5422865e+11 | S41: 7.8536412e+11 | T41: 8.1620654e+11 | U41: 8.4639312e+11 | V41: 8.7621033e+11 | W41: 9.0548492e+11 | X41: 9.3404294e+11 | Y41: 9.6212122e+11 | Z41: 9.8958925e+11 | AA41: 1.0164073e+12 | AB41: 1.0425923e+12 | AC41: 1.068147e+12 | AD41: 1.0931747e+12 | AE41: 1.1174607e+12 | AF41: 1.1410527e+12 | AG41: 1.164198e+12 | AH41: 1.1865832e+12 | AI41: 1.2083622e+12 | AJ41: 1.2295663e+12 | AK41: 1.2500825e+12 | AL41: 1.2700678e+12 | AM41: 1.2894578e+12 | AN41: 1.3082711e+12 | AO41: 1.3265368e+12 | AP41: 1.3442427e+12 | AQ41: 1.3614569e+12 | AR41: 1.3781068e+12
A42: 文化、体育和娱乐 | B42: ISIC 90T96 | C42: 1.6104591e+11 | D42: 2.2223516e+11 | E42: 2.1385918e+11 | F42: 2.3208037e+11 | G42: 2.5073317e+11 | H42: 2.6968329e+11 | I42: 2.8908748e+11 | J42: 3.0868831e+11 | K42: 3.2846676e+11 | L42: 3.4841656e+11 | M42: 3.6834908e+11 | N42: 3.8828094e+11 | O42: 4.0812389e+11 | P42: 4.2777909e+11 | Q42: 4.4734755e+11 | R42: 4.6672101e+11 | S42: 4.8572471e+11 | T42: 5.0451459e+11 | U42: 5.2299283e+11 | V42: 5.4117662e+11 | W42: 5.5894554e+11 | X42: 5.7630556e+11 | Y42: 5.9331145e+11 | Z42: 6.0990836e+11 | AA42: 6.260614e+11 | AB42: 6.4177687e+11 | AC42: 6.5709404e+11 | AD42: 6.7198139e+11 | AE42: 6.8645413e+11 | AF42: 7.0046684e+11 | AG42: 7.1410946e+11 | AH42: 7.27333e+11 | AI42: 7.4016729e+11 | AJ42: 7.5261778e+11 | AK42: 7.6469515e+11 | AL42: 7.7646979e+11 | AM42: 7.8793272e+11 | AN42: 7.991146e+11 | AO42: 8.1005984e+11 | AP42: 8.2076483e+11 | AQ42: 8.3130053e+11 | AR42: 8.417096e+11
A43: 居民服务、修理和其他服务 | B43: ISIC 97T98 | C43: 2.9331522e+11 | D43: 4.0342571e+11 | E43: 3.8456958e+11 | F43: 4.201914e+11 | G43: 4.5665099e+11 | H43: 4.9348826e+11 | I43: 5.3155602e+11 | J43: 5.6983799e+11 | K43: 6.0835028e+11 | L43: 6.4731442e+11 | M43: 6.8608989e+11 | N43: 7.2516052e+11 | O43: 7.6395543e+11 | P43: 8.0223337e+11 | Q43: 8.4049131e+11 | R43: 8.7817972e+11 | S43: 9.1521519e+11 | T43: 9.5194814e+11 | U43: 9.8790312e+11 | V43: 1.0234742e+12 | W43: 1.0582707e+12 | X43: 1.0921632e+12 | Y43: 1.1255136e+12 | Z43: 1.1580728e+12 | AA43: 1.1898702e+12 | AB43: 1.2207865e+12 | AC43: 1.2509179e+12 | AD43: 1.2804635e+12 | AE43: 1.3090492e+12 | AF43: 1.3367555e+12 | AG43: 1.3639496e+12 | AH43: 1.3902288e+12 | AI43: 1.4158571e+12 | AJ43: 1.4408028e+12 | AK43: 1.464955e+12 | AL43: 1.4885516e+12 | AM43: 1.5115421e+12 | AN43: 1.5339893e+12 | AO43: 1.5559092e+12 | AP43: 1.5773673e+12 | AQ43: 1.5984641e+12 | AR43: 1.6191153e+12

Sheet BPCiObIC
A1: Unit: dimensionless (% change) | B1: 2020 | C1: 2021 | D1: 2022 | E1: 2023 | F1: 2024 | G1: 2025 | H1: 2026 | I1: 2027 | J1: 2028 | K1: 2029 | L1: 2030 | M1: 2031 | N1: 2032 | O1: 2033 | P1: 2034 | Q1: 2035 | R1: 2036 | S1: 2037 | T1: 2038 | U1: 2039 | V1: 2040 | W1: 2041 | X1: 2042 | Y1: 2043 | Z1: 2044 | AA1: 2045 | AB1: 2046 | AC1: 2047 | AD1: 2048 | AE1: 2049 | AF1: 2050 | AG1: 2051 | AH1: 2052 | AI1: 2053 | AJ1: 2054 | AK1: 2055 | AL1: 2056 | AM1: 2057 | AN1: 2058 | AO1: 2059 | AP1: 2060
A2: ISIC 01T03 | B2: ='分42行业工业增加值（2012年美元）'!D2/'分42行业工业增加值（2012年美元）'!C2-1 -> 0.095186479 | C2: ='分42行业工业增加值（2012年美元）'!E2/'分42行业工业增加值（2012年美元）'!D2-1 -> 0.04715514 | D2: ='分42行业工业增加值（2012年美元）'!F2/'分42行业工业增加值（2012年美元）'!E2-1 -> 0.038028557 | E2: ='分42行业工业增加值（2012年美元）'!G2/'分42行业工业增加值（2012年美元）'!F2-1 -> 0.035924697 | F2: ='分42行业工业增加值（2012年美元）'!H2/'分42行业工业增加值（2012年美元）'!G2-1 -> 0.033778792 | G2: ='分42行业工业增加值（2012年美元）'!I2/'分42行业工业增加值（2012年美元）'!H2-1 -> 0.032496169 | H2: ='分42行业工业增加值（2012年美元）'!J2/'分42行业工业增加值（2012年美元）'!I2-1 -> 0.030679447 | I2: ='分42行业工业增加值（2012年美元）'!K2/'分42行业工业增加值（2012年美元）'!J2-1 -> 0.029113962 | ... AP2: ='分42行业工业增加值（2012年美元）'!AR2/'分42行业工业增加值（2012年美元）'!AQ2-1 -> 0.0075187716
A3: ISIC 05 | B3: ='分42行业工业增加值（2012年美元）'!D3/'分42行业工业增加值（2012年美元）'!C3-1 -> 0.18756598 | C3: ='分42行业工业增加值（2012年美元）'!E3/'分42行业工业增加值（2012年美元）'!D3-1 -> 0.012105788 | D3: ='分42行业工业增加值（2012年美元）'!F3/'分42行业工业增加值（2012年美元）'!E3-1 -> 0.010697673 | E3: ='分42行业工业增加值（2012年美元）'!G3/'分42行业工业增加值（2012年美元）'!F3-1 -> 0.0088270838 | F3: ='分42行业工业增加值（2012年美元）'!H3/'分42行业工业增加值（2012年美元）'!G3-1 -> 0.0071842571 | G3: ='分42行业工业增加值（2012年美元）'!I3/'分42行业工业增加值（2012年美元）'!H3-1 -> 0.0057501089 | H3: ='分42行业工业增加值（2012年美元）'!J3/'分42行业工业增加值（2012年美元）'!I3-1 -> 0.0045042495 | I3: ='分42行业工业增加值（2012年美元）'!K3/'分42行业工业增加值（2012年美元）'!J3-1 -> 0.0034263149 | ... AP3: ='分42行业工业增加值（2012年美元）'!AR3/'分42行业工业增加值（2012年美元）'!AQ3-1 -> -0.0023297746
A4: ISIC 06 | B4: ='分42行业工业增加值（2012年美元）'!D4/'分42行业工业增加值（2012年美元）'!C4-1 -> -0.26314039 | C4: ='分42行业工业增加值（2012年美元）'!E4/'分42行业工业增加值（2012年美元）'!D4-1 -> 0.091459189 | D4: ='分42行业工业增加值（2012年美元）'!F4/'分42行业工业增加值（2012年美元）'!E4-1 -> -0.012443072 | E4: ='分42行业工业增加值（2012年美元）'!G4/'分42行业工业增加值（2012年美元）'!F4-1 -> -0.013753824 | F4: ='分42行业工业增加值（2012年美元）'!H4/'分42行业工业增加值（2012年美元）'!G4-1 -> -0.014866314 | G4: ='分42行业工业增加值（2012年美元）'!I4/'分42行业工业增加值（2012年美元）'!H4-1 -> -0.01579732 | H4: ='分42行业工业增加值（2012年美元）'!J4/'分42行业工业增加值（2012年美元）'!I4-1 -> -0.016565093 | I4: ='分42行业工业增加值（2012年美元）'!K4/'分42行业工业增加值（2012年美元）'!J4-1 -> -0.017188035 | ... AP4: ='分42行业工业增加值（2012年美元）'!AR4/'分42行业工业增加值（2012年美元）'!AQ4-1 -> -0.014544733
A5: ISIC 07T08 | B5: ='分42行业工业增加值（2012年美元）'!D5/'分42行业工业增加值（2012年美元）'!C5-1 -> -0.031465781 | C5: ='分42行业工业增加值（2012年美元）'!E5/'分42行业工业增加值（2012年美元）'!D5-1 -> 0.091459189 | D5: ='分42行业工业增加值（2012年美元）'!F5/'分42行业工业增加值（2012年美元）'!E5-1 -> -0.012443072 | E5: ='分42行业工业增加值（2012年美元）'!G5/'分42行业工业增加值（2012年美元）'!F5-1 -> -0.013753824 | F5: ='分42行业工业增加值（2012年美元）'!H5/'分42行业工业增加值（2012年美元）'!G5-1 -> -0.014866314 | G5: ='分42行业工业增加值（2012年美元）'!I5/'分42行业工业增加值（2012年美元）'!H5-1 -> -0.01579732 | H5: ='分42行业工业增加值（2012年美元）'!J5/'分42行业工业增加值（2012年美元）'!I5-1 -> -0.016565093 | I5: ='分42行业工业增加值（2012年美元）'!K5/'分42行业工业增加值（2012年美元）'!J5-1 -> -0.017188035 | ... AP5: ='分42行业工业增加值（2012年美元）'!AR5/'分42行业工业增加值（2012年美元）'!AQ5-1 -> -0.014544733
A6: ISIC 09 | B6: ='分42行业工业增加值（2012年美元）'!D6/'分42行业工业增加值（2012年美元）'!C6-1 -> -0.031465781 | C6: ='分42行业工业增加值（2012年美元）'!E6/'分42行业工业增加值（2012年美元）'!D6-1 -> 0.091459189 | D6: ='分42行业工业增加值（2012年美元）'!F6/'分42行业工业增加值（2012年美元）'!E6-1 -> -0.012443072 | E6: ='分42行业工业增加值（2012年美元）'!G6/'分42行业工业增加值（2012年美元）'!F6-1 -> -0.013753824 | F6: ='分42行业工业增加值（2012年美元）'!H6/'分42行业工业增加值（2012年美元）'!G6-1 -> -0.014866314 | G6: ='分42行业工业增加值（2012年美元）'!I6/'分42行业工业增加值（2012年美元）'!H6-1 -> -0.01579732 | H6: ='分42行业工业增加值（2012年美元）'!J6/'分42行业工业增加值（2012年美元）'!I6-1 -> -0.016565093 | I6: ='分42行业工业增加值（2012年美元）'!K6/'分42行业工业增加值（2012年美元）'!J6-1 -> -0.017188035 | ... AP6: ='分42行业工业增加值（2012年美元）'!AR6/'分42行业工业增加值（2012年美元）'!AQ6-1 -> -0.014544733
A7: ISIC 10T12 | B7: ='分42行业工业增加值（2012年美元）'!D7/'分42行业工业增加值（2012年美元）'!C7-1 -> -0.0094507719 | C7: ='分42行业工业增加值（2012年美元）'!E7/'分42行业工业增加值（2012年美元）'!D7-1 -> 0.14827458 | D7: ='分42行业工业增加值（2012年美元）'!F7/'分42行业工业增加值（2012年美元）'!E7-1 -> 0.014191919 | E7: ='分42行业工业增加值（2012年美元）'!G7/'分42行业工业增加值（2012年美元）'!F7-1 -> 0.012147248 | F7: ='分42行业工业增加值（2012年美元）'!H7/'分42行业工业增加值（2012年美元）'!G7-1 -> 0.010343475 | G7: ='分42行业工业增加值（2012年美元）'!I7/'分42行业工业增加值（2012年美元）'!H7-1 -> 0.0087602118 | H7: ='分42行业工业增加值（2012年美元）'!J7/'分42行业工业增加值（2012年美元）'!I7-1 -> 0.0073759125 | I7: ='分42行业工业增加值（2012年美元）'!K7/'分42行业工业增加值（2012年美元）'!J7-1 -> 0.0061691909 | ... AP7: ='分42行业工业增加值（2012年美元）'!AR7/'分42行业工业增加值（2012年美元）'!AQ7-1 -> -0.0014188797
A8: ISIC 13T15 | B8: ='分42行业工业增加值（2012年美元）'!D8/'分42行业工业增加值（2012年美元）'!C8-1 -> -0.1117227 | C8: ='分42行业工业增加值（2012年美元）'!E8/'分42行业工业增加值（2012年美元）'!D8-1 -> 0.091459189 | D8: ='分42行业工业增加值（2012年美元）'!F8/'分42行业工业增加值（2012年美元）'!E8-1 -> -0.012443072 | E8: ='分42行业工业增加值（2012年美元）'!G8/'分42行业工业增加值（2012年美元）'!F8-1 -> -0.013753824 | F8: ='分42行业工业增加值（2012年美元）'!H8/'分42行业工业增加值（2012年美元）'!G8-1 -> -0.014866314 | G8: ='分42行业工业增加值（2012年美元）'!I8/'分42行业工业增加值（2012年美元）'!H8-1 -> -0.01579732 | H8: ='分42行业工业增加值（2012年美元）'!J8/'分42行业工业增加值（2012年美元）'!I8-1 -> -0.016565093 | I8: ='分42行业工业增加值（2012年美元）'!K8/'分42行业工业增加值（2012年美元）'!J8-1 -> -0.017188035 | ... AP8: ='分42行业工业增加值（2012年美元）'!AR8/'分42行业工业增加值（2012年美元）'!AQ8-1 -> -0.014544733
A9: ISIC 16 | B9: ='分42行业工业增加值（2012年美元）'!D9/'分42行业工业增加值（2012年美元）'!C9-1 -> -0.075528143 | C9: ='分42行业工业增加值（2012年美元）'!E9/'分42行业工业增加值（2012年美元）'!D9-1 -> 0.16315603 | D9: ='分42行业工业增加值（2012年美元）'!F9/'分42行业工业增加值（2012年美元）'!E9-1 -> -0.0085827481 | E9: ='分42行业工业增加值（2012年美元）'!G9/'分42行业工业增加值（2012年美元）'!F9-1 -> -0.0099136348 | F9: ='分42行业工业增加值（2012年美元）'!H9/'分42行业工业增加值（2012年美元）'!G9-1 -> -0.011045334 | G9: ='分42行业工业增加值（2012年美元）'!I9/'分42行业工业增加值（2012年美元）'!H9-1 -> -0.0119947 | H9: ='分42行业工业增加值（2012年美元）'!J9/'分42行业工业增加值（2012年美元）'!I9-1 -> -0.012780064 | I9: ='分42行业工业增加值（2012年美元）'!K9/'分42行业工业增加值（2012年美元）'!J9-1 -> -0.013419906 | ... AP9: ='分42行业工业增加值（2012年美元）'!AR9/'分42行业工业增加值（2012年美元）'!AQ9-1 -> -0.011190817
A10: ISIC 17T18 | B10: ='分42行业工业增加值（2012年美元）'!D10/'分42行业工业增加值（2012年美元）'!C10-1 -> -0.028649677 | C10: ='分42行业工业增加值（2012年美元）'!E10/'分42行业工业增加值（2012年美元）'!D10-1 -> 0.16973063 | D10: ='分42行业工业增加值（2012年美元）'!F10/'分42行业工业增加值（2012年美元）'!E10-1 -> 0.018049357 | E10: ='分42行业工业增加值（2012年美元）'!G10/'分42行业工业增加值（2012年美元）'!F10-1 -> 0.015786042 | F10: ='分42行业工业增加值（2012年美元）'!H10/'分42行业工业增加值（2012年美元）'!G10-1 -> 0.013782157 | G10: ='分42行业工业增加值（2012年美元）'!I10/'分42行业工业增加值（2012年美元）'!H10-1 -> 0.012015265 | H10: ='分42行业工业增加值（2012年美元）'!J10/'分42行业工业增加值（2012年美元）'!I10-1 -> 0.010462036 | I10: ='分42行业工业增加值（2012年美元）'!K10/'分42行业工业增加值（2012年美元）'!J10-1 -> 0.0090995291 | ... AP10: ='分42行业工业增加值（2012年美元）'!AR10/'分42行业工业增加值（2012年美元）'!AQ10-1 -> -0.00054419414
A11: ISIC 19 | B11: ='分42行业工业增加值（2012年美元）'!D11/'分42行业工业增加值（2012年美元）'!C11-1 -> -0.076792851 | C11: ='分42行业工业增加值（2012年美元）'!E11/'分42行业工业增加值（2012年美元）'!D11-1 -> 0.27904088 | D11: ='分42行业工业增加值（2012年美元）'!F11/'分42行业工业增加值（2012年美元）'!E11-1 -> 0.043594786 | E11: ='分42行业工业增加值（2012年美元）'!G11/'分42行业工业增加值（2012年美元）'!F11-1 -> 0.039204589 | F11: ='分42行业工业增加值（2012年美元）'!H11/'分42行业工业增加值（2012年美元）'!G11-1 -> 0.035336617 | G11: ='分42行业工业增加值（2012年美元）'!I11/'分42行业工业增加值（2012年美元）'!H11-1 -> 0.031926154 | H11: ='分42行业工业增加值（2012年美元）'!J11/'分42行业工业增加值（2012年美元）'!I11-1 -> 0.028915806 | I11: ='分42行业工业增加值（2012年美元）'!K11/'分42行业工业增加值（2012年美元）'!J11-1 -> 0.026254948 | ... AP11: ='分42行业工业增加值（2012年美元）'!AR11/'分42行业工业增加值（2012年美元）'!AQ11-1 -> 0.0031719442
A12: ISIC 20 | B12: ='分42行业工业增加值（2012年美元）'!D12/'分42行业工业增加值（2012年美元）'!C12-1 -> -0.019320165 | C12: ='分42行业工业增加值（2012年美元）'!E12/'分42行业工业增加值（2012年美元）'!D12-1 -> 0.19077955 | D12: ='分42行业工业增加值（2012年美元）'!F12/'分42行业工业增加值（2012年美元）'!E12-1 -> 0.023561027 | E12: ='分42行业工业增加值（2012年美元）'!G12/'分42行业工业增加值（2012年美元）'!F12-1 -> 0.020937713 | F12: ='分42行业工业增加值（2012年美元）'!H12/'分42行业工业增加值（2012年美元）'!G12-1 -> 0.0186086 | G12: ='分42行业工业增加值（2012年美元）'!I12/'分42行业工业增加值（2012年美元）'!H12-1 -> 0.016546899 | H12: ='分42行业工业增加值（2012年美元）'!J12/'分42行业工业增加值（2012年美元）'!I12-1 -> 0.014725578 | I12: ='分42行业工业增加值（2012年美元）'!K12/'分42行业工业增加值（2012年美元）'!J12-1 -> 0.013118529 | ... AP12: ='分42行业工业增加值（2012年美元）'!AR12/'分42行业工业增加值（2012年美元）'!AQ12-1 -> 0.00051670903
A13: ISIC 21 | B13: ='分42行业工业增加值（2012年美元）'!D13/'分42行业工业增加值（2012年美元）'!C13-1 -> -0.019320165 | C13: ='分42行业工业增加值（2012年美元）'!E13/'分42行业工业增加值（2012年美元）'!D13-1 -> 0.19077955 | D13: ='分42行业工业增加值（2012年美元）'!F13/'分42行业工业增加值（2012年美元）'!E13-1 -> 0.023561027 | E13: ='分42行业工业增加值（2012年美元）'!G13/'分42行业工业增加值（2012年美元）'!F13-1 -> 0.020937713 | F13: ='分42行业工业增加值（2012年美元）'!H13/'分42行业工业增加值（2012年美元）'!G13-1 -> 0.0186086 | G13: ='分42行业工业增加值（2012年美元）'!I13/'分42行业工业增加值（2012年美元）'!H13-1 -> 0.016546899 | H13: ='分42行业工业增加值（2012年美元）'!J13/'分42行业工业增加值（2012年美元）'!I13-1 -> 0.014725578 | I13: ='分42行业工业增加值（2012年美元）'!K13/'分42行业工业增加值（2012年美元）'!J13-1 -> 0.013118529 | ... AP13: ='分42行业工业增加值（2012年美元）'!AR13/'分42行业工业增加值（2012年美元）'!AQ13-1 -> 0.00051670903
... A43: ISIC 97T98 | B43: ='分42行业工业增加值（2012年美元）'!D43/'分42行业工业增加值（2012年美元）'!C43-1 -> 0.37539989 | C43: ='分42行业工业增加值（2012年美元）'!E43/'分42行业工业增加值（2012年美元）'!D43-1 -> -0.046740029 | D43: ='分42行业工业增加值（2012年美元）'!F43/'分42行业工业增加值（2012年美元）'!E43-1 -> 0.092627757 | E43: ='分42行业工业增加值（2012年美元）'!G43/'分42行业工业增加值（2012年美元）'!F43-1 -> 0.086768998 | F43: ='分42行业工业增加值（2012年美元）'!H43/'分42行业工业增加值（2012年美元）'!G43-1 -> 0.080668315 | G43: ='分42行业工业增加值（2012年美元）'!I43/'分42行业工业增加值（2012年美元）'!H43-1 -> 0.077140172 | H43: ='分42行业工业增加值（2012年美元）'!J43/'分42行业工业增加值（2012年美元）'!I43-1 -> 0.072018676 | I43: ='分42行业工业增加值（2012年美元）'!K43/'分42行业工业增加值（2012年美元）'!J43-1 -> 0.067584632 | ... AP43: ='分42行业工业增加值（2012年美元）'!AR43/'分42行业工业增加值（2012年美元）'!AQ43-1 -> 0.012919387
