Workbook

Sheet About
A1: Web App Data
A3: This spreadsheet contains data that is used to populate the web application interface
A4: for the Energy Policy Simulator. The data in other tabs in this spreadsheet are used
A5: to establish the policy levers, lever bounds, descriptive text for pop-over
A6: panels, output graphs, and reference scenarios available in the web app.
A8: A live version of the web application interface powered by a copy of this model
A9: can be found at:
A10: https://www.energypolicy.solutions
A12: You are unlikely to need to use or change the contents of this spreadsheet, unless
A13: you are adapting the Energy Policy Simulator to a new country and desire
A14: a web application interface customized for your country-specific model version.
A16: Checks for Policy ID Number Validity
A17: Max policy ID number in use | B17: =MAX(PolicyLevers!H:H) -> 1655
A18: Lowest duplicate ID number | B18: {=IF(MIN(IF(COUNTIF(PolicyLevers!$H$2:$H$1271,PolicyLevers!$H$2:$H$1271)>1,PolicyLevers!$H$2:$H$1271,""))=0,"No duplicate ID numbers",MIN(IF(COUNTIF(PolicyLevers!$H$2:$H$1271,PolicyLevers!$H$2:$H$1271)>1,PolicyLevers!$H$2:$H$1271,"")))} -> No duplicate ID numbers
A19: Row of first policy missing a valid ID number | B19: {=IF(MIN(IF((NOT(ISNUMBER(PolicyLevers!$H$2:$H$1271)))*(ISTEXT(PolicyLevers!$I$2:$I$1271)),ROW(PolicyLevers!$H$2:$H$1271)))=0,"No missing ID numbers",MIN(IF((NOT(ISNUMBER(PolicyLevers!$H$2:$H$1271)))*(ISTEXT(PolicyLevers!$I$2:$I$1271)),ROW(PolicyLevers!$H$2:$H$1271))))} -> No missing ID numbers
A21: Customizing Policy Levers
A22: Define most policy properties on the "Policy Characteristics" tab.
A23: Specify the subscripted elements of each policy and which are enabled/disabled on the "PolicyLevers" tab.
A24: On the PolicyLevers tab, only manually edit the cells under the green column headers. Simply extend the
A25: existing formulas up or down to fill cells under the red headers on that tab.
A27: Notes on Meaning of Blank Cells on the Policy Characteristics Tab
A28: Leave the "Policy Schedule Subscript" cell blank to deny the ability to edit the implementation
A29: schedule for a lever. This should generally only be done for levers that do not use an
A30: implementation schedule: the toggle to Non-BAU Mandated Capacity Construction
A31: (which has its own schedule built into its input data) and the Nuclear Lifetime Extension
A32: (which simply delays retirements that would occur in the BAU Retirements input data).
A34: Leave the "Policy Group" cell blank to exclude a lever from wedge diagrams and abatement cost curves.
... A53: step size (e.g. 1.5% is not a valid step size, but 1%, 2%, 0.5% and 0.05% are all valid).

Sheet Policy Characteristics
A1: This tab contains information about each policy that does not vary by subscripted element of that policy.
A2: It matches policies to the listing in the "PolicyLevers" tab using the "Vensim Variable Name" column.
A3: Sector | B3: Short Name | C3: Vensim Variable Name | D3: Policy Group | E3: Policy Schedule Subscript | F3: Min Slider Value | G3: Max Slider Value | H3: Slider Step Size | I3: Units | J3: Text for Pop-Over Panel Description | K3: URL for "How the model handles this policy" links | L3: URL for "How to design this policy well" links | M3: Source for Guidance Text (if any) | N3: Source for Max Slider Value (if any)
A4: Transportation | B4: Conventional Pollutant Standards | C4: Percentage Reduction of Separately Regulated Pollutants | D4: Conventional Pollutant Standard | E4: trans reduce regulated pollutants | F4: 0 | G4: 1 | H4: 0.02 | I4: % reduction in emissions | J4: **Description:** This policy represents strengthening standards for the selected pollutant(s) emitted by the selected vehicle type(s). Conventional pollutants' most important, harmful impacts are on human health rather than on climate change. // **Guidance for setting values:** By 2025, the concentration of fine particulate matter (PM2.5) in prefectural-level and above cities will be 10% lower than that in 2020, and the total emissions of volatile organic compounds (VOCs) and nitrogen oxides will be more than 10% lower than that in 2020 respectively. (Reference: Opinions of the CPC and the State Council on Further Combating Pollution and Preventing the Battle against Pollution) | K4: transportation-sector-main.html#conv-pol-stds | L4: conventional-pollutant-standards.html
A5: Transportation | B5: Electric Vehicle Charger Deployment | C5: EV Charger Deployment | D5: EV Charger Deployment | E5: trans EV charger deployment | F5: 0 | G5: 300 | H5: 5 | I5: chargers / 100k pop | J5: **Description:** This policy represents increasing the deployment of EV charging stations, including DC Fast and Level 2 charging stations. It is set in chargers per 100,000 people (cumulative, not per year), additional to chargers in the BAU case. This policy only affects passenger LDVs. // **Guidance for setting values:** The Implementation Program for Accelerating the Construction of Charging and Switching Infrastructure in the Inner Mongolia Autonomous Region (2021-2025) makes it clear that by 2025, all types of charging and switching facilities in the region will strive to reach about 40,000 units. | L5: ev-charger-deployment.html | M5: Number of EV chargers: https://evadoption.com/ev-charging-stations-statistics/ Number of gas stations: U.S. Census, Statistics of U.S. Businesses, https://www.census.gov/data/tables/2016/econ/susb/2016-susb-annual.html Pumps per station: https://247wallst.com/economy/2014/05/22/why-are-there-115000-or-150000-gas-stations-in-america/
A6: Transportation | B6: Electric Vehicle Range & Charging Time | C6: Reduce EV Range Anxiety and Charging Time | D6: EV Range & Charging Time | E6: trans reduce EV range anxiety and charging time | F6: 0 | G6: 1 | H6: 0.02 | I6: % reduction in concern | J6: **Description:** This policy specifies a percentage reduction in vehicle buyers' aversion to electric vehicles due to concerns over the vehicles' range (how far the EV can travel on a charge) and charging time. A 100% setting implies consumers are no more concerned about EV range and charging time than they are about range and fueling time of gasoline vehicles. It does not imply that range is infinite, nor that charging is instantaneous. This policy only affects passenger LDVs. // **Guidance for setting values:**Technology roadmap 2.0 proposes that by 2030, the high ratio of charging facilities will cover residential communities and surrounding areas, as well as unit parking Spaces, social parking lots, and main areas of cities above the county level, key areas of townships, intercity connections, and highway service areas. | L6: reduce-range-anxiety-charging-time.html | M6: Ranges: https://www.energy.gov/eere/vehicles/articles/fotw-1010-january-1-2018-all-electric-light-vehicle-ranges-can-exceed-those Charging Times: https://www.chargepoint.com/files/Quick_Guide_to_Fast_Charging.pdf
A7: Transportation | B7: Zero-Emission Vehicle Sales Standard | C7: Minimum Required ZEV Sales Percentage | D7: ZEV Sales Standard | E7: trans ZEV minimum | F7: 0 | G7: 1 | H7: 0.01 | I7: % of new vehicles sold | J7: **Description:** This policy requires the specified percentage of newly sold vehicles of the selected type(s) to consist of zero-emission vehicles (ZEV). If that percentage would already be achieved through BAU sales plus the effects of other policies, such as an EV subsidy, this policy has no effect. Manufactures may meet a sales standard through techniques such as more heavily marketing electric vehicles, lowering the price of electric vehicles, or raising the price of non-electric vehicles. This policy only applies to road vehicles, not aircraft, rail, or ships. The following descriptions detail the different vehicle types: // **Passenger cars and SUVs:** most light-duty road vehicles //**Light and Medium Commercial, Heavy Duty Trucks, and Heavy Heavy Duty Trucks:** commercial trucks carrying freight, not passengers // **Buses:** including school, transit, and intercity buses // **Heavy Heavy Duty Trucks:** all other heavy road vehicles (mostly freight trucks) // **Passenger motorbikes:** registered motorcycles // **Guidance for setting values:** // **Passenger LDVs:** China aims to achieve about 20% new sales of new energy vehicles (NEV) in 2025, and ensure that new NEV sales is the majority in 2035 (more than 50% of total sales). // **Freight Trucks:** Today, the share of electric freight trucks is very low, but electrification is particularly promising for certain types of trucks, such as those used to make deliveries within cities, those involved in port operations, garbage trucks, and others with frequent starts and stops. // **Passenger HDVs:**Nationally planning sets the goal of 100% electrification for public transportation, and total BEV+PHEV sales for passenger HDVs should reach 50% in 2035. // **Aircraft:** Electricity is commonly used by drones, and small, manned electric aircraft have been developed. However, limited payload and range may complicate the electrification potential of large, long-haul aircraft. Therefore, a low setting of this policy lever may be more realistic than a high setting. // **Rail:** Today, in China, electrification rate reaches 74.9%. Passenger rail has a higher electrification rate than freight and the rates will likely continue to rise. // **Passenger Ships:** Although only a small percentage of recreational boats are powered by electricity today, the market for electric recreational boats is growing rapidly and is projected to reach $20 billion / year globally by 2027. Batteries and electric motors are suitable for the typical travel distances and demand cycles of most small pleasure craft, and in some cases, it is possible to retrofit an existing boat with an electric outboard motor and batteries. Accordingly, a high setting of this policy lever may be reasonable. // **Freight Ships:** Today, few freight ships rely solely on electricity for energy. The large loads and long distances traveled by ocean-going vessels (with no opportunity to charge while underway) limit the suitability of electricity for these vessel types. However, there are freight vessels better-suited to electricity, including tug boats (which benefit from the high torque of electric motors) and offshore support vessels (which carry personnel and goods between offshore platforms and the mainland, and perform other support tasks), as these types of vessels travel predictable distances and may easily return to a dock to charge. Accordingly, a modest setting of this policy lever may be reasonable. // **Passenger Motorbikes:** Electric scooters are very prominent in China and therefore electrification rate is close to 100%. | K7: transportation-sector-main.html#ev-mandate | L7: ev-mandate.html | M7: https://autoalliance.org/energy-environment/state-electric-vehicle-mandate/ https://www.cnbc.com/2019/08/26/colorado-joins-california-in-requiring-automakers-to-sell-more-evs.html https://www.consumerreports.org/hybrids-evs/california-says-new-cars-sold-in-the-state-must-be-zero-emissions-by-2035/ https://www.greentechmedia.com/articles/read/electric-buses-are-going-to-dominate statistics from FoVObE variable https://www.prnewswire.com/news-releases/electric-boats-and-ships-2017-2027-300561222.html
A8: Transportation | B8: Non BAU ZEV Qualifying Vehicles | C8: Boolean Use Non BAU ZEV Qualifying Vehicle Defintions | D8: ZEV Sales Standard | E8: trans non BAU ZEV vehicle definitions | F8: 0 | G8: 1 | H8: 1 | I8: on/off | J8: **Description:** This lever changes which vehicles qualify under the ZEV standard. With the lever off, ZEV qualifying vehicles include: battery electric vehicles, plugin hybrid vehicles, and hydrogen fueled vehicles. With the lever on, only battery electric vehicles and hydrogen fueled vehicles qualify.
A9: Transportation | B9: Electric Vehicle Subsidy | C9: Additional EV Subsidy Percentage | D9: EV Subsidy | E9: trans EV subsidy | F9: 0 | G9: 0.5 | H9: 0.01 | I9: % of vehicle cost | J9: **Description:** This policy causes government to pay for the specified percentage of the purchase price of new battery electric passenger LDVs. This is in addition to EV subsidies that exist in the BAU case. // **Guidance for setting values:** According to the Notice of the Development and Reform Commission of the Ministry of Finance, Ministry of Industry and Information Technology on Improving the Financial Subsidy Policy for the Promotion and Application of New energy Vehicles (Caijian (2020) No. 86), the 2022 new energy vehicle purchase subsidy policy will be terminated on December 31, 2022, and vehicles registered after December 31, 2022 will no longer be subsidized. | K9: transportation-sector-main.html#ev-subsidy | L9: ev-subsidy.html | M9: https://www.fueleconomy.gov/feg/taxevb.shtml plus Chevrolet and Tesla websites
A10: Transportation | B10: Feebate | C10: LDVs Feebate Rate | D10: Feebate | E10: trans LDVs feebate | F10: 0 | G10: 1 | H10: 0.02 | I10: % of global best practice rate | J10: **Description:** This policy implements a fee on sales of inefficient light-duty vehicles (LDVs; namely cars and SUVs) that is rebated to buyers of efficient LDVs. The feebate policy is revenue-neutral, as the pivot point (the efficiency level that incurs neither a rebate nor a fee) is set such that the total of all fees equals the total of all rebates. // **Guidance for setting values:** The feebate is set as a fraction of the global best practice feebate rate. The global best practice feebate rate is $2000 per (hundredth gal/mile), which equates to a $2000 fee on an LDV that gets 20 mpg if the pivot point is 25 mpg. (To see this: 20 mpg is 0.04 gpm. 25 mpg is 0.05 gpm. The difference is -.01 gpm. So in order to levy a $2000 fee on the 20 mpg car when the pivot point is 25 mpg, we need a rate of $2000/.01 gpm.) China does not have feebate currently | K10: transportation-sector-main.html#feebate | L10: feebate.html | M10: Greene et al., 2005, "Feebates, rebates and gas-guzzler taxes: a study of incentives for increased fuel economy", Energy Policy, 33(6), 757-775, http://cta.ornl.gov/cta/Publications/Reports/FeebateEnergyPolicy_FINAL.pdf. | N10: John German and Dan Meszler, 2010, "Best Practices for Feebate Program Design and Implementation", ICCT, http://www.theicct.org/sites/default/files/publications/ICCT_feebates_may2010.pdf, Table 2
A11: Transportation | B11: Fuel Economy Standard | C11: Percentage Additional Improvement of Fuel Economy Std | D11: Vehicle Fuel Economy Standards | E11: trans fuel economy standards | F11: 0 | G11: =ROUND(MaxBoundCalculations!B88,1) -> 1 | H11: 0.01 | I11: % increase in miles/gal | J11: **Description:** This policy specifies a percentage improvement in fuel economy (distance traveled on the same quantity of fuel with the same cargo or passenger loading) due to fuel economy standards for newly sold vehicles of the selected type(s) with fossil fuel-burning engines. // **Guidance for setting values:** // **The Inner Mongolia Autonomous Region has not issued updated policies related to the economic fuel efficiency of vehicles. | K11: transportation-sector-main.html#fuel-econ-std | L11: fuel-economy-standard.html | M11: U. S. EPA, 2012, "Fact Sheet: EPA and NHTSA Set Standards to Reduce Greenhouse Gases and Improve Fuel Economy for Model Years 2017-2025 Cars and Light Trucks", https://nepis.epa.gov/Exe/ZyNET.exe/P100EZ7C.txt?ZyActionD=ZyDocument&Client=EPA&Index=2011%20Thru%202015&Docs=&Query=&Time=&EndTime=&SearchMethod=1&TocRestrict=n&Toc=&TocEntry=&QField=&QFieldYear=&QFieldMonth=&QFieldDay=&UseQField=&IntQFieldOp=0&ExtQFieldOp=0&XmlQuery=&File=D%3A%5CZYFILES%5CINDEX%20DATA%5C11THRU15%5CTXT%5C00000005%5CP100EZ7C.txt&User=ANONYMOUS&Password=anonymous&SortMethod=h%7C-&MaximumDocuments=1&FuzzyDegree=0&ImageQuality=r75g8/r75g8/x150y150g16/i425&Display=hpfr&DefSeekPage=x&SearchBack=ZyActionL&Back=ZyActionS&BackDesc=Results%20page&MaximumPages=1&ZyEntry=4, Table 1, Row 4. U.S. EPA, 2015, "EPA and NHTSA Propose Standards to Reduce Greenhouse Gas Emissions and Improve Fuel Efficiency of Medium- and Heavy-Duty Vehicles for Model Year 2018 and Beyond", https://nepis.epa.gov/Exe/ZyNET.exe/P100P7NL.txt?ZyActionD=ZyDocument&Client=EPA&Index=2016%20Thru%202020&Docs=&Query=&Time=&EndTime=&SearchMethod=1&TocRestrict=n&Toc=&TocEntry=&QField=&QFieldYear=&QFieldMonth=&QFieldDay=&UseQField=&IntQFieldOp=0&ExtQFieldOp=0&XmlQuery=&File=D%3A%5CZYFILES%5CINDEX%20DATA%5C16THRU20%5CTXT%5C00000002%5CP100P7NL.txt&User=ANONYMOUS&Password=anonymous&SortMethod=h%7C-&MaximumDocuments=1&FuzzyDegree=0&ImageQuality=r75g8/r75g8/x150y150g16/i425&Display=hpfr&DefSeekPage=x&SearchBack=ZyActionL&Back=ZyActionS&BackDesc=Results%20page&MaximumPages=1&ZyEntry=3, Page 3. https://theicct.org/sites/default/files/publications/ICCT_ShipEfficiency_20130723.pdf Others calculated from model input data. | N11: National Research Council, 2013, "Transitions to Alternative Vehicles and Fuels", https://www.nap.edu/catalog/18264/transitions-to-alternative-vehicles-and-fuels, Table 2.9, Fuel economy test mpg. U.S. DoE, 2013, "Potential for Energy Efficiency Improvement Beyond the Light-Duty-Vehicle Sector," http://www.nrel.gov/docs/fy13osti/55637.pdf, Table 2.2 and Section 3.4.5, Paragraph 1 David McCollum, Gregory Gould, and Davide Greene, 2009, "Greenhouse Gas Emissions from Aviation and Marine Transportation: Mitigation Potential and Policies", Pew Center on Global Climate Change, http://www.c2es.org/docUploads/aviation-and-marine-report-2009.pdf, Table 4 https://theicct.org/sites/default/files/publications/ICCT_ShipEfficiency_20130723.pdf
A12: Transportation | B12: Low Carbon Fuel Standard | C12: Additional LCFS Percentage | D12: Low Carbon Fuel Standard | E12: trans LCFS | F12: 0 | G12: 1 | H12: 0.01 | I12: % reduction in carbon emissions | J12: **Description:** This policy specifies the percentage reduction in carbon emissions from the transportation sector that must be achieved via fuel switching. This value is in addition to BAU requirements. // **Guidance for setting values:** China does not have LCFS. The U.S. National Renewable Fuel Standard equates to a BAU LCFS of 2.2% - 4.6% (varying by year). California adopted an LCFS that requires a 10% reduction in carbon intensity of the transportation fuel pool by 2020. | K12: transportation-sector-main.html#lcfs | L12: low-carbon-fuel-standard.html | M12: https://www.arb.ca.gov/fuels/lcfs/background/basics.htm
A13: Transportation | B13: Mode Shifting | C13: Percent of Travel Demand Shifted to Other Modes or Eliminated | D13: Mode Shifting | E13: trans mode shifting | F13: 0 | G13: =-ROUND(MaxBoundCalculations!$B$206,2) -> 0.26 | H13: 0.01 | I13: % of trips shifted | J13: **Description:** This policy represents a set of measures aimed at reducing demand for passenger or freight transportation in the selected vehicle type(s). **Passenger LDV** trips may be shifted to other travel modes, such as buses, rail, walking, biking, or eliminated through technology such as videoconferencing. Example measures include improved public transit systems, more walking and bike paths, zoning for higher density along transit corridors, zoning for mixed-use developments, roadway and congestion pricing, and increased parking fees. **Aircraft** trips may be shifted to inter-city rail or eliminated using technology such as videoconferencing. **Freight Truck** trips can be reduced through improved logistics that avoids backhauls and transporting empty shipping containers. // **Guidance for setting values:** The Inner Mongolia Autonomous Region has not issued any updated relevant official policies. | K13: transportation-sector-main.html#tdm | L13: transportation-demand-management.html | M13: International Energy Agency, 2009, "Transport, Energy and CO2: Moving toward Sustainability", http://www.iea.org/publications/freepublications/publication/transport2009.pdf "Freight Facts and Figures", 2013, https://ops.fhwa.dot.gov/freight/freight_analysis/nat_freight_stats/docs/13factsfigures/pdfs/fff2013_highres.pdf
A14: Buildings and Appliances | B14: Building Component Electrification | C14: Fraction of New Bldg Components Shifted to Other Fuels | D14: Building Component Electrification | E14: bldgs new component fuel shifting | F14: 0 | G14: 1 | H14: 0.01 | I14: % of newly sold non-electric building components | J14: **Description:** This policy replaces the specified fraction of newly sold non-electric building components of the selected type(s) in buildings of the selected type(s) with electricity-using components. // **Guidance for setting values:** The "Implementation Plan for Carbon Peaking in Urban and Rural Buildings" promotes the 100% electrification of newly-built public buildings, and encourages the electrification of heating, water heating, cooking, etc. in the building sector. By 2030, electricity accounts for more than 65% of building energy consumption. | K14: buildings-sector-main.html#component-elec | L14: building-component-electrification.html | M14: EIA AEO
A15: Buildings and Appliances | B15: Building Energy Efficiency Standards | C15: Reduction in E Use Allowed by Component Eff Std | D15: Building Energy Efficiency Standards | E15: bldgs efficiency standards | F15: 0 | G15: 1 | H15: 0.01 | I15: % reduction in energy use | J15: **Description:** This policy tightens energy efficiency standards for the selected component(s) in the selected building type(s). The policy only applies to newly sold components each year (whether for new buildings or replacement of old components of existing buildings). // **Guidance for setting values:** The average energy-saving rate of one-star green residential buildings is no higher than the mandatory energy-saving rate, while 10% higher for two-star and three-star buildings; According to the Technical Standards for Near-Zero Energy Buildings (GB/T51350-2019), ultra-low energy buildings are to save 50% more energy (residential and public buildings) on the compared to mandatory standards; near-zero energy buildings are to save 60%-75% more energy (75% for residential and 60% for public buildings). | K15: buildings-sector-main.html#eff-stds | L15: building-energy-efficiency-standards.html | M15: Edison Foundation, 2011, "Assessment of Electricity Savings in the U.S. Achievable through New Appliance/Equipment Efficiency Standards and Building Efficiency Codes (2010 - 2025)", http://www.edisonfoundation.net/iei/Documents/IEE_CodesandStandardsAssessment_2010-2025_UPDATE.pdf, Page B-2, Table B-1. | N15: Itron, 2007, "ASSESSMENT OF LONG-TERM ELECTRIC ENERGY EFFICIENCY POTENTIAL IN CALIFORNIA’S RESIDENTIAL SECTOR," http://www.energy.ca.gov/2007publications/CEC-500-2007-002/CEC-500-2007-002.PDF, p.33, Table 5-1
A16: Buildings and Appliances | B16: Contractor Training | C16: Boolean Improved Contractor Edu and Training | D16: Contractor Training | E16: bldgs contractor training | F16: 0 | G16: 1 | H16: 1 | I16: on/off | J16: **Description:** This policy represents a program to train contractors in energy-efficient products and installation practices. This covers activities such as air sealing, building framing, and choice and application of insulation. This policy affects newly sold building envelope components, which reduce the energy use of heating, cooling, and ventilation systems in buildings by 3.7% (based on a 2006 study from the Energy Center of Wisconsin). | K16: buildings-sector-main.html#contractor-ed | L16: contractor-training.html
A17: Buildings and Appliances | B17: Distributed Solar Carve-Out | C17: Min Fraction of Total Elec Demand to be Met by Distributed Solar PV | D17: Distributed Solar Promotion | E17: bldgs min fraction distributed solar | F17: 0 | G17: =ROUND(MaxBoundCalculations!B172,2) -> 0.24 | H17: 0.005 | I17: minimum % elec from solar | J17: **Description:** This policy requires at least the specified percentage of total retail electricity demand to be generated by residential and commercial buildings' distributed solar systems (typically rooftop PV). // **Guidance for setting values:**The proportion of electricity from rooftop PV in the total electricity consumption. | K17: buildings-sector-main.html#solar-carve-out | L17: solar-carve-out.html | M17: MASSACHUSETTS: http://www.mass.gov/eea/energy-utilities-clean-tech/renewable-energy/solar/rps-solar-carve-out/current-status-of-the-rps-solar-carve-out-program.html COLORADO: http://www.seia.org/research-resources/rps-solar-carve-out-colorado | N17: RMI, 2011, "Reinventing Fire Electricity Sector Methodology," http://www.rmi.org/cms/Download.aspx?id=10765&file=Reinventing+Fire+Electricity+Sector+Methodology.pdf&title=Reinventing+Fire+Electricity+Sector+Methodology, Page 11, 2050 Generation by Case
A18: Buildings and Appliances | B18: Distributed Solar Subsidy | C18: Perc Subsidy for Distributed Solar PV Capacity | D18: Distributed Solar Promotion | E18: bldgs distributed solar subsidy | F18: 0 | G18: 0.5 | H18: 0.01 | I18: % of PV system cost | J18: **Description:** This policy causes the government to reimburse building owners for a percentage of the cost of new distributed solar PV capacity that is installed on or around buildings. // **Guidance for setting values:** According to "Notice on matters related to the new energy feed-in tariff policy in 2021", from 2021 onwards for the new record of centralized photovoltaic power plants, commercial and industrial distributed photovoltaic projects and newly approved onshore wind power projects, the central government no longer subsidize. | K18: buildings-sector-main.html#distributed-solar-subsidy | L18: distributed-solar-subsidy.html | M18: Department of Energy. Business Energy Investment Tax Credit (ITC). http://energy.gov/savings/business-energy-investment-tax-credit-itc
A19: Buildings and Appliances | B19: Improved Labeling | C19: Boolean Improved Device Labeling | D19: Improved Labeling | E19: bldgs device labeling | F19: 0 | G19: 1 | H19: 1 | I19: on/off | J19: **Description:** This policy represents a program requiring newly sold heating systems, cooling and ventilation systems, and appliances to feature prominent, well-designed labels highlighting their energy efficiencies. The policy reduces energy consumption of newly sold building components of these types by 10%.// **Guidance for setting values:** China has implemented the "Energy Efficiency Labeling Management Measures" since 2016. | K19: buildings-sector-main.html#device-labeling | L19: improved-labeling.html | M19: none
A20: Buildings and Appliances | B20: Retrofit Existing Buildings | C20: Share of Preexisting Buildings Subject to Retrofitting | D20: Increased Retrofitting | E20: bldgs retrofitting | F20: 0 | G20: 0.5 | H20: 0.01 | I20: % of existing buildings | J20: **Description:** Each year, the specified percentage of the selected building type(s) that existed at the start of the model run will be retrofit with more efficient heating, cooling, and envelope components. // **Guidance for setting values:** China's target during 2020-2025 is around 0.1%, while the annual building retrofitting rate must increase to 2.5% by 2030 in developed economies to achieve net zero emission. | K20: buildings-sector-main.html#retrofitting | L20: increased-retrofitting.html | M20: Calculated from model data; see the relevant variable(s) in the InputData folder for source information.
A21: Buildings and Appliances | B21: Rebate for Efficient Products | C21: Boolean Rebate Program for Efficient Components | D21: Rebate for Efficient Products | E21: bldgs rebate | F21: 0 | G21: 1 | H21: 1 | I21: on/off | J21: **Description:** This policy represents a modest rebate paid to customers who purchase energy-efficient building equipment of the selected type(s). **Guidance for setting values:** After releasing Notice on Several Measures to Promote The Consumption of Green Smart Home Appliances, provincial and municipal implementation landed. | K21: buildings-sector-main.html#rebate | L21: rebate-for-efficient-products.html
A22: Electricity Supply | B22: Ban New Power Plants | C22: Boolean Ban New Power Plants | D22: Ban New Power Plants | E22: elec ban new power plants | F22: 0 | G22: 1 | H22: 1 | I22: on/off | J22: **Description:** This policy prevents new capacity of the selected type(s) from being built or deployed. | K22: electricity-sector-main.html#ban | L22: ban-new-capacity.html
A23: Electricity Supply | B23: Carbon Capture and Sequestration | C23: Electricity Sector Fraction of Potential Additional CCS Achieved | D23: Clean Electricity Standard | E23: elec CCS | F23: 0 | G23: 1 | H23: 0.01 | I23: % of CO2 captured | J23: **Description:** This policy specifies the fraction of CO2 emissions from power plants that is captured and stored, above the amount predicted in the business-as-usual scenario. // **Guidance for setting values:** As very few CCS-equipped power plants exist today, a value above 20% or so is likely very optimistic in most policy scenarios. The main exception would be a scenario in which most fossil power plants retire due to other policies, making it feasible to equip a high percentage of the few surviving fossil plants with CCS. | K23: ccs.html#ccs | L23: carbon-capture-and-sequestration.html
A24: Electricity Supply | B24: Renewable Energy | C24: Renewable Portfolio Std Percentage | D24: Renewable Energy | E24: elec renewable portfolio standards | F24: 0 | G24: 1 | H24: 0.01 | I24: % of electricity generation | J24: **Description:** This policy specifies an increase in the fraction of electricity generation that must come from qualifying carbon-free sources (wind, solar, biomass, nuclear, hydro, and geothermal) in 2060. This policy has no effect until the user-set value exceeds the existing fraction of carbon-free electricity and any carbon-free electricity standards reflected in BAU. // **Guidance for setting values:** China came out with new RPS policies to reach about 33% in 2025. A request for public opinion, a goal of 40% for all provinces except Tibet in 2030 was proposed. Inner Mongolia's Energy 14th FYP declared the that share of non-fossil power generation will rise from 17.3% in 2020, to 30% by 2035. When setting a high CES with this lever, users should also turn on supporting power sector policies (i.e., Grid-Scale Electricity Storage, Increase Transmission, and Demand Response) to avoid curtailment of renewables. At very high CES values, the associated policy costs are highly uncertain and should be complemented with other modeling. | K24: electricity-sector-main.html#ces | L24: clean-energy-standard.html | M24: White House, 2015, "Fact Sheet: President Obama to Announce Historic Carbon Pollution Standards for Power Plants", https://www.whitehouse.gov/the-press-office/2015/08/03/fact-sheet-president-obama-announce-historic-carbon-pollution-standards.
A25: Electricity Supply | B25: Change Electricity Exports | C25: Percent Change in Electricity Exports | D25: Electricity Imports and Exports | E25: elec change exports | F25: -0.5 | G25: 1 | H25: 0.02 | I25: % change in exports | J25: **Description:** This policy increases or decreases the amount of electricity exported from Shandong. It does not cause the construction or removal of transmission lines linking the province. // **Guidance for setting values:** Thanks to its vast land area, great solar and wind resource, and abundant coal reserve. Inner Mongolia has always been a major power provider in China, the construction of new export powerline enhances its capability to export. Between 2017 and 2021, Inner Mongolia's annual electricity export has increased from 156TWh to 247TWh, and is seeking to continuely increase its capacity to export renewable energy. | K25: electricity-sector-main.html#elec-exports | L25: electricity-imports-exports.html | M25: Energy Information Administation. 2016. Electric Power Annual. Table 2.13.
A26: Electricity Supply | B26: Change Electricity Imports | C26: Percent Change in Electricity Imports | D26: Electricity Imports and Exports | E26: elec change imports | F26: -0.5 | G26: 1 | H26: 0.02 | I26: % change in imports | J26: **Description:** This policy increases or decreases the amount of electricity imported to Shandong. It does not cause the construction or removal of transmission lines linking the province. // **Guidance for setting values:** Eastern Inner Mongolia accepts power from China's northeast regions, particular Jilin province, whereas western Inner Mongolia imports power from Shanxi and Ningxia Province, but its electricity import is much smaller than export. | K26: electricity-sector-main.html#elec-imports | L26: electricity-imports-exports.html | M26: Energy Information Administation. 2016. Electric Power Annual. Table 2.13.
A27: Electricity Supply | B27: Non BAU Guaranteed Dispatch | C27: Boolean Use Non BAU Guaranteed Dispatch Settings | D27: Non BAU Guaranteed Dispatch | E27: elec non BAU guaranteed dispatch | F27: 0 | G27: 1 | H27: 1 | I27: on/off | J27: **Description:** This policy uses an alternative garanteed dispatched percentage for each type of generation. // **Guidance for setting values:** China currently has a garanteed full purchase of renewable generation (wind, solar, biomass, geothermal and tidal energy). However, the policy may not be preferable as renewable penetration continues to grow. An alternative garanteed dispatch percentage is set at 80% for wind and solar, and 50% for all other renewable generation.
A28: Electricity Supply | B28: Demand Response | C28: Fraction of Additional Demand Response Potential Achieved | D28: Demand Response | E28: elec demand response | F28: 0 | G28: 1 | H28: 0.01 | I28: % of potential achieved | J28: **Description:** This policy represents regulations that cause more demand response (DR) capacity to be added to the electric grid. Demand response provides flexibility that allows for the integration of more wind and solar PV, if the electricity system is flexibility-constrained. // **Guidance for setting values:** A 100% setting provides will make Inner Mongolia's DR capacity to reach 20% of peak hour demand capacity by 2035, instead of the 3% requirement released in 2016. The announced policy scenario increases the DR capacity to 8% by 2030, as laid out in Western Inner Mongolia New Power System Action Plan. | K28: electricity-sector-main.html#dr | L28: demand-response.html | M28: Calculated from model data; see the relevant variable(s) in the InputData folder for source information.
A29: Electricity Supply | B29: Early Retirement of Power Plants | C29: Annual Additional Capacity Retired due to Early Retirement Policy | D29: Early Retirement of Power Plants | E29: elec early retirement | F29: 0 | G29: 25000 | H29: 500 | I29: MW/year | J29: **Description:** This policy causes the specified quantity of otherwise non-retiring capacity of the selected type(s) to be retired each year. | K29: electricity-sector-main.html#early-ret | L29: early-retirement-of-power-plants.html | M29: Energy Information Administration, 2014, "Annual Energy Outlook 2014", http://www.eia.gov/oiaf/aeo/tablebrowser/#release=AEO2014&subject=6-AEO2014&table=9-AEO2014&region=0-0&cases=hccstom-d012314a,ref2014-d102413a, Table Browser. Select Electric Power Sector, Electricity Generating Capacity (and check Reference and Accelerated coal retirements scenarios). | N29: The Brattle Group, 2012, "Potential Coal Plant Retirements: 2012 Update," http://greatlakeslegalfoundation.org/wwcms/wp-content/uploads/documents/regulatory/TrainWreck/12Oct15_BrattleStudy.pdf, Page 8, Table 4
A30: Electricity Supply | B30: Grid-Scale Electricity Storage | C30: Fraction of Additional Grid Battery Storage Potential Achieved | D30: Grid-Scale Electricity Storage | E30: elec storage growth | F30: 0 | G30: 1 | H30: 0.01 | I30: % of potential achieved | J30: **Description:** This policy causes grid-scale electricity storage from chemical batteries to increase above the amount predicted in the BAU Scenario. // **Guidance for setting values:** A 100% setting provides will double Inner Mongolia's grid side battery installation from 31 GW to 205 GW in 2060. | K30: electricity-sector-main.html#storage | L30: grid-scale-electricity-storage.html | M30: National Renewable Energy Laboratory, 2014, Renewable Electricity Futures Scenario Viewer, http://www.nrel.gov/analysis/re_futures/data_viewer/# 80% RE-ITI (2014) scenario
A31: Electricity Supply | B31: Increase Transmission | C31: Percentage Increase in Transmission Capacity vs BAU | D31: Increase Transmission | E31: elec transmission growth | F31: 0 | G31: =ROUND(MaxBoundCalculations!B181,2) -> 1.13 | H31: 0.01 | I31: % increase in transmission capacity | J31: **Description:** This policy causes additional transmission capacity to be built relative to the BAU case. Transmission increases the flexibility of the grid, allowing for the integration of more wind and solar PV, if the electricity system is flexibility-constrained. // **Guidance for setting values:** According to our current setting, Inner Mongolia's transmission capacity grows proportionally with its total generation capacity. The renewable generation growth generally is not constrained by transmission or system flexibility. Increasing transmission will not significantly alter the model's output. | K31: electricity-sector-main.html#transmission | L31: increase-transmission.html | M31: National Renewable Energy Laboratory, 2014, Renewable Electricity Futures (Vol. 1), http://www.nrel.gov/docs/fy12osti/52409-1.pdf, Page xli, Figure ES-8, 80% RE scenario. | N31: National Renewable Energy Laboratory, 2014, Renewable Electricity Futures (Vol. 1), http://www.nrel.gov/docs/fy12osti/52409-1.pdf, Page 2-10, 90% RE scenario.
A32: Electricity Supply | B32: Non BAU Capacity Retirement Schedule | C32: Boolean Use Non BAU Capacity Retirement Schedule | D32: Non BAU Capacity Retirement Schedule | F32: 0 | G32: 1 | H32: 1 | I32: on/off | J32: **Description:** This policy uses an alternative retirement schedule for existing capacity of the selected type(s). // **Guidance for setting values:** The alternative retirement schedule considers the additional capacity installed in the non BAU mandated capacity construction, so for a given type of generation, it is best to turn on/off retirement and construction schedule at the same time.
A33: Electricity Supply | B33: Non BAU Mandated Capacity Construction | C33: Boolean Use Non BAU Mandated Capacity Construction Schedule | D33: Non BAU Mandated Capacity Construction | F33: 0 | G33: 1 | H33: 1 | I33: on/off | J33: **Description:** The business-as-usual case includes all planned capacity additions. // **Guidance for setting values:** This policy includes all announced plant projects to date as well as the targets annouced in Inner Mongolia's 14th FYP. Since China has loosen its constraints in coal generation recently, the alternative schedule will include more coal capacity. The alternative retirement schedule considers the additional capacity installed in the non BAU mandated capacity construction, so for a given type of generation, it is best to turn on/off retirement and construction schedule at the same time.
A34: Electricity Supply | B34: Non BAU RPS Qualifying Resources | C34: Boolean Use Non BAU RPS Qualifying Resource Definitions | D34: Non BAU RPS Qualifying Resources | E34: elec non BAU RPS qualifying resources | F34: 0 | G34: 1 | H34: 1 | I34: on/off | J34: **Description:** This policy uses an alternative definition of what qualifies as renewable generation. // **Guidance for setting values:** Under BAU scenario, all non-fossil fuel generation are viewed as Renewable in China. Under alternative assumption, nuclear and hydro are excluded for environmental and safety concerns. Biomass and municipal solid waste generation are also excluded as they are not truly carbon-neutral.
A35: Electricity Supply | B35: Nuclear Plant Lifetime Extension | C35: Nuclear Capacity Lifetime Extension | D35: Nuclear Lifetime Extension | F35: 0 | G35: 20 | H35: 1 | I35: year(s) | J35: **Description:** This policy extends the lifetime of all nuclear plants by the specified number of years. | K35: electricity-sector-main.html#life-ext | L35: nuclear-lifetime-extension.html | M35: U.S. Energy Information Administration, 2014, "Almost all U.S. nuclear plants require life extension past 60 years to operate beyond 2050", http://www.eia.gov/todayinenergy/detail.cfm?id=19091. | N35: U.S. Energy Information Administration, 2014, "Almost all U.S. nuclear plants require life extension past 60 years to operate beyond 2050", http://www.eia.gov/todayinenergy/detail.cfm?id=19091.
A36: Electricity Supply | B36: Reduce Plant Downtime | C36: Percentage Reduction in Plant Downtime | D36: Reduce Plant Downtime | E36: elec reduce plant downtime | F36: 0 | G36: 0.6 | H36: 0.01 | I36: % reduction in downtime | J36: **Description:** This policy specifies the reduction in downtime (time spent not generating power) for plants of the selected type(s) that exist at the start of the model run. This policy increases these plants' target capacity factors, but it does not force them to be dispatched if it would be uneconomical to do so. // **Guidance for setting values:** // **Preexisting Natural Gas Nonpeaker:** Preexisting natural gas nonpeakers have an average capacity factor of 48%. As part of the proposed Clean Power Plan, the EPA assumed that nonpeaking natural gas plants could be reach a 75% capacity factor (ramping up to that value over a number of years). This would represent a 49% reduction in downtime. // **New Wind:** Availability of wind cannot be changed by policy, so the main method of increasing capacity factor is technological improvement of wind turbines. The National Renewable Energy Laboratory estimates that "near-future" wind technology could increase capacity factors by about 10 percentage points in most parts of the country. The average capacity factor of new turbines in the BAU case is roughly 47%, so an improvement to 57% might be represented as an 19% setting of this policy lever. // **New Solar PV:** Availability of sunlight cannot be changed by policy, so the main method of improvement is increasing the efficiency of solar cells. Typical crystalline silicon cells today have efficiencies of 20-25%, while today's best multi-junction cells (used primarily in concentrator PV and aerospace applications) have efficiencies of 40-45%. If the typical cells installed in 2050 will have efficiencies similar to today's best multi-junction cells, this might be represented as a 26% setting of this policy lever. | K36: electricity-sector-main.html#red-downtime | L36: reduce-downtime.html | M36: E&E Publishing. The Clean Power Plan - A Summary. http://www.eenews.net/interactive/clean_power_plan/fact_sheets/rule National Renewable Energy Laboratory. United States (48 Contiguous States) Potential Wind Capacity Cumulative Area vs. Gross Capacity Factor. http://apps2.eere.energy.gov/wind/windexchange/pdfs/wind_maps/us_contiguous_wind_potential_chart.pdf See the discussion of multi-junction solar cells on Wikipedia at https://en.wikipedia.org/wiki/Multi-junction_solar_cell. Also NREL has a useful chart at http://www.nrel.gov/ncpv/images/efficiency_chart.jpg.
A37: Electricity Supply | B37: Reduce Soft Costs | C37: Percent Reduction in Soft Costs of Capacity Construction | D37: Reduce Soft Costs | E37: elec reduce soft costs | F37: 0 | G37: 0.9 | H37: 0.01 | I37: % reduction in soft costs | J37: **Description:** This policy specifies a reduction in soft costs (costs for things other than capital equipment) for new plants of the selected type(s), such as the costs of permitting, financing, project management, assembly, etc. // **Guidance for setting values:** Costs of permitting and financing can be reduced by streamlining permitting processes, but some soft costs (such as labor) may be difficult to reduce via policy. A value of 50% would be an aggressive soft cost reduction. | K37: endogenous-learning.html#red-soft-costs | L37: reduce-soft-costs.html
A38: Electricity Supply | B38: Reduce Transmission & Distribution Losses | C38: Percentage TnD Losses Avoided | D38: Reduce T&D Losses | E38: elec avoid TND loss | F38: 0 | G38: 0.4 | H38: 0.01 | I38: % of losses avoided | J38: **Description:** This policy specifies the reduction in transmission and distribution losses that will be achieved by 2050. // **Guidance for setting values:** In 2020, Inner Mongolia's electricity transmission losses is about 3.82% according to statistics, which is lower than the national average by 1.4%. In its 14th FYP, the Autonomous Region announced to reduce losses to 3.5% by 2025, or 8.46% decrease compared to BAU. | K38: electricity-sector-main.html#red-tnd-losses | L38: reduce-tnd-losses.html | M38: The World Bank. Electric power transmission and distribution losses (% of output). http://data.worldbank.org/indicator/EG.ELC.LOSS.ZS
A39: Electricity Supply | B39: Subsidy for Capacity Construction | C39: Perc Subsidy for Elec Capacity Construction | D39: Subsidy for Capacity Construction | E39: elec capacity construction subsidy | F39: 0 | G39: 0.95 | H39: 0.01 | I39: % of construction cost | J39: **Description:** This policy is a subsidy paid by the government to electricity suppliers per unit of new capacity constructed. This only applies to utilities, not distributed systems (such as rooftop solar). // **Guidance for setting values:** Generally speaking, China is phasing out subsidy for renewables gradually. However, there might be local subsidies still in place. | K39: electricity-sector-main.html#subsidies | M39: https://www.energy.gov/articles/secretary-perry-announces-financial-close-additional-loan-guarantees-during-trip-vogtle https://www.energysage.com/solar/cost-benefit/solar-investment-tax-credit/ http://biomassmagazine.com/articles/8185/usda-loan-guarantees-support-3-biomass-power-plants
A40: Electricity Supply | B40: Subsidy for Electricity Production | C40: Subsidy for Elec Production by Fuel | D40: Subsidy for Electricity Production | E40: elec generation subsidy | F40: 0 | G40: 60 | H40: 1 | I40: =UnitControlCenter!$B$48 -> 2020 RMB / MWh | J40: **Description:** This policy is a subsidy paid by the government to suppliers of electricity per unit of electricity generated from the selected plant type(s). // **Guidance for setting values:** China is phasing out subsidy for renewables gradually. However, there are still subsidies for renewables in subnational regions. | K40: electricity-sector-main.html#subsidies | L40: subsidy-for-electricity-production.html | M40: PRODUCTION TAX CREDIT: Database of State Incentives for Renewables & Efficiency, 2013, "Renewable Energy Production Tax Credit (PTC)", http://dsireusa.org/incentives/incentive.cfm?Incentive_Code=US13F. STATE-LEVEL INCENTIVES: Energy Information Administration, 2013, "Feed-In Tariffs and similar programs", http://www.eia.gov/electricity/policies/provider_programs.cfm.
A41: Industry | B41: Buy In-Region Products | C41: Fraction of Imported Industrial Outputs Shifted to In Region Suppliers | D41: Buy In-Region Products | E41: indst buy in region outputs | F41: 0 | G41: 0.5 | H41: 0.01 | I41: % of imports shifted | J41: **Description:** This policy increases the extent to which the selected industry's products are supplied by producers within the modeled region. // **Guidance for setting values:** The lever specifies the percentage of imported products (in the BAU case) that are shifted to domestic suppliers (in the policy case). For example, suppose buyers within the modeled region purchase 60% of their road vehicles from domestic automakers and 40% from automakers outside the modeled region. If this policy lever is applied to the "Road Vehicles" industry with a 50% setting, buyers will obtain 80% of their road vehicles from domestic automakers and 20% from automakers outside the modeled region. // **Implementation Note:** This policy reduces imports. In reality, other regions might retaliate by restricting their own purchases of goods produced by the modeled region. However, the EPS only considers policies within the modeled region, so the Buy In-Region Products policy does not affect export levels (i.e., other countries/regions are assumed not to retaliate).
A42: Industry | B42: Carbon Capture and Sequestration | C42: Industry Sector Fraction of Potential Additional CCS Achieved | D42: Industry CCS | E42: indst CCS | F42: 0 | G42: 1 | H42: 0.01 | I42: % of CO2 captured | J42: **Description:** This policy specifies the fraction of CO2 emissions from power plants that is captured and stored, above the amount predicted in the business-as-usual scenario. // **Guidance for setting values:** As very few CCS-equipped power plants exist today, a value above 20% or so is likely very optimistic in most policy scenarios. The main exception would be a scenario in which most fossil power plants retire due to other policies, making it feasible to equip a high percentage of the few surviving fossil plants with CCS. | K42: ccs.html#ccs | L42: carbon-capture-and-sequestration.html
A43: Industry | B43: Cement Clinker Substitution | C43: Fraction of Cement Measures Achieved | D43: Cement Clinker Substitution | E43: indst cement measures | F43: 0 | G43: 1 | H43: 0.01 | I43: % of potential achieved | J43: **Description:** This policy reduces CO2 emissions from the cement industry by substituting other inputs, such as fly ash, for a portion of the clinker in cement. // **Guidance for setting values:** If this policy is fully implemented, the share of clinker in cement is reduced from 74% to 60%, clinker percentage will decrease by 18.9%. | K43: industry-ag-main.html#clinker | L43: cement-clinker-substitution.html | M43: International Energy Agency and Cement Sustainability Initiative. 2018. Technology Roadmap: Low-Carbon Transition in the Cement Industry. p41. http://www.iea.org/publications/freepublications/publication/TechnologyRoadmapLowCarbonTransitionintheCementIndustry.pdf
A44: Industry | B44: Cogeneration and Waste Heat Recovery | C44: Fraction of Potential Cogeneration and Waste Heat Recovery Adopted | D44: Cogeneration and Waste Heat Recovery | E44: indst CHP | F44: 0 | G44: 1 | H44: 0.01 | I44: % of potential achieved | J44: **Description:** This policy reduces fuel consumption in the industry sector by increasing the use of cogeneration (also known as combined heat and power) and recovery of waste heat (to perform useful work). | K44: industry-ag-main.html#cogen | L44: cogeneration-and-waste-heat-recovery.html | M44: Calculated from model data; see the relevant variable(s) in the InputData folder for source information.
A45: Industry | B45: Early Retirement of Industrial Facilities | C45: Fraction of Energy Savings from Early Facility Retirement Achieved | D45: Early Retirement of Industrial Facilities | E45: indst early retirement | F45: 0 | G45: 1 | H45: 0.01 | I45: % of potential achieved | J45: **Description:** This policy reduces fuel consumption in the industry sector by retiring older, inefficient industrial facilities sooner than they otherwise would retire. This policy does not affect demand for industrial products, so it is assumed that any facilities retired under this policy are replaced by new facilities or increased output from existing facilities in the same year. // **Guidance for setting values:** In Inner Mongolia, if this policy is fully implemented, fuel use in the 6 high energy-consuming industriesis will reduced between 1% and 11% in 2025. | K45: industry-ag-main.html#early-ret | L45: early-retirement-of-industrial-facilities.html | M45: Calculated from model data; see the relevant variable(s) in the InputData folder for source information.
A46: Industry | B46: Industry Energy Efficiency Standards | C46: Percentage Improvement in Eqpt Efficiency Standards above BAU | D46: Industry Energy Efficiency Standards | E46: indst efficiency standards | F46: 0 | G46: 0.25 | H46: 0.01 | I46: % reduction in energy use | J46: **Description:** This policy reduces fuel consumption by the selected industry by increasing the efficiency of industrial equipment through stronger standards. The policy setting refers to overall energy use reduction, not the reduction in energy use of newly sold equipment. // **Guidance for setting values:** In 2022, the Ministry of Industry and Information Technology and five other ministries issued a notification on the "Action Plan for Industrial Energy Efficiency Improvement," which proposed continuous improvement in the energy efficiency of equipment systems. In Inner Mongolia, if this policy is fully implemented, fuel use in the 5 high energy-consuming industriesis will reduced between 1% and 14% in 2025. | K46: industry-ag-main.html#eff-stds | L46: industry-energy-efficiency-standards.html | M46: U.S. DOE, 2016, Industrial Energy Efficiency Potential Analysis, https://energy.gov/sites/prod/files/2017/04/f34/energy-savings-by-state-industrial-methodology.pdf | N46: U.S. DOE, 2016, Industrial Energy Efficiency Potential Analysis, https://energy.gov/sites/prod/files/2017/04/f34/energy-savings-by-state-industrial-methodology.pdf
A47: Industry | B47: Improved System Design | C47: Fraction of Installation and System Integration Issues Remedied | D47: Improved System Design | E47: indst system integration | F47: 0 | G47: 1 | H47: 0.01 | I47: % of potential achieved | J47: **Description:** This policy reduces fuel consumption in the industry sector by improving the way components are put together and the way material or energy flows between them. | K47: industry-ag-main.html#system-integ | L47: improved-system-design.html | M47: Calculated from model data; see the relevant variable(s) in the InputData folder for source information.
A48: Industry | B48: Electrification + Hydrogen (Med & High Temp) | C48: Fraction of Med and High Temp Industrial Heat Shifted to Other Fuels | D48: Electrification + Hydrogen | E48: indst med and high temp fuel type shifting | F48: 0 | G48: 1 | H48: 0.01 | I48: % of fuel shifted | J48: **Description:** This policy reduces greenhouse gas emissions from the selected industry by switching the fuels used by facilities for medium and high-temperature heat to electricity and/or hydrogen. Only fuel consumed for energy, not fuel used as a chemical feedstock, is affected by this policy. // **Guidance for setting values:** Separately set the percentages of non-electricity, non-hydrogen fuel used by this industry for medium and high-temp heat in the BAU case to be shifted to electricity and to hydrogen. (If your settings total more than 100%, the effects will be scaled down proportionately so that the total fuel shifted does not exceed 100%.) Over 90% of thermal fuels (excluding feedstocks) are used to generate process heat or to fuel boilers. Generally, lower-temperature heat is easier to electrify than higher-temperature heat, while hydrogen can meet heat needs of any temprature.In the heat-intensive 19 industries in the China, about one-third of heat demand is below 200 degrees Celsius, while the remaining two-thirds is above 200 degrees Celsius. According to "Action Plan for Industrial Energy Efficiency Enhancement", the proportion of electricity in industrial final energy consumption is expected to reach approximately 30% in 2025. According to "China Annual Development Report on Electrification 2021", the proportion of electricity in industrial final energy consumption was 26.2% in 2020. | K48: industry-ag-main.html#fuel-switching | L48: industry-elec-and-hydrogen.html
A49: Industry | B49: Electrification (Low Temp) | C49: Fraction of Low Temp Industrial Heat Shifted to Other Fuels | D49: Electrification + Hydrogen | E49: indst low temp fuel type shifting | F49: 0 | G49: 1 | H49: 0.01 | I49: % of fuel shifted | J49: **Description:** This policy reduces greenhouse gas emissions from the selected industry by switching the fuels used by facilities for low-temperature heat to electricity. Only fuel consumed for energy, not fuel used as a chemical feedstock, is affected by this policy. // **Guidance for setting values:** Separately set the percentages of non-electricity, non-hydrogen fuel used by this industry for low-temp heat in the BAU case to be shifted to electricity. (If your settings total more than 100%, the effects will be scaled down proportionately so that the total fuel shifted does not exceed 100%.) Over 90% of thermal fuels (excluding feedstocks) are used to generate process heat or to fuel boilers. Generally, lower-temperature heat is easier to electrify than higher-temperature heat, while hydrogen can meet heat needs of any temperature (we reserve switching to hydrogen fuel for medium and high-temperature processes). In the heat-intensive 19 industries in the China, about one-third of heat demand is below 200 degrees Celsius, while the remaining two-thirds is above 200 degrees Celsius. According to "Action Plan for Industrial Energy Efficiency Enhancement", the proportion of electricity in industrial final energy consumption is expected to reach approximately 30% in 2025. According to "China Annual Development Report on Electrification 2021", the proportion of electricity in industrial final energy consumption was 26.2% in 2020. | K49: industry-ag-main.html#fuel-switching | L49: industry-elec-and-hydrogen.html
A50: Industry | B50: F-Gas Substitution | C50: Fraction of F Gas Substitution Achieved | D50: F-gas Measures | E50: indst f gas substitution | F50: 0 | G50: 1 | H50: 0.01 | I50: % of potential achieved | J50: **Description:** This policy reduces emissions of high-GWP, fluorinated gases (F-gases) from the industry sector by substituting less-harmful chemicals. // **Guidance for setting values:** If this policy is fully implemented, its emission reduction potential in that year would be that of all cost-effective measures based on the level of the carbon price in that year. | K50: industry-ag-main.html#avoid-f-gases | L50: avoid-f-gases.html | M50: Calculated from model data; see the relevant variable(s) in the InputData folder for source information.
A51: Industry | B51: F-Gas Destruction | C51: Fraction of F Gas Destruction Achieved | D51: F-gas Measures | E51: indst f gas destruction | F51: 0 | G51: 1 | H51: 0.01 | I51: % of potential achieved | J51: **Description:** This policy reduces emissions of high-GWP, fluorinated gases (F-gases) from the industry sector by destroying F-gases created as byproducts during the creation of desired products. // **Guidance for setting values:** If this policy is fully implemented, its emission reduction potential in that year would be that of all cost-effective measures based on the level of the carbon price in that year. | K51: industry-ag-main.html#avoid-f-gases | L51: avoid-f-gases.html
A52: Industry | B52: F-Gas Recovery | C52: Fraction of F Gas Recovery Achieved | D52: F-gas Measures | E52: indst f gas recovery | F52: 0 | G52: 1 | H52: 0.01 | I52: % of potential achieved | J52: **Description:** This policy reduces emissions of high-GWP, fluorinated gases (F-gases) from the industry sector by reducing leakage and losses through improved inspections, maintenance, and retrofitting of equipment. // **Guidance for setting values:** If this policy is fully implemented, its emission reduction potential in that year would be that of all cost-effective measures based on the level of the carbon price in that year. | K52: industry-ag-main.html#avoid-f-gases | L52: avoid-f-gases.html
A53: Industry | B53: F-Gas Eqpt. Maintenance & Retrofits | C53: Fraction of F Gas Inspct Maint Retrofit Achieved | D53: F-gas Measures | E53: indst f gas inspct maint retrofit | F53: 0 | G53: 1 | H53: 0.01 | I53: % of potential achieved | J53: **Description:** This policy reduces emissions of high-GWP, fluorinated gases (F-gases) from the industry sector by reducing leakage and losses through improved inspections, maintenance, and retrofitting of equipment. // **Guidance for setting values:** If this policy is fully implemented, its emission reduction potential in that year would be that of all cost-effective measures based on the level of the carbon price in that year. | K53: industry-ag-main.html#avoid-f-gases | L53: avoid-f-gases.html
A54: Industry | B54: Material Efficiency, Longevity, & Re-Use | C54: Percent Reduction in Nonenergy Nonagriculture Industry Product Demand | D54: Material Efficiency, Longevity, & Re-Use | E54: indst reduce nonenergy product demand | F54: 0 | G54: 1 | H54: 0.01 | I54: % demand reduction | J54: **Description:** // **Cement and Iron & Steel:** This policy reduces demand for the selected materials through techniques such as material-efficient building codes (using modern designs that require less material per unit floor area), requirements for greater building and infrastructure longevity, greater re-use and re-purposing of buildings (rather than tearing down and building new), etc. // **Guidance for setting values:**According to the study "Reinventing Energy: China Industrial Volume, The 2050 remodeling scenario could reduce cement production by 795 million tons by reducing unreasonable demand and improving material quality and strength, contributing 49.68% relative to the 2050 reference scenario. // **Water and Waste:** This policy reduces demand for water treatment and waste management services through techniques such as water conservation, reduction in disposable packaging, requirements for greater product longevity, greater repair and re-use of products, and increased recycling and composting. // **Guidance for setting values:** The majority of energy use and emissions from the water and waste sector are a result of water treatment, not solid waste management. The USDA reports that agriculture accounts for 80% of U.S. water consumption, and the U.S. EPA reports that "as much as 50 percent of the water we use outdoors is lost due to wind, evaporation, and runoff caused by inefficient irrigation methods and systems." Non-agriculture uses, including lawn irrigation and in-home use, may be able to achieve similar savings through improved practices and fixtures. | L54: material-efficiency-longevity-reuse.html | M54: Allwood and Cullen, "Sustainable Materials Without the Hot Air: Making Buildings, Vehicles and Products Efficiently and with Less New Material" Allwood and Cullen, "Sustainable Materials With Both Eyes Open" - page 185, http://www.withbotheyesopen.com/read.php?c=12 USDA Irrigation & Water Use: https://www.ers.usda.gov/topics/farm-practices-management/irrigation-water-use.aspx and EPA WaterSense Statistics and Facts: https://www.epa.gov/watersense/statistics-and-facts
A55: Industry | B55: Methane Capture | C55: Fraction of Methane Capture Opportunities Achieved | D55: Methane Capture and Destruction | E55: indst methane capture | F55: 0 | G55: 1 | H55: 0.01 | I55: % of potential achieved | J55: **Description:** This policy reduces methane emissions from the selected industry by increasing the capture of methane that is currently being released into the atmosphere (for example, stopping leaks from wellheads, pipes, coal mines, landfills, etc.). // **Guidance for setting values:** According to "Complementary Plan for Coalbed Methane (Coal Mine Gas) Development and Utilization in the 14th Five-Year Plan for the Development of the Coal Industry in Inner Mongolia Autonomous Region", during the 13th Five-Year Plan period, the gas utilization rate increased from 35.8% in 2016 to 39.5% in 2020. During the 14th Five-Year Plan period, demonstration mines for gas management will be established in five coal mines, including Huangbaizi in Wuhai and Bailing in Alxa Left Banner. The annual extraction volume will be 43 million cubic meters, and the annual utilization volume will be 24 million cubic meters, with a utilization rate of 56%. | K55: industry-ag-main.html#methane-capture | L55: methane-capture.html
A56: Industry | B56: Methane Destruction | C56: Fraction of Methane Destruction Opportunities Achieved | D56: Methane Capture and Destruction | E56: indst methane destruction | F56: 0 | G56: 1 | H56: 0.01 | I56: % of potential achieved | J56: **Description:** This policy reduces methane emissions from the selected industry by increasing the burning of methane that is currently being released into the atmosphere (i.e. flaring instead of venting/leaking). | K56: industry-ag-main.html#methane-destr | L56: methane-destruction.html
A57: Industry | B57: N2O Abatement | C57: Fraction of N2O Abatement Achieved | D57: N2O Abatement | E57: indst N2O abatement | F57: 0 | G57: 1 | H57: 0.01 | I57: % of potential achieved | J57: **Description:** This policy reduces nitrous oxide (N2O) process emissions from the chemicals industry (primarily from the production of nitric acid and adipic acid) by destroying the N2O rather than venting it to the atmosphere.
A58: Industry | B58: Reduce Fossil Fuel Exports | C58: Percent Reduction in Fossil Fuel Exports | D58: Percent Reduction in Fossil Fuel Exports | E58: indst reduce fossil fuel exports | F58: 0 | G58: 1 | H58: 0.01 | I58: % reduction in exports | J58: **Description:** This policy reduces production of the selected fuel type(s) for export. This lever may represent a reduction in fuel demand by actors outside the modeled region (i.e., not caused by domestic policy) or a conscious policy within the modeled region to transition its economy away from dependence on fossil fuel exports. // **Guidance for setting values:** Inner Mongolia is a major coal export hub in China. The region produced more than 1 billion tonnes to coal in 2020, approximately a quarter of China's total production, and exported 579 million tons of coal, 56% of its total production. | L58: reduce-fuel-exports.html | M58: Calculated from model data; see the relevant variable(s) in the InputData folder for source information.
A59: Agriculture, Land Use, and Forestry | B59: Afforestation and Reforestation | C59: Fraction of Afforestation and Reforestation Achieved | D59: Afforestation and Reforestation | E59: land afforestation and reforestation | F59: 0 | G59: 1 | H59: 0.01 | I59: % of potential achieved | J59: **Description:** This policy increases the sequestration of CO2 by planting forests. Planted forests are assumed to be managed with best practices and are not used for timber harvesting. //**Guidance for setting values:**"Inner Mongolia Autonomous Region's 14th Five-Year Plan for Forestry and Grassland Conservation and Development" outlines the main objectives for forestry and grassland conservation and development in Inner Mongolia Autonomous Region during the 14th Five-Year Plan period. The goal is to increase the forest coverage rate from 23% to 23.5% over five years. | K59: lulucf.html#aff-ref | L59: afforestation-and-reforestation.html | M59: Calculated from model data; see the relevant variable(s) in the InputData folder for source information. | N59: Ross W. Gorte, 2009, "U.S. Tree Planting for Carbon Sequestration," Congressional Research Service, https://www.fas.org/sgp/crs/misc/R40562.pdf, p.3, paragraph 1
A60: Agriculture, Land Use, and Forestry | B60: Avoid Deforestation | C60: Fraction of Avoided Deforestation Achieved | D60: Avoid Deforestation | E60: land avoid deforestation | F60: 0 | G60: 1 | H60: 0.01 | I60: % of potential achieved | J60: **Description:** This policy prevents clear cutting of forests that would otherwise be cleared. Preserved forests are assumed to be managed with best practices. | K60: lulucf.html#avoid-def | L60: avoid-deforestation.html
A61: Agriculture, Land Use, and Forestry | B61: Forest Restoration | C61: Fraction of Forest Restoration Achieved | D61: Forest Restoration | E61: land forest restoration | F61: 0 | G61: 1 | H61: 0.01 | I61: % of potential achieved | J61: **Description:** This policy increases CO2 sequestration by avoiding the conversion of forests and restoring forested areas. | L61: forest-restoration.html | M61: See file PLANAbPiaSY
A62: Agriculture, Land Use, and Forestry | B62: Forest Set-Asides | C62: Fraction of Forest Set Asides Achieved | D62: Forest Set-Asides | E62: land forest set asides | F62: 0 | G62: 1 | H62: 0.01 | I62: % of potential achieved | J62: **Description:** This policy avoids the release of CO2 from forests by reducing timber harvesting. // **Guidance for setting values:** A 100% setting of this lever reduces timber harvesting by 2% of the BAU amount per year, reaching a roughly 70% reduction in timber harvesting by 2050. | K62: lulucf.html#set-asides | L62: forest-set-asides.html | M62: Calculated from model data; see the relevant variable(s) in the InputData folder for source information.
A63: Agriculture, Land Use, and Forestry | B63: Cropland and Rice Measures | C63: Fraction of Cropland and Rice Measures Achieved | D63: Cropland and Rice Measures | E63: indst cropland and rice measures | F63: 0 | G63: 1 | H63: 0.01 | I63: % of potential achieved | J63: **Description:** This policy reduces greenhouse gas emissions from agriculture through cropland management practices, such as improved crop rotations, reduced soil tillage, and improvements in fertilizer composition and application. Measures particular to rice cultivation include improved flooding practices that avoid anaerobic, methane-forming conditions.. // **Guidance for setting values:**If this policy is fully implemented, its emission reduction potential in that year would be that of all cost-effective measures based on the level of the carbon price in that year. | K63: industry-ag-main.html#cropland | L63: cropland-management.html | M63: Calculated from model data; see the relevant variable(s) in the InputData folder for source information.
A64: Agriculture, Land Use, and Forestry | B64: Improved Soil Measures | C64: Fraction of CO2 Storage Through Tillage Practices | D64: Improved Soil Measures | E64: indst tillage | F64: 0 | G64: 1 | H64: 0.01 | I64: % of potential achieved | J64: **Description:** This policy stores CO2 in agricultural soils through improved tillage practices.
A65: Agriculture, Land Use, and Forestry | B65: Improved Forest Management | C65: Fraction of Improved Forest Management Achieved | D65: Improved Forest Management | E65: land forest management | F65: 0 | G65: 1 | H65: 0.01 | I65: % of potential achieved | J65: **Description:** This policy increases CO2 sequestration by forests through improved forest management practices. | K65: lulucf.html#forest-mgmt | L65: improved-forest-management.html | M65: Calculated from model data; see the relevant variable(s) in the InputData folder for source information.
A66: Agriculture, Land Use, and Forestry | B66: Livestock Measures | C66: Fraction of Livestock Measures Achieved | D66: Livestock Measures | E66: indst livestock measures | F66: 0 | G66: 1 | H66: 0.01 | I66: % of potential achieved | J66: **Description:** This policy reduces greenhouse gas emissions from agriculture through livestock-related measures, such as feed supplements or drugs to prevent enteric methane formation. // **Guidance for setting values:** According to "Work Plan for the Resource Utilization of Livestock and Poultry Manure(2017-2020)",the utilization rate of animal manure in Inner Mongolia was 75% in 2020. According to "Implementation Plan for Energy Conservation and Emission Reduction in Inner Mongolia Autonomous Region during the 14th Five-Year Plan",the utilization rate is expected to reach 84% or higher in 2025. The utilization rate of animal manure is expected to increase by 36% in 2025 compared to 2020. According to "Energy Conservation and Emission Reduction 13th Five-Year Plan for Inner Mongolia Autonomous Region", the comprehensive utilization rate of crop straw was 85% in 2020. According to "Implementation Plan for Energy Conservation and Emission Reduction in Inner Mongolia Autonomous Region during the 14th Five-Year Plan", the comprehensive utilization rate of crop straw is projected to stabilize at 90% or higher in 2025. the comprehensive utilization rate of crop straw is expected to increase by 33.3% in 2025 compared to 2020. According to "Recommendations for Promoting Methane Emission Reduction and Pollution Control in Livestock Industry", China's agricultural methane emissions were approximately 20.493 million tons (ranging from 18.696 to 22.289 million tons), with emissions from livestock manure management and straw burning accounting for 10.2% and 2.2% respectively. After weighted calculation, livestock measures are projected to reduce greenhouse gas emissions by 4.41% in 2025. | K66: industry-ag-main.html#livestock | L66: livestock-measures.html | M66: Calculated from model data; see the relevant variable(s) in the InputData folder for source information.
A67: Agriculture, Land Use, and Forestry | B67: Wetland Restoration | C67: Fraction of Peatland Restoration Achieved | D67: Wetland Restoration | E67: land peatland restoration | F67: 0 | G67: 1 | H67: 0.01 | I67: % of potential achieved | J67: **Description:** This policy increases CO2 sequestration by restoring wetlands and riparian forest buffers. | L67: peatland-restoration.html | M67: https://www.usda.gov/sites/default/files/documents/White_Paper_WEB71816.pdf
A68: Agriculture, Land Use, and Forestry | B68: Shift to Non-Animal Products | C68: Percent Animal Products Shifted to Nonanimal Products | D68: Shift to Non-Animal Products | E68: indst shift to nonanimal products | F68: 0 | G68: 1 | H68: 0.01 | I68: % reduction in animal products | J68: **Description:** This policy causes non-animal products to be substituted for animal products, which might be achieved by changes in consumer preferences or by changes in costs of agricultural products (such as by redirecting subsidies currently paid to farmers who raise animals or feed crops to farmers growing fruits, vegetables, and other plant-based foods for human consumption). Moderate settings of this policy lever do not imply a vegan diet: for instance, a 50% setting could represent each individual consuming half as many animal products, rather than half of the population consuming no animal products. // **Guidance for setting values:** Meat consmption value is based on the recommended value from the Dietary Guidelines for Chinese Residents | L68: shift-to-non-animal-products.html | M68: https://en.wikipedia.org/wiki/List_of_countries_by_meat_consumption_per_capita (article revision 00:12, 22 Feb 2019)
A69: District Heat and Hydrogen | B69: Use CHP for District Heat | C69: Fraction of Non CHP Heat Production Converted to CHP | D69: District Heat CHP | E69: heat convert heat to CHP | F69: 0 | G69: 1 | H69: 0.01 | I69: % non-CHP heat converted | J69: **Description:** This policy causes a percentage of the district heat that would be generated by dedicated heat plants to instead be generated via CHP plants. In this model, this causes them to consume no additional fuel, since it is assumed CHP plants would be run anyway in order to produce electricity. | K69: district-heating.html#chp | L69: convert-non-chp-heat-production.html | M69: Calculated from model data; see the relevant variable(s) in the InputData folder for source information.
A70: District Heat and Hydrogen | B70: Produce District Heat with Hydrogen | C70: Fraction of District Heat Fuel Use Shifted to Other Fuels | D70: District Heat Fuel Switching | E70: heat fuel type shifting | F70: 0 | G70: 1 | H70: 0.01 | I70: % of fuel use | J70: **Description:** This policy causes a percentage of the district heat to be generated by burning hydrogen instead of the fuels used in the BAU case. // **Guidance for setting values:** In China in 2020, around 90% of district heat is from coal, 6% from natural gas, and 4% from biomass. Hydrogen technologies are still emerging, and it is not yet clear if it will be more economical to electrify end uses of heat (ceasing to use district heat), or if decarbonizing district heat facilities will be an economical pathway. | K70: district-heating.html#convert-coal | L70: district-heat-fuel-switching.html | M70: Calculated from model data; see the relevant variable(s) in the InputData folder for source information.
A71: District Heat and Hydrogen | B71: Shift Hydrogen Production to Electrolysis | C71: Fraction of Hydrogen Production Pathways Shifted | D71: Hydrogen Electrolysis | E71: hydgn shift production pathways | F71: 0 | G71: 1 | H71: 0.01 | I71: % of hydrogen production | J71: **Description:** This policy causes a percentage of merchant hydrogen (i.e. hydrogen produced for sale, not hydrogen produced and consumed on-site within a facility) to be produced via electrolysis rather than via other production pathways. // **Guidance for setting values:** In China in 2020, 63.5% of hydrogen production is through coal gasification, 13.8% from natural gas reforming, 21.2%% from biomass, and 1.5% from electrolysis. These shares are not projected to change in the BAU case. | L71: switch-hydrogen-production-pathway.html
A72: Cross-Sector | B72: Carbon Price | C72: Additional Carbon Tax Rate | D72: Carbon Price | E72: cross carbon tax | F72: 0 | G72: 300 | H72: 5 | I72: =UnitControlCenter!$B$47 -> 2020 RMB / metric ton CO2e | J72: **Description:** This policy applies a price on fuels used in the selected sector(s) based on their greenhouse gas emissions. It also increases the base cost of capital equipment (e.g., vehicles, power plants, building components) according to their embedded carbon content. When applied to the Industry Sector, the tax **is** levied on greenhouse gas emissions from non-energy industrial and agricultural processes by default, but these emissions sources can be exempted from the tax by enabling the policy lever "Exempt Process Emissions from C Tax." // **Guidance for setting values:**Currently, China's carbon pricing is based on its development of the national carbon market, which currently only includes the power sector, with a carbon price of around 70 yuan per ton. Policy settings need to consider industry coverage and carbon prices in the future carbon market. | K72: fuels.html#carbon-tax | L72: carbon-tax.html | M72: U.S. EPA, 2015, "The Social Cost of Carbon", https://www.epa.gov/climatechange/social-cost-carbon, Row "2050". (For source for adjustment to 2018 dollars, see cpi.xlsx in InputData.) | N72: U.S. EPA, 2016, "Social Cost of CO2, 2015-2020," https://www.epa.gov/climatechange/social-cost-carbon
A73: Cross-Sector | B73: End Existing Subsidies | C73: Percent Reduction in BAU Subsidies | D73: End Existing Subsidies | E73: cross reduce BAU subsidies | F73: 0 | G73: 1 | H73: 0.01 | I73: % reduction in BAU subsidies | J73: **Description:** This policy reduces the subsidies paid for the production of the selected energy source(s) in the BAU case. | K73: fuels.html#end-subsidies | L73: end-existing-subsidies.html | M73: Calculated from model data; see the relevant variable(s) in the InputData folder for source information.
A74: Cross-Sector | B74: Exempt Non-CO2 Emissions from C Tax | C74: Toggle Whether Carbon Tax Affects Non CO2 Emissions | E74: cross toggle whether carbon tax affects non CO2 emissions | F74: 0 | G74: 1 | H74: 1 | I74: on/off | J74: **Description:** By default, the carbon tax applies to CO2 and non-CO2 emissions. This policy exempts non-CO2 emissions, meaning the carbon tax will only apply to CO2 emissions. | K74: fuels.html#carbon-tax | L74: carbon-tax.html
A75: Cross-Sector | B75: Exempt Process Emissions from C Tax | C75: BEPEfCT Boolean Exempt Process Emissions from Carbon Tax | E75: cross toggle whether carbon tax affects process emissions | F75: 0 | G75: 1 | H75: 1 | I75: on/off | J75: **Description:** This policy prevents the carbon tax from being levied on process emissions (non-energy greenhouse gas emissions from industrial and agricultural operations). | K75: fuels.html#carbon-tax | L75: carbon-tax.html
A76: Cross-Sector | B76: Toggle Carbon Tax Border Adjustment | C76: BDCTBA Boolean Disable Carbon Tax Border Adjustment | F76: 0 | G76: 1 | H76: 1 | I76: on/off | J76: **Description:** By default, carbon taxes apply to only domestically produced goods. If set to zero, this policy enables carbon tax border adjustments, meaning the carbon tax will apply to both domestically produced and imported goods. | K76: fuels.html#carbon-tax | L76: carbon-tax.html
A77: Cross-Sector | B77: Fixed Energy Prices | C77: Toggle Whether Policies Affect Energy Prices | D77: Fixed Energy Prices | E77: cross toggle whether policies affect energy prices | F77: 0 | G77: 1 | H77: 1 | I77: on/off | J77: **Description:** By default, policies affect energy prices. Turning on this policy prevents policy from affecting energy prices.
A78: Cross-Sector | B78: Fuel Price Deregulation | C78: Fuel Price Deregulation | D78: Fuel Price Deregulation | E78: cross fuel price deregulation | F78: 0 | G78: 1 | H78: 0.01 | I78: % of price deregulated | J78: **Description:** This policy causes the price of the selected fuel(s) for domestic buyers to approach international market prices. // **Guidance for setting values:** A value of 100% causes domestic fuel prices to equal international market prices, increasing the domestic price by roughly X% in 2050. | K78: fuels.html#fuel-price-deregulation
A79: Cross-Sector | B79: Fuel Taxes or Subsidies | C79: Additional Fuel Tax or Subsidy Rate by Fuel | D79: Fuel Taxes or Subsidies | E79: cross fuel tax | F79: -0.5 | G79: 0.5 | H79: 0.01 | I79: % of BAU price | J79: **Description:** This policy changes the tax rate for the selected fuel type(s). It is expressed as a percentage of the BAU Scenario price, which includes sales and excise taxes. To increase the tax rate, set a positive value. To reduce the BAU tax rate (or to apply a subsidy), set a negative value. // **Guidance for setting values:** In 2012, the national average sales tax rate was 6.8% and the national average tax rate on gasoline was 14%. | K79: fuels.html#fuel-taxes | L79: fuel-taxes.html | M79: AVG SALES TAX: The Sales Tax Clearinghouse, FAQ, https://thestc.com/FAQ.stm, Question "What is the average sales tax nationally?" AVG GASOLINE TAX: Energy Information Administration, 2014, Annual Energy Outlook 2014, http://www.eia.gov/forecasts/aeo/supplement/suptab_130.xlsx, Supplement Table 130.
A80: Research and Development | B80: Capital Cost Reduction | C80: RnD Building Capital Cost Perc Reduction | D80: R&D Capital Cost Reductions | E80: RnD building capital cost reduction | F80: 0 | G80: 0.4 | H80: 0.01 | I80: % reduction in cost | J80: **Description:** This policy causes the capital cost of the selected type(s) of equipment to decline by the set percentage over the course of the model run. The R&D progress caused by this policy is additional to any R&D necessary to comply with other policies, such as tighter fuel economy standards. No costs associated with conducting this additional R&D (such as investments in laboratories or engineers' salaries) are included in the model. // **Guidance for setting values:** This policy should generally be set to zero unless you are exploring a scenario with unusual and unexpected technological advancement. If setting a non-zero value, more mature technologies, such as coal, should have lower values than younger technologies, such as solar. A setting of 30% implies an average of roughly 1% annual improvement, which is very substantial. | K80: architectural-design.html#rnd | L80: research-and-development.html
A81: =A$80 -> Research and Development | B81: =B$80 -> Capital Cost Reduction | C81: RnD CCS Capital Cost Perc Reduction | D81: =D$80 -> R&D Capital Cost Reductions | E81: RnD CCS capital cost reduction | F81: =F$80 -> 0 | G81: =G$80 -> 0.4 | H81: =H$80 -> 0.01 | I81: =I$80 -> % reduction in cost | J81: **Description:** This policy causes the capital cost of the selected type(s) of equipment to decline by the set percentage over the course of the model run. The R&D progress caused by this policy is additional to any R&D necessary to comply with other policies, such as tighter fuel economy standards. No costs associated with conducting this additional R&D (such as investments in laboratories or engineers' salaries) are included in the model. // **Guidance for setting values:** This policy should generally be set to zero unless you are exploring a scenario with unusual and unexpected technological advancement. If setting a non-zero value, more mature technologies, such as coal, should have lower values than younger technologies, such as solar. A setting of 30% implies an average of roughly 1% annual improvement, which is very substantial. | K81: =K$80 -> architectural-design.html#rnd | L81: =L$80 -> research-and-development.html
A82: =A$80 -> Research and Development | B82: =B$80 -> Capital Cost Reduction | C82: RnD Electricity Capital Cost Perc Reduction | D82: =D$80 -> R&D Capital Cost Reductions | E82: RnD electricity capital cost reduction | F82: =F$80 -> 0 | G82: =G$80 -> 0.4 | H82: =H$80 -> 0.01 | I82: =I$80 -> % reduction in cost | J82: **Description:** This policy causes the capital cost of the selected type(s) of equipment to decline by the set percentage over the course of the model run. The R&D progress caused by this policy is additional to any R&D necessary to comply with other policies, such as tighter fuel economy standards. No costs associated with conducting this additional R&D (such as investments in laboratories or engineers' salaries) are included in the model. // **Guidance for setting values:** This policy should generally be set to zero unless you are exploring a scenario with unusual and unexpected technological advancement. If setting a non-zero value, more mature technologies, such as coal, should have lower values than younger technologies, such as solar. A setting of 30% implies an average of roughly 1% annual improvement, which is very substantial. | K82: =K$80 -> architectural-design.html#rnd | L82: =L$80 -> research-and-development.html
A83: =A$80 -> Research and Development | B83: =B$80 -> Capital Cost Reduction | C83: RnD Industry Capital Cost Perc Reduction | D83: =D$80 -> R&D Capital Cost Reductions | E83: RnD industry capital cost reduction | F83: =F$80 -> 0 | G83: =G$80 -> 0.4 | H83: =H$80 -> 0.01 | I83: =I$80 -> % reduction in cost | J83: **Description:** This policy causes the capital cost of the selected type(s) of equipment to decline by the set percentage over the course of the model run. The R&D progress caused by this policy is additional to any R&D necessary to comply with other policies, such as tighter fuel economy standards. No costs associated with conducting this additional R&D (such as investments in laboratories or engineers' salaries) are included in the model. // **Guidance for setting values:** This policy should generally be set to zero unless you are exploring a scenario with unusual and unexpected technological advancement. If setting a non-zero value, more mature technologies, such as coal, should have lower values than younger technologies, such as solar. A setting of 30% implies an average of roughly 1% annual improvement, which is very substantial. | K83: =K$80 -> architectural-design.html#rnd | L83: =L$80 -> research-and-development.html
A84: =A$80 -> Research and Development | B84: =B$80 -> Capital Cost Reduction | C84: RnD Transportation Capital Cost Perc Reduction | D84: =D$80 -> R&D Capital Cost Reductions | E84: RnD transportation capital cost reduction | F84: =F$80 -> 0 | G84: =G$80 -> 0.4 | H84: =H$80 -> 0.01 | I84: =I$80 -> % reduction in cost | J84: **Description:** This policy causes the capital cost of the selected type(s) of equipment to decline by the set percentage over the course of the model run. The R&D progress caused by this policy is additional to any R&D necessary to comply with other policies, such as tighter fuel economy standards. No costs associated with conducting this additional R&D (such as investments in laboratories or engineers' salaries) are included in the model. // **Guidance for setting values:** This policy should generally be set to zero unless you are exploring a scenario with unusual and unexpected technological advancement. If setting a non-zero value, more mature technologies, such as coal, should have lower values than younger technologies, such as solar. A setting of 30% implies an average of roughly 1% annual improvement, which is very substantial. | K84: =K$80 -> architectural-design.html#rnd | L84: =L$80 -> research-and-development.html
A85: Research and Development | B85: Direct Air Capture | C85: Fraction of Direct Air Capture Potential Achieved | D85: Direct Air Capture | E85: geoeng direct air capture | F85: 0 | G85: 1 | H85: 0.01 | I85: % of potential achieved | J85: **Description:** This policy causes direct air capture (DAC) technology to be used to remove carbon dioxide from the atmosphere. The modeled technology is based on hydroxide sorbents, as this is the most mature DAC technology. Alternatives (such as amine-based technologies) are unlikely to have a perceptible impact by 2050, the last year of the EPS model run. Note that all DAC technologies, even hydroxide sorbents, have their greatest potential effects after 2050, which cannot be seen in a model run that ends in 2050. (DAC refers only to mechanical methods of carbon dioxide removal, not afforestation and other land use measures. For those measures, see the policy levers in the "Agriculture, Land Use, and Forestry" category.) // **Guidance for setting values:** A 100% setting implies large DAC research and development investments starting today, and aggressive deployment in line with a global 1.5-degree-compatible trajectory from a 2019 Nature paper from Realmonte et al. That paper's global deployment rate has been scaled for the U.S. by the U.S.'s share of world GDP in 2017 (about 24%). | K85: direct-air-capture.html#dac | L85: direct-air-capture.html | M85: Realmonte et al., 2019, An inter-model assessment of the role of direct air capture in deep mitigation pathways, https://www.nature.com/articles/s41467-019-10842-5, Table 2, https://static-content.springer.com/esm/art%3A10.1038%2Fs41467-019-10842-5/MediaObjects/41467_2019_10842_MOESM1_ESM.pdf, Supplementary materials, Fig 3
A86: Research and Development | B86: Fuel Use Reduction | C86: RnD Building Fuel Use Perc Reduction | D86: R&D Fuel Use Reductions | E86: RnD building fuel use reduction | F86: 0 | G86: 0.4 | H86: 0.01 | I86: % reduction in fuel use | J86: **Description:** This policy causes the fuel use of the selected type(s) of equipment to decline by the set percentage over the course of the model run. The R&D progress caused by this policy is additional to any R&D necessary to comply with other policies, such as tighter fuel economy standards. No costs associated with conducting this additional R&D (such as investments in laboratories or engineers' salaries) are included in the model. // **Guidance for setting values:** This policy should generally be set to zero unless you are exploring a scenario with unusual and unexpected technological advancement. If setting a non-zero value, more mature technologies, such as coal, should have lower values than younger technologies, such as solar. A setting of 30% implies an average of roughly 1% annual improvement, which is very substantial. | K86: architectural-design.html#rnd | L86: research-and-development.html
A87: =A$86 -> Research and Development | B87: =B$86 -> Fuel Use Reduction | C87: RnD CCS Fuel Use Perc Reduction | D87: =D$86 -> R&D Fuel Use Reductions | E87: RnD CCS fuel use reduction | F87: =F$86 -> 0 | G87: =G$86 -> 0.4 | H87: =H$86 -> 0.01 | I87: =I$86 -> % reduction in fuel use | J87: **Description:** This policy causes the fuel use of the selected type(s) of equipment to decline by the set percentage over the course of the model run. The R&D progress caused by this policy is additional to any R&D necessary to comply with other policies, such as tighter fuel economy standards. No costs associated with conducting this additional R&D (such as investments in laboratories or engineers' salaries) are included in the model. // **Guidance for setting values:** This policy should generally be set to zero unless you are exploring a scenario with unusual and unexpected technological advancement. If setting a non-zero value, more mature technologies, such as coal, should have lower values than younger technologies, such as solar. A setting of 30% implies an average of roughly 1% annual improvement, which is very substantial. | K87: =K$86 -> architectural-design.html#rnd | L87: =L$86 -> research-and-development.html
A88: =A$86 -> Research and Development | B88: =B$86 -> Fuel Use Reduction | C88: RnD Electricity Fuel Use Perc Reduction | D88: =D$86 -> R&D Fuel Use Reductions | E88: RnD electricity fuel use reduction | F88: =F$86 -> 0 | G88: =G$86 -> 0.4 | H88: =H$86 -> 0.01 | I88: =I$86 -> % reduction in fuel use | J88: **Description:** This policy causes the fuel use of the selected type(s) of equipment to decline by the set percentage over the course of the model run. The R&D progress caused by this policy is additional to any R&D necessary to comply with other policies, such as tighter fuel economy standards. No costs associated with conducting this additional R&D (such as investments in laboratories or engineers' salaries) are included in the model. // **Guidance for setting values:** This policy should generally be set to zero unless you are exploring a scenario with unusual and unexpected technological advancement. If setting a non-zero value, more mature technologies, such as coal, should have lower values than younger technologies, such as solar. A setting of 30% implies an average of roughly 1% annual improvement, which is very substantial. | K88: =K$86 -> architectural-design.html#rnd | L88: =L$86 -> research-and-development.html
A89: =A$86 -> Research and Development | B89: =B$86 -> Fuel Use Reduction | C89: RnD Industry Fuel Use Perc Reduction | D89: =D$86 -> R&D Fuel Use Reductions | E89: RnD industry fuel use reduction | F89: =F$86 -> 0 | G89: =G$86 -> 0.4 | H89: =H$86 -> 0.01 | I89: =I$86 -> % reduction in fuel use | J89: **Description:** This policy causes the fuel use of the selected type(s) of equipment to decline by the set percentage over the course of the model run. The R&D progress caused by this policy is additional to any R&D necessary to comply with other policies, such as tighter fuel economy standards. No costs associated with conducting this additional R&D (such as investments in laboratories or engineers' salaries) are included in the model. // **Guidance for setting values:** This policy should generally be set to zero unless you are exploring a scenario with unusual and unexpected technological advancement. If setting a non-zero value, more mature technologies, such as coal, should have lower values than younger technologies, such as solar. A setting of 30% implies an average of roughly 1% annual improvement, which is very substantial. | K89: =K$86 -> architectural-design.html#rnd | L89: =L$86 -> research-and-development.html
A90: =A$86 -> Research and Development | B90: =B$86 -> Fuel Use Reduction | C90: RnD Transportation Fuel Use Perc Reduction | D90: =D$86 -> R&D Fuel Use Reductions | E90: RnD transportation fuel use reduction | F90: =F$86 -> 0 | G90: =G$86 -> 0.4 | H90: =H$86 -> 0.01 | I90: =I$86 -> % reduction in fuel use | J90: **Description:** This policy causes the fuel use of the selected type(s) of equipment to decline by the set percentage over the course of the model run. The R&D progress caused by this policy is additional to any R&D necessary to comply with other policies, such as tighter fuel economy standards. No costs associated with conducting this additional R&D (such as investments in laboratories or engineers' salaries) are included in the model. // **Guidance for setting values:** This policy should generally be set to zero unless you are exploring a scenario with unusual and unexpected technological advancement. If setting a non-zero value, more mature technologies, such as coal, should have lower values than younger technologies, such as solar. A setting of 30% implies an average of roughly 1% annual improvement, which is very substantial. | K90: =K$86 -> architectural-design.html#rnd | L90: =L$86 -> research-and-development.html
A91: Control Settings | B91: COVID-19 Recession | C91: EGGRA Boolean Use Exogenous GDP Growth Rate Adjustment | E91: settings exogenous GDP adjustment | F91: 0 | G91: 1 | H91: 1 | I91: on/off | J91: **Description:** This control setting enables or disables the GDP impact of the recession caused by SARS-CoV-2 (COVID-19). This adjusts energy demand to account for the fact that Chinese energy demand forecasts (used as input data in the EPS) have generally not yet been updated to account for pandemic impacts and associated lockdowns, shipping delays, etc.
A92: Government Revenue Accounting | B92: Carbon Tax Revenue | C92: GRA for Carbon Tax Revenue | E92: GRA carbon tax revenue | F92: 0 | G92: 10 | H92: 1 | I92: weight | J92: **Description:** This is one of several control settings that help determine how government accounts for policy-driven changes in its cash flow (such as increased or decreased tax revenues or subsidy payments). **Regular Spending** means government will increase or decrease its spending on its normal budget (e.g. activities such as defense, education, and administrative expenses) to spend increased revenue or to make up for a reduction in revenue. **Budget Deficit** means government will grow or shrink the national debt (with associated implications for interest payments) to spend increased revenue or to make up for a reduction in revenue. **Household Taxes** means government will increase or decrease taxes on households (or give households a "climate dividend") to spend increased revenue or to make up for a reduction in revenue. **Payroll Taxes** means government will increase or decrease payroll taxes to spend increased revenue or to make up for a reduction in revenue. **Corporate Taxes** means government will increase or decrease corporate income taxes to spend increased revenue or to make up for a reduction in revenue. // **Guidance for setting values:** This value is set as a weight (1 to 10) to indicate its relative importance among the modeled government revenue accounting modes. The share of the change in government cash flow using this mode is this mode's weight divided by the total of the weights assigned to all modes (or an equal share, if every mode is assigned zero weight). | K92: io-model.html
A93: Government Revenue Accounting | B93: Fuel Tax Revenue | C93: GRA for Fuel Tax Revenue | E93: GRA fuel tax revenue | F93: 0 | G93: 10 | H93: 1 | I93: weight | J93: **Description:** This is one of several control settings that help determine how government accounts for policy-driven changes in its cash flow (such as increased or decreased tax revenues or subsidy payments). **Regular Spending** means government will increase or decrease its spending on its normal budget (e.g. activities such as defense, education, and administrative expenses) to spend increased revenue or to make up for a reduction in revenue. **Budget Deficit** means government will grow or shrink the national debt (with associated implications for interest payments) to spend increased revenue or to make up for a reduction in revenue. **Household Taxes** means government will increase or decrease taxes on households (or give households a "climate dividend") to spend increased revenue or to make up for a reduction in revenue. **Payroll Taxes** means government will increase or decrease payroll taxes to spend increased revenue or to make up for a reduction in revenue. **Corporate Taxes** means government will increase or decrease corporate income taxes to spend increased revenue or to make up for a reduction in revenue. // **Guidance for setting values:** This value is set as a weight (1 to 10) to indicate its relative importance among the modeled government revenue accounting modes. The share of the change in government cash flow using this mode is this mode's weight divided by the total of the weights assigned to all modes (or an equal share, if every mode is assigned zero weight). | K93: =K$92 -> io-model.html
A94: Government Revenue Accounting | B94: EV Subsidy | C94: GRA for EV Subsidy | E94: GRA EV subsidy | F94: 0 | G94: 10 | H94: 1 | I94: weight | J94: **Description:** This is one of several control settings that help determine how government accounts for policy-driven changes in its cash flow (such as increased or decreased tax revenues or subsidy payments). **Regular Spending** means government will increase or decrease its spending on its normal budget (e.g. activities such as defense, education, and administrative expenses) to spend increased revenue or to make up for a reduction in revenue. **Budget Deficit** means government will grow or shrink the national debt (with associated implications for interest payments) to spend increased revenue or to make up for a reduction in revenue. **Household Taxes** means government will increase or decrease taxes on households (or give households a "climate dividend") to spend increased revenue or to make up for a reduction in revenue. **Payroll Taxes** means government will increase or decrease payroll taxes to spend increased revenue or to make up for a reduction in revenue. **Corporate Taxes** means government will increase or decrease corporate income taxes to spend increased revenue or to make up for a reduction in revenue. // **Guidance for setting values:** This value is set as a weight (1 to 10) to indicate its relative importance among the modeled government revenue accounting modes. The share of the change in government cash flow using this mode is this mode's weight divided by the total of the weights assigned to all modes (or an equal share, if every mode is assigned zero weight). | K94: =K$92 -> io-model.html
A95: Government Revenue Accounting | B95: Electricity Generation Subsidy | C95: GRA for Electricity Generation Subsidies | E95: GRA elec gen subsidy | F95: 0 | G95: 10 | H95: 1 | I95: weight | J95: **Description:** This is one of several control settings that help determine how government accounts for policy-driven changes in its cash flow (such as increased or decreased tax revenues or subsidy payments). **Regular Spending** means government will increase or decrease its spending on its normal budget (e.g. activities such as defense, education, and administrative expenses) to spend increased revenue or to make up for a reduction in revenue. **Budget Deficit** means government will grow or shrink the national debt (with associated implications for interest payments) to spend increased revenue or to make up for a reduction in revenue. **Household Taxes** means government will increase or decrease taxes on households (or give households a "climate dividend") to spend increased revenue or to make up for a reduction in revenue. **Payroll Taxes** means government will increase or decrease payroll taxes to spend increased revenue or to make up for a reduction in revenue. **Corporate Taxes** means government will increase or decrease corporate income taxes to spend increased revenue or to make up for a reduction in revenue. // **Guidance for setting values:** This value is set as a weight (1 to 10) to indicate its relative importance among the modeled government revenue accounting modes. The share of the change in government cash flow using this mode is this mode's weight divided by the total of the weights assigned to all modes (or an equal share, if every mode is assigned zero weight). | K95: =K$92 -> io-model.html
A96: Government Revenue Accounting | B96: Electricity Capacity Construction Subsidy | C96: GRA for Electricity Capacity Construction Subsidies | E96: GRA elec cap const subsidy | F96: 0 | G96: 10 | H96: 1 | I96: weight | J96: **Description:** This is one of several control settings that help determine how government accounts for policy-driven changes in its cash flow (such as increased or decreased tax revenues or subsidy payments). **Regular Spending** means government will increase or decrease its spending on its normal budget (e.g. activities such as defense, education, and administrative expenses) to spend increased revenue or to make up for a reduction in revenue. **Budget Deficit** means government will grow or shrink the national debt (with associated implications for interest payments) to spend increased revenue or to make up for a reduction in revenue. **Household Taxes** means government will increase or decrease taxes on households (or give households a "climate dividend") to spend increased revenue or to make up for a reduction in revenue. **Payroll Taxes** means government will increase or decrease payroll taxes to spend increased revenue or to make up for a reduction in revenue. **Corporate Taxes** means government will increase or decrease corporate income taxes to spend increased revenue or to make up for a reduction in revenue. // **Guidance for setting values:** This value is set as a weight (1 to 10) to indicate its relative importance among the modeled government revenue accounting modes. The share of the change in government cash flow using this mode is this mode's weight divided by the total of the weights assigned to all modes (or an equal share, if every mode is assigned zero weight). | K96: =K$92 -> io-model.html
A97: Government Revenue Accounting | B97: Distributed Solar Subsidy | C97: GRA for Distributed Solar Subsidy | E97: GRA dist solar subsidy | F97: 0 | G97: 10 | H97: 1 | I97: weight | J97: **Description:** This policy causes the government to reimburse building owners for a percentage of the cost of new distributed solar PV capacity that is installed on or around buildings. // **Guidance for setting values:** According to "Notice on matters related to the new energy feed-in tariff policy in 2021", from 2021 onwards for the new record of centralized photovoltaic power plants, commercial and industrial distributed photovoltaic projects and newly approved onshore wind power projects, the central government no longer subsidize. | K97: =K$92 -> io-model.html
A98: Government Revenue Accounting | B98: Fuel Subsidy | C98: GRA for Fuel Subsidies | E98: GRA fuel subsidy | F98: 0 | G98: 10 | H98: 1 | I98: weight | J98: **Description:** This is one of several control settings that help determine how government accounts for policy-driven changes in its cash flow (such as increased or decreased tax revenues or subsidy payments). **Regular Spending** means government will increase or decrease its spending on its normal budget (e.g. activities such as defense, education, and administrative expenses) to spend increased revenue or to make up for a reduction in revenue. **Budget Deficit** means government will grow or shrink the national debt (with associated implications for interest payments) to spend increased revenue or to make up for a reduction in revenue. **Household Taxes** means government will increase or decrease taxes on households (or give households a "climate dividend") to spend increased revenue or to make up for a reduction in revenue. **Payroll Taxes** means government will increase or decrease payroll taxes to spend increased revenue or to make up for a reduction in revenue. **Corporate Taxes** means government will increase or decrease corporate income taxes to spend increased revenue or to make up for a reduction in revenue. // **Guidance for setting values:** This value is set as a weight (1 to 10) to indicate its relative importance among the modeled government revenue accounting modes. The share of the change in government cash flow using this mode is this mode's weight divided by the total of the weights assigned to all modes (or an equal share, if every mode is assigned zero weight). | K98: =K$92 -> io-model.html
A99: Government Revenue Accounting | B99: National Debt Interest | C99: GRA for National Debt Interest | E99: GRA national debt interest | F99: 0 | G99: 10 | H99: 1 | I99: weight | J99: **Description:** This is one of several control settings that help determine how government accounts for policy-driven changes in its cash flow (such as increased or decreased tax revenues or subsidy payments). **Regular Spending** means government will increase or decrease its spending on its normal budget (e.g. activities such as defense, education, and administrative expenses) to spend increased revenue or to make up for a reduction in revenue. **Budget Deficit** means government will grow or shrink the national debt (with associated implications for interest payments) to spend increased revenue or to make up for a reduction in revenue. **Household Taxes** means government will increase or decrease taxes on households (or give households a "climate dividend") to spend increased revenue or to make up for a reduction in revenue. **Payroll Taxes** means government will increase or decrease payroll taxes to spend increased revenue or to make up for a reduction in revenue. **Corporate Taxes** means government will increase or decrease corporate income taxes to spend increased revenue or to make up for a reduction in revenue. // **Guidance for setting values:** This value is set as a weight (1 to 10) to indicate its relative importance among the modeled government revenue accounting modes. The share of the change in government cash flow using this mode is this mode's weight divided by the total of the weights assigned to all modes (or an equal share, if every mode is assigned zero weight). | K99: =K$92 -> io-model.html
A100: Government Revenue Accounting | B100: Remaining Government Cash Flows | C100: GRA for Remaining Government Cash Flow Changes | E100: GRA remaining cash flow changes | F100: 0 | G100: 10 | H100: 1 | I100: weight | J100: **Description:** This is one of several control settings that help determine how government accounts for policy-driven changes in its cash flow (such as increased or decreased tax revenues or subsidy payments). **Regular Spending** means government will increase or decrease its spending on its normal budget (e.g. activities such as defense, education, and administrative expenses) to spend increased revenue or to make up for a reduction in revenue. **Budget Deficit** means government will grow or shrink the national debt (with associated implications for interest payments) to spend increased revenue or to make up for a reduction in revenue. **Household Taxes** means government will increase or decrease taxes on households (or give households a "climate dividend") to spend increased revenue or to make up for a reduction in revenue. **Payroll Taxes** means government will increase or decrease payroll taxes to spend increased revenue or to make up for a reduction in revenue. **Corporate Taxes** means government will increase or decrease corporate income taxes to spend increased revenue or to make up for a reduction in revenue. // **Guidance for setting values:** This value is set as a weight (1 to 10) to indicate its relative importance among the modeled government revenue accounting modes. The share of the change in government cash flow using this mode is this mode's weight divided by the total of the weights assigned to all modes (or an equal share, if every mode is assigned zero weight). | K100: =K$92 -> io-model.html
...

Sheet PolicyLevers
A1: Sector | B1: Short Name | C1: Vensim Variable Name | D1: Subscript 1 Value | E1: Subscript 2 Value | F1: Subscript 1 Display Name | G1: Subscript 2 Display Name | H1: Policy ID Number | I1: Include in Web App | J1: Policy Group | K1: Policy Schedule Subscript | L1: Min Slider Value | M1: Max Slider Value | N1: Slider Step Size | O1: Units | P1: Text for Pop-Over Panel Description | Q1: URL for "How the model handles this policy" links | R1: URL for "How to design this policy well" links
A2: =IF(ISBLANK(INDEX('Policy Characteristics'!A:A,MATCH($C2,'Policy Characteristics'!$C:$C,0))),"",INDEX('Policy Characteristics'!A:A,MATCH($C2,'Policy Characteristics'!$C:$C,0))) -> Transportation | B2: =IF(ISBLANK(INDEX('Policy Characteristics'!B:B,MATCH($C2,'Policy Characteristics'!$C:$C,0))),"",INDEX('Policy Characteristics'!B:B,MATCH($C2,'Policy Characteristics'!$C:$C,0))) -> Conventional Pollutant Standards | C2: Percentage Reduction of Separately Regulated Pollutants | D2: LDVs | E2: VOC | F2: Passenger cars, SUVs, Light and Medium Commercial Trucks | G2: VOCs | H2: 300 | I2: Yes | J2: =IF(ISBLANK(INDEX('Policy Characteristics'!D:D,MATCH($C2,'Policy Characteristics'!$C:$C,0))),"",INDEX('Policy Characteristics'!D:D,MATCH($C2,'Policy Characteristics'!$C:$C,0))) -> Conventional Pollutant Standard | K2: =IF(ISBLANK(INDEX('Policy Characteristics'!E:E,MATCH($C2,'Policy Characteristics'!$C:$C,0))),"",INDEX('Policy Characteristics'!E:E,MATCH($C2,'Policy Characteristics'!$C:$C,0))) -> trans reduce regulated pollutants | L2: =IF(ISBLANK(INDEX('Policy Characteristics'!F:F,MATCH($C2,'Policy Characteristics'!$C:$C,0))),"",INDEX('Policy Characteristics'!F:F,MATCH($C2,'Policy Characteristics'!$C:$C,0))) -> 0 | M2: =IF(ISBLANK(INDEX('Policy Characteristics'!G:G,MATCH($C2,'Policy Characteristics'!$C:$C,0))),"",INDEX('Policy Characteristics'!G:G,MATCH($C2,'Policy Characteristics'!$C:$C,0))) -> 1 | N2: =IF(ISBLANK(INDEX('Policy Characteristics'!H:H,MATCH($C2,'Policy Characteristics'!$C:$C,0))),"",INDEX('Policy Characteristics'!H:H,MATCH($C2,'Policy Characteristics'!$C:$C,0))) -> 0.02 | O2: =IF(ISBLANK(INDEX('Policy Characteristics'!I:I,MATCH($C2,'Policy Characteristics'!$C:$C,0))),"",INDEX('Policy Characteristics'!I:I,MATCH($C2,'Policy Characteristics'!$C:$C,0))) -> % reduction in emissions | P2: =IF(ISBLANK(INDEX('Policy Characteristics'!J:J,MATCH($C2,'Policy Characteristics'!$C:$C,0))),"",INDEX('Policy Characteristics'!J:J,MATCH($C2,'Policy Characteristics'!$C:$C,0))) -> **Description:** This policy represents strengthening standards for the selected pollutant(s) emitted by the selected vehicle type(s). Conventional pollutants' most important, harmful impacts are on human health rather than on climate change. // **Guidance for setting values:** By 2025, the concentration of fine particulate matter (PM2.5) in prefectural-level and above cities will be 10% lower than that in 2020, and the total emissions of volatile organic compounds (VOCs) and nitrogen oxides will be more than 10% lower than that in 2020 respectively. (Reference: Opinions of the CPC and the State Council on Further Combating Pollution and Preventing the Battle against Pollution) | Q2: =IF(ISBLANK(INDEX('Policy Characteristics'!K:K,MATCH($C2,'Policy Characteristics'!$C:$C,0))),"",INDEX('Policy Characteristics'!K:K,MATCH($C2,'Policy Characteristics'!$C:$C,0))) -> transportation-sector-main.html#conv-pol-stds | R2: =IF(ISBLANK(INDEX('Policy Characteristics'!L:L,MATCH($C2,'Policy Characteristics'!$C:$C,0))),"",INDEX('Policy Characteristics'!L:L,MATCH($C2,'Policy Characteristics'!$C:$C,0))) -> conventional-pollutant-standards.html
A3: =IF(ISBLANK(INDEX('Policy Characteristics'!A:A,MATCH($C3,'Policy Characteristics'!$C:$C,0))),"",INDEX('Policy Characteristics'!A:A,MATCH($C3,'Policy Characteristics'!$C:$C,0))) -> Transportation | B3: =IF(ISBLANK(INDEX('Policy Characteristics'!B:B,MATCH($C3,'Policy Characteristics'!$C:$C,0))),"",INDEX('Policy Characteristics'!B:B,MATCH($C3,'Policy Characteristics'!$C:$C,0))) -> Conventional Pollutant Standards | C3: =C$2 -> Percentage Reduction of Separately Regulated Pollutants | D3: LDVs | E3: CO | F3: Passenger cars, SUVs, Light and Medium Commercial Trucks | G3: CO | H3: 301 | I3: Yes | J3: =IF(ISBLANK(INDEX('Policy Characteristics'!D:D,MATCH($C3,'Policy Characteristics'!$C:$C,0))),"",INDEX('Policy Characteristics'!D:D,MATCH($C3,'Policy Characteristics'!$C:$C,0))) -> Conventional Pollutant Standard | K3: =IF(ISBLANK(INDEX('Policy Characteristics'!E:E,MATCH($C3,'Policy Characteristics'!$C:$C,0))),"",INDEX('Policy Characteristics'!E:E,MATCH($C3,'Policy Characteristics'!$C:$C,0))) -> trans reduce regulated pollutants | L3: =IF(ISBLANK(INDEX('Policy Characteristics'!F:F,MATCH($C3,'Policy Characteristics'!$C:$C,0))),"",INDEX('Policy Characteristics'!F:F,MATCH($C3,'Policy Characteristics'!$C:$C,0))) -> 0 | M3: =IF(ISBLANK(INDEX('Policy Characteristics'!G:G,MATCH($C3,'Policy Characteristics'!$C:$C,0))),"",INDEX('Policy Characteristics'!G:G,MATCH($C3,'Policy Characteristics'!$C:$C,0))) -> 1 | N3: =IF(ISBLANK(INDEX('Policy Characteristics'!H:H,MATCH($C3,'Policy Characteristics'!$C:$C,0))),"",INDEX('Policy Characteristics'!H:H,MATCH($C3,'Policy Characteristics'!$C:$C,0))) -> 0.02 | O3: =IF(ISBLANK(INDEX('Policy Characteristics'!I:I,MATCH($C3,'Policy Characteristics'!$C:$C,0))),"",INDEX('Policy Characteristics'!I:I,MATCH($C3,'Policy Characteristics'!$C:$C,0))) -> % reduction in emissions | P3: =IF(ISBLANK(INDEX('Policy Characteristics'!J:J,MATCH($C3,'Policy Characteristics'!$C:$C,0))),"",INDEX('Policy Characteristics'!J:J,MATCH($C3,'Policy Characteristics'!$C:$C,0))) -> **Description:** This policy represents strengthening standards for the selected pollutant(s) emitted by the selected vehicle type(s). Conventional pollutants' most important, harmful impacts are on human health rather than on climate change. // **Guidance for setting values:** By 2025, the concentration of fine particulate matter (PM2.5) in prefectural-level and above cities will be 10% lower than that in 2020, and the total emissions of volatile organic compounds (VOCs) and nitrogen oxides will be more than 10% lower than that in 2020 respectively. (Reference: Opinions of the CPC and the State Council on Further Combating Pollution and Preventing the Battle against Pollution) | Q3: =IF(ISBLANK(INDEX('Policy Characteristics'!K:K,MATCH($C3,'Policy Characteristics'!$C:$C,0))),"",INDEX('Policy Characteristics'!K:K,MATCH($C3,'Policy Characteristics'!$C:$C,0))) -> transportation-sector-main.html#conv-pol-stds | R3: =IF(ISBLANK(INDEX('Policy Characteristics'!L:L,MATCH($C3,'Policy Characteristics'!$C:$C,0))),"",INDEX('Policy Characteristics'!L:L,MATCH($C3,'Policy Characteristics'!$C:$C,0))) -> conventional-pollutant-standards.html
A4: =IF(ISBLANK(INDEX('Policy Characteristics'!A:A,MATCH($C4,'Policy Characteristics'!$C:$C,0))),"",INDEX('Policy Characteristics'!A:A,MATCH($C4,'Policy Characteristics'!$C:$C,0))) -> Transportation | B4: =IF(ISBLANK(INDEX('Policy Characteristics'!B:B,MATCH($C4,'Policy Characteristics'!$C:$C,0))),"",INDEX('Policy Characteristics'!B:B,MATCH($C4,'Policy Characteristics'!$C:$C,0))) -> Conventional Pollutant Standards | C4: =C$2 -> Percentage Reduction of Separately Regulated Pollutants | D4: LDVs | E4: NOx | F4: Passenger cars, SUVs, Light and Medium Commercial Trucks | G4: NOx | H4: 302 | I4: Yes | J4: =IF(ISBLANK(INDEX('Policy Characteristics'!D:D,MATCH($C4,'Policy Characteristics'!$C:$C,0))),"",INDEX('Policy Characteristics'!D:D,MATCH($C4,'Policy Characteristics'!$C:$C,0))) -> Conventional Pollutant Standard | K4: =IF(ISBLANK(INDEX('Policy Characteristics'!E:E,MATCH($C4,'Policy Characteristics'!$C:$C,0))),"",INDEX('Policy Characteristics'!E:E,MATCH($C4,'Policy Characteristics'!$C:$C,0))) -> trans reduce regulated pollutants | L4: =IF(ISBLANK(INDEX('Policy Characteristics'!F:F,MATCH($C4,'Policy Characteristics'!$C:$C,0))),"",INDEX('Policy Characteristics'!F:F,MATCH($C4,'Policy Characteristics'!$C:$C,0))) -> 0 | M4: =IF(ISBLANK(INDEX('Policy Characteristics'!G:G,MATCH($C4,'Policy Characteristics'!$C:$C,0))),"",INDEX('Policy Characteristics'!G:G,MATCH($C4,'Policy Characteristics'!$C:$C,0))) -> 1 | N4: =IF(ISBLANK(INDEX('Policy Characteristics'!H:H,MATCH($C4,'Policy Characteristics'!$C:$C,0))),"",INDEX('Policy Characteristics'!H:H,MATCH($C4,'Policy Characteristics'!$C:$C,0))) -> 0.02 | O4: =IF(ISBLANK(INDEX('Policy Characteristics'!I:I,MATCH($C4,'Policy Characteristics'!$C:$C,0))),"",INDEX('Policy Characteristics'!I:I,MATCH($C4,'Policy Characteristics'!$C:$C,0))) -> % reduction in emissions | P4: =IF(ISBLANK(INDEX('Policy Characteristics'!J:J,MATCH($C4,'Policy Characteristics'!$C:$C,0))),"",INDEX('Policy Characteristics'!J:J,MATCH($C4,'Policy Characteristics'!$C:$C,0))) -> **Description:** This policy represents strengthening standards for the selected pollutant(s) emitted by the selected vehicle type(s). Conventional pollutants' most important, harmful impacts are on human health rather than on climate change. // **Guidance for setting values:** By 2025, the concentration of fine particulate matter (PM2.5) in prefectural-level and above cities will be 10% lower than that in 2020, and the total emissions of volatile organic compounds (VOCs) and nitrogen oxides will be more than 10% lower than that in 2020 respectively. (Reference: Opinions of the CPC and the State Council on Further Combating Pollution and Preventing the Battle against Pollution) | Q4: =IF(ISBLANK(INDEX('Policy Characteristics'!K:K,MATCH($C4,'Policy Characteristics'!$C:$C,0))),"",INDEX('Policy Characteristics'!K:K,MATCH($C4,'Policy Characteristics'!$C:$C,0))) -> transportation-sector-main.html#conv-pol-stds | R4: =IF(ISBLANK(INDEX('Policy Characteristics'!L:L,MATCH($C4,'Policy Characteristics'!$C:$C,0))),"",INDEX('Policy Characteristics'!L:L,MATCH($C4,'Policy Characteristics'!$C:$C,0))) -> conventional-pollutant-standards.html
A5: =IF(ISBLANK(INDEX('Policy Characteristics'!A:A,MATCH($C5,'Policy Characteristics'!$C:$C,0))),"",INDEX('Policy Characteristics'!A:A,MATCH($C5,'Policy Characteristics'!$C:$C,0))) -> Transportation | B5: =IF(ISBLANK(INDEX('Policy Characteristics'!B:B,MATCH($C5,'Policy Characteristics'!$C:$C,0))),"",INDEX('Policy Characteristics'!B:B,MATCH($C5,'Policy Characteristics'!$C:$C,0))) -> Conventional Pollutant Standards | C5: =C$2 -> Percentage Reduction of Separately Regulated Pollutants | D5: LDVs | E5: PM10 | F5: Passenger cars, SUVs, Light and Medium Commercial Trucks | G5: PM10 | H5: 303 | I5: Yes | J5: =IF(ISBLANK(INDEX('Policy Characteristics'!D:D,MATCH($C5,'Policy Characteristics'!$C:$C,0))),"",INDEX('Policy Characteristics'!D:D,MATCH($C5,'Policy Characteristics'!$C:$C,0))) -> Conventional Pollutant Standard | K5: =IF(ISBLANK(INDEX('Policy Characteristics'!E:E,MATCH($C5,'Policy Characteristics'!$C:$C,0))),"",INDEX('Policy Characteristics'!E:E,MATCH($C5,'Policy Characteristics'!$C:$C,0))) -> trans reduce regulated pollutants | L5: =IF(ISBLANK(INDEX('Policy Characteristics'!F:F,MATCH($C5,'Policy Characteristics'!$C:$C,0))),"",INDEX('Policy Characteristics'!F:F,MATCH($C5,'Policy Characteristics'!$C:$C,0))) -> 0 | M5: =IF(ISBLANK(INDEX('Policy Characteristics'!G:G,MATCH($C5,'Policy Characteristics'!$C:$C,0))),"",INDEX('Policy Characteristics'!G:G,MATCH($C5,'Policy Characteristics'!$C:$C,0))) -> 1 | N5: =IF(ISBLANK(INDEX('Policy Characteristics'!H:H,MATCH($C5,'Policy Characteristics'!$C:$C,0))),"",INDEX('Policy Characteristics'!H:H,MATCH($C5,'Policy Characteristics'!$C:$C,0))) -> 0.02 | O5: =IF(ISBLANK(INDEX('Policy Characteristics'!I:I,MATCH($C5,'Policy Characteristics'!$C:$C,0))),"",INDEX('Policy Characteristics'!I:I,MATCH($C5,'Policy Characteristics'!$C:$C,0))) -> % reduction in emissions | P5: =IF(ISBLANK(INDEX('Policy Characteristics'!J:J,MATCH($C5,'Policy Characteristics'!$C:$C,0))),"",INDEX('Policy Characteristics'!J:J,MATCH($C5,'Policy Characteristics'!$C:$C,0))) -> **Description:** This policy represents strengthening standards for the selected pollutant(s) emitted by the selected vehicle type(s). Conventional pollutants' most important, harmful impacts are on human health rather than on climate change. // **Guidance for setting values:** By 2025, the concentration of fine particulate matter (PM2.5) in prefectural-level and above cities will be 10% lower than that in 2020, and the total emissions of volatile organic compounds (VOCs) and nitrogen oxides will be more than 10% lower than that in 2020 respectively. (Reference: Opinions of the CPC and the State Council on Further Combating Pollution and Preventing the Battle against Pollution) | Q5: =IF(ISBLANK(INDEX('Policy Characteristics'!K:K,MATCH($C5,'Policy Characteristics'!$C:$C,0))),"",INDEX('Policy Characteristics'!K:K,MATCH($C5,'Policy Characteristics'!$C:$C,0))) -> transportation-sector-main.html#conv-pol-stds | R5: =IF(ISBLANK(INDEX('Policy Characteristics'!L:L,MATCH($C5,'Policy Characteristics'!$C:$C,0))),"",INDEX('Policy Characteristics'!L:L,MATCH($C5,'Policy Characteristics'!$C:$C,0))) -> conventional-pollutant-standards.html
A6: =IF(ISBLANK(INDEX('Policy Characteristics'!A:A,MATCH($C6,'Policy Characteristics'!$C:$C,0))),"",INDEX('Policy Characteristics'!A:A,MATCH($C6,'Policy Characteristics'!$C:$C,0))) -> Transportation | B6: =IF(ISBLANK(INDEX('Policy Characteristics'!B:B,MATCH($C6,'Policy Characteristics'!$C:$C,0))),"",INDEX('Policy Characteristics'!B:B,MATCH($C6,'Policy Characteristics'!$C:$C,0))) -> Conventional Pollutant Standards | C6: =C$2 -> Percentage Reduction of Separately Regulated Pollutants | D6: LDVs | E6: PM25 | F6: Passenger cars, SUVs, Light and Medium Commercial Trucks | G6: PM2.5 | H6: 304 | I6: Yes | J6: =IF(ISBLANK(INDEX('Policy Characteristics'!D:D,MATCH($C6,'Policy Characteristics'!$C:$C,0))),"",INDEX('Policy Characteristics'!D:D,MATCH($C6,'Policy Characteristics'!$C:$C,0))) -> Conventional Pollutant Standard | K6: =IF(ISBLANK(INDEX('Policy Characteristics'!E:E,MATCH($C6,'Policy Characteristics'!$C:$C,0))),"",INDEX('Policy Characteristics'!E:E,MATCH($C6,'Policy Characteristics'!$C:$C,0))) -> trans reduce regulated pollutants | L6: =IF(ISBLANK(INDEX('Policy Characteristics'!F:F,MATCH($C6,'Policy Characteristics'!$C:$C,0))),"",INDEX('Policy Characteristics'!F:F,MATCH($C6,'Policy Characteristics'!$C:$C,0))) -> 0 | M6: =IF(ISBLANK(INDEX('Policy Characteristics'!G:G,MATCH($C6,'Policy Characteristics'!$C:$C,0))),"",INDEX('Policy Characteristics'!G:G,MATCH($C6,'Policy Characteristics'!$C:$C,0))) -> 1 | N6: =IF(ISBLANK(INDEX('Policy Characteristics'!H:H,MATCH($C6,'Policy Characteristics'!$C:$C,0))),"",INDEX('Policy Characteristics'!H:H,MATCH($C6,'Policy Characteristics'!$C:$C,0))) -> 0.02 | O6: =IF(ISBLANK(INDEX('Policy Characteristics'!I:I,MATCH($C6,'Policy Characteristics'!$C:$C,0))),"",INDEX('Policy Characteristics'!I:I,MATCH($C6,'Policy Characteristics'!$C:$C,0))) -> % reduction in emissions | P6: =IF(ISBLANK(INDEX('Policy Characteristics'!J:J,MATCH($C6,'Policy Characteristics'!$C:$C,0))),"",INDEX('Policy Characteristics'!J:J,MATCH($C6,'Policy Characteristics'!$C:$C,0))) -> **Description:** This policy represents strengthening standards for the selected pollutant(s) emitted by the selected vehicle type(s). Conventional pollutants' most important, harmful impacts are on human health rather than on climate change. // **Guidance for setting values:** By 2025, the concentration of fine particulate matter (PM2.5) in prefectural-level and above cities will be 10% lower than that in 2020, and the total emissions of volatile organic compounds (VOCs) and nitrogen oxides will be more than 10% lower than that in 2020 respectively. (Reference: Opinions of the CPC and the State Council on Further Combating Pollution and Preventing the Battle against Pollution) | Q6: =IF(ISBLANK(INDEX('Policy Characteristics'!K:K,MATCH($C6,'Policy Characteristics'!$C:$C,0))),"",INDEX('Policy Characteristics'!K:K,MATCH($C6,'Policy Characteristics'!$C:$C,0))) -> transportation-sector-main.html#conv-pol-stds | R6: =IF(ISBLANK(INDEX('Policy Characteristics'!L:L,MATCH($C6,'Policy Characteristics'!$C:$C,0))),"",INDEX('Policy Characteristics'!L:L,MATCH($C6,'Policy Characteristics'!$C:$C,0))) -> conventional-pollutant-standards.html
A7: =IF(ISBLANK(INDEX('Policy Characteristics'!A:A,MATCH($C7,'Policy Characteristics'!$C:$C,0))),"",INDEX('Policy Characteristics'!A:A,MATCH($C7,'Policy Characteristics'!$C:$C,0))) -> Transportation | B7: =IF(ISBLANK(INDEX('Policy Characteristics'!B:B,MATCH($C7,'Policy Characteristics'!$C:$C,0))),"",INDEX('Policy Characteristics'!B:B,MATCH($C7,'Policy Characteristics'!$C:$C,0))) -> Conventional Pollutant Standards | C7: =C$2 -> Percentage Reduction of Separately Regulated Pollutants | D7: LDVs | E7: SOx | F7: Passenger cars, SUVs, Light and Medium Commercial Trucks | G7: SOx | H7: 305 | I7: Yes | J7: =IF(ISBLANK(INDEX('Policy Characteristics'!D:D,MATCH($C7,'Policy Characteristics'!$C:$C,0))),"",INDEX('Policy Characteristics'!D:D,MATCH($C7,'Policy Characteristics'!$C:$C,0))) -> Conventional Pollutant Standard | K7: =IF(ISBLANK(INDEX('Policy Characteristics'!E:E,MATCH($C7,'Policy Characteristics'!$C:$C,0))),"",INDEX('Policy Characteristics'!E:E,MATCH($C7,'Policy Characteristics'!$C:$C,0))) -> trans reduce regulated pollutants | L7: =IF(ISBLANK(INDEX('Policy Characteristics'!F:F,MATCH($C7,'Policy Characteristics'!$C:$C,0))),"",INDEX('Policy Characteristics'!F:F,MATCH($C7,'Policy Characteristics'!$C:$C,0))) -> 0 | M7: =IF(ISBLANK(INDEX('Policy Characteristics'!G:G,MATCH($C7,'Policy Characteristics'!$C:$C,0))),"",INDEX('Policy Characteristics'!G:G,MATCH($C7,'Policy Characteristics'!$C:$C,0))) -> 1 | N7: =IF(ISBLANK(INDEX('Policy Characteristics'!H:H,MATCH($C7,'Policy Characteristics'!$C:$C,0))),"",INDEX('Policy Characteristics'!H:H,MATCH($C7,'Policy Characteristics'!$C:$C,0))) -> 0.02 | O7: =IF(ISBLANK(INDEX('Policy Characteristics'!I:I,MATCH($C7,'Policy Characteristics'!$C:$C,0))),"",INDEX('Policy Characteristics'!I:I,MATCH($C7,'Policy Characteristics'!$C:$C,0))) -> % reduction in emissions | P7: =IF(ISBLANK(INDEX('Policy Characteristics'!J:J,MATCH($C7,'Policy Characteristics'!$C:$C,0))),"",INDEX('Policy Characteristics'!J:J,MATCH($C7,'Policy Characteristics'!$C:$C,0))) -> **Description:** This policy represents strengthening standards for the selected pollutant(s) emitted by the selected vehicle type(s). Conventional pollutants' most important, harmful impacts are on human health rather than on climate change. // **Guidance for setting values:** By 2025, the concentration of fine particulate matter (PM2.5) in prefectural-level and above cities will be 10% lower than that in 2020, and the total emissions of volatile organic compounds (VOCs) and nitrogen oxides will be more than 10% lower than that in 2020 respectively. (Reference: Opinions of the CPC and the State Council on Further Combating Pollution and Preventing the Battle against Pollution) | Q7: =IF(ISBLANK(INDEX('Policy Characteristics'!K:K,MATCH($C7,'Policy Characteristics'!$C:$C,0))),"",INDEX('Policy Characteristics'!K:K,MATCH($C7,'Policy Characteristics'!$C:$C,0))) -> transportation-sector-main.html#conv-pol-stds | R7: =IF(ISBLANK(INDEX('Policy Characteristics'!L:L,MATCH($C7,'Policy Characteristics'!$C:$C,0))),"",INDEX('Policy Characteristics'!L:L,MATCH($C7,'Policy Characteristics'!$C:$C,0))) -> conventional-pollutant-standards.html
A8: =IF(ISBLANK(INDEX('Policy Characteristics'!A:A,MATCH($C8,'Policy Characteristics'!$C:$C,0))),"",INDEX('Policy Characteristics'!A:A,MATCH($C8,'Policy Characteristics'!$C:$C,0))) -> Transportation | B8: =IF(ISBLANK(INDEX('Policy Characteristics'!B:B,MATCH($C8,'Policy Characteristics'!$C:$C,0))),"",INDEX('Policy Characteristics'!B:B,MATCH($C8,'Policy Characteristics'!$C:$C,0))) -> Conventional Pollutant Standards | C8: =C$2 -> Percentage Reduction of Separately Regulated Pollutants | D8: LDVs | E8: BC | F8: Passenger cars, SUVs, Light and Medium Commercial Trucks | G8: BC | H8: 306 | I8: Yes | J8: =IF(ISBLANK(INDEX('Policy Characteristics'!D:D,MATCH($C8,'Policy Characteristics'!$C:$C,0))),"",INDEX('Policy Characteristics'!D:D,MATCH($C8,'Policy Characteristics'!$C:$C,0))) -> Conventional Pollutant Standard | K8: =IF(ISBLANK(INDEX('Policy Characteristics'!E:E,MATCH($C8,'Policy Characteristics'!$C:$C,0))),"",INDEX('Policy Characteristics'!E:E,MATCH($C8,'Policy Characteristics'!$C:$C,0))) -> trans reduce regulated pollutants | L8: =IF(ISBLANK(INDEX('Policy Characteristics'!F:F,MATCH($C8,'Policy Characteristics'!$C:$C,0))),"",INDEX('Policy Characteristics'!F:F,MATCH($C8,'Policy Characteristics'!$C:$C,0))) -> 0 | M8: =IF(ISBLANK(INDEX('Policy Characteristics'!G:G,MATCH($C8,'Policy Characteristics'!$C:$C,0))),"",INDEX('Policy Characteristics'!G:G,MATCH($C8,'Policy Characteristics'!$C:$C,0))) -> 1 | N8: =IF(ISBLANK(INDEX('Policy Characteristics'!H:H,MATCH($C8,'Policy Characteristics'!$C:$C,0))),"",INDEX('Policy Characteristics'!H:H,MATCH($C8,'Policy Characteristics'!$C:$C,0))) -> 0.02 | O8: =IF(ISBLANK(INDEX('Policy Characteristics'!I:I,MATCH($C8,'Policy Characteristics'!$C:$C,0))),"",INDEX('Policy Characteristics'!I:I,MATCH($C8,'Policy Characteristics'!$C:$C,0))) -> % reduction in emissions | P8: =IF(ISBLANK(INDEX('Policy Characteristics'!J:J,MATCH($C8,'Policy Characteristics'!$C:$C,0))),"",INDEX('Policy Characteristics'!J:J,MATCH($C8,'Policy Characteristics'!$C:$C,0))) -> **Description:** This policy represents strengthening standards for the selected pollutant(s) emitted by the selected vehicle type(s). Conventional pollutants' most important, harmful impacts are on human health rather than on climate change. // **Guidance for setting values:** By 2025, the concentration of fine particulate matter (PM2.5) in prefectural-level and above cities will be 10% lower than that in 2020, and the total emissions of volatile organic compounds (VOCs) and nitrogen oxides will be more than 10% lower than that in 2020 respectively. (Reference: Opinions of the CPC and the State Council on Further Combating Pollution and Preventing the Battle against Pollution) | Q8: =IF(ISBLANK(INDEX('Policy Characteristics'!K:K,MATCH($C8,'Policy Characteristics'!$C:$C,0))),"",INDEX('Policy Characteristics'!K:K,MATCH($C8,'Policy Characteristics'!$C:$C,0))) -> transportation-sector-main.html#conv-pol-stds | R8: =IF(ISBLANK(INDEX('Policy Characteristics'!L:L,MATCH($C8,'Policy Characteristics'!$C:$C,0))),"",INDEX('Policy Characteristics'!L:L,MATCH($C8,'Policy Characteristics'!$C:$C,0))) -> conventional-pollutant-standards.html
A9: =IF(ISBLANK(INDEX('Policy Characteristics'!A:A,MATCH($C9,'Policy Characteristics'!$C:$C,0))),"",INDEX('Policy Characteristics'!A:A,MATCH($C9,'Policy Characteristics'!$C:$C,0))) -> Transportation | B9: =IF(ISBLANK(INDEX('Policy Characteristics'!B:B,MATCH($C9,'Policy Characteristics'!$C:$C,0))),"",INDEX('Policy Characteristics'!B:B,MATCH($C9,'Policy Characteristics'!$C:$C,0))) -> Conventional Pollutant Standards | C9: =C$2 -> Percentage Reduction of Separately Regulated Pollutants | D9: LDVs | E9: OC | F9: Passenger cars, SUVs, Light and Medium Commercial Trucks | G9: OC | H9: 307 | I9: Yes | J9: =IF(ISBLANK(INDEX('Policy Characteristics'!D:D,MATCH($C9,'Policy Characteristics'!$C:$C,0))),"",INDEX('Policy Characteristics'!D:D,MATCH($C9,'Policy Characteristics'!$C:$C,0))) -> Conventional Pollutant Standard | K9: =IF(ISBLANK(INDEX('Policy Characteristics'!E:E,MATCH($C9,'Policy Characteristics'!$C:$C,0))),"",INDEX('Policy Characteristics'!E:E,MATCH($C9,'Policy Characteristics'!$C:$C,0))) -> trans reduce regulated pollutants | L9: =IF(ISBLANK(INDEX('Policy Characteristics'!F:F,MATCH($C9,'Policy Characteristics'!$C:$C,0))),"",INDEX('Policy Characteristics'!F:F,MATCH($C9,'Policy Characteristics'!$C:$C,0))) -> 0 | M9: =IF(ISBLANK(INDEX('Policy Characteristics'!G:G,MATCH($C9,'Policy Characteristics'!$C:$C,0))),"",INDEX('Policy Characteristics'!G:G,MATCH($C9,'Policy Characteristics'!$C:$C,0))) -> 1 | N9: =IF(ISBLANK(INDEX('Policy Characteristics'!H:H,MATCH($C9,'Policy Characteristics'!$C:$C,0))),"",INDEX('Policy Characteristics'!H:H,MATCH($C9,'Policy Characteristics'!$C:$C,0))) -> 0.02 | O9: =IF(ISBLANK(INDEX('Policy Characteristics'!I:I,MATCH($C9,'Policy Characteristics'!$C:$C,0))),"",INDEX('Policy Characteristics'!I:I,MATCH($C9,'Policy Characteristics'!$C:$C,0))) -> % reduction in emissions | P9: =IF(ISBLANK(INDEX('Policy Characteristics'!J:J,MATCH($C9,'Policy Characteristics'!$C:$C,0))),"",INDEX('Policy Characteristics'!J:J,MATCH($C9,'Policy Characteristics'!$C:$C,0))) -> **Description:** This policy represents strengthening standards for the selected pollutant(s) emitted by the selected vehicle type(s). Conventional pollutants' most important, harmful impacts are on human health rather than on climate change. // **Guidance for setting values:** By 2025, the concentration of fine particulate matter (PM2.5) in prefectural-level and above cities will be 10% lower than that in 2020, and the total emissions of volatile organic compounds (VOCs) and nitrogen oxides will be more than 10% lower than that in 2020 respectively. (Reference: Opinions of the CPC and the State Council on Further Combating Pollution and Preventing the Battle against Pollution) | Q9: =IF(ISBLANK(INDEX('Policy Characteristics'!K:K,MATCH($C9,'Policy Characteristics'!$C:$C,0))),"",INDEX('Policy Characteristics'!K:K,MATCH($C9,'Policy Characteristics'!$C:$C,0))) -> transportation-sector-main.html#conv-pol-stds | R9: =IF(ISBLANK(INDEX('Policy Characteristics'!L:L,MATCH($C9,'Policy Characteristics'!$C:$C,0))),"",INDEX('Policy Characteristics'!L:L,MATCH($C9,'Policy Characteristics'!$C:$C,0))) -> conventional-pollutant-standards.html
A10: =IF(ISBLANK(INDEX('Policy Characteristics'!A:A,MATCH($C10,'Policy Characteristics'!$C:$C,0))),"",INDEX('Policy Characteristics'!A:A,MATCH($C10,'Policy Characteristics'!$C:$C,0))) -> Transportation | B10: =IF(ISBLANK(INDEX('Policy Characteristics'!B:B,MATCH($C10,'Policy Characteristics'!$C:$C,0))),"",INDEX('Policy Characteristics'!B:B,MATCH($C10,'Policy Characteristics'!$C:$C,0))) -> Conventional Pollutant Standards | C10: =C$2 -> Percentage Reduction of Separately Regulated Pollutants | D10: LDVs | E10: CH4 | F10: Passenger cars, SUVs, Light and Medium Commercial Trucks | G10: CH4 | H10: 308 | I10: No | J10: =IF(ISBLANK(INDEX('Policy Characteristics'!D:D,MATCH($C10,'Policy Characteristics'!$C:$C,0))),"",INDEX('Policy Characteristics'!D:D,MATCH($C10,'Policy Characteristics'!$C:$C,0))) -> Conventional Pollutant Standard | K10: =IF(ISBLANK(INDEX('Policy Characteristics'!E:E,MATCH($C10,'Policy Characteristics'!$C:$C,0))),"",INDEX('Policy Characteristics'!E:E,MATCH($C10,'Policy Characteristics'!$C:$C,0))) -> trans reduce regulated pollutants | L10: =IF(ISBLANK(INDEX('Policy Characteristics'!F:F,MATCH($C10,'Policy Characteristics'!$C:$C,0))),"",INDEX('Policy Characteristics'!F:F,MATCH($C10,'Policy Characteristics'!$C:$C,0))) -> 0 | M10: =IF(ISBLANK(INDEX('Policy Characteristics'!G:G,MATCH($C10,'Policy Characteristics'!$C:$C,0))),"",INDEX('Policy Characteristics'!G:G,MATCH($C10,'Policy Characteristics'!$C:$C,0))) -> 1 | N10: =IF(ISBLANK(INDEX('Policy Characteristics'!H:H,MATCH($C10,'Policy Characteristics'!$C:$C,0))),"",INDEX('Policy Characteristics'!H:H,MATCH($C10,'Policy Characteristics'!$C:$C,0))) -> 0.02 | O10: =IF(ISBLANK(INDEX('Policy Characteristics'!I:I,MATCH($C10,'Policy Characteristics'!$C:$C,0))),"",INDEX('Policy Characteristics'!I:I,MATCH($C10,'Policy Characteristics'!$C:$C,0))) -> % reduction in emissions | P10: =IF(ISBLANK(INDEX('Policy Characteristics'!J:J,MATCH($C10,'Policy Characteristics'!$C:$C,0))),"",INDEX('Policy Characteristics'!J:J,MATCH($C10,'Policy Characteristics'!$C:$C,0))) -> **Description:** This policy represents strengthening standards for the selected pollutant(s) emitted by the selected vehicle type(s). Conventional pollutants' most important, harmful impacts are on human health rather than on climate change. // **Guidance for setting values:** By 2025, the concentration of fine particulate matter (PM2.5) in prefectural-level and above cities will be 10% lower than that in 2020, and the total emissions of volatile organic compounds (VOCs) and nitrogen oxides will be more than 10% lower than that in 2020 respectively. (Reference: Opinions of the CPC and the State Council on Further Combating Pollution and Preventing the Battle against Pollution) | Q10: =IF(ISBLANK(INDEX('Policy Characteristics'!K:K,MATCH($C10,'Policy Characteristics'!$C:$C,0))),"",INDEX('Policy Characteristics'!K:K,MATCH($C10,'Policy Characteristics'!$C:$C,0))) -> transportation-sector-main.html#conv-pol-stds | R10: =IF(ISBLANK(INDEX('Policy Characteristics'!L:L,MATCH($C10,'Policy Characteristics'!$C:$C,0))),"",INDEX('Policy Characteristics'!L:L,MATCH($C10,'Policy Characteristics'!$C:$C,0))) -> conventional-pollutant-standards.html
A11: =IF(ISBLANK(INDEX('Policy Characteristics'!A:A,MATCH($C11,'Policy Characteristics'!$C:$C,0))),"",INDEX('Policy Characteristics'!A:A,MATCH($C11,'Policy Characteristics'!$C:$C,0))) -> Transportation | B11: =IF(ISBLANK(INDEX('Policy Characteristics'!B:B,MATCH($C11,'Policy Characteristics'!$C:$C,0))),"",INDEX('Policy Characteristics'!B:B,MATCH($C11,'Policy Characteristics'!$C:$C,0))) -> Conventional Pollutant Standards | C11: =C$2 -> Percentage Reduction of Separately Regulated Pollutants | D11: LDVs | E11: N2O | F11: Passenger cars, SUVs, Light and Medium Commercial Trucks | G11: N2O | H11: 309 | I11: No | J11: =IF(ISBLANK(INDEX('Policy Characteristics'!D:D,MATCH($C11,'Policy Characteristics'!$C:$C,0))),"",INDEX('Policy Characteristics'!D:D,MATCH($C11,'Policy Characteristics'!$C:$C,0))) -> Conventional Pollutant Standard | K11: =IF(ISBLANK(INDEX('Policy Characteristics'!E:E,MATCH($C11,'Policy Characteristics'!$C:$C,0))),"",INDEX('Policy Characteristics'!E:E,MATCH($C11,'Policy Characteristics'!$C:$C,0))) -> trans reduce regulated pollutants | L11: =IF(ISBLANK(INDEX('Policy Characteristics'!F:F,MATCH($C11,'Policy Characteristics'!$C:$C,0))),"",INDEX('Policy Characteristics'!F:F,MATCH($C11,'Policy Characteristics'!$C:$C,0))) -> 0 | M11: =IF(ISBLANK(INDEX('Policy Characteristics'!G:G,MATCH($C11,'Policy Characteristics'!$C:$C,0))),"",INDEX('Policy Characteristics'!G:G,MATCH($C11,'Policy Characteristics'!$C:$C,0))) -> 1 | N11: =IF(ISBLANK(INDEX('Policy Characteristics'!H:H,MATCH($C11,'Policy Characteristics'!$C:$C,0))),"",INDEX('Policy Characteristics'!H:H,MATCH($C11,'Policy Characteristics'!$C:$C,0))) -> 0.02 | O11: =IF(ISBLANK(INDEX('Policy Characteristics'!I:I,MATCH($C11,'Policy Characteristics'!$C:$C,0))),"",INDEX('Policy Characteristics'!I:I,MATCH($C11,'Policy Characteristics'!$C:$C,0))) -> % reduction in emissions | P11: =IF(ISBLANK(INDEX('Policy Characteristics'!J:J,MATCH($C11,'Policy Characteristics'!$C:$C,0))),"",INDEX('Policy Characteristics'!J:J,MATCH($C11,'Policy Characteristics'!$C:$C,0))) -> **Description:** This policy represents strengthening standards for the selected pollutant(s) emitted by the selected vehicle type(s). Conventional pollutants' most important, harmful impacts are on human health rather than on climate change. // **Guidance for setting values:** By 2025, the concentration of fine particulate matter (PM2.5) in prefectural-level and above cities will be 10% lower than that in 2020, and the total emissions of volatile organic compounds (VOCs) and nitrogen oxides will be more than 10% lower than that in 2020 respectively. (Reference: Opinions of the CPC and the State Council on Further Combating Pollution and Preventing the Battle against Pollution) | Q11: =IF(ISBLANK(INDEX('Policy Characteristics'!K:K,MATCH($C11,'Policy Characteristics'!$C:$C,0))),"",INDEX('Policy Characteristics'!K:K,MATCH($C11,'Policy Characteristics'!$C:$C,0))) -> transportation-sector-main.html#conv-pol-stds | R11: =IF(ISBLANK(INDEX('Policy Characteristics'!L:L,MATCH($C11,'Policy Characteristics'!$C:$C,0))),"",INDEX('Policy Characteristics'!L:L,MATCH($C11,'Policy Characteristics'!$C:$C,0))) -> conventional-pollutant-standards.html
A12: =IF(ISBLANK(INDEX('Policy Characteristics'!A:A,MATCH($C12,'Policy Characteristics'!$C:$C,0))),"",INDEX('Policy Characteristics'!A:A,MATCH($C12,'Policy Characteristics'!$C:$C,0))) -> Transportation | B12: =IF(ISBLANK(INDEX('Policy Characteristics'!B:B,MATCH($C12,'Policy Characteristics'!$C:$C,0))),"",INDEX('Policy Characteristics'!B:B,MATCH($C12,'Policy Characteristics'!$C:$C,0))) -> Conventional Pollutant Standards | C12: =C$2 -> Percentage Reduction of Separately Regulated Pollutants | D12: HDVs | E12: VOC | F12: Buses and Heavy Duty Trucks | G12: VOCs | H12: 310 | I12: Yes | J12: =IF(ISBLANK(INDEX('Policy Characteristics'!D:D,MATCH($C12,'Policy Characteristics'!$C:$C,0))),"",INDEX('Policy Characteristics'!D:D,MATCH($C12,'Policy Characteristics'!$C:$C,0))) -> Conventional Pollutant Standard | K12: =IF(ISBLANK(INDEX('Policy Characteristics'!E:E,MATCH($C12,'Policy Characteristics'!$C:$C,0))),"",INDEX('Policy Characteristics'!E:E,MATCH($C12,'Policy Characteristics'!$C:$C,0))) -> trans reduce regulated pollutants | L12: =IF(ISBLANK(INDEX('Policy Characteristics'!F:F,MATCH($C12,'Policy Characteristics'!$C:$C,0))),"",INDEX('Policy Characteristics'!F:F,MATCH($C12,'Policy Characteristics'!$C:$C,0))) -> 0 | M12: =IF(ISBLANK(INDEX('Policy Characteristics'!G:G,MATCH($C12,'Policy Characteristics'!$C:$C,0))),"",INDEX('Policy Characteristics'!G:G,MATCH($C12,'Policy Characteristics'!$C:$C,0))) -> 1 | N12: =IF(ISBLANK(INDEX('Policy Characteristics'!H:H,MATCH($C12,'Policy Characteristics'!$C:$C,0))),"",INDEX('Policy Characteristics'!H:H,MATCH($C12,'Policy Characteristics'!$C:$C,0))) -> 0.02 | O12: =IF(ISBLANK(INDEX('Policy Characteristics'!I:I,MATCH($C12,'Policy Characteristics'!$C:$C,0))),"",INDEX('Policy Characteristics'!I:I,MATCH($C12,'Policy Characteristics'!$C:$C,0))) -> % reduction in emissions | P12: =IF(ISBLANK(INDEX('Policy Characteristics'!J:J,MATCH($C12,'Policy Characteristics'!$C:$C,0))),"",INDEX('Policy Characteristics'!J:J,MATCH($C12,'Policy Characteristics'!$C:$C,0))) -> **Description:** This policy represents strengthening standards for the selected pollutant(s) emitted by the selected vehicle type(s). Conventional pollutants' most important, harmful impacts are on human health rather than on climate change. // **Guidance for setting values:** By 2025, the concentration of fine particulate matter (PM2.5) in prefectural-level and above cities will be 10% lower than that in 2020, and the total emissions of volatile organic compounds (VOCs) and nitrogen oxides will be more than 10% lower than that in 2020 respectively. (Reference: Opinions of the CPC and the State Council on Further Combating Pollution and Preventing the Battle against Pollution) | Q12: =IF(ISBLANK(INDEX('Policy Characteristics'!K:K,MATCH($C12,'Policy Characteristics'!$C:$C,0))),"",INDEX('Policy Characteristics'!K:K,MATCH($C12,'Policy Characteristics'!$C:$C,0))) -> transportation-sector-main.html#conv-pol-stds | R12: =IF(ISBLANK(INDEX('Policy Characteristics'!L:L,MATCH($C12,'Policy Characteristics'!$C:$C,0))),"",INDEX('Policy Characteristics'!L:L,MATCH($C12,'Policy Characteristics'!$C:$C,0))) -> conventional-pollutant-standards.html
A13: =IF(ISBLANK(INDEX('Policy Characteristics'!A:A,MATCH($C13,'Policy Characteristics'!$C:$C,0))),"",INDEX('Policy Characteristics'!A:A,MATCH($C13,'Policy Characteristics'!$C:$C,0))) -> Transportation | B13: =IF(ISBLANK(INDEX('Policy Characteristics'!B:B,MATCH($C13,'Policy Characteristics'!$C:$C,0))),"",INDEX('Policy Characteristics'!B:B,MATCH($C13,'Policy Characteristics'!$C:$C,0))) -> Conventional Pollutant Standards | C13: =C$2 -> Percentage Reduction of Separately Regulated Pollutants | D13: HDVs | E13: CO | F13: Buses and Heavy Duty Trucks | G13: CO | H13: 311 | I13: Yes | J13: =IF(ISBLANK(INDEX('Policy Characteristics'!D:D,MATCH($C13,'Policy Characteristics'!$C:$C,0))),"",INDEX('Policy Characteristics'!D:D,MATCH($C13,'Policy Characteristics'!$C:$C,0))) -> Conventional Pollutant Standard | K13: =IF(ISBLANK(INDEX('Policy Characteristics'!E:E,MATCH($C13,'Policy Characteristics'!$C:$C,0))),"",INDEX('Policy Characteristics'!E:E,MATCH($C13,'Policy Characteristics'!$C:$C,0))) -> trans reduce regulated pollutants | L13: =IF(ISBLANK(INDEX('Policy Characteristics'!F:F,MATCH($C13,'Policy Characteristics'!$C:$C,0))),"",INDEX('Policy Characteristics'!F:F,MATCH($C13,'Policy Characteristics'!$C:$C,0))) -> 0 | M13: =IF(ISBLANK(INDEX('Policy Characteristics'!G:G,MATCH($C13,'Policy Characteristics'!$C:$C,0))),"",INDEX('Policy Characteristics'!G:G,MATCH($C13,'Policy Characteristics'!$C:$C,0))) -> 1 | N13: =IF(ISBLANK(INDEX('Policy Characteristics'!H:H,MATCH($C13,'Policy Characteristics'!$C:$C,0))),"",INDEX('Policy Characteristics'!H:H,MATCH($C13,'Policy Characteristics'!$C:$C,0))) -> 0.02 | O13: =IF(ISBLANK(INDEX('Policy Characteristics'!I:I,MATCH($C13,'Policy Characteristics'!$C:$C,0))),"",INDEX('Policy Characteristics'!I:I,MATCH($C13,'Policy Characteristics'!$C:$C,0))) -> % reduction in emissions | P13: =IF(ISBLANK(INDEX('Policy Characteristics'!J:J,MATCH($C13,'Policy Characteristics'!$C:$C,0))),"",INDEX('Policy Characteristics'!J:J,MATCH($C13,'Policy Characteristics'!$C:$C,0))) -> **Description:** This policy represents strengthening standards for the selected pollutant(s) emitted by the selected vehicle type(s). Conventional pollutants' most important, harmful impacts are on human health rather than on climate change. // **Guidance for setting values:** By 2025, the concentration of fine particulate matter (PM2.5) in prefectural-level and above cities will be 10% lower than that in 2020, and the total emissions of volatile organic compounds (VOCs) and nitrogen oxides will be more than 10% lower than that in 2020 respectively. (Reference: Opinions of the CPC and the State Council on Further Combating Pollution and Preventing the Battle against Pollution) | Q13: =IF(ISBLANK(INDEX('Policy Characteristics'!K:K,MATCH($C13,'Policy Characteristics'!$C:$C,0))),"",INDEX('Policy Characteristics'!K:K,MATCH($C13,'Policy Characteristics'!$C:$C,0))) -> transportation-sector-main.html#conv-pol-stds | R13: =IF(ISBLANK(INDEX('Policy Characteristics'!L:L,MATCH($C13,'Policy Characteristics'!$C:$C,0))),"",INDEX('Policy Characteristics'!L:L,MATCH($C13,'Policy Characteristics'!$C:$C,0))) -> conventional-pollutant-standards.html
A14: =IF(ISBLANK(INDEX('Policy Characteristics'!A:A,MATCH($C14,'Policy Characteristics'!$C:$C,0))),"",INDEX('Policy Characteristics'!A:A,MATCH($C14,'Policy Characteristics'!$C:$C,0))) -> Transportation | B14: =IF(ISBLANK(INDEX('Policy Characteristics'!B:B,MATCH($C14,'Policy Characteristics'!$C:$C,0))),"",INDEX('Policy Characteristics'!B:B,MATCH($C14,'Policy Characteristics'!$C:$C,0))) -> Conventional Pollutant Standards | C14: =C$2 -> Percentage Reduction of Separately Regulated Pollutants | D14: HDVs | E14: NOx | F14: Buses and Heavy Duty Trucks | G14: NOx | H14: 312 | I14: Yes | J14: =IF(ISBLANK(INDEX('Policy Characteristics'!D:D,MATCH($C14,'Policy Characteristics'!$C:$C,0))),"",INDEX('Policy Characteristics'!D:D,MATCH($C14,'Policy Characteristics'!$C:$C,0))) -> Conventional Pollutant Standard | K14: =IF(ISBLANK(INDEX('Policy Characteristics'!E:E,MATCH($C14,'Policy Characteristics'!$C:$C,0))),"",INDEX('Policy Characteristics'!E:E,MATCH($C14,'Policy Characteristics'!$C:$C,0))) -> trans reduce regulated pollutants | L14: =IF(ISBLANK(INDEX('Policy Characteristics'!F:F,MATCH($C14,'Policy Characteristics'!$C:$C,0))),"",INDEX('Policy Characteristics'!F:F,MATCH($C14,'Policy Characteristics'!$C:$C,0))) -> 0 | M14: =IF(ISBLANK(INDEX('Policy Characteristics'!G:G,MATCH($C14,'Policy Characteristics'!$C:$C,0))),"",INDEX('Policy Characteristics'!G:G,MATCH($C14,'Policy Characteristics'!$C:$C,0))) -> 1 | N14: =IF(ISBLANK(INDEX('Policy Characteristics'!H:H,MATCH($C14,'Policy Characteristics'!$C:$C,0))),"",INDEX('Policy Characteristics'!H:H,MATCH($C14,'Policy Characteristics'!$C:$C,0))) -> 0.02 | O14: =IF(ISBLANK(INDEX('Policy Characteristics'!I:I,MATCH($C14,'Policy Characteristics'!$C:$C,0))),"",INDEX('Policy Characteristics'!I:I,MATCH($C14,'Policy Characteristics'!$C:$C,0))) -> % reduction in emissions | P14: =IF(ISBLANK(INDEX('Policy Characteristics'!J:J,MATCH($C14,'Policy Characteristics'!$C:$C,0))),"",INDEX('Policy Characteristics'!J:J,MATCH($C14,'Policy Characteristics'!$C:$C,0))) -> **Description:** This policy represents strengthening standards for the selected pollutant(s) emitted by the selected vehicle type(s). Conventional pollutants' most important, harmful impacts are on human health rather than on climate change. // **Guidance for setting values:** By 2025, the concentration of fine particulate matter (PM2.5) in prefectural-level and above cities will be 10% lower than that in 2020, and the total emissions of volatile organic compounds (VOCs) and nitrogen oxides will be more than 10% lower than that in 2020 respectively. (Reference: Opinions of the CPC and the State Council on Further Combating Pollution and Preventing the Battle against Pollution) | Q14: =IF(ISBLANK(INDEX('Policy Characteristics'!K:K,MATCH($C14,'Policy Characteristics'!$C:$C,0))),"",INDEX('Policy Characteristics'!K:K,MATCH($C14,'Policy Characteristics'!$C:$C,0))) -> transportation-sector-main.html#conv-pol-stds | R14: =IF(ISBLANK(INDEX('Policy Characteristics'!L:L,MATCH($C14,'Policy Characteristics'!$C:$C,0))),"",INDEX('Policy Characteristics'!L:L,MATCH($C14,'Policy Characteristics'!$C:$C,0))) -> conventional-pollutant-standards.html
... A61: =IF(ISBLANK(INDEX('Policy Characteristics'!A:A,MATCH($C61,'Policy Characteristics'!$C:$C,0))),"",INDEX('Policy Characteristics'!A:A,MATCH($C61,'Policy Characteristics'!$C:$C,0))) -> Transportation | B61: =IF(ISBLANK(INDEX('Policy Characteristics'!B:B,MATCH($C61,'Policy Characteristics'!$C:$C,0))),"",INDEX('Policy Characteristics'!B:B,MATCH($C61,'Policy Characteristics'!$C:$C,0))) -> Conventional Pollutant Standards | C61: =C$2 -> Percentage Reduction of Separately Regulated Pollutants | D61: motorbikes | E61: N2O | F61: Passenger motorbikes | G61: N2O | H61: 359 | I61: No | J61: =IF(ISBLANK(INDEX('Policy Characteristics'!D:D,MATCH($C61,'Policy Characteristics'!$C:$C,0))),"",INDEX('Policy Characteristics'!D:D,MATCH($C61,'Policy Characteristics'!$C:$C,0))) -> Conventional Pollutant Standard | K61: =IF(ISBLANK(INDEX('Policy Characteristics'!E:E,MATCH($C61,'Policy Characteristics'!$C:$C,0))),"",INDEX('Policy Characteristics'!E:E,MATCH($C61,'Policy Characteristics'!$C:$C,0))) -> trans reduce regulated pollutants | L61: =IF(ISBLANK(INDEX('Policy Characteristics'!F:F,MATCH($C61,'Policy Characteristics'!$C:$C,0))),"",INDEX('Policy Characteristics'!F:F,MATCH($C61,'Policy Characteristics'!$C:$C,0))) -> 0 | M61: =IF(ISBLANK(INDEX('Policy Characteristics'!G:G,MATCH($C61,'Policy Characteristics'!$C:$C,0))),"",INDEX('Policy Characteristics'!G:G,MATCH($C61,'Policy Characteristics'!$C:$C,0))) -> 1 | N61: =IF(ISBLANK(INDEX('Policy Characteristics'!H:H,MATCH($C61,'Policy Characteristics'!$C:$C,0))),"",INDEX('Policy Characteristics'!H:H,MATCH($C61,'Policy Characteristics'!$C:$C,0))) -> 0.02 | O61: =IF(ISBLANK(INDEX('Policy Characteristics'!I:I,MATCH($C61,'Policy Characteristics'!$C:$C,0))),"",INDEX('Policy Characteristics'!I:I,MATCH($C61,'Policy Characteristics'!$C:$C,0))) -> % reduction in emissions | P61: =IF(ISBLANK(INDEX('Policy Characteristics'!J:J,MATCH($C61,'Policy Characteristics'!$C:$C,0))),"",INDEX('Policy Characteristics'!J:J,MATCH($C61,'Policy Characteristics'!$C:$C,0))) -> **Description:** This policy represents strengthening standards for the selected pollutant(s) emitted by the selected vehicle type(s). Conventional pollutants' most important, harmful impacts are on human health rather than on climate change. // **Guidance for setting values:** By 2025, the concentration of fine particulate matter (PM2.5) in prefectural-level and above cities will be 10% lower than that in 2020, and the total emissions of volatile organic compounds (VOCs) and nitrogen oxides will be more than 10% lower than that in 2020 respectively. (Reference: Opinions of the CPC and the State Council on Further Combating Pollution and Preventing the Battle against Pollution) | Q61: =IF(ISBLANK(INDEX('Policy Characteristics'!K:K,MATCH($C61,'Policy Characteristics'!$C:$C,0))),"",INDEX('Policy Characteristics'!K:K,MATCH($C61,'Policy Characteristics'!$C:$C,0))) -> transportation-sector-main.html#conv-pol-stds | R61: =IF(ISBLANK(INDEX('Policy Characteristics'!L:L,MATCH($C61,'Policy Characteristics'!$C:$C,0))),"",INDEX('Policy Characteristics'!L:L,MATCH($C61,'Policy Characteristics'!$C:$C,0))) -> conventional-pollutant-standards.html
A62: =IF(ISBLANK(INDEX('Policy Characteristics'!A:A,MATCH($C62,'Policy Characteristics'!$C:$C,0))),"",INDEX('Policy Characteristics'!A:A,MATCH($C62,'Policy Characteristics'!$C:$C,0))) -> Transportation | B62: =IF(ISBLANK(INDEX('Policy Characteristics'!B:B,MATCH($C62,'Policy Characteristics'!$C:$C,0))),"",INDEX('Policy Characteristics'!B:B,MATCH($C62,'Policy Characteristics'!$C:$C,0))) -> Electric Vehicle Charger Deployment | C62: EV Charger Deployment | H62: 360 | I62: Yes | J62: =IF(ISBLANK(INDEX('Policy Characteristics'!D:D,MATCH($C62,'Policy Characteristics'!$C:$C,0))),"",INDEX('Policy Characteristics'!D:D,MATCH($C62,'Policy Characteristics'!$C:$C,0))) -> EV Charger Deployment | K62: =IF(ISBLANK(INDEX('Policy Characteristics'!E:E,MATCH($C62,'Policy Characteristics'!$C:$C,0))),"",INDEX('Policy Characteristics'!E:E,MATCH($C62,'Policy Characteristics'!$C:$C,0))) -> trans EV charger deployment | L62: =IF(ISBLANK(INDEX('Policy Characteristics'!F:F,MATCH($C62,'Policy Characteristics'!$C:$C,0))),"",INDEX('Policy Characteristics'!F:F,MATCH($C62,'Policy Characteristics'!$C:$C,0))) -> 0 | M62: =IF(ISBLANK(INDEX('Policy Characteristics'!G:G,MATCH($C62,'Policy Characteristics'!$C:$C,0))),"",INDEX('Policy Characteristics'!G:G,MATCH($C62,'Policy Characteristics'!$C:$C,0))) -> 300 | N62: =IF(ISBLANK(INDEX('Policy Characteristics'!H:H,MATCH($C62,'Policy Characteristics'!$C:$C,0))),"",INDEX('Policy Characteristics'!H:H,MATCH($C62,'Policy Characteristics'!$C:$C,0))) -> 5 | O62: =IF(ISBLANK(INDEX('Policy Characteristics'!I:I,MATCH($C62,'Policy Characteristics'!$C:$C,0))),"",INDEX('Policy Characteristics'!I:I,MATCH($C62,'Policy Characteristics'!$C:$C,0))) -> chargers / 100k pop | P62: =IF(ISBLANK(INDEX('Policy Characteristics'!J:J,MATCH($C62,'Policy Characteristics'!$C:$C,0))),"",INDEX('Policy Characteristics'!J:J,MATCH($C62,'Policy Characteristics'!$C:$C,0))) -> **Description:** This policy represents increasing the deployment of EV charging stations, including DC Fast and Level 2 charging stations. It is set in chargers per 100,000 people (cumulative, not per year), additional to chargers in the BAU case. This policy only affects passenger LDVs. // **Guidance for setting values:** The Implementation Program for Accelerating the Construction of Charging and Switching Infrastructure in the Inner Mongolia Autonomous Region (2021-2025) makes it clear that by 2025, all types of charging and switching facilities in the region will strive to reach about 40,000 units. | Q62: =IF(ISBLANK(INDEX('Policy Characteristics'!K:K,MATCH($C62,'Policy Characteristics'!$C:$C,0))),"",INDEX('Policy Characteristics'!K:K,MATCH($C62,'Policy Characteristics'!$C:$C,0))) | R62: =IF(ISBLANK(INDEX('Policy Characteristics'!L:L,MATCH($C62,'Policy Characteristics'!$C:$C,0))),"",INDEX('Policy Characteristics'!L:L,MATCH($C62,'Policy Characteristics'!$C:$C,0))) -> ev-charger-deployment.html
A63: =IF(ISBLANK(INDEX('Policy Characteristics'!A:A,MATCH($C63,'Policy Characteristics'!$C:$C,0))),"",INDEX('Policy Characteristics'!A:A,MATCH($C63,'Policy Characteristics'!$C:$C,0))) -> Transportation | B63: =IF(ISBLANK(INDEX('Policy Characteristics'!B:B,MATCH($C63,'Policy Characteristics'!$C:$C,0))),"",INDEX('Policy Characteristics'!B:B,MATCH($C63,'Policy Characteristics'!$C:$C,0))) -> Electric Vehicle Range & Charging Time | C63: Reduce EV Range Anxiety and Charging Time | H63: 361 | I63: Yes | J63: =IF(ISBLANK(INDEX('Policy Characteristics'!D:D,MATCH($C63,'Policy Characteristics'!$C:$C,0))),"",INDEX('Policy Characteristics'!D:D,MATCH($C63,'Policy Characteristics'!$C:$C,0))) -> EV Range & Charging Time | K63: =IF(ISBLANK(INDEX('Policy Characteristics'!E:E,MATCH($C63,'Policy Characteristics'!$C:$C,0))),"",INDEX('Policy Characteristics'!E:E,MATCH($C63,'Policy Characteristics'!$C:$C,0))) -> trans reduce EV range anxiety and charging time | L63: =IF(ISBLANK(INDEX('Policy Characteristics'!F:F,MATCH($C63,'Policy Characteristics'!$C:$C,0))),"",INDEX('Policy Characteristics'!F:F,MATCH($C63,'Policy Characteristics'!$C:$C,0))) -> 0 | M63: =IF(ISBLANK(INDEX('Policy Characteristics'!G:G,MATCH($C63,'Policy Characteristics'!$C:$C,0))),"",INDEX('Policy Characteristics'!G:G,MATCH($C63,'Policy Characteristics'!$C:$C,0))) -> 1 | N63: =IF(ISBLANK(INDEX('Policy Characteristics'!H:H,MATCH($C63,'Policy Characteristics'!$C:$C,0))),"",INDEX('Policy Characteristics'!H:H,MATCH($C63,'Policy Characteristics'!$C:$C,0))) -> 0.02 | O63: =IF(ISBLANK(INDEX('Policy Characteristics'!I:I,MATCH($C63,'Policy Characteristics'!$C:$C,0))),"",INDEX('Policy Characteristics'!I:I,MATCH($C63,'Policy Characteristics'!$C:$C,0))) -> % reduction in concern | P63: =IF(ISBLANK(INDEX('Policy Characteristics'!J:J,MATCH($C63,'Policy Characteristics'!$C:$C,0))),"",INDEX('Policy Characteristics'!J:J,MATCH($C63,'Policy Characteristics'!$C:$C,0))) -> **Description:** This policy specifies a percentage reduction in vehicle buyers' aversion to electric vehicles due to concerns over the vehicles' range (how far the EV can travel on a charge) and charging time. A 100% setting implies consumers are no more concerned about EV range and charging time than they are about range and fueling time of gasoline vehicles. It does not imply that range is infinite, nor that charging is instantaneous. This policy only affects passenger LDVs. // **Guidance for setting values:**Technology roadmap 2.0 proposes that by 2030, the high ratio of charging facilities will cover residential communities and surrounding areas, as well as unit parking Spaces, social parking lots, and main areas of cities above the county level, key areas of townships, intercity connections, and highway service areas. | Q63: =IF(ISBLANK(INDEX('Policy Characteristics'!K:K,MATCH($C63,'Policy Characteristics'!$C:$C,0))),"",INDEX('Policy Characteristics'!K:K,MATCH($C63,'Policy Characteristics'!$C:$C,0))) | R63: =IF(ISBLANK(INDEX('Policy Characteristics'!L:L,MATCH($C63,'Policy Characteristics'!$C:$C,0))),"",INDEX('Policy Characteristics'!L:L,MATCH($C63,'Policy Characteristics'!$C:$C,0))) -> reduce-range-anxiety-charging-time.html
A64: =IF(ISBLANK(INDEX('Policy Characteristics'!A:A,MATCH($C64,'Policy Characteristics'!$C:$C,0))),"",INDEX('Policy Characteristics'!A:A,MATCH($C64,'Policy Characteristics'!$C:$C,0))) -> Transportation | B64: =IF(ISBLANK(INDEX('Policy Characteristics'!B:B,MATCH($C64,'Policy Characteristics'!$C:$C,0))),"",INDEX('Policy Characteristics'!B:B,MATCH($C64,'Policy Characteristics'!$C:$C,0))) -> Zero-Emission Vehicle Sales Standard | C64: Minimum Required ZEV Sales Percentage | D64: passenger | E64: LDVs | F64: Passenger | G64: Cars and SUVs | H64: 186 | I64: Yes | J64: =IF(ISBLANK(INDEX('Policy Characteristics'!D:D,MATCH($C64,'Policy Characteristics'!$C:$C,0))),"",INDEX('Policy Characteristics'!D:D,MATCH($C64,'Policy Characteristics'!$C:$C,0))) -> ZEV Sales Standard | K64: =IF(ISBLANK(INDEX('Policy Characteristics'!E:E,MATCH($C64,'Policy Characteristics'!$C:$C,0))),"",INDEX('Policy Characteristics'!E:E,MATCH($C64,'Policy Characteristics'!$C:$C,0))) -> trans ZEV minimum | L64: =IF(ISBLANK(INDEX('Policy Characteristics'!F:F,MATCH($C64,'Policy Characteristics'!$C:$C,0))),"",INDEX('Policy Characteristics'!F:F,MATCH($C64,'Policy Characteristics'!$C:$C,0))) -> 0 | M64: =IF(ISBLANK(INDEX('Policy Characteristics'!G:G,MATCH($C64,'Policy Characteristics'!$C:$C,0))),"",INDEX('Policy Characteristics'!G:G,MATCH($C64,'Policy Characteristics'!$C:$C,0))) -> 1 | N64: =IF(ISBLANK(INDEX('Policy Characteristics'!H:H,MATCH($C64,'Policy Characteristics'!$C:$C,0))),"",INDEX('Policy Characteristics'!H:H,MATCH($C64,'Policy Characteristics'!$C:$C,0))) -> 0.01 | O64: =IF(ISBLANK(INDEX('Policy Characteristics'!I:I,MATCH($C64,'Policy Characteristics'!$C:$C,0))),"",INDEX('Policy Characteristics'!I:I,MATCH($C64,'Policy Characteristics'!$C:$C,0))) -> % of new vehicles sold | P64: =IF(ISBLANK(INDEX('Policy Characteristics'!J:J,MATCH($C64,'Policy Characteristics'!$C:$C,0))),"",INDEX('Policy Characteristics'!J:J,MATCH($C64,'Policy Characteristics'!$C:$C,0))) -> **Description:** This policy requires the specified percentage of newly sold vehicles of the selected type(s) to consist of zero-emission vehicles (ZEV). If that percentage would already be achieved through BAU sales plus the effects of other policies, such as an EV subsidy, this policy has no effect. Manufactures may meet a sales standard through techniques such as more heavily marketing electric vehicles, lowering the price of electric vehicles, or raising the price of non-electric vehicles. This policy only applies to road vehicles, not aircraft, rail, or ships. The following descriptions detail the different vehicle types: // **Passenger cars and SUVs:** most light-duty road vehicles //**Light and Medium Commercial, Heavy Duty Trucks, and Heavy Heavy Duty Trucks:** commercial trucks carrying freight, not passengers // **Buses:** including school, transit, and intercity buses // **Heavy Heavy Duty Trucks:** all other heavy road vehicles (mostly freight trucks) // **Passenger motorbikes:** registered motorcycles // **Guidance for setting values:** // **Passenger LDVs:** China aims to achieve about 20% new sales of new energy vehicles (NEV) in 2025, and ensure that new NEV sales is the majority in 2035 (more than 50% of total sales). // **Freight Trucks:** Today, the share of electric freight trucks is very low, but electrification is particularly promising for certain types of trucks, such as those used to make deliveries within cities, those involved in port operations, garbage trucks, and others with frequent starts and stops. // **Passenger HDVs:**Nationally planning sets the goal of 100% electrification for public transportation, and total BEV+PHEV sales for passenger HDVs should reach 50% in 2035. // **Aircraft:** Electricity is commonly used by drones, and small, manned electric aircraft have been developed. However, limited payload and range may complicate the electrification potential of large, long-haul aircraft. Therefore, a low setting of this policy lever may be more realistic than a high setting. // **Rail:** Today, in China, electrification rate reaches 74.9%. Passenger rail has a higher electrification rate than freight and the rates will likely continue to rise. // **Passenger Ships:** Although only a small percentage of recreational boats are powered by electricity today, the market for electric recreational boats is growing rapidly and is projected to reach $20 billion / year globally by 2027. Batteries and electric motors are suitable for the typical travel distances and demand cycles of most small pleasure craft, and in some cases, it is possible to retrofit an existing boat with an electric outboard motor and batteries. Accordingly, a high setting of this policy lever may be reasonable. // **Freight Ships:** Today, few freight ships rely solely on electricity for energy. The large loads and long distances traveled by ocean-going vessels (with no opportunity to charge while underway) limit the suitability of electricity for these vessel types. However, there are freight vessels better-suited to electricity, including tug boats (which benefit from the high torque of electric motors) and offshore support vessels (which carry personnel and goods between offshore platforms and the mainland, and perform other support tasks), as these types of vessels travel predictable distances and may easily return to a dock to charge. Accordingly, a modest setting of this policy lever may be reasonable. // **Passenger Motorbikes:** Electric scooters are very prominent in China and therefore electrification rate is close to 100%. | Q64: =IF(ISBLANK(INDEX('Policy Characteristics'!K:K,MATCH($C64,'Policy Characteristics'!$C:$C,0))),"",INDEX('Policy Characteristics'!K:K,MATCH($C64,'Policy Characteristics'!$C:$C,0))) -> transportation-sector-main.html#ev-mandate | R64: =IF(ISBLANK(INDEX('Policy Characteristics'!L:L,MATCH($C64,'Policy Characteristics'!$C:$C,0))),"",INDEX('Policy Characteristics'!L:L,MATCH($C64,'Policy Characteristics'!$C:$C,0))) -> ev-mandate.html
A65: =IF(ISBLANK(INDEX('Policy Characteristics'!A:A,MATCH($C65,'Policy Characteristics'!$C:$C,0))),"",INDEX('Policy Characteristics'!A:A,MATCH($C65,'Policy Characteristics'!$C:$C,0))) -> Transportation | B65: =IF(ISBLANK(INDEX('Policy Characteristics'!B:B,MATCH($C65,'Policy Characteristics'!$C:$C,0))),"",INDEX('Policy Characteristics'!B:B,MATCH($C65,'Policy Characteristics'!$C:$C,0))) -> Zero-Emission Vehicle Sales Standard | C65: =C$64 -> Minimum Required ZEV Sales Percentage | D65: freight | E65: LDVs | F65: Freight | G65: Light and Medium Commercial Trucks | H65: 203 | I65: Yes | J65: =IF(ISBLANK(INDEX('Policy Characteristics'!D:D,MATCH($C65,'Policy Characteristics'!$C:$C,0))),"",INDEX('Policy Characteristics'!D:D,MATCH($C65,'Policy Characteristics'!$C:$C,0))) -> ZEV Sales Standard | K65: =IF(ISBLANK(INDEX('Policy Characteristics'!E:E,MATCH($C65,'Policy Characteristics'!$C:$C,0))),"",INDEX('Policy Characteristics'!E:E,MATCH($C65,'Policy Characteristics'!$C:$C,0))) -> trans ZEV minimum | L65: =IF(ISBLANK(INDEX('Policy Characteristics'!F:F,MATCH($C65,'Policy Characteristics'!$C:$C,0))),"",INDEX('Policy Characteristics'!F:F,MATCH($C65,'Policy Characteristics'!$C:$C,0))) -> 0 | M65: =IF(ISBLANK(INDEX('Policy Characteristics'!G:G,MATCH($C65,'Policy Characteristics'!$C:$C,0))),"",INDEX('Policy Characteristics'!G:G,MATCH($C65,'Policy Characteristics'!$C:$C,0))) -> 1 | N65: =IF(ISBLANK(INDEX('Policy Characteristics'!H:H,MATCH($C65,'Policy Characteristics'!$C:$C,0))),"",INDEX('Policy Characteristics'!H:H,MATCH($C65,'Policy Characteristics'!$C:$C,0))) -> 0.01 | O65: =IF(ISBLANK(INDEX('Policy Characteristics'!I:I,MATCH($C65,'Policy Characteristics'!$C:$C,0))),"",INDEX('Policy Characteristics'!I:I,MATCH($C65,'Policy Characteristics'!$C:$C,0))) -> % of new vehicles sold | P65: =IF(ISBLANK(INDEX('Policy Characteristics'!J:J,MATCH($C65,'Policy Characteristics'!$C:$C,0))),"",INDEX('Policy Characteristics'!J:J,MATCH($C65,'Policy Characteristics'!$C:$C,0))) -> **Description:** This policy requires the specified percentage of newly sold vehicles of the selected type(s) to consist of zero-emission vehicles (ZEV). If that percentage would already be achieved through BAU sales plus the effects of other policies, such as an EV subsidy, this policy has no effect. Manufactures may meet a sales standard through techniques such as more heavily marketing electric vehicles, lowering the price of electric vehicles, or raising the price of non-electric vehicles. This policy only applies to road vehicles, not aircraft, rail, or ships. The following descriptions detail the different vehicle types: // **Passenger cars and SUVs:** most light-duty road vehicles //**Light and Medium Commercial, Heavy Duty Trucks, and Heavy Heavy Duty Trucks:** commercial trucks carrying freight, not passengers // **Buses:** including school, transit, and intercity buses // **Heavy Heavy Duty Trucks:** all other heavy road vehicles (mostly freight trucks) // **Passenger motorbikes:** registered motorcycles // **Guidance for setting values:** // **Passenger LDVs:** China aims to achieve about 20% new sales of new energy vehicles (NEV) in 2025, and ensure that new NEV sales is the majority in 2035 (more than 50% of total sales). // **Freight Trucks:** Today, the share of electric freight trucks is very low, but electrification is particularly promising for certain types of trucks, such as those used to make deliveries within cities, those involved in port operations, garbage trucks, and others with frequent starts and stops. // **Passenger HDVs:**Nationally planning sets the goal of 100% electrification for public transportation, and total BEV+PHEV sales for passenger HDVs should reach 50% in 2035. // **Aircraft:** Electricity is commonly used by drones, and small, manned electric aircraft have been developed. However, limited payload and range may complicate the electrification potential of large, long-haul aircraft. Therefore, a low setting of this policy lever may be more realistic than a high setting. // **Rail:** Today, in China, electrification rate reaches 74.9%. Passenger rail has a higher electrification rate than freight and the rates will likely continue to rise. // **Passenger Ships:** Although only a small percentage of recreational boats are powered by electricity today, the market for electric recreational boats is growing rapidly and is projected to reach $20 billion / year globally by 2027. Batteries and electric motors are suitable for the typical travel distances and demand cycles of most small pleasure craft, and in some cases, it is possible to retrofit an existing boat with an electric outboard motor and batteries. Accordingly, a high setting of this policy lever may be reasonable. // **Freight Ships:** Today, few freight ships rely solely on electricity for energy. The large loads and long distances traveled by ocean-going vessels (with no opportunity to charge while underway) limit the suitability of electricity for these vessel types. However, there are freight vessels better-suited to electricity, including tug boats (which benefit from the high torque of electric motors) and offshore support vessels (which carry personnel and goods between offshore platforms and the mainland, and perform other support tasks), as these types of vessels travel predictable distances and may easily return to a dock to charge. Accordingly, a modest setting of this policy lever may be reasonable. // **Passenger Motorbikes:** Electric scooters are very prominent in China and therefore electrification rate is close to 100%. | Q65: =IF(ISBLANK(INDEX('Policy Characteristics'!K:K,MATCH($C65,'Policy Characteristics'!$C:$C,0))),"",INDEX('Policy Characteristics'!K:K,MATCH($C65,'Policy Characteristics'!$C:$C,0))) -> transportation-sector-main.html#ev-mandate | R65: =IF(ISBLANK(INDEX('Policy Characteristics'!L:L,MATCH($C65,'Policy Characteristics'!$C:$C,0))),"",INDEX('Policy Characteristics'!L:L,MATCH($C65,'Policy Characteristics'!$C:$C,0))) -> ev-mandate.html
A66: =IF(ISBLANK(INDEX('Policy Characteristics'!A:A,MATCH($C66,'Policy Characteristics'!$C:$C,0))),"",INDEX('Policy Characteristics'!A:A,MATCH($C66,'Policy Characteristics'!$C:$C,0))) -> Transportation | B66: =IF(ISBLANK(INDEX('Policy Characteristics'!B:B,MATCH($C66,'Policy Characteristics'!$C:$C,0))),"",INDEX('Policy Characteristics'!B:B,MATCH($C66,'Policy Characteristics'!$C:$C,0))) -> Zero-Emission Vehicle Sales Standard | C66: =C$64 -> Minimum Required ZEV Sales Percentage | D66: passenger | E66: HDVs | F66: Passenger | G66: Buses | H66: 187 | I66: Yes | J66: =IF(ISBLANK(INDEX('Policy Characteristics'!D:D,MATCH($C66,'Policy Characteristics'!$C:$C,0))),"",INDEX('Policy Characteristics'!D:D,MATCH($C66,'Policy Characteristics'!$C:$C,0))) -> ZEV Sales Standard | K66: =IF(ISBLANK(INDEX('Policy Characteristics'!E:E,MATCH($C66,'Policy Characteristics'!$C:$C,0))),"",INDEX('Policy Characteristics'!E:E,MATCH($C66,'Policy Characteristics'!$C:$C,0))) -> trans ZEV minimum | L66: =IF(ISBLANK(INDEX('Policy Characteristics'!F:F,MATCH($C66,'Policy Characteristics'!$C:$C,0))),"",INDEX('Policy Characteristics'!F:F,MATCH($C66,'Policy Characteristics'!$C:$C,0))) -> 0 | M66: =IF(ISBLANK(INDEX('Policy Characteristics'!G:G,MATCH($C66,'Policy Characteristics'!$C:$C,0))),"",INDEX('Policy Characteristics'!G:G,MATCH($C66,'Policy Characteristics'!$C:$C,0))) -> 1 | N66: =IF(ISBLANK(INDEX('Policy Characteristics'!H:H,MATCH($C66,'Policy Characteristics'!$C:$C,0))),"",INDEX('Policy Characteristics'!H:H,MATCH($C66,'Policy Characteristics'!$C:$C,0))) -> 0.01 | O66: =IF(ISBLANK(INDEX('Policy Characteristics'!I:I,MATCH($C66,'Policy Characteristics'!$C:$C,0))),"",INDEX('Policy Characteristics'!I:I,MATCH($C66,'Policy Characteristics'!$C:$C,0))) -> % of new vehicles sold | P66: =IF(ISBLANK(INDEX('Policy Characteristics'!J:J,MATCH($C66,'Policy Characteristics'!$C:$C,0))),"",INDEX('Policy Characteristics'!J:J,MATCH($C66,'Policy Characteristics'!$C:$C,0))) -> **Description:** This policy requires the specified percentage of newly sold vehicles of the selected type(s) to consist of zero-emission vehicles (ZEV). If that percentage would already be achieved through BAU sales plus the effects of other policies, such as an EV subsidy, this policy has no effect. Manufactures may meet a sales standard through techniques such as more heavily marketing electric vehicles, lowering the price of electric vehicles, or raising the price of non-electric vehicles. This policy only applies to road vehicles, not aircraft, rail, or ships. The following descriptions detail the different vehicle types: // **Passenger cars and SUVs:** most light-duty road vehicles //**Light and Medium Commercial, Heavy Duty Trucks, and Heavy Heavy Duty Trucks:** commercial trucks carrying freight, not passengers // **Buses:** including school, transit, and intercity buses // **Heavy Heavy Duty Trucks:** all other heavy road vehicles (mostly freight trucks) // **Passenger motorbikes:** registered motorcycles // **Guidance for setting values:** // **Passenger LDVs:** China aims to achieve about 20% new sales of new energy vehicles (NEV) in 2025, and ensure that new NEV sales is the majority in 2035 (more than 50% of total sales). // **Freight Trucks:** Today, the share of electric freight trucks is very low, but electrification is particularly promising for certain types of trucks, such as those used to make deliveries within cities, those involved in port operations, garbage trucks, and others with frequent starts and stops. // **Passenger HDVs:**Nationally planning sets the goal of 100% electrification for public transportation, and total BEV+PHEV sales for passenger HDVs should reach 50% in 2035. // **Aircraft:** Electricity is commonly used by drones, and small, manned electric aircraft have been developed. However, limited payload and range may complicate the electrification potential of large, long-haul aircraft. Therefore, a low setting of this policy lever may be more realistic than a high setting. // **Rail:** Today, in China, electrification rate reaches 74.9%. Passenger rail has a higher electrification rate than freight and the rates will likely continue to rise. // **Passenger Ships:** Although only a small percentage of recreational boats are powered by electricity today, the market for electric recreational boats is growing rapidly and is projected to reach $20 billion / year globally by 2027. Batteries and electric motors are suitable for the typical travel distances and demand cycles of most small pleasure craft, and in some cases, it is possible to retrofit an existing boat with an electric outboard motor and batteries. Accordingly, a high setting of this policy lever may be reasonable. // **Freight Ships:** Today, few freight ships rely solely on electricity for energy. The large loads and long distances traveled by ocean-going vessels (with no opportunity to charge while underway) limit the suitability of electricity for these vessel types. However, there are freight vessels better-suited to electricity, including tug boats (which benefit from the high torque of electric motors) and offshore support vessels (which carry personnel and goods between offshore platforms and the mainland, and perform other support tasks), as these types of vessels travel predictable distances and may easily return to a dock to charge. Accordingly, a modest setting of this policy lever may be reasonable. // **Passenger Motorbikes:** Electric scooters are very prominent in China and therefore electrification rate is close to 100%. | Q66: =IF(ISBLANK(INDEX('Policy Characteristics'!K:K,MATCH($C66,'Policy Characteristics'!$C:$C,0))),"",INDEX('Policy Characteristics'!K:K,MATCH($C66,'Policy Characteristics'!$C:$C,0))) -> transportation-sector-main.html#ev-mandate | R66: =IF(ISBLANK(INDEX('Policy Characteristics'!L:L,MATCH($C66,'Policy Characteristics'!$C:$C,0))),"",INDEX('Policy Characteristics'!L:L,MATCH($C66,'Policy Characteristics'!$C:$C,0))) -> ev-mandate.html
A67: =IF(ISBLANK(INDEX('Policy Characteristics'!A:A,MATCH($C67,'Policy Characteristics'!$C:$C,0))),"",INDEX('Policy Characteristics'!A:A,MATCH($C67,'Policy Characteristics'!$C:$C,0))) -> Transportation | B67: =IF(ISBLANK(INDEX('Policy Characteristics'!B:B,MATCH($C67,'Policy Characteristics'!$C:$C,0))),"",INDEX('Policy Characteristics'!B:B,MATCH($C67,'Policy Characteristics'!$C:$C,0))) -> Zero-Emission Vehicle Sales Standard | C67: =C$64 -> Minimum Required ZEV Sales Percentage | D67: freight | E67: HDVs | F67: Freight | G67: Heavy Duty Trucks | H67: 191 | I67: Yes | J67: =IF(ISBLANK(INDEX('Policy Characteristics'!D:D,MATCH($C67,'Policy Characteristics'!$C:$C,0))),"",INDEX('Policy Characteristics'!D:D,MATCH($C67,'Policy Characteristics'!$C:$C,0))) -> ZEV Sales Standard | K67: =IF(ISBLANK(INDEX('Policy Characteristics'!E:E,MATCH($C67,'Policy Characteristics'!$C:$C,0))),"",INDEX('Policy Characteristics'!E:E,MATCH($C67,'Policy Characteristics'!$C:$C,0))) -> trans ZEV minimum | L67: =IF(ISBLANK(INDEX('Policy Characteristics'!F:F,MATCH($C67,'Policy Characteristics'!$C:$C,0))),"",INDEX('Policy Characteristics'!F:F,MATCH($C67,'Policy Characteristics'!$C:$C,0))) -> 0 | M67: =IF(ISBLANK(INDEX('Policy Characteristics'!G:G,MATCH($C67,'Policy Characteristics'!$C:$C,0))),"",INDEX('Policy Characteristics'!G:G,MATCH($C67,'Policy Characteristics'!$C:$C,0))) -> 1 | N67: =IF(ISBLANK(INDEX('Policy Characteristics'!H:H,MATCH($C67,'Policy Characteristics'!$C:$C,0))),"",INDEX('Policy Characteristics'!H:H,MATCH($C67,'Policy Characteristics'!$C:$C,0))) -> 0.01 | O67: =IF(ISBLANK(INDEX('Policy Characteristics'!I:I,MATCH($C67,'Policy Characteristics'!$C:$C,0))),"",INDEX('Policy Characteristics'!I:I,MATCH($C67,'Policy Characteristics'!$C:$C,0))) -> % of new vehicles sold | P67: =IF(ISBLANK(INDEX('Policy Characteristics'!J:J,MATCH($C67,'Policy Characteristics'!$C:$C,0))),"",INDEX('Policy Characteristics'!J:J,MATCH($C67,'Policy Characteristics'!$C:$C,0))) -> **Description:** This policy requires the specified percentage of newly sold vehicles of the selected type(s) to consist of zero-emission vehicles (ZEV). If that percentage would already be achieved through BAU sales plus the effects of other policies, such as an EV subsidy, this policy has no effect. Manufactures may meet a sales standard through techniques such as more heavily marketing electric vehicles, lowering the price of electric vehicles, or raising the price of non-electric vehicles. This policy only applies to road vehicles, not aircraft, rail, or ships. The following descriptions detail the different vehicle types: // **Passenger cars and SUVs:** most light-duty road vehicles //**Light and Medium Commercial, Heavy Duty Trucks, and Heavy Heavy Duty Trucks:** commercial trucks carrying freight, not passengers // **Buses:** including school, transit, and intercity buses // **Heavy Heavy Duty Trucks:** all other heavy road vehicles (mostly freight trucks) // **Passenger motorbikes:** registered motorcycles // **Guidance for setting values:** // **Passenger LDVs:** China aims to achieve about 20% new sales of new energy vehicles (NEV) in 2025, and ensure that new NEV sales is the majority in 2035 (more than 50% of total sales). // **Freight Trucks:** Today, the share of electric freight trucks is very low, but electrification is particularly promising for certain types of trucks, such as those used to make deliveries within cities, those involved in port operations, garbage trucks, and others with frequent starts and stops. // **Passenger HDVs:**Nationally planning sets the goal of 100% electrification for public transportation, and total BEV+PHEV sales for passenger HDVs should reach 50% in 2035. // **Aircraft:** Electricity is commonly used by drones, and small, manned electric aircraft have been developed. However, limited payload and range may complicate the electrification potential of large, long-haul aircraft. Therefore, a low setting of this policy lever may be more realistic than a high setting. // **Rail:** Today, in China, electrification rate reaches 74.9%. Passenger rail has a higher electrification rate than freight and the rates will likely continue to rise. // **Passenger Ships:** Although only a small percentage of recreational boats are powered by electricity today, the market for electric recreational boats is growing rapidly and is projected to reach $20 billion / year globally by 2027. Batteries and electric motors are suitable for the typical travel distances and demand cycles of most small pleasure craft, and in some cases, it is possible to retrofit an existing boat with an electric outboard motor and batteries. Accordingly, a high setting of this policy lever may be reasonable. // **Freight Ships:** Today, few freight ships rely solely on electricity for energy. The large loads and long distances traveled by ocean-going vessels (with no opportunity to charge while underway) limit the suitability of electricity for these vessel types. However, there are freight vessels better-suited to electricity, including tug boats (which benefit from the high torque of electric motors) and offshore support vessels (which carry personnel and goods between offshore platforms and the mainland, and perform other support tasks), as these types of vessels travel predictable distances and may easily return to a dock to charge. Accordingly, a modest setting of this policy lever may be reasonable. // **Passenger Motorbikes:** Electric scooters are very prominent in China and therefore electrification rate is close to 100%. | Q67: =IF(ISBLANK(INDEX('Policy Characteristics'!K:K,MATCH($C67,'Policy Characteristics'!$C:$C,0))),"",INDEX('Policy Characteristics'!K:K,MATCH($C67,'Policy Characteristics'!$C:$C,0))) -> transportation-sector-main.html#ev-mandate | R67: =IF(ISBLANK(INDEX('Policy Characteristics'!L:L,MATCH($C67,'Policy Characteristics'!$C:$C,0))),"",INDEX('Policy Characteristics'!L:L,MATCH($C67,'Policy Characteristics'!$C:$C,0))) -> ev-mandate.html
A68: =IF(ISBLANK(INDEX('Policy Characteristics'!A:A,MATCH($C68,'Policy Characteristics'!$C:$C,0))),"",INDEX('Policy Characteristics'!A:A,MATCH($C68,'Policy Characteristics'!$C:$C,0))) -> Transportation | B68: =IF(ISBLANK(INDEX('Policy Characteristics'!B:B,MATCH($C68,'Policy Characteristics'!$C:$C,0))),"",INDEX('Policy Characteristics'!B:B,MATCH($C68,'Policy Characteristics'!$C:$C,0))) -> Zero-Emission Vehicle Sales Standard | C68: =C$64 -> Minimum Required ZEV Sales Percentage | D68: passenger | E68: aircraft | F68: Passenger | G68: Commercial flights | H68: 496 | I68: Yes | J68: =IF(ISBLANK(INDEX('Policy Characteristics'!D:D,MATCH($C68,'Policy Characteristics'!$C:$C,0))),"",INDEX('Policy Characteristics'!D:D,MATCH($C68,'Policy Characteristics'!$C:$C,0))) -> ZEV Sales Standard | K68: =IF(ISBLANK(INDEX('Policy Characteristics'!E:E,MATCH($C68,'Policy Characteristics'!$C:$C,0))),"",INDEX('Policy Characteristics'!E:E,MATCH($C68,'Policy Characteristics'!$C:$C,0))) -> trans ZEV minimum | L68: =IF(ISBLANK(INDEX('Policy Characteristics'!F:F,MATCH($C68,'Policy Characteristics'!$C:$C,0))),"",INDEX('Policy Characteristics'!F:F,MATCH($C68,'Policy Characteristics'!$C:$C,0))) -> 0 | M68: =IF(ISBLANK(INDEX('Policy Characteristics'!G:G,MATCH($C68,'Policy Characteristics'!$C:$C,0))),"",INDEX('Policy Characteristics'!G:G,MATCH($C68,'Policy Characteristics'!$C:$C,0))) -> 1 | N68: =IF(ISBLANK(INDEX('Policy Characteristics'!H:H,MATCH($C68,'Policy Characteristics'!$C:$C,0))),"",INDEX('Policy Characteristics'!H:H,MATCH($C68,'Policy Characteristics'!$C:$C,0))) -> 0.01 | O68: =IF(ISBLANK(INDEX('Policy Characteristics'!I:I,MATCH($C68,'Policy Characteristics'!$C:$C,0))),"",INDEX('Policy Characteristics'!I:I,MATCH($C68,'Policy Characteristics'!$C:$C,0))) -> % of new vehicles sold | P68: =IF(ISBLANK(INDEX('Policy Characteristics'!J:J,MATCH($C68,'Policy Characteristics'!$C:$C,0))),"",INDEX('Policy Characteristics'!J:J,MATCH($C68,'Policy Characteristics'!$C:$C,0))) -> **Description:** This policy requires the specified percentage of newly sold vehicles of the selected type(s) to consist of zero-emission vehicles (ZEV). If that percentage would already be achieved through BAU sales plus the effects of other policies, such as an EV subsidy, this policy has no effect. Manufactures may meet a sales standard through techniques such as more heavily marketing electric vehicles, lowering the price of electric vehicles, or raising the price of non-electric vehicles. This policy only applies to road vehicles, not aircraft, rail, or ships. The following descriptions detail the different vehicle types: // **Passenger cars and SUVs:** most light-duty road vehicles //**Light and Medium Commercial, Heavy Duty Trucks, and Heavy Heavy Duty Trucks:** commercial trucks carrying freight, not passengers // **Buses:** including school, transit, and intercity buses // **Heavy Heavy Duty Trucks:** all other heavy road vehicles (mostly freight trucks) // **Passenger motorbikes:** registered motorcycles // **Guidance for setting values:** // **Passenger LDVs:** China aims to achieve about 20% new sales of new energy vehicles (NEV) in 2025, and ensure that new NEV sales is the majority in 2035 (more than 50% of total sales). // **Freight Trucks:** Today, the share of electric freight trucks is very low, but electrification is particularly promising for certain types of trucks, such as those used to make deliveries within cities, those involved in port operations, garbage trucks, and others with frequent starts and stops. // **Passenger HDVs:**Nationally planning sets the goal of 100% electrification for public transportation, and total BEV+PHEV sales for passenger HDVs should reach 50% in 2035. // **Aircraft:** Electricity is commonly used by drones, and small, manned electric aircraft have been developed. However, limited payload and range may complicate the electrification potential of large, long-haul aircraft. Therefore, a low setting of this policy lever may be more realistic than a high setting. // **Rail:** Today, in China, electrification rate reaches 74.9%. Passenger rail has a higher electrification rate than freight and the rates will likely continue to rise. // **Passenger Ships:** Although only a small percentage of recreational boats are powered by electricity today, the market for electric recreational boats is growing rapidly and is projected to reach $20 billion / year globally by 2027. Batteries and electric motors are suitable for the typical travel distances and demand cycles of most small pleasure craft, and in some cases, it is possible to retrofit an existing boat with an electric outboard motor and batteries. Accordingly, a high setting of this policy lever may be reasonable. // **Freight Ships:** Today, few freight ships rely solely on electricity for energy. The large loads and long distances traveled by ocean-going vessels (with no opportunity to charge while underway) limit the suitability of electricity for these vessel types. However, there are freight vessels better-suited to electricity, including tug boats (which benefit from the high torque of electric motors) and offshore support vessels (which carry personnel and goods between offshore platforms and the mainland, and perform other support tasks), as these types of vessels travel predictable distances and may easily return to a dock to charge. Accordingly, a modest setting of this policy lever may be reasonable. // **Passenger Motorbikes:** Electric scooters are very prominent in China and therefore electrification rate is close to 100%. | Q68: =IF(ISBLANK(INDEX('Policy Characteristics'!K:K,MATCH($C68,'Policy Characteristics'!$C:$C,0))),"",INDEX('Policy Characteristics'!K:K,MATCH($C68,'Policy Characteristics'!$C:$C,0))) -> transportation-sector-main.html#ev-mandate | R68: =IF(ISBLANK(INDEX('Policy Characteristics'!L:L,MATCH($C68,'Policy Characteristics'!$C:$C,0))),"",INDEX('Policy Characteristics'!L:L,MATCH($C68,'Policy Characteristics'!$C:$C,0))) -> ev-mandate.html
A69: =IF(ISBLANK(INDEX('Policy Characteristics'!A:A,MATCH($C69,'Policy Characteristics'!$C:$C,0))),"",INDEX('Policy Characteristics'!A:A,MATCH($C69,'Policy Characteristics'!$C:$C,0))) -> Transportation | B69: =IF(ISBLANK(INDEX('Policy Characteristics'!B:B,MATCH($C69,'Policy Characteristics'!$C:$C,0))),"",INDEX('Policy Characteristics'!B:B,MATCH($C69,'Policy Characteristics'!$C:$C,0))) -> Zero-Emission Vehicle Sales Standard | C69: =C$64 -> Minimum Required ZEV Sales Percentage | D69: freight | E69: aircraft | F69: Freight | G69: Commercial flights | H69: 497 | I69: No | J69: =IF(ISBLANK(INDEX('Policy Characteristics'!D:D,MATCH($C69,'Policy Characteristics'!$C:$C,0))),"",INDEX('Policy Characteristics'!D:D,MATCH($C69,'Policy Characteristics'!$C:$C,0))) -> ZEV Sales Standard | K69: =IF(ISBLANK(INDEX('Policy Characteristics'!E:E,MATCH($C69,'Policy Characteristics'!$C:$C,0))),"",INDEX('Policy Characteristics'!E:E,MATCH($C69,'Policy Characteristics'!$C:$C,0))) -> trans ZEV minimum | L69: =IF(ISBLANK(INDEX('Policy Characteristics'!F:F,MATCH($C69,'Policy Characteristics'!$C:$C,0))),"",INDEX('Policy Characteristics'!F:F,MATCH($C69,'Policy Characteristics'!$C:$C,0))) -> 0 | M69: =IF(ISBLANK(INDEX('Policy Characteristics'!G:G,MATCH($C69,'Policy Characteristics'!$C:$C,0))),"",INDEX('Policy Characteristics'!G:G,MATCH($C69,'Policy Characteristics'!$C:$C,0))) -> 1 | N69: =IF(ISBLANK(INDEX('Policy Characteristics'!H:H,MATCH($C69,'Policy Characteristics'!$C:$C,0))),"",INDEX('Policy Characteristics'!H:H,MATCH($C69,'Policy Characteristics'!$C:$C,0))) -> 0.01 | O69: =IF(ISBLANK(INDEX('Policy Characteristics'!I:I,MATCH($C69,'Policy Characteristics'!$C:$C,0))),"",INDEX('Policy Characteristics'!I:I,MATCH($C69,'Policy Characteristics'!$C:$C,0))) -> % of new vehicles sold | P69: =IF(ISBLANK(INDEX('Policy Characteristics'!J:J,MATCH($C69,'Policy Characteristics'!$C:$C,0))),"",INDEX('Policy Characteristics'!J:J,MATCH($C69,'Policy Characteristics'!$C:$C,0))) -> **Description:** This policy requires the specified percentage of newly sold vehicles of the selected type(s) to consist of zero-emission vehicles (ZEV). If that percentage would already be achieved through BAU sales plus the effects of other policies, such as an EV subsidy, this policy has no effect. Manufactures may meet a sales standard through techniques such as more heavily marketing electric vehicles, lowering the price of electric vehicles, or raising the price of non-electric vehicles. This policy only applies to road vehicles, not aircraft, rail, or ships. The following descriptions detail the different vehicle types: // **Passenger cars and SUVs:** most light-duty road vehicles //**Light and Medium Commercial, Heavy Duty Trucks, and Heavy Heavy Duty Trucks:** commercial trucks carrying freight, not passengers // **Buses:** including school, transit, and intercity buses // **Heavy Heavy Duty Trucks:** all other heavy road vehicles (mostly freight trucks) // **Passenger motorbikes:** registered motorcycles // **Guidance for setting values:** // **Passenger LDVs:** China aims to achieve about 20% new sales of new energy vehicles (NEV) in 2025, and ensure that new NEV sales is the majority in 2035 (more than 50% of total sales). // **Freight Trucks:** Today, the share of electric freight trucks is very low, but electrification is particularly promising for certain types of trucks, such as those used to make deliveries within cities, those involved in port operations, garbage trucks, and others with frequent starts and stops. // **Passenger HDVs:**Nationally planning sets the goal of 100% electrification for public transportation, and total BEV+PHEV sales for passenger HDVs should reach 50% in 2035. // **Aircraft:** Electricity is commonly used by drones, and small, manned electric aircraft have been developed. However, limited payload and range may complicate the electrification potential of large, long-haul aircraft. Therefore, a low setting of this policy lever may be more realistic than a high setting. // **Rail:** Today, in China, electrification rate reaches 74.9%. Passenger rail has a higher electrification rate than freight and the rates will likely continue to rise. // **Passenger Ships:** Although only a small percentage of recreational boats are powered by electricity today, the market for electric recreational boats is growing rapidly and is projected to reach $20 billion / year globally by 2027. Batteries and electric motors are suitable for the typical travel distances and demand cycles of most small pleasure craft, and in some cases, it is possible to retrofit an existing boat with an electric outboard motor and batteries. Accordingly, a high setting of this policy lever may be reasonable. // **Freight Ships:** Today, few freight ships rely solely on electricity for energy. The large loads and long distances traveled by ocean-going vessels (with no opportunity to charge while underway) limit the suitability of electricity for these vessel types. However, there are freight vessels better-suited to electricity, including tug boats (which benefit from the high torque of electric motors) and offshore support vessels (which carry personnel and goods between offshore platforms and the mainland, and perform other support tasks), as these types of vessels travel predictable distances and may easily return to a dock to charge. Accordingly, a modest setting of this policy lever may be reasonable. // **Passenger Motorbikes:** Electric scooters are very prominent in China and therefore electrification rate is close to 100%. | Q69: =IF(ISBLANK(INDEX('Policy Characteristics'!K:K,MATCH($C69,'Policy Characteristics'!$C:$C,0))),"",INDEX('Policy Characteristics'!K:K,MATCH($C69,'Policy Characteristics'!$C:$C,0))) -> transportation-sector-main.html#ev-mandate | R69: =IF(ISBLANK(INDEX('Policy Characteristics'!L:L,MATCH($C69,'Policy Characteristics'!$C:$C,0))),"",INDEX('Policy Characteristics'!L:L,MATCH($C69,'Policy Characteristics'!$C:$C,0))) -> ev-mandate.html
